Workbook
Name LISTA_COLORES: COLORES!$A$4:$A$53
Name LISTA_CLIENTES: CLIENTES!$A$4:$A$18
Name LISTA_PRODUCTOS: PRODUCTOS!$A$4:$A$28

Sheet COBROS_DIARIOS
A1: COBROS DIARIOS — Una fila por entrega/cobro
A2: Cantidades en columnas S/M/L/XL, el TOTAL se suma automático. COLOR dropdown.
A3: FECHA | B3: N° CORTE | C3: N° FACTURA | D3: CLIENTE | E3: PRODUCTO | F3: COLOR | G3: S | H3: M | I3: L | J3: XL | K3: TOTAL (auto) | L3: PRECIO UNIT (auto) | M3: BRUTO (auto) | N3: DETRACCIÓN 10% | O3: DISPONIBLE 90% | P3: ESTADO | Q3: NOTAS
A4: 46146 | B4: q | C4: 1234 | D4: OverShark | E4: baby ty ml | F4: Perla | G4: 32 | H4: 62 | K4: 94 | L4: =IFERROR(VLOOKUP(E4,PRODUCTOS!$A$4:$F$28,6,FALSE()),0) -> 1.7 | M4: =IFERROR(K4*L4,0) -> 159.8 | N4: =IFERROR(M4*CONFIG!$B$4,0) -> 15.98 | O4: =IFERROR(M4-N4,0) -> 143.82 | P4: PENDIENTE
A5: 46146 | B5: q | C5: 1234 | D5: OverShark | E5: baby ty ml | F5: Vino | G5: 54 | I5: 56 | K5: 110 | L5: =IFERROR(VLOOKUP(E5,PRODUCTOS!$A$4:$F$28,6,FALSE()),0) -> 1.7 | M5: =IFERROR(K5*L5,0) -> 187 | N5: =IFERROR(M5*CONFIG!$B$4,0) -> 18.7 | O5: =IFERROR(M5-N5,0) -> 168.3 | P5: PENDIENTE
A6: 46146 | B6: q | C6: 1234 | D6: OverShark | E6: pique camisero | F6: Azul Marino | H6: 8 | I6: 25 | J6: 5 | K6: 38 | L6: =IFERROR(VLOOKUP(E6,PRODUCTOS!$A$4:$F$28,6,FALSE()),0) -> 4 | M6: =IFERROR(K6*L6,0) -> 152 | N6: =IFERROR(M6*CONFIG!$B$4,0) -> 15.2 | O6: =IFERROR(M6-N6,0) -> 136.8 | P6: PENDIENTE
A7: 46146 | B7: q | C7: 1234 | D7: OverShark | E7: jersey manga corta | F7: Denim | G7: 82 | H7: 165 | J7: 80 | K7: 327 | L7: =IFERROR(VLOOKUP(E7,PRODUCTOS!$A$4:$F$28,6,FALSE()),0) -> 1.7 | M7: =IFERROR(K7*L7,0) -> 555.9 | N7: =IFERROR(M7*CONFIG!$B$4,0) -> 55.59 | O7: =IFERROR(M7-N7,0) -> 500.31 | P7: PENDIENTE
A8: 46146 | B8: q | C8: 1234 | D8: OverShark | E8: wafle clasico | F8: Beige | G8: 64 | H8: 137 | I8: 134 | J8: 69 | K8: 404 | L8: =IFERROR(VLOOKUP(E8,PRODUCTOS!$A$4:$F$28,6,FALSE()),0) -> 1.7 | M8: =IFERROR(K8*L8,0) -> 686.8 | N8: =IFERROR(M8*CONFIG!$B$4,0) -> 68.68 | O8: =IFERROR(M8-N8,0) -> 618.12 | P8: PENDIENTE
A9: 46146 | B9: q | C9: 1234 | D9: Bravos | E9: polera neru | F9: Perla | G9: 80 | K9: 80 | L9: =IFERROR(VLOOKUP(E9,PRODUCTOS!$A$4:$F$28,6,FALSE()),0) -> 6 | M9: =IFERROR(K9*L9,0) -> 480 | N9: =IFERROR(M9*CONFIG!$B$4,0) -> 48 | O9: =IFERROR(M9-N9,0) -> 432 | P9: PENDIENTE
A10: 46146 | B10: q | C10: 1234 | D10: Bravos | E10: Polera Boxy | F10: Negro | G10: 58 | H10: 62 | I10: 49 | K10: 169 | L10: =IFERROR(VLOOKUP(E10,PRODUCTOS!$A$4:$F$28,6,FALSE()),0) -> 4 | M10: =IFERROR(K10*L10,0) -> 676 | N10: =IFERROR(M10*CONFIG!$B$4,0) -> 67.6 | O10: =IFERROR(M10-N10,0) -> 608.4 | P10: PENDIENTE
A11: 46146 | B11: q | C11: 1234 | D11: Bravos | E11: polera neru | F11: Perla | G11: 10 | K11: 10 | L11: =IFERROR(VLOOKUP(E11,PRODUCTOS!$A$4:$F$28,6,FALSE()),0) -> 6 | M11: =IFERROR(K11*L11,0) -> 60 | N11: =IFERROR(M11*CONFIG!$B$4,0) -> 6 | O11: =IFERROR(M11-N11,0) -> 54 | P11: PENDIENTE
A12: 46146 | B12: q | C12: 1234 | D12: Bravos | E12: polera neru | F12: Negro | G12: 1 | K12: 1 | L12: =IFERROR(VLOOKUP(E12,PRODUCTOS!$A$4:$F$28,6,FALSE()),0) -> 6 | M12: =IFERROR(K12*L12,0) -> 6 | N12: =IFERROR(M12*CONFIG!$B$4,0) -> 0.6 | O12: =IFERROR(M12-N12,0) -> 5.4 | P12: PENDIENTE
A13: 46146 | B13: q | C13: 1234 | D13: OverShark | E13: jersey manga corta | F13: Denim | I13: 156 | K13: 156 | L13: =IFERROR(VLOOKUP(E13,PRODUCTOS!$A$4:$F$28,6,FALSE()),0) -> 1.7 | M13: =IFERROR(K13*L13,0) -> 265.2 | N13: =IFERROR(M13*CONFIG!$B$4,0) -> 26.52 | O13: =IFERROR(M13-N13,0) -> 238.68 | P13: PENDIENTE
A14: 46146 | B14: q | C14: 1234 | D14: OverShark | E14: wafle clasico | F14: P. Rosa | G14: 17 | H14: 36 | I14: 34 | J14: 18 | K14: 105 | L14: =IFERROR(VLOOKUP(E14,PRODUCTOS!$A$4:$F$28,6,FALSE()),0) -> 1.7 | M14: =IFERROR(K14*L14,0) -> 178.5 | N14: =IFERROR(M14*CONFIG!$B$4,0) -> 17.85 | O14: =IFERROR(M14-N14,0) -> 160.65 | P14: PENDIENTE
A15: 46146 | B15: q | C15: 1234 | D15: OverShark | E15: wafle clasico | F15: Denim | G15: 33 | I15: 68 | J15: 34 | K15: 135 | L15: =IFERROR(VLOOKUP(E15,PRODUCTOS!$A$4:$F$28,6,FALSE()),0) -> 1.7 | M15: =IFERROR(K15*L15,0) -> 229.5 | N15: =IFERROR(M15*CONFIG!$B$4,0) -> 22.95 | O15: =IFERROR(M15-N15,0) -> 206.55 | P15: PENDIENTE
A16: 46147 | B16: q | C16: 1234 | D16: Bravos | E16: Polera Boxy | F16: Vino | H16: 60 | K16: 60 | L16: =IFERROR(VLOOKUP(E16,PRODUCTOS!$A$4:$F$28,6,FALSE()),0) -> 4 | M16: =IFERROR(K16*L16,0) -> 240 | N16: =IFERROR(M16*CONFIG!$B$4,0) -> 24 | O16: =IFERROR(M16-N16,0) -> 216 | P16: PENDIENTE
A17: 46147 | B17: q | C17: 1234 | D17: Bravos | E17: Polera Boxy | F17: Negro | G17: 2 | H17: 2 | I17: 1 | K17: 5 | L17: =IFERROR(VLOOKUP(E17,PRODUCTOS!$A$4:$F$28,6,FALSE()),0) -> 4 | M17: =IFERROR(K17*L17,0) -> 20 | N17: =IFERROR(M17*CONFIG!$B$4,0) -> 2 | O17: =IFERROR(M17-N17,0) -> 18 | P17: PENDIENTE
A18: 46147 | B18: q | C18: 1234 | D18: OverShark | E18: jersey manga corta | F18: Vino | G18: 59 | H18: 118 | I18: 118 | J18: 58 | K18: 353 | L18: =IFERROR(VLOOKUP(E18,PRODUCTOS!$A$4:$F$28,6,FALSE()),0) -> 1.7 | M18: =IFERROR(K18*L18,0) -> 600.1 | N18: =IFERROR(M18*CONFIG!$B$4,0) -> 60.01 | O18: =IFERROR(M18-N18,0) -> 540.09 | P18: PENDIENTE
A19: 46147 | B19: q | C19: 1234 | D19: OverShark | E19: jersey manga corta | F19: Topo | I19: 152 | K19: 152 | L19: =IFERROR(VLOOKUP(E19,PRODUCTOS!$A$4:$F$28,6,FALSE()),0) -> 1.7 | M19: =IFERROR(K19*L19,0) -> 258.4 | N19: =IFERROR(M19*CONFIG!$B$4,0) -> 25.84 | O19: =IFERROR(M19-N19,0) -> 232.56 | P19: PENDIENTE
A20: 46147 | B20: q | C20: 1234 | D20: OverShark | E20: jersey manga corta | F20: Azul Marino | H20: 71 | I20: 72 | J20: 35 | K20: 178 | L20: =IFERROR(VLOOKUP(E20,PRODUCTOS!$A$4:$F$28,6,FALSE()),0) -> 1.7 | M20: =IFERROR(K20*L20,0) -> 302.6 | N20: =IFERROR(M20*CONFIG!$B$4,0) -> 30.26 | O20: =IFERROR(M20-N20,0) -> 272.34 | P20: PENDIENTE
A21: 46147 | B21: q | C21: 1234 | D21: OverShark | E21: pique camisero | F21: Negro | I21: 123 | J21: 90 | K21: 213 | L21: =IFERROR(VLOOKUP(E21,PRODUCTOS!$A$4:$F$28,6,FALSE()),0) -> 4 | M21: =IFERROR(K21*L21,0) -> 852 | N21: =IFERROR(M21*CONFIG!$B$4,0) -> 85.2 | O21: =IFERROR(M21-N21,0) -> 766.8 | P21: PENDIENTE
A22: 46147 | B22: q | C22: 1234 | D22: OverShark | E22: Baby Tee con S | F22: Negro | G22: 47 | H22: 48 | I22: 47 | K22: 142 | L22: =IFERROR(VLOOKUP(E22,PRODUCTOS!$A$4:$F$28,6,FALSE()),0) -> 1.7 | M22: =IFERROR(K22*L22,0) -> 241.4 | N22: =IFERROR(M22*CONFIG!$B$4,0) -> 24.14 | O22: =IFERROR(M22-N22,0) -> 217.26 | P22: PENDIENTE
A23: 46147 | B23: q | C23: 1234 | D23: OverShark | E23: Baby Tee M/L S | F23: Negro | G23: 48 | H23: 48 | I23: 48 | K23: 144 | L23: =IFERROR(VLOOKUP(E23,PRODUCTOS!$A$4:$F$28,6,FALSE()),0) -> 1.7 | M23: =IFERROR(K23*L23,0) -> 244.8 | N23: =IFERROR(M23*CONFIG!$B$4,0) -> 24.48 | O23: =IFERROR(M23-N23,0) -> 220.32 | P23: PENDIENTE
A24: 46147 | B24: q | C24: 1234 | D24: OverShark | E24: pique camisero | F24: Negro | H24: 118 | K24: 118 | L24: =IFERROR(VLOOKUP(E24,PRODUCTOS!$A$4:$F$28,6,FALSE()),0) -> 4 | M24: =IFERROR(K24*L24,0) -> 472 | N24: =IFERROR(M24*CONFIG!$B$4,0) -> 47.2 | O24: =IFERROR(M24-N24,0) -> 424.8 | P24: PENDIENTE
A25: 46147 | B25: q | C25: 1234 | D25: OverShark | E25: Baby Tee con S | F25: Azul Marino | I25: 69 | K25: 69 | L25: =IFERROR(VLOOKUP(E25,PRODUCTOS!$A$4:$F$28,6,FALSE()),0) -> 1.7 | M25: =IFERROR(K25*L25,0) -> 117.3 | N25: =IFERROR(M25*CONFIG!$B$4,0) -> 11.73 | O25: =IFERROR(M25-N25,0) -> 105.57 | P25: PENDIENTE
A26: 46147 | B26: q | C26: 1234 | D26: OverShark | E26: jersey manga corta | F26: Negro | G26: 50 | H26: 85 | K26: 135 | L26: =IFERROR(VLOOKUP(E26,PRODUCTOS!$A$4:$F$28,6,FALSE()),0) -> 1.7 | M26: =IFERROR(K26*L26,0) -> 229.5 | N26: =IFERROR(M26*CONFIG!$B$4,0) -> 22.95 | O26: =IFERROR(M26-N26,0) -> 206.55 | P26: PENDIENTE
A27: 46147 | B27: q | C27: 1234 | D27: OverShark | E27: Baby Tee con S | F27: Vino | H27: 55 | K27: 55 | L27: =IFERROR(VLOOKUP(E27,PRODUCTOS!$A$4:$F$28,6,FALSE()),0) -> 1.7 | M27: =IFERROR(K27*L27,0) -> 93.5 | N27: =IFERROR(M27*CONFIG!$B$4,0) -> 9.35 | O27: =IFERROR(M27-N27,0) -> 84.15 | P27: PENDIENTE
A28: 46147 | B28: q | C28: 1234 | D28: OverShark | E28: Baby Tee M/L S | F28: Azul Marino | H28: 69 | K28: 69 | L28: =IFERROR(VLOOKUP(E28,PRODUCTOS!$A$4:$F$28,6,FALSE()),0) -> 1.7 | M28: =IFERROR(K28*L28,0) -> 117.3 | N28: =IFERROR(M28*CONFIG!$B$4,0) -> 11.73 | O28: =IFERROR(M28-N28,0) -> 105.57 | P28: PENDIENTE
A29: 46147 | B29: q | C29: 1234 | D29: OverShark | E29: Baby Tee con S | F29: Colegial | H29: 55 | K29: 55 | L29: =IFERROR(VLOOKUP(E29,PRODUCTOS!$A$4:$F$28,6,FALSE()),0) -> 1.7 | M29: =IFERROR(K29*L29,0) -> 93.5 | N29: =IFERROR(M29*CONFIG!$B$4,0) -> 9.35 | O29: =IFERROR(M29-N29,0) -> 84.15 | P29: PENDIENTE
A30: 46147 | B30: q | C30: 1234 | D30: OverShark | E30: Baby Tee M/L S | F30: Azul Marino | G30: 70 | K30: 70 | L30: =IFERROR(VLOOKUP(E30,PRODUCTOS!$A$4:$F$28,6,FALSE()),0) -> 1.7 | M30: =IFERROR(K30*L30,0) -> 119 | N30: =IFERROR(M30*CONFIG!$B$4,0) -> 11.9 | O30: =IFERROR(M30-N30,0) -> 107.1 | P30: PENDIENTE
A31: 46147 | B31: q | C31: 1234 | D31: OverShark | E31: Baby Tee M/L S | F31: V. Pacay | G31: 26 | H31: 23 | I31: 27 | K31: 76 | L31: =IFERROR(VLOOKUP(E31,PRODUCTOS!$A$4:$F$28,6,FALSE()),0) -> 1.7 | M31: =IFERROR(K31*L31,0) -> 129.2 | N31: =IFERROR(M31*CONFIG!$B$4,0) -> 12.92 | O31: =IFERROR(M31-N31,0) -> 116.28 | P31: PENDIENTE
A32: 46147 | B32: q | C32: 1234 | D32: OverShark | E32: Baby Tee con S | F32: Azul Marino | G32: 68 | H32: 67 | K32: 135 | L32: =IFERROR(VLOOKUP(E32,PRODUCTOS!$A$4:$F$28,6,FALSE()),0) -> 1.7 | M32: =IFERROR(K32*L32,0) -> 229.5 | N32: =IFERROR(M32*CONFIG!$B$4,0) -> 22.95 | O32: =IFERROR(M32-N32,0) -> 206.55 | P32: PENDIENTE
A33: 46147 | B33: q | C33: 1234 | D33: OverShark | E33: Baby Tee M/L S | F33: Vino | G33: 55 | H33: 55 | I33: 54 | K33: 164 | L33: =IFERROR(VLOOKUP(E33,PRODUCTOS!$A$4:$F$28,6,FALSE()),0) -> 1.7 | M33: =IFERROR(K33*L33,0) -> 278.8 | N33: =IFERROR(M33*CONFIG!$B$4,0) -> 27.88 | O33: =IFERROR(M33-N33,0) -> 250.92 | P33: PENDIENTE
A34: 46147 | B34: q | C34: 1234 | D34: OverShark | E34: Baby Tee con S | F34: V. Pacay | G34: 25 | H34: 25 | I34: 26 | K34: 76 | L34: =IFERROR(VLOOKUP(E34,PRODUCTOS!$A$4:$F$28,6,FALSE()),0) -> 1.7 | M34: =IFERROR(K34*L34,0) -> 129.2 | N34: =IFERROR(M34*CONFIG!$B$4,0) -> 12.92 | O34: =IFERROR(M34-N34,0) -> 116.28 | P34: PENDIENTE
A35: 46147 | B35: q | C35: 1234 | D35: OverShark | E35: wafle clasico | F35: Denim | H35: 68 | K35: 68 | L35: =IFERROR(VLOOKUP(E35,PRODUCTOS!$A$4:$F$28,6,FALSE()),0) -> 1.7 | M35: =IFERROR(K35*L35,0) -> 115.6 | N35: =IFERROR(M35*CONFIG!$B$4,0) -> 11.56 | O35: =IFERROR(M35-N35,0) -> 104.04 | P35: PENDIENTE
A36: 46147 | B36: q | C36: 1234 | D36: OverShark | E36: Baby Tee M/L S | F36: Colegial | H36: 58 | K36: 58 | L36: =IFERROR(VLOOKUP(E36,PRODUCTOS!$A$4:$F$28,6,FALSE()),0) -> 1.7 | M36: =IFERROR(K36*L36,0) -> 98.6 | N36: =IFERROR(M36*CONFIG!$B$4,0) -> 9.86 | O36: =IFERROR(M36-N36,0) -> 88.74 | P36: PENDIENTE
A37: 46147 | B37: q | C37: 1234 | D37: OverShark | E37: Baby Tee con S | F37: Colegial | I37: 54 | K37: 54 | L37: =IFERROR(VLOOKUP(E37,PRODUCTOS!$A$4:$F$28,6,FALSE()),0) -> 1.7 | M37: =IFERROR(K37*L37,0) -> 91.8 | N37: =IFERROR(M37*CONFIG!$B$4,0) -> 9.18 | O37: =IFERROR(M37-N37,0) -> 82.62 | P37: PENDIENTE
A38: 46147 | B38: q | C38: 1234 | D38: OverShark | E38: Baby Tee con S | F38: Vino | G38: 55 | I38: 56 | K38: 111 | L38: =IFERROR(VLOOKUP(E38,PRODUCTOS!$A$4:$F$28,6,FALSE()),0) -> 1.7 | M38: =IFERROR(K38*L38,0) -> 188.7 | N38: =IFERROR(M38*CONFIG!$B$4,0) -> 18.87 | O38: =IFERROR(M38-N38,0) -> 169.83 | P38: PENDIENTE
A39: 46147 | B39: q | C39: 1234 | D39: OverShark | E39: Baby Tee M/L S | F39: Perla | H39: 62 | K39: 62 | L39: =IFERROR(VLOOKUP(E39,PRODUCTOS!$A$4:$F$28,6,FALSE()),0) -> 1.7 | M39: =IFERROR(K39*L39,0) -> 105.4 | N39: =IFERROR(M39*CONFIG!$B$4,0) -> 10.54 | O39: =IFERROR(M39-N39,0) -> 94.86 | P39: PENDIENTE
A40: 46147 | B40: q | C40: 1234 | D40: OverShark | E40: Baby Tee con S | F40: Perla | G40: 60 | H40: 60 | K40: 120 | L40: =IFERROR(VLOOKUP(E40,PRODUCTOS!$A$4:$F$28,6,FALSE()),0) -> 1.7 | M40: =IFERROR(K40*L40,0) -> 204 | N40: =IFERROR(M40*CONFIG!$B$4,0) -> 20.4 | O40: =IFERROR(M40-N40,0) -> 183.6 | P40: PENDIENTE
A41: 46147 | B41: q | C41: 1234 | D41: OverShark | E41: Baby Tee M/L S | F41: Perla | G41: 60 | K41: 60 | L41: =IFERROR(VLOOKUP(E41,PRODUCTOS!$A$4:$F$28,6,FALSE()),0) -> 1.7 | M41: =IFERROR(K41*L41,0) -> 102 | N41: =IFERROR(M41*CONFIG!$B$4,0) -> 10.2 | O41: =IFERROR(M41-N41,0) -> 91.8 | P41: PENDIENTE
A42: 46148 | B42: q | C42: 1234 | D42: OverShark | E42: Baby Tee con S | F42: Colegial | G42: 58 | K42: 58 | L42: =IFERROR(VLOOKUP(E42,PRODUCTOS!$A$4:$F$28,6,FALSE()),0) -> 1.7 | M42: =IFERROR(K42*L42,0) -> 98.6 | N42: =IFERROR(M42*CONFIG!$B$4,0) -> 9.86 | O42: =IFERROR(M42-N42,0) -> 88.74 | P42: PENDIENTE
A43: 46148 | B43: q | C43: 1234 | D43: OverShark | E43: Baby Tee M/L S | F43: Colegial | G43: 57 | I43: 57 | K43: 114 | L43: =IFERROR(VLOOKUP(E43,PRODUCTOS!$A$4:$F$28,6,FALSE()),0) -> 1.7 | M43: =IFERROR(K43*L43,0) -> 193.8 | N43: =IFERROR(M43*CONFIG!$B$4,0) -> 19.38 | O43: =IFERROR(M43-N43,0) -> 174.42 | P43: PENDIENTE
A44: 46148 | B44: q | C44: 1234 | D44: OverShark | E44: jersey manga corta | F44: Azul Marino | G44: 34 | K44: 34 | L44: =IFERROR(VLOOKUP(E44,PRODUCTOS!$A$4:$F$28,6,FALSE()),0) -> 1.7 | M44: =IFERROR(K44*L44,0) -> 57.8 | N44: =IFERROR(M44*CONFIG!$B$4,0) -> 5.78 | O44: =IFERROR(M44-N44,0) -> 52.02 | P44: PENDIENTE
A45: 46148 | B45: q | C45: 1234 | D45: OverShark | E45: jersey manga corta | F45: Negro | G45: 22 | J45: 50 | K45: 72 | L45: =IFERROR(VLOOKUP(E45,PRODUCTOS!$A$4:$F$28,6,FALSE()),0) -> 1.7 | M45: =IFERROR(K45*L45,0) -> 122.4 | N45: =IFERROR(M45*CONFIG!$B$4,0) -> 12.24 | O45: =IFERROR(M45-N45,0) -> 110.16 | P45: PENDIENTE
A46: 46148 | B46: q | C46: 1234 | D46: Bravos | E46: polera neru | F46: Colegial | G46: 84 | H46: 63 | I46: 84 | K46: 231 | L46: =IFERROR(VLOOKUP(E46,PRODUCTOS!$A$4:$F$28,6,FALSE()),0) -> 6 | M46: =IFERROR(K46*L46,0) -> 1386 | N46: =IFERROR(M46*CONFIG!$B$4,0) -> 138.6 | O46: =IFERROR(M46-N46,0) -> 1247.4 | P46: PENDIENTE
A47: 46148 | B47: q | C47: 1234 | D47: OverShark | E47: jersey manga corta | F47: V. Pacay | H47: 216 | K47: 216 | L47: =IFERROR(VLOOKUP(E47,PRODUCTOS!$A$4:$F$28,6,FALSE()),0) -> 1.7 | M47: =IFERROR(K47*L47,0) -> 367.2 | N47: =IFERROR(M47*CONFIG!$B$4,0) -> 36.72 | O47: =IFERROR(M47-N47,0) -> 330.48 | P47: PENDIENTE
A48: 46148 | B48: q | C48: 1234 | D48: Bravos | E48: polera neru | F48: Colegial | H48: 60 | K48: 60 | L48: =IFERROR(VLOOKUP(E48,PRODUCTOS!$A$4:$F$28,6,FALSE()),0) -> 6 | M48: =IFERROR(K48*L48,0) -> 360 | N48: =IFERROR(M48*CONFIG!$B$4,0) -> 36 | O48: =IFERROR(M48-N48,0) -> 324 | P48: PENDIENTE
A49: 46148 | B49: q | C49: 1234 | D49: Bravos | E49: polera neru | F49: Negro | H49: 2 | K49: 2 | L49: =IFERROR(VLOOKUP(E49,PRODUCTOS!$A$4:$F$28,6,FALSE()),0) -> 6 | M49: =IFERROR(K49*L49,0) -> 12 | N49: =IFERROR(M49*CONFIG!$B$4,0) -> 1.2 | O49: =IFERROR(M49-N49,0) -> 10.8 | P49: PENDIENTE
A50: 46148 | B50: q | C50: 1234 | D50: OverShark | E50: baby ty ml | F50: Colegial | H50: 2 | I50: 2 | K50: 4 | L50: =IFERROR(VLOOKUP(E50,PRODUCTOS!$A$4:$F$28,6,FALSE()),0) -> 1.7 | M50: =IFERROR(K50*L50,0) -> 6.8 | N50: =IFERROR(M50*CONFIG!$B$4,0) -> 0.68 | O50: =IFERROR(M50-N50,0) -> 6.12 | P50: PENDIENTE
A51: 46148 | B51: q | C51: 1234 | D51: OverShark | E51: pique camisero | F51: Beige | G51: 34 | H51: 16 | J51: 33 | K51: 83 | L51: =IFERROR(VLOOKUP(E51,PRODUCTOS!$A$4:$F$28,6,FALSE()),0) -> 4 | M51: =IFERROR(K51*L51,0) -> 332 | N51: =IFERROR(M51*CONFIG!$B$4,0) -> 33.2 | O51: =IFERROR(M51-N51,0) -> 298.8 | P51: PENDIENTE
A52: 46148 | B52: q | C52: 1234 | D52: OverShark | E52: wafle clasico | F52: Negro | G52: 69 | H52: 135 | I52: 67 | K52: 271 | L52: =IFERROR(VLOOKUP(E52,PRODUCTOS!$A$4:$F$28,6,FALSE()),0) -> 1.7 | M52: =IFERROR(K52*L52,0) -> 460.7 | N52: =IFERROR(M52*CONFIG!$B$4,0) -> 46.07 | O52: =IFERROR(M52-N52,0) -> 414.63 | P52: PENDIENTE
A53: 46148 | B53: q | C53: 1234 | D53: OverShark | E53: jersey manga corta | F53: Topo | G53: 75 | K53: 75 | L53: =IFERROR(VLOOKUP(E53,PRODUCTOS!$A$4:$F$28,6,FALSE()),0) -> 1.7 | M53: =IFERROR(K53*L53,0) -> 127.5 | N53: =IFERROR(M53*CONFIG!$B$4,0) -> 12.75 | O53: =IFERROR(M53-N53,0) -> 114.75 | P53: PENDIENTE
A54: 46148 | B54: q | C54: 1234 | D54: Bravos | E54: polera neru | F54: Perla | H54: 120 | K54: 120 | L54: =IFERROR(VLOOKUP(E54,PRODUCTOS!$A$4:$F$28,6,FALSE()),0) -> 6 | M54: =IFERROR(K54*L54,0) -> 720 | N54: =IFERROR(M54*CONFIG!$B$4,0) -> 72 | O54: =IFERROR(M54-N54,0) -> 648 | P54: PENDIENTE
A55: 46149 | B55: q | C55: 1234 | D55: OverShark | E55: pique camisero | F55: Negro | G55: 62 | J55: 134 | K55: 196 | L55: =IFERROR(VLOOKUP(E55,PRODUCTOS!$A$4:$F$28,6,FALSE()),0) -> 4 | M55: =IFERROR(K55*L55,0) -> 784 | N55: =IFERROR(M55*CONFIG!$B$4,0) -> 78.4 | O55: =IFERROR(M55-N55,0) -> 705.6 | P55: PENDIENTE
A56: 46149 | B56: q | C56: 1234 | D56: Bravos | E56: Polera Boxy | F56: Colegial | H56: 48 | K56: 48 | L56: =IFERROR(VLOOKUP(E56,PRODUCTOS!$A$4:$F$28,6,FALSE()),0) -> 4 | M56: =IFERROR(K56*L56,0) -> 192 | N56: =IFERROR(M56*CONFIG!$B$4,0) -> 19.2 | O56: =IFERROR(M56-N56,0) -> 172.8 | P56: PENDIENTE
A57: 46149 | B57: q | C57: 1234 | D57: OverShark | E57: top ml rib | F57: Perla | K57: 75 | L57: =IFERROR(VLOOKUP(E57,PRODUCTOS!$A$4:$F$28,6,FALSE()),0) -> 1.7 | M57: =IFERROR(K57*L57,0) -> 127.5 | N57: =IFERROR(M57*CONFIG!$B$4,0) -> 12.75 | O57: =IFERROR(M57-N57,0) -> 114.75 | P57: PENDIENTE
A58: 46149 | B58: q | C58: 1234 | D58: OverShark | E58: top mc rib | F58: Perla | K58: 126 | L58: =IFERROR(VLOOKUP(E58,PRODUCTOS!$A$4:$F$28,6,FALSE()),0) -> 1.7 | M58: =IFERROR(K58*L58,0) -> 214.2 | N58: =IFERROR(M58*CONFIG!$B$4,0) -> 21.42 | O58: =IFERROR(M58-N58,0) -> 192.78 | P58: PENDIENTE
A59: 46149 | B59: q | C59: 1234 | D59: OverShark | E59: pique camisero | F59: Negro | G59: 82 | H59: 113 | I59: 97 | K59: 292 | L59: =IFERROR(VLOOKUP(E59,PRODUCTOS!$A$4:$F$28,6,FALSE()),0) -> 4 | M59: =IFERROR(K59*L59,0) -> 1168 | N59: =IFERROR(M59*CONFIG!$B$4,0) -> 116.8 | O59: =IFERROR(M59-N59,0) -> 1051.2 | P59: PENDIENTE
A60: 46149 | B60: q | C60: 1234 | D60: OverShark | E60: jersey manga larga | F60: Cemento | H60: 180 | I60: 182 | K60: 362 | L60: =IFERROR(VLOOKUP(E60,PRODUCTOS!$A$4:$F$28,6,FALSE()),0) -> 2 | M60: =IFERROR(K60*L60,0) -> 724 | N60: =IFERROR(M60*CONFIG!$B$4,0) -> 72.4 | O60: =IFERROR(M60-N60,0) -> 651.6 | P60: PENDIENTE
A61: 46149 | B61: q | C61: 1234 | D61: OverShark | E61: wafle camisero | F61: Vino | H61: 131 | K61: 131 | L61: =IFERROR(VLOOKUP(E61,PRODUCTOS!$A$4:$F$28,6,FALSE()),0) -> 4 | M61: =IFERROR(K61*L61,0) -> 524 | N61: =IFERROR(M61*CONFIG!$B$4,0) -> 52.4 | O61: =IFERROR(M61-N61,0) -> 471.6 | P61: PENDIENTE
A62: 46149 | B62: q | C62: 1234 | D62: OverShark | E62: Baby Tee M/L S | F62: Azul Marino | I62: 69 | K62: 69 | L62: =IFERROR(VLOOKUP(E62,PRODUCTOS!$A$4:$F$28,6,FALSE()),0) -> 1.7 | M62: =IFERROR(K62*L62,0) -> 117.3 | N62: =IFERROR(M62*CONFIG!$B$4,0) -> 11.73 | O62: =IFERROR(M62-N62,0) -> 105.57 | P62: PENDIENTE
A63: 46149 | B63: q | C63: 1234 | D63: Bravos | E63: polera neru | F63: Negro | I63: 96 | K63: 96 | L63: =IFERROR(VLOOKUP(E63,PRODUCTOS!$A$4:$F$28,6,FALSE()),0) -> 6 | M63: =IFERROR(K63*L63,0) -> 576 | N63: =IFERROR(M63*CONFIG!$B$4,0) -> 57.6 | O63: =IFERROR(M63-N63,0) -> 518.4 | P63: PENDIENTE
A64: 46149 | B64: q | C64: 1234 | D64: Bravos | E64: polera neru | F64: Beige | G64: 31 | K64: 31 | L64: =IFERROR(VLOOKUP(E64,PRODUCTOS!$A$4:$F$28,6,FALSE()),0) -> 6 | M64: =IFERROR(K64*L64,0) -> 186 | N64: =IFERROR(M64*CONFIG!$B$4,0) -> 18.6 | O64: =IFERROR(M64-N64,0) -> 167.4 | P64: PENDIENTE
A65: 46149 | B65: q | C65: 1234 | D65: OverShark | E65: wafle clasico | F65: Negro | J65: 68 | K65: 68 | L65: =IFERROR(VLOOKUP(E65,PRODUCTOS!$A$4:$F$28,6,FALSE()),0) -> 1.7 | M65: =IFERROR(K65*L65,0) -> 115.6 | N65: =IFERROR(M65*CONFIG!$B$4,0) -> 11.56 | O65: =IFERROR(M65-N65,0) -> 104.04 | P65: PENDIENTE
A66: 46149 | B66: q | C66: 1234 | D66: OverShark | E66: Baby Tee con S | F66: Perla | I66: 60 | K66: 60 | L66: =IFERROR(VLOOKUP(E66,PRODUCTOS!$A$4:$F$28,6,FALSE()),0) -> 1.7 | M66: =IFERROR(K66*L66,0) -> 102 | N66: =IFERROR(M66*CONFIG!$B$4,0) -> 10.2 | O66: =IFERROR(M66-N66,0) -> 91.8 | P66: PENDIENTE
A67: 46149 | B67: q | C67: 1234 | D67: OverShark | E67: Baby Tee M/L S | F67: Perla | I67: 62 | K67: 62 | L67: =IFERROR(VLOOKUP(E67,PRODUCTOS!$A$4:$F$28,6,FALSE()),0) -> 1.7 | M67: =IFERROR(K67*L67,0) -> 105.4 | N67: =IFERROR(M67*CONFIG!$B$4,0) -> 10.54 | O67: =IFERROR(M67-N67,0) -> 94.86 | P67: PENDIENTE
A68: 46149 | B68: q | C68: 1234 | D68: OverShark | E68: top mc rib | F68: Negro | K68: 190 | L68: =IFERROR(VLOOKUP(E68,PRODUCTOS!$A$4:$F$28,6,FALSE()),0) -> 1.7 | M68: =IFERROR(K68*L68,0) -> 323 | N68: =IFERROR(M68*CONFIG!$B$4,0) -> 32.3 | O68: =IFERROR(M68-N68,0) -> 290.7 | P68: PENDIENTE
A69: 46149 | B69: q | C69: 1234 | D69: OverShark | E69: top mc rib | F69: Azul Marino | K69: 118 | L69: =IFERROR(VLOOKUP(E69,PRODUCTOS!$A$4:$F$28,6,FALSE()),0) -> 1.7 | M69: =IFERROR(K69*L69,0) -> 200.6 | N69: =IFERROR(M69*CONFIG!$B$4,0) -> 20.06 | O69: =IFERROR(M69-N69,0) -> 180.54 | P69: PENDIENTE
A70: 46149 | B70: q | C70: 1234 | D70: Bravos | E70: polera neru | F70: Negro | G70: 99 | H70: 49 | K70: 148 | L70: =IFERROR(VLOOKUP(E70,PRODUCTOS!$A$4:$F$28,6,FALSE()),0) -> 6 | M70: =IFERROR(K70*L70,0) -> 888 | N70: =IFERROR(M70*CONFIG!$B$4,0) -> 88.8 | O70: =IFERROR(M70-N70,0) -> 799.2 | P70: PENDIENTE
A71: 46149 | B71: q | C71: 1234 | D71: Bravos | E71: Polera Boxy | F71: Colegial | G71: 35 | I71: 33 | K71: 68 | L71: =IFERROR(VLOOKUP(E71,PRODUCTOS!$A$4:$F$28,6,FALSE()),0) -> 4 | M71: =IFERROR(K71*L71,0) -> 272 | N71: =IFERROR(M71*CONFIG!$B$4,0) -> 27.2 | O71: =IFERROR(M71-N71,0) -> 244.8 | P71: PENDIENTE
A72: 46149 | B72: q | C72: 1234 | D72: OverShark | E72: top ml rib | F72: Negro | K72: 141 | L72: =IFERROR(VLOOKUP(E72,PRODUCTOS!$A$4:$F$28,6,FALSE()),0) -> 1.7 | M72: =IFERROR(K72*L72,0) -> 239.7 | N72: =IFERROR(M72*CONFIG!$B$4,0) -> 23.97 | O72: =IFERROR(M72-N72,0) -> 215.73 | P72: PENDIENTE
A73: 46149 | B73: q | C73: 1234 | D73: OverShark | E73: top ml rib | F73: P. Rosa | K73: 46 | L73: =IFERROR(VLOOKUP(E73,PRODUCTOS!$A$4:$F$28,6,FALSE()),0) -> 1.7 | M73: =IFERROR(K73*L73,0) -> 78.2 | N73: =IFERROR(M73*CONFIG!$B$4,0) -> 7.82 | O73: =IFERROR(M73-N73,0) -> 70.38 | P73: PENDIENTE
A74: 46149 | B74: q | C74: 1234 | D74: OverShark | E74: top mc rib | F74: P. Rosa | K74: 62 | L74: =IFERROR(VLOOKUP(E74,PRODUCTOS!$A$4:$F$28,6,FALSE()),0) -> 1.7 | M74: =IFERROR(K74*L74,0) -> 105.4 | N74: =IFERROR(M74*CONFIG!$B$4,0) -> 10.54 | O74: =IFERROR(M74-N74,0) -> 94.86 | P74: PENDIENTE
A75: 46149 | B75: q | C75: 1234 | D75: OverShark | E75: top ml rib | F75: Azul Marino | K75: 90 | L75: =IFERROR(VLOOKUP(E75,PRODUCTOS!$A$4:$F$28,6,FALSE()),0) -> 1.7 | M75: =IFERROR(K75*L75,0) -> 153 | N75: =IFERROR(M75*CONFIG!$B$4,0) -> 15.3 | O75: =IFERROR(M75-N75,0) -> 137.7 | P75: PENDIENTE
A76: 46149 | B76: q | C76: 1234 | D76: OverShark | E76: pique camisero | F76: Azul Marino | H76: 128 | I76: 120 | J76: 63 | K76: 311 | L76: =IFERROR(VLOOKUP(E76,PRODUCTOS!$A$4:$F$28,6,FALSE()),0) -> 4 | M76: =IFERROR(K76*L76,0) -> 1244 | N76: =IFERROR(M76*CONFIG!$B$4,0) -> 124.4 | O76: =IFERROR(M76-N76,0) -> 1119.6 | P76: PENDIENTE
A77: 46150 | B77: q | C77: 1234 | D77: OverShark | E77: wafle clasico | F77: Cemento | G77: 34 | H77: 67 | I77: 67 | J77: 33 | K77: 201 | L77: =IFERROR(VLOOKUP(E77,PRODUCTOS!$A$4:$F$28,6,FALSE()),0) -> 1.7 | M77: =IFERROR(K77*L77,0) -> 341.7 | N77: =IFERROR(M77*CONFIG!$B$4,0) -> 34.17 | O77: =IFERROR(M77-N77,0) -> 307.53 | P77: PENDIENTE
A78: 46150 | B78: q | C78: 1234 | D78: OverShark | E78: pique camisero | F78: Vino | G78: 54 | H78: 105 | I78: 109 | J78: 53 | K78: 321 | L78: =IFERROR(VLOOKUP(E78,PRODUCTOS!$A$4:$F$28,6,FALSE()),0) -> 4 | M78: =IFERROR(K78*L78,0) -> 1284 | N78: =IFERROR(M78*CONFIG!$B$4,0) -> 128.4 | O78: =IFERROR(M78-N78,0) -> 1155.6 | P78: PENDIENTE
A79: 46150 | B79: q | C79: 1234 | D79: Bravos | E79: polera neru | F79: Botella | H79: 63 | K79: 63 | L79: =IFERROR(VLOOKUP(E79,PRODUCTOS!$A$4:$F$28,6,FALSE()),0) -> 6 | M79: =IFERROR(K79*L79,0) -> 378 | N79: =IFERROR(M79*CONFIG!$B$4,0) -> 37.8 | O79: =IFERROR(M79-N79,0) -> 340.2 | P79: PENDIENTE
A80: 46150 | B80: q | C80: 1234 | D80: OverShark | E80: jersey manga corta | F80: Vino | H80: 115 | K80: 115 | L80: =IFERROR(VLOOKUP(E80,PRODUCTOS!$A$4:$F$28,6,FALSE()),0) -> 1.7 | M80: =IFERROR(K80*L80,0) -> 195.5 | N80: =IFERROR(M80*CONFIG!$B$4,0) -> 19.55 | O80: =IFERROR(M80-N80,0) -> 175.95 | P80: PENDIENTE
A81: 46150 | B81: q | C81: 1234 | D81: OverShark | E81: top mc rib | F81: Beige | K81: 56 | L81: =IFERROR(VLOOKUP(E81,PRODUCTOS!$A$4:$F$28,6,FALSE()),0) -> 1.7 | M81: =IFERROR(K81*L81,0) -> 95.2 | N81: =IFERROR(M81*CONFIG!$B$4,0) -> 9.52 | O81: =IFERROR(M81-N81,0) -> 85.68 | P81: PENDIENTE
A82: 46150 | B82: q | C82: 1234 | D82: OverShark | E82: top ml rib | F82: Beige | K82: 42 | L82: =IFERROR(VLOOKUP(E82,PRODUCTOS!$A$4:$F$28,6,FALSE()),0) -> 1.7 | M82: =IFERROR(K82*L82,0) -> 71.4 | N82: =IFERROR(M82*CONFIG!$B$4,0) -> 7.14 | O82: =IFERROR(M82-N82,0) -> 64.26 | P82: PENDIENTE
A83: 46150 | B83: q | C83: 1234 | D83: OverShark | E83: wafle clasico | F83: Vino | G83: 69 | H83: 134 | I83: 137 | J83: 67 | K83: 407 | L83: =IFERROR(VLOOKUP(E83,PRODUCTOS!$A$4:$F$28,6,FALSE()),0) -> 1.7 | M83: =IFERROR(K83*L83,0) -> 691.9 | N83: =IFERROR(M83*CONFIG!$B$4,0) -> 69.19 | O83: =IFERROR(M83-N83,0) -> 622.71 | P83: PENDIENTE
A84: 46150 | B84: q | C84: 1234 | D84: OverShark | E84: top mc rib | F84: Cemento | K84: 54 | L84: =IFERROR(VLOOKUP(E84,PRODUCTOS!$A$4:$F$28,6,FALSE()),0) -> 1.7 | M84: =IFERROR(K84*L84,0) -> 91.8 | N84: =IFERROR(M84*CONFIG!$B$4,0) -> 9.18 | O84: =IFERROR(M84-N84,0) -> 82.62 | P84: PENDIENTE
A85: 46150 | B85: q | C85: 1234 | D85: Bravos | E85: polera neru | F85: Negro | G85: 40 | H85: 20 | I85: 40 | K85: 100 | L85: =IFERROR(VLOOKUP(E85,PRODUCTOS!$A$4:$F$28,6,FALSE()),0) -> 6 | M85: =IFERROR(K85*L85,0) -> 600 | N85: =IFERROR(M85*CONFIG!$B$4,0) -> 60 | O85: =IFERROR(M85-N85,0) -> 540 | P85: PENDIENTE
A86: 46150 | B86: q | C86: 1234 | D86: OverShark | E86: top ml rib | F86: Cemento | K86: 42 | L86: =IFERROR(VLOOKUP(E86,PRODUCTOS!$A$4:$F$28,6,FALSE()),0) -> 1.7 | M86: =IFERROR(K86*L86,0) -> 71.4 | N86: =IFERROR(M86*CONFIG!$B$4,0) -> 7.14 | O86: =IFERROR(M86-N86,0) -> 64.26 | P86: PENDIENTE
A87: 46150 | B87: q | C87: 1234 | D87: OverShark | E87: top ml rib | F87: Perla | K87: 20 | L87: =IFERROR(VLOOKUP(E87,PRODUCTOS!$A$4:$F$28,6,FALSE()),0) -> 1.7 | M87: =IFERROR(K87*L87,0) -> 34 | N87: =IFERROR(M87*CONFIG!$B$4,0) -> 3.4 | O87: =IFERROR(M87-N87,0) -> 30.6 | P87: PENDIENTE
A88: 46150 | B88: q | C88: 1234 | D88: Bravos | E88: polera neru | F88: Vino | G88: 2 | K88: 2 | L88: =IFERROR(VLOOKUP(E88,PRODUCTOS!$A$4:$F$28,6,FALSE()),0) -> 6 | M88: =IFERROR(K88*L88,0) -> 12 | N88: =IFERROR(M88*CONFIG!$B$4,0) -> 1.2 | O88: =IFERROR(M88-N88,0) -> 10.8 | P88: PENDIENTE
A89: 46150 | B89: q | C89: 1234 | D89: OverShark | E89: wafle clasico | F89: Colegial | G89: 32 | I89: 64 | J89: 32 | K89: 128 | L89: =IFERROR(VLOOKUP(E89,PRODUCTOS!$A$4:$F$28,6,FALSE()),0) -> 1.7 | M89: =IFERROR(K89*L89,0) -> 217.6 | N89: =IFERROR(M89*CONFIG!$B$4,0) -> 21.76 | O89: =IFERROR(M89-N89,0) -> 195.84 | P89: PENDIENTE
A90: 46150 | B90: q | C90: 1234 | D90: OverShark | E90: jersey manga larga | F90: Vino | G90: 57 | J90: 58 | K90: 115 | L90: =IFERROR(VLOOKUP(E90,PRODUCTOS!$A$4:$F$28,6,FALSE()),0) -> 2 | M90: =IFERROR(K90*L90,0) -> 230 | N90: =IFERROR(M90*CONFIG!$B$4,0) -> 23 | O90: =IFERROR(M90-N90,0) -> 207 | P90: PENDIENTE
A91: 46150 | B91: q | C91: 1234 | D91: OverShark | E91: pique camisero | F91: Denim | G91: 51 | H91: 101 | I91: 103 | J91: 50 | K91: 305 | L91: =IFERROR(VLOOKUP(E91,PRODUCTOS!$A$4:$F$28,6,FALSE()),0) -> 4 | M91: =IFERROR(K91*L91,0) -> 1220 | N91: =IFERROR(M91*CONFIG!$B$4,0) -> 122 | O91: =IFERROR(M91-N91,0) -> 1098 | P91: PENDIENTE
A92: 46150 | B92: q | C92: 1234 | D92: OverShark | E92: wafle clasico | F92: Colegial | H92: 63 | K92: 63 | L92: =IFERROR(VLOOKUP(E92,PRODUCTOS!$A$4:$F$28,6,FALSE()),0) -> 1.7 | M92: =IFERROR(K92*L92,0) -> 107.1 | N92: =IFERROR(M92*CONFIG!$B$4,0) -> 10.71 | O92: =IFERROR(M92-N92,0) -> 96.39 | P92: PENDIENTE
A93: 46150 | B93: q | C93: 1234 | D93: OverShark | E93: jersey manga larga | F93: Perla | G93: 34 | I93: 66 | J93: 35 | K93: 135 | L93: =IFERROR(VLOOKUP(E93,PRODUCTOS!$A$4:$F$28,6,FALSE()),0) -> 2 | M93: =IFERROR(K93*L93,0) -> 270 | N93: =IFERROR(M93*CONFIG!$B$4,0) -> 27 | O93: =IFERROR(M93-N93,0) -> 243 | P93: PENDIENTE
A94: 46150 | B94: q | C94: 1234 | D94: Bravos | E94: polera neru | F94: Botella | G94: 68 | H94: 47 | I94: 1 | K94: 116 | L94: =IFERROR(VLOOKUP(E94,PRODUCTOS!$A$4:$F$28,6,FALSE()),0) -> 6 | M94: =IFERROR(K94*L94,0) -> 696 | N94: =IFERROR(M94*CONFIG!$B$4,0) -> 69.6 | O94: =IFERROR(M94-N94,0) -> 626.4 | P94: PENDIENTE
A95: 46150 | B95: q | C95: 1234 | D95: OverShark | E95: wafle clasico | F95: Negro | I95: 71 | K95: 71 | L95: =IFERROR(VLOOKUP(E95,PRODUCTOS!$A$4:$F$28,6,FALSE()),0) -> 1.7 | M95: =IFERROR(K95*L95,0) -> 120.7 | N95: =IFERROR(M95*CONFIG!$B$4,0) -> 12.07 | O95: =IFERROR(M95-N95,0) -> 108.63 | P95: PENDIENTE
A96: 46150 | B96: q | C96: 1234 | D96: OverShark | E96: jersey manga corta | F96: Negro | I96: 99 | K96: 99 | L96: =IFERROR(VLOOKUP(E96,PRODUCTOS!$A$4:$F$28,6,FALSE()),0) -> 1.7 | M96: =IFERROR(K96*L96,0) -> 168.3 | N96: =IFERROR(M96*CONFIG!$B$4,0) -> 16.83 | O96: =IFERROR(M96-N96,0) -> 151.47 | P96: PENDIENTE
A97: 46150 | B97: q | C97: 1234 | D97: OverShark | E97: jersey manga larga | F97: Azul Marino | I97: 44 | K97: 44 | L97: =IFERROR(VLOOKUP(E97,PRODUCTOS!$A$4:$F$28,6,FALSE()),0) -> 2 | M97: =IFERROR(K97*L97,0) -> 88 | N97: =IFERROR(M97*CONFIG!$B$4,0) -> 8.8 | O97: =IFERROR(M97-N97,0) -> 79.2 | P97: PENDIENTE
A98: 46151 | B98: q | C98: 1234 | D98: OverShark | E98: pique camisero | F98: Topo | G98: 67 | H98: 133 | I98: 135 | J98: 67 | K98: 402 | L98: =IFERROR(VLOOKUP(E98,PRODUCTOS!$A$4:$F$28,6,FALSE()),0) -> 4 | M98: =IFERROR(K98*L98,0) -> 1608 | N98: =IFERROR(M98*CONFIG!$B$4,0) -> 160.8 | O98: =IFERROR(M98-N98,0) -> 1447.2 | P98: PENDIENTE
A99: 46151 | B99: q | C99: 1234 | D99: OverShark | E99: jersey manga larga | F99: Negro | G99: 50 | H99: 98 | I99: 98 | J99: 48 | K99: 294 | L99: =IFERROR(VLOOKUP(E99,PRODUCTOS!$A$4:$F$28,6,FALSE()),0) -> 2 | M99: =IFERROR(K99*L99,0) -> 588 | N99: =IFERROR(M99*CONFIG!$B$4,0) -> 58.8 | O99: =IFERROR(M99-N99,0) -> 529.2 | P99: PENDIENTE
A100: 46151 | B100: q | C100: 1234 | D100: OverShark | E100: jersey manga larga | F100: Azul Marino | G100: 28 | H100: 56 | I100: 11 | J100: 27 | K100: 122 | L100: =IFERROR(VLOOKUP(E100,PRODUCTOS!$A$4:$F$28,6,FALSE()),0) -> 2 | M100: =IFERROR(K100*L100,0) -> 244 | N100: =IFERROR(M100*CONFIG!$B$4,0) -> 24.4 | O100: =IFERROR(M100-N100,0) -> 219.6 | P100: PENDIENTE
...

Sheet Hoja 1

Sheet INSTRUCCIONES
A1: COBROS TALLER — Cuánto cobrar al cliente x prenda
A3: PROPÓSITO:
A4: Saber cuánto debes cobrar al cliente por cada prenda que confeccionas,
A5: considerando tu costo de mano de obra interno, el margen que quieres ganar
A6: y la detracción del 10% que se aplica en Perú.
A8: CÓMO USAR:
A9: 1) PRODUCTOS — tabla con todos los productos del taller.
A10: • Llena COSTO MO (lo que pagas a los costureros por hacer 1 prenda)
A11: • Llena PRECIO VENTA ACTUAL (lo que estás cobrando hoy al cliente)
A12: • El sistema calcula PRECIO RECOMENDADO según margen + detracción.
A14: 2) COBROS_DIARIOS — registro diario.
A15: • Una fila por entrega/cobro. Pones fecha, cliente, producto, cantidad.
... A33: • "DISPONIBLE INMEDIATO" = 90% que entra a tu cuenta corriente al toque

Sheet CONFIG
A1: CONFIGURACIÓN
A2: Parámetro | B2: Valor | C2: Descripción
A3: Margen objetivo (sobre costo MO) | B3: 0.4 | C3: Margen deseado: 40% sobre costo MO
A4: Detracción (%) | B4: 0.1 | C4: 10% se retiene para cuenta de detracción
A5: IGV (%) | B5: 0.18 | C5: 18% en Perú (opcional, si emites factura)
A6: Incluir IGV en precio sugerido | B6: NO | C6: SÍ/NO. Si SÍ, suma 18% al precio sugerido

Sheet PRODUCTOS
A1: PRODUCTOS — Costos y precios de confección
A2: COSTO MO = lo que pagas en mano de obra por hacer 1 prenda. PRECIO VENTA = lo que cobras al cliente.
A3: PRODUCTO | B3: COSTO MO (interno) S/. | C3: MARGEN % | D3: PRECIO BASE (auto) | E3: PRECIO SUGERIDO (costo + margen) | F3: PRECIO VENTA ACTUAL S/. | G3: + Detracc. (auto) | H3: DISPONIBLE INMEDIATO 90% | I3: MARGEN REAL (vs costo)
A4: jersey manga corta | B4: 0.95 | C4: =CONFIG!$B$3 -> 0.4 | D4: =IFERROR(B4*(1+C4),0) -> 1.33 | E4: =IFERROR(IF(B4="","",IF(CONFIG!$B$6="SÍ",D4*(1+CONFIG!$B$5),D4)),"") -> 1.33 | F4: 1.7 | G4: =IFERROR(F4*CONFIG!$B$4,0) -> 0.17 | H4: =IFERROR(F4-G4,0) -> 1.53 | I4: =IFERROR(IF(F4>0,(F4-B4)/F4,""),"") -> 0.44117647
A5: jersey manga larga | B5: 1 | C5: =CONFIG!$B$3 -> 0.4 | D5: =IFERROR(B5*(1+C5),0) -> 1.4 | E5: =IFERROR(IF(B5="","",IF(CONFIG!$B$6="SÍ",D5*(1+CONFIG!$B$5),D5)),"") -> 1.4 | F5: 2 | G5: =IFERROR(F5*CONFIG!$B$4,0) -> 0.2 | H5: =IFERROR(F5-G5,0) -> 1.8 | I5: =IFERROR(IF(F5>0,(F5-B5)/F5,""),"") -> 0.5
A6: wafle clasico | B6: 0.95 | C6: =CONFIG!$B$3 -> 0.4 | D6: =IFERROR(B6*(1+C6),0) -> 1.33 | E6: =IFERROR(IF(B6="","",IF(CONFIG!$B$6="SÍ",D6*(1+CONFIG!$B$5),D6)),"") -> 1.33 | F6: 1.7 | G6: =IFERROR(F6*CONFIG!$B$4,0) -> 0.17 | H6: =IFERROR(F6-G6,0) -> 1.53 | I6: =IFERROR(IF(F6>0,(F6-B6)/F6,""),"") -> 0.44117647
A7: wafle manga larga | B7: 1 | C7: =CONFIG!$B$3 -> 0.4 | D7: =IFERROR(B7*(1+C7),0) -> 1.4 | E7: =IFERROR(IF(B7="","",IF(CONFIG!$B$6="SÍ",D7*(1+CONFIG!$B$5),D7)),"") -> 1.4 | F7: 2 | G7: =IFERROR(F7*CONFIG!$B$4,0) -> 0.2 | H7: =IFERROR(F7-G7,0) -> 1.8 | I7: =IFERROR(IF(F7>0,(F7-B7)/F7,""),"") -> 0.5
A8: wafle camisero | B8: 1.96 | C8: =CONFIG!$B$3 -> 0.4 | D8: =IFERROR(B8*(1+C8),0) -> 2.744 | E8: =IFERROR(IF(B8="","",IF(CONFIG!$B$6="SÍ",D8*(1+CONFIG!$B$5),D8)),"") -> 2.744 | F8: 4 | G8: =IFERROR(F8*CONFIG!$B$4,0) -> 0.4 | H8: =IFERROR(F8-G8,0) -> 3.6 | I8: =IFERROR(IF(F8>0,(F8-B8)/F8,""),"") -> 0.51
A9: pique camisero | B9: 1.96 | C9: =CONFIG!$B$3 -> 0.4 | D9: =IFERROR(B9*(1+C9),0) -> 2.744 | E9: =IFERROR(IF(B9="","",IF(CONFIG!$B$6="SÍ",D9*(1+CONFIG!$B$5),D9)),"") -> 2.744 | F9: 4 | G9: =IFERROR(F9*CONFIG!$B$4,0) -> 0.4 | H9: =IFERROR(F9-G9,0) -> 3.6 | I9: =IFERROR(IF(F9>0,(F9-B9)/F9,""),"") -> 0.51
A10: top cero rib | B10: 0.74 | C10: =CONFIG!$B$3 -> 0.4 | D10: =IFERROR(B10*(1+C10),0) -> 1.036 | E10: =IFERROR(IF(B10="","",IF(CONFIG!$B$6="SÍ",D10*(1+CONFIG!$B$5),D10)),"") -> 1.036 | F10: 1.1 | G10: =IFERROR(F10*CONFIG!$B$4,0) -> 0.11 | H10: =IFERROR(F10-G10,0) -> 0.99 | I10: =IFERROR(IF(F10>0,(F10-B10)/F10,""),"") -> 0.32727273
A11: top mc rib | B11: 0.8 | C11: =CONFIG!$B$3 -> 0.4 | D11: =IFERROR(B11*(1+C11),0) -> 1.12 | E11: =IFERROR(IF(B11="","",IF(CONFIG!$B$6="SÍ",D11*(1+CONFIG!$B$5),D11)),"") -> 1.12 | F11: 1.7 | G11: =IFERROR(F11*CONFIG!$B$4,0) -> 0.17 | H11: =IFERROR(F11-G11,0) -> 1.53 | I11: =IFERROR(IF(F11>0,(F11-B11)/F11,""),"") -> 0.52941176
A12: top ml rib | B12: 0.85 | C12: =CONFIG!$B$3 -> 0.4 | D12: =IFERROR(B12*(1+C12),0) -> 1.19 | E12: =IFERROR(IF(B12="","",IF(CONFIG!$B$6="SÍ",D12*(1+CONFIG!$B$5),D12)),"") -> 1.19 | F12: 1.7 | G12: =IFERROR(F12*CONFIG!$B$4,0) -> 0.17 | H12: =IFERROR(F12-G12,0) -> 1.53 | I12: =IFERROR(IF(F12>0,(F12-B12)/F12,""),"") -> 0.5
A13: baby ty mc | B13: 0.76 | C13: =CONFIG!$B$3 -> 0.4 | D13: =IFERROR(B13*(1+C13),0) -> 1.064 | E13: =IFERROR(IF(B13="","",IF(CONFIG!$B$6="SÍ",D13*(1+CONFIG!$B$5),D13)),"") -> 1.064 | F13: 1.7 | G13: =IFERROR(F13*CONFIG!$B$4,0) -> 0.17 | H13: =IFERROR(F13-G13,0) -> 1.53 | I13: =IFERROR(IF(F13>0,(F13-B13)/F13,""),"") -> 0.55294118
A14: baby ty ml | B14: 0.83 | C14: =CONFIG!$B$3 -> 0.4 | D14: =IFERROR(B14*(1+C14),0) -> 1.162 | E14: =IFERROR(IF(B14="","",IF(CONFIG!$B$6="SÍ",D14*(1+CONFIG!$B$5),D14)),"") -> 1.162 | F14: 1.7 | G14: =IFERROR(F14*CONFIG!$B$4,0) -> 0.17 | H14: =IFERROR(F14-G14,0) -> 1.53 | I14: =IFERROR(IF(F14>0,(F14-B14)/F14,""),"") -> 0.51176471
A15: Baby Tee con S | B15: 0.64 | C15: =CONFIG!$B$3 -> 0.4 | D15: =IFERROR(B15*(1+C15),0) -> 0.896 | E15: =IFERROR(IF(B15="","",IF(CONFIG!$B$6="SÍ",D15*(1+CONFIG!$B$5),D15)),"") -> 0.896 | F15: 1.7 | G15: =IFERROR(F15*CONFIG!$B$4,0) -> 0.17 | H15: =IFERROR(F15-G15,0) -> 1.53 | I15: =IFERROR(IF(F15>0,(F15-B15)/F15,""),"") -> 0.62352941
... A18: polera boxy | B18: 1.66 | C18: =CONFIG!$B$3 -> 0.4 | D18: =IFERROR(B18*(1+C18),0) -> 2.324 | E18: =IFERROR(IF(B18="","",IF(CONFIG!$B$6="SÍ",D18*(1+CONFIG!$B$5),D18)),"") -> 2.324 | F18: 4 | G18: =IFERROR(F18*CONFIG!$B$4,0) -> 0.4 | H18: =IFERROR(F18-G18,0) -> 3.6 | I18: =IFERROR(IF(F18>0,(F18-B18)/F18,""),"") -> 0.585
A19: pique cuello chino | B19: 1.53 | C19: =CONFIG!$B$3 -> 0.4 | D19: =IFERROR(B19*(1+C19),0) -> 2.142 | E19: =IFERROR(IF(B19="","",IF(CONFIG!$B$6="SÍ",D19*(1+CONFIG!$B$5),D19)),"") -> 2.142 | G19: =IFERROR(F19*CONFIG!$B$4,0) -> 0 | H19: =IFERROR(F19-G19,0) -> 0 | I19: =IFERROR(IF(F19>0,(F19-B19)/F19,""),"")
A20: wafle camisa | B20: 1.91 | C20: =CONFIG!$B$3 -> 0.4 | D20: =IFERROR(B20*(1+C20),0) -> 2.674 | E20: =IFERROR(IF(B20="","",IF(CONFIG!$B$6="SÍ",D20*(1+CONFIG!$B$5),D20)),"") -> 2.674 | G20: =IFERROR(F20*CONFIG!$B$4,0) -> 0 | H20: =IFERROR(F20-G20,0) -> 0 | I20: =IFERROR(IF(F20>0,(F20-B20)/F20,""),"")
C21: =CONFIG!$B$3 -> 0.4 | D21: =IFERROR(B21*(1+C21),0) -> 0 | E21: =IFERROR(IF(B21="","",IF(CONFIG!$B$6="SÍ",D21*(1+CONFIG!$B$5),D21)),"") | G21: =IFERROR(F21*CONFIG!$B$4,0) -> 0 | H21: =IFERROR(F21-G21,0) -> 0 | I21: =IFERROR(IF(F21>0,(F21-B21)/F21,""),"")
C22: =CONFIG!$B$3 -> 0.4 | D22: =IFERROR(B22*(1+C22),0) -> 0 | E22: =IFERROR(IF(B22="","",IF(CONFIG!$B$6="SÍ",D22*(1+CONFIG!$B$5),D22)),"") | G22: =IFERROR(F22*CONFIG!$B$4,0) -> 0 | H22: =IFERROR(F22-G22,0) -> 0 | I22: =IFERROR(IF(F22>0,(F22-B22)/F22,""),"")
C23: =CONFIG!$B$3 -> 0.4 | D23: =IFERROR(B23*(1+C23),0) -> 0 | E23: =IFERROR(IF(B23="","",IF(CONFIG!$B$6="SÍ",D23*(1+CONFIG!$B$5),D23)),"") | G23: =IFERROR(F23*CONFIG!$B$4,0) -> 0 | H23: =IFERROR(F23-G23,0) -> 0 | I23: =IFERROR(IF(F23>0,(F23-B23)/F23,""),"")
C24: =CONFIG!$B$3 -> 0.4 | D24: =IFERROR(B24*(1+C24),0) -> 0 | E24: =IFERROR(IF(B24="","",IF(CONFIG!$B$6="SÍ",D24*(1+CONFIG!$B$5),D24)),"") | G24: =IFERROR(F24*CONFIG!$B$4,0) -> 0 | H24: =IFERROR(F24-G24,0) -> 0 | I24: =IFERROR(IF(F24>0,(F24-B24)/F24,""),"")
C25: =CONFIG!$B$3 -> 0.4 | D25: =IFERROR(B25*(1+C25),0) -> 0 | E25: =IFERROR(IF(B25="","",IF(CONFIG!$B$6="SÍ",D25*(1+CONFIG!$B$5),D25)),"") | G25: =IFERROR(F25*CONFIG!$B$4,0) -> 0 | H25: =IFERROR(F25-G25,0) -> 0 | I25: =IFERROR(IF(F25>0,(F25-B25)/F25,""),"")
C26: =CONFIG!$B$3 -> 0.4 | D26: =IFERROR(B26*(1+C26),0) -> 0 | E26: =IFERROR(IF(B26="","",IF(CONFIG!$B$6="SÍ",D26*(1+CONFIG!$B$5),D26)),"") | G26: =IFERROR(F26*CONFIG!$B$4,0) -> 0 | H26: =IFERROR(F26-G26,0) -> 0 | I26: =IFERROR(IF(F26>0,(F26-B26)/F26,""),"")
C27: =CONFIG!$B$3 -> 0.4 | D27: =IFERROR(B27*(1+C27),0) -> 0 | E27: =IFERROR(IF(B27="","",IF(CONFIG!$B$6="SÍ",D27*(1+CONFIG!$B$5),D27)),"") | G27: =IFERROR(F27*CONFIG!$B$4,0) -> 0 | H27: =IFERROR(F27-G27,0) -> 0 | I27: =IFERROR(IF(F27>0,(F27-B27)/F27,""),"")
C28: =CONFIG!$B$3 -> 0.4 | D28: =IFERROR(B28*(1+C28),0) -> 0 | E28: =IFERROR(IF(B28="","",IF(CONFIG!$B$6="SÍ",D28*(1+CONFIG!$B$5),D28)),"") | G28: =IFERROR(F28*CONFIG!$B$4,0) -> 0 | H28: =IFERROR(F28-G28,0) -> 0 | I28: =IFERROR(IF(F28>0,(F28-B28)/F28,""),"")

Sheet CLIENTES
A1: CLIENTES — Catálogo
A3: CLIENTE | B3: CONTACTO | C3: TELÉFONO/EMAIL | D3: NOTAS
A4: OverShark | D4: Cliente principal
A5: Bravos | D5: Cliente principal

Sheet COLORES
A1: COLORES — Catálogo
A3: COLOR | B3: NOTAS
A4: Negro
A5: Perla
A6: Blanco
A7: Azul
A8: Beige
A9: Melange
A10: Botella
A11: Pacay
A12: V. Pacay
A13: Cemento
A14: Camote
A15: Denim
... A33: Vino Tinto

Sheet DASHBOARD
A1: DASHBOARD — Cobros del Taller (mes filtrable)
A2: Filtro Mes: | B2: =EOMONTH(TODAY(),-1)+1 -> 46143 | C2: (escribe el 1ro del mes, ej: 01/05/2026)
A4: COBRADO (mes) | C4: CUENTAS POR COBRAR | E4: ENTREGADO SIN COBRAR | G4: BRUTO TOTAL (mes)
A5: =SUMIFS(COBROS_DIARIOS!$M$4:$M$505,COBROS_DIARIOS!$A$4:$A$505,">="&$B$2,COBROS_DIARIOS!$A$4:$A$505,"<="&EOMONTH($B$2,0),COBROS_DIARIOS!$P$4:$P$505,"PAGADO") -> 0 | C5: =SUMIFS(COBROS_DIARIOS!$M$4:$M$505,COBROS_DIARIOS!$A$4:$A$505,">="&$B$2,COBROS_DIARIOS!$A$4:$A$505,"<="&EOMONTH($B$2,0),COBROS_DIARIOS!$P$4:$P$505,"PENDIENTE")+SUMIFS(COBROS_DIARIOS!$M$4:$M$505,COBROS_DIARIOS!$A$4:$A$505,">="&$B$2,COBROS_DIARIOS!$A$4:$A$505,"<="&EOMONTH($B$2,0),COBROS_DIARIOS!$P$4:$P$505,"PARCIAL") -> 80793.1 | E5: =SUMIFS(COBROS_DIARIOS!$M$4:$M$505,COBROS_DIARIOS!$A$4:$A$505,">="&$B$2,COBROS_DIARIOS!$A$4:$A$505,"<="&EOMONTH($B$2,0),COBROS_DIARIOS!$P$4:$P$505,"ENTREGADO SIN FACTURAR") -> 0 | G5: =SUMIFS(COBROS_DIARIOS!$M$4:$M$505,COBROS_DIARIOS!$A$4:$A$505,">="&$B$2,COBROS_DIARIOS!$A$4:$A$505,"<="&EOMONTH($B$2,0)) -> 82583.2
A6: DETRACCIÓN MES | C6: DISPONIBLE INMEDIATO | E6: # PRENDAS COBRADAS | G6: # OPERACIONES MES
A7: =SUMIFS(COBROS_DIARIOS!$N$4:$N$505,COBROS_DIARIOS!$A$4:$A$505,">="&$B$2,COBROS_DIARIOS!$A$4:$A$505,"<="&EOMONTH($B$2,0),COBROS_DIARIOS!$P$4:$P$505,"PAGADO") -> 0 | C7: =SUMIFS(COBROS_DIARIOS!$O$4:$O$505,COBROS_DIARIOS!$A$4:$A$505,">="&$B$2,COBROS_DIARIOS!$A$4:$A$505,"<="&EOMONTH($B$2,0),COBROS_DIARIOS!$P$4:$P$505,"PAGADO") -> 0 | E7: =SUMIFS(COBROS_DIARIOS!$K$4:$K$505,COBROS_DIARIOS!$A$4:$A$505,">="&$B$2,COBROS_DIARIOS!$A$4:$A$505,"<="&EOMONTH($B$2,0),COBROS_DIARIOS!$P$4:$P$505,"PAGADO") -> 0 | G7: =COUNTIFS(COBROS_DIARIOS!$A$4:$A$505,">="&$B$2,COBROS_DIARIOS!$A$4:$A$505,"<="&EOMONTH($B$2,0)) -> 253
A9: PRODUCCIÓN POR PRODUCTO (mes filtrado, todas las prendas)
A10: PRODUCTO | B10: S | C10: M | D10: L | E10: XL | F10: TOTAL PRENDAS | G10: BRUTO S/.
A11: =IFERROR(IF(PRODUCTOS!A4="","",PRODUCTOS!A4),"") -> jersey manga corta | B11: =IF(A11="","",SUMIFS(COBROS_DIARIOS!$G$4:$G$505,COBROS_DIARIOS!$E$4:$E$505,A11,COBROS_DIARIOS!$A$4:$A$505,">="&$B$2,COBROS_DIARIOS!$A$4:$A$505,"<="&EOMONTH($B$2,0))) -> 959 | C11: =IF(A11="","",SUMIFS(COBROS_DIARIOS!$H$4:$H$505,COBROS_DIARIOS!$E$4:$E$505,A11,COBROS_DIARIOS!$A$4:$A$505,">="&$B$2,COBROS_DIARIOS!$A$4:$A$505,"<="&EOMONTH($B$2,0))) -> 1969 | D11: =IF(A11="","",SUMIFS(COBROS_DIARIOS!$I$4:$I$505,COBROS_DIARIOS!$E$4:$E$505,A11,COBROS_DIARIOS!$A$4:$A$505,">="&$B$2,COBROS_DIARIOS!$A$4:$A$505,"<="&EOMONTH($B$2,0))) -> 1577 | E11: =IF(A11="","",SUMIFS(COBROS_DIARIOS!$J$4:$J$505,COBROS_DIARIOS!$E$4:$E$505,A11,COBROS_DIARIOS!$A$4:$A$505,">="&$B$2,COBROS_DIARIOS!$A$4:$A$505,"<="&EOMONTH($B$2,0))) -> 1016 | F11: =IF(A11="","",B11+C11+D11+E11) -> 5521 | G11: =IF(A11="","",SUMIFS(COBROS_DIARIOS!$M$4:$M$505,COBROS_DIARIOS!$E$4:$E$505,A11,COBROS_DIARIOS!$A$4:$A$505,">="&$B$2,COBROS_DIARIOS!$A$4:$A$505,"<="&EOMONTH($B$2,0))) -> 9385.7
A12: =IFERROR(IF(PRODUCTOS!A5="","",PRODUCTOS!A5),"") -> jersey manga larga | B12: =IF(A12="","",SUMIFS(COBROS_DIARIOS!$G$4:$G$505,COBROS_DIARIOS!$E$4:$E$505,A12,COBROS_DIARIOS!$A$4:$A$505,">="&$B$2,COBROS_DIARIOS!$A$4:$A$505,"<="&EOMONTH($B$2,0))) -> 513 | C12: =IF(A12="","",SUMIFS(COBROS_DIARIOS!$H$4:$H$505,COBROS_DIARIOS!$E$4:$E$505,A12,COBROS_DIARIOS!$A$4:$A$505,">="&$B$2,COBROS_DIARIOS!$A$4:$A$505,"<="&EOMONTH($B$2,0))) -> 830 | D12: =IF(A12="","",SUMIFS(COBROS_DIARIOS!$I$4:$I$505,COBROS_DIARIOS!$E$4:$E$505,A12,COBROS_DIARIOS!$A$4:$A$505,">="&$B$2,COBROS_DIARIOS!$A$4:$A$505,"<="&EOMONTH($B$2,0))) -> 990 | E12: =IF(A12="","",SUMIFS(COBROS_DIARIOS!$J$4:$J$505,COBROS_DIARIOS!$E$4:$E$505,A12,COBROS_DIARIOS!$A$4:$A$505,">="&$B$2,COBROS_DIARIOS!$A$4:$A$505,"<="&EOMONTH($B$2,0))) -> 514 | F12: =IF(A12="","",B12+C12+D12+E12) -> 2847 | G12: =IF(A12="","",SUMIFS(COBROS_DIARIOS!$M$4:$M$505,COBROS_DIARIOS!$E$4:$E$505,A12,COBROS_DIARIOS!$A$4:$A$505,">="&$B$2,COBROS_DIARIOS!$A$4:$A$505,"<="&EOMONTH($B$2,0))) -> 5694
A13: =IFERROR(IF(PRODUCTOS!A6="","",PRODUCTOS!A6),"") -> wafle clasico | B13: =IF(A13="","",SUMIFS(COBROS_DIARIOS!$G$4:$G$505,COBROS_DIARIOS!$E$4:$E$505,A13,COBROS_DIARIOS!$A$4:$A$505,">="&$B$2,COBROS_DIARIOS!$A$4:$A$505,"<="&EOMONTH($B$2,0))) -> 1520 | C13: =IF(A13="","",SUMIFS(COBROS_DIARIOS!$H$4:$H$505,COBROS_DIARIOS!$E$4:$E$505,A13,COBROS_DIARIOS!$A$4:$A$505,">="&$B$2,COBROS_DIARIOS!$A$4:$A$505,"<="&EOMONTH($B$2,0))) -> 2386 | D13: =IF(A13="","",SUMIFS(COBROS_DIARIOS!$I$4:$I$505,COBROS_DIARIOS!$E$4:$E$505,A13,COBROS_DIARIOS!$A$4:$A$505,">="&$B$2,COBROS_DIARIOS!$A$4:$A$505,"<="&EOMONTH($B$2,0))) -> 2565 | E13: =IF(A13="","",SUMIFS(COBROS_DIARIOS!$J$4:$J$505,COBROS_DIARIOS!$E$4:$E$505,A13,COBROS_DIARIOS!$A$4:$A$505,">="&$B$2,COBROS_DIARIOS!$A$4:$A$505,"<="&EOMONTH($B$2,0))) -> 1477 | F13: =IF(A13="","",B13+C13+D13+E13) -> 7948 | G13: =IF(A13="","",SUMIFS(COBROS_DIARIOS!$M$4:$M$505,COBROS_DIARIOS!$E$4:$E$505,A13,COBROS_DIARIOS!$A$4:$A$505,">="&$B$2,COBROS_DIARIOS!$A$4:$A$505,"<="&EOMONTH($B$2,0))) -> 13511.6
A14: =IFERROR(IF(PRODUCTOS!A7="","",PRODUCTOS!A7),"") -> wafle manga larga | B14: =IF(A14="","",SUMIFS(COBROS_DIARIOS!$G$4:$G$505,COBROS_DIARIOS!$E$4:$E$505,A14,COBROS_DIARIOS!$A$4:$A$505,">="&$B$2,COBROS_DIARIOS!$A$4:$A$505,"<="&EOMONTH($B$2,0))) -> 134 | C14: =IF(A14="","",SUMIFS(COBROS_DIARIOS!$H$4:$H$505,COBROS_DIARIOS!$E$4:$E$505,A14,COBROS_DIARIOS!$A$4:$A$505,">="&$B$2,COBROS_DIARIOS!$A$4:$A$505,"<="&EOMONTH($B$2,0))) -> 358 | D14: =IF(A14="","",SUMIFS(COBROS_DIARIOS!$I$4:$I$505,COBROS_DIARIOS!$E$4:$E$505,A14,COBROS_DIARIOS!$A$4:$A$505,">="&$B$2,COBROS_DIARIOS!$A$4:$A$505,"<="&EOMONTH($B$2,0))) -> 315 | E14: =IF(A14="","",SUMIFS(COBROS_DIARIOS!$J$4:$J$505,COBROS_DIARIOS!$E$4:$E$505,A14,COBROS_DIARIOS!$A$4:$A$505,">="&$B$2,COBROS_DIARIOS!$A$4:$A$505,"<="&EOMONTH($B$2,0))) -> 135 | F14: =IF(A14="","",B14+C14+D14+E14) -> 942 | G14: =IF(A14="","",SUMIFS(COBROS_DIARIOS!$M$4:$M$505,COBROS_DIARIOS!$E$4:$E$505,A14,COBROS_DIARIOS!$A$4:$A$505,">="&$B$2,COBROS_DIARIOS!$A$4:$A$505,"<="&EOMONTH($B$2,0))) -> 1884
A15: =IFERROR(IF(PRODUCTOS!A8="","",PRODUCTOS!A8),"") -> wafle camisero | B15: =IF(A15="","",SUMIFS(COBROS_DIARIOS!$G$4:$G$505,COBROS_DIARIOS!$E$4:$E$505,A15,COBROS_DIARIOS!$A$4:$A$505,">="&$B$2,COBROS_DIARIOS!$A$4:$A$505,"<="&EOMONTH($B$2,0))) -> 82 | C15: =IF(A15="","",SUMIFS(COBROS_DIARIOS!$H$4:$H$505,COBROS_DIARIOS!$E$4:$E$505,A15,COBROS_DIARIOS!$A$4:$A$505,">="&$B$2,COBROS_DIARIOS!$A$4:$A$505,"<="&EOMONTH($B$2,0))) -> 294 | D15: =IF(A15="","",SUMIFS(COBROS_DIARIOS!$I$4:$I$505,COBROS_DIARIOS!$E$4:$E$505,A15,COBROS_DIARIOS!$A$4:$A$505,">="&$B$2,COBROS_DIARIOS!$A$4:$A$505,"<="&EOMONTH($B$2,0))) -> 11 | E15: =IF(A15="","",SUMIFS(COBROS_DIARIOS!$J$4:$J$505,COBROS_DIARIOS!$E$4:$E$505,A15,COBROS_DIARIOS!$A$4:$A$505,">="&$B$2,COBROS_DIARIOS!$A$4:$A$505,"<="&EOMONTH($B$2,0))) -> 80 | F15: =IF(A15="","",B15+C15+D15+E15) -> 467 | G15: =IF(A15="","",SUMIFS(COBROS_DIARIOS!$M$4:$M$505,COBROS_DIARIOS!$E$4:$E$505,A15,COBROS_DIARIOS!$A$4:$A$505,">="&$B$2,COBROS_DIARIOS!$A$4:$A$505,"<="&EOMONTH($B$2,0))) -> 1868
A16: =IFERROR(IF(PRODUCTOS!A9="","",PRODUCTOS!A9),"") -> pique camisero | B16: =IF(A16="","",SUMIFS(COBROS_DIARIOS!$G$4:$G$505,COBROS_DIARIOS!$E$4:$E$505,A16,COBROS_DIARIOS!$A$4:$A$505,">="&$B$2,COBROS_DIARIOS!$A$4:$A$505,"<="&EOMONTH($B$2,0))) -> 772 | C16: =IF(A16="","",SUMIFS(COBROS_DIARIOS!$H$4:$H$505,COBROS_DIARIOS!$E$4:$E$505,A16,COBROS_DIARIOS!$A$4:$A$505,">="&$B$2,COBROS_DIARIOS!$A$4:$A$505,"<="&EOMONTH($B$2,0))) -> 1331 | D16: =IF(A16="","",SUMIFS(COBROS_DIARIOS!$I$4:$I$505,COBROS_DIARIOS!$E$4:$E$505,A16,COBROS_DIARIOS!$A$4:$A$505,">="&$B$2,COBROS_DIARIOS!$A$4:$A$505,"<="&EOMONTH($B$2,0))) -> 1313 | E16: =IF(A16="","",SUMIFS(COBROS_DIARIOS!$J$4:$J$505,COBROS_DIARIOS!$E$4:$E$505,A16,COBROS_DIARIOS!$A$4:$A$505,">="&$B$2,COBROS_DIARIOS!$A$4:$A$505,"<="&EOMONTH($B$2,0))) -> 893 | F16: =IF(A16="","",B16+C16+D16+E16) -> 4309 | G16: =IF(A16="","",SUMIFS(COBROS_DIARIOS!$M$4:$M$505,COBROS_DIARIOS!$E$4:$E$505,A16,COBROS_DIARIOS!$A$4:$A$505,">="&$B$2,COBROS_DIARIOS!$A$4:$A$505,"<="&EOMONTH($B$2,0))) -> 17236
A17: =IFERROR(IF(PRODUCTOS!A10="","",PRODUCTOS!A10),"") -> top cero rib | B17: =IF(A17="","",SUMIFS(COBROS_DIARIOS!$G$4:$G$505,COBROS_DIARIOS!$E$4:$E$505,A17,COBROS_DIARIOS!$A$4:$A$505,">="&$B$2,COBROS_DIARIOS!$A$4:$A$505,"<="&EOMONTH($B$2,0))) -> 0 | C17: =IF(A17="","",SUMIFS(COBROS_DIARIOS!$H$4:$H$505,COBROS_DIARIOS!$E$4:$E$505,A17,COBROS_DIARIOS!$A$4:$A$505,">="&$B$2,COBROS_DIARIOS!$A$4:$A$505,"<="&EOMONTH($B$2,0))) -> 0 | D17: =IF(A17="","",SUMIFS(COBROS_DIARIOS!$I$4:$I$505,COBROS_DIARIOS!$E$4:$E$505,A17,COBROS_DIARIOS!$A$4:$A$505,">="&$B$2,COBROS_DIARIOS!$A$4:$A$505,"<="&EOMONTH($B$2,0))) -> 0 | E17: =IF(A17="","",SUMIFS(COBROS_DIARIOS!$J$4:$J$505,COBROS_DIARIOS!$E$4:$E$505,A17,COBROS_DIARIOS!$A$4:$A$505,">="&$B$2,COBROS_DIARIOS!$A$4:$A$505,"<="&EOMONTH($B$2,0))) -> 0 | F17: =IF(A17="","",B17+C17+D17+E17) -> 0 | G17: =IF(A17="","",SUMIFS(COBROS_DIARIOS!$M$4:$M$505,COBROS_DIARIOS!$E$4:$E$505,A17,COBROS_DIARIOS!$A$4:$A$505,">="&$B$2,COBROS_DIARIOS!$A$4:$A$505,"<="&EOMONTH($B$2,0))) -> 411.4
A18: =IFERROR(IF(PRODUCTOS!A11="","",PRODUCTOS!A11),"") -> top mc rib | B18: =IF(A18="","",SUMIFS(COBROS_DIARIOS!$G$4:$G$505,COBROS_DIARIOS!$E$4:$E$505,A18,COBROS_DIARIOS!$A$4:$A$505,">="&$B$2,COBROS_DIARIOS!$A$4:$A$505,"<="&EOMONTH($B$2,0))) -> 0 | C18: =IF(A18="","",SUMIFS(COBROS_DIARIOS!$H$4:$H$505,COBROS_DIARIOS!$E$4:$E$505,A18,COBROS_DIARIOS!$A$4:$A$505,">="&$B$2,COBROS_DIARIOS!$A$4:$A$505,"<="&EOMONTH($B$2,0))) -> 0 | D18: =IF(A18="","",SUMIFS(COBROS_DIARIOS!$I$4:$I$505,COBROS_DIARIOS!$E$4:$E$505,A18,COBROS_DIARIOS!$A$4:$A$505,">="&$B$2,COBROS_DIARIOS!$A$4:$A$505,"<="&EOMONTH($B$2,0))) -> 0 | E18: =IF(A18="","",SUMIFS(COBROS_DIARIOS!$J$4:$J$505,COBROS_DIARIOS!$E$4:$E$505,A18,COBROS_DIARIOS!$A$4:$A$505,">="&$B$2,COBROS_DIARIOS!$A$4:$A$505,"<="&EOMONTH($B$2,0))) -> 0 | F18: =IF(A18="","",B18+C18+D18+E18) -> 0 | G18: =IF(A18="","",SUMIFS(COBROS_DIARIOS!$M$4:$M$505,COBROS_DIARIOS!$E$4:$E$505,A18,COBROS_DIARIOS!$A$4:$A$505,">="&$B$2,COBROS_DIARIOS!$A$4:$A$505,"<="&EOMONTH($B$2,0))) -> 1232.5
A19: =IFERROR(IF(PRODUCTOS!A12="","",PRODUCTOS!A12),"") -> top ml rib | B19: =IF(A19="","",SUMIFS(COBROS_DIARIOS!$G$4:$G$505,COBROS_DIARIOS!$E$4:$E$505,A19,COBROS_DIARIOS!$A$4:$A$505,">="&$B$2,COBROS_DIARIOS!$A$4:$A$505,"<="&EOMONTH($B$2,0))) -> 0 | C19: =IF(A19="","",SUMIFS(COBROS_DIARIOS!$H$4:$H$505,COBROS_DIARIOS!$E$4:$E$505,A19,COBROS_DIARIOS!$A$4:$A$505,">="&$B$2,COBROS_DIARIOS!$A$4:$A$505,"<="&EOMONTH($B$2,0))) -> 0 | D19: =IF(A19="","",SUMIFS(COBROS_DIARIOS!$I$4:$I$505,COBROS_DIARIOS!$E$4:$E$505,A19,COBROS_DIARIOS!$A$4:$A$505,">="&$B$2,COBROS_DIARIOS!$A$4:$A$505,"<="&EOMONTH($B$2,0))) -> 0 | E19: =IF(A19="","",SUMIFS(COBROS_DIARIOS!$J$4:$J$505,COBROS_DIARIOS!$E$4:$E$505,A19,COBROS_DIARIOS!$A$4:$A$505,">="&$B$2,COBROS_DIARIOS!$A$4:$A$505,"<="&EOMONTH($B$2,0))) -> 0 | F19: =IF(A19="","",B19+C19+D19+E19) -> 0 | G19: =IF(A19="","",SUMIFS(COBROS_DIARIOS!$M$4:$M$505,COBROS_DIARIOS!$E$4:$E$505,A19,COBROS_DIARIOS!$A$4:$A$505,">="&$B$2,COBROS_DIARIOS!$A$4:$A$505,"<="&EOMONTH($B$2,0))) -> 1084.6
A20: =IFERROR(IF(PRODUCTOS!A13="","",PRODUCTOS!A13),"") -> baby ty mc | B20: =IF(A20="","",SUMIFS(COBROS_DIARIOS!$G$4:$G$505,COBROS_DIARIOS!$E$4:$E$505,A20,COBROS_DIARIOS!$A$4:$A$505,">="&$B$2,COBROS_DIARIOS!$A$4:$A$505,"<="&EOMONTH($B$2,0))) -> 634 | C20: =IF(A20="","",SUMIFS(COBROS_DIARIOS!$H$4:$H$505,COBROS_DIARIOS!$E$4:$E$505,A20,COBROS_DIARIOS!$A$4:$A$505,">="&$B$2,COBROS_DIARIOS!$A$4:$A$505,"<="&EOMONTH($B$2,0))) -> 671 | D20: =IF(A20="","",SUMIFS(COBROS_DIARIOS!$I$4:$I$505,COBROS_DIARIOS!$E$4:$E$505,A20,COBROS_DIARIOS!$A$4:$A$505,">="&$B$2,COBROS_DIARIOS!$A$4:$A$505,"<="&EOMONTH($B$2,0))) -> 667 | E20: =IF(A20="","",SUMIFS(COBROS_DIARIOS!$J$4:$J$505,COBROS_DIARIOS!$E$4:$E$505,A20,COBROS_DIARIOS!$A$4:$A$505,">="&$B$2,COBROS_DIARIOS!$A$4:$A$505,"<="&EOMONTH($B$2,0))) -> 0 | F20: =IF(A20="","",B20+C20+D20+E20) -> 1972 | G20: =IF(A20="","",SUMIFS(COBROS_DIARIOS!$M$4:$M$505,COBROS_DIARIOS!$E$4:$E$505,A20,COBROS_DIARIOS!$A$4:$A$505,">="&$B$2,COBROS_DIARIOS!$A$4:$A$505,"<="&EOMONTH($B$2,0))) -> 3352.4
A21: =IFERROR(IF(PRODUCTOS!A14="","",PRODUCTOS!A14),"") -> baby ty ml | B21: =IF(A21="","",SUMIFS(COBROS_DIARIOS!$G$4:$G$505,COBROS_DIARIOS!$E$4:$E$505,A21,COBROS_DIARIOS!$A$4:$A$505,">="&$B$2,COBROS_DIARIOS!$A$4:$A$505,"<="&EOMONTH($B$2,0))) -> 358 | C21: =IF(A21="","",SUMIFS(COBROS_DIARIOS!$H$4:$H$505,COBROS_DIARIOS!$E$4:$E$505,A21,COBROS_DIARIOS!$A$4:$A$505,">="&$B$2,COBROS_DIARIOS!$A$4:$A$505,"<="&EOMONTH($B$2,0))) -> 400 | D21: =IF(A21="","",SUMIFS(COBROS_DIARIOS!$I$4:$I$505,COBROS_DIARIOS!$E$4:$E$505,A21,COBROS_DIARIOS!$A$4:$A$505,">="&$B$2,COBROS_DIARIOS!$A$4:$A$505,"<="&EOMONTH($B$2,0))) -> 389 | E21: =IF(A21="","",SUMIFS(COBROS_DIARIOS!$J$4:$J$505,COBROS_DIARIOS!$E$4:$E$505,A21,COBROS_DIARIOS!$A$4:$A$505,">="&$B$2,COBROS_DIARIOS!$A$4:$A$505,"<="&EOMONTH($B$2,0))) -> 0 | F21: =IF(A21="","",B21+C21+D21+E21) -> 1147 | G21: =IF(A21="","",SUMIFS(COBROS_DIARIOS!$M$4:$M$505,COBROS_DIARIOS!$E$4:$E$505,A21,COBROS_DIARIOS!$A$4:$A$505,">="&$B$2,COBROS_DIARIOS!$A$4:$A$505,"<="&EOMONTH($B$2,0))) -> 1949.9
A22: =IFERROR(IF(PRODUCTOS!A15="","",PRODUCTOS!A15),"") -> Baby Tee con S | B22: =IF(A22="","",SUMIFS(COBROS_DIARIOS!$G$4:$G$505,COBROS_DIARIOS!$E$4:$E$505,A22,COBROS_DIARIOS!$A$4:$A$505,">="&$B$2,COBROS_DIARIOS!$A$4:$A$505,"<="&EOMONTH($B$2,0))) -> 313 | C22: =IF(A22="","",SUMIFS(COBROS_DIARIOS!$H$4:$H$505,COBROS_DIARIOS!$E$4:$E$505,A22,COBROS_DIARIOS!$A$4:$A$505,">="&$B$2,COBROS_DIARIOS!$A$4:$A$505,"<="&EOMONTH($B$2,0))) -> 310 | D22: =IF(A22="","",SUMIFS(COBROS_DIARIOS!$I$4:$I$505,COBROS_DIARIOS!$E$4:$E$505,A22,COBROS_DIARIOS!$A$4:$A$505,">="&$B$2,COBROS_DIARIOS!$A$4:$A$505,"<="&EOMONTH($B$2,0))) -> 312 | E22: =IF(A22="","",SUMIFS(COBROS_DIARIOS!$J$4:$J$505,COBROS_DIARIOS!$E$4:$E$505,A22,COBROS_DIARIOS!$A$4:$A$505,">="&$B$2,COBROS_DIARIOS!$A$4:$A$505,"<="&EOMONTH($B$2,0))) -> 0 | F22: =IF(A22="","",B22+C22+D22+E22) -> 935 | G22: =IF(A22="","",SUMIFS(COBROS_DIARIOS!$M$4:$M$505,COBROS_DIARIOS!$E$4:$E$505,A22,COBROS_DIARIOS!$A$4:$A$505,">="&$B$2,COBROS_DIARIOS!$A$4:$A$505,"<="&EOMONTH($B$2,0))) -> 1589.5
... A35: =IFERROR(IF(PRODUCTOS!A28="","",PRODUCTOS!A28),"") | B35: =IF(A35="","",SUMIFS(COBROS_DIARIOS!$G$4:$G$505,COBROS_DIARIOS!$E$4:$E$505,A35,COBROS_DIARIOS!$A$4:$A$505,">="&$B$2,COBROS_DIARIOS!$A$4:$A$505,"<="&EOMONTH($B$2,0))) | C35: =IF(A35="","",SUMIFS(COBROS_DIARIOS!$H$4:$H$505,COBROS_DIARIOS!$E$4:$E$505,A35,COBROS_DIARIOS!$A$4:$A$505,">="&$B$2,COBROS_DIARIOS!$A$4:$A$505,"<="&EOMONTH($B$2,0))) | D35: =IF(A35="","",SUMIFS(COBROS_DIARIOS!$I$4:$I$505,COBROS_DIARIOS!$E$4:$E$505,A35,COBROS_DIARIOS!$A$4:$A$505,">="&$B$2,COBROS_DIARIOS!$A$4:$A$505,"<="&EOMONTH($B$2,0))) | E35: =IF(A35="","",SUMIFS(COBROS_DIARIOS!$J$4:$J$505,COBROS_DIARIOS!$E$4:$E$505,A35,COBROS_DIARIOS!$A$4:$A$505,">="&$B$2,COBROS_DIARIOS!$A$4:$A$505,"<="&EOMONTH($B$2,0))) | F35: =IF(A35="","",B35+C35+D35+E35) | G35: =IF(A35="","",SUMIFS(COBROS_DIARIOS!$M$4:$M$505,COBROS_DIARIOS!$E$4:$E$505,A35,COBROS_DIARIOS!$A$4:$A$505,">="&$B$2,COBROS_DIARIOS!$A$4:$A$505,"<="&EOMONTH($B$2,0)))
A36: TOTAL ⇒ | B36: =SUM(B11:B35) -> 7197 | C36: =SUM(C11:C35) -> 10314 | D36: =SUM(D11:D35) -> 9806 | E36: =SUM(E11:E35) -> 4240 | F36: =SUM(F11:F35) -> 31557 | G36: =SUM(G11:G35) -> 82583.2
A38: CANTIDAD POR COLOR — Total entregado (todos los productos)
A39: COLOR | B39: TOTAL PRENDAS | C39: BRUTO S/. | D39: % TOTAL
A40: {=IFERROR(IF(LARGE($D$200:$D$249,1)<=0,"",INDEX($A$200:$A$249,MATCH(LARGE($D$200:$D$249,1),$D$200:$D$249,0))),"")} -> Negro | B40: {=IFERROR(IF(LARGE($D$200:$D$249,1)<=0,"",INDEX($B$200:$B$249,MATCH(LARGE($D$200:$D$249,1),$D$200:$D$249,0))),"")} -> 6201 | C40: {=IFERROR(IF(LARGE($D$200:$D$249,1)<=0,"",INDEX($C$200:$C$249,MATCH(LARGE($D$200:$D$249,1),$D$200:$D$249,0))),"")} -> 16120.7 | D40: =IFERROR(IF(B40="","",B40/SUMIFS(COBROS_DIARIOS!$K$4:$K$505,COBROS_DIARIOS!$A$4:$A$505,">="&$B$2,COBROS_DIARIOS!$A$4:$A$505,"<="&EOMONTH($B$2,0))),"") -> 0.18194355
A41: {=IFERROR(IF(LARGE($D$200:$D$249,2)<=0,"",INDEX($A$200:$A$249,MATCH(LARGE($D$200:$D$249,2),$D$200:$D$249,0))),"")} -> Vino | B41: {=IFERROR(IF(LARGE($D$200:$D$249,2)<=0,"",INDEX($B$200:$B$249,MATCH(LARGE($D$200:$D$249,2),$D$200:$D$249,0))),"")} -> 4566 | C41: {=IFERROR(IF(LARGE($D$200:$D$249,2)<=0,"",INDEX($C$200:$C$249,MATCH(LARGE($D$200:$D$249,2),$D$200:$D$249,0))),"")} -> 9329.4 | D41: =IFERROR(IF(B41="","",B41/SUMIFS(COBROS_DIARIOS!$K$4:$K$505,COBROS_DIARIOS!$A$4:$A$505,">="&$B$2,COBROS_DIARIOS!$A$4:$A$505,"<="&EOMONTH($B$2,0))),"") -> 0.13397101
A42: {=IFERROR(IF(LARGE($D$200:$D$249,3)<=0,"",INDEX($A$200:$A$249,MATCH(LARGE($D$200:$D$249,3),$D$200:$D$249,0))),"")} -> Azul Marino | B42: {=IFERROR(IF(LARGE($D$200:$D$249,3)<=0,"",INDEX($B$200:$B$249,MATCH(LARGE($D$200:$D$249,3),$D$200:$D$249,0))),"")} -> 4340 | C42: {=IFERROR(IF(LARGE($D$200:$D$249,3)<=0,"",INDEX($C$200:$C$249,MATCH(LARGE($D$200:$D$249,3),$D$200:$D$249,0))),"")} -> 11485.3 | D42: =IFERROR(IF(B42="","",B42/SUMIFS(COBROS_DIARIOS!$K$4:$K$505,COBROS_DIARIOS!$A$4:$A$505,">="&$B$2,COBROS_DIARIOS!$A$4:$A$505,"<="&EOMONTH($B$2,0))),"") -> 0.12733994
A43: {=IFERROR(IF(LARGE($D$200:$D$249,4)<=0,"",INDEX($A$200:$A$249,MATCH(LARGE($D$200:$D$249,4),$D$200:$D$249,0))),"")} -> Perla | B43: {=IFERROR(IF(LARGE($D$200:$D$249,4)<=0,"",INDEX($B$200:$B$249,MATCH(LARGE($D$200:$D$249,4),$D$200:$D$249,0))),"")} -> 3124 | C43: {=IFERROR(IF(LARGE($D$200:$D$249,4)<=0,"",INDEX($C$200:$C$249,MATCH(LARGE($D$200:$D$249,4),$D$200:$D$249,0))),"")} -> 6951.7 | D43: =IFERROR(IF(B43="","",B43/SUMIFS(COBROS_DIARIOS!$K$4:$K$505,COBROS_DIARIOS!$A$4:$A$505,">="&$B$2,COBROS_DIARIOS!$A$4:$A$505,"<="&EOMONTH($B$2,0))),"") -> 0.091661287
A44: {=IFERROR(IF(LARGE($D$200:$D$249,5)<=0,"",INDEX($A$200:$A$249,MATCH(LARGE($D$200:$D$249,5),$D$200:$D$249,0))),"")} -> Colegial | B44: {=IFERROR(IF(LARGE($D$200:$D$249,5)<=0,"",INDEX($B$200:$B$249,MATCH(LARGE($D$200:$D$249,5),$D$200:$D$249,0))),"")} -> 2998 | C44: {=IFERROR(IF(LARGE($D$200:$D$249,5)<=0,"",INDEX($C$200:$C$249,MATCH(LARGE($D$200:$D$249,5),$D$200:$D$249,0))),"")} -> 7367 | D44: =IFERROR(IF(B44="","",B44/SUMIFS(COBROS_DIARIOS!$K$4:$K$505,COBROS_DIARIOS!$A$4:$A$505,">="&$B$2,COBROS_DIARIOS!$A$4:$A$505,"<="&EOMONTH($B$2,0))),"") -> 0.087964321
A45: {=IFERROR(IF(LARGE($D$200:$D$249,6)<=0,"",INDEX($A$200:$A$249,MATCH(LARGE($D$200:$D$249,6),$D$200:$D$249,0))),"")} -> Denim | B45: {=IFERROR(IF(LARGE($D$200:$D$249,6)<=0,"",INDEX($B$200:$B$249,MATCH(LARGE($D$200:$D$249,6),$D$200:$D$249,0))),"")} -> 2363 | C45: {=IFERROR(IF(LARGE($D$200:$D$249,6)<=0,"",INDEX($C$200:$C$249,MATCH(LARGE($D$200:$D$249,6),$D$200:$D$249,0))),"")} -> 4836.2 | D45: =IFERROR(IF(B45="","",B45/SUMIFS(COBROS_DIARIOS!$K$4:$K$505,COBROS_DIARIOS!$A$4:$A$505,">="&$B$2,COBROS_DIARIOS!$A$4:$A$505,"<="&EOMONTH($B$2,0))),"") -> 0.069332786
A46: {=IFERROR(IF(LARGE($D$200:$D$249,7)<=0,"",INDEX($A$200:$A$249,MATCH(LARGE($D$200:$D$249,7),$D$200:$D$249,0))),"")} -> Botella | B46: {=IFERROR(IF(LARGE($D$200:$D$249,7)<=0,"",INDEX($B$200:$B$249,MATCH(LARGE($D$200:$D$249,7),$D$200:$D$249,0))),"")} -> 2100 | C46: {=IFERROR(IF(LARGE($D$200:$D$249,7)<=0,"",INDEX($C$200:$C$249,MATCH(LARGE($D$200:$D$249,7),$D$200:$D$249,0))),"")} -> 6356.1 | D46: =IFERROR(IF(B46="","",B46/SUMIFS(COBROS_DIARIOS!$K$4:$K$505,COBROS_DIARIOS!$A$4:$A$505,">="&$B$2,COBROS_DIARIOS!$A$4:$A$505,"<="&EOMONTH($B$2,0))),"") -> 0.061616102
A47: {=IFERROR(IF(LARGE($D$200:$D$249,8)<=0,"",INDEX($A$200:$A$249,MATCH(LARGE($D$200:$D$249,8),$D$200:$D$249,0))),"")} -> Beige | B47: {=IFERROR(IF(LARGE($D$200:$D$249,8)<=0,"",INDEX($B$200:$B$249,MATCH(LARGE($D$200:$D$249,8),$D$200:$D$249,0))),"")} -> 1871 | C47: {=IFERROR(IF(LARGE($D$200:$D$249,8)<=0,"",INDEX($C$200:$C$249,MATCH(LARGE($D$200:$D$249,8),$D$200:$D$249,0))),"")} -> 4322.9 | D47: =IFERROR(IF(B47="","",B47/SUMIFS(COBROS_DIARIOS!$K$4:$K$505,COBROS_DIARIOS!$A$4:$A$505,">="&$B$2,COBROS_DIARIOS!$A$4:$A$505,"<="&EOMONTH($B$2,0))),"") -> 0.054897013
A48: {=IFERROR(IF(LARGE($D$200:$D$249,9)<=0,"",INDEX($A$200:$A$249,MATCH(LARGE($D$200:$D$249,9),$D$200:$D$249,0))),"")} -> Topo | B48: {=IFERROR(IF(LARGE($D$200:$D$249,9)<=0,"",INDEX($B$200:$B$249,MATCH(LARGE($D$200:$D$249,9),$D$200:$D$249,0))),"")} -> 1543 | C48: {=IFERROR(IF(LARGE($D$200:$D$249,9)<=0,"",INDEX($C$200:$C$249,MATCH(LARGE($D$200:$D$249,9),$D$200:$D$249,0))),"")} -> 3547.7 | D48: =IFERROR(IF(B48="","",B48/SUMIFS(COBROS_DIARIOS!$K$4:$K$505,COBROS_DIARIOS!$A$4:$A$505,">="&$B$2,COBROS_DIARIOS!$A$4:$A$505,"<="&EOMONTH($B$2,0))),"") -> 0.045273165
A49: {=IFERROR(IF(LARGE($D$200:$D$249,10)<=0,"",INDEX($A$200:$A$249,MATCH(LARGE($D$200:$D$249,10),$D$200:$D$249,0))),"")} -> P. Rosa | B49: {=IFERROR(IF(LARGE($D$200:$D$249,10)<=0,"",INDEX($B$200:$B$249,MATCH(LARGE($D$200:$D$249,10),$D$200:$D$249,0))),"")} -> 1492 | C49: {=IFERROR(IF(LARGE($D$200:$D$249,10)<=0,"",INDEX($C$200:$C$249,MATCH(LARGE($D$200:$D$249,10),$D$200:$D$249,0))),"")} -> 3677.1 | D49: =IFERROR(IF(B49="","",B49/SUMIFS(COBROS_DIARIOS!$K$4:$K$505,COBROS_DIARIOS!$A$4:$A$505,">="&$B$2,COBROS_DIARIOS!$A$4:$A$505,"<="&EOMONTH($B$2,0))),"") -> 0.043776774
A50: {=IFERROR(IF(LARGE($D$200:$D$249,11)<=0,"",INDEX($A$200:$A$249,MATCH(LARGE($D$200:$D$249,11),$D$200:$D$249,0))),"")} -> V. Pacay | B50: {=IFERROR(IF(LARGE($D$200:$D$249,11)<=0,"",INDEX($B$200:$B$249,MATCH(LARGE($D$200:$D$249,11),$D$200:$D$249,0))),"")} -> 1337 | C50: {=IFERROR(IF(LARGE($D$200:$D$249,11)<=0,"",INDEX($C$200:$C$249,MATCH(LARGE($D$200:$D$249,11),$D$200:$D$249,0))),"")} -> 3456.3 | D50: =IFERROR(IF(B50="","",B50/SUMIFS(COBROS_DIARIOS!$K$4:$K$505,COBROS_DIARIOS!$A$4:$A$505,">="&$B$2,COBROS_DIARIOS!$A$4:$A$505,"<="&EOMONTH($B$2,0))),"") -> 0.039228918
A51: {=IFERROR(IF(LARGE($D$200:$D$249,12)<=0,"",INDEX($A$200:$A$249,MATCH(LARGE($D$200:$D$249,12),$D$200:$D$249,0))),"")} -> Cemento | B51: {=IFERROR(IF(LARGE($D$200:$D$249,12)<=0,"",INDEX($B$200:$B$249,MATCH(LARGE($D$200:$D$249,12),$D$200:$D$249,0))),"")} -> 1257 | C51: {=IFERROR(IF(LARGE($D$200:$D$249,12)<=0,"",INDEX($C$200:$C$249,MATCH(LARGE($D$200:$D$249,12),$D$200:$D$249,0))),"")} -> 2260.2 | D51: =IFERROR(IF(B51="","",B51/SUMIFS(COBROS_DIARIOS!$K$4:$K$505,COBROS_DIARIOS!$A$4:$A$505,">="&$B$2,COBROS_DIARIOS!$A$4:$A$505,"<="&EOMONTH($B$2,0))),"") -> 0.036881638
A52: {=IFERROR(IF(LARGE($D$200:$D$249,13)<=0,"",INDEX($A$200:$A$249,MATCH(LARGE($D$200:$D$249,13),$D$200:$D$249,0))),"")} -> Melange | B52: {=IFERROR(IF(LARGE($D$200:$D$249,13)<=0,"",INDEX($B$200:$B$249,MATCH(LARGE($D$200:$D$249,13),$D$200:$D$249,0))),"")} -> 692 | C52: {=IFERROR(IF(LARGE($D$200:$D$249,13)<=0,"",INDEX($C$200:$C$249,MATCH(LARGE($D$200:$D$249,13),$D$200:$D$249,0))),"")} -> 2536 | D52: =IFERROR(IF(B52="","",B52/SUMIFS(COBROS_DIARIOS!$K$4:$K$505,COBROS_DIARIOS!$A$4:$A$505,">="&$B$2,COBROS_DIARIOS!$A$4:$A$505,"<="&EOMONTH($B$2,0))),"") -> 0.020303973
A53: {=IFERROR(IF(LARGE($D$200:$D$249,14)<=0,"",INDEX($A$200:$A$249,MATCH(LARGE($D$200:$D$249,14),$D$200:$D$249,0))),"")} -> Palo Rosa | B53: {=IFERROR(IF(LARGE($D$200:$D$249,14)<=0,"",INDEX($B$200:$B$249,MATCH(LARGE($D$200:$D$249,14),$D$200:$D$249,0))),"")} -> 198 | C53: {=IFERROR(IF(LARGE($D$200:$D$249,14)<=0,"",INDEX($C$200:$C$249,MATCH(LARGE($D$200:$D$249,14),$D$200:$D$249,0))),"")} -> 336.6 | D53: =IFERROR(IF(B53="","",B53/SUMIFS(COBROS_DIARIOS!$K$4:$K$505,COBROS_DIARIOS!$A$4:$A$505,">="&$B$2,COBROS_DIARIOS!$A$4:$A$505,"<="&EOMONTH($B$2,0))),"") -> 0.0058095182
A54: {=IFERROR(IF(LARGE($D$200:$D$249,15)<=0,"",INDEX($A$200:$A$249,MATCH(LARGE($D$200:$D$249,15),$D$200:$D$249,0))),"")} | B54: {=IFERROR(IF(LARGE($D$200:$D$249,15)<=0,"",INDEX($B$200:$B$249,MATCH(LARGE($D$200:$D$249,15),$D$200:$D$249,0))),"")} | C54: {=IFERROR(IF(LARGE($D$200:$D$249,15)<=0,"",INDEX($C$200:$C$249,MATCH(LARGE($D$200:$D$249,15),$D$200:$D$249,0))),"")} | D54: =IFERROR(IF(B54="","",B54/SUMIFS(COBROS_DIARIOS!$K$4:$K$505,COBROS_DIARIOS!$A$4:$A$505,">="&$B$2,COBROS_DIARIOS!$A$4:$A$505,"<="&EOMONTH($B$2,0))),"")
A55: {=IFERROR(IF(LARGE($D$200:$D$249,16)<=0,"",INDEX($A$200:$A$249,MATCH(LARGE($D$200:$D$249,16),$D$200:$D$249,0))),"")} | B55: {=IFERROR(IF(LARGE($D$200:$D$249,16)<=0,"",INDEX($B$200:$B$249,MATCH(LARGE($D$200:$D$249,16),$D$200:$D$249,0))),"")} | C55: {=IFERROR(IF(LARGE($D$200:$D$249,16)<=0,"",INDEX($C$200:$C$249,MATCH(LARGE($D$200:$D$249,16),$D$200:$D$249,0))),"")} | D55: =IFERROR(IF(B55="","",B55/SUMIFS(COBROS_DIARIOS!$K$4:$K$505,COBROS_DIARIOS!$A$4:$A$505,">="&$B$2,COBROS_DIARIOS!$A$4:$A$505,"<="&EOMONTH($B$2,0))),"")
A56: {=IFERROR(IF(LARGE($D$200:$D$249,17)<=0,"",INDEX($A$200:$A$249,MATCH(LARGE($D$200:$D$249,17),$D$200:$D$249,0))),"")} | B56: {=IFERROR(IF(LARGE($D$200:$D$249,17)<=0,"",INDEX($B$200:$B$249,MATCH(LARGE($D$200:$D$249,17),$D$200:$D$249,0))),"")} | C56: {=IFERROR(IF(LARGE($D$200:$D$249,17)<=0,"",INDEX($C$200:$C$249,MATCH(LARGE($D$200:$D$249,17),$D$200:$D$249,0))),"")} | D56: =IFERROR(IF(B56="","",B56/SUMIFS(COBROS_DIARIOS!$K$4:$K$505,COBROS_DIARIOS!$A$4:$A$505,">="&$B$2,COBROS_DIARIOS!$A$4:$A$505,"<="&EOMONTH($B$2,0))),"")
A57: {=IFERROR(IF(LARGE($D$200:$D$249,18)<=0,"",INDEX($A$200:$A$249,MATCH(LARGE($D$200:$D$249,18),$D$200:$D$249,0))),"")} | B57: {=IFERROR(IF(LARGE($D$200:$D$249,18)<=0,"",INDEX($B$200:$B$249,MATCH(LARGE($D$200:$D$249,18),$D$200:$D$249,0))),"")} | C57: {=IFERROR(IF(LARGE($D$200:$D$249,18)<=0,"",INDEX($C$200:$C$249,MATCH(LARGE($D$200:$D$249,18),$D$200:$D$249,0))),"")} | D57: =IFERROR(IF(B57="","",B57/SUMIFS(COBROS_DIARIOS!$K$4:$K$505,COBROS_DIARIOS!$A$4:$A$505,">="&$B$2,COBROS_DIARIOS!$A$4:$A$505,"<="&EOMONTH($B$2,0))),"")
A58: {=IFERROR(IF(LARGE($D$200:$D$249,19)<=0,"",INDEX($A$200:$A$249,MATCH(LARGE($D$200:$D$249,19),$D$200:$D$249,0))),"")} | B58: {=IFERROR(IF(LARGE($D$200:$D$249,19)<=0,"",INDEX($B$200:$B$249,MATCH(LARGE($D$200:$D$249,19),$D$200:$D$249,0))),"")} | C58: {=IFERROR(IF(LARGE($D$200:$D$249,19)<=0,"",INDEX($C$200:$C$249,MATCH(LARGE($D$200:$D$249,19),$D$200:$D$249,0))),"")} | D58: =IFERROR(IF(B58="","",B58/SUMIFS(COBROS_DIARIOS!$K$4:$K$505,COBROS_DIARIOS!$A$4:$A$505,">="&$B$2,COBROS_DIARIOS!$A$4:$A$505,"<="&EOMONTH($B$2,0))),"")
A59: {=IFERROR(IF(LARGE($D$200:$D$249,20)<=0,"",INDEX($A$200:$A$249,MATCH(LARGE($D$200:$D$249,20),$D$200:$D$249,0))),"")} | B59: {=IFERROR(IF(LARGE($D$200:$D$249,20)<=0,"",INDEX($B$200:$B$249,MATCH(LARGE($D$200:$D$249,20),$D$200:$D$249,0))),"")} | C59: {=IFERROR(IF(LARGE($D$200:$D$249,20)<=0,"",INDEX($C$200:$C$249,MATCH(LARGE($D$200:$D$249,20),$D$200:$D$249,0))),"")} | D59: =IFERROR(IF(B59="","",B59/SUMIFS(COBROS_DIARIOS!$K$4:$K$505,COBROS_DIARIOS!$A$4:$A$505,">="&$B$2,COBROS_DIARIOS!$A$4:$A$505,"<="&EOMONTH($B$2,0))),"")
A60: {=IFERROR(IF(LARGE($D$200:$D$249,21)<=0,"",INDEX($A$200:$A$249,MATCH(LARGE($D$200:$D$249,21),$D$200:$D$249,0))),"")} | B60: {=IFERROR(IF(LARGE($D$200:$D$249,21)<=0,"",INDEX($B$200:$B$249,MATCH(LARGE($D$200:$D$249,21),$D$200:$D$249,0))),"")} | C60: {=IFERROR(IF(LARGE($D$200:$D$249,21)<=0,"",INDEX($C$200:$C$249,MATCH(LARGE($D$200:$D$249,21),$D$200:$D$249,0))),"")} | D60: =IFERROR(IF(B60="","",B60/SUMIFS(COBROS_DIARIOS!$K$4:$K$505,COBROS_DIARIOS!$A$4:$A$505,">="&$B$2,COBROS_DIARIOS!$A$4:$A$505,"<="&EOMONTH($B$2,0))),"")
A61: {=IFERROR(IF(LARGE($D$200:$D$249,22)<=0,"",INDEX($A$200:$A$249,MATCH(LARGE($D$200:$D$249,22),$D$200:$D$249,0))),"")} | B61: {=IFERROR(IF(LARGE($D$200:$D$249,22)<=0,"",INDEX($B$200:$B$249,MATCH(LARGE($D$200:$D$249,22),$D$200:$D$249,0))),"")} | C61: {=IFERROR(IF(LARGE($D$200:$D$249,22)<=0,"",INDEX($C$200:$C$249,MATCH(LARGE($D$200:$D$249,22),$D$200:$D$249,0))),"")} | D61: =IFERROR(IF(B61="","",B61/SUMIFS(COBROS_DIARIOS!$K$4:$K$505,COBROS_DIARIOS!$A$4:$A$505,">="&$B$2,COBROS_DIARIOS!$A$4:$A$505,"<="&EOMONTH($B$2,0))),"")
A62: {=IFERROR(IF(LARGE($D$200:$D$249,23)<=0,"",INDEX($A$200:$A$249,MATCH(LARGE($D$200:$D$249,23),$D$200:$D$249,0))),"")} | B62: {=IFERROR(IF(LARGE($D$200:$D$249,23)<=0,"",INDEX($B$200:$B$249,MATCH(LARGE($D$200:$D$249,23),$D$200:$D$249,0))),"")} | C62: {=IFERROR(IF(LARGE($D$200:$D$249,23)<=0,"",INDEX($C$200:$C$249,MATCH(LARGE($D$200:$D$249,23),$D$200:$D$249,0))),"")} | D62: =IFERROR(IF(B62="","",B62/SUMIFS(COBROS_DIARIOS!$K$4:$K$505,COBROS_DIARIOS!$A$4:$A$505,">="&$B$2,COBROS_DIARIOS!$A$4:$A$505,"<="&EOMONTH($B$2,0))),"")
A63: {=IFERROR(IF(LARGE($D$200:$D$249,24)<=0,"",INDEX($A$200:$A$249,MATCH(LARGE($D$200:$D$249,24),$D$200:$D$249,0))),"")} | B63: {=IFERROR(IF(LARGE($D$200:$D$249,24)<=0,"",INDEX($B$200:$B$249,MATCH(LARGE($D$200:$D$249,24),$D$200:$D$249,0))),"")} | C63: {=IFERROR(IF(LARGE($D$200:$D$249,24)<=0,"",INDEX($C$200:$C$249,MATCH(LARGE($D$200:$D$249,24),$D$200:$D$249,0))),"")} | D63: =IFERROR(IF(B63="","",B63/SUMIFS(COBROS_DIARIOS!$K$4:$K$505,COBROS_DIARIOS!$A$4:$A$505,">="&$B$2,COBROS_DIARIOS!$A$4:$A$505,"<="&EOMONTH($B$2,0))),"")
A64: {=IFERROR(IF(LARGE($D$200:$D$249,25)<=0,"",INDEX($A$200:$A$249,MATCH(LARGE($D$200:$D$249,25),$D$200:$D$249,0))),"")} | B64: {=IFERROR(IF(LARGE($D$200:$D$249,25)<=0,"",INDEX($B$200:$B$249,MATCH(LARGE($D$200:$D$249,25),$D$200:$D$249,0))),"")} | C64: {=IFERROR(IF(LARGE($D$200:$D$249,25)<=0,"",INDEX($C$200:$C$249,MATCH(LARGE($D$200:$D$249,25),$D$200:$D$249,0))),"")} | D64: =IFERROR(IF(B64="","",B64/SUMIFS(COBROS_DIARIOS!$K$4:$K$505,COBROS_DIARIOS!$A$4:$A$505,">="&$B$2,COBROS_DIARIOS!$A$4:$A$505,"<="&EOMONTH($B$2,0))),"")
A65: {=IFERROR(IF(LARGE($D$200:$D$249,26)<=0,"",INDEX($A$200:$A$249,MATCH(LARGE($D$200:$D$249,26),$D$200:$D$249,0))),"")} | B65: {=IFERROR(IF(LARGE($D$200:$D$249,26)<=0,"",INDEX($B$200:$B$249,MATCH(LARGE($D$200:$D$249,26),$D$200:$D$249,0))),"")} | C65: {=IFERROR(IF(LARGE($D$200:$D$249,26)<=0,"",INDEX($C$200:$C$249,MATCH(LARGE($D$200:$D$249,26),$D$200:$D$249,0))),"")} | D65: =IFERROR(IF(B65="","",B65/SUMIFS(COBROS_DIARIOS!$K$4:$K$505,COBROS_DIARIOS!$A$4:$A$505,">="&$B$2,COBROS_DIARIOS!$A$4:$A$505,"<="&EOMONTH($B$2,0))),"")
A66: {=IFERROR(IF(LARGE($D$200:$D$249,27)<=0,"",INDEX($A$200:$A$249,MATCH(LARGE($D$200:$D$249,27),$D$200:$D$249,0))),"")} | B66: {=IFERROR(IF(LARGE($D$200:$D$249,27)<=0,"",INDEX($B$200:$B$249,MATCH(LARGE($D$200:$D$249,27),$D$200:$D$249,0))),"")} | C66: {=IFERROR(IF(LARGE($D$200:$D$249,27)<=0,"",INDEX($C$200:$C$249,MATCH(LARGE($D$200:$D$249,27),$D$200:$D$249,0))),"")} | D66: =IFERROR(IF(B66="","",B66/SUMIFS(COBROS_DIARIOS!$K$4:$K$505,COBROS_DIARIOS!$A$4:$A$505,">="&$B$2,COBROS_DIARIOS!$A$4:$A$505,"<="&EOMONTH($B$2,0))),"")
A67: {=IFERROR(IF(LARGE($D$200:$D$249,28)<=0,"",INDEX($A$200:$A$249,MATCH(LARGE($D$200:$D$249,28),$D$200:$D$249,0))),"")} | B67: {=IFERROR(IF(LARGE($D$200:$D$249,28)<=0,"",INDEX($B$200:$B$249,MATCH(LARGE($D$200:$D$249,28),$D$200:$D$249,0))),"")} | C67: {=IFERROR(IF(LARGE($D$200:$D$249,28)<=0,"",INDEX($C$200:$C$249,MATCH(LARGE($D$200:$D$249,28),$D$200:$D$249,0))),"")} | D67: =IFERROR(IF(B67="","",B67/SUMIFS(COBROS_DIARIOS!$K$4:$K$505,COBROS_DIARIOS!$A$4:$A$505,">="&$B$2,COBROS_DIARIOS!$A$4:$A$505,"<="&EOMONTH($B$2,0))),"")
A68: {=IFERROR(IF(LARGE($D$200:$D$249,29)<=0,"",INDEX($A$200:$A$249,MATCH(LARGE($D$200:$D$249,29),$D$200:$D$249,0))),"")} | B68: {=IFERROR(IF(LARGE($D$200:$D$249,29)<=0,"",INDEX($B$200:$B$249,MATCH(LARGE($D$200:$D$249,29),$D$200:$D$249,0))),"")} | C68: {=IFERROR(IF(LARGE($D$200:$D$249,29)<=0,"",INDEX($C$200:$C$249,MATCH(LARGE($D$200:$D$249,29),$D$200:$D$249,0))),"")} | D68: =IFERROR(IF(B68="","",B68/SUMIFS(COBROS_DIARIOS!$K$4:$K$505,COBROS_DIARIOS!$A$4:$A$505,">="&$B$2,COBROS_DIARIOS!$A$4:$A$505,"<="&EOMONTH($B$2,0))),"")
A69: {=IFERROR(IF(LARGE($D$200:$D$249,30)<=0,"",INDEX($A$200:$A$249,MATCH(LARGE($D$200:$D$249,30),$D$200:$D$249,0))),"")} | B69: {=IFERROR(IF(LARGE($D$200:$D$249,30)<=0,"",INDEX($B$200:$B$249,MATCH(LARGE($D$200:$D$249,30),$D$200:$D$249,0))),"")} | C69: {=IFERROR(IF(LARGE($D$200:$D$249,30)<=0,"",INDEX($C$200:$C$249,MATCH(LARGE($D$200:$D$249,30),$D$200:$D$249,0))),"")} | D69: =IFERROR(IF(B69="","",B69/SUMIFS(COBROS_DIARIOS!$K$4:$K$505,COBROS_DIARIOS!$A$4:$A$505,">="&$B$2,COBROS_DIARIOS!$A$4:$A$505,"<="&EOMONTH($B$2,0))),"")
A72: CANTIDAD POR COLOR × PRODUCTO (desglose mes)
A73: COLOR | B73: =IFERROR(IF(PRODUCTOS!A4="","",PRODUCTOS!A4),"") -> jersey manga corta | C73: =IFERROR(IF(PRODUCTOS!A5="","",PRODUCTOS!A5),"") -> jersey manga larga | D73: =IFERROR(IF(PRODUCTOS!A6="","",PRODUCTOS!A6),"") -> wafle clasico | E73: =IFERROR(IF(PRODUCTOS!A7="","",PRODUCTOS!A7),"") -> wafle manga larga | F73: =IFERROR(IF(PRODUCTOS!A8="","",PRODUCTOS!A8),"") -> wafle camisero | G73: =IFERROR(IF(PRODUCTOS!A9="","",PRODUCTOS!A9),"") -> pique camisero | H73: =IFERROR(IF(PRODUCTOS!A10="","",PRODUCTOS!A10),"") -> top cero rib | I73: =IFERROR(IF(PRODUCTOS!A11="","",PRODUCTOS!A11),"") -> top mc rib | J73: =IFERROR(IF(PRODUCTOS!A12="","",PRODUCTOS!A12),"") -> top ml rib | K73: =IFERROR(IF(PRODUCTOS!A13="","",PRODUCTOS!A13),"") -> baby ty mc | L73: =IFERROR(IF(PRODUCTOS!A14="","",PRODUCTOS!A14),"") -> baby ty ml | M73: =IFERROR(IF(PRODUCTOS!A15="","",PRODUCTOS!A15),"") -> Baby Tee con S | N73: =IFERROR(IF(PRODUCTOS!A16="","",PRODUCTOS!A16),"") -> Baby Tee M/L S | O73: =IFERROR(IF(PRODUCTOS!A17="","",PRODUCTOS!A17),"") -> polera neru | P73: =IFERROR(IF(PRODUCTOS!A18="","",PRODUCTOS!A18),"") -> polera boxy | Q73: =IFERROR(IF(PRODUCTOS!A19="","",PRODUCTOS!A19),"") -> pique cuello chino | R73: =IFERROR(IF(PRODUCTOS!A20="","",PRODUCTOS!A20),"") -> wafle camisa | S73: =IFERROR(IF(PRODUCTOS!A21="","",PRODUCTOS!A21),"") | T73: =IFERROR(IF(PRODUCTOS!A22="","",PRODUCTOS!A22),"") | U73: =IFERROR(IF(PRODUCTOS!A23="","",PRODUCTOS!A23),"") | V73: =IFERROR(IF(PRODUCTOS!A24="","",PRODUCTOS!A24),"") | W73: =IFERROR(IF(PRODUCTOS!A25="","",PRODUCTOS!A25),"") | X73: =IFERROR(IF(PRODUCTOS!A26="","",PRODUCTOS!A26),"") | Y73: =IFERROR(IF(PRODUCTOS!A27="","",PRODUCTOS!A27),"") | Z73: =IFERROR(IF(PRODUCTOS!A28="","",PRODUCTOS!A28),"") | AA73: TOTAL
A74: =IFERROR(IF(COLORES!A4="","",COLORES!A4),"") -> Negro | B74: =IF(OR(B$73="",$A74=""),"",IFERROR(SUMIFS(COBROS_DIARIOS!$K$4:$K$505,COBROS_DIARIOS!$E$4:$E$505,B$73,COBROS_DIARIOS!$F$4:$F$505,$A74,COBROS_DIARIOS!$A$4:$A$505,">="&$B$2,COBROS_DIARIOS!$A$4:$A$505,"<="&EOMONTH($B$2,0)),0)) -> 668 | C74: =IF(OR(C$73="",$A74=""),"",IFERROR(SUMIFS(COBROS_DIARIOS!$K$4:$K$505,COBROS_DIARIOS!$E$4:$E$505,C$73,COBROS_DIARIOS!$F$4:$F$505,$A74,COBROS_DIARIOS!$A$4:$A$505,">="&$B$2,COBROS_DIARIOS!$A$4:$A$505,"<="&EOMONTH($B$2,0)),0)) -> 294 | D74: =IF(OR(D$73="",$A74=""),"",IFERROR(SUMIFS(COBROS_DIARIOS!$K$4:$K$505,COBROS_DIARIOS!$E$4:$E$505,D$73,COBROS_DIARIOS!$F$4:$F$505,$A74,COBROS_DIARIOS!$A$4:$A$505,">="&$B$2,COBROS_DIARIOS!$A$4:$A$505,"<="&EOMONTH($B$2,0)),0)) -> 1845 | E74: =IF(OR(E$73="",$A74=""),"",IFERROR(SUMIFS(COBROS_DIARIOS!$K$4:$K$505,COBROS_DIARIOS!$E$4:$E$505,E$73,COBROS_DIARIOS!$F$4:$F$505,$A74,COBROS_DIARIOS!$A$4:$A$505,">="&$B$2,COBROS_DIARIOS!$A$4:$A$505,"<="&EOMONTH($B$2,0)),0)) -> 0 | F74: =IF(OR(F$73="",$A74=""),"",IFERROR(SUMIFS(COBROS_DIARIOS!$K$4:$K$505,COBROS_DIARIOS!$E$4:$E$505,F$73,COBROS_DIARIOS!$F$4:$F$505,$A74,COBROS_DIARIOS!$A$4:$A$505,">="&$B$2,COBROS_DIARIOS!$A$4:$A$505,"<="&EOMONTH($B$2,0)),0)) -> 0 | G74: =IF(OR(G$73="",$A74=""),"",IFERROR(SUMIFS(COBROS_DIARIOS!$K$4:$K$505,COBROS_DIARIOS!$E$4:$E$505,G$73,COBROS_DIARIOS!$F$4:$F$505,$A74,COBROS_DIARIOS!$A$4:$A$505,">="&$B$2,COBROS_DIARIOS!$A$4:$A$505,"<="&EOMONTH($B$2,0)),0)) -> 819 | H74: =IF(OR(H$73="",$A74=""),"",IFERROR(SUMIFS(COBROS_DIARIOS!$K$4:$K$505,COBROS_DIARIOS!$E$4:$E$505,H$73,COBROS_DIARIOS!$F$4:$F$505,$A74,COBROS_DIARIOS!$A$4:$A$505,">="&$B$2,COBROS_DIARIOS!$A$4:$A$505,"<="&EOMONTH($B$2,0)),0)) -> 92 | I74: =IF(OR(I$73="",$A74=""),"",IFERROR(SUMIFS(COBROS_DIARIOS!$K$4:$K$505,COBROS_DIARIOS!$E$4:$E$505,I$73,COBROS_DIARIOS!$F$4:$F$505,$A74,COBROS_DIARIOS!$A$4:$A$505,">="&$B$2,COBROS_DIARIOS!$A$4:$A$505,"<="&EOMONTH($B$2,0)),0)) -> 190 | ... Z74: =IF(OR(Z$73="",$A74=""),"",IFERROR(SUMIFS(COBROS_DIARIOS!$K$4:$K$505,COBROS_DIARIOS!$E$4:$E$505,Z$73,COBROS_DIARIOS!$F$4:$F$505,$A74,COBROS_DIARIOS!$A$4:$A$505,">="&$B$2,COBROS_DIARIOS!$A$4:$A$505,"<="&EOMONTH($B$2,0)),0)) | AA74: =IFERROR(SUM(B74:Z74),0) -> 6024
A75: =IFERROR(IF(COLORES!A5="","",COLORES!A5),"") -> Perla | B75: =IF(OR(B$73="",$A75=""),"",IFERROR(SUMIFS(COBROS_DIARIOS!$K$4:$K$505,COBROS_DIARIOS!$E$4:$E$505,B$73,COBROS_DIARIOS!$F$4:$F$505,$A75,COBROS_DIARIOS!$A$4:$A$505,">="&$B$2,COBROS_DIARIOS!$A$4:$A$505,"<="&EOMONTH($B$2,0)),0)) -> 0 | C75: =IF(OR(C$73="",$A75=""),"",IFERROR(SUMIFS(COBROS_DIARIOS!$K$4:$K$505,COBROS_DIARIOS!$E$4:$E$505,C$73,COBROS_DIARIOS!$F$4:$F$505,$A75,COBROS_DIARIOS!$A$4:$A$505,">="&$B$2,COBROS_DIARIOS!$A$4:$A$505,"<="&EOMONTH($B$2,0)),0)) -> 202 | D75: =IF(OR(D$73="",$A75=""),"",IFERROR(SUMIFS(COBROS_DIARIOS!$K$4:$K$505,COBROS_DIARIOS!$E$4:$E$505,D$73,COBROS_DIARIOS!$F$4:$F$505,$A75,COBROS_DIARIOS!$A$4:$A$505,">="&$B$2,COBROS_DIARIOS!$A$4:$A$505,"<="&EOMONTH($B$2,0)),0)) -> 904 | E75: =IF(OR(E$73="",$A75=""),"",IFERROR(SUMIFS(COBROS_DIARIOS!$K$4:$K$505,COBROS_DIARIOS!$E$4:$E$505,E$73,COBROS_DIARIOS!$F$4:$F$505,$A75,COBROS_DIARIOS!$A$4:$A$505,">="&$B$2,COBROS_DIARIOS!$A$4:$A$505,"<="&EOMONTH($B$2,0)),0)) -> 0 | F75: =IF(OR(F$73="",$A75=""),"",IFERROR(SUMIFS(COBROS_DIARIOS!$K$4:$K$505,COBROS_DIARIOS!$E$4:$E$505,F$73,COBROS_DIARIOS!$F$4:$F$505,$A75,COBROS_DIARIOS!$A$4:$A$505,">="&$B$2,COBROS_DIARIOS!$A$4:$A$505,"<="&EOMONTH($B$2,0)),0)) -> 0 | G75: =IF(OR(G$73="",$A75=""),"",IFERROR(SUMIFS(COBROS_DIARIOS!$K$4:$K$505,COBROS_DIARIOS!$E$4:$E$505,G$73,COBROS_DIARIOS!$F$4:$F$505,$A75,COBROS_DIARIOS!$A$4:$A$505,">="&$B$2,COBROS_DIARIOS!$A$4:$A$505,"<="&EOMONTH($B$2,0)),0)) -> 406 | H75: =IF(OR(H$73="",$A75=""),"",IFERROR(SUMIFS(COBROS_DIARIOS!$K$4:$K$505,COBROS_DIARIOS!$E$4:$E$505,H$73,COBROS_DIARIOS!$F$4:$F$505,$A75,COBROS_DIARIOS!$A$4:$A$505,">="&$B$2,COBROS_DIARIOS!$A$4:$A$505,"<="&EOMONTH($B$2,0)),0)) -> 62 | I75: =IF(OR(I$73="",$A75=""),"",IFERROR(SUMIFS(COBROS_DIARIOS!$K$4:$K$505,COBROS_DIARIOS!$E$4:$E$505,I$73,COBROS_DIARIOS!$F$4:$F$505,$A75,COBROS_DIARIOS!$A$4:$A$505,">="&$B$2,COBROS_DIARIOS!$A$4:$A$505,"<="&EOMONTH($B$2,0)),0)) -> 126 | ... Z75: =IF(OR(Z$73="",$A75=""),"",IFERROR(SUMIFS(COBROS_DIARIOS!$K$4:$K$505,COBROS_DIARIOS!$E$4:$E$505,Z$73,COBROS_DIARIOS!$F$4:$F$505,$A75,COBROS_DIARIOS!$A$4:$A$505,">="&$B$2,COBROS_DIARIOS!$A$4:$A$505,"<="&EOMONTH($B$2,0)),0)) | AA75: =IFERROR(SUM(B75:Z75),0) -> 3124
A76: =IFERROR(IF(COLORES!A6="","",COLORES!A6),"") -> Blanco | B76: =IF(OR(B$73="",$A76=""),"",IFERROR(SUMIFS(COBROS_DIARIOS!$K$4:$K$505,COBROS_DIARIOS!$E$4:$E$505,B$73,COBROS_DIARIOS!$F$4:$F$505,$A76,COBROS_DIARIOS!$A$4:$A$505,">="&$B$2,COBROS_DIARIOS!$A$4:$A$505,"<="&EOMONTH($B$2,0)),0)) -> 0 | C76: =IF(OR(C$73="",$A76=""),"",IFERROR(SUMIFS(COBROS_DIARIOS!$K$4:$K$505,COBROS_DIARIOS!$E$4:$E$505,C$73,COBROS_DIARIOS!$F$4:$F$505,$A76,COBROS_DIARIOS!$A$4:$A$505,">="&$B$2,COBROS_DIARIOS!$A$4:$A$505,"<="&EOMONTH($B$2,0)),0)) -> 0 | D76: =IF(OR(D$73="",$A76=""),"",IFERROR(SUMIFS(COBROS_DIARIOS!$K$4:$K$505,COBROS_DIARIOS!$E$4:$E$505,D$73,COBROS_DIARIOS!$F$4:$F$505,$A76,COBROS_DIARIOS!$A$4:$A$505,">="&$B$2,COBROS_DIARIOS!$A$4:$A$505,"<="&EOMONTH($B$2,0)),0)) -> 0 | E76: =IF(OR(E$73="",$A76=""),"",IFERROR(SUMIFS(COBROS_DIARIOS!$K$4:$K$505,COBROS_DIARIOS!$E$4:$E$505,E$73,COBROS_DIARIOS!$F$4:$F$505,$A76,COBROS_DIARIOS!$A$4:$A$505,">="&$B$2,COBROS_DIARIOS!$A$4:$A$505,"<="&EOMONTH($B$2,0)),0)) -> 0 | F76: =IF(OR(F$73="",$A76=""),"",IFERROR(SUMIFS(COBROS_DIARIOS!$K$4:$K$505,COBROS_DIARIOS!$E$4:$E$505,F$73,COBROS_DIARIOS!$F$4:$F$505,$A76,COBROS_DIARIOS!$A$4:$A$505,">="&$B$2,COBROS_DIARIOS!$A$4:$A$505,"<="&EOMONTH($B$2,0)),0)) -> 0 | G76: =IF(OR(G$73="",$A76=""),"",IFERROR(SUMIFS(COBROS_DIARIOS!$K$4:$K$505,COBROS_DIARIOS!$E$4:$E$505,G$73,COBROS_DIARIOS!$F$4:$F$505,$A76,COBROS_DIARIOS!$A$4:$A$505,">="&$B$2,COBROS_DIARIOS!$A$4:$A$505,"<="&EOMONTH($B$2,0)),0)) -> 0 | H76: =IF(OR(H$73="",$A76=""),"",IFERROR(SUMIFS(COBROS_DIARIOS!$K$4:$K$505,COBROS_DIARIOS!$E$4:$E$505,H$73,COBROS_DIARIOS!$F$4:$F$505,$A76,COBROS_DIARIOS!$A$4:$A$505,">="&$B$2,COBROS_DIARIOS!$A$4:$A$505,"<="&EOMONTH($B$2,0)),0)) -> 0 | I76: =IF(OR(I$73="",$A76=""),"",IFERROR(SUMIFS(COBROS_DIARIOS!$K$4:$K$505,COBROS_DIARIOS!$E$4:$E$505,I$73,COBROS_DIARIOS!$F$4:$F$505,$A76,COBROS_DIARIOS!$A$4:$A$505,">="&$B$2,COBROS_DIARIOS!$A$4:$A$505,"<="&EOMONTH($B$2,0)),0)) -> 0 | ... Z76: =IF(OR(Z$73="",$A76=""),"",IFERROR(SUMIFS(COBROS_DIARIOS!$K$4:$K$505,COBROS_DIARIOS!$E$4:$E$505,Z$73,COBROS_DIARIOS!$F$4:$F$505,$A76,COBROS_DIARIOS!$A$4:$A$505,">="&$B$2,COBROS_DIARIOS!$A$4:$A$505,"<="&EOMONTH($B$2,0)),0)) | AA76: =IFERROR(SUM(B76:Z76),0) -> 0
A77: =IFERROR(IF(COLORES!A7="","",COLORES!A7),"") -> Azul | B77: =IF(OR(B$73="",$A77=""),"",IFERROR(SUMIFS(COBROS_DIARIOS!$K$4:$K$505,COBROS_DIARIOS!$E$4:$E$505,B$73,COBROS_DIARIOS!$F$4:$F$505,$A77,COBROS_DIARIOS!$A$4:$A$505,">="&$B$2,COBROS_DIARIOS!$A$4:$A$505,"<="&EOMONTH($B$2,0)),0)) -> 0 | C77: =IF(OR(C$73="",$A77=""),"",IFERROR(SUMIFS(COBROS_DIARIOS!$K$4:$K$505,COBROS_DIARIOS!$E$4:$E$505,C$73,COBROS_DIARIOS!$F$4:$F$505,$A77,COBROS_DIARIOS!$A$4:$A$505,">="&$B$2,COBROS_DIARIOS!$A$4:$A$505,"<="&EOMONTH($B$2,0)),0)) -> 0 | D77: =IF(OR(D$73="",$A77=""),"",IFERROR(SUMIFS(COBROS_DIARIOS!$K$4:$K$505,COBROS_DIARIOS!$E$4:$E$505,D$73,COBROS_DIARIOS!$F$4:$F$505,$A77,COBROS_DIARIOS!$A$4:$A$505,">="&$B$2,COBROS_DIARIOS!$A$4:$A$505,"<="&EOMONTH($B$2,0)),0)) -> 0 | E77: =IF(OR(E$73="",$A77=""),"",IFERROR(SUMIFS(COBROS_DIARIOS!$K$4:$K$505,COBROS_DIARIOS!$E$4:$E$505,E$73,COBROS_DIARIOS!$F$4:$F$505,$A77,COBROS_DIARIOS!$A$4:$A$505,">="&$B$2,COBROS_DIARIOS!$A$4:$A$505,"<="&EOMONTH($B$2,0)),0)) -> 0 | F77: =IF(OR(F$73="",$A77=""),"",IFERROR(SUMIFS(COBROS_DIARIOS!$K$4:$K$505,COBROS_DIARIOS!$E$4:$E$505,F$73,COBROS_DIARIOS!$F$4:$F$505,$A77,COBROS_DIARIOS!$A$4:$A$505,">="&$B$2,COBROS_DIARIOS!$A$4:$A$505,"<="&EOMONTH($B$2,0)),0)) -> 0 | G77: =IF(OR(G$73="",$A77=""),"",IFERROR(SUMIFS(COBROS_DIARIOS!$K$4:$K$505,COBROS_DIARIOS!$E$4:$E$505,G$73,COBROS_DIARIOS!$F$4:$F$505,$A77,COBROS_DIARIOS!$A$4:$A$505,">="&$B$2,COBROS_DIARIOS!$A$4:$A$505,"<="&EOMONTH($B$2,0)),0)) -> 0 | H77: =IF(OR(H$73="",$A77=""),"",IFERROR(SUMIFS(COBROS_DIARIOS!$K$4:$K$505,COBROS_DIARIOS!$E$4:$E$505,H$73,COBROS_DIARIOS!$F$4:$F$505,$A77,COBROS_DIARIOS!$A$4:$A$505,">="&$B$2,COBROS_DIARIOS!$A$4:$A$505,"<="&EOMONTH($B$2,0)),0)) -> 0 | I77: =IF(OR(I$73="",$A77=""),"",IFERROR(SUMIFS(COBROS_DIARIOS!$K$4:$K$505,COBROS_DIARIOS!$E$4:$E$505,I$73,COBROS_DIARIOS!$F$4:$F$505,$A77,COBROS_DIARIOS!$A$4:$A$505,">="&$B$2,COBROS_DIARIOS!$A$4:$A$505,"<="&EOMONTH($B$2,0)),0)) -> 0 | ... Z77: =IF(OR(Z$73="",$A77=""),"",IFERROR(SUMIFS(COBROS_DIARIOS!$K$4:$K$505,COBROS_DIARIOS!$E$4:$E$505,Z$73,COBROS_DIARIOS!$F$4:$F$505,$A77,COBROS_DIARIOS!$A$4:$A$505,">="&$B$2,COBROS_DIARIOS!$A$4:$A$505,"<="&EOMONTH($B$2,0)),0)) | AA77: =IFERROR(SUM(B77:Z77),0) -> 0
A78: =IFERROR(IF(COLORES!A8="","",COLORES!A8),"") -> Beige | B78: =IF(OR(B$73="",$A78=""),"",IFERROR(SUMIFS(COBROS_DIARIOS!$K$4:$K$505,COBROS_DIARIOS!$E$4:$E$505,B$73,COBROS_DIARIOS!$F$4:$F$505,$A78,COBROS_DIARIOS!$A$4:$A$505,">="&$B$2,COBROS_DIARIOS!$A$4:$A$505,"<="&EOMONTH($B$2,0)),0)) -> 392 | C78: =IF(OR(C$73="",$A78=""),"",IFERROR(SUMIFS(COBROS_DIARIOS!$K$4:$K$505,COBROS_DIARIOS!$E$4:$E$505,C$73,COBROS_DIARIOS!$F$4:$F$505,$A78,COBROS_DIARIOS!$A$4:$A$505,">="&$B$2,COBROS_DIARIOS!$A$4:$A$505,"<="&EOMONTH($B$2,0)),0)) -> 0 | D78: =IF(OR(D$73="",$A78=""),"",IFERROR(SUMIFS(COBROS_DIARIOS!$K$4:$K$505,COBROS_DIARIOS!$E$4:$E$505,D$73,COBROS_DIARIOS!$F$4:$F$505,$A78,COBROS_DIARIOS!$A$4:$A$505,">="&$B$2,COBROS_DIARIOS!$A$4:$A$505,"<="&EOMONTH($B$2,0)),0)) -> 404 | E78: =IF(OR(E$73="",$A78=""),"",IFERROR(SUMIFS(COBROS_DIARIOS!$K$4:$K$505,COBROS_DIARIOS!$E$4:$E$505,E$73,COBROS_DIARIOS!$F$4:$F$505,$A78,COBROS_DIARIOS!$A$4:$A$505,">="&$B$2,COBROS_DIARIOS!$A$4:$A$505,"<="&EOMONTH($B$2,0)),0)) -> 323 | F78: =IF(OR(F$73="",$A78=""),"",IFERROR(SUMIFS(COBROS_DIARIOS!$K$4:$K$505,COBROS_DIARIOS!$E$4:$E$505,F$73,COBROS_DIARIOS!$F$4:$F$505,$A78,COBROS_DIARIOS!$A$4:$A$505,">="&$B$2,COBROS_DIARIOS!$A$4:$A$505,"<="&EOMONTH($B$2,0)),0)) -> 0 | G78: =IF(OR(G$73="",$A78=""),"",IFERROR(SUMIFS(COBROS_DIARIOS!$K$4:$K$505,COBROS_DIARIOS!$E$4:$E$505,G$73,COBROS_DIARIOS!$F$4:$F$505,$A78,COBROS_DIARIOS!$A$4:$A$505,">="&$B$2,COBROS_DIARIOS!$A$4:$A$505,"<="&EOMONTH($B$2,0)),0)) -> 207 | H78: =IF(OR(H$73="",$A78=""),"",IFERROR(SUMIFS(COBROS_DIARIOS!$K$4:$K$505,COBROS_DIARIOS!$E$4:$E$505,H$73,COBROS_DIARIOS!$F$4:$F$505,$A78,COBROS_DIARIOS!$A$4:$A$505,">="&$B$2,COBROS_DIARIOS!$A$4:$A$505,"<="&EOMONTH($B$2,0)),0)) -> 26 | I78: =IF(OR(I$73="",$A78=""),"",IFERROR(SUMIFS(COBROS_DIARIOS!$K$4:$K$505,COBROS_DIARIOS!$E$4:$E$505,I$73,COBROS_DIARIOS!$F$4:$F$505,$A78,COBROS_DIARIOS!$A$4:$A$505,">="&$B$2,COBROS_DIARIOS!$A$4:$A$505,"<="&EOMONTH($B$2,0)),0)) -> 56 | ... Z78: =IF(OR(Z$73="",$A78=""),"",IFERROR(SUMIFS(COBROS_DIARIOS!$K$4:$K$505,COBROS_DIARIOS!$E$4:$E$505,Z$73,COBROS_DIARIOS!$F$4:$F$505,$A78,COBROS_DIARIOS!$A$4:$A$505,">="&$B$2,COBROS_DIARIOS!$A$4:$A$505,"<="&EOMONTH($B$2,0)),0)) | AA78: =IFERROR(SUM(B78:Z78),0) -> 1871
A79: =IFERROR(IF(COLORES!A9="","",COLORES!A9),"") -> Melange | B79: =IF(OR(B$73="",$A79=""),"",IFERROR(SUMIFS(COBROS_DIARIOS!$K$4:$K$505,COBROS_DIARIOS!$E$4:$E$505,B$73,COBROS_DIARIOS!$F$4:$F$505,$A79,COBROS_DIARIOS!$A$4:$A$505,">="&$B$2,COBROS_DIARIOS!$A$4:$A$505,"<="&EOMONTH($B$2,0)),0)) -> 0 | C79: =IF(OR(C$73="",$A79=""),"",IFERROR(SUMIFS(COBROS_DIARIOS!$K$4:$K$505,COBROS_DIARIOS!$E$4:$E$505,C$73,COBROS_DIARIOS!$F$4:$F$505,$A79,COBROS_DIARIOS!$A$4:$A$505,">="&$B$2,COBROS_DIARIOS!$A$4:$A$505,"<="&EOMONTH($B$2,0)),0)) -> 0 | D79: =IF(OR(D$73="",$A79=""),"",IFERROR(SUMIFS(COBROS_DIARIOS!$K$4:$K$505,COBROS_DIARIOS!$E$4:$E$505,D$73,COBROS_DIARIOS!$F$4:$F$505,$A79,COBROS_DIARIOS!$A$4:$A$505,">="&$B$2,COBROS_DIARIOS!$A$4:$A$505,"<="&EOMONTH($B$2,0)),0)) -> 0 | E79: =IF(OR(E$73="",$A79=""),"",IFERROR(SUMIFS(COBROS_DIARIOS!$K$4:$K$505,COBROS_DIARIOS!$E$4:$E$505,E$73,COBROS_DIARIOS!$F$4:$F$505,$A79,COBROS_DIARIOS!$A$4:$A$505,">="&$B$2,COBROS_DIARIOS!$A$4:$A$505,"<="&EOMONTH($B$2,0)),0)) -> 0 | F79: =IF(OR(F$73="",$A79=""),"",IFERROR(SUMIFS(COBROS_DIARIOS!$K$4:$K$505,COBROS_DIARIOS!$E$4:$E$505,F$73,COBROS_DIARIOS!$F$4:$F$505,$A79,COBROS_DIARIOS!$A$4:$A$505,">="&$B$2,COBROS_DIARIOS!$A$4:$A$505,"<="&EOMONTH($B$2,0)),0)) -> 325 | G79: =IF(OR(G$73="",$A79=""),"",IFERROR(SUMIFS(COBROS_DIARIOS!$K$4:$K$505,COBROS_DIARIOS!$E$4:$E$505,G$73,COBROS_DIARIOS!$F$4:$F$505,$A79,COBROS_DIARIOS!$A$4:$A$505,">="&$B$2,COBROS_DIARIOS!$A$4:$A$505,"<="&EOMONTH($B$2,0)),0)) -> 309 | H79: =IF(OR(H$73="",$A79=""),"",IFERROR(SUMIFS(COBROS_DIARIOS!$K$4:$K$505,COBROS_DIARIOS!$E$4:$E$505,H$73,COBROS_DIARIOS!$F$4:$F$505,$A79,COBROS_DIARIOS!$A$4:$A$505,">="&$B$2,COBROS_DIARIOS!$A$4:$A$505,"<="&EOMONTH($B$2,0)),0)) -> 0 | I79: =IF(OR(I$73="",$A79=""),"",IFERROR(SUMIFS(COBROS_DIARIOS!$K$4:$K$505,COBROS_DIARIOS!$E$4:$E$505,I$73,COBROS_DIARIOS!$F$4:$F$505,$A79,COBROS_DIARIOS!$A$4:$A$505,">="&$B$2,COBROS_DIARIOS!$A$4:$A$505,"<="&EOMONTH($B$2,0)),0)) -> 0 | ... Z79: =IF(OR(Z$73="",$A79=""),"",IFERROR(SUMIFS(COBROS_DIARIOS!$K$4:$K$505,COBROS_DIARIOS!$E$4:$E$505,Z$73,COBROS_DIARIOS!$F$4:$F$505,$A79,COBROS_DIARIOS!$A$4:$A$505,">="&$B$2,COBROS_DIARIOS!$A$4:$A$505,"<="&EOMONTH($B$2,0)),0)) | AA79: =IFERROR(SUM(B79:Z79),0) -> 692
A80: =IFERROR(IF(COLORES!A10="","",COLORES!A10),"") -> Botella | B80: =IF(OR(B$73="",$A80=""),"",IFERROR(SUMIFS(COBROS_DIARIOS!$K$4:$K$505,COBROS_DIARIOS!$E$4:$E$505,B$73,COBROS_DIARIOS!$F$4:$F$505,$A80,COBROS_DIARIOS!$A$4:$A$505,">="&$B$2,COBROS_DIARIOS!$A$4:$A$505,"<="&EOMONTH($B$2,0)),0)) -> 496 | C80: =IF(OR(C$73="",$A80=""),"",IFERROR(SUMIFS(COBROS_DIARIOS!$K$4:$K$505,COBROS_DIARIOS!$E$4:$E$505,C$73,COBROS_DIARIOS!$F$4:$F$505,$A80,COBROS_DIARIOS!$A$4:$A$505,">="&$B$2,COBROS_DIARIOS!$A$4:$A$505,"<="&EOMONTH($B$2,0)),0)) -> 252 | D80: =IF(OR(D$73="",$A80=""),"",IFERROR(SUMIFS(COBROS_DIARIOS!$K$4:$K$505,COBROS_DIARIOS!$E$4:$E$505,D$73,COBROS_DIARIOS!$F$4:$F$505,$A80,COBROS_DIARIOS!$A$4:$A$505,">="&$B$2,COBROS_DIARIOS!$A$4:$A$505,"<="&EOMONTH($B$2,0)),0)) -> 317 | E80: =IF(OR(E$73="",$A80=""),"",IFERROR(SUMIFS(COBROS_DIARIOS!$K$4:$K$505,COBROS_DIARIOS!$E$4:$E$505,E$73,COBROS_DIARIOS!$F$4:$F$505,$A80,COBROS_DIARIOS!$A$4:$A$505,">="&$B$2,COBROS_DIARIOS!$A$4:$A$505,"<="&EOMONTH($B$2,0)),0)) -> 0 | F80: =IF(OR(F$73="",$A80=""),"",IFERROR(SUMIFS(COBROS_DIARIOS!$K$4:$K$505,COBROS_DIARIOS!$E$4:$E$505,F$73,COBROS_DIARIOS!$F$4:$F$505,$A80,COBROS_DIARIOS!$A$4:$A$505,">="&$B$2,COBROS_DIARIOS!$A$4:$A$505,"<="&EOMONTH($B$2,0)),0)) -> 0 | G80: =IF(OR(G$73="",$A80=""),"",IFERROR(SUMIFS(COBROS_DIARIOS!$K$4:$K$505,COBROS_DIARIOS!$E$4:$E$505,G$73,COBROS_DIARIOS!$F$4:$F$505,$A80,COBROS_DIARIOS!$A$4:$A$505,">="&$B$2,COBROS_DIARIOS!$A$4:$A$505,"<="&EOMONTH($B$2,0)),0)) -> 394 | H80: =IF(OR(H$73="",$A80=""),"",IFERROR(SUMIFS(COBROS_DIARIOS!$K$4:$K$505,COBROS_DIARIOS!$E$4:$E$505,H$73,COBROS_DIARIOS!$F$4:$F$505,$A80,COBROS_DIARIOS!$A$4:$A$505,">="&$B$2,COBROS_DIARIOS!$A$4:$A$505,"<="&EOMONTH($B$2,0)),0)) -> 0 | I80: =IF(OR(I$73="",$A80=""),"",IFERROR(SUMIFS(COBROS_DIARIOS!$K$4:$K$505,COBROS_DIARIOS!$E$4:$E$505,I$73,COBROS_DIARIOS!$F$4:$F$505,$A80,COBROS_DIARIOS!$A$4:$A$505,">="&$B$2,COBROS_DIARIOS!$A$4:$A$505,"<="&EOMONTH($B$2,0)),0)) -> 0 | ... Z80: =IF(OR(Z$73="",$A80=""),"",IFERROR(SUMIFS(COBROS_DIARIOS!$K$4:$K$505,COBROS_DIARIOS!$E$4:$E$505,Z$73,COBROS_DIARIOS!$F$4:$F$505,$A80,COBROS_DIARIOS!$A$4:$A$505,">="&$B$2,COBROS_DIARIOS!$A$4:$A$505,"<="&EOMONTH($B$2,0)),0)) | AA80: =IFERROR(SUM(B80:Z80),0) -> 1980
A81: =IFERROR(IF(COLORES!A11="","",COLORES!A11),"") -> Pacay | B81: =IF(OR(B$73="",$A81=""),"",IFERROR(SUMIFS(COBROS_DIARIOS!$K$4:$K$505,COBROS_DIARIOS!$E$4:$E$505,B$73,COBROS_DIARIOS!$F$4:$F$505,$A81,COBROS_DIARIOS!$A$4:$A$505,">="&$B$2,COBROS_DIARIOS!$A$4:$A$505,"<="&EOMONTH($B$2,0)),0)) -> 0 | C81: =IF(OR(C$73="",$A81=""),"",IFERROR(SUMIFS(COBROS_DIARIOS!$K$4:$K$505,COBROS_DIARIOS!$E$4:$E$505,C$73,COBROS_DIARIOS!$F$4:$F$505,$A81,COBROS_DIARIOS!$A$4:$A$505,">="&$B$2,COBROS_DIARIOS!$A$4:$A$505,"<="&EOMONTH($B$2,0)),0)) -> 0 | D81: =IF(OR(D$73="",$A81=""),"",IFERROR(SUMIFS(COBROS_DIARIOS!$K$4:$K$505,COBROS_DIARIOS!$E$4:$E$505,D$73,COBROS_DIARIOS!$F$4:$F$505,$A81,COBROS_DIARIOS!$A$4:$A$505,">="&$B$2,COBROS_DIARIOS!$A$4:$A$505,"<="&EOMONTH($B$2,0)),0)) -> 0 | E81: =IF(OR(E$73="",$A81=""),"",IFERROR(SUMIFS(COBROS_DIARIOS!$K$4:$K$505,COBROS_DIARIOS!$E$4:$E$505,E$73,COBROS_DIARIOS!$F$4:$F$505,$A81,COBROS_DIARIOS!$A$4:$A$505,">="&$B$2,COBROS_DIARIOS!$A$4:$A$505,"<="&EOMONTH($B$2,0)),0)) -> 0 | F81: =IF(OR(F$73="",$A81=""),"",IFERROR(SUMIFS(COBROS_DIARIOS!$K$4:$K$505,COBROS_DIARIOS!$E$4:$E$505,F$73,COBROS_DIARIOS!$F$4:$F$505,$A81,COBROS_DIARIOS!$A$4:$A$505,">="&$B$2,COBROS_DIARIOS!$A$4:$A$505,"<="&EOMONTH($B$2,0)),0)) -> 0 | G81: =IF(OR(G$73="",$A81=""),"",IFERROR(SUMIFS(COBROS_DIARIOS!$K$4:$K$505,COBROS_DIARIOS!$E$4:$E$505,G$73,COBROS_DIARIOS!$F$4:$F$505,$A81,COBROS_DIARIOS!$A$4:$A$505,">="&$B$2,COBROS_DIARIOS!$A$4:$A$505,"<="&EOMONTH($B$2,0)),0)) -> 0 | H81: =IF(OR(H$73="",$A81=""),"",IFERROR(SUMIFS(COBROS_DIARIOS!$K$4:$K$505,COBROS_DIARIOS!$E$4:$E$505,H$73,COBROS_DIARIOS!$F$4:$F$505,$A81,COBROS_DIARIOS!$A$4:$A$505,">="&$B$2,COBROS_DIARIOS!$A$4:$A$505,"<="&EOMONTH($B$2,0)),0)) -> 0 | I81: =IF(OR(I$73="",$A81=""),"",IFERROR(SUMIFS(COBROS_DIARIOS!$K$4:$K$505,COBROS_DIARIOS!$E$4:$E$505,I$73,COBROS_DIARIOS!$F$4:$F$505,$A81,COBROS_DIARIOS!$A$4:$A$505,">="&$B$2,COBROS_DIARIOS!$A$4:$A$505,"<="&EOMONTH($B$2,0)),0)) -> 0 | ... Z81: =IF(OR(Z$73="",$A81=""),"",IFERROR(SUMIFS(COBROS_DIARIOS!$K$4:$K$505,COBROS_DIARIOS!$E$4:$E$505,Z$73,COBROS_DIARIOS!$F$4:$F$505,$A81,COBROS_DIARIOS!$A$4:$A$505,">="&$B$2,COBROS_DIARIOS!$A$4:$A$505,"<="&EOMONTH($B$2,0)),0)) | AA81: =IFERROR(SUM(B81:Z81),0) -> 0
A82: =IFERROR(IF(COLORES!A12="","",COLORES!A12),"") -> V. Pacay | B82: =IF(OR(B$73="",$A82=""),"",IFERROR(SUMIFS(COBROS_DIARIOS!$K$4:$K$505,COBROS_DIARIOS!$E$4:$E$505,B$73,COBROS_DIARIOS!$F$4:$F$505,$A82,COBROS_DIARIOS!$A$4:$A$505,">="&$B$2,COBROS_DIARIOS!$A$4:$A$505,"<="&EOMONTH($B$2,0)),0)) -> 216 | C82: =IF(OR(C$73="",$A82=""),"",IFERROR(SUMIFS(COBROS_DIARIOS!$K$4:$K$505,COBROS_DIARIOS!$E$4:$E$505,C$73,COBROS_DIARIOS!$F$4:$F$505,$A82,COBROS_DIARIOS!$A$4:$A$505,">="&$B$2,COBROS_DIARIOS!$A$4:$A$505,"<="&EOMONTH($B$2,0)),0)) -> 0 | D82: =IF(OR(D$73="",$A82=""),"",IFERROR(SUMIFS(COBROS_DIARIOS!$K$4:$K$505,COBROS_DIARIOS!$E$4:$E$505,D$73,COBROS_DIARIOS!$F$4:$F$505,$A82,COBROS_DIARIOS!$A$4:$A$505,">="&$B$2,COBROS_DIARIOS!$A$4:$A$505,"<="&EOMONTH($B$2,0)),0)) -> 0 | E82: =IF(OR(E$73="",$A82=""),"",IFERROR(SUMIFS(COBROS_DIARIOS!$K$4:$K$505,COBROS_DIARIOS!$E$4:$E$505,E$73,COBROS_DIARIOS!$F$4:$F$505,$A82,COBROS_DIARIOS!$A$4:$A$505,">="&$B$2,COBROS_DIARIOS!$A$4:$A$505,"<="&EOMONTH($B$2,0)),0)) -> 0 | F82: =IF(OR(F$73="",$A82=""),"",IFERROR(SUMIFS(COBROS_DIARIOS!$K$4:$K$505,COBROS_DIARIOS!$E$4:$E$505,F$73,COBROS_DIARIOS!$F$4:$F$505,$A82,COBROS_DIARIOS!$A$4:$A$505,">="&$B$2,COBROS_DIARIOS!$A$4:$A$505,"<="&EOMONTH($B$2,0)),0)) -> 0 | G82: =IF(OR(G$73="",$A82=""),"",IFERROR(SUMIFS(COBROS_DIARIOS!$K$4:$K$505,COBROS_DIARIOS!$E$4:$E$505,G$73,COBROS_DIARIOS!$F$4:$F$505,$A82,COBROS_DIARIOS!$A$4:$A$505,">="&$B$2,COBROS_DIARIOS!$A$4:$A$505,"<="&EOMONTH($B$2,0)),0)) -> 0 | H82: =IF(OR(H$73="",$A82=""),"",IFERROR(SUMIFS(COBROS_DIARIOS!$K$4:$K$505,COBROS_DIARIOS!$E$4:$E$505,H$73,COBROS_DIARIOS!$F$4:$F$505,$A82,COBROS_DIARIOS!$A$4:$A$505,">="&$B$2,COBROS_DIARIOS!$A$4:$A$505,"<="&EOMONTH($B$2,0)),0)) -> 25 | I82: =IF(OR(I$73="",$A82=""),"",IFERROR(SUMIFS(COBROS_DIARIOS!$K$4:$K$505,COBROS_DIARIOS!$E$4:$E$505,I$73,COBROS_DIARIOS!$F$4:$F$505,$A82,COBROS_DIARIOS!$A$4:$A$505,">="&$B$2,COBROS_DIARIOS!$A$4:$A$505,"<="&EOMONTH($B$2,0)),0)) -> 53 | ... Z82: =IF(OR(Z$73="",$A82=""),"",IFERROR(SUMIFS(COBROS_DIARIOS!$K$4:$K$505,COBROS_DIARIOS!$E$4:$E$505,Z$73,COBROS_DIARIOS!$F$4:$F$505,$A82,COBROS_DIARIOS!$A$4:$A$505,">="&$B$2,COBROS_DIARIOS!$A$4:$A$505,"<="&EOMONTH($B$2,0)),0)) | AA82: =IFERROR(SUM(B82:Z82),0) -> 1214
A83: =IFERROR(IF(COLORES!A13="","",COLORES!A13),"") -> Cemento | B83: =IF(OR(B$73="",$A83=""),"",IFERROR(SUMIFS(COBROS_DIARIOS!$K$4:$K$505,COBROS_DIARIOS!$E$4:$E$505,B$73,COBROS_DIARIOS!$F$4:$F$505,$A83,COBROS_DIARIOS!$A$4:$A$505,">="&$B$2,COBROS_DIARIOS!$A$4:$A$505,"<="&EOMONTH($B$2,0)),0)) -> 0 | C83: =IF(OR(C$73="",$A83=""),"",IFERROR(SUMIFS(COBROS_DIARIOS!$K$4:$K$505,COBROS_DIARIOS!$E$4:$E$505,C$73,COBROS_DIARIOS!$F$4:$F$505,$A83,COBROS_DIARIOS!$A$4:$A$505,">="&$B$2,COBROS_DIARIOS!$A$4:$A$505,"<="&EOMONTH($B$2,0)),0)) -> 544 | D83: =IF(OR(D$73="",$A83=""),"",IFERROR(SUMIFS(COBROS_DIARIOS!$K$4:$K$505,COBROS_DIARIOS!$E$4:$E$505,D$73,COBROS_DIARIOS!$F$4:$F$505,$A83,COBROS_DIARIOS!$A$4:$A$505,">="&$B$2,COBROS_DIARIOS!$A$4:$A$505,"<="&EOMONTH($B$2,0)),0)) -> 201 | E83: =IF(OR(E$73="",$A83=""),"",IFERROR(SUMIFS(COBROS_DIARIOS!$K$4:$K$505,COBROS_DIARIOS!$E$4:$E$505,E$73,COBROS_DIARIOS!$F$4:$F$505,$A83,COBROS_DIARIOS!$A$4:$A$505,">="&$B$2,COBROS_DIARIOS!$A$4:$A$505,"<="&EOMONTH($B$2,0)),0)) -> 0 | F83: =IF(OR(F$73="",$A83=""),"",IFERROR(SUMIFS(COBROS_DIARIOS!$K$4:$K$505,COBROS_DIARIOS!$E$4:$E$505,F$73,COBROS_DIARIOS!$F$4:$F$505,$A83,COBROS_DIARIOS!$A$4:$A$505,">="&$B$2,COBROS_DIARIOS!$A$4:$A$505,"<="&EOMONTH($B$2,0)),0)) -> 0 | G83: =IF(OR(G$73="",$A83=""),"",IFERROR(SUMIFS(COBROS_DIARIOS!$K$4:$K$505,COBROS_DIARIOS!$E$4:$E$505,G$73,COBROS_DIARIOS!$F$4:$F$505,$A83,COBROS_DIARIOS!$A$4:$A$505,">="&$B$2,COBROS_DIARIOS!$A$4:$A$505,"<="&EOMONTH($B$2,0)),0)) -> 37 | H83: =IF(OR(H$73="",$A83=""),"",IFERROR(SUMIFS(COBROS_DIARIOS!$K$4:$K$505,COBROS_DIARIOS!$E$4:$E$505,H$73,COBROS_DIARIOS!$F$4:$F$505,$A83,COBROS_DIARIOS!$A$4:$A$505,">="&$B$2,COBROS_DIARIOS!$A$4:$A$505,"<="&EOMONTH($B$2,0)),0)) -> 27 | I83: =IF(OR(I$73="",$A83=""),"",IFERROR(SUMIFS(COBROS_DIARIOS!$K$4:$K$505,COBROS_DIARIOS!$E$4:$E$505,I$73,COBROS_DIARIOS!$F$4:$F$505,$A83,COBROS_DIARIOS!$A$4:$A$505,">="&$B$2,COBROS_DIARIOS!$A$4:$A$505,"<="&EOMONTH($B$2,0)),0)) -> 54 | ... Z83: =IF(OR(Z$73="",$A83=""),"",IFERROR(SUMIFS(COBROS_DIARIOS!$K$4:$K$505,COBROS_DIARIOS!$E$4:$E$505,Z$73,COBROS_DIARIOS!$F$4:$F$505,$A83,COBROS_DIARIOS!$A$4:$A$505,">="&$B$2,COBROS_DIARIOS!$A$4:$A$505,"<="&EOMONTH($B$2,0)),0)) | AA83: =IFERROR(SUM(B83:Z83),0) -> 1257
A84: =IFERROR(IF(COLORES!A14="","",COLORES!A14),"") -> Camote | B84: =IF(OR(B$73="",$A84=""),"",IFERROR(SUMIFS(COBROS_DIARIOS!$K$4:$K$505,COBROS_DIARIOS!$E$4:$E$505,B$73,COBROS_DIARIOS!$F$4:$F$505,$A84,COBROS_DIARIOS!$A$4:$A$505,">="&$B$2,COBROS_DIARIOS!$A$4:$A$505,"<="&EOMONTH($B$2,0)),0)) -> 0 | C84: =IF(OR(C$73="",$A84=""),"",IFERROR(SUMIFS(COBROS_DIARIOS!$K$4:$K$505,COBROS_DIARIOS!$E$4:$E$505,C$73,COBROS_DIARIOS!$F$4:$F$505,$A84,COBROS_DIARIOS!$A$4:$A$505,">="&$B$2,COBROS_DIARIOS!$A$4:$A$505,"<="&EOMONTH($B$2,0)),0)) -> 0 | D84: =IF(OR(D$73="",$A84=""),"",IFERROR(SUMIFS(COBROS_DIARIOS!$K$4:$K$505,COBROS_DIARIOS!$E$4:$E$505,D$73,COBROS_DIARIOS!$F$4:$F$505,$A84,COBROS_DIARIOS!$A$4:$A$505,">="&$B$2,COBROS_DIARIOS!$A$4:$A$505,"<="&EOMONTH($B$2,0)),0)) -> 0 | E84: =IF(OR(E$73="",$A84=""),"",IFERROR(SUMIFS(COBROS_DIARIOS!$K$4:$K$505,COBROS_DIARIOS!$E$4:$E$505,E$73,COBROS_DIARIOS!$F$4:$F$505,$A84,COBROS_DIARIOS!$A$4:$A$505,">="&$B$2,COBROS_DIARIOS!$A$4:$A$505,"<="&EOMONTH($B$2,0)),0)) -> 0 | F84: =IF(OR(F$73="",$A84=""),"",IFERROR(SUMIFS(COBROS_DIARIOS!$K$4:$K$505,COBROS_DIARIOS!$E$4:$E$505,F$73,COBROS_DIARIOS!$F$4:$F$505,$A84,COBROS_DIARIOS!$A$4:$A$505,">="&$B$2,COBROS_DIARIOS!$A$4:$A$505,"<="&EOMONTH($B$2,0)),0)) -> 0 | G84: =IF(OR(G$73="",$A84=""),"",IFERROR(SUMIFS(COBROS_DIARIOS!$K$4:$K$505,COBROS_DIARIOS!$E$4:$E$505,G$73,COBROS_DIARIOS!$F$4:$F$505,$A84,COBROS_DIARIOS!$A$4:$A$505,">="&$B$2,COBROS_DIARIOS!$A$4:$A$505,"<="&EOMONTH($B$2,0)),0)) -> 0 | H84: =IF(OR(H$73="",$A84=""),"",IFERROR(SUMIFS(COBROS_DIARIOS!$K$4:$K$505,COBROS_DIARIOS!$E$4:$E$505,H$73,COBROS_DIARIOS!$F$4:$F$505,$A84,COBROS_DIARIOS!$A$4:$A$505,">="&$B$2,COBROS_DIARIOS!$A$4:$A$505,"<="&EOMONTH($B$2,0)),0)) -> 0 | I84: =IF(OR(I$73="",$A84=""),"",IFERROR(SUMIFS(COBROS_DIARIOS!$K$4:$K$505,COBROS_DIARIOS!$E$4:$E$505,I$73,COBROS_DIARIOS!$F$4:$F$505,$A84,COBROS_DIARIOS!$A$4:$A$505,">="&$B$2,COBROS_DIARIOS!$A$4:$A$505,"<="&EOMONTH($B$2,0)),0)) -> 0 | ... Z84: =IF(OR(Z$73="",$A84=""),"",IFERROR(SUMIFS(COBROS_DIARIOS!$K$4:$K$505,COBROS_DIARIOS!$E$4:$E$505,Z$73,COBROS_DIARIOS!$F$4:$F$505,$A84,COBROS_DIARIOS!$A$4:$A$505,">="&$B$2,COBROS_DIARIOS!$A$4:$A$505,"<="&EOMONTH($B$2,0)),0)) | AA84: =IFERROR(SUM(B84:Z84),0) -> 0
A85: =IFERROR(IF(COLORES!A15="","",COLORES!A15),"") -> Denim | B85: =IF(OR(B$73="",$A85=""),"",IFERROR(SUMIFS(COBROS_DIARIOS!$K$4:$K$505,COBROS_DIARIOS!$E$4:$E$505,B$73,COBROS_DIARIOS!$F$4:$F$505,$A85,COBROS_DIARIOS!$A$4:$A$505,">="&$B$2,COBROS_DIARIOS!$A$4:$A$505,"<="&EOMONTH($B$2,0)),0)) -> 1153 | C85: =IF(OR(C$73="",$A85=""),"",IFERROR(SUMIFS(COBROS_DIARIOS!$K$4:$K$505,COBROS_DIARIOS!$E$4:$E$505,C$73,COBROS_DIARIOS!$F$4:$F$505,$A85,COBROS_DIARIOS!$A$4:$A$505,">="&$B$2,COBROS_DIARIOS!$A$4:$A$505,"<="&EOMONTH($B$2,0)),0)) -> 306 | D85: =IF(OR(D$73="",$A85=""),"",IFERROR(SUMIFS(COBROS_DIARIOS!$K$4:$K$505,COBROS_DIARIOS!$E$4:$E$505,D$73,COBROS_DIARIOS!$F$4:$F$505,$A85,COBROS_DIARIOS!$A$4:$A$505,">="&$B$2,COBROS_DIARIOS!$A$4:$A$505,"<="&EOMONTH($B$2,0)),0)) -> 203 | E85: =IF(OR(E$73="",$A85=""),"",IFERROR(SUMIFS(COBROS_DIARIOS!$K$4:$K$505,COBROS_DIARIOS!$E$4:$E$505,E$73,COBROS_DIARIOS!$F$4:$F$505,$A85,COBROS_DIARIOS!$A$4:$A$505,">="&$B$2,COBROS_DIARIOS!$A$4:$A$505,"<="&EOMONTH($B$2,0)),0)) -> 0 | F85: =IF(OR(F$73="",$A85=""),"",IFERROR(SUMIFS(COBROS_DIARIOS!$K$4:$K$505,COBROS_DIARIOS!$E$4:$E$505,F$73,COBROS_DIARIOS!$F$4:$F$505,$A85,COBROS_DIARIOS!$A$4:$A$505,">="&$B$2,COBROS_DIARIOS!$A$4:$A$505,"<="&EOMONTH($B$2,0)),0)) -> 0 | G85: =IF(OR(G$73="",$A85=""),"",IFERROR(SUMIFS(COBROS_DIARIOS!$K$4:$K$505,COBROS_DIARIOS!$E$4:$E$505,G$73,COBROS_DIARIOS!$F$4:$F$505,$A85,COBROS_DIARIOS!$A$4:$A$505,">="&$B$2,COBROS_DIARIOS!$A$4:$A$505,"<="&EOMONTH($B$2,0)),0)) -> 305 | H85: =IF(OR(H$73="",$A85=""),"",IFERROR(SUMIFS(COBROS_DIARIOS!$K$4:$K$505,COBROS_DIARIOS!$E$4:$E$505,H$73,COBROS_DIARIOS!$F$4:$F$505,$A85,COBROS_DIARIOS!$A$4:$A$505,">="&$B$2,COBROS_DIARIOS!$A$4:$A$505,"<="&EOMONTH($B$2,0)),0)) -> 31 | I85: =IF(OR(I$73="",$A85=""),"",IFERROR(SUMIFS(COBROS_DIARIOS!$K$4:$K$505,COBROS_DIARIOS!$E$4:$E$505,I$73,COBROS_DIARIOS!$F$4:$F$505,$A85,COBROS_DIARIOS!$A$4:$A$505,">="&$B$2,COBROS_DIARIOS!$A$4:$A$505,"<="&EOMONTH($B$2,0)),0)) -> 66 | ... Z85: =IF(OR(Z$73="",$A85=""),"",IFERROR(SUMIFS(COBROS_DIARIOS!$K$4:$K$505,COBROS_DIARIOS!$E$4:$E$505,Z$73,COBROS_DIARIOS!$F$4:$F$505,$A85,COBROS_DIARIOS!$A$4:$A$505,">="&$B$2,COBROS_DIARIOS!$A$4:$A$505,"<="&EOMONTH($B$2,0)),0)) | AA85: =IFERROR(SUM(B85:Z85),0) -> 2363
... A98: =IFERROR(IF(COLORES!A28="","",COLORES!A28),"") -> Negro 2 | B98: =IF(OR(B$73="",$A98=""),"",IFERROR(SUMIFS(COBROS_DIARIOS!$K$4:$K$505,COBROS_DIARIOS!$E$4:$E$505,B$73,COBROS_DIARIOS!$F$4:$F$505,$A98,COBROS_DIARIOS!$A$4:$A$505,">="&$B$2,COBROS_DIARIOS!$A$4:$A$505,"<="&EOMONTH($B$2,0)),0)) -> 0 | C98: =IF(OR(C$73="",$A98=""),"",IFERROR(SUMIFS(COBROS_DIARIOS!$K$4:$K$505,COBROS_DIARIOS!$E$4:$E$505,C$73,COBROS_DIARIOS!$F$4:$F$505,$A98,COBROS_DIARIOS!$A$4:$A$505,">="&$B$2,COBROS_DIARIOS!$A$4:$A$505,"<="&EOMONTH($B$2,0)),0)) -> 0 | D98: =IF(OR(D$73="",$A98=""),"",IFERROR(SUMIFS(COBROS_DIARIOS!$K$4:$K$505,COBROS_DIARIOS!$E$4:$E$505,D$73,COBROS_DIARIOS!$F$4:$F$505,$A98,COBROS_DIARIOS!$A$4:$A$505,">="&$B$2,COBROS_DIARIOS!$A$4:$A$505,"<="&EOMONTH($B$2,0)),0)) -> 0 | E98: =IF(OR(E$73="",$A98=""),"",IFERROR(SUMIFS(COBROS_DIARIOS!$K$4:$K$505,COBROS_DIARIOS!$E$4:$E$505,E$73,COBROS_DIARIOS!$F$4:$F$505,$A98,COBROS_DIARIOS!$A$4:$A$505,">="&$B$2,COBROS_DIARIOS!$A$4:$A$505,"<="&EOMONTH($B$2,0)),0)) -> 0 | F98: =IF(OR(F$73="",$A98=""),"",IFERROR(SUMIFS(COBROS_DIARIOS!$K$4:$K$505,COBROS_DIARIOS!$E$4:$E$505,F$73,COBROS_DIARIOS!$F$4:$F$505,$A98,COBROS_DIARIOS!$A$4:$A$505,">="&$B$2,COBROS_DIARIOS!$A$4:$A$505,"<="&EOMONTH($B$2,0)),0)) -> 0 | G98: =IF(OR(G$73="",$A98=""),"",IFERROR(SUMIFS(COBROS_DIARIOS!$K$4:$K$505,COBROS_DIARIOS!$E$4:$E$505,G$73,COBROS_DIARIOS!$F$4:$F$505,$A98,COBROS_DIARIOS!$A$4:$A$505,">="&$B$2,COBROS_DIARIOS!$A$4:$A$505,"<="&EOMONTH($B$2,0)),0)) -> 0 | H98: =IF(OR(H$73="",$A98=""),"",IFERROR(SUMIFS(COBROS_DIARIOS!$K$4:$K$505,COBROS_DIARIOS!$E$4:$E$505,H$73,COBROS_DIARIOS!$F$4:$F$505,$A98,COBROS_DIARIOS!$A$4:$A$505,">="&$B$2,COBROS_DIARIOS!$A$4:$A$505,"<="&EOMONTH($B$2,0)),0)) -> 0 | I98: =IF(OR(I$73="",$A98=""),"",IFERROR(SUMIFS(COBROS_DIARIOS!$K$4:$K$505,COBROS_DIARIOS!$E$4:$E$505,I$73,COBROS_DIARIOS!$F$4:$F$505,$A98,COBROS_DIARIOS!$A$4:$A$505,">="&$B$2,COBROS_DIARIOS!$A$4:$A$505,"<="&EOMONTH($B$2,0)),0)) -> 0 | ... Z98: =IF(OR(Z$73="",$A98=""),"",IFERROR(SUMIFS(COBROS_DIARIOS!$K$4:$K$505,COBROS_DIARIOS!$E$4:$E$505,Z$73,COBROS_DIARIOS!$F$4:$F$505,$A98,COBROS_DIARIOS!$A$4:$A$505,">="&$B$2,COBROS_DIARIOS!$A$4:$A$505,"<="&EOMONTH($B$2,0)),0)) | AA98: =IFERROR(SUM(B98:Z98),0) -> 0
A101: COBROS POR CLIENTE — Quién te debe (mes filtrado)
A102: CLIENTE | B102: # PRENDAS | C102: BRUTO | D102: COBRADO | E102: POR COBRAR | F102: % COBRADO
A103: =IFERROR(IF(CLIENTES!A4="","",CLIENTES!A4),"") -> OverShark | B103: =IF(A103="","",SUMIFS(COBROS_DIARIOS!$K$4:$K$505,COBROS_DIARIOS!$D$4:$D$505,A103,COBROS_DIARIOS!$A$4:$A$505,">="&$B$2,COBROS_DIARIOS!$A$4:$A$505,"<="&EOMONTH($B$2,0))) -> 30362 | C103: =IF(A103="","",SUMIFS(COBROS_DIARIOS!$M$4:$M$505,COBROS_DIARIOS!$D$4:$D$505,A103,COBROS_DIARIOS!$A$4:$A$505,">="&$B$2,COBROS_DIARIOS!$A$4:$A$505,"<="&EOMONTH($B$2,0))) -> 65691.2 | D103: =IF(A103="","",SUMIFS(COBROS_DIARIOS!$M$4:$M$505,COBROS_DIARIOS!$D$4:$D$505,A103,COBROS_DIARIOS!$A$4:$A$505,">="&$B$2,COBROS_DIARIOS!$A$4:$A$505,"<="&EOMONTH($B$2,0),COBROS_DIARIOS!$P$4:$P$505,"PAGADO")) -> 0 | E103: =IF(A103="","",SUMIFS(COBROS_DIARIOS!$M$4:$M$505,COBROS_DIARIOS!$D$4:$D$505,A103,COBROS_DIARIOS!$A$4:$A$505,">="&$B$2,COBROS_DIARIOS!$A$4:$A$505,"<="&EOMONTH($B$2,0),COBROS_DIARIOS!$P$4:$P$505,"PENDIENTE")+SUMIFS(COBROS_DIARIOS!$M$4:$M$505,COBROS_DIARIOS!$D$4:$D$505,A103,COBROS_DIARIOS!$A$4:$A$505,">="&$B$2,COBROS_DIARIOS!$A$4:$A$505,"<="&EOMONTH($B$2,0),COBROS_DIARIOS!$P$4:$P$505,"PARCIAL")+SUMIFS(COBROS_DIARIOS!$M$4:$M$505,COBROS_DIARIOS!$D$4:$D$505,A103,COBROS_DIARIOS!$A$4:$A$505,">="&$B$2,COBROS_DIARIOS!$A$4:$A$505,"<="&EOMONTH($B$2,0),COBROS_DIARIOS!$P$4:$P$505,"ENTREGADO SIN FACTURAR")) -> 63901.1 | F103: =IFERROR(IF(C103=0,"",D103/C103),"") -> 0
A104: =IFERROR(IF(CLIENTES!A5="","",CLIENTES!A5),"") -> Bravos | B104: =IF(A104="","",SUMIFS(COBROS_DIARIOS!$K$4:$K$505,COBROS_DIARIOS!$D$4:$D$505,A104,COBROS_DIARIOS!$A$4:$A$505,">="&$B$2,COBROS_DIARIOS!$A$4:$A$505,"<="&EOMONTH($B$2,0))) -> 3720 | C104: =IF(A104="","",SUMIFS(COBROS_DIARIOS!$M$4:$M$505,COBROS_DIARIOS!$D$4:$D$505,A104,COBROS_DIARIOS!$A$4:$A$505,">="&$B$2,COBROS_DIARIOS!$A$4:$A$505,"<="&EOMONTH($B$2,0))) -> 16892 | D104: =IF(A104="","",SUMIFS(COBROS_DIARIOS!$M$4:$M$505,COBROS_DIARIOS!$D$4:$D$505,A104,COBROS_DIARIOS!$A$4:$A$505,">="&$B$2,COBROS_DIARIOS!$A$4:$A$505,"<="&EOMONTH($B$2,0),COBROS_DIARIOS!$P$4:$P$505,"PAGADO")) -> 0 | E104: =IF(A104="","",SUMIFS(COBROS_DIARIOS!$M$4:$M$505,COBROS_DIARIOS!$D$4:$D$505,A104,COBROS_DIARIOS!$A$4:$A$505,">="&$B$2,COBROS_DIARIOS!$A$4:$A$505,"<="&EOMONTH($B$2,0),COBROS_DIARIOS!$P$4:$P$505,"PENDIENTE")+SUMIFS(COBROS_DIARIOS!$M$4:$M$505,COBROS_DIARIOS!$D$4:$D$505,A104,COBROS_DIARIOS!$A$4:$A$505,">="&$B$2,COBROS_DIARIOS!$A$4:$A$505,"<="&EOMONTH($B$2,0),COBROS_DIARIOS!$P$4:$P$505,"PARCIAL")+SUMIFS(COBROS_DIARIOS!$M$4:$M$505,COBROS_DIARIOS!$D$4:$D$505,A104,COBROS_DIARIOS!$A$4:$A$505,">="&$B$2,COBROS_DIARIOS!$A$4:$A$505,"<="&EOMONTH($B$2,0),COBROS_DIARIOS!$P$4:$P$505,"ENTREGADO SIN FACTURAR")) -> 16892 | F104: =IFERROR(IF(C104=0,"",D104/C104),"") -> 0
A105: =IFERROR(IF(CLIENTES!A6="","",CLIENTES!A6),"") | B105: =IF(A105="","",SUMIFS(COBROS_DIARIOS!$K$4:$K$505,COBROS_DIARIOS!$D$4:$D$505,A105,COBROS_DIARIOS!$A$4:$A$505,">="&$B$2,COBROS_DIARIOS!$A$4:$A$505,"<="&EOMONTH($B$2,0))) | C105: =IF(A105="","",SUMIFS(COBROS_DIARIOS!$M$4:$M$505,COBROS_DIARIOS!$D$4:$D$505,A105,COBROS_DIARIOS!$A$4:$A$505,">="&$B$2,COBROS_DIARIOS!$A$4:$A$505,"<="&EOMONTH($B$2,0))) | D105: =IF(A105="","",SUMIFS(COBROS_DIARIOS!$M$4:$M$505,COBROS_DIARIOS!$D$4:$D$505,A105,COBROS_DIARIOS!$A$4:$A$505,">="&$B$2,COBROS_DIARIOS!$A$4:$A$505,"<="&EOMONTH($B$2,0),COBROS_DIARIOS!$P$4:$P$505,"PAGADO")) | E105: =IF(A105="","",SUMIFS(COBROS_DIARIOS!$M$4:$M$505,COBROS_DIARIOS!$D$4:$D$505,A105,COBROS_DIARIOS!$A$4:$A$505,">="&$B$2,COBROS_DIARIOS!$A$4:$A$505,"<="&EOMONTH($B$2,0),COBROS_DIARIOS!$P$4:$P$505,"PENDIENTE")+SUMIFS(COBROS_DIARIOS!$M$4:$M$505,COBROS_DIARIOS!$D$4:$D$505,A105,COBROS_DIARIOS!$A$4:$A$505,">="&$B$2,COBROS_DIARIOS!$A$4:$A$505,"<="&EOMONTH($B$2,0),COBROS_DIARIOS!$P$4:$P$505,"PARCIAL")+SUMIFS(COBROS_DIARIOS!$M$4:$M$505,COBROS_DIARIOS!$D$4:$D$505,A105,COBROS_DIARIOS!$A$4:$A$505,">="&$B$2,COBROS_DIARIOS!$A$4:$A$505,"<="&EOMONTH($B$2,0),COBROS_DIARIOS!$P$4:$P$505,"ENTREGADO SIN FACTURAR")) | F105: =IFERROR(IF(C105=0,"",D105/C105),"")
A106: =IFERROR(IF(CLIENTES!A7="","",CLIENTES!A7),"") | B106: =IF(A106="","",SUMIFS(COBROS_DIARIOS!$K$4:$K$505,COBROS_DIARIOS!$D$4:$D$505,A106,COBROS_DIARIOS!$A$4:$A$505,">="&$B$2,COBROS_DIARIOS!$A$4:$A$505,"<="&EOMONTH($B$2,0))) | C106: =IF(A106="","",SUMIFS(COBROS_DIARIOS!$M$4:$M$505,COBROS_DIARIOS!$D$4:$D$505,A106,COBROS_DIARIOS!$A$4:$A$505,">="&$B$2,COBROS_DIARIOS!$A$4:$A$505,"<="&EOMONTH($B$2,0))) | D106: =IF(A106="","",SUMIFS(COBROS_DIARIOS!$M$4:$M$505,COBROS_DIARIOS!$D$4:$D$505,A106,COBROS_DIARIOS!$A$4:$A$505,">="&$B$2,COBROS_DIARIOS!$A$4:$A$505,"<="&EOMONTH($B$2,0),COBROS_DIARIOS!$P$4:$P$505,"PAGADO")) | E106: =IF(A106="","",SUMIFS(COBROS_DIARIOS!$M$4:$M$505,COBROS_DIARIOS!$D$4:$D$505,A106,COBROS_DIARIOS!$A$4:$A$505,">="&$B$2,COBROS_DIARIOS!$A$4:$A$505,"<="&EOMONTH($B$2,0),COBROS_DIARIOS!$P$4:$P$505,"PENDIENTE")+SUMIFS(COBROS_DIARIOS!$M$4:$M$505,COBROS_DIARIOS!$D$4:$D$505,A106,COBROS_DIARIOS!$A$4:$A$505,">="&$B$2,COBROS_DIARIOS!$A$4:$A$505,"<="&EOMONTH($B$2,0),COBROS_DIARIOS!$P$4:$P$505,"PARCIAL")+SUMIFS(COBROS_DIARIOS!$M$4:$M$505,COBROS_DIARIOS!$D$4:$D$505,A106,COBROS_DIARIOS!$A$4:$A$505,">="&$B$2,COBROS_DIARIOS!$A$4:$A$505,"<="&EOMONTH($B$2,0),COBROS_DIARIOS!$P$4:$P$505,"ENTREGADO SIN FACTURAR")) | F106: =IFERROR(IF(C106=0,"",D106/C106),"")
A107: =IFERROR(IF(CLIENTES!A8="","",CLIENTES!A8),"") | B107: =IF(A107="","",SUMIFS(COBROS_DIARIOS!$K$4:$K$505,COBROS_DIARIOS!$D$4:$D$505,A107,COBROS_DIARIOS!$A$4:$A$505,">="&$B$2,COBROS_DIARIOS!$A$4:$A$505,"<="&EOMONTH($B$2,0))) | C107: =IF(A107="","",SUMIFS(COBROS_DIARIOS!$M$4:$M$505,COBROS_DIARIOS!$D$4:$D$505,A107,COBROS_DIARIOS!$A$4:$A$505,">="&$B$2,COBROS_DIARIOS!$A$4:$A$505,"<="&EOMONTH($B$2,0))) | D107: =IF(A107="","",SUMIFS(COBROS_DIARIOS!$M$4:$M$505,COBROS_DIARIOS!$D$4:$D$505,A107,COBROS_DIARIOS!$A$4:$A$505,">="&$B$2,COBROS_DIARIOS!$A$4:$A$505,"<="&EOMONTH($B$2,0),COBROS_DIARIOS!$P$4:$P$505,"PAGADO")) | E107: =IF(A107="","",SUMIFS(COBROS_DIARIOS!$M$4:$M$505,COBROS_DIARIOS!$D$4:$D$505,A107,COBROS_DIARIOS!$A$4:$A$505,">="&$B$2,COBROS_DIARIOS!$A$4:$A$505,"<="&EOMONTH($B$2,0),COBROS_DIARIOS!$P$4:$P$505,"PENDIENTE")+SUMIFS(COBROS_DIARIOS!$M$4:$M$505,COBROS_DIARIOS!$D$4:$D$505,A107,COBROS_DIARIOS!$A$4:$A$505,">="&$B$2,COBROS_DIARIOS!$A$4:$A$505,"<="&EOMONTH($B$2,0),COBROS_DIARIOS!$P$4:$P$505,"PARCIAL")+SUMIFS(COBROS_DIARIOS!$M$4:$M$505,COBROS_DIARIOS!$D$4:$D$505,A107,COBROS_DIARIOS!$A$4:$A$505,">="&$B$2,COBROS_DIARIOS!$A$4:$A$505,"<="&EOMONTH($B$2,0),COBROS_DIARIOS!$P$4:$P$505,"ENTREGADO SIN FACTURAR")) | F107: =IFERROR(IF(C107=0,"",D107/C107),"")
A108: =IFERROR(IF(CLIENTES!A9="","",CLIENTES!A9),"") | B108: =IF(A108="","",SUMIFS(COBROS_DIARIOS!$K$4:$K$505,COBROS_DIARIOS!$D$4:$D$505,A108,COBROS_DIARIOS!$A$4:$A$505,">="&$B$2,COBROS_DIARIOS!$A$4:$A$505,"<="&EOMONTH($B$2,0))) | C108: =IF(A108="","",SUMIFS(COBROS_DIARIOS!$M$4:$M$505,COBROS_DIARIOS!$D$4:$D$505,A108,COBROS_DIARIOS!$A$4:$A$505,">="&$B$2,COBROS_DIARIOS!$A$4:$A$505,"<="&EOMONTH($B$2,0))) | D108: =IF(A108="","",SUMIFS(COBROS_DIARIOS!$M$4:$M$505,COBROS_DIARIOS!$D$4:$D$505,A108,COBROS_DIARIOS!$A$4:$A$505,">="&$B$2,COBROS_DIARIOS!$A$4:$A$505,"<="&EOMONTH($B$2,0),COBROS_DIARIOS!$P$4:$P$505,"PAGADO")) | E108: =IF(A108="","",SUMIFS(COBROS_DIARIOS!$M$4:$M$505,COBROS_DIARIOS!$D$4:$D$505,A108,COBROS_DIARIOS!$A$4:$A$505,">="&$B$2,COBROS_DIARIOS!$A$4:$A$505,"<="&EOMONTH($B$2,0),COBROS_DIARIOS!$P$4:$P$505,"PENDIENTE")+SUMIFS(COBROS_DIARIOS!$M$4:$M$505,COBROS_DIARIOS!$D$4:$D$505,A108,COBROS_DIARIOS!$A$4:$A$505,">="&$B$2,COBROS_DIARIOS!$A$4:$A$505,"<="&EOMONTH($B$2,0),COBROS_DIARIOS!$P$4:$P$505,"PARCIAL")+SUMIFS(COBROS_DIARIOS!$M$4:$M$505,COBROS_DIARIOS!$D$4:$D$505,A108,COBROS_DIARIOS!$A$4:$A$505,">="&$B$2,COBROS_DIARIOS!$A$4:$A$505,"<="&EOMONTH($B$2,0),COBROS_DIARIOS!$P$4:$P$505,"ENTREGADO SIN FACTURAR")) | F108: =IFERROR(IF(C108=0,"",D108/C108),"")
A109: =IFERROR(IF(CLIENTES!A10="","",CLIENTES!A10),"") | B109: =IF(A109="","",SUMIFS(COBROS_DIARIOS!$K$4:$K$505,COBROS_DIARIOS!$D$4:$D$505,A109,COBROS_DIARIOS!$A$4:$A$505,">="&$B$2,COBROS_DIARIOS!$A$4:$A$505,"<="&EOMONTH($B$2,0))) | C109: =IF(A109="","",SUMIFS(COBROS_DIARIOS!$M$4:$M$505,COBROS_DIARIOS!$D$4:$D$505,A109,COBROS_DIARIOS!$A$4:$A$505,">="&$B$2,COBROS_DIARIOS!$A$4:$A$505,"<="&EOMONTH($B$2,0))) | D109: =IF(A109="","",SUMIFS(COBROS_DIARIOS!$M$4:$M$505,COBROS_DIARIOS!$D$4:$D$505,A109,COBROS_DIARIOS!$A$4:$A$505,">="&$B$2,COBROS_DIARIOS!$A$4:$A$505,"<="&EOMONTH($B$2,0),COBROS_DIARIOS!$P$4:$P$505,"PAGADO")) | E109: =IF(A109="","",SUMIFS(COBROS_DIARIOS!$M$4:$M$505,COBROS_DIARIOS!$D$4:$D$505,A109,COBROS_DIARIOS!$A$4:$A$505,">="&$B$2,COBROS_DIARIOS!$A$4:$A$505,"<="&EOMONTH($B$2,0),COBROS_DIARIOS!$P$4:$P$505,"PENDIENTE")+SUMIFS(COBROS_DIARIOS!$M$4:$M$505,COBROS_DIARIOS!$D$4:$D$505,A109,COBROS_DIARIOS!$A$4:$A$505,">="&$B$2,COBROS_DIARIOS!$A$4:$A$505,"<="&EOMONTH($B$2,0),COBROS_DIARIOS!$P$4:$P$505,"PARCIAL")+SUMIFS(COBROS_DIARIOS!$M$4:$M$505,COBROS_DIARIOS!$D$4:$D$505,A109,COBROS_DIARIOS!$A$4:$A$505,">="&$B$2,COBROS_DIARIOS!$A$4:$A$505,"<="&EOMONTH($B$2,0),COBROS_DIARIOS!$P$4:$P$505,"ENTREGADO SIN FACTURAR")) | F109: =IFERROR(IF(C109=0,"",D109/C109),"")
A110: =IFERROR(IF(CLIENTES!A11="","",CLIENTES!A11),"") | B110: =IF(A110="","",SUMIFS(COBROS_DIARIOS!$K$4:$K$505,COBROS_DIARIOS!$D$4:$D$505,A110,COBROS_DIARIOS!$A$4:$A$505,">="&$B$2,COBROS_DIARIOS!$A$4:$A$505,"<="&EOMONTH($B$2,0))) | C110: =IF(A110="","",SUMIFS(COBROS_DIARIOS!$M$4:$M$505,COBROS_DIARIOS!$D$4:$D$505,A110,COBROS_DIARIOS!$A$4:$A$505,">="&$B$2,COBROS_DIARIOS!$A$4:$A$505,"<="&EOMONTH($B$2,0))) | D110: =IF(A110="","",SUMIFS(COBROS_DIARIOS!$M$4:$M$505,COBROS_DIARIOS!$D$4:$D$505,A110,COBROS_DIARIOS!$A$4:$A$505,">="&$B$2,COBROS_DIARIOS!$A$4:$A$505,"<="&EOMONTH($B$2,0),COBROS_DIARIOS!$P$4:$P$505,"PAGADO")) | E110: =IF(A110="","",SUMIFS(COBROS_DIARIOS!$M$4:$M$505,COBROS_DIARIOS!$D$4:$D$505,A110,COBROS_DIARIOS!$A$4:$A$505,">="&$B$2,COBROS_DIARIOS!$A$4:$A$505,"<="&EOMONTH($B$2,0),COBROS_DIARIOS!$P$4:$P$505,"PENDIENTE")+SUMIFS(COBROS_DIARIOS!$M$4:$M$505,COBROS_DIARIOS!$D$4:$D$505,A110,COBROS_DIARIOS!$A$4:$A$505,">="&$B$2,COBROS_DIARIOS!$A$4:$A$505,"<="&EOMONTH($B$2,0),COBROS_DIARIOS!$P$4:$P$505,"PARCIAL")+SUMIFS(COBROS_DIARIOS!$M$4:$M$505,COBROS_DIARIOS!$D$4:$D$505,A110,COBROS_DIARIOS!$A$4:$A$505,">="&$B$2,COBROS_DIARIOS!$A$4:$A$505,"<="&EOMONTH($B$2,0),COBROS_DIARIOS!$P$4:$P$505,"ENTREGADO SIN FACTURAR")) | F110: =IFERROR(IF(C110=0,"",D110/C110),"")
A111: =IFERROR(IF(CLIENTES!A12="","",CLIENTES!A12),"") | B111: =IF(A111="","",SUMIFS(COBROS_DIARIOS!$K$4:$K$505,COBROS_DIARIOS!$D$4:$D$505,A111,COBROS_DIARIOS!$A$4:$A$505,">="&$B$2,COBROS_DIARIOS!$A$4:$A$505,"<="&EOMONTH($B$2,0))) | C111: =IF(A111="","",SUMIFS(COBROS_DIARIOS!$M$4:$M$505,COBROS_DIARIOS!$D$4:$D$505,A111,COBROS_DIARIOS!$A$4:$A$505,">="&$B$2,COBROS_DIARIOS!$A$4:$A$505,"<="&EOMONTH($B$2,0))) | D111: =IF(A111="","",SUMIFS(COBROS_DIARIOS!$M$4:$M$505,COBROS_DIARIOS!$D$4:$D$505,A111,COBROS_DIARIOS!$A$4:$A$505,">="&$B$2,COBROS_DIARIOS!$A$4:$A$505,"<="&EOMONTH($B$2,0),COBROS_DIARIOS!$P$4:$P$505,"PAGADO")) | E111: =IF(A111="","",SUMIFS(COBROS_DIARIOS!$M$4:$M$505,COBROS_DIARIOS!$D$4:$D$505,A111,COBROS_DIARIOS!$A$4:$A$505,">="&$B$2,COBROS_DIARIOS!$A$4:$A$505,"<="&EOMONTH($B$2,0),COBROS_DIARIOS!$P$4:$P$505,"PENDIENTE")+SUMIFS(COBROS_DIARIOS!$M$4:$M$505,COBROS_DIARIOS!$D$4:$D$505,A111,COBROS_DIARIOS!$A$4:$A$505,">="&$B$2,COBROS_DIARIOS!$A$4:$A$505,"<="&EOMONTH($B$2,0),COBROS_DIARIOS!$P$4:$P$505,"PARCIAL")+SUMIFS(COBROS_DIARIOS!$M$4:$M$505,COBROS_DIARIOS!$D$4:$D$505,A111,COBROS_DIARIOS!$A$4:$A$505,">="&$B$2,COBROS_DIARIOS!$A$4:$A$505,"<="&EOMONTH($B$2,0),COBROS_DIARIOS!$P$4:$P$505,"ENTREGADO SIN FACTURAR")) | F111: =IFERROR(IF(C111=0,"",D111/C111),"")
A112: =IFERROR(IF(CLIENTES!A13="","",CLIENTES!A13),"") | B112: =IF(A112="","",SUMIFS(COBROS_DIARIOS!$K$4:$K$505,COBROS_DIARIOS!$D$4:$D$505,A112,COBROS_DIARIOS!$A$4:$A$505,">="&$B$2,COBROS_DIARIOS!$A$4:$A$505,"<="&EOMONTH($B$2,0))) | C112: =IF(A112="","",SUMIFS(COBROS_DIARIOS!$M$4:$M$505,COBROS_DIARIOS!$D$4:$D$505,A112,COBROS_DIARIOS!$A$4:$A$505,">="&$B$2,COBROS_DIARIOS!$A$4:$A$505,"<="&EOMONTH($B$2,0))) | D112: =IF(A112="","",SUMIFS(COBROS_DIARIOS!$M$4:$M$505,COBROS_DIARIOS!$D$4:$D$505,A112,COBROS_DIARIOS!$A$4:$A$505,">="&$B$2,COBROS_DIARIOS!$A$4:$A$505,"<="&EOMONTH($B$2,0),COBROS_DIARIOS!$P$4:$P$505,"PAGADO")) | E112: =IF(A112="","",SUMIFS(COBROS_DIARIOS!$M$4:$M$505,COBROS_DIARIOS!$D$4:$D$505,A112,COBROS_DIARIOS!$A$4:$A$505,">="&$B$2,COBROS_DIARIOS!$A$4:$A$505,"<="&EOMONTH($B$2,0),COBROS_DIARIOS!$P$4:$P$505,"PENDIENTE")+SUMIFS(COBROS_DIARIOS!$M$4:$M$505,COBROS_DIARIOS!$D$4:$D$505,A112,COBROS_DIARIOS!$A$4:$A$505,">="&$B$2,COBROS_DIARIOS!$A$4:$A$505,"<="&EOMONTH($B$2,0),COBROS_DIARIOS!$P$4:$P$505,"PARCIAL")+SUMIFS(COBROS_DIARIOS!$M$4:$M$505,COBROS_DIARIOS!$D$4:$D$505,A112,COBROS_DIARIOS!$A$4:$A$505,">="&$B$2,COBROS_DIARIOS!$A$4:$A$505,"<="&EOMONTH($B$2,0),COBROS_DIARIOS!$P$4:$P$505,"ENTREGADO SIN FACTURAR")) | F112: =IFERROR(IF(C112=0,"",D112/C112),"")
A113: TOTAL ⇒ | B113: =SUM(B103:B112) -> 34082 | C113: =SUM(C103:C112) -> 82583.2 | D113: =SUM(D103:D112) -> 0 | E113: =SUM(E103:E112) -> 80793.1 | F113: =IFERROR(D113/C113,0) -> 0
A200: =IFERROR(IF(COLORES!A4="","",COLORES!A4),"") -> Negro | B200: =IF(A200="","",SUMIFS(COBROS_DIARIOS!$K$4:$K$505,COBROS_DIARIOS!$F$4:$F$505,A200,COBROS_DIARIOS!$A$4:$A$505,">="&$B$2,COBROS_DIARIOS!$A$4:$A$505,"<="&EOMONTH($B$2,0))) -> 6201 | C200: =IF(A200="","",SUMIFS(COBROS_DIARIOS!$M$4:$M$505,COBROS_DIARIOS!$F$4:$F$505,A200,COBROS_DIARIOS!$A$4:$A$505,">="&$B$2,COBROS_DIARIOS!$A$4:$A$505,"<="&EOMONTH($B$2,0))) -> 16120.7 | D200: =IF(A200="","",B200-ROW()/100000) -> 6200.998
A201: =IFERROR(IF(COLORES!A5="","",COLORES!A5),"") -> Perla | B201: =IF(A201="","",SUMIFS(COBROS_DIARIOS!$K$4:$K$505,COBROS_DIARIOS!$F$4:$F$505,A201,COBROS_DIARIOS!$A$4:$A$505,">="&$B$2,COBROS_DIARIOS!$A$4:$A$505,"<="&EOMONTH($B$2,0))) -> 3124 | C201: =IF(A201="","",SUMIFS(COBROS_DIARIOS!$M$4:$M$505,COBROS_DIARIOS!$F$4:$F$505,A201,COBROS_DIARIOS!$A$4:$A$505,">="&$B$2,COBROS_DIARIOS!$A$4:$A$505,"<="&EOMONTH($B$2,0))) -> 6951.7 | D201: =IF(A201="","",B201-ROW()/100000) -> 3123.998
A202: =IFERROR(IF(COLORES!A6="","",COLORES!A6),"") -> Blanco | B202: =IF(A202="","",SUMIFS(COBROS_DIARIOS!$K$4:$K$505,COBROS_DIARIOS!$F$4:$F$505,A202,COBROS_DIARIOS!$A$4:$A$505,">="&$B$2,COBROS_DIARIOS!$A$4:$A$505,"<="&EOMONTH($B$2,0))) -> 0 | C202: =IF(A202="","",SUMIFS(COBROS_DIARIOS!$M$4:$M$505,COBROS_DIARIOS!$F$4:$F$505,A202,COBROS_DIARIOS!$A$4:$A$505,">="&$B$2,COBROS_DIARIOS!$A$4:$A$505,"<="&EOMONTH($B$2,0))) -> 0 | D202: =IF(A202="","",B202-ROW()/100000) -> -0.00202
A203: =IFERROR(IF(COLORES!A7="","",COLORES!A7),"") -> Azul | B203: =IF(A203="","",SUMIFS(COBROS_DIARIOS!$K$4:$K$505,COBROS_DIARIOS!$F$4:$F$505,A203,COBROS_DIARIOS!$A$4:$A$505,">="&$B$2,COBROS_DIARIOS!$A$4:$A$505,"<="&EOMONTH($B$2,0))) -> 0 | C203: =IF(A203="","",SUMIFS(COBROS_DIARIOS!$M$4:$M$505,COBROS_DIARIOS!$F$4:$F$505,A203,COBROS_DIARIOS!$A$4:$A$505,">="&$B$2,COBROS_DIARIOS!$A$4:$A$505,"<="&EOMONTH($B$2,0))) -> 0 | D203: =IF(A203="","",B203-ROW()/100000) -> -0.00203
A204: =IFERROR(IF(COLORES!A8="","",COLORES!A8),"") -> Beige | B204: =IF(A204="","",SUMIFS(COBROS_DIARIOS!$K$4:$K$505,COBROS_DIARIOS!$F$4:$F$505,A204,COBROS_DIARIOS!$A$4:$A$505,">="&$B$2,COBROS_DIARIOS!$A$4:$A$505,"<="&EOMONTH($B$2,0))) -> 1871 | C204: =IF(A204="","",SUMIFS(COBROS_DIARIOS!$M$4:$M$505,COBROS_DIARIOS!$F$4:$F$505,A204,COBROS_DIARIOS!$A$4:$A$505,">="&$B$2,COBROS_DIARIOS!$A$4:$A$505,"<="&EOMONTH($B$2,0))) -> 4322.9 | D204: =IF(A204="","",B204-ROW()/100000) -> 1870.998
A205: =IFERROR(IF(COLORES!A9="","",COLORES!A9),"") -> Melange | B205: =IF(A205="","",SUMIFS(COBROS_DIARIOS!$K$4:$K$505,COBROS_DIARIOS!$F$4:$F$505,A205,COBROS_DIARIOS!$A$4:$A$505,">="&$B$2,COBROS_DIARIOS!$A$4:$A$505,"<="&EOMONTH($B$2,0))) -> 692 | C205: =IF(A205="","",SUMIFS(COBROS_DIARIOS!$M$4:$M$505,COBROS_DIARIOS!$F$4:$F$505,A205,COBROS_DIARIOS!$A$4:$A$505,">="&$B$2,COBROS_DIARIOS!$A$4:$A$505,"<="&EOMONTH($B$2,0))) -> 2536 | D205: =IF(A205="","",B205-ROW()/100000) -> 691.99795
A206: =IFERROR(IF(COLORES!A10="","",COLORES!A10),"") -> Botella | B206: =IF(A206="","",SUMIFS(COBROS_DIARIOS!$K$4:$K$505,COBROS_DIARIOS!$F$4:$F$505,A206,COBROS_DIARIOS!$A$4:$A$505,">="&$B$2,COBROS_DIARIOS!$A$4:$A$505,"<="&EOMONTH($B$2,0))) -> 2100 | C206: =IF(A206="","",SUMIFS(COBROS_DIARIOS!$M$4:$M$505,COBROS_DIARIOS!$F$4:$F$505,A206,COBROS_DIARIOS!$A$4:$A$505,">="&$B$2,COBROS_DIARIOS!$A$4:$A$505,"<="&EOMONTH($B$2,0))) -> 6356.1 | D206: =IF(A206="","",B206-ROW()/100000) -> 2099.9979
A207: =IFERROR(IF(COLORES!A11="","",COLORES!A11),"") -> Pacay | B207: =IF(A207="","",SUMIFS(COBROS_DIARIOS!$K$4:$K$505,COBROS_DIARIOS!$F$4:$F$505,A207,COBROS_DIARIOS!$A$4:$A$505,">="&$B$2,COBROS_DIARIOS!$A$4:$A$505,"<="&EOMONTH($B$2,0))) -> 0 | C207: =IF(A207="","",SUMIFS(COBROS_DIARIOS!$M$4:$M$505,COBROS_DIARIOS!$F$4:$F$505,A207,COBROS_DIARIOS!$A$4:$A$505,">="&$B$2,COBROS_DIARIOS!$A$4:$A$505,"<="&EOMONTH($B$2,0))) -> 0 | D207: =IF(A207="","",B207-ROW()/100000) -> -0.00207
A208: =IFERROR(IF(COLORES!A12="","",COLORES!A12),"") -> V. Pacay | B208: =IF(A208="","",SUMIFS(COBROS_DIARIOS!$K$4:$K$505,COBROS_DIARIOS!$F$4:$F$505,A208,COBROS_DIARIOS!$A$4:$A$505,">="&$B$2,COBROS_DIARIOS!$A$4:$A$505,"<="&EOMONTH($B$2,0))) -> 1337 | C208: =IF(A208="","",SUMIFS(COBROS_DIARIOS!$M$4:$M$505,COBROS_DIARIOS!$F$4:$F$505,A208,COBROS_DIARIOS!$A$4:$A$505,">="&$B$2,COBROS_DIARIOS!$A$4:$A$505,"<="&EOMONTH($B$2,0))) -> 3456.3 | D208: =IF(A208="","",B208-ROW()/100000) -> 1336.9979
A209: =IFERROR(IF(COLORES!A13="","",COLORES!A13),"") -> Cemento | B209: =IF(A209="","",SUMIFS(COBROS_DIARIOS!$K$4:$K$505,COBROS_DIARIOS!$F$4:$F$505,A209,COBROS_DIARIOS!$A$4:$A$505,">="&$B$2,COBROS_DIARIOS!$A$4:$A$505,"<="&EOMONTH($B$2,0))) -> 1257 | C209: =IF(A209="","",SUMIFS(COBROS_DIARIOS!$M$4:$M$505,COBROS_DIARIOS!$F$4:$F$505,A209,COBROS_DIARIOS!$A$4:$A$505,">="&$B$2,COBROS_DIARIOS!$A$4:$A$505,"<="&EOMONTH($B$2,0))) -> 2260.2 | D209: =IF(A209="","",B209-ROW()/100000) -> 1256.9979
A210: =IFERROR(IF(COLORES!A14="","",COLORES!A14),"") -> Camote | B210: =IF(A210="","",SUMIFS(COBROS_DIARIOS!$K$4:$K$505,COBROS_DIARIOS!$F$4:$F$505,A210,COBROS_DIARIOS!$A$4:$A$505,">="&$B$2,COBROS_DIARIOS!$A$4:$A$505,"<="&EOMONTH($B$2,0))) -> 0 | C210: =IF(A210="","",SUMIFS(COBROS_DIARIOS!$M$4:$M$505,COBROS_DIARIOS!$F$4:$F$505,A210,COBROS_DIARIOS!$A$4:$A$505,">="&$B$2,COBROS_DIARIOS!$A$4:$A$505,"<="&EOMONTH($B$2,0))) -> 0 | D210: =IF(A210="","",B210-ROW()/100000) -> -0.0021
A211: =IFERROR(IF(COLORES!A15="","",COLORES!A15),"") -> Denim | B211: =IF(A211="","",SUMIFS(COBROS_DIARIOS!$K$4:$K$505,COBROS_DIARIOS!$F$4:$F$505,A211,COBROS_DIARIOS!$A$4:$A$505,">="&$B$2,COBROS_DIARIOS!$A$4:$A$505,"<="&EOMONTH($B$2,0))) -> 2363 | C211: =IF(A211="","",SUMIFS(COBROS_DIARIOS!$M$4:$M$505,COBROS_DIARIOS!$F$4:$F$505,A211,COBROS_DIARIOS!$A$4:$A$505,">="&$B$2,COBROS_DIARIOS!$A$4:$A$505,"<="&EOMONTH($B$2,0))) -> 4836.2 | D211: =IF(A211="","",B211-ROW()/100000) -> 2362.9979
... A249: =IFERROR(IF(COLORES!A53="","",COLORES!A53),"") | B249: =IF(A249="","",SUMIFS(COBROS_DIARIOS!$K$4:$K$505,COBROS_DIARIOS!$F$4:$F$505,A249,COBROS_DIARIOS!$A$4:$A$505,">="&$B$2,COBROS_DIARIOS!$A$4:$A$505,"<="&EOMONTH($B$2,0))) | C249: =IF(A249="","",SUMIFS(COBROS_DIARIOS!$M$4:$M$505,COBROS_DIARIOS!$F$4:$F$505,A249,COBROS_DIARIOS!$A$4:$A$505,">="&$B$2,COBROS_DIARIOS!$A$4:$A$505,"<="&EOMONTH($B$2,0))) | D249: =IF(A249="","",B249-ROW()/100000)
