Workbook
Name LISTA_PROVEEDORES: PROVEEDORES!$A$4:$A$52
Name LISTA_PRODUCTOS: PRODUCTOS!$A$4:$A$52
Name LISTA_CLIENTES: CLIENTES!$A$4:$A$9
Name LISTA_DESTINOS: PRODUCTOS!$N$4:$N$52
Name LISTA_CLIENTES_FILTRO: CLIENTES!$G$4:$G$10
Name LISTA_COLORES: COLORES!$A$4:$A$102
Name LISTA_TELAS: TELAS!$A$4:$A$32

Sheet MOVIMIENTOS
A1: MOVIMIENTOS DIARIOS — Llenar SOLO esta hoja (cardista)
A2: Fecha · Tipo · Cliente · Tela · Color · Rollos. Para INGRESO también: Proveedor · N° Factura · Costo Real. El sistema calcula Kg, Precio y Total automáticamente.
A3: FECHA | B3: TIPO | C3: CLIENTE | D3: TELA | E3: COLOR | F3: ROLLOS | G3: KG TOTAL | H3: CATEG. COLOR | I3: PRECIO/KG | J3: TOTAL S/. | K3: STOCK ANTES (rollos) | L3: STOCK DESPUÉS (rollos) | M3: RESPONSABLE | N3: NOTAS | O3: PROVEEDOR | P3: N° FACTURA | Q3: COSTO REAL FACT. S/. | R3: DIFERENCIA % (real vs teórico)
A4: 46146 | B4: INGRESO | C4: OverShark | D4: jersey 30/1 | E4: Negro | F4: 29 | G4: =IFERROR(F4*VLOOKUP(D4,TELAS!$A$4:$C$32,3,FALSE()),0) -> 580 | H4: =IFERROR(VLOOKUP(E4,COLORES!$A$4:$B$102,2,FALSE()),"") -> OSCURO | I4: =IFERROR(IF(H4="OSCURO",VLOOKUP(D4,PRECIOS!$A$4:$F$32,2,FALSE()),IF(H4="CLARO",VLOOKUP(D4,PRECIOS!$A$4:$F$32,3,FALSE()),IF(H4="MELANGE",VLOOKUP(D4,PRECIOS!$A$4:$F$32,4,FALSE()),IF(H4="PPT",VLOOKUP(D4,PRECIOS!$A$4:$F$32,5,FALSE()),0)))),0) -> 24 | J4: =IFERROR(G4*I4,0) -> 13920 | K4: =0 -> 0 | L4: =IF(C4="",0,K4+IF(OR(B4="INGRESO",B4="DE REPROCESO",B4="AJUSTE+"),F4,IF(OR(B4="A CORTE",B4="A REPROCESO",B4="MUESTRA",B4="AJUSTE-"),-F4,0))) -> 29 | M4: tomas | O4: progreso | R4: =IF(OR(Q4="",Q4=0,J4=0),"",(Q4-J4)/J4)
A5: 46146 | B5: INGRESO | C5: OverShark | D5: jersey 30/1 | E5: Perla | F5: 48 | G5: =IFERROR(F5*VLOOKUP(D5,TELAS!$A$4:$C$32,3,FALSE()),0) -> 960 | H5: =IFERROR(VLOOKUP(E5,COLORES!$A$4:$B$102,2,FALSE()),"") -> PPT | I5: =IFERROR(IF(H5="OSCURO",VLOOKUP(D5,PRECIOS!$A$4:$F$32,2,FALSE()),IF(H5="CLARO",VLOOKUP(D5,PRECIOS!$A$4:$F$32,3,FALSE()),IF(H5="MELANGE",VLOOKUP(D5,PRECIOS!$A$4:$F$32,4,FALSE()),IF(H5="PPT",VLOOKUP(D5,PRECIOS!$A$4:$F$32,5,FALSE()),0)))),0) -> 18 | J5: =IFERROR(G5*I5,0) -> 17280 | K5: =IFERROR(IF(C5="",0,SUMIFS($F$4,$C$4,C5,$D$4,D5,$E$4,E5,$B$4,"INGRESO")+SUMIFS($F$4,$C$4,C5,$D$4,D5,$E$4,E5,$B$4,"DE REPROCESO")+SUMIFS($F$4,$C$4,C5,$D$4,D5,$E$4,E5,$B$4,"AJUSTE+")-SUMIFS($F$4,$C$4,C5,$D$4,D5,$E$4,E5,$B$4,"A CORTE")-SUMIFS($F$4,$C$4,C5,$D$4,D5,$E$4,E5,$B$4,"A REPROCESO")-SUMIFS($F$4,$C$4,C5,$D$4,D5,$E$4,E5,$B$4,"MUESTRA")-SUMIFS($F$4,$C$4,C5,$D$4,D5,$E$4,E5,$B$4,"AJUSTE-")),0) -> 0 | L5: =IF(C5="",0,K5+IF(OR(B5="INGRESO",B5="DE REPROCESO",B5="AJUSTE+"),F5,IF(OR(B5="A CORTE",B5="A REPROCESO",B5="MUESTRA",B5="AJUSTE-"),-F5,0))) -> 48 | M5: tomas | O5: progreso | R5: =IF(OR(Q5="",Q5=0,J5=0),"",(Q5-J5)/J5)
A6: 46146 | B6: INGRESO | C6: OverShark | D6: jersey 30/1 | E6: Azul | F6: 10 | G6: =IFERROR(F6*VLOOKUP(D6,TELAS!$A$4:$C$32,3,FALSE()),0) -> 200 | H6: =IFERROR(VLOOKUP(E6,COLORES!$A$4:$B$102,2,FALSE()),"") -> OSCURO | I6: =IFERROR(IF(H6="OSCURO",VLOOKUP(D6,PRECIOS!$A$4:$F$32,2,FALSE()),IF(H6="CLARO",VLOOKUP(D6,PRECIOS!$A$4:$F$32,3,FALSE()),IF(H6="MELANGE",VLOOKUP(D6,PRECIOS!$A$4:$F$32,4,FALSE()),IF(H6="PPT",VLOOKUP(D6,PRECIOS!$A$4:$F$32,5,FALSE()),0)))),0) -> 24 | J6: =IFERROR(G6*I6,0) -> 4800 | K6: =IFERROR(IF(C6="",0,SUMIFS($F$4:$F$5,$C$4:$C$5,C6,$D$4:$D$5,D6,$E$4:$E$5,E6,$B$4:$B$5,"INGRESO")+SUMIFS($F$4:$F$5,$C$4:$C$5,C6,$D$4:$D$5,D6,$E$4:$E$5,E6,$B$4:$B$5,"DE REPROCESO")+SUMIFS($F$4:$F$5,$C$4:$C$5,C6,$D$4:$D$5,D6,$E$4:$E$5,E6,$B$4:$B$5,"AJUSTE+")-SUMIFS($F$4:$F$5,$C$4:$C$5,C6,$D$4:$D$5,D6,$E$4:$E$5,E6,$B$4:$B$5,"A CORTE")-SUMIFS($F$4:$F$5,$C$4:$C$5,C6,$D$4:$D$5,D6,$E$4:$E$5,E6,$B$4:$B$5,"A REPROCESO")-SUMIFS($F$4:$F$5,$C$4:$C$5,C6,$D$4:$D$5,D6,$E$4:$E$5,E6,$B$4:$B$5,"MUESTRA")-SUMIFS($F$4:$F$5,$C$4:$C$5,C6,$D$4:$D$5,D6,$E$4:$E$5,E6,$B$4:$B$5,"AJUSTE-")),0) -> 0 | L6: =IF(C6="",0,K6+IF(OR(B6="INGRESO",B6="DE REPROCESO",B6="AJUSTE+"),F6,IF(OR(B6="A CORTE",B6="A REPROCESO",B6="MUESTRA",B6="AJUSTE-"),-F6,0))) -> 10 | M6: tomas | O6: progreso | R6: =IF(OR(Q6="",Q6=0,J6=0),"",(Q6-J6)/J6)
A7: 46146 | B7: INGRESO | C7: OverShark | D7: jersey 30/1 | E7: Botella | F7: 15 | G7: =IFERROR(F7*VLOOKUP(D7,TELAS!$A$4:$C$32,3,FALSE()),0) -> 300 | H7: =IFERROR(VLOOKUP(E7,COLORES!$A$4:$B$102,2,FALSE()),"") -> OSCURO | I7: =IFERROR(IF(H7="OSCURO",VLOOKUP(D7,PRECIOS!$A$4:$F$32,2,FALSE()),IF(H7="CLARO",VLOOKUP(D7,PRECIOS!$A$4:$F$32,3,FALSE()),IF(H7="MELANGE",VLOOKUP(D7,PRECIOS!$A$4:$F$32,4,FALSE()),IF(H7="PPT",VLOOKUP(D7,PRECIOS!$A$4:$F$32,5,FALSE()),0)))),0) -> 24 | J7: =IFERROR(G7*I7,0) -> 7200 | K7: =IFERROR(IF(C7="",0,SUMIFS($F$4:$F$6,$C$4:$C$6,C7,$D$4:$D$6,D7,$E$4:$E$6,E7,$B$4:$B$6,"INGRESO")+SUMIFS($F$4:$F$6,$C$4:$C$6,C7,$D$4:$D$6,D7,$E$4:$E$6,E7,$B$4:$B$6,"DE REPROCESO")+SUMIFS($F$4:$F$6,$C$4:$C$6,C7,$D$4:$D$6,D7,$E$4:$E$6,E7,$B$4:$B$6,"AJUSTE+")-SUMIFS($F$4:$F$6,$C$4:$C$6,C7,$D$4:$D$6,D7,$E$4:$E$6,E7,$B$4:$B$6,"A CORTE")-SUMIFS($F$4:$F$6,$C$4:$C$6,C7,$D$4:$D$6,D7,$E$4:$E$6,E7,$B$4:$B$6,"A REPROCESO")-SUMIFS($F$4:$F$6,$C$4:$C$6,C7,$D$4:$D$6,D7,$E$4:$E$6,E7,$B$4:$B$6,"MUESTRA")-SUMIFS($F$4:$F$6,$C$4:$C$6,C7,$D$4:$D$6,D7,$E$4:$E$6,E7,$B$4:$B$6,"AJUSTE-")),0) -> 0 | L7: =IF(C7="",0,K7+IF(OR(B7="INGRESO",B7="DE REPROCESO",B7="AJUSTE+"),F7,IF(OR(B7="A CORTE",B7="A REPROCESO",B7="MUESTRA",B7="AJUSTE-"),-F7,0))) -> 15 | M7: tomas | O7: progreso | R7: =IF(OR(Q7="",Q7=0,J7=0),"",(Q7-J7)/J7)
A8: 46146 | B8: INGRESO | C8: OverShark | D8: jersey 30/1 | E8: Pacay | F8: 10 | G8: =IFERROR(F8*VLOOKUP(D8,TELAS!$A$4:$C$32,3,FALSE()),0) -> 200 | H8: =IFERROR(VLOOKUP(E8,COLORES!$A$4:$B$102,2,FALSE()),"") -> CLARO | I8: =IFERROR(IF(H8="OSCURO",VLOOKUP(D8,PRECIOS!$A$4:$F$32,2,FALSE()),IF(H8="CLARO",VLOOKUP(D8,PRECIOS!$A$4:$F$32,3,FALSE()),IF(H8="MELANGE",VLOOKUP(D8,PRECIOS!$A$4:$F$32,4,FALSE()),IF(H8="PPT",VLOOKUP(D8,PRECIOS!$A$4:$F$32,5,FALSE()),0)))),0) -> 21 | J8: =IFERROR(G8*I8,0) -> 4200 | K8: =IFERROR(IF(C8="",0,SUMIFS($F$4:$F$7,$C$4:$C$7,C8,$D$4:$D$7,D8,$E$4:$E$7,E8,$B$4:$B$7,"INGRESO")+SUMIFS($F$4:$F$7,$C$4:$C$7,C8,$D$4:$D$7,D8,$E$4:$E$7,E8,$B$4:$B$7,"DE REPROCESO")+SUMIFS($F$4:$F$7,$C$4:$C$7,C8,$D$4:$D$7,D8,$E$4:$E$7,E8,$B$4:$B$7,"AJUSTE+")-SUMIFS($F$4:$F$7,$C$4:$C$7,C8,$D$4:$D$7,D8,$E$4:$E$7,E8,$B$4:$B$7,"A CORTE")-SUMIFS($F$4:$F$7,$C$4:$C$7,C8,$D$4:$D$7,D8,$E$4:$E$7,E8,$B$4:$B$7,"A REPROCESO")-SUMIFS($F$4:$F$7,$C$4:$C$7,C8,$D$4:$D$7,D8,$E$4:$E$7,E8,$B$4:$B$7,"MUESTRA")-SUMIFS($F$4:$F$7,$C$4:$C$7,C8,$D$4:$D$7,D8,$E$4:$E$7,E8,$B$4:$B$7,"AJUSTE-")),0) -> 0 | L8: =IF(C8="",0,K8+IF(OR(B8="INGRESO",B8="DE REPROCESO",B8="AJUSTE+"),F8,IF(OR(B8="A CORTE",B8="A REPROCESO",B8="MUESTRA",B8="AJUSTE-"),-F8,0))) -> 10 | M8: tomas | O8: progreso | R8: =IF(OR(Q8="",Q8=0,J8=0),"",(Q8-J8)/J8)
A9: 46146 | B9: INGRESO | C9: OverShark | D9: jersey 30/1 | E9: Cemento | F9: 23 | G9: =IFERROR(F9*VLOOKUP(D9,TELAS!$A$4:$C$32,3,FALSE()),0) -> 460 | H9: =IFERROR(VLOOKUP(E9,COLORES!$A$4:$B$102,2,FALSE()),"") -> CLARO | I9: =IFERROR(IF(H9="OSCURO",VLOOKUP(D9,PRECIOS!$A$4:$F$32,2,FALSE()),IF(H9="CLARO",VLOOKUP(D9,PRECIOS!$A$4:$F$32,3,FALSE()),IF(H9="MELANGE",VLOOKUP(D9,PRECIOS!$A$4:$F$32,4,FALSE()),IF(H9="PPT",VLOOKUP(D9,PRECIOS!$A$4:$F$32,5,FALSE()),0)))),0) -> 21 | J9: =IFERROR(G9*I9,0) -> 9660 | K9: =IFERROR(IF(C9="",0,SUMIFS($F$4:$F$8,$C$4:$C$8,C9,$D$4:$D$8,D9,$E$4:$E$8,E9,$B$4:$B$8,"INGRESO")+SUMIFS($F$4:$F$8,$C$4:$C$8,C9,$D$4:$D$8,D9,$E$4:$E$8,E9,$B$4:$B$8,"DE REPROCESO")+SUMIFS($F$4:$F$8,$C$4:$C$8,C9,$D$4:$D$8,D9,$E$4:$E$8,E9,$B$4:$B$8,"AJUSTE+")-SUMIFS($F$4:$F$8,$C$4:$C$8,C9,$D$4:$D$8,D9,$E$4:$E$8,E9,$B$4:$B$8,"A CORTE")-SUMIFS($F$4:$F$8,$C$4:$C$8,C9,$D$4:$D$8,D9,$E$4:$E$8,E9,$B$4:$B$8,"A REPROCESO")-SUMIFS($F$4:$F$8,$C$4:$C$8,C9,$D$4:$D$8,D9,$E$4:$E$8,E9,$B$4:$B$8,"MUESTRA")-SUMIFS($F$4:$F$8,$C$4:$C$8,C9,$D$4:$D$8,D9,$E$4:$E$8,E9,$B$4:$B$8,"AJUSTE-")),0) -> 0 | L9: =IF(C9="",0,K9+IF(OR(B9="INGRESO",B9="DE REPROCESO",B9="AJUSTE+"),F9,IF(OR(B9="A CORTE",B9="A REPROCESO",B9="MUESTRA",B9="AJUSTE-"),-F9,0))) -> 23 | M9: tomas | O9: progreso | R9: =IF(OR(Q9="",Q9=0,J9=0),"",(Q9-J9)/J9)
A10: 46146 | B10: INGRESO | C10: OverShark | D10: jersey 30/1 | E10: P. Rosa | F10: 24 | G10: =IFERROR(F10*VLOOKUP(D10,TELAS!$A$4:$C$32,3,FALSE()),0) -> 480 | H10: =IFERROR(VLOOKUP(E10,COLORES!$A$4:$B$102,2,FALSE()),"") -> CLARO | I10: =IFERROR(IF(H10="OSCURO",VLOOKUP(D10,PRECIOS!$A$4:$F$32,2,FALSE()),IF(H10="CLARO",VLOOKUP(D10,PRECIOS!$A$4:$F$32,3,FALSE()),IF(H10="MELANGE",VLOOKUP(D10,PRECIOS!$A$4:$F$32,4,FALSE()),IF(H10="PPT",VLOOKUP(D10,PRECIOS!$A$4:$F$32,5,FALSE()),0)))),0) -> 21 | J10: =IFERROR(G10*I10,0) -> 10080 | K10: =IFERROR(IF(C10="",0,SUMIFS($F$4:$F$9,$C$4:$C$9,C10,$D$4:$D$9,D10,$E$4:$E$9,E10,$B$4:$B$9,"INGRESO")+SUMIFS($F$4:$F$9,$C$4:$C$9,C10,$D$4:$D$9,D10,$E$4:$E$9,E10,$B$4:$B$9,"DE REPROCESO")+SUMIFS($F$4:$F$9,$C$4:$C$9,C10,$D$4:$D$9,D10,$E$4:$E$9,E10,$B$4:$B$9,"AJUSTE+")-SUMIFS($F$4:$F$9,$C$4:$C$9,C10,$D$4:$D$9,D10,$E$4:$E$9,E10,$B$4:$B$9,"A CORTE")-SUMIFS($F$4:$F$9,$C$4:$C$9,C10,$D$4:$D$9,D10,$E$4:$E$9,E10,$B$4:$B$9,"A REPROCESO")-SUMIFS($F$4:$F$9,$C$4:$C$9,C10,$D$4:$D$9,D10,$E$4:$E$9,E10,$B$4:$B$9,"MUESTRA")-SUMIFS($F$4:$F$9,$C$4:$C$9,C10,$D$4:$D$9,D10,$E$4:$E$9,E10,$B$4:$B$9,"AJUSTE-")),0) -> 0 | L10: =IF(C10="",0,K10+IF(OR(B10="INGRESO",B10="DE REPROCESO",B10="AJUSTE+"),F10,IF(OR(B10="A CORTE",B10="A REPROCESO",B10="MUESTRA",B10="AJUSTE-"),-F10,0))) -> 24 | M10: tomas | O10: progreso | R10: =IF(OR(Q10="",Q10=0,J10=0),"",(Q10-J10)/J10)
A11: 46146 | B11: INGRESO | C11: OverShark | D11: jersey 30/1 | E11: Beige | F11: 14 | G11: =IFERROR(F11*VLOOKUP(D11,TELAS!$A$4:$C$32,3,FALSE()),0) -> 280 | H11: =IFERROR(VLOOKUP(E11,COLORES!$A$4:$B$102,2,FALSE()),"") -> CLARO | I11: =IFERROR(IF(H11="OSCURO",VLOOKUP(D11,PRECIOS!$A$4:$F$32,2,FALSE()),IF(H11="CLARO",VLOOKUP(D11,PRECIOS!$A$4:$F$32,3,FALSE()),IF(H11="MELANGE",VLOOKUP(D11,PRECIOS!$A$4:$F$32,4,FALSE()),IF(H11="PPT",VLOOKUP(D11,PRECIOS!$A$4:$F$32,5,FALSE()),0)))),0) -> 21 | J11: =IFERROR(G11*I11,0) -> 5880 | K11: =IFERROR(IF(C11="",0,SUMIFS($F$4:$F$10,$C$4:$C$10,C11,$D$4:$D$10,D11,$E$4:$E$10,E11,$B$4:$B$10,"INGRESO")+SUMIFS($F$4:$F$10,$C$4:$C$10,C11,$D$4:$D$10,D11,$E$4:$E$10,E11,$B$4:$B$10,"DE REPROCESO")+SUMIFS($F$4:$F$10,$C$4:$C$10,C11,$D$4:$D$10,D11,$E$4:$E$10,E11,$B$4:$B$10,"AJUSTE+")-SUMIFS($F$4:$F$10,$C$4:$C$10,C11,$D$4:$D$10,D11,$E$4:$E$10,E11,$B$4:$B$10,"A CORTE")-SUMIFS($F$4:$F$10,$C$4:$C$10,C11,$D$4:$D$10,D11,$E$4:$E$10,E11,$B$4:$B$10,"A REPROCESO")-SUMIFS($F$4:$F$10,$C$4:$C$10,C11,$D$4:$D$10,D11,$E$4:$E$10,E11,$B$4:$B$10,"MUESTRA")-SUMIFS($F$4:$F$10,$C$4:$C$10,C11,$D$4:$D$10,D11,$E$4:$E$10,E11,$B$4:$B$10,"AJUSTE-")),0) -> 0 | L11: =IF(C11="",0,K11+IF(OR(B11="INGRESO",B11="DE REPROCESO",B11="AJUSTE+"),F11,IF(OR(B11="A CORTE",B11="A REPROCESO",B11="MUESTRA",B11="AJUSTE-"),-F11,0))) -> 14 | M11: tomas | O11: progreso | R11: =IF(OR(Q11="",Q11=0,J11=0),"",(Q11-J11)/J11)
A12: 46146 | B12: INGRESO | C12: OverShark | D12: jersey 30/1 | E12: Vino | F12: 18 | G12: =IFERROR(F12*VLOOKUP(D12,TELAS!$A$4:$C$32,3,FALSE()),0) -> 360 | H12: =IFERROR(VLOOKUP(E12,COLORES!$A$4:$B$102,2,FALSE()),"") -> OSCURO | I12: =IFERROR(IF(H12="OSCURO",VLOOKUP(D12,PRECIOS!$A$4:$F$32,2,FALSE()),IF(H12="CLARO",VLOOKUP(D12,PRECIOS!$A$4:$F$32,3,FALSE()),IF(H12="MELANGE",VLOOKUP(D12,PRECIOS!$A$4:$F$32,4,FALSE()),IF(H12="PPT",VLOOKUP(D12,PRECIOS!$A$4:$F$32,5,FALSE()),0)))),0) -> 24 | J12: =IFERROR(G12*I12,0) -> 8640 | K12: =IFERROR(IF(C12="",0,SUMIFS($F$4:$F$11,$C$4:$C$11,C12,$D$4:$D$11,D12,$E$4:$E$11,E12,$B$4:$B$11,"INGRESO")+SUMIFS($F$4:$F$11,$C$4:$C$11,C12,$D$4:$D$11,D12,$E$4:$E$11,E12,$B$4:$B$11,"DE REPROCESO")+SUMIFS($F$4:$F$11,$C$4:$C$11,C12,$D$4:$D$11,D12,$E$4:$E$11,E12,$B$4:$B$11,"AJUSTE+")-SUMIFS($F$4:$F$11,$C$4:$C$11,C12,$D$4:$D$11,D12,$E$4:$E$11,E12,$B$4:$B$11,"A CORTE")-SUMIFS($F$4:$F$11,$C$4:$C$11,C12,$D$4:$D$11,D12,$E$4:$E$11,E12,$B$4:$B$11,"A REPROCESO")-SUMIFS($F$4:$F$11,$C$4:$C$11,C12,$D$4:$D$11,D12,$E$4:$E$11,E12,$B$4:$B$11,"MUESTRA")-SUMIFS($F$4:$F$11,$C$4:$C$11,C12,$D$4:$D$11,D12,$E$4:$E$11,E12,$B$4:$B$11,"AJUSTE-")),0) -> 0 | L12: =IF(C12="",0,K12+IF(OR(B12="INGRESO",B12="DE REPROCESO",B12="AJUSTE+"),F12,IF(OR(B12="A CORTE",B12="A REPROCESO",B12="MUESTRA",B12="AJUSTE-"),-F12,0))) -> 18 | M12: tomas | O12: progreso | R12: =IF(OR(Q12="",Q12=0,J12=0),"",(Q12-J12)/J12)
A13: 46146 | B13: INGRESO | C13: OverShark | D13: jersey 30/1 | E13: Denim | F13: 18 | G13: =IFERROR(F13*VLOOKUP(D13,TELAS!$A$4:$C$32,3,FALSE()),0) -> 360 | H13: =IFERROR(VLOOKUP(E13,COLORES!$A$4:$B$102,2,FALSE()),"") -> CLARO | I13: =IFERROR(IF(H13="OSCURO",VLOOKUP(D13,PRECIOS!$A$4:$F$32,2,FALSE()),IF(H13="CLARO",VLOOKUP(D13,PRECIOS!$A$4:$F$32,3,FALSE()),IF(H13="MELANGE",VLOOKUP(D13,PRECIOS!$A$4:$F$32,4,FALSE()),IF(H13="PPT",VLOOKUP(D13,PRECIOS!$A$4:$F$32,5,FALSE()),0)))),0) -> 21 | J13: =IFERROR(G13*I13,0) -> 7560 | K13: =IFERROR(IF(C13="",0,SUMIFS($F$4:$F$12,$C$4:$C$12,C13,$D$4:$D$12,D13,$E$4:$E$12,E13,$B$4:$B$12,"INGRESO")+SUMIFS($F$4:$F$12,$C$4:$C$12,C13,$D$4:$D$12,D13,$E$4:$E$12,E13,$B$4:$B$12,"DE REPROCESO")+SUMIFS($F$4:$F$12,$C$4:$C$12,C13,$D$4:$D$12,D13,$E$4:$E$12,E13,$B$4:$B$12,"AJUSTE+")-SUMIFS($F$4:$F$12,$C$4:$C$12,C13,$D$4:$D$12,D13,$E$4:$E$12,E13,$B$4:$B$12,"A CORTE")-SUMIFS($F$4:$F$12,$C$4:$C$12,C13,$D$4:$D$12,D13,$E$4:$E$12,E13,$B$4:$B$12,"A REPROCESO")-SUMIFS($F$4:$F$12,$C$4:$C$12,C13,$D$4:$D$12,D13,$E$4:$E$12,E13,$B$4:$B$12,"MUESTRA")-SUMIFS($F$4:$F$12,$C$4:$C$12,C13,$D$4:$D$12,D13,$E$4:$E$12,E13,$B$4:$B$12,"AJUSTE-")),0) -> 0 | L13: =IF(C13="",0,K13+IF(OR(B13="INGRESO",B13="DE REPROCESO",B13="AJUSTE+"),F13,IF(OR(B13="A CORTE",B13="A REPROCESO",B13="MUESTRA",B13="AJUSTE-"),-F13,0))) -> 18 | M13: tomas | O13: progreso | R13: =IF(OR(Q13="",Q13=0,J13=0),"",(Q13-J13)/J13)
A14: 46146 | B14: INGRESO | C14: OverShark | D14: jersey 30/1 | E14: Plomo | F14: 15 | G14: =IFERROR(F14*VLOOKUP(D14,TELAS!$A$4:$C$32,3,FALSE()),0) -> 300 | H14: =IFERROR(VLOOKUP(E14,COLORES!$A$4:$B$102,2,FALSE()),"") -> OSCURO | I14: =IFERROR(IF(H14="OSCURO",VLOOKUP(D14,PRECIOS!$A$4:$F$32,2,FALSE()),IF(H14="CLARO",VLOOKUP(D14,PRECIOS!$A$4:$F$32,3,FALSE()),IF(H14="MELANGE",VLOOKUP(D14,PRECIOS!$A$4:$F$32,4,FALSE()),IF(H14="PPT",VLOOKUP(D14,PRECIOS!$A$4:$F$32,5,FALSE()),0)))),0) -> 24 | J14: =IFERROR(G14*I14,0) -> 7200 | K14: =IFERROR(IF(C14="",0,SUMIFS($F$4:$F$13,$C$4:$C$13,C14,$D$4:$D$13,D14,$E$4:$E$13,E14,$B$4:$B$13,"INGRESO")+SUMIFS($F$4:$F$13,$C$4:$C$13,C14,$D$4:$D$13,D14,$E$4:$E$13,E14,$B$4:$B$13,"DE REPROCESO")+SUMIFS($F$4:$F$13,$C$4:$C$13,C14,$D$4:$D$13,D14,$E$4:$E$13,E14,$B$4:$B$13,"AJUSTE+")-SUMIFS($F$4:$F$13,$C$4:$C$13,C14,$D$4:$D$13,D14,$E$4:$E$13,E14,$B$4:$B$13,"A CORTE")-SUMIFS($F$4:$F$13,$C$4:$C$13,C14,$D$4:$D$13,D14,$E$4:$E$13,E14,$B$4:$B$13,"A REPROCESO")-SUMIFS($F$4:$F$13,$C$4:$C$13,C14,$D$4:$D$13,D14,$E$4:$E$13,E14,$B$4:$B$13,"MUESTRA")-SUMIFS($F$4:$F$13,$C$4:$C$13,C14,$D$4:$D$13,D14,$E$4:$E$13,E14,$B$4:$B$13,"AJUSTE-")),0) -> 0 | L14: =IF(C14="",0,K14+IF(OR(B14="INGRESO",B14="DE REPROCESO",B14="AJUSTE+"),F14,IF(OR(B14="A CORTE",B14="A REPROCESO",B14="MUESTRA",B14="AJUSTE-"),-F14,0))) -> 15 | M14: tomas | O14: progreso | R14: =IF(OR(Q14="",Q14=0,J14=0),"",(Q14-J14)/J14)
A15: 46141 | B15: INGRESO | C15: Bravos | D15: french terry 24/1 | E15: Negro | F15: 37 | G15: =IFERROR(F15*VLOOKUP(D15,TELAS!$A$4:$C$32,3,FALSE()),0) -> 740 | H15: =IFERROR(VLOOKUP(E15,COLORES!$A$4:$B$102,2,FALSE()),"") -> OSCURO | I15: =IFERROR(IF(H15="OSCURO",VLOOKUP(D15,PRECIOS!$A$4:$F$32,2,FALSE()),IF(H15="CLARO",VLOOKUP(D15,PRECIOS!$A$4:$F$32,3,FALSE()),IF(H15="MELANGE",VLOOKUP(D15,PRECIOS!$A$4:$F$32,4,FALSE()),IF(H15="PPT",VLOOKUP(D15,PRECIOS!$A$4:$F$32,5,FALSE()),0)))),0) -> 24 | J15: =IFERROR(G15*I15,0) -> 17760 | K15: =IFERROR(IF(C15="",0,SUMIFS($F$4:$F$14,$C$4:$C$14,C15,$D$4:$D$14,D15,$E$4:$E$14,E15,$B$4:$B$14,"INGRESO")+SUMIFS($F$4:$F$14,$C$4:$C$14,C15,$D$4:$D$14,D15,$E$4:$E$14,E15,$B$4:$B$14,"DE REPROCESO")+SUMIFS($F$4:$F$14,$C$4:$C$14,C15,$D$4:$D$14,D15,$E$4:$E$14,E15,$B$4:$B$14,"AJUSTE+")-SUMIFS($F$4:$F$14,$C$4:$C$14,C15,$D$4:$D$14,D15,$E$4:$E$14,E15,$B$4:$B$14,"A CORTE")-SUMIFS($F$4:$F$14,$C$4:$C$14,C15,$D$4:$D$14,D15,$E$4:$E$14,E15,$B$4:$B$14,"A REPROCESO")-SUMIFS($F$4:$F$14,$C$4:$C$14,C15,$D$4:$D$14,D15,$E$4:$E$14,E15,$B$4:$B$14,"MUESTRA")-SUMIFS($F$4:$F$14,$C$4:$C$14,C15,$D$4:$D$14,D15,$E$4:$E$14,E15,$B$4:$B$14,"AJUSTE-")),0) -> 0 | L15: =IF(C15="",0,K15+IF(OR(B15="INGRESO",B15="DE REPROCESO",B15="AJUSTE+"),F15,IF(OR(B15="A CORTE",B15="A REPROCESO",B15="MUESTRA",B15="AJUSTE-"),-F15,0))) -> 37 | M15: tomas | O15: progreso | R15: =IF(OR(Q15="",Q15=0,J15=0),"",(Q15-J15)/J15)
A16: 46141 | B16: INGRESO | C16: Bravos | D16: french terry 24/1 | E16: Perla | F16: 28 | G16: =IFERROR(F16*VLOOKUP(D16,TELAS!$A$4:$C$32,3,FALSE()),0) -> 560 | H16: =IFERROR(VLOOKUP(E16,COLORES!$A$4:$B$102,2,FALSE()),"") -> PPT | I16: =IFERROR(IF(H16="OSCURO",VLOOKUP(D16,PRECIOS!$A$4:$F$32,2,FALSE()),IF(H16="CLARO",VLOOKUP(D16,PRECIOS!$A$4:$F$32,3,FALSE()),IF(H16="MELANGE",VLOOKUP(D16,PRECIOS!$A$4:$F$32,4,FALSE()),IF(H16="PPT",VLOOKUP(D16,PRECIOS!$A$4:$F$32,5,FALSE()),0)))),0) -> 18 | J16: =IFERROR(G16*I16,0) -> 10080 | K16: =IFERROR(IF(C16="",0,SUMIFS($F$4:$F$15,$C$4:$C$15,C16,$D$4:$D$15,D16,$E$4:$E$15,E16,$B$4:$B$15,"INGRESO")+SUMIFS($F$4:$F$15,$C$4:$C$15,C16,$D$4:$D$15,D16,$E$4:$E$15,E16,$B$4:$B$15,"DE REPROCESO")+SUMIFS($F$4:$F$15,$C$4:$C$15,C16,$D$4:$D$15,D16,$E$4:$E$15,E16,$B$4:$B$15,"AJUSTE+")-SUMIFS($F$4:$F$15,$C$4:$C$15,C16,$D$4:$D$15,D16,$E$4:$E$15,E16,$B$4:$B$15,"A CORTE")-SUMIFS($F$4:$F$15,$C$4:$C$15,C16,$D$4:$D$15,D16,$E$4:$E$15,E16,$B$4:$B$15,"A REPROCESO")-SUMIFS($F$4:$F$15,$C$4:$C$15,C16,$D$4:$D$15,D16,$E$4:$E$15,E16,$B$4:$B$15,"MUESTRA")-SUMIFS($F$4:$F$15,$C$4:$C$15,C16,$D$4:$D$15,D16,$E$4:$E$15,E16,$B$4:$B$15,"AJUSTE-")),0) -> 0 | L16: =IF(C16="",0,K16+IF(OR(B16="INGRESO",B16="DE REPROCESO",B16="AJUSTE+"),F16,IF(OR(B16="A CORTE",B16="A REPROCESO",B16="MUESTRA",B16="AJUSTE-"),-F16,0))) -> 28 | M16: tomas | O16: progreso | R16: =IF(OR(Q16="",Q16=0,J16=0),"",(Q16-J16)/J16)
A17: 46141 | B17: INGRESO | C17: Bravos | D17: french terry 24/1 | E17: Azul | F17: 7 | G17: =IFERROR(F17*VLOOKUP(D17,TELAS!$A$4:$C$32,3,FALSE()),0) -> 140 | H17: =IFERROR(VLOOKUP(E17,COLORES!$A$4:$B$102,2,FALSE()),"") -> OSCURO | I17: =IFERROR(IF(H17="OSCURO",VLOOKUP(D17,PRECIOS!$A$4:$F$32,2,FALSE()),IF(H17="CLARO",VLOOKUP(D17,PRECIOS!$A$4:$F$32,3,FALSE()),IF(H17="MELANGE",VLOOKUP(D17,PRECIOS!$A$4:$F$32,4,FALSE()),IF(H17="PPT",VLOOKUP(D17,PRECIOS!$A$4:$F$32,5,FALSE()),0)))),0) -> 24 | J17: =IFERROR(G17*I17,0) -> 3360 | K17: =IFERROR(IF(C17="",0,SUMIFS($F$4:$F$16,$C$4:$C$16,C17,$D$4:$D$16,D17,$E$4:$E$16,E17,$B$4:$B$16,"INGRESO")+SUMIFS($F$4:$F$16,$C$4:$C$16,C17,$D$4:$D$16,D17,$E$4:$E$16,E17,$B$4:$B$16,"DE REPROCESO")+SUMIFS($F$4:$F$16,$C$4:$C$16,C17,$D$4:$D$16,D17,$E$4:$E$16,E17,$B$4:$B$16,"AJUSTE+")-SUMIFS($F$4:$F$16,$C$4:$C$16,C17,$D$4:$D$16,D17,$E$4:$E$16,E17,$B$4:$B$16,"A CORTE")-SUMIFS($F$4:$F$16,$C$4:$C$16,C17,$D$4:$D$16,D17,$E$4:$E$16,E17,$B$4:$B$16,"A REPROCESO")-SUMIFS($F$4:$F$16,$C$4:$C$16,C17,$D$4:$D$16,D17,$E$4:$E$16,E17,$B$4:$B$16,"MUESTRA")-SUMIFS($F$4:$F$16,$C$4:$C$16,C17,$D$4:$D$16,D17,$E$4:$E$16,E17,$B$4:$B$16,"AJUSTE-")),0) -> 0 | L17: =IF(C17="",0,K17+IF(OR(B17="INGRESO",B17="DE REPROCESO",B17="AJUSTE+"),F17,IF(OR(B17="A CORTE",B17="A REPROCESO",B17="MUESTRA",B17="AJUSTE-"),-F17,0))) -> 7 | M17: tomas | O17: progreso | R17: =IF(OR(Q17="",Q17=0,J17=0),"",(Q17-J17)/J17)
A18: 46141 | B18: INGRESO | C18: Bravos | D18: french terry 24/1 | E18: Botella | F18: 5 | G18: =IFERROR(F18*VLOOKUP(D18,TELAS!$A$4:$C$32,3,FALSE()),0) -> 100 | H18: =IFERROR(VLOOKUP(E18,COLORES!$A$4:$B$102,2,FALSE()),"") -> OSCURO | I18: =IFERROR(IF(H18="OSCURO",VLOOKUP(D18,PRECIOS!$A$4:$F$32,2,FALSE()),IF(H18="CLARO",VLOOKUP(D18,PRECIOS!$A$4:$F$32,3,FALSE()),IF(H18="MELANGE",VLOOKUP(D18,PRECIOS!$A$4:$F$32,4,FALSE()),IF(H18="PPT",VLOOKUP(D18,PRECIOS!$A$4:$F$32,5,FALSE()),0)))),0) -> 24 | J18: =IFERROR(G18*I18,0) -> 2400 | K18: =IFERROR(IF(C18="",0,SUMIFS($F$4:$F$17,$C$4:$C$17,C18,$D$4:$D$17,D18,$E$4:$E$17,E18,$B$4:$B$17,"INGRESO")+SUMIFS($F$4:$F$17,$C$4:$C$17,C18,$D$4:$D$17,D18,$E$4:$E$17,E18,$B$4:$B$17,"DE REPROCESO")+SUMIFS($F$4:$F$17,$C$4:$C$17,C18,$D$4:$D$17,D18,$E$4:$E$17,E18,$B$4:$B$17,"AJUSTE+")-SUMIFS($F$4:$F$17,$C$4:$C$17,C18,$D$4:$D$17,D18,$E$4:$E$17,E18,$B$4:$B$17,"A CORTE")-SUMIFS($F$4:$F$17,$C$4:$C$17,C18,$D$4:$D$17,D18,$E$4:$E$17,E18,$B$4:$B$17,"A REPROCESO")-SUMIFS($F$4:$F$17,$C$4:$C$17,C18,$D$4:$D$17,D18,$E$4:$E$17,E18,$B$4:$B$17,"MUESTRA")-SUMIFS($F$4:$F$17,$C$4:$C$17,C18,$D$4:$D$17,D18,$E$4:$E$17,E18,$B$4:$B$17,"AJUSTE-")),0) -> 0 | L18: =IF(C18="",0,K18+IF(OR(B18="INGRESO",B18="DE REPROCESO",B18="AJUSTE+"),F18,IF(OR(B18="A CORTE",B18="A REPROCESO",B18="MUESTRA",B18="AJUSTE-"),-F18,0))) -> 5 | M18: tomas | O18: progreso | R18: =IF(OR(Q18="",Q18=0,J18=0),"",(Q18-J18)/J18)
A19: 46141 | B19: INGRESO | C19: Bravos | D19: french terry 24/1 | E19: Pacay | F19: 1 | G19: =IFERROR(F19*VLOOKUP(D19,TELAS!$A$4:$C$32,3,FALSE()),0) -> 20 | H19: =IFERROR(VLOOKUP(E19,COLORES!$A$4:$B$102,2,FALSE()),"") -> CLARO | I19: =IFERROR(IF(H19="OSCURO",VLOOKUP(D19,PRECIOS!$A$4:$F$32,2,FALSE()),IF(H19="CLARO",VLOOKUP(D19,PRECIOS!$A$4:$F$32,3,FALSE()),IF(H19="MELANGE",VLOOKUP(D19,PRECIOS!$A$4:$F$32,4,FALSE()),IF(H19="PPT",VLOOKUP(D19,PRECIOS!$A$4:$F$32,5,FALSE()),0)))),0) -> 21 | J19: =IFERROR(G19*I19,0) -> 420 | K19: =IFERROR(IF(C19="",0,SUMIFS($F$4:$F$18,$C$4:$C$18,C19,$D$4:$D$18,D19,$E$4:$E$18,E19,$B$4:$B$18,"INGRESO")+SUMIFS($F$4:$F$18,$C$4:$C$18,C19,$D$4:$D$18,D19,$E$4:$E$18,E19,$B$4:$B$18,"DE REPROCESO")+SUMIFS($F$4:$F$18,$C$4:$C$18,C19,$D$4:$D$18,D19,$E$4:$E$18,E19,$B$4:$B$18,"AJUSTE+")-SUMIFS($F$4:$F$18,$C$4:$C$18,C19,$D$4:$D$18,D19,$E$4:$E$18,E19,$B$4:$B$18,"A CORTE")-SUMIFS($F$4:$F$18,$C$4:$C$18,C19,$D$4:$D$18,D19,$E$4:$E$18,E19,$B$4:$B$18,"A REPROCESO")-SUMIFS($F$4:$F$18,$C$4:$C$18,C19,$D$4:$D$18,D19,$E$4:$E$18,E19,$B$4:$B$18,"MUESTRA")-SUMIFS($F$4:$F$18,$C$4:$C$18,C19,$D$4:$D$18,D19,$E$4:$E$18,E19,$B$4:$B$18,"AJUSTE-")),0) -> 0 | L19: =IF(C19="",0,K19+IF(OR(B19="INGRESO",B19="DE REPROCESO",B19="AJUSTE+"),F19,IF(OR(B19="A CORTE",B19="A REPROCESO",B19="MUESTRA",B19="AJUSTE-"),-F19,0))) -> 1 | M19: tomas | O19: progreso | R19: =IF(OR(Q19="",Q19=0,J19=0),"",(Q19-J19)/J19)
A20: 46141 | B20: INGRESO | C20: Bravos | D20: french terry 24/1 | E20: P. Rosa | F20: 2 | G20: =IFERROR(F20*VLOOKUP(D20,TELAS!$A$4:$C$32,3,FALSE()),0) -> 40 | H20: =IFERROR(VLOOKUP(E20,COLORES!$A$4:$B$102,2,FALSE()),"") -> CLARO | I20: =IFERROR(IF(H20="OSCURO",VLOOKUP(D20,PRECIOS!$A$4:$F$32,2,FALSE()),IF(H20="CLARO",VLOOKUP(D20,PRECIOS!$A$4:$F$32,3,FALSE()),IF(H20="MELANGE",VLOOKUP(D20,PRECIOS!$A$4:$F$32,4,FALSE()),IF(H20="PPT",VLOOKUP(D20,PRECIOS!$A$4:$F$32,5,FALSE()),0)))),0) -> 21 | J20: =IFERROR(G20*I20,0) -> 840 | K20: =IFERROR(IF(C20="",0,SUMIFS($F$4:$F$19,$C$4:$C$19,C20,$D$4:$D$19,D20,$E$4:$E$19,E20,$B$4:$B$19,"INGRESO")+SUMIFS($F$4:$F$19,$C$4:$C$19,C20,$D$4:$D$19,D20,$E$4:$E$19,E20,$B$4:$B$19,"DE REPROCESO")+SUMIFS($F$4:$F$19,$C$4:$C$19,C20,$D$4:$D$19,D20,$E$4:$E$19,E20,$B$4:$B$19,"AJUSTE+")-SUMIFS($F$4:$F$19,$C$4:$C$19,C20,$D$4:$D$19,D20,$E$4:$E$19,E20,$B$4:$B$19,"A CORTE")-SUMIFS($F$4:$F$19,$C$4:$C$19,C20,$D$4:$D$19,D20,$E$4:$E$19,E20,$B$4:$B$19,"A REPROCESO")-SUMIFS($F$4:$F$19,$C$4:$C$19,C20,$D$4:$D$19,D20,$E$4:$E$19,E20,$B$4:$B$19,"MUESTRA")-SUMIFS($F$4:$F$19,$C$4:$C$19,C20,$D$4:$D$19,D20,$E$4:$E$19,E20,$B$4:$B$19,"AJUSTE-")),0) -> 0 | L20: =IF(C20="",0,K20+IF(OR(B20="INGRESO",B20="DE REPROCESO",B20="AJUSTE+"),F20,IF(OR(B20="A CORTE",B20="A REPROCESO",B20="MUESTRA",B20="AJUSTE-"),-F20,0))) -> 2 | M20: tomas | O20: progreso | R20: =IF(OR(Q20="",Q20=0,J20=0),"",(Q20-J20)/J20)
A21: 46141 | B21: INGRESO | C21: Bravos | D21: french terry 24/1 | E21: Beige | F21: 2 | G21: =IFERROR(F21*VLOOKUP(D21,TELAS!$A$4:$C$32,3,FALSE()),0) -> 40 | H21: =IFERROR(VLOOKUP(E21,COLORES!$A$4:$B$102,2,FALSE()),"") -> CLARO | I21: =IFERROR(IF(H21="OSCURO",VLOOKUP(D21,PRECIOS!$A$4:$F$32,2,FALSE()),IF(H21="CLARO",VLOOKUP(D21,PRECIOS!$A$4:$F$32,3,FALSE()),IF(H21="MELANGE",VLOOKUP(D21,PRECIOS!$A$4:$F$32,4,FALSE()),IF(H21="PPT",VLOOKUP(D21,PRECIOS!$A$4:$F$32,5,FALSE()),0)))),0) -> 21 | J21: =IFERROR(G21*I21,0) -> 840 | K21: =IFERROR(IF(C21="",0,SUMIFS($F$4:$F$20,$C$4:$C$20,C21,$D$4:$D$20,D21,$E$4:$E$20,E21,$B$4:$B$20,"INGRESO")+SUMIFS($F$4:$F$20,$C$4:$C$20,C21,$D$4:$D$20,D21,$E$4:$E$20,E21,$B$4:$B$20,"DE REPROCESO")+SUMIFS($F$4:$F$20,$C$4:$C$20,C21,$D$4:$D$20,D21,$E$4:$E$20,E21,$B$4:$B$20,"AJUSTE+")-SUMIFS($F$4:$F$20,$C$4:$C$20,C21,$D$4:$D$20,D21,$E$4:$E$20,E21,$B$4:$B$20,"A CORTE")-SUMIFS($F$4:$F$20,$C$4:$C$20,C21,$D$4:$D$20,D21,$E$4:$E$20,E21,$B$4:$B$20,"A REPROCESO")-SUMIFS($F$4:$F$20,$C$4:$C$20,C21,$D$4:$D$20,D21,$E$4:$E$20,E21,$B$4:$B$20,"MUESTRA")-SUMIFS($F$4:$F$20,$C$4:$C$20,C21,$D$4:$D$20,D21,$E$4:$E$20,E21,$B$4:$B$20,"AJUSTE-")),0) -> 0 | L21: =IF(C21="",0,K21+IF(OR(B21="INGRESO",B21="DE REPROCESO",B21="AJUSTE+"),F21,IF(OR(B21="A CORTE",B21="A REPROCESO",B21="MUESTRA",B21="AJUSTE-"),-F21,0))) -> 2 | M21: tomas | O21: progreso | R21: =IF(OR(Q21="",Q21=0,J21=0),"",(Q21-J21)/J21)
A22: 46141 | B22: INGRESO | C22: Bravos | D22: french terry 24/1 | E22: Denim | F22: 1 | G22: =IFERROR(F22*VLOOKUP(D22,TELAS!$A$4:$C$32,3,FALSE()),0) -> 20 | H22: =IFERROR(VLOOKUP(E22,COLORES!$A$4:$B$102,2,FALSE()),"") -> CLARO | I22: =IFERROR(IF(H22="OSCURO",VLOOKUP(D22,PRECIOS!$A$4:$F$32,2,FALSE()),IF(H22="CLARO",VLOOKUP(D22,PRECIOS!$A$4:$F$32,3,FALSE()),IF(H22="MELANGE",VLOOKUP(D22,PRECIOS!$A$4:$F$32,4,FALSE()),IF(H22="PPT",VLOOKUP(D22,PRECIOS!$A$4:$F$32,5,FALSE()),0)))),0) -> 21 | J22: =IFERROR(G22*I22,0) -> 420 | K22: =IFERROR(IF(C22="",0,SUMIFS($F$4:$F$21,$C$4:$C$21,C22,$D$4:$D$21,D22,$E$4:$E$21,E22,$B$4:$B$21,"INGRESO")+SUMIFS($F$4:$F$21,$C$4:$C$21,C22,$D$4:$D$21,D22,$E$4:$E$21,E22,$B$4:$B$21,"DE REPROCESO")+SUMIFS($F$4:$F$21,$C$4:$C$21,C22,$D$4:$D$21,D22,$E$4:$E$21,E22,$B$4:$B$21,"AJUSTE+")-SUMIFS($F$4:$F$21,$C$4:$C$21,C22,$D$4:$D$21,D22,$E$4:$E$21,E22,$B$4:$B$21,"A CORTE")-SUMIFS($F$4:$F$21,$C$4:$C$21,C22,$D$4:$D$21,D22,$E$4:$E$21,E22,$B$4:$B$21,"A REPROCESO")-SUMIFS($F$4:$F$21,$C$4:$C$21,C22,$D$4:$D$21,D22,$E$4:$E$21,E22,$B$4:$B$21,"MUESTRA")-SUMIFS($F$4:$F$21,$C$4:$C$21,C22,$D$4:$D$21,D22,$E$4:$E$21,E22,$B$4:$B$21,"AJUSTE-")),0) -> 0 | L22: =IF(C22="",0,K22+IF(OR(B22="INGRESO",B22="DE REPROCESO",B22="AJUSTE+"),F22,IF(OR(B22="A CORTE",B22="A REPROCESO",B22="MUESTRA",B22="AJUSTE-"),-F22,0))) -> 1 | M22: tomas | O22: progreso | R22: =IF(OR(Q22="",Q22=0,J22=0),"",(Q22-J22)/J22)
A23: 46141 | B23: INGRESO | C23: Bravos | D23: french terry 24/1 | E23: Plomo | F23: 4 | G23: =IFERROR(F23*VLOOKUP(D23,TELAS!$A$4:$C$32,3,FALSE()),0) -> 80 | H23: =IFERROR(VLOOKUP(E23,COLORES!$A$4:$B$102,2,FALSE()),"") -> OSCURO | I23: =IFERROR(IF(H23="OSCURO",VLOOKUP(D23,PRECIOS!$A$4:$F$32,2,FALSE()),IF(H23="CLARO",VLOOKUP(D23,PRECIOS!$A$4:$F$32,3,FALSE()),IF(H23="MELANGE",VLOOKUP(D23,PRECIOS!$A$4:$F$32,4,FALSE()),IF(H23="PPT",VLOOKUP(D23,PRECIOS!$A$4:$F$32,5,FALSE()),0)))),0) -> 24 | J23: =IFERROR(G23*I23,0) -> 1920 | K23: =IFERROR(IF(C23="",0,SUMIFS($F$4:$F$22,$C$4:$C$22,C23,$D$4:$D$22,D23,$E$4:$E$22,E23,$B$4:$B$22,"INGRESO")+SUMIFS($F$4:$F$22,$C$4:$C$22,C23,$D$4:$D$22,D23,$E$4:$E$22,E23,$B$4:$B$22,"DE REPROCESO")+SUMIFS($F$4:$F$22,$C$4:$C$22,C23,$D$4:$D$22,D23,$E$4:$E$22,E23,$B$4:$B$22,"AJUSTE+")-SUMIFS($F$4:$F$22,$C$4:$C$22,C23,$D$4:$D$22,D23,$E$4:$E$22,E23,$B$4:$B$22,"A CORTE")-SUMIFS($F$4:$F$22,$C$4:$C$22,C23,$D$4:$D$22,D23,$E$4:$E$22,E23,$B$4:$B$22,"A REPROCESO")-SUMIFS($F$4:$F$22,$C$4:$C$22,C23,$D$4:$D$22,D23,$E$4:$E$22,E23,$B$4:$B$22,"MUESTRA")-SUMIFS($F$4:$F$22,$C$4:$C$22,C23,$D$4:$D$22,D23,$E$4:$E$22,E23,$B$4:$B$22,"AJUSTE-")),0) -> 0 | L23: =IF(C23="",0,K23+IF(OR(B23="INGRESO",B23="DE REPROCESO",B23="AJUSTE+"),F23,IF(OR(B23="A CORTE",B23="A REPROCESO",B23="MUESTRA",B23="AJUSTE-"),-F23,0))) -> 4 | M23: tomas | O23: progreso | R23: =IF(OR(Q23="",Q23=0,J23=0),"",(Q23-J23)/J23)
A24: 46142 | B24: INGRESO | C24: OverShark | D24: pique 30/1 | E24: Perla | F24: 10 | G24: =IFERROR(F24*VLOOKUP(D24,TELAS!$A$4:$C$32,3,FALSE()),0) -> 200 | H24: =IFERROR(VLOOKUP(E24,COLORES!$A$4:$B$102,2,FALSE()),"") -> PPT | I24: =IFERROR(IF(H24="OSCURO",VLOOKUP(D24,PRECIOS!$A$4:$F$32,2,FALSE()),IF(H24="CLARO",VLOOKUP(D24,PRECIOS!$A$4:$F$32,3,FALSE()),IF(H24="MELANGE",VLOOKUP(D24,PRECIOS!$A$4:$F$32,4,FALSE()),IF(H24="PPT",VLOOKUP(D24,PRECIOS!$A$4:$F$32,5,FALSE()),0)))),0) -> 18 | J24: =IFERROR(G24*I24,0) -> 3600 | K24: =IFERROR(IF(C24="",0,SUMIFS($F$4:$F$23,$C$4:$C$23,C24,$D$4:$D$23,D24,$E$4:$E$23,E24,$B$4:$B$23,"INGRESO")+SUMIFS($F$4:$F$23,$C$4:$C$23,C24,$D$4:$D$23,D24,$E$4:$E$23,E24,$B$4:$B$23,"DE REPROCESO")+SUMIFS($F$4:$F$23,$C$4:$C$23,C24,$D$4:$D$23,D24,$E$4:$E$23,E24,$B$4:$B$23,"AJUSTE+")-SUMIFS($F$4:$F$23,$C$4:$C$23,C24,$D$4:$D$23,D24,$E$4:$E$23,E24,$B$4:$B$23,"A CORTE")-SUMIFS($F$4:$F$23,$C$4:$C$23,C24,$D$4:$D$23,D24,$E$4:$E$23,E24,$B$4:$B$23,"A REPROCESO")-SUMIFS($F$4:$F$23,$C$4:$C$23,C24,$D$4:$D$23,D24,$E$4:$E$23,E24,$B$4:$B$23,"MUESTRA")-SUMIFS($F$4:$F$23,$C$4:$C$23,C24,$D$4:$D$23,D24,$E$4:$E$23,E24,$B$4:$B$23,"AJUSTE-")),0) -> 0 | L24: =IF(C24="",0,K24+IF(OR(B24="INGRESO",B24="DE REPROCESO",B24="AJUSTE+"),F24,IF(OR(B24="A CORTE",B24="A REPROCESO",B24="MUESTRA",B24="AJUSTE-"),-F24,0))) -> 10 | M24: tomas | O24: progreso | R24: =IF(OR(Q24="",Q24=0,J24=0),"",(Q24-J24)/J24)
A25: 46142 | B25: INGRESO | C25: OverShark | D25: pique 30/1 | E25: Azul | F25: 6 | G25: =IFERROR(F25*VLOOKUP(D25,TELAS!$A$4:$C$32,3,FALSE()),0) -> 120 | H25: =IFERROR(VLOOKUP(E25,COLORES!$A$4:$B$102,2,FALSE()),"") -> OSCURO | I25: =IFERROR(IF(H25="OSCURO",VLOOKUP(D25,PRECIOS!$A$4:$F$32,2,FALSE()),IF(H25="CLARO",VLOOKUP(D25,PRECIOS!$A$4:$F$32,3,FALSE()),IF(H25="MELANGE",VLOOKUP(D25,PRECIOS!$A$4:$F$32,4,FALSE()),IF(H25="PPT",VLOOKUP(D25,PRECIOS!$A$4:$F$32,5,FALSE()),0)))),0) -> 24 | J25: =IFERROR(G25*I25,0) -> 2880 | K25: =IFERROR(IF(C25="",0,SUMIFS($F$4:$F$24,$C$4:$C$24,C25,$D$4:$D$24,D25,$E$4:$E$24,E25,$B$4:$B$24,"INGRESO")+SUMIFS($F$4:$F$24,$C$4:$C$24,C25,$D$4:$D$24,D25,$E$4:$E$24,E25,$B$4:$B$24,"DE REPROCESO")+SUMIFS($F$4:$F$24,$C$4:$C$24,C25,$D$4:$D$24,D25,$E$4:$E$24,E25,$B$4:$B$24,"AJUSTE+")-SUMIFS($F$4:$F$24,$C$4:$C$24,C25,$D$4:$D$24,D25,$E$4:$E$24,E25,$B$4:$B$24,"A CORTE")-SUMIFS($F$4:$F$24,$C$4:$C$24,C25,$D$4:$D$24,D25,$E$4:$E$24,E25,$B$4:$B$24,"A REPROCESO")-SUMIFS($F$4:$F$24,$C$4:$C$24,C25,$D$4:$D$24,D25,$E$4:$E$24,E25,$B$4:$B$24,"MUESTRA")-SUMIFS($F$4:$F$24,$C$4:$C$24,C25,$D$4:$D$24,D25,$E$4:$E$24,E25,$B$4:$B$24,"AJUSTE-")),0) -> 0 | L25: =IF(C25="",0,K25+IF(OR(B25="INGRESO",B25="DE REPROCESO",B25="AJUSTE+"),F25,IF(OR(B25="A CORTE",B25="A REPROCESO",B25="MUESTRA",B25="AJUSTE-"),-F25,0))) -> 6 | M25: tomas | O25: progreso | R25: =IF(OR(Q25="",Q25=0,J25=0),"",(Q25-J25)/J25)
A26: 46142 | B26: INGRESO | C26: OverShark | D26: pique 30/1 | E26: Botella | F26: 6 | G26: =IFERROR(F26*VLOOKUP(D26,TELAS!$A$4:$C$32,3,FALSE()),0) -> 120 | H26: =IFERROR(VLOOKUP(E26,COLORES!$A$4:$B$102,2,FALSE()),"") -> OSCURO | I26: =IFERROR(IF(H26="OSCURO",VLOOKUP(D26,PRECIOS!$A$4:$F$32,2,FALSE()),IF(H26="CLARO",VLOOKUP(D26,PRECIOS!$A$4:$F$32,3,FALSE()),IF(H26="MELANGE",VLOOKUP(D26,PRECIOS!$A$4:$F$32,4,FALSE()),IF(H26="PPT",VLOOKUP(D26,PRECIOS!$A$4:$F$32,5,FALSE()),0)))),0) -> 24 | J26: =IFERROR(G26*I26,0) -> 2880 | K26: =IFERROR(IF(C26="",0,SUMIFS($F$4:$F$25,$C$4:$C$25,C26,$D$4:$D$25,D26,$E$4:$E$25,E26,$B$4:$B$25,"INGRESO")+SUMIFS($F$4:$F$25,$C$4:$C$25,C26,$D$4:$D$25,D26,$E$4:$E$25,E26,$B$4:$B$25,"DE REPROCESO")+SUMIFS($F$4:$F$25,$C$4:$C$25,C26,$D$4:$D$25,D26,$E$4:$E$25,E26,$B$4:$B$25,"AJUSTE+")-SUMIFS($F$4:$F$25,$C$4:$C$25,C26,$D$4:$D$25,D26,$E$4:$E$25,E26,$B$4:$B$25,"A CORTE")-SUMIFS($F$4:$F$25,$C$4:$C$25,C26,$D$4:$D$25,D26,$E$4:$E$25,E26,$B$4:$B$25,"A REPROCESO")-SUMIFS($F$4:$F$25,$C$4:$C$25,C26,$D$4:$D$25,D26,$E$4:$E$25,E26,$B$4:$B$25,"MUESTRA")-SUMIFS($F$4:$F$25,$C$4:$C$25,C26,$D$4:$D$25,D26,$E$4:$E$25,E26,$B$4:$B$25,"AJUSTE-")),0) -> 0 | L26: =IF(C26="",0,K26+IF(OR(B26="INGRESO",B26="DE REPROCESO",B26="AJUSTE+"),F26,IF(OR(B26="A CORTE",B26="A REPROCESO",B26="MUESTRA",B26="AJUSTE-"),-F26,0))) -> 6 | M26: tomas | O26: progreso | R26: =IF(OR(Q26="",Q26=0,J26=0),"",(Q26-J26)/J26)
A27: 46142 | B27: INGRESO | C27: OverShark | D27: pique 30/1 | E27: Pacay | F27: 13 | G27: =IFERROR(F27*VLOOKUP(D27,TELAS!$A$4:$C$32,3,FALSE()),0) -> 260 | H27: =IFERROR(VLOOKUP(E27,COLORES!$A$4:$B$102,2,FALSE()),"") -> CLARO | I27: =IFERROR(IF(H27="OSCURO",VLOOKUP(D27,PRECIOS!$A$4:$F$32,2,FALSE()),IF(H27="CLARO",VLOOKUP(D27,PRECIOS!$A$4:$F$32,3,FALSE()),IF(H27="MELANGE",VLOOKUP(D27,PRECIOS!$A$4:$F$32,4,FALSE()),IF(H27="PPT",VLOOKUP(D27,PRECIOS!$A$4:$F$32,5,FALSE()),0)))),0) -> 21 | J27: =IFERROR(G27*I27,0) -> 5460 | K27: =IFERROR(IF(C27="",0,SUMIFS($F$4:$F$26,$C$4:$C$26,C27,$D$4:$D$26,D27,$E$4:$E$26,E27,$B$4:$B$26,"INGRESO")+SUMIFS($F$4:$F$26,$C$4:$C$26,C27,$D$4:$D$26,D27,$E$4:$E$26,E27,$B$4:$B$26,"DE REPROCESO")+SUMIFS($F$4:$F$26,$C$4:$C$26,C27,$D$4:$D$26,D27,$E$4:$E$26,E27,$B$4:$B$26,"AJUSTE+")-SUMIFS($F$4:$F$26,$C$4:$C$26,C27,$D$4:$D$26,D27,$E$4:$E$26,E27,$B$4:$B$26,"A CORTE")-SUMIFS($F$4:$F$26,$C$4:$C$26,C27,$D$4:$D$26,D27,$E$4:$E$26,E27,$B$4:$B$26,"A REPROCESO")-SUMIFS($F$4:$F$26,$C$4:$C$26,C27,$D$4:$D$26,D27,$E$4:$E$26,E27,$B$4:$B$26,"MUESTRA")-SUMIFS($F$4:$F$26,$C$4:$C$26,C27,$D$4:$D$26,D27,$E$4:$E$26,E27,$B$4:$B$26,"AJUSTE-")),0) -> 0 | L27: =IF(C27="",0,K27+IF(OR(B27="INGRESO",B27="DE REPROCESO",B27="AJUSTE+"),F27,IF(OR(B27="A CORTE",B27="A REPROCESO",B27="MUESTRA",B27="AJUSTE-"),-F27,0))) -> 13 | M27: tomas | O27: progreso | R27: =IF(OR(Q27="",Q27=0,J27=0),"",(Q27-J27)/J27)
A28: 46142 | B28: INGRESO | C28: OverShark | D28: pique 30/1 | E28: Cemento | F28: 9 | G28: =IFERROR(F28*VLOOKUP(D28,TELAS!$A$4:$C$32,3,FALSE()),0) -> 180 | H28: =IFERROR(VLOOKUP(E28,COLORES!$A$4:$B$102,2,FALSE()),"") -> CLARO | I28: =IFERROR(IF(H28="OSCURO",VLOOKUP(D28,PRECIOS!$A$4:$F$32,2,FALSE()),IF(H28="CLARO",VLOOKUP(D28,PRECIOS!$A$4:$F$32,3,FALSE()),IF(H28="MELANGE",VLOOKUP(D28,PRECIOS!$A$4:$F$32,4,FALSE()),IF(H28="PPT",VLOOKUP(D28,PRECIOS!$A$4:$F$32,5,FALSE()),0)))),0) -> 21 | J28: =IFERROR(G28*I28,0) -> 3780 | K28: =IFERROR(IF(C28="",0,SUMIFS($F$4:$F$27,$C$4:$C$27,C28,$D$4:$D$27,D28,$E$4:$E$27,E28,$B$4:$B$27,"INGRESO")+SUMIFS($F$4:$F$27,$C$4:$C$27,C28,$D$4:$D$27,D28,$E$4:$E$27,E28,$B$4:$B$27,"DE REPROCESO")+SUMIFS($F$4:$F$27,$C$4:$C$27,C28,$D$4:$D$27,D28,$E$4:$E$27,E28,$B$4:$B$27,"AJUSTE+")-SUMIFS($F$4:$F$27,$C$4:$C$27,C28,$D$4:$D$27,D28,$E$4:$E$27,E28,$B$4:$B$27,"A CORTE")-SUMIFS($F$4:$F$27,$C$4:$C$27,C28,$D$4:$D$27,D28,$E$4:$E$27,E28,$B$4:$B$27,"A REPROCESO")-SUMIFS($F$4:$F$27,$C$4:$C$27,C28,$D$4:$D$27,D28,$E$4:$E$27,E28,$B$4:$B$27,"MUESTRA")-SUMIFS($F$4:$F$27,$C$4:$C$27,C28,$D$4:$D$27,D28,$E$4:$E$27,E28,$B$4:$B$27,"AJUSTE-")),0) -> 0 | L28: =IF(C28="",0,K28+IF(OR(B28="INGRESO",B28="DE REPROCESO",B28="AJUSTE+"),F28,IF(OR(B28="A CORTE",B28="A REPROCESO",B28="MUESTRA",B28="AJUSTE-"),-F28,0))) -> 9 | M28: tomas | O28: progreso | R28: =IF(OR(Q28="",Q28=0,J28=0),"",(Q28-J28)/J28)
A29: 46142 | B29: INGRESO | C29: OverShark | D29: pique 30/1 | E29: P. Rosa | F29: 9 | G29: =IFERROR(F29*VLOOKUP(D29,TELAS!$A$4:$C$32,3,FALSE()),0) -> 180 | H29: =IFERROR(VLOOKUP(E29,COLORES!$A$4:$B$102,2,FALSE()),"") -> CLARO | I29: =IFERROR(IF(H29="OSCURO",VLOOKUP(D29,PRECIOS!$A$4:$F$32,2,FALSE()),IF(H29="CLARO",VLOOKUP(D29,PRECIOS!$A$4:$F$32,3,FALSE()),IF(H29="MELANGE",VLOOKUP(D29,PRECIOS!$A$4:$F$32,4,FALSE()),IF(H29="PPT",VLOOKUP(D29,PRECIOS!$A$4:$F$32,5,FALSE()),0)))),0) -> 21 | J29: =IFERROR(G29*I29,0) -> 3780 | K29: =IFERROR(IF(C29="",0,SUMIFS($F$4:$F$28,$C$4:$C$28,C29,$D$4:$D$28,D29,$E$4:$E$28,E29,$B$4:$B$28,"INGRESO")+SUMIFS($F$4:$F$28,$C$4:$C$28,C29,$D$4:$D$28,D29,$E$4:$E$28,E29,$B$4:$B$28,"DE REPROCESO")+SUMIFS($F$4:$F$28,$C$4:$C$28,C29,$D$4:$D$28,D29,$E$4:$E$28,E29,$B$4:$B$28,"AJUSTE+")-SUMIFS($F$4:$F$28,$C$4:$C$28,C29,$D$4:$D$28,D29,$E$4:$E$28,E29,$B$4:$B$28,"A CORTE")-SUMIFS($F$4:$F$28,$C$4:$C$28,C29,$D$4:$D$28,D29,$E$4:$E$28,E29,$B$4:$B$28,"A REPROCESO")-SUMIFS($F$4:$F$28,$C$4:$C$28,C29,$D$4:$D$28,D29,$E$4:$E$28,E29,$B$4:$B$28,"MUESTRA")-SUMIFS($F$4:$F$28,$C$4:$C$28,C29,$D$4:$D$28,D29,$E$4:$E$28,E29,$B$4:$B$28,"AJUSTE-")),0) -> 0 | L29: =IF(C29="",0,K29+IF(OR(B29="INGRESO",B29="DE REPROCESO",B29="AJUSTE+"),F29,IF(OR(B29="A CORTE",B29="A REPROCESO",B29="MUESTRA",B29="AJUSTE-"),-F29,0))) -> 9 | M29: tomas | O29: progreso | R29: =IF(OR(Q29="",Q29=0,J29=0),"",(Q29-J29)/J29)
A30: 46142 | B30: INGRESO | C30: OverShark | D30: pique 30/1 | E30: Topo | F30: 3 | G30: =IFERROR(F30*VLOOKUP(D30,TELAS!$A$4:$C$32,3,FALSE()),0) -> 60 | H30: =IFERROR(VLOOKUP(E30,COLORES!$A$4:$B$102,2,FALSE()),"") -> CLARO | I30: =IFERROR(IF(H30="OSCURO",VLOOKUP(D30,PRECIOS!$A$4:$F$32,2,FALSE()),IF(H30="CLARO",VLOOKUP(D30,PRECIOS!$A$4:$F$32,3,FALSE()),IF(H30="MELANGE",VLOOKUP(D30,PRECIOS!$A$4:$F$32,4,FALSE()),IF(H30="PPT",VLOOKUP(D30,PRECIOS!$A$4:$F$32,5,FALSE()),0)))),0) -> 21 | J30: =IFERROR(G30*I30,0) -> 1260 | K30: =IFERROR(IF(C30="",0,SUMIFS($F$4:$F$29,$C$4:$C$29,C30,$D$4:$D$29,D30,$E$4:$E$29,E30,$B$4:$B$29,"INGRESO")+SUMIFS($F$4:$F$29,$C$4:$C$29,C30,$D$4:$D$29,D30,$E$4:$E$29,E30,$B$4:$B$29,"DE REPROCESO")+SUMIFS($F$4:$F$29,$C$4:$C$29,C30,$D$4:$D$29,D30,$E$4:$E$29,E30,$B$4:$B$29,"AJUSTE+")-SUMIFS($F$4:$F$29,$C$4:$C$29,C30,$D$4:$D$29,D30,$E$4:$E$29,E30,$B$4:$B$29,"A CORTE")-SUMIFS($F$4:$F$29,$C$4:$C$29,C30,$D$4:$D$29,D30,$E$4:$E$29,E30,$B$4:$B$29,"A REPROCESO")-SUMIFS($F$4:$F$29,$C$4:$C$29,C30,$D$4:$D$29,D30,$E$4:$E$29,E30,$B$4:$B$29,"MUESTRA")-SUMIFS($F$4:$F$29,$C$4:$C$29,C30,$D$4:$D$29,D30,$E$4:$E$29,E30,$B$4:$B$29,"AJUSTE-")),0) -> 0 | L30: =IF(C30="",0,K30+IF(OR(B30="INGRESO",B30="DE REPROCESO",B30="AJUSTE+"),F30,IF(OR(B30="A CORTE",B30="A REPROCESO",B30="MUESTRA",B30="AJUSTE-"),-F30,0))) -> 3 | M30: tomas | O30: progreso | R30: =IF(OR(Q30="",Q30=0,J30=0),"",(Q30-J30)/J30)
A31: 46142 | B31: INGRESO | C31: OverShark | D31: pique 30/1 | E31: Vino | F31: 2 | G31: =IFERROR(F31*VLOOKUP(D31,TELAS!$A$4:$C$32,3,FALSE()),0) -> 40 | H31: =IFERROR(VLOOKUP(E31,COLORES!$A$4:$B$102,2,FALSE()),"") -> OSCURO | I31: =IFERROR(IF(H31="OSCURO",VLOOKUP(D31,PRECIOS!$A$4:$F$32,2,FALSE()),IF(H31="CLARO",VLOOKUP(D31,PRECIOS!$A$4:$F$32,3,FALSE()),IF(H31="MELANGE",VLOOKUP(D31,PRECIOS!$A$4:$F$32,4,FALSE()),IF(H31="PPT",VLOOKUP(D31,PRECIOS!$A$4:$F$32,5,FALSE()),0)))),0) -> 24 | J31: =IFERROR(G31*I31,0) -> 960 | K31: =IFERROR(IF(C31="",0,SUMIFS($F$4:$F$30,$C$4:$C$30,C31,$D$4:$D$30,D31,$E$4:$E$30,E31,$B$4:$B$30,"INGRESO")+SUMIFS($F$4:$F$30,$C$4:$C$30,C31,$D$4:$D$30,D31,$E$4:$E$30,E31,$B$4:$B$30,"DE REPROCESO")+SUMIFS($F$4:$F$30,$C$4:$C$30,C31,$D$4:$D$30,D31,$E$4:$E$30,E31,$B$4:$B$30,"AJUSTE+")-SUMIFS($F$4:$F$30,$C$4:$C$30,C31,$D$4:$D$30,D31,$E$4:$E$30,E31,$B$4:$B$30,"A CORTE")-SUMIFS($F$4:$F$30,$C$4:$C$30,C31,$D$4:$D$30,D31,$E$4:$E$30,E31,$B$4:$B$30,"A REPROCESO")-SUMIFS($F$4:$F$30,$C$4:$C$30,C31,$D$4:$D$30,D31,$E$4:$E$30,E31,$B$4:$B$30,"MUESTRA")-SUMIFS($F$4:$F$30,$C$4:$C$30,C31,$D$4:$D$30,D31,$E$4:$E$30,E31,$B$4:$B$30,"AJUSTE-")),0) -> 0 | L31: =IF(C31="",0,K31+IF(OR(B31="INGRESO",B31="DE REPROCESO",B31="AJUSTE+"),F31,IF(OR(B31="A CORTE",B31="A REPROCESO",B31="MUESTRA",B31="AJUSTE-"),-F31,0))) -> 2 | M31: tomas | O31: progreso | R31: =IF(OR(Q31="",Q31=0,J31=0),"",(Q31-J31)/J31)
A32: 46142 | B32: INGRESO | C32: OverShark | D32: pique 30/1 | E32: Denim | F32: 13 | G32: =IFERROR(F32*VLOOKUP(D32,TELAS!$A$4:$C$32,3,FALSE()),0) -> 260 | H32: =IFERROR(VLOOKUP(E32,COLORES!$A$4:$B$102,2,FALSE()),"") -> CLARO | I32: =IFERROR(IF(H32="OSCURO",VLOOKUP(D32,PRECIOS!$A$4:$F$32,2,FALSE()),IF(H32="CLARO",VLOOKUP(D32,PRECIOS!$A$4:$F$32,3,FALSE()),IF(H32="MELANGE",VLOOKUP(D32,PRECIOS!$A$4:$F$32,4,FALSE()),IF(H32="PPT",VLOOKUP(D32,PRECIOS!$A$4:$F$32,5,FALSE()),0)))),0) -> 21 | J32: =IFERROR(G32*I32,0) -> 5460 | K32: =IFERROR(IF(C32="",0,SUMIFS($F$4:$F$31,$C$4:$C$31,C32,$D$4:$D$31,D32,$E$4:$E$31,E32,$B$4:$B$31,"INGRESO")+SUMIFS($F$4:$F$31,$C$4:$C$31,C32,$D$4:$D$31,D32,$E$4:$E$31,E32,$B$4:$B$31,"DE REPROCESO")+SUMIFS($F$4:$F$31,$C$4:$C$31,C32,$D$4:$D$31,D32,$E$4:$E$31,E32,$B$4:$B$31,"AJUSTE+")-SUMIFS($F$4:$F$31,$C$4:$C$31,C32,$D$4:$D$31,D32,$E$4:$E$31,E32,$B$4:$B$31,"A CORTE")-SUMIFS($F$4:$F$31,$C$4:$C$31,C32,$D$4:$D$31,D32,$E$4:$E$31,E32,$B$4:$B$31,"A REPROCESO")-SUMIFS($F$4:$F$31,$C$4:$C$31,C32,$D$4:$D$31,D32,$E$4:$E$31,E32,$B$4:$B$31,"MUESTRA")-SUMIFS($F$4:$F$31,$C$4:$C$31,C32,$D$4:$D$31,D32,$E$4:$E$31,E32,$B$4:$B$31,"AJUSTE-")),0) -> 0 | L32: =IF(C32="",0,K32+IF(OR(B32="INGRESO",B32="DE REPROCESO",B32="AJUSTE+"),F32,IF(OR(B32="A CORTE",B32="A REPROCESO",B32="MUESTRA",B32="AJUSTE-"),-F32,0))) -> 13 | M32: tomas | O32: progreso | R32: =IF(OR(Q32="",Q32=0,J32=0),"",(Q32-J32)/J32)
A33: 46142 | B33: INGRESO | C33: OverShark | D33: pique 30/1 | E33: Plomo | F33: 6 | G33: =IFERROR(F33*VLOOKUP(D33,TELAS!$A$4:$C$32,3,FALSE()),0) -> 120 | H33: =IFERROR(VLOOKUP(E33,COLORES!$A$4:$B$102,2,FALSE()),"") -> OSCURO | I33: =IFERROR(IF(H33="OSCURO",VLOOKUP(D33,PRECIOS!$A$4:$F$32,2,FALSE()),IF(H33="CLARO",VLOOKUP(D33,PRECIOS!$A$4:$F$32,3,FALSE()),IF(H33="MELANGE",VLOOKUP(D33,PRECIOS!$A$4:$F$32,4,FALSE()),IF(H33="PPT",VLOOKUP(D33,PRECIOS!$A$4:$F$32,5,FALSE()),0)))),0) -> 24 | J33: =IFERROR(G33*I33,0) -> 2880 | K33: =IFERROR(IF(C33="",0,SUMIFS($F$4:$F$32,$C$4:$C$32,C33,$D$4:$D$32,D33,$E$4:$E$32,E33,$B$4:$B$32,"INGRESO")+SUMIFS($F$4:$F$32,$C$4:$C$32,C33,$D$4:$D$32,D33,$E$4:$E$32,E33,$B$4:$B$32,"DE REPROCESO")+SUMIFS($F$4:$F$32,$C$4:$C$32,C33,$D$4:$D$32,D33,$E$4:$E$32,E33,$B$4:$B$32,"AJUSTE+")-SUMIFS($F$4:$F$32,$C$4:$C$32,C33,$D$4:$D$32,D33,$E$4:$E$32,E33,$B$4:$B$32,"A CORTE")-SUMIFS($F$4:$F$32,$C$4:$C$32,C33,$D$4:$D$32,D33,$E$4:$E$32,E33,$B$4:$B$32,"A REPROCESO")-SUMIFS($F$4:$F$32,$C$4:$C$32,C33,$D$4:$D$32,D33,$E$4:$E$32,E33,$B$4:$B$32,"MUESTRA")-SUMIFS($F$4:$F$32,$C$4:$C$32,C33,$D$4:$D$32,D33,$E$4:$E$32,E33,$B$4:$B$32,"AJUSTE-")),0) -> 0 | L33: =IF(C33="",0,K33+IF(OR(B33="INGRESO",B33="DE REPROCESO",B33="AJUSTE+"),F33,IF(OR(B33="A CORTE",B33="A REPROCESO",B33="MUESTRA",B33="AJUSTE-"),-F33,0))) -> 6 | M33: tomas | O33: progreso | R33: =IF(OR(Q33="",Q33=0,J33=0),"",(Q33-J33)/J33)
A34: 46142 | B34: INGRESO | C34: OverShark | D34: pique 30/1 | E34: Melange | F34: 9 | G34: =IFERROR(F34*VLOOKUP(D34,TELAS!$A$4:$C$32,3,FALSE()),0) -> 180 | H34: =IFERROR(VLOOKUP(E34,COLORES!$A$4:$B$102,2,FALSE()),"") -> MELANGE | I34: =IFERROR(IF(H34="OSCURO",VLOOKUP(D34,PRECIOS!$A$4:$F$32,2,FALSE()),IF(H34="CLARO",VLOOKUP(D34,PRECIOS!$A$4:$F$32,3,FALSE()),IF(H34="MELANGE",VLOOKUP(D34,PRECIOS!$A$4:$F$32,4,FALSE()),IF(H34="PPT",VLOOKUP(D34,PRECIOS!$A$4:$F$32,5,FALSE()),0)))),0) -> 18 | J34: =IFERROR(G34*I34,0) -> 3240 | K34: =IFERROR(IF(C34="",0,SUMIFS($F$4:$F$33,$C$4:$C$33,C34,$D$4:$D$33,D34,$E$4:$E$33,E34,$B$4:$B$33,"INGRESO")+SUMIFS($F$4:$F$33,$C$4:$C$33,C34,$D$4:$D$33,D34,$E$4:$E$33,E34,$B$4:$B$33,"DE REPROCESO")+SUMIFS($F$4:$F$33,$C$4:$C$33,C34,$D$4:$D$33,D34,$E$4:$E$33,E34,$B$4:$B$33,"AJUSTE+")-SUMIFS($F$4:$F$33,$C$4:$C$33,C34,$D$4:$D$33,D34,$E$4:$E$33,E34,$B$4:$B$33,"A CORTE")-SUMIFS($F$4:$F$33,$C$4:$C$33,C34,$D$4:$D$33,D34,$E$4:$E$33,E34,$B$4:$B$33,"A REPROCESO")-SUMIFS($F$4:$F$33,$C$4:$C$33,C34,$D$4:$D$33,D34,$E$4:$E$33,E34,$B$4:$B$33,"MUESTRA")-SUMIFS($F$4:$F$33,$C$4:$C$33,C34,$D$4:$D$33,D34,$E$4:$E$33,E34,$B$4:$B$33,"AJUSTE-")),0) -> 0 | L34: =IF(C34="",0,K34+IF(OR(B34="INGRESO",B34="DE REPROCESO",B34="AJUSTE+"),F34,IF(OR(B34="A CORTE",B34="A REPROCESO",B34="MUESTRA",B34="AJUSTE-"),-F34,0))) -> 9 | M34: tomas | O34: progreso | R34: =IF(OR(Q34="",Q34=0,J34=0),"",(Q34-J34)/J34)
A35: 46147 | B35: INGRESO | C35: OverShark | D35: wafle 30/1 | E35: Negro | F35: 33 | G35: =IFERROR(F35*VLOOKUP(D35,TELAS!$A$4:$C$32,3,FALSE()),0) -> 660 | H35: =IFERROR(VLOOKUP(E35,COLORES!$A$4:$B$102,2,FALSE()),"") -> OSCURO | I35: =IFERROR(IF(H35="OSCURO",VLOOKUP(D35,PRECIOS!$A$4:$F$32,2,FALSE()),IF(H35="CLARO",VLOOKUP(D35,PRECIOS!$A$4:$F$32,3,FALSE()),IF(H35="MELANGE",VLOOKUP(D35,PRECIOS!$A$4:$F$32,4,FALSE()),IF(H35="PPT",VLOOKUP(D35,PRECIOS!$A$4:$F$32,5,FALSE()),0)))),0) -> 26 | J35: =IFERROR(G35*I35,0) -> 17160 | K35: =IFERROR(IF(C35="",0,SUMIFS($F$4:$F$34,$C$4:$C$34,C35,$D$4:$D$34,D35,$E$4:$E$34,E35,$B$4:$B$34,"INGRESO")+SUMIFS($F$4:$F$34,$C$4:$C$34,C35,$D$4:$D$34,D35,$E$4:$E$34,E35,$B$4:$B$34,"DE REPROCESO")+SUMIFS($F$4:$F$34,$C$4:$C$34,C35,$D$4:$D$34,D35,$E$4:$E$34,E35,$B$4:$B$34,"AJUSTE+")-SUMIFS($F$4:$F$34,$C$4:$C$34,C35,$D$4:$D$34,D35,$E$4:$E$34,E35,$B$4:$B$34,"A CORTE")-SUMIFS($F$4:$F$34,$C$4:$C$34,C35,$D$4:$D$34,D35,$E$4:$E$34,E35,$B$4:$B$34,"A REPROCESO")-SUMIFS($F$4:$F$34,$C$4:$C$34,C35,$D$4:$D$34,D35,$E$4:$E$34,E35,$B$4:$B$34,"MUESTRA")-SUMIFS($F$4:$F$34,$C$4:$C$34,C35,$D$4:$D$34,D35,$E$4:$E$34,E35,$B$4:$B$34,"AJUSTE-")),0) -> 0 | L35: =IF(C35="",0,K35+IF(OR(B35="INGRESO",B35="DE REPROCESO",B35="AJUSTE+"),F35,IF(OR(B35="A CORTE",B35="A REPROCESO",B35="MUESTRA",B35="AJUSTE-"),-F35,0))) -> 33 | M35: tomas | O35: progreso | R35: =IF(OR(Q35="",Q35=0,J35=0),"",(Q35-J35)/J35)
A36: 46147 | B36: INGRESO | C36: OverShark | D36: wafle 30/1 | E36: Perla | F36: 36 | G36: =IFERROR(F36*VLOOKUP(D36,TELAS!$A$4:$C$32,3,FALSE()),0) -> 720 | H36: =IFERROR(VLOOKUP(E36,COLORES!$A$4:$B$102,2,FALSE()),"") -> PPT | I36: =IFERROR(IF(H36="OSCURO",VLOOKUP(D36,PRECIOS!$A$4:$F$32,2,FALSE()),IF(H36="CLARO",VLOOKUP(D36,PRECIOS!$A$4:$F$32,3,FALSE()),IF(H36="MELANGE",VLOOKUP(D36,PRECIOS!$A$4:$F$32,4,FALSE()),IF(H36="PPT",VLOOKUP(D36,PRECIOS!$A$4:$F$32,5,FALSE()),0)))),0) -> 19 | J36: =IFERROR(G36*I36,0) -> 13680 | K36: =IFERROR(IF(C36="",0,SUMIFS($F$4:$F$35,$C$4:$C$35,C36,$D$4:$D$35,D36,$E$4:$E$35,E36,$B$4:$B$35,"INGRESO")+SUMIFS($F$4:$F$35,$C$4:$C$35,C36,$D$4:$D$35,D36,$E$4:$E$35,E36,$B$4:$B$35,"DE REPROCESO")+SUMIFS($F$4:$F$35,$C$4:$C$35,C36,$D$4:$D$35,D36,$E$4:$E$35,E36,$B$4:$B$35,"AJUSTE+")-SUMIFS($F$4:$F$35,$C$4:$C$35,C36,$D$4:$D$35,D36,$E$4:$E$35,E36,$B$4:$B$35,"A CORTE")-SUMIFS($F$4:$F$35,$C$4:$C$35,C36,$D$4:$D$35,D36,$E$4:$E$35,E36,$B$4:$B$35,"A REPROCESO")-SUMIFS($F$4:$F$35,$C$4:$C$35,C36,$D$4:$D$35,D36,$E$4:$E$35,E36,$B$4:$B$35,"MUESTRA")-SUMIFS($F$4:$F$35,$C$4:$C$35,C36,$D$4:$D$35,D36,$E$4:$E$35,E36,$B$4:$B$35,"AJUSTE-")),0) -> 0 | L36: =IF(C36="",0,K36+IF(OR(B36="INGRESO",B36="DE REPROCESO",B36="AJUSTE+"),F36,IF(OR(B36="A CORTE",B36="A REPROCESO",B36="MUESTRA",B36="AJUSTE-"),-F36,0))) -> 36 | M36: tomas | O36: progreso | R36: =IF(OR(Q36="",Q36=0,J36=0),"",(Q36-J36)/J36)
A37: 46147 | B37: INGRESO | C37: OverShark | D37: wafle 30/1 | E37: Azul | F37: 35 | G37: =IFERROR(F37*VLOOKUP(D37,TELAS!$A$4:$C$32,3,FALSE()),0) -> 700 | H37: =IFERROR(VLOOKUP(E37,COLORES!$A$4:$B$102,2,FALSE()),"") -> OSCURO | I37: =IFERROR(IF(H37="OSCURO",VLOOKUP(D37,PRECIOS!$A$4:$F$32,2,FALSE()),IF(H37="CLARO",VLOOKUP(D37,PRECIOS!$A$4:$F$32,3,FALSE()),IF(H37="MELANGE",VLOOKUP(D37,PRECIOS!$A$4:$F$32,4,FALSE()),IF(H37="PPT",VLOOKUP(D37,PRECIOS!$A$4:$F$32,5,FALSE()),0)))),0) -> 26 | J37: =IFERROR(G37*I37,0) -> 18200 | K37: =IFERROR(IF(C37="",0,SUMIFS($F$4:$F$36,$C$4:$C$36,C37,$D$4:$D$36,D37,$E$4:$E$36,E37,$B$4:$B$36,"INGRESO")+SUMIFS($F$4:$F$36,$C$4:$C$36,C37,$D$4:$D$36,D37,$E$4:$E$36,E37,$B$4:$B$36,"DE REPROCESO")+SUMIFS($F$4:$F$36,$C$4:$C$36,C37,$D$4:$D$36,D37,$E$4:$E$36,E37,$B$4:$B$36,"AJUSTE+")-SUMIFS($F$4:$F$36,$C$4:$C$36,C37,$D$4:$D$36,D37,$E$4:$E$36,E37,$B$4:$B$36,"A CORTE")-SUMIFS($F$4:$F$36,$C$4:$C$36,C37,$D$4:$D$36,D37,$E$4:$E$36,E37,$B$4:$B$36,"A REPROCESO")-SUMIFS($F$4:$F$36,$C$4:$C$36,C37,$D$4:$D$36,D37,$E$4:$E$36,E37,$B$4:$B$36,"MUESTRA")-SUMIFS($F$4:$F$36,$C$4:$C$36,C37,$D$4:$D$36,D37,$E$4:$E$36,E37,$B$4:$B$36,"AJUSTE-")),0) -> 0 | L37: =IF(C37="",0,K37+IF(OR(B37="INGRESO",B37="DE REPROCESO",B37="AJUSTE+"),F37,IF(OR(B37="A CORTE",B37="A REPROCESO",B37="MUESTRA",B37="AJUSTE-"),-F37,0))) -> 35 | M37: tomas | O37: progreso | R37: =IF(OR(Q37="",Q37=0,J37=0),"",(Q37-J37)/J37)
A38: 46147 | B38: INGRESO | C38: OverShark | D38: wafle 30/1 | E38: Botella | F38: 20 | G38: =IFERROR(F38*VLOOKUP(D38,TELAS!$A$4:$C$32,3,FALSE()),0) -> 400 | H38: =IFERROR(VLOOKUP(E38,COLORES!$A$4:$B$102,2,FALSE()),"") -> OSCURO | I38: =IFERROR(IF(H38="OSCURO",VLOOKUP(D38,PRECIOS!$A$4:$F$32,2,FALSE()),IF(H38="CLARO",VLOOKUP(D38,PRECIOS!$A$4:$F$32,3,FALSE()),IF(H38="MELANGE",VLOOKUP(D38,PRECIOS!$A$4:$F$32,4,FALSE()),IF(H38="PPT",VLOOKUP(D38,PRECIOS!$A$4:$F$32,5,FALSE()),0)))),0) -> 26 | J38: =IFERROR(G38*I38,0) -> 10400 | K38: =IFERROR(IF(C38="",0,SUMIFS($F$4:$F$37,$C$4:$C$37,C38,$D$4:$D$37,D38,$E$4:$E$37,E38,$B$4:$B$37,"INGRESO")+SUMIFS($F$4:$F$37,$C$4:$C$37,C38,$D$4:$D$37,D38,$E$4:$E$37,E38,$B$4:$B$37,"DE REPROCESO")+SUMIFS($F$4:$F$37,$C$4:$C$37,C38,$D$4:$D$37,D38,$E$4:$E$37,E38,$B$4:$B$37,"AJUSTE+")-SUMIFS($F$4:$F$37,$C$4:$C$37,C38,$D$4:$D$37,D38,$E$4:$E$37,E38,$B$4:$B$37,"A CORTE")-SUMIFS($F$4:$F$37,$C$4:$C$37,C38,$D$4:$D$37,D38,$E$4:$E$37,E38,$B$4:$B$37,"A REPROCESO")-SUMIFS($F$4:$F$37,$C$4:$C$37,C38,$D$4:$D$37,D38,$E$4:$E$37,E38,$B$4:$B$37,"MUESTRA")-SUMIFS($F$4:$F$37,$C$4:$C$37,C38,$D$4:$D$37,D38,$E$4:$E$37,E38,$B$4:$B$37,"AJUSTE-")),0) -> 0 | L38: =IF(C38="",0,K38+IF(OR(B38="INGRESO",B38="DE REPROCESO",B38="AJUSTE+"),F38,IF(OR(B38="A CORTE",B38="A REPROCESO",B38="MUESTRA",B38="AJUSTE-"),-F38,0))) -> 20 | M38: tomas | O38: progreso | R38: =IF(OR(Q38="",Q38=0,J38=0),"",(Q38-J38)/J38)
A39: 46147 | B39: INGRESO | C39: OverShark | D39: wafle 30/1 | E39: Pacay | F39: 15 | G39: =IFERROR(F39*VLOOKUP(D39,TELAS!$A$4:$C$32,3,FALSE()),0) -> 300 | H39: =IFERROR(VLOOKUP(E39,COLORES!$A$4:$B$102,2,FALSE()),"") -> CLARO | I39: =IFERROR(IF(H39="OSCURO",VLOOKUP(D39,PRECIOS!$A$4:$F$32,2,FALSE()),IF(H39="CLARO",VLOOKUP(D39,PRECIOS!$A$4:$F$32,3,FALSE()),IF(H39="MELANGE",VLOOKUP(D39,PRECIOS!$A$4:$F$32,4,FALSE()),IF(H39="PPT",VLOOKUP(D39,PRECIOS!$A$4:$F$32,5,FALSE()),0)))),0) -> 22.5 | J39: =IFERROR(G39*I39,0) -> 6750 | K39: =IFERROR(IF(C39="",0,SUMIFS($F$4:$F$38,$C$4:$C$38,C39,$D$4:$D$38,D39,$E$4:$E$38,E39,$B$4:$B$38,"INGRESO")+SUMIFS($F$4:$F$38,$C$4:$C$38,C39,$D$4:$D$38,D39,$E$4:$E$38,E39,$B$4:$B$38,"DE REPROCESO")+SUMIFS($F$4:$F$38,$C$4:$C$38,C39,$D$4:$D$38,D39,$E$4:$E$38,E39,$B$4:$B$38,"AJUSTE+")-SUMIFS($F$4:$F$38,$C$4:$C$38,C39,$D$4:$D$38,D39,$E$4:$E$38,E39,$B$4:$B$38,"A CORTE")-SUMIFS($F$4:$F$38,$C$4:$C$38,C39,$D$4:$D$38,D39,$E$4:$E$38,E39,$B$4:$B$38,"A REPROCESO")-SUMIFS($F$4:$F$38,$C$4:$C$38,C39,$D$4:$D$38,D39,$E$4:$E$38,E39,$B$4:$B$38,"MUESTRA")-SUMIFS($F$4:$F$38,$C$4:$C$38,C39,$D$4:$D$38,D39,$E$4:$E$38,E39,$B$4:$B$38,"AJUSTE-")),0) -> 0 | L39: =IF(C39="",0,K39+IF(OR(B39="INGRESO",B39="DE REPROCESO",B39="AJUSTE+"),F39,IF(OR(B39="A CORTE",B39="A REPROCESO",B39="MUESTRA",B39="AJUSTE-"),-F39,0))) -> 15 | M39: tomas | O39: progreso | R39: =IF(OR(Q39="",Q39=0,J39=0),"",(Q39-J39)/J39)
A40: 46147 | B40: INGRESO | C40: OverShark | D40: wafle 30/1 | E40: Cemento | F40: 14 | G40: =IFERROR(F40*VLOOKUP(D40,TELAS!$A$4:$C$32,3,FALSE()),0) -> 280 | H40: =IFERROR(VLOOKUP(E40,COLORES!$A$4:$B$102,2,FALSE()),"") -> CLARO | I40: =IFERROR(IF(H40="OSCURO",VLOOKUP(D40,PRECIOS!$A$4:$F$32,2,FALSE()),IF(H40="CLARO",VLOOKUP(D40,PRECIOS!$A$4:$F$32,3,FALSE()),IF(H40="MELANGE",VLOOKUP(D40,PRECIOS!$A$4:$F$32,4,FALSE()),IF(H40="PPT",VLOOKUP(D40,PRECIOS!$A$4:$F$32,5,FALSE()),0)))),0) -> 22.5 | J40: =IFERROR(G40*I40,0) -> 6300 | K40: =IFERROR(IF(C40="",0,SUMIFS($F$4:$F$39,$C$4:$C$39,C40,$D$4:$D$39,D40,$E$4:$E$39,E40,$B$4:$B$39,"INGRESO")+SUMIFS($F$4:$F$39,$C$4:$C$39,C40,$D$4:$D$39,D40,$E$4:$E$39,E40,$B$4:$B$39,"DE REPROCESO")+SUMIFS($F$4:$F$39,$C$4:$C$39,C40,$D$4:$D$39,D40,$E$4:$E$39,E40,$B$4:$B$39,"AJUSTE+")-SUMIFS($F$4:$F$39,$C$4:$C$39,C40,$D$4:$D$39,D40,$E$4:$E$39,E40,$B$4:$B$39,"A CORTE")-SUMIFS($F$4:$F$39,$C$4:$C$39,C40,$D$4:$D$39,D40,$E$4:$E$39,E40,$B$4:$B$39,"A REPROCESO")-SUMIFS($F$4:$F$39,$C$4:$C$39,C40,$D$4:$D$39,D40,$E$4:$E$39,E40,$B$4:$B$39,"MUESTRA")-SUMIFS($F$4:$F$39,$C$4:$C$39,C40,$D$4:$D$39,D40,$E$4:$E$39,E40,$B$4:$B$39,"AJUSTE-")),0) -> 0 | L40: =IF(C40="",0,K40+IF(OR(B40="INGRESO",B40="DE REPROCESO",B40="AJUSTE+"),F40,IF(OR(B40="A CORTE",B40="A REPROCESO",B40="MUESTRA",B40="AJUSTE-"),-F40,0))) -> 14 | M40: tomas | O40: progreso | R40: =IF(OR(Q40="",Q40=0,J40=0),"",(Q40-J40)/J40)
A41: 46147 | B41: INGRESO | C41: OverShark | D41: wafle 30/1 | E41: P. Rosa | F41: 17 | G41: =IFERROR(F41*VLOOKUP(D41,TELAS!$A$4:$C$32,3,FALSE()),0) -> 340 | H41: =IFERROR(VLOOKUP(E41,COLORES!$A$4:$B$102,2,FALSE()),"") -> CLARO | I41: =IFERROR(IF(H41="OSCURO",VLOOKUP(D41,PRECIOS!$A$4:$F$32,2,FALSE()),IF(H41="CLARO",VLOOKUP(D41,PRECIOS!$A$4:$F$32,3,FALSE()),IF(H41="MELANGE",VLOOKUP(D41,PRECIOS!$A$4:$F$32,4,FALSE()),IF(H41="PPT",VLOOKUP(D41,PRECIOS!$A$4:$F$32,5,FALSE()),0)))),0) -> 22.5 | J41: =IFERROR(G41*I41,0) -> 7650 | K41: =IFERROR(IF(C41="",0,SUMIFS($F$4:$F$40,$C$4:$C$40,C41,$D$4:$D$40,D41,$E$4:$E$40,E41,$B$4:$B$40,"INGRESO")+SUMIFS($F$4:$F$40,$C$4:$C$40,C41,$D$4:$D$40,D41,$E$4:$E$40,E41,$B$4:$B$40,"DE REPROCESO")+SUMIFS($F$4:$F$40,$C$4:$C$40,C41,$D$4:$D$40,D41,$E$4:$E$40,E41,$B$4:$B$40,"AJUSTE+")-SUMIFS($F$4:$F$40,$C$4:$C$40,C41,$D$4:$D$40,D41,$E$4:$E$40,E41,$B$4:$B$40,"A CORTE")-SUMIFS($F$4:$F$40,$C$4:$C$40,C41,$D$4:$D$40,D41,$E$4:$E$40,E41,$B$4:$B$40,"A REPROCESO")-SUMIFS($F$4:$F$40,$C$4:$C$40,C41,$D$4:$D$40,D41,$E$4:$E$40,E41,$B$4:$B$40,"MUESTRA")-SUMIFS($F$4:$F$40,$C$4:$C$40,C41,$D$4:$D$40,D41,$E$4:$E$40,E41,$B$4:$B$40,"AJUSTE-")),0) -> 0 | L41: =IF(C41="",0,K41+IF(OR(B41="INGRESO",B41="DE REPROCESO",B41="AJUSTE+"),F41,IF(OR(B41="A CORTE",B41="A REPROCESO",B41="MUESTRA",B41="AJUSTE-"),-F41,0))) -> 17 | M41: tomas | O41: progreso | R41: =IF(OR(Q41="",Q41=0,J41=0),"",(Q41-J41)/J41)
A42: 46147 | B42: INGRESO | C42: OverShark | D42: wafle 30/1 | E42: Topo | F42: 11 | G42: =IFERROR(F42*VLOOKUP(D42,TELAS!$A$4:$C$32,3,FALSE()),0) -> 220 | H42: =IFERROR(VLOOKUP(E42,COLORES!$A$4:$B$102,2,FALSE()),"") -> CLARO | I42: =IFERROR(IF(H42="OSCURO",VLOOKUP(D42,PRECIOS!$A$4:$F$32,2,FALSE()),IF(H42="CLARO",VLOOKUP(D42,PRECIOS!$A$4:$F$32,3,FALSE()),IF(H42="MELANGE",VLOOKUP(D42,PRECIOS!$A$4:$F$32,4,FALSE()),IF(H42="PPT",VLOOKUP(D42,PRECIOS!$A$4:$F$32,5,FALSE()),0)))),0) -> 22.5 | J42: =IFERROR(G42*I42,0) -> 4950 | K42: =IFERROR(IF(C42="",0,SUMIFS($F$4:$F$41,$C$4:$C$41,C42,$D$4:$D$41,D42,$E$4:$E$41,E42,$B$4:$B$41,"INGRESO")+SUMIFS($F$4:$F$41,$C$4:$C$41,C42,$D$4:$D$41,D42,$E$4:$E$41,E42,$B$4:$B$41,"DE REPROCESO")+SUMIFS($F$4:$F$41,$C$4:$C$41,C42,$D$4:$D$41,D42,$E$4:$E$41,E42,$B$4:$B$41,"AJUSTE+")-SUMIFS($F$4:$F$41,$C$4:$C$41,C42,$D$4:$D$41,D42,$E$4:$E$41,E42,$B$4:$B$41,"A CORTE")-SUMIFS($F$4:$F$41,$C$4:$C$41,C42,$D$4:$D$41,D42,$E$4:$E$41,E42,$B$4:$B$41,"A REPROCESO")-SUMIFS($F$4:$F$41,$C$4:$C$41,C42,$D$4:$D$41,D42,$E$4:$E$41,E42,$B$4:$B$41,"MUESTRA")-SUMIFS($F$4:$F$41,$C$4:$C$41,C42,$D$4:$D$41,D42,$E$4:$E$41,E42,$B$4:$B$41,"AJUSTE-")),0) -> 0 | L42: =IF(C42="",0,K42+IF(OR(B42="INGRESO",B42="DE REPROCESO",B42="AJUSTE+"),F42,IF(OR(B42="A CORTE",B42="A REPROCESO",B42="MUESTRA",B42="AJUSTE-"),-F42,0))) -> 11 | M42: tomas | O42: progreso | R42: =IF(OR(Q42="",Q42=0,J42=0),"",(Q42-J42)/J42)
A43: 46147 | B43: INGRESO | C43: OverShark | D43: wafle 30/1 | E43: Beige | F43: 7 | G43: =IFERROR(F43*VLOOKUP(D43,TELAS!$A$4:$C$32,3,FALSE()),0) -> 140 | H43: =IFERROR(VLOOKUP(E43,COLORES!$A$4:$B$102,2,FALSE()),"") -> CLARO | I43: =IFERROR(IF(H43="OSCURO",VLOOKUP(D43,PRECIOS!$A$4:$F$32,2,FALSE()),IF(H43="CLARO",VLOOKUP(D43,PRECIOS!$A$4:$F$32,3,FALSE()),IF(H43="MELANGE",VLOOKUP(D43,PRECIOS!$A$4:$F$32,4,FALSE()),IF(H43="PPT",VLOOKUP(D43,PRECIOS!$A$4:$F$32,5,FALSE()),0)))),0) -> 22.5 | J43: =IFERROR(G43*I43,0) -> 3150 | K43: =IFERROR(IF(C43="",0,SUMIFS($F$4:$F$42,$C$4:$C$42,C43,$D$4:$D$42,D43,$E$4:$E$42,E43,$B$4:$B$42,"INGRESO")+SUMIFS($F$4:$F$42,$C$4:$C$42,C43,$D$4:$D$42,D43,$E$4:$E$42,E43,$B$4:$B$42,"DE REPROCESO")+SUMIFS($F$4:$F$42,$C$4:$C$42,C43,$D$4:$D$42,D43,$E$4:$E$42,E43,$B$4:$B$42,"AJUSTE+")-SUMIFS($F$4:$F$42,$C$4:$C$42,C43,$D$4:$D$42,D43,$E$4:$E$42,E43,$B$4:$B$42,"A CORTE")-SUMIFS($F$4:$F$42,$C$4:$C$42,C43,$D$4:$D$42,D43,$E$4:$E$42,E43,$B$4:$B$42,"A REPROCESO")-SUMIFS($F$4:$F$42,$C$4:$C$42,C43,$D$4:$D$42,D43,$E$4:$E$42,E43,$B$4:$B$42,"MUESTRA")-SUMIFS($F$4:$F$42,$C$4:$C$42,C43,$D$4:$D$42,D43,$E$4:$E$42,E43,$B$4:$B$42,"AJUSTE-")),0) -> 0 | L43: =IF(C43="",0,K43+IF(OR(B43="INGRESO",B43="DE REPROCESO",B43="AJUSTE+"),F43,IF(OR(B43="A CORTE",B43="A REPROCESO",B43="MUESTRA",B43="AJUSTE-"),-F43,0))) -> 7 | M43: tomas | O43: progreso | R43: =IF(OR(Q43="",Q43=0,J43=0),"",(Q43-J43)/J43)
A44: 46147 | B44: INGRESO | C44: OverShark | D44: wafle 30/1 | E44: Vino | F44: 7 | G44: =IFERROR(F44*VLOOKUP(D44,TELAS!$A$4:$C$32,3,FALSE()),0) -> 140 | H44: =IFERROR(VLOOKUP(E44,COLORES!$A$4:$B$102,2,FALSE()),"") -> OSCURO | I44: =IFERROR(IF(H44="OSCURO",VLOOKUP(D44,PRECIOS!$A$4:$F$32,2,FALSE()),IF(H44="CLARO",VLOOKUP(D44,PRECIOS!$A$4:$F$32,3,FALSE()),IF(H44="MELANGE",VLOOKUP(D44,PRECIOS!$A$4:$F$32,4,FALSE()),IF(H44="PPT",VLOOKUP(D44,PRECIOS!$A$4:$F$32,5,FALSE()),0)))),0) -> 26 | J44: =IFERROR(G44*I44,0) -> 3640 | K44: =IFERROR(IF(C44="",0,SUMIFS($F$4:$F$43,$C$4:$C$43,C44,$D$4:$D$43,D44,$E$4:$E$43,E44,$B$4:$B$43,"INGRESO")+SUMIFS($F$4:$F$43,$C$4:$C$43,C44,$D$4:$D$43,D44,$E$4:$E$43,E44,$B$4:$B$43,"DE REPROCESO")+SUMIFS($F$4:$F$43,$C$4:$C$43,C44,$D$4:$D$43,D44,$E$4:$E$43,E44,$B$4:$B$43,"AJUSTE+")-SUMIFS($F$4:$F$43,$C$4:$C$43,C44,$D$4:$D$43,D44,$E$4:$E$43,E44,$B$4:$B$43,"A CORTE")-SUMIFS($F$4:$F$43,$C$4:$C$43,C44,$D$4:$D$43,D44,$E$4:$E$43,E44,$B$4:$B$43,"A REPROCESO")-SUMIFS($F$4:$F$43,$C$4:$C$43,C44,$D$4:$D$43,D44,$E$4:$E$43,E44,$B$4:$B$43,"MUESTRA")-SUMIFS($F$4:$F$43,$C$4:$C$43,C44,$D$4:$D$43,D44,$E$4:$E$43,E44,$B$4:$B$43,"AJUSTE-")),0) -> 0 | L44: =IF(C44="",0,K44+IF(OR(B44="INGRESO",B44="DE REPROCESO",B44="AJUSTE+"),F44,IF(OR(B44="A CORTE",B44="A REPROCESO",B44="MUESTRA",B44="AJUSTE-"),-F44,0))) -> 7 | M44: tomas | O44: progreso | R44: =IF(OR(Q44="",Q44=0,J44=0),"",(Q44-J44)/J44)
A45: 46147 | B45: INGRESO | C45: OverShark | D45: wafle 30/1 | E45: Denim | F45: 14 | G45: =IFERROR(F45*VLOOKUP(D45,TELAS!$A$4:$C$32,3,FALSE()),0) -> 280 | H45: =IFERROR(VLOOKUP(E45,COLORES!$A$4:$B$102,2,FALSE()),"") -> CLARO | I45: =IFERROR(IF(H45="OSCURO",VLOOKUP(D45,PRECIOS!$A$4:$F$32,2,FALSE()),IF(H45="CLARO",VLOOKUP(D45,PRECIOS!$A$4:$F$32,3,FALSE()),IF(H45="MELANGE",VLOOKUP(D45,PRECIOS!$A$4:$F$32,4,FALSE()),IF(H45="PPT",VLOOKUP(D45,PRECIOS!$A$4:$F$32,5,FALSE()),0)))),0) -> 22.5 | J45: =IFERROR(G45*I45,0) -> 6300 | K45: =IFERROR(IF(C45="",0,SUMIFS($F$4:$F$44,$C$4:$C$44,C45,$D$4:$D$44,D45,$E$4:$E$44,E45,$B$4:$B$44,"INGRESO")+SUMIFS($F$4:$F$44,$C$4:$C$44,C45,$D$4:$D$44,D45,$E$4:$E$44,E45,$B$4:$B$44,"DE REPROCESO")+SUMIFS($F$4:$F$44,$C$4:$C$44,C45,$D$4:$D$44,D45,$E$4:$E$44,E45,$B$4:$B$44,"AJUSTE+")-SUMIFS($F$4:$F$44,$C$4:$C$44,C45,$D$4:$D$44,D45,$E$4:$E$44,E45,$B$4:$B$44,"A CORTE")-SUMIFS($F$4:$F$44,$C$4:$C$44,C45,$D$4:$D$44,D45,$E$4:$E$44,E45,$B$4:$B$44,"A REPROCESO")-SUMIFS($F$4:$F$44,$C$4:$C$44,C45,$D$4:$D$44,D45,$E$4:$E$44,E45,$B$4:$B$44,"MUESTRA")-SUMIFS($F$4:$F$44,$C$4:$C$44,C45,$D$4:$D$44,D45,$E$4:$E$44,E45,$B$4:$B$44,"AJUSTE-")),0) -> 0 | L45: =IF(C45="",0,K45+IF(OR(B45="INGRESO",B45="DE REPROCESO",B45="AJUSTE+"),F45,IF(OR(B45="A CORTE",B45="A REPROCESO",B45="MUESTRA",B45="AJUSTE-"),-F45,0))) -> 14 | M45: tomas | O45: progreso | R45: =IF(OR(Q45="",Q45=0,J45=0),"",(Q45-J45)/J45)
A46: 46147 | B46: INGRESO | C46: OverShark | D46: wafle 30/1 | E46: Plomo | F46: 28 | G46: =IFERROR(F46*VLOOKUP(D46,TELAS!$A$4:$C$32,3,FALSE()),0) -> 560 | H46: =IFERROR(VLOOKUP(E46,COLORES!$A$4:$B$102,2,FALSE()),"") -> OSCURO | I46: =IFERROR(IF(H46="OSCURO",VLOOKUP(D46,PRECIOS!$A$4:$F$32,2,FALSE()),IF(H46="CLARO",VLOOKUP(D46,PRECIOS!$A$4:$F$32,3,FALSE()),IF(H46="MELANGE",VLOOKUP(D46,PRECIOS!$A$4:$F$32,4,FALSE()),IF(H46="PPT",VLOOKUP(D46,PRECIOS!$A$4:$F$32,5,FALSE()),0)))),0) -> 26 | J46: =IFERROR(G46*I46,0) -> 14560 | K46: =IFERROR(IF(C46="",0,SUMIFS($F$4:$F$45,$C$4:$C$45,C46,$D$4:$D$45,D46,$E$4:$E$45,E46,$B$4:$B$45,"INGRESO")+SUMIFS($F$4:$F$45,$C$4:$C$45,C46,$D$4:$D$45,D46,$E$4:$E$45,E46,$B$4:$B$45,"DE REPROCESO")+SUMIFS($F$4:$F$45,$C$4:$C$45,C46,$D$4:$D$45,D46,$E$4:$E$45,E46,$B$4:$B$45,"AJUSTE+")-SUMIFS($F$4:$F$45,$C$4:$C$45,C46,$D$4:$D$45,D46,$E$4:$E$45,E46,$B$4:$B$45,"A CORTE")-SUMIFS($F$4:$F$45,$C$4:$C$45,C46,$D$4:$D$45,D46,$E$4:$E$45,E46,$B$4:$B$45,"A REPROCESO")-SUMIFS($F$4:$F$45,$C$4:$C$45,C46,$D$4:$D$45,D46,$E$4:$E$45,E46,$B$4:$B$45,"MUESTRA")-SUMIFS($F$4:$F$45,$C$4:$C$45,C46,$D$4:$D$45,D46,$E$4:$E$45,E46,$B$4:$B$45,"AJUSTE-")),0) -> 0 | L46: =IF(C46="",0,K46+IF(OR(B46="INGRESO",B46="DE REPROCESO",B46="AJUSTE+"),F46,IF(OR(B46="A CORTE",B46="A REPROCESO",B46="MUESTRA",B46="AJUSTE-"),-F46,0))) -> 28 | M46: tomas | O46: progreso | R46: =IF(OR(Q46="",Q46=0,J46=0),"",(Q46-J46)/J46)
A47: 46147 | B47: INGRESO | C47: OverShark | D47: wafle 30/1 | E47: Melange | F47: 21 | G47: =IFERROR(F47*VLOOKUP(D47,TELAS!$A$4:$C$32,3,FALSE()),0) -> 420 | H47: =IFERROR(VLOOKUP(E47,COLORES!$A$4:$B$102,2,FALSE()),"") -> MELANGE | I47: =IFERROR(IF(H47="OSCURO",VLOOKUP(D47,PRECIOS!$A$4:$F$32,2,FALSE()),IF(H47="CLARO",VLOOKUP(D47,PRECIOS!$A$4:$F$32,3,FALSE()),IF(H47="MELANGE",VLOOKUP(D47,PRECIOS!$A$4:$F$32,4,FALSE()),IF(H47="PPT",VLOOKUP(D47,PRECIOS!$A$4:$F$32,5,FALSE()),0)))),0) -> 19 | J47: =IFERROR(G47*I47,0) -> 7980 | K47: =IFERROR(IF(C47="",0,SUMIFS($F$4:$F$46,$C$4:$C$46,C47,$D$4:$D$46,D47,$E$4:$E$46,E47,$B$4:$B$46,"INGRESO")+SUMIFS($F$4:$F$46,$C$4:$C$46,C47,$D$4:$D$46,D47,$E$4:$E$46,E47,$B$4:$B$46,"DE REPROCESO")+SUMIFS($F$4:$F$46,$C$4:$C$46,C47,$D$4:$D$46,D47,$E$4:$E$46,E47,$B$4:$B$46,"AJUSTE+")-SUMIFS($F$4:$F$46,$C$4:$C$46,C47,$D$4:$D$46,D47,$E$4:$E$46,E47,$B$4:$B$46,"A CORTE")-SUMIFS($F$4:$F$46,$C$4:$C$46,C47,$D$4:$D$46,D47,$E$4:$E$46,E47,$B$4:$B$46,"A REPROCESO")-SUMIFS($F$4:$F$46,$C$4:$C$46,C47,$D$4:$D$46,D47,$E$4:$E$46,E47,$B$4:$B$46,"MUESTRA")-SUMIFS($F$4:$F$46,$C$4:$C$46,C47,$D$4:$D$46,D47,$E$4:$E$46,E47,$B$4:$B$46,"AJUSTE-")),0) -> 0 | L47: =IF(C47="",0,K47+IF(OR(B47="INGRESO",B47="DE REPROCESO",B47="AJUSTE+"),F47,IF(OR(B47="A CORTE",B47="A REPROCESO",B47="MUESTRA",B47="AJUSTE-"),-F47,0))) -> 21 | M47: tomas | O47: progreso | R47: =IF(OR(Q47="",Q47=0,J47=0),"",(Q47-J47)/J47)
A48: 46141 | B48: A CORTE | C48: OverShark | D48: jersey 30/1 | E48: Negro | F48: 4 | G48: =IFERROR(F48*VLOOKUP(D48,TELAS!$A$4:$C$32,3,FALSE()),0) -> 80 | H48: =IFERROR(VLOOKUP(E48,COLORES!$A$4:$B$102,2,FALSE()),"") -> OSCURO | I48: =IFERROR(IF(H48="OSCURO",VLOOKUP(D48,PRECIOS!$A$4:$F$32,2,FALSE()),IF(H48="CLARO",VLOOKUP(D48,PRECIOS!$A$4:$F$32,3,FALSE()),IF(H48="MELANGE",VLOOKUP(D48,PRECIOS!$A$4:$F$32,4,FALSE()),IF(H48="PPT",VLOOKUP(D48,PRECIOS!$A$4:$F$32,5,FALSE()),0)))),0) -> 24 | J48: =IFERROR(G48*I48,0) -> 1920 | K48: =IFERROR(IF(C48="",0,SUMIFS($F$4:$F$47,$C$4:$C$47,C48,$D$4:$D$47,D48,$E$4:$E$47,E48,$B$4:$B$47,"INGRESO")+SUMIFS($F$4:$F$47,$C$4:$C$47,C48,$D$4:$D$47,D48,$E$4:$E$47,E48,$B$4:$B$47,"DE REPROCESO")+SUMIFS($F$4:$F$47,$C$4:$C$47,C48,$D$4:$D$47,D48,$E$4:$E$47,E48,$B$4:$B$47,"AJUSTE+")-SUMIFS($F$4:$F$47,$C$4:$C$47,C48,$D$4:$D$47,D48,$E$4:$E$47,E48,$B$4:$B$47,"A CORTE")-SUMIFS($F$4:$F$47,$C$4:$C$47,C48,$D$4:$D$47,D48,$E$4:$E$47,E48,$B$4:$B$47,"A REPROCESO")-SUMIFS($F$4:$F$47,$C$4:$C$47,C48,$D$4:$D$47,D48,$E$4:$E$47,E48,$B$4:$B$47,"MUESTRA")-SUMIFS($F$4:$F$47,$C$4:$C$47,C48,$D$4:$D$47,D48,$E$4:$E$47,E48,$B$4:$B$47,"AJUSTE-")),0) -> 29 | L48: =IF(C48="",0,K48+IF(OR(B48="INGRESO",B48="DE REPROCESO",B48="AJUSTE+"),F48,IF(OR(B48="A CORTE",B48="A REPROCESO",B48="MUESTRA",B48="AJUSTE-"),-F48,0))) -> 25 | M48: tomas | N48: Manga Larga | R48: =IF(OR(Q48="",Q48=0,J48=0),"",(Q48-J48)/J48)
A49: 46141 | B49: A CORTE | C49: OverShark | D49: jersey 30/1 | E49: Cemento | F49: 5 | G49: =IFERROR(F49*VLOOKUP(D49,TELAS!$A$4:$C$32,3,FALSE()),0) -> 100 | H49: =IFERROR(VLOOKUP(E49,COLORES!$A$4:$B$102,2,FALSE()),"") -> CLARO | I49: =IFERROR(IF(H49="OSCURO",VLOOKUP(D49,PRECIOS!$A$4:$F$32,2,FALSE()),IF(H49="CLARO",VLOOKUP(D49,PRECIOS!$A$4:$F$32,3,FALSE()),IF(H49="MELANGE",VLOOKUP(D49,PRECIOS!$A$4:$F$32,4,FALSE()),IF(H49="PPT",VLOOKUP(D49,PRECIOS!$A$4:$F$32,5,FALSE()),0)))),0) -> 21 | J49: =IFERROR(G49*I49,0) -> 2100 | K49: =IFERROR(IF(C49="",0,SUMIFS($F$4:$F$48,$C$4:$C$48,C49,$D$4:$D$48,D49,$E$4:$E$48,E49,$B$4:$B$48,"INGRESO")+SUMIFS($F$4:$F$48,$C$4:$C$48,C49,$D$4:$D$48,D49,$E$4:$E$48,E49,$B$4:$B$48,"DE REPROCESO")+SUMIFS($F$4:$F$48,$C$4:$C$48,C49,$D$4:$D$48,D49,$E$4:$E$48,E49,$B$4:$B$48,"AJUSTE+")-SUMIFS($F$4:$F$48,$C$4:$C$48,C49,$D$4:$D$48,D49,$E$4:$E$48,E49,$B$4:$B$48,"A CORTE")-SUMIFS($F$4:$F$48,$C$4:$C$48,C49,$D$4:$D$48,D49,$E$4:$E$48,E49,$B$4:$B$48,"A REPROCESO")-SUMIFS($F$4:$F$48,$C$4:$C$48,C49,$D$4:$D$48,D49,$E$4:$E$48,E49,$B$4:$B$48,"MUESTRA")-SUMIFS($F$4:$F$48,$C$4:$C$48,C49,$D$4:$D$48,D49,$E$4:$E$48,E49,$B$4:$B$48,"AJUSTE-")),0) -> 23 | L49: =IF(C49="",0,K49+IF(OR(B49="INGRESO",B49="DE REPROCESO",B49="AJUSTE+"),F49,IF(OR(B49="A CORTE",B49="A REPROCESO",B49="MUESTRA",B49="AJUSTE-"),-F49,0))) -> 18 | M49: tomas | N49: Manga Larga | R49: =IF(OR(Q49="",Q49=0,J49=0),"",(Q49-J49)/J49)
A50: 46141 | B50: A CORTE | C50: OverShark | D50: jersey 30/1 | E50: P. Rosa | F50: 5 | G50: =IFERROR(F50*VLOOKUP(D50,TELAS!$A$4:$C$32,3,FALSE()),0) -> 100 | H50: =IFERROR(VLOOKUP(E50,COLORES!$A$4:$B$102,2,FALSE()),"") -> CLARO | I50: =IFERROR(IF(H50="OSCURO",VLOOKUP(D50,PRECIOS!$A$4:$F$32,2,FALSE()),IF(H50="CLARO",VLOOKUP(D50,PRECIOS!$A$4:$F$32,3,FALSE()),IF(H50="MELANGE",VLOOKUP(D50,PRECIOS!$A$4:$F$32,4,FALSE()),IF(H50="PPT",VLOOKUP(D50,PRECIOS!$A$4:$F$32,5,FALSE()),0)))),0) -> 21 | J50: =IFERROR(G50*I50,0) -> 2100 | K50: =IFERROR(IF(C50="",0,SUMIFS($F$4:$F$49,$C$4:$C$49,C50,$D$4:$D$49,D50,$E$4:$E$49,E50,$B$4:$B$49,"INGRESO")+SUMIFS($F$4:$F$49,$C$4:$C$49,C50,$D$4:$D$49,D50,$E$4:$E$49,E50,$B$4:$B$49,"DE REPROCESO")+SUMIFS($F$4:$F$49,$C$4:$C$49,C50,$D$4:$D$49,D50,$E$4:$E$49,E50,$B$4:$B$49,"AJUSTE+")-SUMIFS($F$4:$F$49,$C$4:$C$49,C50,$D$4:$D$49,D50,$E$4:$E$49,E50,$B$4:$B$49,"A CORTE")-SUMIFS($F$4:$F$49,$C$4:$C$49,C50,$D$4:$D$49,D50,$E$4:$E$49,E50,$B$4:$B$49,"A REPROCESO")-SUMIFS($F$4:$F$49,$C$4:$C$49,C50,$D$4:$D$49,D50,$E$4:$E$49,E50,$B$4:$B$49,"MUESTRA")-SUMIFS($F$4:$F$49,$C$4:$C$49,C50,$D$4:$D$49,D50,$E$4:$E$49,E50,$B$4:$B$49,"AJUSTE-")),0) -> 24 | L50: =IF(C50="",0,K50+IF(OR(B50="INGRESO",B50="DE REPROCESO",B50="AJUSTE+"),F50,IF(OR(B50="A CORTE",B50="A REPROCESO",B50="MUESTRA",B50="AJUSTE-"),-F50,0))) -> 19 | M50: tomas | N50: Manga Larga | R50: =IF(OR(Q50="",Q50=0,J50=0),"",(Q50-J50)/J50)
A51: 46141 | B51: A CORTE | C51: OverShark | D51: jersey 30/1 | E51: Vino | F51: 4 | G51: =IFERROR(F51*VLOOKUP(D51,TELAS!$A$4:$C$32,3,FALSE()),0) -> 80 | H51: =IFERROR(VLOOKUP(E51,COLORES!$A$4:$B$102,2,FALSE()),"") -> OSCURO | I51: =IFERROR(IF(H51="OSCURO",VLOOKUP(D51,PRECIOS!$A$4:$F$32,2,FALSE()),IF(H51="CLARO",VLOOKUP(D51,PRECIOS!$A$4:$F$32,3,FALSE()),IF(H51="MELANGE",VLOOKUP(D51,PRECIOS!$A$4:$F$32,4,FALSE()),IF(H51="PPT",VLOOKUP(D51,PRECIOS!$A$4:$F$32,5,FALSE()),0)))),0) -> 24 | J51: =IFERROR(G51*I51,0) -> 1920 | K51: =IFERROR(IF(C51="",0,SUMIFS($F$4:$F$50,$C$4:$C$50,C51,$D$4:$D$50,D51,$E$4:$E$50,E51,$B$4:$B$50,"INGRESO")+SUMIFS($F$4:$F$50,$C$4:$C$50,C51,$D$4:$D$50,D51,$E$4:$E$50,E51,$B$4:$B$50,"DE REPROCESO")+SUMIFS($F$4:$F$50,$C$4:$C$50,C51,$D$4:$D$50,D51,$E$4:$E$50,E51,$B$4:$B$50,"AJUSTE+")-SUMIFS($F$4:$F$50,$C$4:$C$50,C51,$D$4:$D$50,D51,$E$4:$E$50,E51,$B$4:$B$50,"A CORTE")-SUMIFS($F$4:$F$50,$C$4:$C$50,C51,$D$4:$D$50,D51,$E$4:$E$50,E51,$B$4:$B$50,"A REPROCESO")-SUMIFS($F$4:$F$50,$C$4:$C$50,C51,$D$4:$D$50,D51,$E$4:$E$50,E51,$B$4:$B$50,"MUESTRA")-SUMIFS($F$4:$F$50,$C$4:$C$50,C51,$D$4:$D$50,D51,$E$4:$E$50,E51,$B$4:$B$50,"AJUSTE-")),0) -> 18 | L51: =IF(C51="",0,K51+IF(OR(B51="INGRESO",B51="DE REPROCESO",B51="AJUSTE+"),F51,IF(OR(B51="A CORTE",B51="A REPROCESO",B51="MUESTRA",B51="AJUSTE-"),-F51,0))) -> 14 | M51: tomas | N51: Manga Larga | R51: =IF(OR(Q51="",Q51=0,J51=0),"",(Q51-J51)/J51)
A52: 46141 | B52: A CORTE | C52: OverShark | D52: jersey 30/1 | E52: Denim | F52: 3 | G52: =IFERROR(F52*VLOOKUP(D52,TELAS!$A$4:$C$32,3,FALSE()),0) -> 60 | H52: =IFERROR(VLOOKUP(E52,COLORES!$A$4:$B$102,2,FALSE()),"") -> CLARO | I52: =IFERROR(IF(H52="OSCURO",VLOOKUP(D52,PRECIOS!$A$4:$F$32,2,FALSE()),IF(H52="CLARO",VLOOKUP(D52,PRECIOS!$A$4:$F$32,3,FALSE()),IF(H52="MELANGE",VLOOKUP(D52,PRECIOS!$A$4:$F$32,4,FALSE()),IF(H52="PPT",VLOOKUP(D52,PRECIOS!$A$4:$F$32,5,FALSE()),0)))),0) -> 21 | J52: =IFERROR(G52*I52,0) -> 1260 | K52: =IFERROR(IF(C52="",0,SUMIFS($F$4:$F$51,$C$4:$C$51,C52,$D$4:$D$51,D52,$E$4:$E$51,E52,$B$4:$B$51,"INGRESO")+SUMIFS($F$4:$F$51,$C$4:$C$51,C52,$D$4:$D$51,D52,$E$4:$E$51,E52,$B$4:$B$51,"DE REPROCESO")+SUMIFS($F$4:$F$51,$C$4:$C$51,C52,$D$4:$D$51,D52,$E$4:$E$51,E52,$B$4:$B$51,"AJUSTE+")-SUMIFS($F$4:$F$51,$C$4:$C$51,C52,$D$4:$D$51,D52,$E$4:$E$51,E52,$B$4:$B$51,"A CORTE")-SUMIFS($F$4:$F$51,$C$4:$C$51,C52,$D$4:$D$51,D52,$E$4:$E$51,E52,$B$4:$B$51,"A REPROCESO")-SUMIFS($F$4:$F$51,$C$4:$C$51,C52,$D$4:$D$51,D52,$E$4:$E$51,E52,$B$4:$B$51,"MUESTRA")-SUMIFS($F$4:$F$51,$C$4:$C$51,C52,$D$4:$D$51,D52,$E$4:$E$51,E52,$B$4:$B$51,"AJUSTE-")),0) -> 18 | L52: =IF(C52="",0,K52+IF(OR(B52="INGRESO",B52="DE REPROCESO",B52="AJUSTE+"),F52,IF(OR(B52="A CORTE",B52="A REPROCESO",B52="MUESTRA",B52="AJUSTE-"),-F52,0))) -> 15 | M52: tomas | N52: Manga Larga | R52: =IF(OR(Q52="",Q52=0,J52=0),"",(Q52-J52)/J52)
A53: 46141 | B53: A CORTE | C53: OverShark | D53: jersey 30/1 | E53: Perla | F53: 2 | G53: =IFERROR(F53*VLOOKUP(D53,TELAS!$A$4:$C$32,3,FALSE()),0) -> 40 | H53: =IFERROR(VLOOKUP(E53,COLORES!$A$4:$B$102,2,FALSE()),"") -> PPT | I53: =IFERROR(IF(H53="OSCURO",VLOOKUP(D53,PRECIOS!$A$4:$F$32,2,FALSE()),IF(H53="CLARO",VLOOKUP(D53,PRECIOS!$A$4:$F$32,3,FALSE()),IF(H53="MELANGE",VLOOKUP(D53,PRECIOS!$A$4:$F$32,4,FALSE()),IF(H53="PPT",VLOOKUP(D53,PRECIOS!$A$4:$F$32,5,FALSE()),0)))),0) -> 18 | J53: =IFERROR(G53*I53,0) -> 720 | K53: =IFERROR(IF(C53="",0,SUMIFS($F$4:$F$52,$C$4:$C$52,C53,$D$4:$D$52,D53,$E$4:$E$52,E53,$B$4:$B$52,"INGRESO")+SUMIFS($F$4:$F$52,$C$4:$C$52,C53,$D$4:$D$52,D53,$E$4:$E$52,E53,$B$4:$B$52,"DE REPROCESO")+SUMIFS($F$4:$F$52,$C$4:$C$52,C53,$D$4:$D$52,D53,$E$4:$E$52,E53,$B$4:$B$52,"AJUSTE+")-SUMIFS($F$4:$F$52,$C$4:$C$52,C53,$D$4:$D$52,D53,$E$4:$E$52,E53,$B$4:$B$52,"A CORTE")-SUMIFS($F$4:$F$52,$C$4:$C$52,C53,$D$4:$D$52,D53,$E$4:$E$52,E53,$B$4:$B$52,"A REPROCESO")-SUMIFS($F$4:$F$52,$C$4:$C$52,C53,$D$4:$D$52,D53,$E$4:$E$52,E53,$B$4:$B$52,"MUESTRA")-SUMIFS($F$4:$F$52,$C$4:$C$52,C53,$D$4:$D$52,D53,$E$4:$E$52,E53,$B$4:$B$52,"AJUSTE-")),0) -> 48 | L53: =IF(C53="",0,K53+IF(OR(B53="INGRESO",B53="DE REPROCESO",B53="AJUSTE+"),F53,IF(OR(B53="A CORTE",B53="A REPROCESO",B53="MUESTRA",B53="AJUSTE-"),-F53,0))) -> 46 | M53: tomas | N53: Manga Larga | R53: =IF(OR(Q53="",Q53=0,J53=0),"",(Q53-J53)/J53)
A54: 46149 | B54: A CORTE | C54: Bravos | D54: french terry 24/1 | E54: Negro | F54: 4 | G54: =IFERROR(F54*VLOOKUP(D54,TELAS!$A$4:$C$32,3,FALSE()),0) -> 80 | H54: =IFERROR(VLOOKUP(E54,COLORES!$A$4:$B$102,2,FALSE()),"") -> OSCURO | I54: =IFERROR(IF(H54="OSCURO",VLOOKUP(D54,PRECIOS!$A$4:$F$32,2,FALSE()),IF(H54="CLARO",VLOOKUP(D54,PRECIOS!$A$4:$F$32,3,FALSE()),IF(H54="MELANGE",VLOOKUP(D54,PRECIOS!$A$4:$F$32,4,FALSE()),IF(H54="PPT",VLOOKUP(D54,PRECIOS!$A$4:$F$32,5,FALSE()),0)))),0) -> 24 | J54: =IFERROR(G54*I54,0) -> 1920 | K54: =IFERROR(IF(C54="",0,SUMIFS($F$4:$F$53,$C$4:$C$53,C54,$D$4:$D$53,D54,$E$4:$E$53,E54,$B$4:$B$53,"INGRESO")+SUMIFS($F$4:$F$53,$C$4:$C$53,C54,$D$4:$D$53,D54,$E$4:$E$53,E54,$B$4:$B$53,"DE REPROCESO")+SUMIFS($F$4:$F$53,$C$4:$C$53,C54,$D$4:$D$53,D54,$E$4:$E$53,E54,$B$4:$B$53,"AJUSTE+")-SUMIFS($F$4:$F$53,$C$4:$C$53,C54,$D$4:$D$53,D54,$E$4:$E$53,E54,$B$4:$B$53,"A CORTE")-SUMIFS($F$4:$F$53,$C$4:$C$53,C54,$D$4:$D$53,D54,$E$4:$E$53,E54,$B$4:$B$53,"A REPROCESO")-SUMIFS($F$4:$F$53,$C$4:$C$53,C54,$D$4:$D$53,D54,$E$4:$E$53,E54,$B$4:$B$53,"MUESTRA")-SUMIFS($F$4:$F$53,$C$4:$C$53,C54,$D$4:$D$53,D54,$E$4:$E$53,E54,$B$4:$B$53,"AJUSTE-")),0) -> 37 | L54: =IF(C54="",0,K54+IF(OR(B54="INGRESO",B54="DE REPROCESO",B54="AJUSTE+"),F54,IF(OR(B54="A CORTE",B54="A REPROCESO",B54="MUESTRA",B54="AJUSTE-"),-F54,0))) -> 33 | M54: tomas | N54: Polera Neru | R54: =IF(OR(Q54="",Q54=0,J54=0),"",(Q54-J54)/J54)
A55: 46149 | B55: A CORTE | C55: Bravos | D55: french terry 24/1 | E55: Azul | F55: 5 | G55: =IFERROR(F55*VLOOKUP(D55,TELAS!$A$4:$C$32,3,FALSE()),0) -> 100 | H55: =IFERROR(VLOOKUP(E55,COLORES!$A$4:$B$102,2,FALSE()),"") -> OSCURO | I55: =IFERROR(IF(H55="OSCURO",VLOOKUP(D55,PRECIOS!$A$4:$F$32,2,FALSE()),IF(H55="CLARO",VLOOKUP(D55,PRECIOS!$A$4:$F$32,3,FALSE()),IF(H55="MELANGE",VLOOKUP(D55,PRECIOS!$A$4:$F$32,4,FALSE()),IF(H55="PPT",VLOOKUP(D55,PRECIOS!$A$4:$F$32,5,FALSE()),0)))),0) -> 24 | J55: =IFERROR(G55*I55,0) -> 2400 | K55: =IFERROR(IF(C55="",0,SUMIFS($F$4:$F$54,$C$4:$C$54,C55,$D$4:$D$54,D55,$E$4:$E$54,E55,$B$4:$B$54,"INGRESO")+SUMIFS($F$4:$F$54,$C$4:$C$54,C55,$D$4:$D$54,D55,$E$4:$E$54,E55,$B$4:$B$54,"DE REPROCESO")+SUMIFS($F$4:$F$54,$C$4:$C$54,C55,$D$4:$D$54,D55,$E$4:$E$54,E55,$B$4:$B$54,"AJUSTE+")-SUMIFS($F$4:$F$54,$C$4:$C$54,C55,$D$4:$D$54,D55,$E$4:$E$54,E55,$B$4:$B$54,"A CORTE")-SUMIFS($F$4:$F$54,$C$4:$C$54,C55,$D$4:$D$54,D55,$E$4:$E$54,E55,$B$4:$B$54,"A REPROCESO")-SUMIFS($F$4:$F$54,$C$4:$C$54,C55,$D$4:$D$54,D55,$E$4:$E$54,E55,$B$4:$B$54,"MUESTRA")-SUMIFS($F$4:$F$54,$C$4:$C$54,C55,$D$4:$D$54,D55,$E$4:$E$54,E55,$B$4:$B$54,"AJUSTE-")),0) -> 7 | L55: =IF(C55="",0,K55+IF(OR(B55="INGRESO",B55="DE REPROCESO",B55="AJUSTE+"),F55,IF(OR(B55="A CORTE",B55="A REPROCESO",B55="MUESTRA",B55="AJUSTE-"),-F55,0))) -> 2 | M55: tomas | N55: Polera Neru | R55: =IF(OR(Q55="",Q55=0,J55=0),"",(Q55-J55)/J55)
A56: 46149 | B56: A CORTE | C56: Bravos | D56: french terry 24/1 | E56: Botella | F56: 5 | G56: =IFERROR(F56*VLOOKUP(D56,TELAS!$A$4:$C$32,3,FALSE()),0) -> 100 | H56: =IFERROR(VLOOKUP(E56,COLORES!$A$4:$B$102,2,FALSE()),"") -> OSCURO | I56: =IFERROR(IF(H56="OSCURO",VLOOKUP(D56,PRECIOS!$A$4:$F$32,2,FALSE()),IF(H56="CLARO",VLOOKUP(D56,PRECIOS!$A$4:$F$32,3,FALSE()),IF(H56="MELANGE",VLOOKUP(D56,PRECIOS!$A$4:$F$32,4,FALSE()),IF(H56="PPT",VLOOKUP(D56,PRECIOS!$A$4:$F$32,5,FALSE()),0)))),0) -> 24 | J56: =IFERROR(G56*I56,0) -> 2400 | K56: =IFERROR(IF(C56="",0,SUMIFS($F$4:$F$55,$C$4:$C$55,C56,$D$4:$D$55,D56,$E$4:$E$55,E56,$B$4:$B$55,"INGRESO")+SUMIFS($F$4:$F$55,$C$4:$C$55,C56,$D$4:$D$55,D56,$E$4:$E$55,E56,$B$4:$B$55,"DE REPROCESO")+SUMIFS($F$4:$F$55,$C$4:$C$55,C56,$D$4:$D$55,D56,$E$4:$E$55,E56,$B$4:$B$55,"AJUSTE+")-SUMIFS($F$4:$F$55,$C$4:$C$55,C56,$D$4:$D$55,D56,$E$4:$E$55,E56,$B$4:$B$55,"A CORTE")-SUMIFS($F$4:$F$55,$C$4:$C$55,C56,$D$4:$D$55,D56,$E$4:$E$55,E56,$B$4:$B$55,"A REPROCESO")-SUMIFS($F$4:$F$55,$C$4:$C$55,C56,$D$4:$D$55,D56,$E$4:$E$55,E56,$B$4:$B$55,"MUESTRA")-SUMIFS($F$4:$F$55,$C$4:$C$55,C56,$D$4:$D$55,D56,$E$4:$E$55,E56,$B$4:$B$55,"AJUSTE-")),0) -> 5 | L56: =IF(C56="",0,K56+IF(OR(B56="INGRESO",B56="DE REPROCESO",B56="AJUSTE+"),F56,IF(OR(B56="A CORTE",B56="A REPROCESO",B56="MUESTRA",B56="AJUSTE-"),-F56,0))) -> 0 | M56: tomas | N56: Polera Neru | R56: =IF(OR(Q56="",Q56=0,J56=0),"",(Q56-J56)/J56)
A57: 46149 | B57: A CORTE | C57: Bravos | D57: french terry 24/1 | E57: Pacay | F57: 1 | G57: =IFERROR(F57*VLOOKUP(D57,TELAS!$A$4:$C$32,3,FALSE()),0) -> 20 | H57: =IFERROR(VLOOKUP(E57,COLORES!$A$4:$B$102,2,FALSE()),"") -> CLARO | I57: =IFERROR(IF(H57="OSCURO",VLOOKUP(D57,PRECIOS!$A$4:$F$32,2,FALSE()),IF(H57="CLARO",VLOOKUP(D57,PRECIOS!$A$4:$F$32,3,FALSE()),IF(H57="MELANGE",VLOOKUP(D57,PRECIOS!$A$4:$F$32,4,FALSE()),IF(H57="PPT",VLOOKUP(D57,PRECIOS!$A$4:$F$32,5,FALSE()),0)))),0) -> 21 | J57: =IFERROR(G57*I57,0) -> 420 | K57: =IFERROR(IF(C57="",0,SUMIFS($F$4:$F$56,$C$4:$C$56,C57,$D$4:$D$56,D57,$E$4:$E$56,E57,$B$4:$B$56,"INGRESO")+SUMIFS($F$4:$F$56,$C$4:$C$56,C57,$D$4:$D$56,D57,$E$4:$E$56,E57,$B$4:$B$56,"DE REPROCESO")+SUMIFS($F$4:$F$56,$C$4:$C$56,C57,$D$4:$D$56,D57,$E$4:$E$56,E57,$B$4:$B$56,"AJUSTE+")-SUMIFS($F$4:$F$56,$C$4:$C$56,C57,$D$4:$D$56,D57,$E$4:$E$56,E57,$B$4:$B$56,"A CORTE")-SUMIFS($F$4:$F$56,$C$4:$C$56,C57,$D$4:$D$56,D57,$E$4:$E$56,E57,$B$4:$B$56,"A REPROCESO")-SUMIFS($F$4:$F$56,$C$4:$C$56,C57,$D$4:$D$56,D57,$E$4:$E$56,E57,$B$4:$B$56,"MUESTRA")-SUMIFS($F$4:$F$56,$C$4:$C$56,C57,$D$4:$D$56,D57,$E$4:$E$56,E57,$B$4:$B$56,"AJUSTE-")),0) -> 1 | L57: =IF(C57="",0,K57+IF(OR(B57="INGRESO",B57="DE REPROCESO",B57="AJUSTE+"),F57,IF(OR(B57="A CORTE",B57="A REPROCESO",B57="MUESTRA",B57="AJUSTE-"),-F57,0))) -> 0 | M57: tomas | N57: Polera Neru | R57: =IF(OR(Q57="",Q57=0,J57=0),"",(Q57-J57)/J57)
A58: 46149 | B58: A CORTE | C58: Bravos | D58: french terry 24/1 | E58: P. Rosa | F58: 2 | G58: =IFERROR(F58*VLOOKUP(D58,TELAS!$A$4:$C$32,3,FALSE()),0) -> 40 | H58: =IFERROR(VLOOKUP(E58,COLORES!$A$4:$B$102,2,FALSE()),"") -> CLARO | I58: =IFERROR(IF(H58="OSCURO",VLOOKUP(D58,PRECIOS!$A$4:$F$32,2,FALSE()),IF(H58="CLARO",VLOOKUP(D58,PRECIOS!$A$4:$F$32,3,FALSE()),IF(H58="MELANGE",VLOOKUP(D58,PRECIOS!$A$4:$F$32,4,FALSE()),IF(H58="PPT",VLOOKUP(D58,PRECIOS!$A$4:$F$32,5,FALSE()),0)))),0) -> 21 | J58: =IFERROR(G58*I58,0) -> 840 | K58: =IFERROR(IF(C58="",0,SUMIFS($F$4:$F$57,$C$4:$C$57,C58,$D$4:$D$57,D58,$E$4:$E$57,E58,$B$4:$B$57,"INGRESO")+SUMIFS($F$4:$F$57,$C$4:$C$57,C58,$D$4:$D$57,D58,$E$4:$E$57,E58,$B$4:$B$57,"DE REPROCESO")+SUMIFS($F$4:$F$57,$C$4:$C$57,C58,$D$4:$D$57,D58,$E$4:$E$57,E58,$B$4:$B$57,"AJUSTE+")-SUMIFS($F$4:$F$57,$C$4:$C$57,C58,$D$4:$D$57,D58,$E$4:$E$57,E58,$B$4:$B$57,"A CORTE")-SUMIFS($F$4:$F$57,$C$4:$C$57,C58,$D$4:$D$57,D58,$E$4:$E$57,E58,$B$4:$B$57,"A REPROCESO")-SUMIFS($F$4:$F$57,$C$4:$C$57,C58,$D$4:$D$57,D58,$E$4:$E$57,E58,$B$4:$B$57,"MUESTRA")-SUMIFS($F$4:$F$57,$C$4:$C$57,C58,$D$4:$D$57,D58,$E$4:$E$57,E58,$B$4:$B$57,"AJUSTE-")),0) -> 2 | L58: =IF(C58="",0,K58+IF(OR(B58="INGRESO",B58="DE REPROCESO",B58="AJUSTE+"),F58,IF(OR(B58="A CORTE",B58="A REPROCESO",B58="MUESTRA",B58="AJUSTE-"),-F58,0))) -> 0 | M58: tomas | N58: Polera Neru | R58: =IF(OR(Q58="",Q58=0,J58=0),"",(Q58-J58)/J58)
A59: 46149 | B59: A CORTE | C59: Bravos | D59: french terry 24/1 | E59: Beige | F59: 2 | G59: =IFERROR(F59*VLOOKUP(D59,TELAS!$A$4:$C$32,3,FALSE()),0) -> 40 | H59: =IFERROR(VLOOKUP(E59,COLORES!$A$4:$B$102,2,FALSE()),"") -> CLARO | I59: =IFERROR(IF(H59="OSCURO",VLOOKUP(D59,PRECIOS!$A$4:$F$32,2,FALSE()),IF(H59="CLARO",VLOOKUP(D59,PRECIOS!$A$4:$F$32,3,FALSE()),IF(H59="MELANGE",VLOOKUP(D59,PRECIOS!$A$4:$F$32,4,FALSE()),IF(H59="PPT",VLOOKUP(D59,PRECIOS!$A$4:$F$32,5,FALSE()),0)))),0) -> 21 | J59: =IFERROR(G59*I59,0) -> 840 | K59: =IFERROR(IF(C59="",0,SUMIFS($F$4:$F$58,$C$4:$C$58,C59,$D$4:$D$58,D59,$E$4:$E$58,E59,$B$4:$B$58,"INGRESO")+SUMIFS($F$4:$F$58,$C$4:$C$58,C59,$D$4:$D$58,D59,$E$4:$E$58,E59,$B$4:$B$58,"DE REPROCESO")+SUMIFS($F$4:$F$58,$C$4:$C$58,C59,$D$4:$D$58,D59,$E$4:$E$58,E59,$B$4:$B$58,"AJUSTE+")-SUMIFS($F$4:$F$58,$C$4:$C$58,C59,$D$4:$D$58,D59,$E$4:$E$58,E59,$B$4:$B$58,"A CORTE")-SUMIFS($F$4:$F$58,$C$4:$C$58,C59,$D$4:$D$58,D59,$E$4:$E$58,E59,$B$4:$B$58,"A REPROCESO")-SUMIFS($F$4:$F$58,$C$4:$C$58,C59,$D$4:$D$58,D59,$E$4:$E$58,E59,$B$4:$B$58,"MUESTRA")-SUMIFS($F$4:$F$58,$C$4:$C$58,C59,$D$4:$D$58,D59,$E$4:$E$58,E59,$B$4:$B$58,"AJUSTE-")),0) -> 2 | L59: =IF(C59="",0,K59+IF(OR(B59="INGRESO",B59="DE REPROCESO",B59="AJUSTE+"),F59,IF(OR(B59="A CORTE",B59="A REPROCESO",B59="MUESTRA",B59="AJUSTE-"),-F59,0))) -> 0 | M59: tomas | N59: Polera Neru | R59: =IF(OR(Q59="",Q59=0,J59=0),"",(Q59-J59)/J59)
A60: 46149 | B60: A CORTE | C60: Bravos | D60: french terry 24/1 | E60: Denim | F60: 1 | G60: =IFERROR(F60*VLOOKUP(D60,TELAS!$A$4:$C$32,3,FALSE()),0) -> 20 | H60: =IFERROR(VLOOKUP(E60,COLORES!$A$4:$B$102,2,FALSE()),"") -> CLARO | I60: =IFERROR(IF(H60="OSCURO",VLOOKUP(D60,PRECIOS!$A$4:$F$32,2,FALSE()),IF(H60="CLARO",VLOOKUP(D60,PRECIOS!$A$4:$F$32,3,FALSE()),IF(H60="MELANGE",VLOOKUP(D60,PRECIOS!$A$4:$F$32,4,FALSE()),IF(H60="PPT",VLOOKUP(D60,PRECIOS!$A$4:$F$32,5,FALSE()),0)))),0) -> 21 | J60: =IFERROR(G60*I60,0) -> 420 | K60: =IFERROR(IF(C60="",0,SUMIFS($F$4:$F$59,$C$4:$C$59,C60,$D$4:$D$59,D60,$E$4:$E$59,E60,$B$4:$B$59,"INGRESO")+SUMIFS($F$4:$F$59,$C$4:$C$59,C60,$D$4:$D$59,D60,$E$4:$E$59,E60,$B$4:$B$59,"DE REPROCESO")+SUMIFS($F$4:$F$59,$C$4:$C$59,C60,$D$4:$D$59,D60,$E$4:$E$59,E60,$B$4:$B$59,"AJUSTE+")-SUMIFS($F$4:$F$59,$C$4:$C$59,C60,$D$4:$D$59,D60,$E$4:$E$59,E60,$B$4:$B$59,"A CORTE")-SUMIFS($F$4:$F$59,$C$4:$C$59,C60,$D$4:$D$59,D60,$E$4:$E$59,E60,$B$4:$B$59,"A REPROCESO")-SUMIFS($F$4:$F$59,$C$4:$C$59,C60,$D$4:$D$59,D60,$E$4:$E$59,E60,$B$4:$B$59,"MUESTRA")-SUMIFS($F$4:$F$59,$C$4:$C$59,C60,$D$4:$D$59,D60,$E$4:$E$59,E60,$B$4:$B$59,"AJUSTE-")),0) -> 1 | L60: =IF(C60="",0,K60+IF(OR(B60="INGRESO",B60="DE REPROCESO",B60="AJUSTE+"),F60,IF(OR(B60="A CORTE",B60="A REPROCESO",B60="MUESTRA",B60="AJUSTE-"),-F60,0))) -> 0 | M60: tomas | N60: Polera Neru | R60: =IF(OR(Q60="",Q60=0,J60=0),"",(Q60-J60)/J60)
A61: 46149 | B61: A CORTE | C61: Bravos | D61: french terry 24/1 | E61: Plomo | F61: 4 | G61: =IFERROR(F61*VLOOKUP(D61,TELAS!$A$4:$C$32,3,FALSE()),0) -> 80 | H61: =IFERROR(VLOOKUP(E61,COLORES!$A$4:$B$102,2,FALSE()),"") -> OSCURO | I61: =IFERROR(IF(H61="OSCURO",VLOOKUP(D61,PRECIOS!$A$4:$F$32,2,FALSE()),IF(H61="CLARO",VLOOKUP(D61,PRECIOS!$A$4:$F$32,3,FALSE()),IF(H61="MELANGE",VLOOKUP(D61,PRECIOS!$A$4:$F$32,4,FALSE()),IF(H61="PPT",VLOOKUP(D61,PRECIOS!$A$4:$F$32,5,FALSE()),0)))),0) -> 24 | J61: =IFERROR(G61*I61,0) -> 1920 | K61: =IFERROR(IF(C61="",0,SUMIFS($F$4:$F$60,$C$4:$C$60,C61,$D$4:$D$60,D61,$E$4:$E$60,E61,$B$4:$B$60,"INGRESO")+SUMIFS($F$4:$F$60,$C$4:$C$60,C61,$D$4:$D$60,D61,$E$4:$E$60,E61,$B$4:$B$60,"DE REPROCESO")+SUMIFS($F$4:$F$60,$C$4:$C$60,C61,$D$4:$D$60,D61,$E$4:$E$60,E61,$B$4:$B$60,"AJUSTE+")-SUMIFS($F$4:$F$60,$C$4:$C$60,C61,$D$4:$D$60,D61,$E$4:$E$60,E61,$B$4:$B$60,"A CORTE")-SUMIFS($F$4:$F$60,$C$4:$C$60,C61,$D$4:$D$60,D61,$E$4:$E$60,E61,$B$4:$B$60,"A REPROCESO")-SUMIFS($F$4:$F$60,$C$4:$C$60,C61,$D$4:$D$60,D61,$E$4:$E$60,E61,$B$4:$B$60,"MUESTRA")-SUMIFS($F$4:$F$60,$C$4:$C$60,C61,$D$4:$D$60,D61,$E$4:$E$60,E61,$B$4:$B$60,"AJUSTE-")),0) -> 4 | L61: =IF(C61="",0,K61+IF(OR(B61="INGRESO",B61="DE REPROCESO",B61="AJUSTE+"),F61,IF(OR(B61="A CORTE",B61="A REPROCESO",B61="MUESTRA",B61="AJUSTE-"),-F61,0))) -> 0 | M61: tomas | N61: Polera Neru | R61: =IF(OR(Q61="",Q61=0,J61=0),"",(Q61-J61)/J61)
A62: 46147 | B62: A CORTE | C62: OverShark | D62: jersey 30/1 | E62: Negro | F62: 6 | G62: =IFERROR(F62*VLOOKUP(D62,TELAS!$A$4:$C$32,3,FALSE()),0) -> 120 | H62: =IFERROR(VLOOKUP(E62,COLORES!$A$4:$B$102,2,FALSE()),"") -> OSCURO | I62: =IFERROR(IF(H62="OSCURO",VLOOKUP(D62,PRECIOS!$A$4:$F$32,2,FALSE()),IF(H62="CLARO",VLOOKUP(D62,PRECIOS!$A$4:$F$32,3,FALSE()),IF(H62="MELANGE",VLOOKUP(D62,PRECIOS!$A$4:$F$32,4,FALSE()),IF(H62="PPT",VLOOKUP(D62,PRECIOS!$A$4:$F$32,5,FALSE()),0)))),0) -> 24 | J62: =IFERROR(G62*I62,0) -> 2880 | K62: =IFERROR(IF(C62="",0,SUMIFS($F$4:$F$61,$C$4:$C$61,C62,$D$4:$D$61,D62,$E$4:$E$61,E62,$B$4:$B$61,"INGRESO")+SUMIFS($F$4:$F$61,$C$4:$C$61,C62,$D$4:$D$61,D62,$E$4:$E$61,E62,$B$4:$B$61,"DE REPROCESO")+SUMIFS($F$4:$F$61,$C$4:$C$61,C62,$D$4:$D$61,D62,$E$4:$E$61,E62,$B$4:$B$61,"AJUSTE+")-SUMIFS($F$4:$F$61,$C$4:$C$61,C62,$D$4:$D$61,D62,$E$4:$E$61,E62,$B$4:$B$61,"A CORTE")-SUMIFS($F$4:$F$61,$C$4:$C$61,C62,$D$4:$D$61,D62,$E$4:$E$61,E62,$B$4:$B$61,"A REPROCESO")-SUMIFS($F$4:$F$61,$C$4:$C$61,C62,$D$4:$D$61,D62,$E$4:$E$61,E62,$B$4:$B$61,"MUESTRA")-SUMIFS($F$4:$F$61,$C$4:$C$61,C62,$D$4:$D$61,D62,$E$4:$E$61,E62,$B$4:$B$61,"AJUSTE-")),0) -> 25 | L62: =IF(C62="",0,K62+IF(OR(B62="INGRESO",B62="DE REPROCESO",B62="AJUSTE+"),F62,IF(OR(B62="A CORTE",B62="A REPROCESO",B62="MUESTRA",B62="AJUSTE-"),-F62,0))) -> 19 | M62: tomas | N62: Clasico | R62: =IF(OR(Q62="",Q62=0,J62=0),"",(Q62-J62)/J62)
A63: 46147 | B63: A CORTE | C63: OverShark | D63: jersey 30/1 | E63: Botella | F63: 4 | G63: =IFERROR(F63*VLOOKUP(D63,TELAS!$A$4:$C$32,3,FALSE()),0) -> 80 | H63: =IFERROR(VLOOKUP(E63,COLORES!$A$4:$B$102,2,FALSE()),"") -> OSCURO | I63: =IFERROR(IF(H63="OSCURO",VLOOKUP(D63,PRECIOS!$A$4:$F$32,2,FALSE()),IF(H63="CLARO",VLOOKUP(D63,PRECIOS!$A$4:$F$32,3,FALSE()),IF(H63="MELANGE",VLOOKUP(D63,PRECIOS!$A$4:$F$32,4,FALSE()),IF(H63="PPT",VLOOKUP(D63,PRECIOS!$A$4:$F$32,5,FALSE()),0)))),0) -> 24 | J63: =IFERROR(G63*I63,0) -> 1920 | K63: =IFERROR(IF(C63="",0,SUMIFS($F$4:$F$62,$C$4:$C$62,C63,$D$4:$D$62,D63,$E$4:$E$62,E63,$B$4:$B$62,"INGRESO")+SUMIFS($F$4:$F$62,$C$4:$C$62,C63,$D$4:$D$62,D63,$E$4:$E$62,E63,$B$4:$B$62,"DE REPROCESO")+SUMIFS($F$4:$F$62,$C$4:$C$62,C63,$D$4:$D$62,D63,$E$4:$E$62,E63,$B$4:$B$62,"AJUSTE+")-SUMIFS($F$4:$F$62,$C$4:$C$62,C63,$D$4:$D$62,D63,$E$4:$E$62,E63,$B$4:$B$62,"A CORTE")-SUMIFS($F$4:$F$62,$C$4:$C$62,C63,$D$4:$D$62,D63,$E$4:$E$62,E63,$B$4:$B$62,"A REPROCESO")-SUMIFS($F$4:$F$62,$C$4:$C$62,C63,$D$4:$D$62,D63,$E$4:$E$62,E63,$B$4:$B$62,"MUESTRA")-SUMIFS($F$4:$F$62,$C$4:$C$62,C63,$D$4:$D$62,D63,$E$4:$E$62,E63,$B$4:$B$62,"AJUSTE-")),0) -> 15 | L63: =IF(C63="",0,K63+IF(OR(B63="INGRESO",B63="DE REPROCESO",B63="AJUSTE+"),F63,IF(OR(B63="A CORTE",B63="A REPROCESO",B63="MUESTRA",B63="AJUSTE-"),-F63,0))) -> 11 | M63: tomas | N63: Clasico | R63: =IF(OR(Q63="",Q63=0,J63=0),"",(Q63-J63)/J63)
A64: 46147 | B64: A CORTE | C64: OverShark | D64: jersey 30/1 | E64: Beige | F64: 3 | G64: =IFERROR(F64*VLOOKUP(D64,TELAS!$A$4:$C$32,3,FALSE()),0) -> 60 | H64: =IFERROR(VLOOKUP(E64,COLORES!$A$4:$B$102,2,FALSE()),"") -> CLARO | I64: =IFERROR(IF(H64="OSCURO",VLOOKUP(D64,PRECIOS!$A$4:$F$32,2,FALSE()),IF(H64="CLARO",VLOOKUP(D64,PRECIOS!$A$4:$F$32,3,FALSE()),IF(H64="MELANGE",VLOOKUP(D64,PRECIOS!$A$4:$F$32,4,FALSE()),IF(H64="PPT",VLOOKUP(D64,PRECIOS!$A$4:$F$32,5,FALSE()),0)))),0) -> 21 | J64: =IFERROR(G64*I64,0) -> 1260 | K64: =IFERROR(IF(C64="",0,SUMIFS($F$4:$F$63,$C$4:$C$63,C64,$D$4:$D$63,D64,$E$4:$E$63,E64,$B$4:$B$63,"INGRESO")+SUMIFS($F$4:$F$63,$C$4:$C$63,C64,$D$4:$D$63,D64,$E$4:$E$63,E64,$B$4:$B$63,"DE REPROCESO")+SUMIFS($F$4:$F$63,$C$4:$C$63,C64,$D$4:$D$63,D64,$E$4:$E$63,E64,$B$4:$B$63,"AJUSTE+")-SUMIFS($F$4:$F$63,$C$4:$C$63,C64,$D$4:$D$63,D64,$E$4:$E$63,E64,$B$4:$B$63,"A CORTE")-SUMIFS($F$4:$F$63,$C$4:$C$63,C64,$D$4:$D$63,D64,$E$4:$E$63,E64,$B$4:$B$63,"A REPROCESO")-SUMIFS($F$4:$F$63,$C$4:$C$63,C64,$D$4:$D$63,D64,$E$4:$E$63,E64,$B$4:$B$63,"MUESTRA")-SUMIFS($F$4:$F$63,$C$4:$C$63,C64,$D$4:$D$63,D64,$E$4:$E$63,E64,$B$4:$B$63,"AJUSTE-")),0) -> 14 | L64: =IF(C64="",0,K64+IF(OR(B64="INGRESO",B64="DE REPROCESO",B64="AJUSTE+"),F64,IF(OR(B64="A CORTE",B64="A REPROCESO",B64="MUESTRA",B64="AJUSTE-"),-F64,0))) -> 11 | M64: tomas | N64: Clasico | R64: =IF(OR(Q64="",Q64=0,J64=0),"",(Q64-J64)/J64)
A65: 46147 | B65: A CORTE | C65: OverShark | D65: jersey 30/1 | E65: Vino | F65: 6 | G65: =IFERROR(F65*VLOOKUP(D65,TELAS!$A$4:$C$32,3,FALSE()),0) -> 120 | H65: =IFERROR(VLOOKUP(E65,COLORES!$A$4:$B$102,2,FALSE()),"") -> OSCURO | I65: =IFERROR(IF(H65="OSCURO",VLOOKUP(D65,PRECIOS!$A$4:$F$32,2,FALSE()),IF(H65="CLARO",VLOOKUP(D65,PRECIOS!$A$4:$F$32,3,FALSE()),IF(H65="MELANGE",VLOOKUP(D65,PRECIOS!$A$4:$F$32,4,FALSE()),IF(H65="PPT",VLOOKUP(D65,PRECIOS!$A$4:$F$32,5,FALSE()),0)))),0) -> 24 | J65: =IFERROR(G65*I65,0) -> 2880 | K65: =IFERROR(IF(C65="",0,SUMIFS($F$4:$F$64,$C$4:$C$64,C65,$D$4:$D$64,D65,$E$4:$E$64,E65,$B$4:$B$64,"INGRESO")+SUMIFS($F$4:$F$64,$C$4:$C$64,C65,$D$4:$D$64,D65,$E$4:$E$64,E65,$B$4:$B$64,"DE REPROCESO")+SUMIFS($F$4:$F$64,$C$4:$C$64,C65,$D$4:$D$64,D65,$E$4:$E$64,E65,$B$4:$B$64,"AJUSTE+")-SUMIFS($F$4:$F$64,$C$4:$C$64,C65,$D$4:$D$64,D65,$E$4:$E$64,E65,$B$4:$B$64,"A CORTE")-SUMIFS($F$4:$F$64,$C$4:$C$64,C65,$D$4:$D$64,D65,$E$4:$E$64,E65,$B$4:$B$64,"A REPROCESO")-SUMIFS($F$4:$F$64,$C$4:$C$64,C65,$D$4:$D$64,D65,$E$4:$E$64,E65,$B$4:$B$64,"MUESTRA")-SUMIFS($F$4:$F$64,$C$4:$C$64,C65,$D$4:$D$64,D65,$E$4:$E$64,E65,$B$4:$B$64,"AJUSTE-")),0) -> 14 | L65: =IF(C65="",0,K65+IF(OR(B65="INGRESO",B65="DE REPROCESO",B65="AJUSTE+"),F65,IF(OR(B65="A CORTE",B65="A REPROCESO",B65="MUESTRA",B65="AJUSTE-"),-F65,0))) -> 8 | M65: tomas | N65: Clasico | R65: =IF(OR(Q65="",Q65=0,J65=0),"",(Q65-J65)/J65)
A66: 46147 | B66: A CORTE | C66: OverShark | D66: jersey 30/1 | E66: Denim | F66: 5 | G66: =IFERROR(F66*VLOOKUP(D66,TELAS!$A$4:$C$32,3,FALSE()),0) -> 100 | H66: =IFERROR(VLOOKUP(E66,COLORES!$A$4:$B$102,2,FALSE()),"") -> CLARO | I66: =IFERROR(IF(H66="OSCURO",VLOOKUP(D66,PRECIOS!$A$4:$F$32,2,FALSE()),IF(H66="CLARO",VLOOKUP(D66,PRECIOS!$A$4:$F$32,3,FALSE()),IF(H66="MELANGE",VLOOKUP(D66,PRECIOS!$A$4:$F$32,4,FALSE()),IF(H66="PPT",VLOOKUP(D66,PRECIOS!$A$4:$F$32,5,FALSE()),0)))),0) -> 21 | J66: =IFERROR(G66*I66,0) -> 2100 | K66: =IFERROR(IF(C66="",0,SUMIFS($F$4:$F$65,$C$4:$C$65,C66,$D$4:$D$65,D66,$E$4:$E$65,E66,$B$4:$B$65,"INGRESO")+SUMIFS($F$4:$F$65,$C$4:$C$65,C66,$D$4:$D$65,D66,$E$4:$E$65,E66,$B$4:$B$65,"DE REPROCESO")+SUMIFS($F$4:$F$65,$C$4:$C$65,C66,$D$4:$D$65,D66,$E$4:$E$65,E66,$B$4:$B$65,"AJUSTE+")-SUMIFS($F$4:$F$65,$C$4:$C$65,C66,$D$4:$D$65,D66,$E$4:$E$65,E66,$B$4:$B$65,"A CORTE")-SUMIFS($F$4:$F$65,$C$4:$C$65,C66,$D$4:$D$65,D66,$E$4:$E$65,E66,$B$4:$B$65,"A REPROCESO")-SUMIFS($F$4:$F$65,$C$4:$C$65,C66,$D$4:$D$65,D66,$E$4:$E$65,E66,$B$4:$B$65,"MUESTRA")-SUMIFS($F$4:$F$65,$C$4:$C$65,C66,$D$4:$D$65,D66,$E$4:$E$65,E66,$B$4:$B$65,"AJUSTE-")),0) -> 15 | L66: =IF(C66="",0,K66+IF(OR(B66="INGRESO",B66="DE REPROCESO",B66="AJUSTE+"),F66,IF(OR(B66="A CORTE",B66="A REPROCESO",B66="MUESTRA",B66="AJUSTE-"),-F66,0))) -> 10 | M66: tomas | N66: Clasico | R66: =IF(OR(Q66="",Q66=0,J66=0),"",(Q66-J66)/J66)
A67: 46147 | B67: A CORTE | C67: OverShark | D67: jersey 30/1 | E67: Plomo | F67: 8 | G67: =IFERROR(F67*VLOOKUP(D67,TELAS!$A$4:$C$32,3,FALSE()),0) -> 160 | H67: =IFERROR(VLOOKUP(E67,COLORES!$A$4:$B$102,2,FALSE()),"") -> OSCURO | I67: =IFERROR(IF(H67="OSCURO",VLOOKUP(D67,PRECIOS!$A$4:$F$32,2,FALSE()),IF(H67="CLARO",VLOOKUP(D67,PRECIOS!$A$4:$F$32,3,FALSE()),IF(H67="MELANGE",VLOOKUP(D67,PRECIOS!$A$4:$F$32,4,FALSE()),IF(H67="PPT",VLOOKUP(D67,PRECIOS!$A$4:$F$32,5,FALSE()),0)))),0) -> 24 | J67: =IFERROR(G67*I67,0) -> 3840 | K67: =IFERROR(IF(C67="",0,SUMIFS($F$4:$F$66,$C$4:$C$66,C67,$D$4:$D$66,D67,$E$4:$E$66,E67,$B$4:$B$66,"INGRESO")+SUMIFS($F$4:$F$66,$C$4:$C$66,C67,$D$4:$D$66,D67,$E$4:$E$66,E67,$B$4:$B$66,"DE REPROCESO")+SUMIFS($F$4:$F$66,$C$4:$C$66,C67,$D$4:$D$66,D67,$E$4:$E$66,E67,$B$4:$B$66,"AJUSTE+")-SUMIFS($F$4:$F$66,$C$4:$C$66,C67,$D$4:$D$66,D67,$E$4:$E$66,E67,$B$4:$B$66,"A CORTE")-SUMIFS($F$4:$F$66,$C$4:$C$66,C67,$D$4:$D$66,D67,$E$4:$E$66,E67,$B$4:$B$66,"A REPROCESO")-SUMIFS($F$4:$F$66,$C$4:$C$66,C67,$D$4:$D$66,D67,$E$4:$E$66,E67,$B$4:$B$66,"MUESTRA")-SUMIFS($F$4:$F$66,$C$4:$C$66,C67,$D$4:$D$66,D67,$E$4:$E$66,E67,$B$4:$B$66,"AJUSTE-")),0) -> 15 | L67: =IF(C67="",0,K67+IF(OR(B67="INGRESO",B67="DE REPROCESO",B67="AJUSTE+"),F67,IF(OR(B67="A CORTE",B67="A REPROCESO",B67="MUESTRA",B67="AJUSTE-"),-F67,0))) -> 7 | M67: tomas | N67: Clasico | R67: =IF(OR(Q67="",Q67=0,J67=0),"",(Q67-J67)/J67)
A68: 46147 | B68: A CORTE | C68: OverShark | D68: pique 30/1 | E68: Botella | F68: 3 | G68: =IFERROR(F68*VLOOKUP(D68,TELAS!$A$4:$C$32,3,FALSE()),0) -> 60 | H68: =IFERROR(VLOOKUP(E68,COLORES!$A$4:$B$102,2,FALSE()),"") -> OSCURO | I68: =IFERROR(IF(H68="OSCURO",VLOOKUP(D68,PRECIOS!$A$4:$F$32,2,FALSE()),IF(H68="CLARO",VLOOKUP(D68,PRECIOS!$A$4:$F$32,3,FALSE()),IF(H68="MELANGE",VLOOKUP(D68,PRECIOS!$A$4:$F$32,4,FALSE()),IF(H68="PPT",VLOOKUP(D68,PRECIOS!$A$4:$F$32,5,FALSE()),0)))),0) -> 24 | J68: =IFERROR(G68*I68,0) -> 1440 | K68: =IFERROR(IF(C68="",0,SUMIFS($F$4:$F$67,$C$4:$C$67,C68,$D$4:$D$67,D68,$E$4:$E$67,E68,$B$4:$B$67,"INGRESO")+SUMIFS($F$4:$F$67,$C$4:$C$67,C68,$D$4:$D$67,D68,$E$4:$E$67,E68,$B$4:$B$67,"DE REPROCESO")+SUMIFS($F$4:$F$67,$C$4:$C$67,C68,$D$4:$D$67,D68,$E$4:$E$67,E68,$B$4:$B$67,"AJUSTE+")-SUMIFS($F$4:$F$67,$C$4:$C$67,C68,$D$4:$D$67,D68,$E$4:$E$67,E68,$B$4:$B$67,"A CORTE")-SUMIFS($F$4:$F$67,$C$4:$C$67,C68,$D$4:$D$67,D68,$E$4:$E$67,E68,$B$4:$B$67,"A REPROCESO")-SUMIFS($F$4:$F$67,$C$4:$C$67,C68,$D$4:$D$67,D68,$E$4:$E$67,E68,$B$4:$B$67,"MUESTRA")-SUMIFS($F$4:$F$67,$C$4:$C$67,C68,$D$4:$D$67,D68,$E$4:$E$67,E68,$B$4:$B$67,"AJUSTE-")),0) -> 6 | L68: =IF(C68="",0,K68+IF(OR(B68="INGRESO",B68="DE REPROCESO",B68="AJUSTE+"),F68,IF(OR(B68="A CORTE",B68="A REPROCESO",B68="MUESTRA",B68="AJUSTE-"),-F68,0))) -> 3 | M68: tomas | N68: Camisero | R68: =IF(OR(Q68="",Q68=0,J68=0),"",(Q68-J68)/J68)
A69: 46148 | B69: A CORTE | C69: OverShark | D69: pique 30/1 | E69: Pacay | F69: 2 | G69: =IFERROR(F69*VLOOKUP(D69,TELAS!$A$4:$C$32,3,FALSE()),0) -> 40 | H69: =IFERROR(VLOOKUP(E69,COLORES!$A$4:$B$102,2,FALSE()),"") -> CLARO | I69: =IFERROR(IF(H69="OSCURO",VLOOKUP(D69,PRECIOS!$A$4:$F$32,2,FALSE()),IF(H69="CLARO",VLOOKUP(D69,PRECIOS!$A$4:$F$32,3,FALSE()),IF(H69="MELANGE",VLOOKUP(D69,PRECIOS!$A$4:$F$32,4,FALSE()),IF(H69="PPT",VLOOKUP(D69,PRECIOS!$A$4:$F$32,5,FALSE()),0)))),0) -> 21 | J69: =IFERROR(G69*I69,0) -> 840 | K69: =IFERROR(IF(C69="",0,SUMIFS($F$4:$F$68,$C$4:$C$68,C69,$D$4:$D$68,D69,$E$4:$E$68,E69,$B$4:$B$68,"INGRESO")+SUMIFS($F$4:$F$68,$C$4:$C$68,C69,$D$4:$D$68,D69,$E$4:$E$68,E69,$B$4:$B$68,"DE REPROCESO")+SUMIFS($F$4:$F$68,$C$4:$C$68,C69,$D$4:$D$68,D69,$E$4:$E$68,E69,$B$4:$B$68,"AJUSTE+")-SUMIFS($F$4:$F$68,$C$4:$C$68,C69,$D$4:$D$68,D69,$E$4:$E$68,E69,$B$4:$B$68,"A CORTE")-SUMIFS($F$4:$F$68,$C$4:$C$68,C69,$D$4:$D$68,D69,$E$4:$E$68,E69,$B$4:$B$68,"A REPROCESO")-SUMIFS($F$4:$F$68,$C$4:$C$68,C69,$D$4:$D$68,D69,$E$4:$E$68,E69,$B$4:$B$68,"MUESTRA")-SUMIFS($F$4:$F$68,$C$4:$C$68,C69,$D$4:$D$68,D69,$E$4:$E$68,E69,$B$4:$B$68,"AJUSTE-")),0) -> 13 | L69: =IF(C69="",0,K69+IF(OR(B69="INGRESO",B69="DE REPROCESO",B69="AJUSTE+"),F69,IF(OR(B69="A CORTE",B69="A REPROCESO",B69="MUESTRA",B69="AJUSTE-"),-F69,0))) -> 11 | M69: tomas | N69: Camisero | R69: =IF(OR(Q69="",Q69=0,J69=0),"",(Q69-J69)/J69)
A70: 46149 | B70: A CORTE | C70: OverShark | D70: pique 30/1 | E70: Cemento | F70: 2 | G70: =IFERROR(F70*VLOOKUP(D70,TELAS!$A$4:$C$32,3,FALSE()),0) -> 40 | H70: =IFERROR(VLOOKUP(E70,COLORES!$A$4:$B$102,2,FALSE()),"") -> CLARO | I70: =IFERROR(IF(H70="OSCURO",VLOOKUP(D70,PRECIOS!$A$4:$F$32,2,FALSE()),IF(H70="CLARO",VLOOKUP(D70,PRECIOS!$A$4:$F$32,3,FALSE()),IF(H70="MELANGE",VLOOKUP(D70,PRECIOS!$A$4:$F$32,4,FALSE()),IF(H70="PPT",VLOOKUP(D70,PRECIOS!$A$4:$F$32,5,FALSE()),0)))),0) -> 21 | J70: =IFERROR(G70*I70,0) -> 840 | K70: =IFERROR(IF(C70="",0,SUMIFS($F$4:$F$69,$C$4:$C$69,C70,$D$4:$D$69,D70,$E$4:$E$69,E70,$B$4:$B$69,"INGRESO")+SUMIFS($F$4:$F$69,$C$4:$C$69,C70,$D$4:$D$69,D70,$E$4:$E$69,E70,$B$4:$B$69,"DE REPROCESO")+SUMIFS($F$4:$F$69,$C$4:$C$69,C70,$D$4:$D$69,D70,$E$4:$E$69,E70,$B$4:$B$69,"AJUSTE+")-SUMIFS($F$4:$F$69,$C$4:$C$69,C70,$D$4:$D$69,D70,$E$4:$E$69,E70,$B$4:$B$69,"A CORTE")-SUMIFS($F$4:$F$69,$C$4:$C$69,C70,$D$4:$D$69,D70,$E$4:$E$69,E70,$B$4:$B$69,"A REPROCESO")-SUMIFS($F$4:$F$69,$C$4:$C$69,C70,$D$4:$D$69,D70,$E$4:$E$69,E70,$B$4:$B$69,"MUESTRA")-SUMIFS($F$4:$F$69,$C$4:$C$69,C70,$D$4:$D$69,D70,$E$4:$E$69,E70,$B$4:$B$69,"AJUSTE-")),0) -> 9 | L70: =IF(C70="",0,K70+IF(OR(B70="INGRESO",B70="DE REPROCESO",B70="AJUSTE+"),F70,IF(OR(B70="A CORTE",B70="A REPROCESO",B70="MUESTRA",B70="AJUSTE-"),-F70,0))) -> 7 | M70: tomas | N70: Camisero | R70: =IF(OR(Q70="",Q70=0,J70=0),"",(Q70-J70)/J70)
A71: 46150 | B71: A CORTE | C71: OverShark | D71: pique 30/1 | E71: P. Rosa | F71: 2 | G71: =IFERROR(F71*VLOOKUP(D71,TELAS!$A$4:$C$32,3,FALSE()),0) -> 40 | H71: =IFERROR(VLOOKUP(E71,COLORES!$A$4:$B$102,2,FALSE()),"") -> CLARO | I71: =IFERROR(IF(H71="OSCURO",VLOOKUP(D71,PRECIOS!$A$4:$F$32,2,FALSE()),IF(H71="CLARO",VLOOKUP(D71,PRECIOS!$A$4:$F$32,3,FALSE()),IF(H71="MELANGE",VLOOKUP(D71,PRECIOS!$A$4:$F$32,4,FALSE()),IF(H71="PPT",VLOOKUP(D71,PRECIOS!$A$4:$F$32,5,FALSE()),0)))),0) -> 21 | J71: =IFERROR(G71*I71,0) -> 840 | K71: =IFERROR(IF(C71="",0,SUMIFS($F$4:$F$70,$C$4:$C$70,C71,$D$4:$D$70,D71,$E$4:$E$70,E71,$B$4:$B$70,"INGRESO")+SUMIFS($F$4:$F$70,$C$4:$C$70,C71,$D$4:$D$70,D71,$E$4:$E$70,E71,$B$4:$B$70,"DE REPROCESO")+SUMIFS($F$4:$F$70,$C$4:$C$70,C71,$D$4:$D$70,D71,$E$4:$E$70,E71,$B$4:$B$70,"AJUSTE+")-SUMIFS($F$4:$F$70,$C$4:$C$70,C71,$D$4:$D$70,D71,$E$4:$E$70,E71,$B$4:$B$70,"A CORTE")-SUMIFS($F$4:$F$70,$C$4:$C$70,C71,$D$4:$D$70,D71,$E$4:$E$70,E71,$B$4:$B$70,"A REPROCESO")-SUMIFS($F$4:$F$70,$C$4:$C$70,C71,$D$4:$D$70,D71,$E$4:$E$70,E71,$B$4:$B$70,"MUESTRA")-SUMIFS($F$4:$F$70,$C$4:$C$70,C71,$D$4:$D$70,D71,$E$4:$E$70,E71,$B$4:$B$70,"AJUSTE-")),0) -> 9 | L71: =IF(C71="",0,K71+IF(OR(B71="INGRESO",B71="DE REPROCESO",B71="AJUSTE+"),F71,IF(OR(B71="A CORTE",B71="A REPROCESO",B71="MUESTRA",B71="AJUSTE-"),-F71,0))) -> 7 | M71: tomas | N71: Camisero | R71: =IF(OR(Q71="",Q71=0,J71=0),"",(Q71-J71)/J71)
A72: 46151 | B72: A CORTE | C72: OverShark | D72: pique 30/1 | E72: Topo | F72: 2 | G72: =IFERROR(F72*VLOOKUP(D72,TELAS!$A$4:$C$32,3,FALSE()),0) -> 40 | H72: =IFERROR(VLOOKUP(E72,COLORES!$A$4:$B$102,2,FALSE()),"") -> CLARO | I72: =IFERROR(IF(H72="OSCURO",VLOOKUP(D72,PRECIOS!$A$4:$F$32,2,FALSE()),IF(H72="CLARO",VLOOKUP(D72,PRECIOS!$A$4:$F$32,3,FALSE()),IF(H72="MELANGE",VLOOKUP(D72,PRECIOS!$A$4:$F$32,4,FALSE()),IF(H72="PPT",VLOOKUP(D72,PRECIOS!$A$4:$F$32,5,FALSE()),0)))),0) -> 21 | J72: =IFERROR(G72*I72,0) -> 840 | K72: =IFERROR(IF(C72="",0,SUMIFS($F$4:$F$71,$C$4:$C$71,C72,$D$4:$D$71,D72,$E$4:$E$71,E72,$B$4:$B$71,"INGRESO")+SUMIFS($F$4:$F$71,$C$4:$C$71,C72,$D$4:$D$71,D72,$E$4:$E$71,E72,$B$4:$B$71,"DE REPROCESO")+SUMIFS($F$4:$F$71,$C$4:$C$71,C72,$D$4:$D$71,D72,$E$4:$E$71,E72,$B$4:$B$71,"AJUSTE+")-SUMIFS($F$4:$F$71,$C$4:$C$71,C72,$D$4:$D$71,D72,$E$4:$E$71,E72,$B$4:$B$71,"A CORTE")-SUMIFS($F$4:$F$71,$C$4:$C$71,C72,$D$4:$D$71,D72,$E$4:$E$71,E72,$B$4:$B$71,"A REPROCESO")-SUMIFS($F$4:$F$71,$C$4:$C$71,C72,$D$4:$D$71,D72,$E$4:$E$71,E72,$B$4:$B$71,"MUESTRA")-SUMIFS($F$4:$F$71,$C$4:$C$71,C72,$D$4:$D$71,D72,$E$4:$E$71,E72,$B$4:$B$71,"AJUSTE-")),0) -> 3 | L72: =IF(C72="",0,K72+IF(OR(B72="INGRESO",B72="DE REPROCESO",B72="AJUSTE+"),F72,IF(OR(B72="A CORTE",B72="A REPROCESO",B72="MUESTRA",B72="AJUSTE-"),-F72,0))) -> 1 | M72: tomas | N72: Camisero | R72: =IF(OR(Q72="",Q72=0,J72=0),"",(Q72-J72)/J72)
A73: 46152 | B73: A CORTE | C73: OverShark | D73: pique 30/1 | E73: Vino | F73: 1 | G73: =IFERROR(F73*VLOOKUP(D73,TELAS!$A$4:$C$32,3,FALSE()),0) -> 20 | H73: =IFERROR(VLOOKUP(E73,COLORES!$A$4:$B$102,2,FALSE()),"") -> OSCURO | I73: =IFERROR(IF(H73="OSCURO",VLOOKUP(D73,PRECIOS!$A$4:$F$32,2,FALSE()),IF(H73="CLARO",VLOOKUP(D73,PRECIOS!$A$4:$F$32,3,FALSE()),IF(H73="MELANGE",VLOOKUP(D73,PRECIOS!$A$4:$F$32,4,FALSE()),IF(H73="PPT",VLOOKUP(D73,PRECIOS!$A$4:$F$32,5,FALSE()),0)))),0) -> 24 | J73: =IFERROR(G73*I73,0) -> 480 | K73: =IFERROR(IF(C73="",0,SUMIFS($F$4:$F$72,$C$4:$C$72,C73,$D$4:$D$72,D73,$E$4:$E$72,E73,$B$4:$B$72,"INGRESO")+SUMIFS($F$4:$F$72,$C$4:$C$72,C73,$D$4:$D$72,D73,$E$4:$E$72,E73,$B$4:$B$72,"DE REPROCESO")+SUMIFS($F$4:$F$72,$C$4:$C$72,C73,$D$4:$D$72,D73,$E$4:$E$72,E73,$B$4:$B$72,"AJUSTE+")-SUMIFS($F$4:$F$72,$C$4:$C$72,C73,$D$4:$D$72,D73,$E$4:$E$72,E73,$B$4:$B$72,"A CORTE")-SUMIFS($F$4:$F$72,$C$4:$C$72,C73,$D$4:$D$72,D73,$E$4:$E$72,E73,$B$4:$B$72,"A REPROCESO")-SUMIFS($F$4:$F$72,$C$4:$C$72,C73,$D$4:$D$72,D73,$E$4:$E$72,E73,$B$4:$B$72,"MUESTRA")-SUMIFS($F$4:$F$72,$C$4:$C$72,C73,$D$4:$D$72,D73,$E$4:$E$72,E73,$B$4:$B$72,"AJUSTE-")),0) -> 2 | L73: =IF(C73="",0,K73+IF(OR(B73="INGRESO",B73="DE REPROCESO",B73="AJUSTE+"),F73,IF(OR(B73="A CORTE",B73="A REPROCESO",B73="MUESTRA",B73="AJUSTE-"),-F73,0))) -> 1 | M73: tomas | N73: Camisero | R73: =IF(OR(Q73="",Q73=0,J73=0),"",(Q73-J73)/J73)
A74: 46153 | B74: A CORTE | C74: OverShark | D74: pique 30/1 | E74: Denim | F74: 3 | G74: =IFERROR(F74*VLOOKUP(D74,TELAS!$A$4:$C$32,3,FALSE()),0) -> 60 | H74: =IFERROR(VLOOKUP(E74,COLORES!$A$4:$B$102,2,FALSE()),"") -> CLARO | I74: =IFERROR(IF(H74="OSCURO",VLOOKUP(D74,PRECIOS!$A$4:$F$32,2,FALSE()),IF(H74="CLARO",VLOOKUP(D74,PRECIOS!$A$4:$F$32,3,FALSE()),IF(H74="MELANGE",VLOOKUP(D74,PRECIOS!$A$4:$F$32,4,FALSE()),IF(H74="PPT",VLOOKUP(D74,PRECIOS!$A$4:$F$32,5,FALSE()),0)))),0) -> 21 | J74: =IFERROR(G74*I74,0) -> 1260 | K74: =IFERROR(IF(C74="",0,SUMIFS($F$4:$F$73,$C$4:$C$73,C74,$D$4:$D$73,D74,$E$4:$E$73,E74,$B$4:$B$73,"INGRESO")+SUMIFS($F$4:$F$73,$C$4:$C$73,C74,$D$4:$D$73,D74,$E$4:$E$73,E74,$B$4:$B$73,"DE REPROCESO")+SUMIFS($F$4:$F$73,$C$4:$C$73,C74,$D$4:$D$73,D74,$E$4:$E$73,E74,$B$4:$B$73,"AJUSTE+")-SUMIFS($F$4:$F$73,$C$4:$C$73,C74,$D$4:$D$73,D74,$E$4:$E$73,E74,$B$4:$B$73,"A CORTE")-SUMIFS($F$4:$F$73,$C$4:$C$73,C74,$D$4:$D$73,D74,$E$4:$E$73,E74,$B$4:$B$73,"A REPROCESO")-SUMIFS($F$4:$F$73,$C$4:$C$73,C74,$D$4:$D$73,D74,$E$4:$E$73,E74,$B$4:$B$73,"MUESTRA")-SUMIFS($F$4:$F$73,$C$4:$C$73,C74,$D$4:$D$73,D74,$E$4:$E$73,E74,$B$4:$B$73,"AJUSTE-")),0) -> 13 | L74: =IF(C74="",0,K74+IF(OR(B74="INGRESO",B74="DE REPROCESO",B74="AJUSTE+"),F74,IF(OR(B74="A CORTE",B74="A REPROCESO",B74="MUESTRA",B74="AJUSTE-"),-F74,0))) -> 10 | M74: tomas | N74: Camisero | R74: =IF(OR(Q74="",Q74=0,J74=0),"",(Q74-J74)/J74)
A75: 46154 | B75: A CORTE | C75: OverShark | D75: pique 30/1 | E75: Melange | F75: 3 | G75: =IFERROR(F75*VLOOKUP(D75,TELAS!$A$4:$C$32,3,FALSE()),0) -> 60 | H75: =IFERROR(VLOOKUP(E75,COLORES!$A$4:$B$102,2,FALSE()),"") -> MELANGE | I75: =IFERROR(IF(H75="OSCURO",VLOOKUP(D75,PRECIOS!$A$4:$F$32,2,FALSE()),IF(H75="CLARO",VLOOKUP(D75,PRECIOS!$A$4:$F$32,3,FALSE()),IF(H75="MELANGE",VLOOKUP(D75,PRECIOS!$A$4:$F$32,4,FALSE()),IF(H75="PPT",VLOOKUP(D75,PRECIOS!$A$4:$F$32,5,FALSE()),0)))),0) -> 18 | J75: =IFERROR(G75*I75,0) -> 1080 | K75: =IFERROR(IF(C75="",0,SUMIFS($F$4:$F$74,$C$4:$C$74,C75,$D$4:$D$74,D75,$E$4:$E$74,E75,$B$4:$B$74,"INGRESO")+SUMIFS($F$4:$F$74,$C$4:$C$74,C75,$D$4:$D$74,D75,$E$4:$E$74,E75,$B$4:$B$74,"DE REPROCESO")+SUMIFS($F$4:$F$74,$C$4:$C$74,C75,$D$4:$D$74,D75,$E$4:$E$74,E75,$B$4:$B$74,"AJUSTE+")-SUMIFS($F$4:$F$74,$C$4:$C$74,C75,$D$4:$D$74,D75,$E$4:$E$74,E75,$B$4:$B$74,"A CORTE")-SUMIFS($F$4:$F$74,$C$4:$C$74,C75,$D$4:$D$74,D75,$E$4:$E$74,E75,$B$4:$B$74,"A REPROCESO")-SUMIFS($F$4:$F$74,$C$4:$C$74,C75,$D$4:$D$74,D75,$E$4:$E$74,E75,$B$4:$B$74,"MUESTRA")-SUMIFS($F$4:$F$74,$C$4:$C$74,C75,$D$4:$D$74,D75,$E$4:$E$74,E75,$B$4:$B$74,"AJUSTE-")),0) -> 9 | L75: =IF(C75="",0,K75+IF(OR(B75="INGRESO",B75="DE REPROCESO",B75="AJUSTE+"),F75,IF(OR(B75="A CORTE",B75="A REPROCESO",B75="MUESTRA",B75="AJUSTE-"),-F75,0))) -> 6 | M75: tomas | N75: Camisero | R75: =IF(OR(Q75="",Q75=0,J75=0),"",(Q75-J75)/J75)
A76: 46146 | B76: INGRESO | C76: OverShark | D76: jersey full lycra 30/1 | E76: Negro | F76: 36 | G76: =IFERROR(F76*VLOOKUP(D76,TELAS!$A$4:$C$32,3,FALSE()),0) -> 720 | H76: =IFERROR(VLOOKUP(E76,COLORES!$A$4:$B$102,2,FALSE()),"") -> OSCURO | I76: =IFERROR(IF(H76="OSCURO",VLOOKUP(D76,PRECIOS!$A$4:$F$32,2,FALSE()),IF(H76="CLARO",VLOOKUP(D76,PRECIOS!$A$4:$F$32,3,FALSE()),IF(H76="MELANGE",VLOOKUP(D76,PRECIOS!$A$4:$F$32,4,FALSE()),IF(H76="PPT",VLOOKUP(D76,PRECIOS!$A$4:$F$32,5,FALSE()),0)))),0) -> 26 | J76: =IFERROR(G76*I76,0) -> 18720 | K76: =IFERROR(IF(C76="",0,SUMIFS($F$4:$F$75,$C$4:$C$75,C76,$D$4:$D$75,D76,$E$4:$E$75,E76,$B$4:$B$75,"INGRESO")+SUMIFS($F$4:$F$75,$C$4:$C$75,C76,$D$4:$D$75,D76,$E$4:$E$75,E76,$B$4:$B$75,"DE REPROCESO")+SUMIFS($F$4:$F$75,$C$4:$C$75,C76,$D$4:$D$75,D76,$E$4:$E$75,E76,$B$4:$B$75,"AJUSTE+")-SUMIFS($F$4:$F$75,$C$4:$C$75,C76,$D$4:$D$75,D76,$E$4:$E$75,E76,$B$4:$B$75,"A CORTE")-SUMIFS($F$4:$F$75,$C$4:$C$75,C76,$D$4:$D$75,D76,$E$4:$E$75,E76,$B$4:$B$75,"A REPROCESO")-SUMIFS($F$4:$F$75,$C$4:$C$75,C76,$D$4:$D$75,D76,$E$4:$E$75,E76,$B$4:$B$75,"MUESTRA")-SUMIFS($F$4:$F$75,$C$4:$C$75,C76,$D$4:$D$75,D76,$E$4:$E$75,E76,$B$4:$B$75,"AJUSTE-")),0) -> 0 | L76: =IF(C76="",0,K76+IF(OR(B76="INGRESO",B76="DE REPROCESO",B76="AJUSTE+"),F76,IF(OR(B76="A CORTE",B76="A REPROCESO",B76="MUESTRA",B76="AJUSTE-"),-F76,0))) -> 36 | M76: tomas | O76: PROGRESO | R76: =IF(OR(Q76="",Q76=0,J76=0),"",(Q76-J76)/J76)
A77: 46147 | B77: INGRESO | C77: OverShark | D77: jersey full lycra 30/1 | E77: Perla | F77: 12 | G77: =IFERROR(F77*VLOOKUP(D77,TELAS!$A$4:$C$32,3,FALSE()),0) -> 240 | H77: =IFERROR(VLOOKUP(E77,COLORES!$A$4:$B$102,2,FALSE()),"") -> PPT | I77: =IFERROR(IF(H77="OSCURO",VLOOKUP(D77,PRECIOS!$A$4:$F$32,2,FALSE()),IF(H77="CLARO",VLOOKUP(D77,PRECIOS!$A$4:$F$32,3,FALSE()),IF(H77="MELANGE",VLOOKUP(D77,PRECIOS!$A$4:$F$32,4,FALSE()),IF(H77="PPT",VLOOKUP(D77,PRECIOS!$A$4:$F$32,5,FALSE()),0)))),0) -> 19 | J77: =IFERROR(G77*I77,0) -> 4560 | K77: =IFERROR(IF(C77="",0,SUMIFS($F$4:$F$76,$C$4:$C$76,C77,$D$4:$D$76,D77,$E$4:$E$76,E77,$B$4:$B$76,"INGRESO")+SUMIFS($F$4:$F$76,$C$4:$C$76,C77,$D$4:$D$76,D77,$E$4:$E$76,E77,$B$4:$B$76,"DE REPROCESO")+SUMIFS($F$4:$F$76,$C$4:$C$76,C77,$D$4:$D$76,D77,$E$4:$E$76,E77,$B$4:$B$76,"AJUSTE+")-SUMIFS($F$4:$F$76,$C$4:$C$76,C77,$D$4:$D$76,D77,$E$4:$E$76,E77,$B$4:$B$76,"A CORTE")-SUMIFS($F$4:$F$76,$C$4:$C$76,C77,$D$4:$D$76,D77,$E$4:$E$76,E77,$B$4:$B$76,"A REPROCESO")-SUMIFS($F$4:$F$76,$C$4:$C$76,C77,$D$4:$D$76,D77,$E$4:$E$76,E77,$B$4:$B$76,"MUESTRA")-SUMIFS($F$4:$F$76,$C$4:$C$76,C77,$D$4:$D$76,D77,$E$4:$E$76,E77,$B$4:$B$76,"AJUSTE-")),0) -> 0 | L77: =IF(C77="",0,K77+IF(OR(B77="INGRESO",B77="DE REPROCESO",B77="AJUSTE+"),F77,IF(OR(B77="A CORTE",B77="A REPROCESO",B77="MUESTRA",B77="AJUSTE-"),-F77,0))) -> 12 | M77: tomas | O77: PROGRESO | R77: =IF(OR(Q77="",Q77=0,J77=0),"",(Q77-J77)/J77)
A78: 46148 | B78: INGRESO | C78: OverShark | D78: jersey full lycra 30/1 | E78: Azul | F78: 19 | G78: =IFERROR(F78*VLOOKUP(D78,TELAS!$A$4:$C$32,3,FALSE()),0) -> 380 | H78: =IFERROR(VLOOKUP(E78,COLORES!$A$4:$B$102,2,FALSE()),"") -> OSCURO | I78: =IFERROR(IF(H78="OSCURO",VLOOKUP(D78,PRECIOS!$A$4:$F$32,2,FALSE()),IF(H78="CLARO",VLOOKUP(D78,PRECIOS!$A$4:$F$32,3,FALSE()),IF(H78="MELANGE",VLOOKUP(D78,PRECIOS!$A$4:$F$32,4,FALSE()),IF(H78="PPT",VLOOKUP(D78,PRECIOS!$A$4:$F$32,5,FALSE()),0)))),0) -> 26 | J78: =IFERROR(G78*I78,0) -> 9880 | K78: =IFERROR(IF(C78="",0,SUMIFS($F$4:$F$77,$C$4:$C$77,C78,$D$4:$D$77,D78,$E$4:$E$77,E78,$B$4:$B$77,"INGRESO")+SUMIFS($F$4:$F$77,$C$4:$C$77,C78,$D$4:$D$77,D78,$E$4:$E$77,E78,$B$4:$B$77,"DE REPROCESO")+SUMIFS($F$4:$F$77,$C$4:$C$77,C78,$D$4:$D$77,D78,$E$4:$E$77,E78,$B$4:$B$77,"AJUSTE+")-SUMIFS($F$4:$F$77,$C$4:$C$77,C78,$D$4:$D$77,D78,$E$4:$E$77,E78,$B$4:$B$77,"A CORTE")-SUMIFS($F$4:$F$77,$C$4:$C$77,C78,$D$4:$D$77,D78,$E$4:$E$77,E78,$B$4:$B$77,"A REPROCESO")-SUMIFS($F$4:$F$77,$C$4:$C$77,C78,$D$4:$D$77,D78,$E$4:$E$77,E78,$B$4:$B$77,"MUESTRA")-SUMIFS($F$4:$F$77,$C$4:$C$77,C78,$D$4:$D$77,D78,$E$4:$E$77,E78,$B$4:$B$77,"AJUSTE-")),0) -> 0 | L78: =IF(C78="",0,K78+IF(OR(B78="INGRESO",B78="DE REPROCESO",B78="AJUSTE+"),F78,IF(OR(B78="A CORTE",B78="A REPROCESO",B78="MUESTRA",B78="AJUSTE-"),-F78,0))) -> 19 | M78: tomas | O78: PROGRESO | R78: =IF(OR(Q78="",Q78=0,J78=0),"",(Q78-J78)/J78)
A79: 46149 | B79: INGRESO | C79: OverShark | D79: jersey full lycra 30/1 | E79: Botella | F79: 10 | G79: =IFERROR(F79*VLOOKUP(D79,TELAS!$A$4:$C$32,3,FALSE()),0) -> 200 | H79: =IFERROR(VLOOKUP(E79,COLORES!$A$4:$B$102,2,FALSE()),"") -> OSCURO | I79: =IFERROR(IF(H79="OSCURO",VLOOKUP(D79,PRECIOS!$A$4:$F$32,2,FALSE()),IF(H79="CLARO",VLOOKUP(D79,PRECIOS!$A$4:$F$32,3,FALSE()),IF(H79="MELANGE",VLOOKUP(D79,PRECIOS!$A$4:$F$32,4,FALSE()),IF(H79="PPT",VLOOKUP(D79,PRECIOS!$A$4:$F$32,5,FALSE()),0)))),0) -> 26 | J79: =IFERROR(G79*I79,0) -> 5200 | K79: =IFERROR(IF(C79="",0,SUMIFS($F$4:$F$78,$C$4:$C$78,C79,$D$4:$D$78,D79,$E$4:$E$78,E79,$B$4:$B$78,"INGRESO")+SUMIFS($F$4:$F$78,$C$4:$C$78,C79,$D$4:$D$78,D79,$E$4:$E$78,E79,$B$4:$B$78,"DE REPROCESO")+SUMIFS($F$4:$F$78,$C$4:$C$78,C79,$D$4:$D$78,D79,$E$4:$E$78,E79,$B$4:$B$78,"AJUSTE+")-SUMIFS($F$4:$F$78,$C$4:$C$78,C79,$D$4:$D$78,D79,$E$4:$E$78,E79,$B$4:$B$78,"A CORTE")-SUMIFS($F$4:$F$78,$C$4:$C$78,C79,$D$4:$D$78,D79,$E$4:$E$78,E79,$B$4:$B$78,"A REPROCESO")-SUMIFS($F$4:$F$78,$C$4:$C$78,C79,$D$4:$D$78,D79,$E$4:$E$78,E79,$B$4:$B$78,"MUESTRA")-SUMIFS($F$4:$F$78,$C$4:$C$78,C79,$D$4:$D$78,D79,$E$4:$E$78,E79,$B$4:$B$78,"AJUSTE-")),0) -> 0 | L79: =IF(C79="",0,K79+IF(OR(B79="INGRESO",B79="DE REPROCESO",B79="AJUSTE+"),F79,IF(OR(B79="A CORTE",B79="A REPROCESO",B79="MUESTRA",B79="AJUSTE-"),-F79,0))) -> 10 | M79: tomas | O79: PROGRESO | R79: =IF(OR(Q79="",Q79=0,J79=0),"",(Q79-J79)/J79)
A80: 46150 | B80: INGRESO | C80: OverShark | D80: jersey full lycra 30/1 | E80: Pacay | F80: 5 | G80: =IFERROR(F80*VLOOKUP(D80,TELAS!$A$4:$C$32,3,FALSE()),0) -> 100 | H80: =IFERROR(VLOOKUP(E80,COLORES!$A$4:$B$102,2,FALSE()),"") -> CLARO | I80: =IFERROR(IF(H80="OSCURO",VLOOKUP(D80,PRECIOS!$A$4:$F$32,2,FALSE()),IF(H80="CLARO",VLOOKUP(D80,PRECIOS!$A$4:$F$32,3,FALSE()),IF(H80="MELANGE",VLOOKUP(D80,PRECIOS!$A$4:$F$32,4,FALSE()),IF(H80="PPT",VLOOKUP(D80,PRECIOS!$A$4:$F$32,5,FALSE()),0)))),0) -> 22.5 | J80: =IFERROR(G80*I80,0) -> 2250 | K80: =IFERROR(IF(C80="",0,SUMIFS($F$4:$F$79,$C$4:$C$79,C80,$D$4:$D$79,D80,$E$4:$E$79,E80,$B$4:$B$79,"INGRESO")+SUMIFS($F$4:$F$79,$C$4:$C$79,C80,$D$4:$D$79,D80,$E$4:$E$79,E80,$B$4:$B$79,"DE REPROCESO")+SUMIFS($F$4:$F$79,$C$4:$C$79,C80,$D$4:$D$79,D80,$E$4:$E$79,E80,$B$4:$B$79,"AJUSTE+")-SUMIFS($F$4:$F$79,$C$4:$C$79,C80,$D$4:$D$79,D80,$E$4:$E$79,E80,$B$4:$B$79,"A CORTE")-SUMIFS($F$4:$F$79,$C$4:$C$79,C80,$D$4:$D$79,D80,$E$4:$E$79,E80,$B$4:$B$79,"A REPROCESO")-SUMIFS($F$4:$F$79,$C$4:$C$79,C80,$D$4:$D$79,D80,$E$4:$E$79,E80,$B$4:$B$79,"MUESTRA")-SUMIFS($F$4:$F$79,$C$4:$C$79,C80,$D$4:$D$79,D80,$E$4:$E$79,E80,$B$4:$B$79,"AJUSTE-")),0) -> 0 | L80: =IF(C80="",0,K80+IF(OR(B80="INGRESO",B80="DE REPROCESO",B80="AJUSTE+"),F80,IF(OR(B80="A CORTE",B80="A REPROCESO",B80="MUESTRA",B80="AJUSTE-"),-F80,0))) -> 5 | M80: tomas | O80: PROGRESO | R80: =IF(OR(Q80="",Q80=0,J80=0),"",(Q80-J80)/J80)
A81: 46151 | B81: INGRESO | C81: OverShark | D81: jersey full lycra 30/1 | E81: Cemento | F81: 6 | G81: =IFERROR(F81*VLOOKUP(D81,TELAS!$A$4:$C$32,3,FALSE()),0) -> 120 | H81: =IFERROR(VLOOKUP(E81,COLORES!$A$4:$B$102,2,FALSE()),"") -> CLARO | I81: =IFERROR(IF(H81="OSCURO",VLOOKUP(D81,PRECIOS!$A$4:$F$32,2,FALSE()),IF(H81="CLARO",VLOOKUP(D81,PRECIOS!$A$4:$F$32,3,FALSE()),IF(H81="MELANGE",VLOOKUP(D81,PRECIOS!$A$4:$F$32,4,FALSE()),IF(H81="PPT",VLOOKUP(D81,PRECIOS!$A$4:$F$32,5,FALSE()),0)))),0) -> 22.5 | J81: =IFERROR(G81*I81,0) -> 2700 | K81: =IFERROR(IF(C81="",0,SUMIFS($F$4:$F$80,$C$4:$C$80,C81,$D$4:$D$80,D81,$E$4:$E$80,E81,$B$4:$B$80,"INGRESO")+SUMIFS($F$4:$F$80,$C$4:$C$80,C81,$D$4:$D$80,D81,$E$4:$E$80,E81,$B$4:$B$80,"DE REPROCESO")+SUMIFS($F$4:$F$80,$C$4:$C$80,C81,$D$4:$D$80,D81,$E$4:$E$80,E81,$B$4:$B$80,"AJUSTE+")-SUMIFS($F$4:$F$80,$C$4:$C$80,C81,$D$4:$D$80,D81,$E$4:$E$80,E81,$B$4:$B$80,"A CORTE")-SUMIFS($F$4:$F$80,$C$4:$C$80,C81,$D$4:$D$80,D81,$E$4:$E$80,E81,$B$4:$B$80,"A REPROCESO")-SUMIFS($F$4:$F$80,$C$4:$C$80,C81,$D$4:$D$80,D81,$E$4:$E$80,E81,$B$4:$B$80,"MUESTRA")-SUMIFS($F$4:$F$80,$C$4:$C$80,C81,$D$4:$D$80,D81,$E$4:$E$80,E81,$B$4:$B$80,"AJUSTE-")),0) -> 0 | L81: =IF(C81="",0,K81+IF(OR(B81="INGRESO",B81="DE REPROCESO",B81="AJUSTE+"),F81,IF(OR(B81="A CORTE",B81="A REPROCESO",B81="MUESTRA",B81="AJUSTE-"),-F81,0))) -> 6 | M81: tomas | O81: PROGRESO | R81: =IF(OR(Q81="",Q81=0,J81=0),"",(Q81-J81)/J81)
A82: 46152 | B82: INGRESO | C82: OverShark | D82: jersey full lycra 30/1 | E82: P. Rosa | F82: 6 | G82: =IFERROR(F82*VLOOKUP(D82,TELAS!$A$4:$C$32,3,FALSE()),0) -> 120 | H82: =IFERROR(VLOOKUP(E82,COLORES!$A$4:$B$102,2,FALSE()),"") -> CLARO | I82: =IFERROR(IF(H82="OSCURO",VLOOKUP(D82,PRECIOS!$A$4:$F$32,2,FALSE()),IF(H82="CLARO",VLOOKUP(D82,PRECIOS!$A$4:$F$32,3,FALSE()),IF(H82="MELANGE",VLOOKUP(D82,PRECIOS!$A$4:$F$32,4,FALSE()),IF(H82="PPT",VLOOKUP(D82,PRECIOS!$A$4:$F$32,5,FALSE()),0)))),0) -> 22.5 | J82: =IFERROR(G82*I82,0) -> 2700 | K82: =IFERROR(IF(C82="",0,SUMIFS($F$4:$F$81,$C$4:$C$81,C82,$D$4:$D$81,D82,$E$4:$E$81,E82,$B$4:$B$81,"INGRESO")+SUMIFS($F$4:$F$81,$C$4:$C$81,C82,$D$4:$D$81,D82,$E$4:$E$81,E82,$B$4:$B$81,"DE REPROCESO")+SUMIFS($F$4:$F$81,$C$4:$C$81,C82,$D$4:$D$81,D82,$E$4:$E$81,E82,$B$4:$B$81,"AJUSTE+")-SUMIFS($F$4:$F$81,$C$4:$C$81,C82,$D$4:$D$81,D82,$E$4:$E$81,E82,$B$4:$B$81,"A CORTE")-SUMIFS($F$4:$F$81,$C$4:$C$81,C82,$D$4:$D$81,D82,$E$4:$E$81,E82,$B$4:$B$81,"A REPROCESO")-SUMIFS($F$4:$F$81,$C$4:$C$81,C82,$D$4:$D$81,D82,$E$4:$E$81,E82,$B$4:$B$81,"MUESTRA")-SUMIFS($F$4:$F$81,$C$4:$C$81,C82,$D$4:$D$81,D82,$E$4:$E$81,E82,$B$4:$B$81,"AJUSTE-")),0) -> 0 | L82: =IF(C82="",0,K82+IF(OR(B82="INGRESO",B82="DE REPROCESO",B82="AJUSTE+"),F82,IF(OR(B82="A CORTE",B82="A REPROCESO",B82="MUESTRA",B82="AJUSTE-"),-F82,0))) -> 6 | M82: tomas | O82: PROGRESO | R82: =IF(OR(Q82="",Q82=0,J82=0),"",(Q82-J82)/J82)
A83: 46153 | B83: INGRESO | C83: OverShark | D83: jersey full lycra 30/1 | E83: Beige | F83: 6 | G83: =IFERROR(F83*VLOOKUP(D83,TELAS!$A$4:$C$32,3,FALSE()),0) -> 120 | H83: =IFERROR(VLOOKUP(E83,COLORES!$A$4:$B$102,2,FALSE()),"") -> CLARO | I83: =IFERROR(IF(H83="OSCURO",VLOOKUP(D83,PRECIOS!$A$4:$F$32,2,FALSE()),IF(H83="CLARO",VLOOKUP(D83,PRECIOS!$A$4:$F$32,3,FALSE()),IF(H83="MELANGE",VLOOKUP(D83,PRECIOS!$A$4:$F$32,4,FALSE()),IF(H83="PPT",VLOOKUP(D83,PRECIOS!$A$4:$F$32,5,FALSE()),0)))),0) -> 22.5 | J83: =IFERROR(G83*I83,0) -> 2700 | K83: =IFERROR(IF(C83="",0,SUMIFS($F$4:$F$82,$C$4:$C$82,C83,$D$4:$D$82,D83,$E$4:$E$82,E83,$B$4:$B$82,"INGRESO")+SUMIFS($F$4:$F$82,$C$4:$C$82,C83,$D$4:$D$82,D83,$E$4:$E$82,E83,$B$4:$B$82,"DE REPROCESO")+SUMIFS($F$4:$F$82,$C$4:$C$82,C83,$D$4:$D$82,D83,$E$4:$E$82,E83,$B$4:$B$82,"AJUSTE+")-SUMIFS($F$4:$F$82,$C$4:$C$82,C83,$D$4:$D$82,D83,$E$4:$E$82,E83,$B$4:$B$82,"A CORTE")-SUMIFS($F$4:$F$82,$C$4:$C$82,C83,$D$4:$D$82,D83,$E$4:$E$82,E83,$B$4:$B$82,"A REPROCESO")-SUMIFS($F$4:$F$82,$C$4:$C$82,C83,$D$4:$D$82,D83,$E$4:$E$82,E83,$B$4:$B$82,"MUESTRA")-SUMIFS($F$4:$F$82,$C$4:$C$82,C83,$D$4:$D$82,D83,$E$4:$E$82,E83,$B$4:$B$82,"AJUSTE-")),0) -> 0 | L83: =IF(C83="",0,K83+IF(OR(B83="INGRESO",B83="DE REPROCESO",B83="AJUSTE+"),F83,IF(OR(B83="A CORTE",B83="A REPROCESO",B83="MUESTRA",B83="AJUSTE-"),-F83,0))) -> 6 | M83: tomas | O83: PROGRESO | R83: =IF(OR(Q83="",Q83=0,J83=0),"",(Q83-J83)/J83)
A84: 46154 | B84: INGRESO | C84: OverShark | D84: jersey full lycra 30/1 | E84: Vino | F84: 5 | G84: =IFERROR(F84*VLOOKUP(D84,TELAS!$A$4:$C$32,3,FALSE()),0) -> 100 | H84: =IFERROR(VLOOKUP(E84,COLORES!$A$4:$B$102,2,FALSE()),"") -> OSCURO | I84: =IFERROR(IF(H84="OSCURO",VLOOKUP(D84,PRECIOS!$A$4:$F$32,2,FALSE()),IF(H84="CLARO",VLOOKUP(D84,PRECIOS!$A$4:$F$32,3,FALSE()),IF(H84="MELANGE",VLOOKUP(D84,PRECIOS!$A$4:$F$32,4,FALSE()),IF(H84="PPT",VLOOKUP(D84,PRECIOS!$A$4:$F$32,5,FALSE()),0)))),0) -> 26 | J84: =IFERROR(G84*I84,0) -> 2600 | K84: =IFERROR(IF(C84="",0,SUMIFS($F$4:$F$83,$C$4:$C$83,C84,$D$4:$D$83,D84,$E$4:$E$83,E84,$B$4:$B$83,"INGRESO")+SUMIFS($F$4:$F$83,$C$4:$C$83,C84,$D$4:$D$83,D84,$E$4:$E$83,E84,$B$4:$B$83,"DE REPROCESO")+SUMIFS($F$4:$F$83,$C$4:$C$83,C84,$D$4:$D$83,D84,$E$4:$E$83,E84,$B$4:$B$83,"AJUSTE+")-SUMIFS($F$4:$F$83,$C$4:$C$83,C84,$D$4:$D$83,D84,$E$4:$E$83,E84,$B$4:$B$83,"A CORTE")-SUMIFS($F$4:$F$83,$C$4:$C$83,C84,$D$4:$D$83,D84,$E$4:$E$83,E84,$B$4:$B$83,"A REPROCESO")-SUMIFS($F$4:$F$83,$C$4:$C$83,C84,$D$4:$D$83,D84,$E$4:$E$83,E84,$B$4:$B$83,"MUESTRA")-SUMIFS($F$4:$F$83,$C$4:$C$83,C84,$D$4:$D$83,D84,$E$4:$E$83,E84,$B$4:$B$83,"AJUSTE-")),0) -> 0 | L84: =IF(C84="",0,K84+IF(OR(B84="INGRESO",B84="DE REPROCESO",B84="AJUSTE+"),F84,IF(OR(B84="A CORTE",B84="A REPROCESO",B84="MUESTRA",B84="AJUSTE-"),-F84,0))) -> 5 | M84: tomas | O84: PROGRESO | R84: =IF(OR(Q84="",Q84=0,J84=0),"",(Q84-J84)/J84)
A85: 46155 | B85: INGRESO | C85: OverShark | D85: jersey full lycra 30/1 | E85: Denim | F85: 6 | G85: =IFERROR(F85*VLOOKUP(D85,TELAS!$A$4:$C$32,3,FALSE()),0) -> 120 | H85: =IFERROR(VLOOKUP(E85,COLORES!$A$4:$B$102,2,FALSE()),"") -> CLARO | I85: =IFERROR(IF(H85="OSCURO",VLOOKUP(D85,PRECIOS!$A$4:$F$32,2,FALSE()),IF(H85="CLARO",VLOOKUP(D85,PRECIOS!$A$4:$F$32,3,FALSE()),IF(H85="MELANGE",VLOOKUP(D85,PRECIOS!$A$4:$F$32,4,FALSE()),IF(H85="PPT",VLOOKUP(D85,PRECIOS!$A$4:$F$32,5,FALSE()),0)))),0) -> 22.5 | J85: =IFERROR(G85*I85,0) -> 2700 | K85: =IFERROR(IF(C85="",0,SUMIFS($F$4:$F$84,$C$4:$C$84,C85,$D$4:$D$84,D85,$E$4:$E$84,E85,$B$4:$B$84,"INGRESO")+SUMIFS($F$4:$F$84,$C$4:$C$84,C85,$D$4:$D$84,D85,$E$4:$E$84,E85,$B$4:$B$84,"DE REPROCESO")+SUMIFS($F$4:$F$84,$C$4:$C$84,C85,$D$4:$D$84,D85,$E$4:$E$84,E85,$B$4:$B$84,"AJUSTE+")-SUMIFS($F$4:$F$84,$C$4:$C$84,C85,$D$4:$D$84,D85,$E$4:$E$84,E85,$B$4:$B$84,"A CORTE")-SUMIFS($F$4:$F$84,$C$4:$C$84,C85,$D$4:$D$84,D85,$E$4:$E$84,E85,$B$4:$B$84,"A REPROCESO")-SUMIFS($F$4:$F$84,$C$4:$C$84,C85,$D$4:$D$84,D85,$E$4:$E$84,E85,$B$4:$B$84,"MUESTRA")-SUMIFS($F$4:$F$84,$C$4:$C$84,C85,$D$4:$D$84,D85,$E$4:$E$84,E85,$B$4:$B$84,"AJUSTE-")),0) -> 0 | L85: =IF(C85="",0,K85+IF(OR(B85="INGRESO",B85="DE REPROCESO",B85="AJUSTE+"),F85,IF(OR(B85="A CORTE",B85="A REPROCESO",B85="MUESTRA",B85="AJUSTE-"),-F85,0))) -> 6 | M85: tomas | O85: PROGRESO | R85: =IF(OR(Q85="",Q85=0,J85=0),"",(Q85-J85)/J85)
A86: 46156 | B86: INGRESO | C86: OverShark | D86: jersey full lycra 30/1 | E86: Plomo | F86: 5 | G86: =IFERROR(F86*VLOOKUP(D86,TELAS!$A$4:$C$32,3,FALSE()),0) -> 100 | H86: =IFERROR(VLOOKUP(E86,COLORES!$A$4:$B$102,2,FALSE()),"") -> OSCURO | I86: =IFERROR(IF(H86="OSCURO",VLOOKUP(D86,PRECIOS!$A$4:$F$32,2,FALSE()),IF(H86="CLARO",VLOOKUP(D86,PRECIOS!$A$4:$F$32,3,FALSE()),IF(H86="MELANGE",VLOOKUP(D86,PRECIOS!$A$4:$F$32,4,FALSE()),IF(H86="PPT",VLOOKUP(D86,PRECIOS!$A$4:$F$32,5,FALSE()),0)))),0) -> 26 | J86: =IFERROR(G86*I86,0) -> 2600 | K86: =IFERROR(IF(C86="",0,SUMIFS($F$4:$F$85,$C$4:$C$85,C86,$D$4:$D$85,D86,$E$4:$E$85,E86,$B$4:$B$85,"INGRESO")+SUMIFS($F$4:$F$85,$C$4:$C$85,C86,$D$4:$D$85,D86,$E$4:$E$85,E86,$B$4:$B$85,"DE REPROCESO")+SUMIFS($F$4:$F$85,$C$4:$C$85,C86,$D$4:$D$85,D86,$E$4:$E$85,E86,$B$4:$B$85,"AJUSTE+")-SUMIFS($F$4:$F$85,$C$4:$C$85,C86,$D$4:$D$85,D86,$E$4:$E$85,E86,$B$4:$B$85,"A CORTE")-SUMIFS($F$4:$F$85,$C$4:$C$85,C86,$D$4:$D$85,D86,$E$4:$E$85,E86,$B$4:$B$85,"A REPROCESO")-SUMIFS($F$4:$F$85,$C$4:$C$85,C86,$D$4:$D$85,D86,$E$4:$E$85,E86,$B$4:$B$85,"MUESTRA")-SUMIFS($F$4:$F$85,$C$4:$C$85,C86,$D$4:$D$85,D86,$E$4:$E$85,E86,$B$4:$B$85,"AJUSTE-")),0) -> 0 | L86: =IF(C86="",0,K86+IF(OR(B86="INGRESO",B86="DE REPROCESO",B86="AJUSTE+"),F86,IF(OR(B86="A CORTE",B86="A REPROCESO",B86="MUESTRA",B86="AJUSTE-"),-F86,0))) -> 5 | M86: tomas | O86: PROGRESO | R86: =IF(OR(Q86="",Q86=0,J86=0),"",(Q86-J86)/J86)
A87: 46146 | B87: INGRESO | C87: OverShark | D87: rib 1x1 | E87: Negro | F87: 3 | G87: =IFERROR(F87*VLOOKUP(D87,TELAS!$A$4:$C$32,3,FALSE()),0) -> 60 | H87: =IFERROR(VLOOKUP(E87,COLORES!$A$4:$B$102,2,FALSE()),"") -> OSCURO | I87: =IFERROR(IF(H87="OSCURO",VLOOKUP(D87,PRECIOS!$A$4:$F$32,2,FALSE()),IF(H87="CLARO",VLOOKUP(D87,PRECIOS!$A$4:$F$32,3,FALSE()),IF(H87="MELANGE",VLOOKUP(D87,PRECIOS!$A$4:$F$32,4,FALSE()),IF(H87="PPT",VLOOKUP(D87,PRECIOS!$A$4:$F$32,5,FALSE()),0)))),0) -> 24 | J87: =IFERROR(G87*I87,0) -> 1440 | K87: =IFERROR(IF(C87="",0,SUMIFS($F$4:$F$86,$C$4:$C$86,C87,$D$4:$D$86,D87,$E$4:$E$86,E87,$B$4:$B$86,"INGRESO")+SUMIFS($F$4:$F$86,$C$4:$C$86,C87,$D$4:$D$86,D87,$E$4:$E$86,E87,$B$4:$B$86,"DE REPROCESO")+SUMIFS($F$4:$F$86,$C$4:$C$86,C87,$D$4:$D$86,D87,$E$4:$E$86,E87,$B$4:$B$86,"AJUSTE+")-SUMIFS($F$4:$F$86,$C$4:$C$86,C87,$D$4:$D$86,D87,$E$4:$E$86,E87,$B$4:$B$86,"A CORTE")-SUMIFS($F$4:$F$86,$C$4:$C$86,C87,$D$4:$D$86,D87,$E$4:$E$86,E87,$B$4:$B$86,"A REPROCESO")-SUMIFS($F$4:$F$86,$C$4:$C$86,C87,$D$4:$D$86,D87,$E$4:$E$86,E87,$B$4:$B$86,"MUESTRA")-SUMIFS($F$4:$F$86,$C$4:$C$86,C87,$D$4:$D$86,D87,$E$4:$E$86,E87,$B$4:$B$86,"AJUSTE-")),0) -> 0 | L87: =IF(C87="",0,K87+IF(OR(B87="INGRESO",B87="DE REPROCESO",B87="AJUSTE+"),F87,IF(OR(B87="A CORTE",B87="A REPROCESO",B87="MUESTRA",B87="AJUSTE-"),-F87,0))) -> 3 | M87: tomas | O87: PROGRESO | R87: =IF(OR(Q87="",Q87=0,J87=0),"",(Q87-J87)/J87)
A88: 46146 | B88: INGRESO | C88: OverShark | D88: rib 1x1 | E88: Perla | F88: 1 | G88: =IFERROR(F88*VLOOKUP(D88,TELAS!$A$4:$C$32,3,FALSE()),0) -> 20 | H88: =IFERROR(VLOOKUP(E88,COLORES!$A$4:$B$102,2,FALSE()),"") -> PPT | I88: =IFERROR(IF(H88="OSCURO",VLOOKUP(D88,PRECIOS!$A$4:$F$32,2,FALSE()),IF(H88="CLARO",VLOOKUP(D88,PRECIOS!$A$4:$F$32,3,FALSE()),IF(H88="MELANGE",VLOOKUP(D88,PRECIOS!$A$4:$F$32,4,FALSE()),IF(H88="PPT",VLOOKUP(D88,PRECIOS!$A$4:$F$32,5,FALSE()),0)))),0) -> 18 | J88: =IFERROR(G88*I88,0) -> 360 | K88: =IFERROR(IF(C88="",0,SUMIFS($F$4:$F$87,$C$4:$C$87,C88,$D$4:$D$87,D88,$E$4:$E$87,E88,$B$4:$B$87,"INGRESO")+SUMIFS($F$4:$F$87,$C$4:$C$87,C88,$D$4:$D$87,D88,$E$4:$E$87,E88,$B$4:$B$87,"DE REPROCESO")+SUMIFS($F$4:$F$87,$C$4:$C$87,C88,$D$4:$D$87,D88,$E$4:$E$87,E88,$B$4:$B$87,"AJUSTE+")-SUMIFS($F$4:$F$87,$C$4:$C$87,C88,$D$4:$D$87,D88,$E$4:$E$87,E88,$B$4:$B$87,"A CORTE")-SUMIFS($F$4:$F$87,$C$4:$C$87,C88,$D$4:$D$87,D88,$E$4:$E$87,E88,$B$4:$B$87,"A REPROCESO")-SUMIFS($F$4:$F$87,$C$4:$C$87,C88,$D$4:$D$87,D88,$E$4:$E$87,E88,$B$4:$B$87,"MUESTRA")-SUMIFS($F$4:$F$87,$C$4:$C$87,C88,$D$4:$D$87,D88,$E$4:$E$87,E88,$B$4:$B$87,"AJUSTE-")),0) -> 0 | L88: =IF(C88="",0,K88+IF(OR(B88="INGRESO",B88="DE REPROCESO",B88="AJUSTE+"),F88,IF(OR(B88="A CORTE",B88="A REPROCESO",B88="MUESTRA",B88="AJUSTE-"),-F88,0))) -> 1 | M88: tomas | O88: PROGRESO | R88: =IF(OR(Q88="",Q88=0,J88=0),"",(Q88-J88)/J88)
A89: 46146 | B89: INGRESO | C89: OverShark | D89: rib 1x1 | E89: Azul | F89: 1 | G89: =IFERROR(F89*VLOOKUP(D89,TELAS!$A$4:$C$32,3,FALSE()),0) -> 20 | H89: =IFERROR(VLOOKUP(E89,COLORES!$A$4:$B$102,2,FALSE()),"") -> OSCURO | I89: =IFERROR(IF(H89="OSCURO",VLOOKUP(D89,PRECIOS!$A$4:$F$32,2,FALSE()),IF(H89="CLARO",VLOOKUP(D89,PRECIOS!$A$4:$F$32,3,FALSE()),IF(H89="MELANGE",VLOOKUP(D89,PRECIOS!$A$4:$F$32,4,FALSE()),IF(H89="PPT",VLOOKUP(D89,PRECIOS!$A$4:$F$32,5,FALSE()),0)))),0) -> 24 | J89: =IFERROR(G89*I89,0) -> 480 | K89: =IFERROR(IF(C89="",0,SUMIFS($F$4:$F$88,$C$4:$C$88,C89,$D$4:$D$88,D89,$E$4:$E$88,E89,$B$4:$B$88,"INGRESO")+SUMIFS($F$4:$F$88,$C$4:$C$88,C89,$D$4:$D$88,D89,$E$4:$E$88,E89,$B$4:$B$88,"DE REPROCESO")+SUMIFS($F$4:$F$88,$C$4:$C$88,C89,$D$4:$D$88,D89,$E$4:$E$88,E89,$B$4:$B$88,"AJUSTE+")-SUMIFS($F$4:$F$88,$C$4:$C$88,C89,$D$4:$D$88,D89,$E$4:$E$88,E89,$B$4:$B$88,"A CORTE")-SUMIFS($F$4:$F$88,$C$4:$C$88,C89,$D$4:$D$88,D89,$E$4:$E$88,E89,$B$4:$B$88,"A REPROCESO")-SUMIFS($F$4:$F$88,$C$4:$C$88,C89,$D$4:$D$88,D89,$E$4:$E$88,E89,$B$4:$B$88,"MUESTRA")-SUMIFS($F$4:$F$88,$C$4:$C$88,C89,$D$4:$D$88,D89,$E$4:$E$88,E89,$B$4:$B$88,"AJUSTE-")),0) -> 0 | L89: =IF(C89="",0,K89+IF(OR(B89="INGRESO",B89="DE REPROCESO",B89="AJUSTE+"),F89,IF(OR(B89="A CORTE",B89="A REPROCESO",B89="MUESTRA",B89="AJUSTE-"),-F89,0))) -> 1 | M89: tomas | O89: PROGRESO | R89: =IF(OR(Q89="",Q89=0,J89=0),"",(Q89-J89)/J89)
A90: 46146 | B90: INGRESO | C90: OverShark | D90: rib 1x1 | E90: Botella | F90: 1 | G90: =IFERROR(F90*VLOOKUP(D90,TELAS!$A$4:$C$32,3,FALSE()),0) -> 20 | H90: =IFERROR(VLOOKUP(E90,COLORES!$A$4:$B$102,2,FALSE()),"") -> OSCURO | I90: =IFERROR(IF(H90="OSCURO",VLOOKUP(D90,PRECIOS!$A$4:$F$32,2,FALSE()),IF(H90="CLARO",VLOOKUP(D90,PRECIOS!$A$4:$F$32,3,FALSE()),IF(H90="MELANGE",VLOOKUP(D90,PRECIOS!$A$4:$F$32,4,FALSE()),IF(H90="PPT",VLOOKUP(D90,PRECIOS!$A$4:$F$32,5,FALSE()),0)))),0) -> 24 | J90: =IFERROR(G90*I90,0) -> 480 | K90: =IFERROR(IF(C90="",0,SUMIFS($F$4:$F$89,$C$4:$C$89,C90,$D$4:$D$89,D90,$E$4:$E$89,E90,$B$4:$B$89,"INGRESO")+SUMIFS($F$4:$F$89,$C$4:$C$89,C90,$D$4:$D$89,D90,$E$4:$E$89,E90,$B$4:$B$89,"DE REPROCESO")+SUMIFS($F$4:$F$89,$C$4:$C$89,C90,$D$4:$D$89,D90,$E$4:$E$89,E90,$B$4:$B$89,"AJUSTE+")-SUMIFS($F$4:$F$89,$C$4:$C$89,C90,$D$4:$D$89,D90,$E$4:$E$89,E90,$B$4:$B$89,"A CORTE")-SUMIFS($F$4:$F$89,$C$4:$C$89,C90,$D$4:$D$89,D90,$E$4:$E$89,E90,$B$4:$B$89,"A REPROCESO")-SUMIFS($F$4:$F$89,$C$4:$C$89,C90,$D$4:$D$89,D90,$E$4:$E$89,E90,$B$4:$B$89,"MUESTRA")-SUMIFS($F$4:$F$89,$C$4:$C$89,C90,$D$4:$D$89,D90,$E$4:$E$89,E90,$B$4:$B$89,"AJUSTE-")),0) -> 0 | L90: =IF(C90="",0,K90+IF(OR(B90="INGRESO",B90="DE REPROCESO",B90="AJUSTE+"),F90,IF(OR(B90="A CORTE",B90="A REPROCESO",B90="MUESTRA",B90="AJUSTE-"),-F90,0))) -> 1 | M90: tomas | O90: PROGRESO | R90: =IF(OR(Q90="",Q90=0,J90=0),"",(Q90-J90)/J90)
A91: 46146 | B91: INGRESO | C91: OverShark | D91: rib 1x1 | E91: Plomo | F91: 1 | G91: =IFERROR(F91*VLOOKUP(D91,TELAS!$A$4:$C$32,3,FALSE()),0) -> 20 | H91: =IFERROR(VLOOKUP(E91,COLORES!$A$4:$B$102,2,FALSE()),"") -> OSCURO | I91: =IFERROR(IF(H91="OSCURO",VLOOKUP(D91,PRECIOS!$A$4:$F$32,2,FALSE()),IF(H91="CLARO",VLOOKUP(D91,PRECIOS!$A$4:$F$32,3,FALSE()),IF(H91="MELANGE",VLOOKUP(D91,PRECIOS!$A$4:$F$32,4,FALSE()),IF(H91="PPT",VLOOKUP(D91,PRECIOS!$A$4:$F$32,5,FALSE()),0)))),0) -> 24 | J91: =IFERROR(G91*I91,0) -> 480 | K91: =IFERROR(IF(C91="",0,SUMIFS($F$4:$F$90,$C$4:$C$90,C91,$D$4:$D$90,D91,$E$4:$E$90,E91,$B$4:$B$90,"INGRESO")+SUMIFS($F$4:$F$90,$C$4:$C$90,C91,$D$4:$D$90,D91,$E$4:$E$90,E91,$B$4:$B$90,"DE REPROCESO")+SUMIFS($F$4:$F$90,$C$4:$C$90,C91,$D$4:$D$90,D91,$E$4:$E$90,E91,$B$4:$B$90,"AJUSTE+")-SUMIFS($F$4:$F$90,$C$4:$C$90,C91,$D$4:$D$90,D91,$E$4:$E$90,E91,$B$4:$B$90,"A CORTE")-SUMIFS($F$4:$F$90,$C$4:$C$90,C91,$D$4:$D$90,D91,$E$4:$E$90,E91,$B$4:$B$90,"A REPROCESO")-SUMIFS($F$4:$F$90,$C$4:$C$90,C91,$D$4:$D$90,D91,$E$4:$E$90,E91,$B$4:$B$90,"MUESTRA")-SUMIFS($F$4:$F$90,$C$4:$C$90,C91,$D$4:$D$90,D91,$E$4:$E$90,E91,$B$4:$B$90,"AJUSTE-")),0) -> 0 | L91: =IF(C91="",0,K91+IF(OR(B91="INGRESO",B91="DE REPROCESO",B91="AJUSTE+"),F91,IF(OR(B91="A CORTE",B91="A REPROCESO",B91="MUESTRA",B91="AJUSTE-"),-F91,0))) -> 1 | M91: tomas | O91: PROGRESO | R91: =IF(OR(Q91="",Q91=0,J91=0),"",(Q91-J91)/J91)
A92: 46150 | B92: INGRESO | C92: OverShark | D92: rib 2x1 lycrado | E92: Negro | F92: 14 | G92: =IFERROR(F92*VLOOKUP(D92,TELAS!$A$4:$C$32,3,FALSE()),0) -> 280 | H92: =IFERROR(VLOOKUP(E92,COLORES!$A$4:$B$102,2,FALSE()),"") -> OSCURO | I92: =IFERROR(IF(H92="OSCURO",VLOOKUP(D92,PRECIOS!$A$4:$F$32,2,FALSE()),IF(H92="CLARO",VLOOKUP(D92,PRECIOS!$A$4:$F$32,3,FALSE()),IF(H92="MELANGE",VLOOKUP(D92,PRECIOS!$A$4:$F$32,4,FALSE()),IF(H92="PPT",VLOOKUP(D92,PRECIOS!$A$4:$F$32,5,FALSE()),0)))),0) -> 24 | J92: =IFERROR(G92*I92,0) -> 6720 | K92: =IFERROR(IF(C92="",0,SUMIFS($F$4:$F$91,$C$4:$C$91,C92,$D$4:$D$91,D92,$E$4:$E$91,E92,$B$4:$B$91,"INGRESO")+SUMIFS($F$4:$F$91,$C$4:$C$91,C92,$D$4:$D$91,D92,$E$4:$E$91,E92,$B$4:$B$91,"DE REPROCESO")+SUMIFS($F$4:$F$91,$C$4:$C$91,C92,$D$4:$D$91,D92,$E$4:$E$91,E92,$B$4:$B$91,"AJUSTE+")-SUMIFS($F$4:$F$91,$C$4:$C$91,C92,$D$4:$D$91,D92,$E$4:$E$91,E92,$B$4:$B$91,"A CORTE")-SUMIFS($F$4:$F$91,$C$4:$C$91,C92,$D$4:$D$91,D92,$E$4:$E$91,E92,$B$4:$B$91,"A REPROCESO")-SUMIFS($F$4:$F$91,$C$4:$C$91,C92,$D$4:$D$91,D92,$E$4:$E$91,E92,$B$4:$B$91,"MUESTRA")-SUMIFS($F$4:$F$91,$C$4:$C$91,C92,$D$4:$D$91,D92,$E$4:$E$91,E92,$B$4:$B$91,"AJUSTE-")),0) -> 0 | L92: =IF(C92="",0,K92+IF(OR(B92="INGRESO",B92="DE REPROCESO",B92="AJUSTE+"),F92,IF(OR(B92="A CORTE",B92="A REPROCESO",B92="MUESTRA",B92="AJUSTE-"),-F92,0))) -> 14 | M92: tomas | O92: PROGRESO | R92: =IF(OR(Q92="",Q92=0,J92=0),"",(Q92-J92)/J92)
A93: 46150 | B93: INGRESO | C93: OverShark | D93: rib 2x1 lycrado | E93: Perla | F93: 12 | G93: =IFERROR(F93*VLOOKUP(D93,TELAS!$A$4:$C$32,3,FALSE()),0) -> 240 | H93: =IFERROR(VLOOKUP(E93,COLORES!$A$4:$B$102,2,FALSE()),"") -> PPT | I93: =IFERROR(IF(H93="OSCURO",VLOOKUP(D93,PRECIOS!$A$4:$F$32,2,FALSE()),IF(H93="CLARO",VLOOKUP(D93,PRECIOS!$A$4:$F$32,3,FALSE()),IF(H93="MELANGE",VLOOKUP(D93,PRECIOS!$A$4:$F$32,4,FALSE()),IF(H93="PPT",VLOOKUP(D93,PRECIOS!$A$4:$F$32,5,FALSE()),0)))),0) -> 18 | J93: =IFERROR(G93*I93,0) -> 4320 | K93: =IFERROR(IF(C93="",0,SUMIFS($F$4:$F$92,$C$4:$C$92,C93,$D$4:$D$92,D93,$E$4:$E$92,E93,$B$4:$B$92,"INGRESO")+SUMIFS($F$4:$F$92,$C$4:$C$92,C93,$D$4:$D$92,D93,$E$4:$E$92,E93,$B$4:$B$92,"DE REPROCESO")+SUMIFS($F$4:$F$92,$C$4:$C$92,C93,$D$4:$D$92,D93,$E$4:$E$92,E93,$B$4:$B$92,"AJUSTE+")-SUMIFS($F$4:$F$92,$C$4:$C$92,C93,$D$4:$D$92,D93,$E$4:$E$92,E93,$B$4:$B$92,"A CORTE")-SUMIFS($F$4:$F$92,$C$4:$C$92,C93,$D$4:$D$92,D93,$E$4:$E$92,E93,$B$4:$B$92,"A REPROCESO")-SUMIFS($F$4:$F$92,$C$4:$C$92,C93,$D$4:$D$92,D93,$E$4:$E$92,E93,$B$4:$B$92,"MUESTRA")-SUMIFS($F$4:$F$92,$C$4:$C$92,C93,$D$4:$D$92,D93,$E$4:$E$92,E93,$B$4:$B$92,"AJUSTE-")),0) -> 0 | L93: =IF(C93="",0,K93+IF(OR(B93="INGRESO",B93="DE REPROCESO",B93="AJUSTE+"),F93,IF(OR(B93="A CORTE",B93="A REPROCESO",B93="MUESTRA",B93="AJUSTE-"),-F93,0))) -> 12 | M93: tomas | O93: PROGRESO | R93: =IF(OR(Q93="",Q93=0,J93=0),"",(Q93-J93)/J93)
A94: 46150 | B94: INGRESO | C94: OverShark | D94: rib 2x1 lycrado | E94: Azul | F94: 10 | G94: =IFERROR(F94*VLOOKUP(D94,TELAS!$A$4:$C$32,3,FALSE()),0) -> 200 | H94: =IFERROR(VLOOKUP(E94,COLORES!$A$4:$B$102,2,FALSE()),"") -> OSCURO | I94: =IFERROR(IF(H94="OSCURO",VLOOKUP(D94,PRECIOS!$A$4:$F$32,2,FALSE()),IF(H94="CLARO",VLOOKUP(D94,PRECIOS!$A$4:$F$32,3,FALSE()),IF(H94="MELANGE",VLOOKUP(D94,PRECIOS!$A$4:$F$32,4,FALSE()),IF(H94="PPT",VLOOKUP(D94,PRECIOS!$A$4:$F$32,5,FALSE()),0)))),0) -> 24 | J94: =IFERROR(G94*I94,0) -> 4800 | K94: =IFERROR(IF(C94="",0,SUMIFS($F$4:$F$93,$C$4:$C$93,C94,$D$4:$D$93,D94,$E$4:$E$93,E94,$B$4:$B$93,"INGRESO")+SUMIFS($F$4:$F$93,$C$4:$C$93,C94,$D$4:$D$93,D94,$E$4:$E$93,E94,$B$4:$B$93,"DE REPROCESO")+SUMIFS($F$4:$F$93,$C$4:$C$93,C94,$D$4:$D$93,D94,$E$4:$E$93,E94,$B$4:$B$93,"AJUSTE+")-SUMIFS($F$4:$F$93,$C$4:$C$93,C94,$D$4:$D$93,D94,$E$4:$E$93,E94,$B$4:$B$93,"A CORTE")-SUMIFS($F$4:$F$93,$C$4:$C$93,C94,$D$4:$D$93,D94,$E$4:$E$93,E94,$B$4:$B$93,"A REPROCESO")-SUMIFS($F$4:$F$93,$C$4:$C$93,C94,$D$4:$D$93,D94,$E$4:$E$93,E94,$B$4:$B$93,"MUESTRA")-SUMIFS($F$4:$F$93,$C$4:$C$93,C94,$D$4:$D$93,D94,$E$4:$E$93,E94,$B$4:$B$93,"AJUSTE-")),0) -> 0 | L94: =IF(C94="",0,K94+IF(OR(B94="INGRESO",B94="DE REPROCESO",B94="AJUSTE+"),F94,IF(OR(B94="A CORTE",B94="A REPROCESO",B94="MUESTRA",B94="AJUSTE-"),-F94,0))) -> 10 | M94: tomas | O94: PROGRESO | R94: =IF(OR(Q94="",Q94=0,J94=0),"",(Q94-J94)/J94)
A95: 46150 | B95: INGRESO | C95: OverShark | D95: rib 2x1 lycrado | E95: Botella | F95: 8 | G95: =IFERROR(F95*VLOOKUP(D95,TELAS!$A$4:$C$32,3,FALSE()),0) -> 160 | H95: =IFERROR(VLOOKUP(E95,COLORES!$A$4:$B$102,2,FALSE()),"") -> OSCURO | I95: =IFERROR(IF(H95="OSCURO",VLOOKUP(D95,PRECIOS!$A$4:$F$32,2,FALSE()),IF(H95="CLARO",VLOOKUP(D95,PRECIOS!$A$4:$F$32,3,FALSE()),IF(H95="MELANGE",VLOOKUP(D95,PRECIOS!$A$4:$F$32,4,FALSE()),IF(H95="PPT",VLOOKUP(D95,PRECIOS!$A$4:$F$32,5,FALSE()),0)))),0) -> 24 | J95: =IFERROR(G95*I95,0) -> 3840 | K95: =IFERROR(IF(C95="",0,SUMIFS($F$4:$F$94,$C$4:$C$94,C95,$D$4:$D$94,D95,$E$4:$E$94,E95,$B$4:$B$94,"INGRESO")+SUMIFS($F$4:$F$94,$C$4:$C$94,C95,$D$4:$D$94,D95,$E$4:$E$94,E95,$B$4:$B$94,"DE REPROCESO")+SUMIFS($F$4:$F$94,$C$4:$C$94,C95,$D$4:$D$94,D95,$E$4:$E$94,E95,$B$4:$B$94,"AJUSTE+")-SUMIFS($F$4:$F$94,$C$4:$C$94,C95,$D$4:$D$94,D95,$E$4:$E$94,E95,$B$4:$B$94,"A CORTE")-SUMIFS($F$4:$F$94,$C$4:$C$94,C95,$D$4:$D$94,D95,$E$4:$E$94,E95,$B$4:$B$94,"A REPROCESO")-SUMIFS($F$4:$F$94,$C$4:$C$94,C95,$D$4:$D$94,D95,$E$4:$E$94,E95,$B$4:$B$94,"MUESTRA")-SUMIFS($F$4:$F$94,$C$4:$C$94,C95,$D$4:$D$94,D95,$E$4:$E$94,E95,$B$4:$B$94,"AJUSTE-")),0) -> 0 | L95: =IF(C95="",0,K95+IF(OR(B95="INGRESO",B95="DE REPROCESO",B95="AJUSTE+"),F95,IF(OR(B95="A CORTE",B95="A REPROCESO",B95="MUESTRA",B95="AJUSTE-"),-F95,0))) -> 8 | M95: tomas | O95: PROGRESO | R95: =IF(OR(Q95="",Q95=0,J95=0),"",(Q95-J95)/J95)
A96: 46150 | B96: INGRESO | C96: OverShark | D96: rib 2x1 lycrado | E96: Pacay | F96: 4 | G96: =IFERROR(F96*VLOOKUP(D96,TELAS!$A$4:$C$32,3,FALSE()),0) -> 80 | H96: =IFERROR(VLOOKUP(E96,COLORES!$A$4:$B$102,2,FALSE()),"") -> CLARO | I96: =IFERROR(IF(H96="OSCURO",VLOOKUP(D96,PRECIOS!$A$4:$F$32,2,FALSE()),IF(H96="CLARO",VLOOKUP(D96,PRECIOS!$A$4:$F$32,3,FALSE()),IF(H96="MELANGE",VLOOKUP(D96,PRECIOS!$A$4:$F$32,4,FALSE()),IF(H96="PPT",VLOOKUP(D96,PRECIOS!$A$4:$F$32,5,FALSE()),0)))),0) -> 21 | J96: =IFERROR(G96*I96,0) -> 1680 | K96: =IFERROR(IF(C96="",0,SUMIFS($F$4:$F$95,$C$4:$C$95,C96,$D$4:$D$95,D96,$E$4:$E$95,E96,$B$4:$B$95,"INGRESO")+SUMIFS($F$4:$F$95,$C$4:$C$95,C96,$D$4:$D$95,D96,$E$4:$E$95,E96,$B$4:$B$95,"DE REPROCESO")+SUMIFS($F$4:$F$95,$C$4:$C$95,C96,$D$4:$D$95,D96,$E$4:$E$95,E96,$B$4:$B$95,"AJUSTE+")-SUMIFS($F$4:$F$95,$C$4:$C$95,C96,$D$4:$D$95,D96,$E$4:$E$95,E96,$B$4:$B$95,"A CORTE")-SUMIFS($F$4:$F$95,$C$4:$C$95,C96,$D$4:$D$95,D96,$E$4:$E$95,E96,$B$4:$B$95,"A REPROCESO")-SUMIFS($F$4:$F$95,$C$4:$C$95,C96,$D$4:$D$95,D96,$E$4:$E$95,E96,$B$4:$B$95,"MUESTRA")-SUMIFS($F$4:$F$95,$C$4:$C$95,C96,$D$4:$D$95,D96,$E$4:$E$95,E96,$B$4:$B$95,"AJUSTE-")),0) -> 0 | L96: =IF(C96="",0,K96+IF(OR(B96="INGRESO",B96="DE REPROCESO",B96="AJUSTE+"),F96,IF(OR(B96="A CORTE",B96="A REPROCESO",B96="MUESTRA",B96="AJUSTE-"),-F96,0))) -> 4 | M96: tomas | O96: PROGRESO | R96: =IF(OR(Q96="",Q96=0,J96=0),"",(Q96-J96)/J96)
A97: 46150 | B97: INGRESO | C97: OverShark | D97: rib 2x1 lycrado | E97: Cemento | F97: 6 | G97: =IFERROR(F97*VLOOKUP(D97,TELAS!$A$4:$C$32,3,FALSE()),0) -> 120 | H97: =IFERROR(VLOOKUP(E97,COLORES!$A$4:$B$102,2,FALSE()),"") -> CLARO | I97: =IFERROR(IF(H97="OSCURO",VLOOKUP(D97,PRECIOS!$A$4:$F$32,2,FALSE()),IF(H97="CLARO",VLOOKUP(D97,PRECIOS!$A$4:$F$32,3,FALSE()),IF(H97="MELANGE",VLOOKUP(D97,PRECIOS!$A$4:$F$32,4,FALSE()),IF(H97="PPT",VLOOKUP(D97,PRECIOS!$A$4:$F$32,5,FALSE()),0)))),0) -> 21 | J97: =IFERROR(G97*I97,0) -> 2520 | K97: =IFERROR(IF(C97="",0,SUMIFS($F$4:$F$96,$C$4:$C$96,C97,$D$4:$D$96,D97,$E$4:$E$96,E97,$B$4:$B$96,"INGRESO")+SUMIFS($F$4:$F$96,$C$4:$C$96,C97,$D$4:$D$96,D97,$E$4:$E$96,E97,$B$4:$B$96,"DE REPROCESO")+SUMIFS($F$4:$F$96,$C$4:$C$96,C97,$D$4:$D$96,D97,$E$4:$E$96,E97,$B$4:$B$96,"AJUSTE+")-SUMIFS($F$4:$F$96,$C$4:$C$96,C97,$D$4:$D$96,D97,$E$4:$E$96,E97,$B$4:$B$96,"A CORTE")-SUMIFS($F$4:$F$96,$C$4:$C$96,C97,$D$4:$D$96,D97,$E$4:$E$96,E97,$B$4:$B$96,"A REPROCESO")-SUMIFS($F$4:$F$96,$C$4:$C$96,C97,$D$4:$D$96,D97,$E$4:$E$96,E97,$B$4:$B$96,"MUESTRA")-SUMIFS($F$4:$F$96,$C$4:$C$96,C97,$D$4:$D$96,D97,$E$4:$E$96,E97,$B$4:$B$96,"AJUSTE-")),0) -> 0 | L97: =IF(C97="",0,K97+IF(OR(B97="INGRESO",B97="DE REPROCESO",B97="AJUSTE+"),F97,IF(OR(B97="A CORTE",B97="A REPROCESO",B97="MUESTRA",B97="AJUSTE-"),-F97,0))) -> 6 | M97: tomas | O97: PROGRESO | R97: =IF(OR(Q97="",Q97=0,J97=0),"",(Q97-J97)/J97)
A98: 46150 | B98: INGRESO | C98: OverShark | D98: rib 2x1 lycrado | E98: P. Rosa | F98: 5 | G98: =IFERROR(F98*VLOOKUP(D98,TELAS!$A$4:$C$32,3,FALSE()),0) -> 100 | H98: =IFERROR(VLOOKUP(E98,COLORES!$A$4:$B$102,2,FALSE()),"") -> CLARO | I98: =IFERROR(IF(H98="OSCURO",VLOOKUP(D98,PRECIOS!$A$4:$F$32,2,FALSE()),IF(H98="CLARO",VLOOKUP(D98,PRECIOS!$A$4:$F$32,3,FALSE()),IF(H98="MELANGE",VLOOKUP(D98,PRECIOS!$A$4:$F$32,4,FALSE()),IF(H98="PPT",VLOOKUP(D98,PRECIOS!$A$4:$F$32,5,FALSE()),0)))),0) -> 21 | J98: =IFERROR(G98*I98,0) -> 2100 | K98: =IFERROR(IF(C98="",0,SUMIFS($F$4:$F$97,$C$4:$C$97,C98,$D$4:$D$97,D98,$E$4:$E$97,E98,$B$4:$B$97,"INGRESO")+SUMIFS($F$4:$F$97,$C$4:$C$97,C98,$D$4:$D$97,D98,$E$4:$E$97,E98,$B$4:$B$97,"DE REPROCESO")+SUMIFS($F$4:$F$97,$C$4:$C$97,C98,$D$4:$D$97,D98,$E$4:$E$97,E98,$B$4:$B$97,"AJUSTE+")-SUMIFS($F$4:$F$97,$C$4:$C$97,C98,$D$4:$D$97,D98,$E$4:$E$97,E98,$B$4:$B$97,"A CORTE")-SUMIFS($F$4:$F$97,$C$4:$C$97,C98,$D$4:$D$97,D98,$E$4:$E$97,E98,$B$4:$B$97,"A REPROCESO")-SUMIFS($F$4:$F$97,$C$4:$C$97,C98,$D$4:$D$97,D98,$E$4:$E$97,E98,$B$4:$B$97,"MUESTRA")-SUMIFS($F$4:$F$97,$C$4:$C$97,C98,$D$4:$D$97,D98,$E$4:$E$97,E98,$B$4:$B$97,"AJUSTE-")),0) -> 0 | L98: =IF(C98="",0,K98+IF(OR(B98="INGRESO",B98="DE REPROCESO",B98="AJUSTE+"),F98,IF(OR(B98="A CORTE",B98="A REPROCESO",B98="MUESTRA",B98="AJUSTE-"),-F98,0))) -> 5 | M98: tomas | O98: PROGRESO | R98: =IF(OR(Q98="",Q98=0,J98=0),"",(Q98-J98)/J98)
A99: 46150 | B99: INGRESO | C99: OverShark | D99: rib 2x1 lycrado | E99: Beige | F99: 4 | G99: =IFERROR(F99*VLOOKUP(D99,TELAS!$A$4:$C$32,3,FALSE()),0) -> 80 | H99: =IFERROR(VLOOKUP(E99,COLORES!$A$4:$B$102,2,FALSE()),"") -> CLARO | I99: =IFERROR(IF(H99="OSCURO",VLOOKUP(D99,PRECIOS!$A$4:$F$32,2,FALSE()),IF(H99="CLARO",VLOOKUP(D99,PRECIOS!$A$4:$F$32,3,FALSE()),IF(H99="MELANGE",VLOOKUP(D99,PRECIOS!$A$4:$F$32,4,FALSE()),IF(H99="PPT",VLOOKUP(D99,PRECIOS!$A$4:$F$32,5,FALSE()),0)))),0) -> 21 | J99: =IFERROR(G99*I99,0) -> 1680 | K99: =IFERROR(IF(C99="",0,SUMIFS($F$4:$F$98,$C$4:$C$98,C99,$D$4:$D$98,D99,$E$4:$E$98,E99,$B$4:$B$98,"INGRESO")+SUMIFS($F$4:$F$98,$C$4:$C$98,C99,$D$4:$D$98,D99,$E$4:$E$98,E99,$B$4:$B$98,"DE REPROCESO")+SUMIFS($F$4:$F$98,$C$4:$C$98,C99,$D$4:$D$98,D99,$E$4:$E$98,E99,$B$4:$B$98,"AJUSTE+")-SUMIFS($F$4:$F$98,$C$4:$C$98,C99,$D$4:$D$98,D99,$E$4:$E$98,E99,$B$4:$B$98,"A CORTE")-SUMIFS($F$4:$F$98,$C$4:$C$98,C99,$D$4:$D$98,D99,$E$4:$E$98,E99,$B$4:$B$98,"A REPROCESO")-SUMIFS($F$4:$F$98,$C$4:$C$98,C99,$D$4:$D$98,D99,$E$4:$E$98,E99,$B$4:$B$98,"MUESTRA")-SUMIFS($F$4:$F$98,$C$4:$C$98,C99,$D$4:$D$98,D99,$E$4:$E$98,E99,$B$4:$B$98,"AJUSTE-")),0) -> 0 | L99: =IF(C99="",0,K99+IF(OR(B99="INGRESO",B99="DE REPROCESO",B99="AJUSTE+"),F99,IF(OR(B99="A CORTE",B99="A REPROCESO",B99="MUESTRA",B99="AJUSTE-"),-F99,0))) -> 4 | M99: tomas | O99: PROGRESO | R99: =IF(OR(Q99="",Q99=0,J99=0),"",(Q99-J99)/J99)
A100: 46150 | B100: INGRESO | C100: OverShark | D100: rib 2x1 lycrado | E100: Vino | F100: 7 | G100: =IFERROR(F100*VLOOKUP(D100,TELAS!$A$4:$C$32,3,FALSE()),0) -> 140 | H100: =IFERROR(VLOOKUP(E100,COLORES!$A$4:$B$102,2,FALSE()),"") -> OSCURO | I100: =IFERROR(IF(H100="OSCURO",VLOOKUP(D100,PRECIOS!$A$4:$F$32,2,FALSE()),IF(H100="CLARO",VLOOKUP(D100,PRECIOS!$A$4:$F$32,3,FALSE()),IF(H100="MELANGE",VLOOKUP(D100,PRECIOS!$A$4:$F$32,4,FALSE()),IF(H100="PPT",VLOOKUP(D100,PRECIOS!$A$4:$F$32,5,FALSE()),0)))),0) -> 24 | J100: =IFERROR(G100*I100,0) -> 3360 | K100: =IFERROR(IF(C100="",0,SUMIFS($F$4:$F$99,$C$4:$C$99,C100,$D$4:$D$99,D100,$E$4:$E$99,E100,$B$4:$B$99,"INGRESO")+SUMIFS($F$4:$F$99,$C$4:$C$99,C100,$D$4:$D$99,D100,$E$4:$E$99,E100,$B$4:$B$99,"DE REPROCESO")+SUMIFS($F$4:$F$99,$C$4:$C$99,C100,$D$4:$D$99,D100,$E$4:$E$99,E100,$B$4:$B$99,"AJUSTE+")-SUMIFS($F$4:$F$99,$C$4:$C$99,C100,$D$4:$D$99,D100,$E$4:$E$99,E100,$B$4:$B$99,"A CORTE")-SUMIFS($F$4:$F$99,$C$4:$C$99,C100,$D$4:$D$99,D100,$E$4:$E$99,E100,$B$4:$B$99,"A REPROCESO")-SUMIFS($F$4:$F$99,$C$4:$C$99,C100,$D$4:$D$99,D100,$E$4:$E$99,E100,$B$4:$B$99,"MUESTRA")-SUMIFS($F$4:$F$99,$C$4:$C$99,C100,$D$4:$D$99,D100,$E$4:$E$99,E100,$B$4:$B$99,"AJUSTE-")),0) -> 0 | L100: =IF(C100="",0,K100+IF(OR(B100="INGRESO",B100="DE REPROCESO",B100="AJUSTE+"),F100,IF(OR(B100="A CORTE",B100="A REPROCESO",B100="MUESTRA",B100="AJUSTE-"),-F100,0))) -> 7 | M100: tomas | O100: PROGRESO | R100: =IF(OR(Q100="",Q100=0,J100=0),"",(Q100-J100)/J100)
...

Sheet MOVIMIENTOS_COMPLEMENTOS
A1: MOVIMIENTOS COMPLEMENTOS — Cuellos / Puños / Pretinas
A2: Solo 3 tipos: INGRESO (compra externa, req. proveedor/factura), DE CORTE (cortado de rib internamente), SALIDA (al taller, muestra, etc).
A3: FECHA | B3: TIPO MOV | C3: CLIENTE | D3: TIPO PIEZA | E3: ORIGEN | F3: PRODUCTO DESTINO | G3: COLOR | H3: TALLA | I3: CANTIDAD | J3: PRECIO UNIT | K3: TOTAL S/. | L3: STOCK ANTES | M3: STOCK DESPUÉS | N3: PROVEEDOR | O3: N° FACTURA | P3: COSTO REAL FACT. | Q3: NOTAS
J4: {=IFERROR(INDEX(PRECIOS_COMPLEMENTOS!$C$4:$F$17,MATCH(D4&"_"&E4,PRECIOS_COMPLEMENTOS!$H$4:$H$17,0),IF(OR(H4="S",H4="20cm"),1,IF(OR(H4="M",H4="25cm"),2,IF(OR(H4="L",H4="30cm"),3,IF(OR(H4="XL",H4="35cm"),4,0))))),0)} -> #REF! | K4: =IFERROR(I4*J4,0) -> 0 | L4: =0 -> 0 | M4: =IF(C4="",0,L4+IF(OR(B4="INGRESO",B4="DE CORTE"),I4,IF(B4="SALIDA",-I4,0))) -> 0
J5: {=IFERROR(INDEX(PRECIOS_COMPLEMENTOS!$C$4:$F$17,MATCH(D5&"_"&E5,PRECIOS_COMPLEMENTOS!$H$4:$H$17,0),IF(OR(H5="S",H5="20cm"),1,IF(OR(H5="M",H5="25cm"),2,IF(OR(H5="L",H5="30cm"),3,IF(OR(H5="XL",H5="35cm"),4,0))))),0)} -> #REF! | K5: =IFERROR(I5*J5,0) -> 0 | L5: =IFERROR(IF(C5="",0,IF(D5="PRETINA",SUMIFS($I$4,$C$4,C5,$D$4,D5,$E$4,E5,$F$4,F5,$G$4,G5,$H$4,H5,$B$4,"INGRESO")+SUMIFS($I$4,$C$4,C5,$D$4,D5,$E$4,E5,$F$4,F5,$G$4,G5,$H$4,H5,$B$4,"DE CORTE")-SUMIFS($I$4,$C$4,C5,$D$4,D5,$E$4,E5,$F$4,F5,$G$4,G5,$H$4,H5,$B$4,"SALIDA"),SUMIFS($I$4,$C$4,C5,$D$4,D5,$E$4,E5,$G$4,G5,$H$4,H5,$B$4,"INGRESO")+SUMIFS($I$4,$C$4,C5,$D$4,D5,$E$4,E5,$G$4,G5,$H$4,H5,$B$4,"DE CORTE")-SUMIFS($I$4,$C$4,C5,$D$4,D5,$E$4,E5,$G$4,G5,$H$4,H5,$B$4,"SALIDA"))),0) -> 0 | M5: =IF(C5="",0,L5+IF(OR(B5="INGRESO",B5="DE CORTE"),I5,IF(B5="SALIDA",-I5,0))) -> 0
J6: {=IFERROR(INDEX(PRECIOS_COMPLEMENTOS!$C$4:$F$17,MATCH(D6&"_"&E6,PRECIOS_COMPLEMENTOS!$H$4:$H$17,0),IF(OR(H6="S",H6="20cm"),1,IF(OR(H6="M",H6="25cm"),2,IF(OR(H6="L",H6="30cm"),3,IF(OR(H6="XL",H6="35cm"),4,0))))),0)} -> #REF! | K6: =IFERROR(I6*J6,0) -> 0 | L6: =IFERROR(IF(C6="",0,IF(D6="PRETINA",SUMIFS($I$4:$I$5,$C$4:$C$5,C6,$D$4:$D$5,D6,$E$4:$E$5,E6,$F$4:$F$5,F6,$G$4:$G$5,G6,$H$4:$H$5,H6,$B$4:$B$5,"INGRESO")+SUMIFS($I$4:$I$5,$C$4:$C$5,C6,$D$4:$D$5,D6,$E$4:$E$5,E6,$F$4:$F$5,F6,$G$4:$G$5,G6,$H$4:$H$5,H6,$B$4:$B$5,"DE CORTE")-SUMIFS($I$4:$I$5,$C$4:$C$5,C6,$D$4:$D$5,D6,$E$4:$E$5,E6,$F$4:$F$5,F6,$G$4:$G$5,G6,$H$4:$H$5,H6,$B$4:$B$5,"SALIDA"),SUMIFS($I$4:$I$5,$C$4:$C$5,C6,$D$4:$D$5,D6,$E$4:$E$5,E6,$G$4:$G$5,G6,$H$4:$H$5,H6,$B$4:$B$5,"INGRESO")+SUMIFS($I$4:$I$5,$C$4:$C$5,C6,$D$4:$D$5,D6,$E$4:$E$5,E6,$G$4:$G$5,G6,$H$4:$H$5,H6,$B$4:$B$5,"DE CORTE")-SUMIFS($I$4:$I$5,$C$4:$C$5,C6,$D$4:$D$5,D6,$E$4:$E$5,E6,$G$4:$G$5,G6,$H$4:$H$5,H6,$B$4:$B$5,"SALIDA"))),0) -> 0 | M6: =IF(C6="",0,L6+IF(OR(B6="INGRESO",B6="DE CORTE"),I6,IF(B6="SALIDA",-I6,0))) -> 0
J7: {=IFERROR(INDEX(PRECIOS_COMPLEMENTOS!$C$4:$F$17,MATCH(D7&"_"&E7,PRECIOS_COMPLEMENTOS!$H$4:$H$17,0),IF(OR(H7="S",H7="20cm"),1,IF(OR(H7="M",H7="25cm"),2,IF(OR(H7="L",H7="30cm"),3,IF(OR(H7="XL",H7="35cm"),4,0))))),0)} -> #REF! | K7: =IFERROR(I7*J7,0) -> 0 | L7: =IFERROR(IF(C7="",0,IF(D7="PRETINA",SUMIFS($I$4:$I$6,$C$4:$C$6,C7,$D$4:$D$6,D7,$E$4:$E$6,E7,$F$4:$F$6,F7,$G$4:$G$6,G7,$H$4:$H$6,H7,$B$4:$B$6,"INGRESO")+SUMIFS($I$4:$I$6,$C$4:$C$6,C7,$D$4:$D$6,D7,$E$4:$E$6,E7,$F$4:$F$6,F7,$G$4:$G$6,G7,$H$4:$H$6,H7,$B$4:$B$6,"DE CORTE")-SUMIFS($I$4:$I$6,$C$4:$C$6,C7,$D$4:$D$6,D7,$E$4:$E$6,E7,$F$4:$F$6,F7,$G$4:$G$6,G7,$H$4:$H$6,H7,$B$4:$B$6,"SALIDA"),SUMIFS($I$4:$I$6,$C$4:$C$6,C7,$D$4:$D$6,D7,$E$4:$E$6,E7,$G$4:$G$6,G7,$H$4:$H$6,H7,$B$4:$B$6,"INGRESO")+SUMIFS($I$4:$I$6,$C$4:$C$6,C7,$D$4:$D$6,D7,$E$4:$E$6,E7,$G$4:$G$6,G7,$H$4:$H$6,H7,$B$4:$B$6,"DE CORTE")-SUMIFS($I$4:$I$6,$C$4:$C$6,C7,$D$4:$D$6,D7,$E$4:$E$6,E7,$G$4:$G$6,G7,$H$4:$H$6,H7,$B$4:$B$6,"SALIDA"))),0) -> 0 | M7: =IF(C7="",0,L7+IF(OR(B7="INGRESO",B7="DE CORTE"),I7,IF(B7="SALIDA",-I7,0))) -> 0
J8: {=IFERROR(INDEX(PRECIOS_COMPLEMENTOS!$C$4:$F$17,MATCH(D8&"_"&E8,PRECIOS_COMPLEMENTOS!$H$4:$H$17,0),IF(OR(H8="S",H8="20cm"),1,IF(OR(H8="M",H8="25cm"),2,IF(OR(H8="L",H8="30cm"),3,IF(OR(H8="XL",H8="35cm"),4,0))))),0)} -> #REF! | K8: =IFERROR(I8*J8,0) -> 0 | L8: =IFERROR(IF(C8="",0,IF(D8="PRETINA",SUMIFS($I$4:$I$7,$C$4:$C$7,C8,$D$4:$D$7,D8,$E$4:$E$7,E8,$F$4:$F$7,F8,$G$4:$G$7,G8,$H$4:$H$7,H8,$B$4:$B$7,"INGRESO")+SUMIFS($I$4:$I$7,$C$4:$C$7,C8,$D$4:$D$7,D8,$E$4:$E$7,E8,$F$4:$F$7,F8,$G$4:$G$7,G8,$H$4:$H$7,H8,$B$4:$B$7,"DE CORTE")-SUMIFS($I$4:$I$7,$C$4:$C$7,C8,$D$4:$D$7,D8,$E$4:$E$7,E8,$F$4:$F$7,F8,$G$4:$G$7,G8,$H$4:$H$7,H8,$B$4:$B$7,"SALIDA"),SUMIFS($I$4:$I$7,$C$4:$C$7,C8,$D$4:$D$7,D8,$E$4:$E$7,E8,$G$4:$G$7,G8,$H$4:$H$7,H8,$B$4:$B$7,"INGRESO")+SUMIFS($I$4:$I$7,$C$4:$C$7,C8,$D$4:$D$7,D8,$E$4:$E$7,E8,$G$4:$G$7,G8,$H$4:$H$7,H8,$B$4:$B$7,"DE CORTE")-SUMIFS($I$4:$I$7,$C$4:$C$7,C8,$D$4:$D$7,D8,$E$4:$E$7,E8,$G$4:$G$7,G8,$H$4:$H$7,H8,$B$4:$B$7,"SALIDA"))),0) -> 0 | M8: =IF(C8="",0,L8+IF(OR(B8="INGRESO",B8="DE CORTE"),I8,IF(B8="SALIDA",-I8,0))) -> 0
J9: {=IFERROR(INDEX(PRECIOS_COMPLEMENTOS!$C$4:$F$17,MATCH(D9&"_"&E9,PRECIOS_COMPLEMENTOS!$H$4:$H$17,0),IF(OR(H9="S",H9="20cm"),1,IF(OR(H9="M",H9="25cm"),2,IF(OR(H9="L",H9="30cm"),3,IF(OR(H9="XL",H9="35cm"),4,0))))),0)} -> #REF! | K9: =IFERROR(I9*J9,0) -> 0 | L9: =IFERROR(IF(C9="",0,IF(D9="PRETINA",SUMIFS($I$4:$I$8,$C$4:$C$8,C9,$D$4:$D$8,D9,$E$4:$E$8,E9,$F$4:$F$8,F9,$G$4:$G$8,G9,$H$4:$H$8,H9,$B$4:$B$8,"INGRESO")+SUMIFS($I$4:$I$8,$C$4:$C$8,C9,$D$4:$D$8,D9,$E$4:$E$8,E9,$F$4:$F$8,F9,$G$4:$G$8,G9,$H$4:$H$8,H9,$B$4:$B$8,"DE CORTE")-SUMIFS($I$4:$I$8,$C$4:$C$8,C9,$D$4:$D$8,D9,$E$4:$E$8,E9,$F$4:$F$8,F9,$G$4:$G$8,G9,$H$4:$H$8,H9,$B$4:$B$8,"SALIDA"),SUMIFS($I$4:$I$8,$C$4:$C$8,C9,$D$4:$D$8,D9,$E$4:$E$8,E9,$G$4:$G$8,G9,$H$4:$H$8,H9,$B$4:$B$8,"INGRESO")+SUMIFS($I$4:$I$8,$C$4:$C$8,C9,$D$4:$D$8,D9,$E$4:$E$8,E9,$G$4:$G$8,G9,$H$4:$H$8,H9,$B$4:$B$8,"DE CORTE")-SUMIFS($I$4:$I$8,$C$4:$C$8,C9,$D$4:$D$8,D9,$E$4:$E$8,E9,$G$4:$G$8,G9,$H$4:$H$8,H9,$B$4:$B$8,"SALIDA"))),0) -> 0 | M9: =IF(C9="",0,L9+IF(OR(B9="INGRESO",B9="DE CORTE"),I9,IF(B9="SALIDA",-I9,0))) -> 0
J10: {=IFERROR(INDEX(PRECIOS_COMPLEMENTOS!$C$4:$F$17,MATCH(D10&"_"&E10,PRECIOS_COMPLEMENTOS!$H$4:$H$17,0),IF(OR(H10="S",H10="20cm"),1,IF(OR(H10="M",H10="25cm"),2,IF(OR(H10="L",H10="30cm"),3,IF(OR(H10="XL",H10="35cm"),4,0))))),0)} -> #REF! | K10: =IFERROR(I10*J10,0) -> 0 | L10: =IFERROR(IF(C10="",0,IF(D10="PRETINA",SUMIFS($I$4:$I$9,$C$4:$C$9,C10,$D$4:$D$9,D10,$E$4:$E$9,E10,$F$4:$F$9,F10,$G$4:$G$9,G10,$H$4:$H$9,H10,$B$4:$B$9,"INGRESO")+SUMIFS($I$4:$I$9,$C$4:$C$9,C10,$D$4:$D$9,D10,$E$4:$E$9,E10,$F$4:$F$9,F10,$G$4:$G$9,G10,$H$4:$H$9,H10,$B$4:$B$9,"DE CORTE")-SUMIFS($I$4:$I$9,$C$4:$C$9,C10,$D$4:$D$9,D10,$E$4:$E$9,E10,$F$4:$F$9,F10,$G$4:$G$9,G10,$H$4:$H$9,H10,$B$4:$B$9,"SALIDA"),SUMIFS($I$4:$I$9,$C$4:$C$9,C10,$D$4:$D$9,D10,$E$4:$E$9,E10,$G$4:$G$9,G10,$H$4:$H$9,H10,$B$4:$B$9,"INGRESO")+SUMIFS($I$4:$I$9,$C$4:$C$9,C10,$D$4:$D$9,D10,$E$4:$E$9,E10,$G$4:$G$9,G10,$H$4:$H$9,H10,$B$4:$B$9,"DE CORTE")-SUMIFS($I$4:$I$9,$C$4:$C$9,C10,$D$4:$D$9,D10,$E$4:$E$9,E10,$G$4:$G$9,G10,$H$4:$H$9,H10,$B$4:$B$9,"SALIDA"))),0) -> 0 | M10: =IF(C10="",0,L10+IF(OR(B10="INGRESO",B10="DE CORTE"),I10,IF(B10="SALIDA",-I10,0))) -> 0
J11: {=IFERROR(INDEX(PRECIOS_COMPLEMENTOS!$C$4:$F$17,MATCH(D11&"_"&E11,PRECIOS_COMPLEMENTOS!$H$4:$H$17,0),IF(OR(H11="S",H11="20cm"),1,IF(OR(H11="M",H11="25cm"),2,IF(OR(H11="L",H11="30cm"),3,IF(OR(H11="XL",H11="35cm"),4,0))))),0)} -> #REF! | K11: =IFERROR(I11*J11,0) -> 0 | L11: =IFERROR(IF(C11="",0,IF(D11="PRETINA",SUMIFS($I$4:$I$10,$C$4:$C$10,C11,$D$4:$D$10,D11,$E$4:$E$10,E11,$F$4:$F$10,F11,$G$4:$G$10,G11,$H$4:$H$10,H11,$B$4:$B$10,"INGRESO")+SUMIFS($I$4:$I$10,$C$4:$C$10,C11,$D$4:$D$10,D11,$E$4:$E$10,E11,$F$4:$F$10,F11,$G$4:$G$10,G11,$H$4:$H$10,H11,$B$4:$B$10,"DE CORTE")-SUMIFS($I$4:$I$10,$C$4:$C$10,C11,$D$4:$D$10,D11,$E$4:$E$10,E11,$F$4:$F$10,F11,$G$4:$G$10,G11,$H$4:$H$10,H11,$B$4:$B$10,"SALIDA"),SUMIFS($I$4:$I$10,$C$4:$C$10,C11,$D$4:$D$10,D11,$E$4:$E$10,E11,$G$4:$G$10,G11,$H$4:$H$10,H11,$B$4:$B$10,"INGRESO")+SUMIFS($I$4:$I$10,$C$4:$C$10,C11,$D$4:$D$10,D11,$E$4:$E$10,E11,$G$4:$G$10,G11,$H$4:$H$10,H11,$B$4:$B$10,"DE CORTE")-SUMIFS($I$4:$I$10,$C$4:$C$10,C11,$D$4:$D$10,D11,$E$4:$E$10,E11,$G$4:$G$10,G11,$H$4:$H$10,H11,$B$4:$B$10,"SALIDA"))),0) -> 0 | M11: =IF(C11="",0,L11+IF(OR(B11="INGRESO",B11="DE CORTE"),I11,IF(B11="SALIDA",-I11,0))) -> 0
J12: {=IFERROR(INDEX(PRECIOS_COMPLEMENTOS!$C$4:$F$17,MATCH(D12&"_"&E12,PRECIOS_COMPLEMENTOS!$H$4:$H$17,0),IF(OR(H12="S",H12="20cm"),1,IF(OR(H12="M",H12="25cm"),2,IF(OR(H12="L",H12="30cm"),3,IF(OR(H12="XL",H12="35cm"),4,0))))),0)} -> #REF! | K12: =IFERROR(I12*J12,0) -> 0 | L12: =IFERROR(IF(C12="",0,IF(D12="PRETINA",SUMIFS($I$4:$I$11,$C$4:$C$11,C12,$D$4:$D$11,D12,$E$4:$E$11,E12,$F$4:$F$11,F12,$G$4:$G$11,G12,$H$4:$H$11,H12,$B$4:$B$11,"INGRESO")+SUMIFS($I$4:$I$11,$C$4:$C$11,C12,$D$4:$D$11,D12,$E$4:$E$11,E12,$F$4:$F$11,F12,$G$4:$G$11,G12,$H$4:$H$11,H12,$B$4:$B$11,"DE CORTE")-SUMIFS($I$4:$I$11,$C$4:$C$11,C12,$D$4:$D$11,D12,$E$4:$E$11,E12,$F$4:$F$11,F12,$G$4:$G$11,G12,$H$4:$H$11,H12,$B$4:$B$11,"SALIDA"),SUMIFS($I$4:$I$11,$C$4:$C$11,C12,$D$4:$D$11,D12,$E$4:$E$11,E12,$G$4:$G$11,G12,$H$4:$H$11,H12,$B$4:$B$11,"INGRESO")+SUMIFS($I$4:$I$11,$C$4:$C$11,C12,$D$4:$D$11,D12,$E$4:$E$11,E12,$G$4:$G$11,G12,$H$4:$H$11,H12,$B$4:$B$11,"DE CORTE")-SUMIFS($I$4:$I$11,$C$4:$C$11,C12,$D$4:$D$11,D12,$E$4:$E$11,E12,$G$4:$G$11,G12,$H$4:$H$11,H12,$B$4:$B$11,"SALIDA"))),0) -> 0 | M12: =IF(C12="",0,L12+IF(OR(B12="INGRESO",B12="DE CORTE"),I12,IF(B12="SALIDA",-I12,0))) -> 0
J13: {=IFERROR(INDEX(PRECIOS_COMPLEMENTOS!$C$4:$F$17,MATCH(D13&"_"&E13,PRECIOS_COMPLEMENTOS!$H$4:$H$17,0),IF(OR(H13="S",H13="20cm"),1,IF(OR(H13="M",H13="25cm"),2,IF(OR(H13="L",H13="30cm"),3,IF(OR(H13="XL",H13="35cm"),4,0))))),0)} -> #REF! | K13: =IFERROR(I13*J13,0) -> 0 | L13: =IFERROR(IF(C13="",0,IF(D13="PRETINA",SUMIFS($I$4:$I$12,$C$4:$C$12,C13,$D$4:$D$12,D13,$E$4:$E$12,E13,$F$4:$F$12,F13,$G$4:$G$12,G13,$H$4:$H$12,H13,$B$4:$B$12,"INGRESO")+SUMIFS($I$4:$I$12,$C$4:$C$12,C13,$D$4:$D$12,D13,$E$4:$E$12,E13,$F$4:$F$12,F13,$G$4:$G$12,G13,$H$4:$H$12,H13,$B$4:$B$12,"DE CORTE")-SUMIFS($I$4:$I$12,$C$4:$C$12,C13,$D$4:$D$12,D13,$E$4:$E$12,E13,$F$4:$F$12,F13,$G$4:$G$12,G13,$H$4:$H$12,H13,$B$4:$B$12,"SALIDA"),SUMIFS($I$4:$I$12,$C$4:$C$12,C13,$D$4:$D$12,D13,$E$4:$E$12,E13,$G$4:$G$12,G13,$H$4:$H$12,H13,$B$4:$B$12,"INGRESO")+SUMIFS($I$4:$I$12,$C$4:$C$12,C13,$D$4:$D$12,D13,$E$4:$E$12,E13,$G$4:$G$12,G13,$H$4:$H$12,H13,$B$4:$B$12,"DE CORTE")-SUMIFS($I$4:$I$12,$C$4:$C$12,C13,$D$4:$D$12,D13,$E$4:$E$12,E13,$G$4:$G$12,G13,$H$4:$H$12,H13,$B$4:$B$12,"SALIDA"))),0) -> 0 | M13: =IF(C13="",0,L13+IF(OR(B13="INGRESO",B13="DE CORTE"),I13,IF(B13="SALIDA",-I13,0))) -> 0
J14: {=IFERROR(INDEX(PRECIOS_COMPLEMENTOS!$C$4:$F$17,MATCH(D14&"_"&E14,PRECIOS_COMPLEMENTOS!$H$4:$H$17,0),IF(OR(H14="S",H14="20cm"),1,IF(OR(H14="M",H14="25cm"),2,IF(OR(H14="L",H14="30cm"),3,IF(OR(H14="XL",H14="35cm"),4,0))))),0)} -> #REF! | K14: =IFERROR(I14*J14,0) -> 0 | L14: =IFERROR(IF(C14="",0,IF(D14="PRETINA",SUMIFS($I$4:$I$13,$C$4:$C$13,C14,$D$4:$D$13,D14,$E$4:$E$13,E14,$F$4:$F$13,F14,$G$4:$G$13,G14,$H$4:$H$13,H14,$B$4:$B$13,"INGRESO")+SUMIFS($I$4:$I$13,$C$4:$C$13,C14,$D$4:$D$13,D14,$E$4:$E$13,E14,$F$4:$F$13,F14,$G$4:$G$13,G14,$H$4:$H$13,H14,$B$4:$B$13,"DE CORTE")-SUMIFS($I$4:$I$13,$C$4:$C$13,C14,$D$4:$D$13,D14,$E$4:$E$13,E14,$F$4:$F$13,F14,$G$4:$G$13,G14,$H$4:$H$13,H14,$B$4:$B$13,"SALIDA"),SUMIFS($I$4:$I$13,$C$4:$C$13,C14,$D$4:$D$13,D14,$E$4:$E$13,E14,$G$4:$G$13,G14,$H$4:$H$13,H14,$B$4:$B$13,"INGRESO")+SUMIFS($I$4:$I$13,$C$4:$C$13,C14,$D$4:$D$13,D14,$E$4:$E$13,E14,$G$4:$G$13,G14,$H$4:$H$13,H14,$B$4:$B$13,"DE CORTE")-SUMIFS($I$4:$I$13,$C$4:$C$13,C14,$D$4:$D$13,D14,$E$4:$E$13,E14,$G$4:$G$13,G14,$H$4:$H$13,H14,$B$4:$B$13,"SALIDA"))),0) -> 0 | M14: =IF(C14="",0,L14+IF(OR(B14="INGRESO",B14="DE CORTE"),I14,IF(B14="SALIDA",-I14,0))) -> 0
J15: {=IFERROR(INDEX(PRECIOS_COMPLEMENTOS!$C$4:$F$17,MATCH(D15&"_"&E15,PRECIOS_COMPLEMENTOS!$H$4:$H$17,0),IF(OR(H15="S",H15="20cm"),1,IF(OR(H15="M",H15="25cm"),2,IF(OR(H15="L",H15="30cm"),3,IF(OR(H15="XL",H15="35cm"),4,0))))),0)} -> #REF! | K15: =IFERROR(I15*J15,0) -> 0 | L15: =IFERROR(IF(C15="",0,IF(D15="PRETINA",SUMIFS($I$4:$I$14,$C$4:$C$14,C15,$D$4:$D$14,D15,$E$4:$E$14,E15,$F$4:$F$14,F15,$G$4:$G$14,G15,$H$4:$H$14,H15,$B$4:$B$14,"INGRESO")+SUMIFS($I$4:$I$14,$C$4:$C$14,C15,$D$4:$D$14,D15,$E$4:$E$14,E15,$F$4:$F$14,F15,$G$4:$G$14,G15,$H$4:$H$14,H15,$B$4:$B$14,"DE CORTE")-SUMIFS($I$4:$I$14,$C$4:$C$14,C15,$D$4:$D$14,D15,$E$4:$E$14,E15,$F$4:$F$14,F15,$G$4:$G$14,G15,$H$4:$H$14,H15,$B$4:$B$14,"SALIDA"),SUMIFS($I$4:$I$14,$C$4:$C$14,C15,$D$4:$D$14,D15,$E$4:$E$14,E15,$G$4:$G$14,G15,$H$4:$H$14,H15,$B$4:$B$14,"INGRESO")+SUMIFS($I$4:$I$14,$C$4:$C$14,C15,$D$4:$D$14,D15,$E$4:$E$14,E15,$G$4:$G$14,G15,$H$4:$H$14,H15,$B$4:$B$14,"DE CORTE")-SUMIFS($I$4:$I$14,$C$4:$C$14,C15,$D$4:$D$14,D15,$E$4:$E$14,E15,$G$4:$G$14,G15,$H$4:$H$14,H15,$B$4:$B$14,"SALIDA"))),0) -> 0 | M15: =IF(C15="",0,L15+IF(OR(B15="INGRESO",B15="DE CORTE"),I15,IF(B15="SALIDA",-I15,0))) -> 0
J16: {=IFERROR(INDEX(PRECIOS_COMPLEMENTOS!$C$4:$F$17,MATCH(D16&"_"&E16,PRECIOS_COMPLEMENTOS!$H$4:$H$17,0),IF(OR(H16="S",H16="20cm"),1,IF(OR(H16="M",H16="25cm"),2,IF(OR(H16="L",H16="30cm"),3,IF(OR(H16="XL",H16="35cm"),4,0))))),0)} -> #REF! | K16: =IFERROR(I16*J16,0) -> 0 | L16: =IFERROR(IF(C16="",0,IF(D16="PRETINA",SUMIFS($I$4:$I$15,$C$4:$C$15,C16,$D$4:$D$15,D16,$E$4:$E$15,E16,$F$4:$F$15,F16,$G$4:$G$15,G16,$H$4:$H$15,H16,$B$4:$B$15,"INGRESO")+SUMIFS($I$4:$I$15,$C$4:$C$15,C16,$D$4:$D$15,D16,$E$4:$E$15,E16,$F$4:$F$15,F16,$G$4:$G$15,G16,$H$4:$H$15,H16,$B$4:$B$15,"DE CORTE")-SUMIFS($I$4:$I$15,$C$4:$C$15,C16,$D$4:$D$15,D16,$E$4:$E$15,E16,$F$4:$F$15,F16,$G$4:$G$15,G16,$H$4:$H$15,H16,$B$4:$B$15,"SALIDA"),SUMIFS($I$4:$I$15,$C$4:$C$15,C16,$D$4:$D$15,D16,$E$4:$E$15,E16,$G$4:$G$15,G16,$H$4:$H$15,H16,$B$4:$B$15,"INGRESO")+SUMIFS($I$4:$I$15,$C$4:$C$15,C16,$D$4:$D$15,D16,$E$4:$E$15,E16,$G$4:$G$15,G16,$H$4:$H$15,H16,$B$4:$B$15,"DE CORTE")-SUMIFS($I$4:$I$15,$C$4:$C$15,C16,$D$4:$D$15,D16,$E$4:$E$15,E16,$G$4:$G$15,G16,$H$4:$H$15,H16,$B$4:$B$15,"SALIDA"))),0) -> 0 | M16: =IF(C16="",0,L16+IF(OR(B16="INGRESO",B16="DE CORTE"),I16,IF(B16="SALIDA",-I16,0))) -> 0
J17: {=IFERROR(INDEX(PRECIOS_COMPLEMENTOS!$C$4:$F$17,MATCH(D17&"_"&E17,PRECIOS_COMPLEMENTOS!$H$4:$H$17,0),IF(OR(H17="S",H17="20cm"),1,IF(OR(H17="M",H17="25cm"),2,IF(OR(H17="L",H17="30cm"),3,IF(OR(H17="XL",H17="35cm"),4,0))))),0)} -> #REF! | K17: =IFERROR(I17*J17,0) -> 0 | L17: =IFERROR(IF(C17="",0,IF(D17="PRETINA",SUMIFS($I$4:$I$16,$C$4:$C$16,C17,$D$4:$D$16,D17,$E$4:$E$16,E17,$F$4:$F$16,F17,$G$4:$G$16,G17,$H$4:$H$16,H17,$B$4:$B$16,"INGRESO")+SUMIFS($I$4:$I$16,$C$4:$C$16,C17,$D$4:$D$16,D17,$E$4:$E$16,E17,$F$4:$F$16,F17,$G$4:$G$16,G17,$H$4:$H$16,H17,$B$4:$B$16,"DE CORTE")-SUMIFS($I$4:$I$16,$C$4:$C$16,C17,$D$4:$D$16,D17,$E$4:$E$16,E17,$F$4:$F$16,F17,$G$4:$G$16,G17,$H$4:$H$16,H17,$B$4:$B$16,"SALIDA"),SUMIFS($I$4:$I$16,$C$4:$C$16,C17,$D$4:$D$16,D17,$E$4:$E$16,E17,$G$4:$G$16,G17,$H$4:$H$16,H17,$B$4:$B$16,"INGRESO")+SUMIFS($I$4:$I$16,$C$4:$C$16,C17,$D$4:$D$16,D17,$E$4:$E$16,E17,$G$4:$G$16,G17,$H$4:$H$16,H17,$B$4:$B$16,"DE CORTE")-SUMIFS($I$4:$I$16,$C$4:$C$16,C17,$D$4:$D$16,D17,$E$4:$E$16,E17,$G$4:$G$16,G17,$H$4:$H$16,H17,$B$4:$B$16,"SALIDA"))),0) -> 0 | M17: =IF(C17="",0,L17+IF(OR(B17="INGRESO",B17="DE CORTE"),I17,IF(B17="SALIDA",-I17,0))) -> 0
J18: {=IFERROR(INDEX(PRECIOS_COMPLEMENTOS!$C$4:$F$17,MATCH(D18&"_"&E18,PRECIOS_COMPLEMENTOS!$H$4:$H$17,0),IF(OR(H18="S",H18="20cm"),1,IF(OR(H18="M",H18="25cm"),2,IF(OR(H18="L",H18="30cm"),3,IF(OR(H18="XL",H18="35cm"),4,0))))),0)} -> #REF! | K18: =IFERROR(I18*J18,0) -> 0 | L18: =IFERROR(IF(C18="",0,IF(D18="PRETINA",SUMIFS($I$4:$I$17,$C$4:$C$17,C18,$D$4:$D$17,D18,$E$4:$E$17,E18,$F$4:$F$17,F18,$G$4:$G$17,G18,$H$4:$H$17,H18,$B$4:$B$17,"INGRESO")+SUMIFS($I$4:$I$17,$C$4:$C$17,C18,$D$4:$D$17,D18,$E$4:$E$17,E18,$F$4:$F$17,F18,$G$4:$G$17,G18,$H$4:$H$17,H18,$B$4:$B$17,"DE CORTE")-SUMIFS($I$4:$I$17,$C$4:$C$17,C18,$D$4:$D$17,D18,$E$4:$E$17,E18,$F$4:$F$17,F18,$G$4:$G$17,G18,$H$4:$H$17,H18,$B$4:$B$17,"SALIDA"),SUMIFS($I$4:$I$17,$C$4:$C$17,C18,$D$4:$D$17,D18,$E$4:$E$17,E18,$G$4:$G$17,G18,$H$4:$H$17,H18,$B$4:$B$17,"INGRESO")+SUMIFS($I$4:$I$17,$C$4:$C$17,C18,$D$4:$D$17,D18,$E$4:$E$17,E18,$G$4:$G$17,G18,$H$4:$H$17,H18,$B$4:$B$17,"DE CORTE")-SUMIFS($I$4:$I$17,$C$4:$C$17,C18,$D$4:$D$17,D18,$E$4:$E$17,E18,$G$4:$G$17,G18,$H$4:$H$17,H18,$B$4:$B$17,"SALIDA"))),0) -> 0 | M18: =IF(C18="",0,L18+IF(OR(B18="INGRESO",B18="DE CORTE"),I18,IF(B18="SALIDA",-I18,0))) -> 0
J19: {=IFERROR(INDEX(PRECIOS_COMPLEMENTOS!$C$4:$F$17,MATCH(D19&"_"&E19,PRECIOS_COMPLEMENTOS!$H$4:$H$17,0),IF(OR(H19="S",H19="20cm"),1,IF(OR(H19="M",H19="25cm"),2,IF(OR(H19="L",H19="30cm"),3,IF(OR(H19="XL",H19="35cm"),4,0))))),0)} -> #REF! | K19: =IFERROR(I19*J19,0) -> 0 | L19: =IFERROR(IF(C19="",0,IF(D19="PRETINA",SUMIFS($I$4:$I$18,$C$4:$C$18,C19,$D$4:$D$18,D19,$E$4:$E$18,E19,$F$4:$F$18,F19,$G$4:$G$18,G19,$H$4:$H$18,H19,$B$4:$B$18,"INGRESO")+SUMIFS($I$4:$I$18,$C$4:$C$18,C19,$D$4:$D$18,D19,$E$4:$E$18,E19,$F$4:$F$18,F19,$G$4:$G$18,G19,$H$4:$H$18,H19,$B$4:$B$18,"DE CORTE")-SUMIFS($I$4:$I$18,$C$4:$C$18,C19,$D$4:$D$18,D19,$E$4:$E$18,E19,$F$4:$F$18,F19,$G$4:$G$18,G19,$H$4:$H$18,H19,$B$4:$B$18,"SALIDA"),SUMIFS($I$4:$I$18,$C$4:$C$18,C19,$D$4:$D$18,D19,$E$4:$E$18,E19,$G$4:$G$18,G19,$H$4:$H$18,H19,$B$4:$B$18,"INGRESO")+SUMIFS($I$4:$I$18,$C$4:$C$18,C19,$D$4:$D$18,D19,$E$4:$E$18,E19,$G$4:$G$18,G19,$H$4:$H$18,H19,$B$4:$B$18,"DE CORTE")-SUMIFS($I$4:$I$18,$C$4:$C$18,C19,$D$4:$D$18,D19,$E$4:$E$18,E19,$G$4:$G$18,G19,$H$4:$H$18,H19,$B$4:$B$18,"SALIDA"))),0) -> 0 | M19: =IF(C19="",0,L19+IF(OR(B19="INGRESO",B19="DE CORTE"),I19,IF(B19="SALIDA",-I19,0))) -> 0
J20: {=IFERROR(INDEX(PRECIOS_COMPLEMENTOS!$C$4:$F$17,MATCH(D20&"_"&E20,PRECIOS_COMPLEMENTOS!$H$4:$H$17,0),IF(OR(H20="S",H20="20cm"),1,IF(OR(H20="M",H20="25cm"),2,IF(OR(H20="L",H20="30cm"),3,IF(OR(H20="XL",H20="35cm"),4,0))))),0)} -> #REF! | K20: =IFERROR(I20*J20,0) -> 0 | L20: =IFERROR(IF(C20="",0,IF(D20="PRETINA",SUMIFS($I$4:$I$19,$C$4:$C$19,C20,$D$4:$D$19,D20,$E$4:$E$19,E20,$F$4:$F$19,F20,$G$4:$G$19,G20,$H$4:$H$19,H20,$B$4:$B$19,"INGRESO")+SUMIFS($I$4:$I$19,$C$4:$C$19,C20,$D$4:$D$19,D20,$E$4:$E$19,E20,$F$4:$F$19,F20,$G$4:$G$19,G20,$H$4:$H$19,H20,$B$4:$B$19,"DE CORTE")-SUMIFS($I$4:$I$19,$C$4:$C$19,C20,$D$4:$D$19,D20,$E$4:$E$19,E20,$F$4:$F$19,F20,$G$4:$G$19,G20,$H$4:$H$19,H20,$B$4:$B$19,"SALIDA"),SUMIFS($I$4:$I$19,$C$4:$C$19,C20,$D$4:$D$19,D20,$E$4:$E$19,E20,$G$4:$G$19,G20,$H$4:$H$19,H20,$B$4:$B$19,"INGRESO")+SUMIFS($I$4:$I$19,$C$4:$C$19,C20,$D$4:$D$19,D20,$E$4:$E$19,E20,$G$4:$G$19,G20,$H$4:$H$19,H20,$B$4:$B$19,"DE CORTE")-SUMIFS($I$4:$I$19,$C$4:$C$19,C20,$D$4:$D$19,D20,$E$4:$E$19,E20,$G$4:$G$19,G20,$H$4:$H$19,H20,$B$4:$B$19,"SALIDA"))),0) -> 0 | M20: =IF(C20="",0,L20+IF(OR(B20="INGRESO",B20="DE CORTE"),I20,IF(B20="SALIDA",-I20,0))) -> 0
J21: {=IFERROR(INDEX(PRECIOS_COMPLEMENTOS!$C$4:$F$17,MATCH(D21&"_"&E21,PRECIOS_COMPLEMENTOS!$H$4:$H$17,0),IF(OR(H21="S",H21="20cm"),1,IF(OR(H21="M",H21="25cm"),2,IF(OR(H21="L",H21="30cm"),3,IF(OR(H21="XL",H21="35cm"),4,0))))),0)} -> #REF! | K21: =IFERROR(I21*J21,0) -> 0 | L21: =IFERROR(IF(C21="",0,IF(D21="PRETINA",SUMIFS($I$4:$I$20,$C$4:$C$20,C21,$D$4:$D$20,D21,$E$4:$E$20,E21,$F$4:$F$20,F21,$G$4:$G$20,G21,$H$4:$H$20,H21,$B$4:$B$20,"INGRESO")+SUMIFS($I$4:$I$20,$C$4:$C$20,C21,$D$4:$D$20,D21,$E$4:$E$20,E21,$F$4:$F$20,F21,$G$4:$G$20,G21,$H$4:$H$20,H21,$B$4:$B$20,"DE CORTE")-SUMIFS($I$4:$I$20,$C$4:$C$20,C21,$D$4:$D$20,D21,$E$4:$E$20,E21,$F$4:$F$20,F21,$G$4:$G$20,G21,$H$4:$H$20,H21,$B$4:$B$20,"SALIDA"),SUMIFS($I$4:$I$20,$C$4:$C$20,C21,$D$4:$D$20,D21,$E$4:$E$20,E21,$G$4:$G$20,G21,$H$4:$H$20,H21,$B$4:$B$20,"INGRESO")+SUMIFS($I$4:$I$20,$C$4:$C$20,C21,$D$4:$D$20,D21,$E$4:$E$20,E21,$G$4:$G$20,G21,$H$4:$H$20,H21,$B$4:$B$20,"DE CORTE")-SUMIFS($I$4:$I$20,$C$4:$C$20,C21,$D$4:$D$20,D21,$E$4:$E$20,E21,$G$4:$G$20,G21,$H$4:$H$20,H21,$B$4:$B$20,"SALIDA"))),0) -> 0 | M21: =IF(C21="",0,L21+IF(OR(B21="INGRESO",B21="DE CORTE"),I21,IF(B21="SALIDA",-I21,0))) -> 0
J22: {=IFERROR(INDEX(PRECIOS_COMPLEMENTOS!$C$4:$F$17,MATCH(D22&"_"&E22,PRECIOS_COMPLEMENTOS!$H$4:$H$17,0),IF(OR(H22="S",H22="20cm"),1,IF(OR(H22="M",H22="25cm"),2,IF(OR(H22="L",H22="30cm"),3,IF(OR(H22="XL",H22="35cm"),4,0))))),0)} -> #REF! | K22: =IFERROR(I22*J22,0) -> 0 | L22: =IFERROR(IF(C22="",0,IF(D22="PRETINA",SUMIFS($I$4:$I$21,$C$4:$C$21,C22,$D$4:$D$21,D22,$E$4:$E$21,E22,$F$4:$F$21,F22,$G$4:$G$21,G22,$H$4:$H$21,H22,$B$4:$B$21,"INGRESO")+SUMIFS($I$4:$I$21,$C$4:$C$21,C22,$D$4:$D$21,D22,$E$4:$E$21,E22,$F$4:$F$21,F22,$G$4:$G$21,G22,$H$4:$H$21,H22,$B$4:$B$21,"DE CORTE")-SUMIFS($I$4:$I$21,$C$4:$C$21,C22,$D$4:$D$21,D22,$E$4:$E$21,E22,$F$4:$F$21,F22,$G$4:$G$21,G22,$H$4:$H$21,H22,$B$4:$B$21,"SALIDA"),SUMIFS($I$4:$I$21,$C$4:$C$21,C22,$D$4:$D$21,D22,$E$4:$E$21,E22,$G$4:$G$21,G22,$H$4:$H$21,H22,$B$4:$B$21,"INGRESO")+SUMIFS($I$4:$I$21,$C$4:$C$21,C22,$D$4:$D$21,D22,$E$4:$E$21,E22,$G$4:$G$21,G22,$H$4:$H$21,H22,$B$4:$B$21,"DE CORTE")-SUMIFS($I$4:$I$21,$C$4:$C$21,C22,$D$4:$D$21,D22,$E$4:$E$21,E22,$G$4:$G$21,G22,$H$4:$H$21,H22,$B$4:$B$21,"SALIDA"))),0) -> 0 | M22: =IF(C22="",0,L22+IF(OR(B22="INGRESO",B22="DE CORTE"),I22,IF(B22="SALIDA",-I22,0))) -> 0
J23: {=IFERROR(INDEX(PRECIOS_COMPLEMENTOS!$C$4:$F$17,MATCH(D23&"_"&E23,PRECIOS_COMPLEMENTOS!$H$4:$H$17,0),IF(OR(H23="S",H23="20cm"),1,IF(OR(H23="M",H23="25cm"),2,IF(OR(H23="L",H23="30cm"),3,IF(OR(H23="XL",H23="35cm"),4,0))))),0)} -> #REF! | K23: =IFERROR(I23*J23,0) -> 0 | L23: =IFERROR(IF(C23="",0,IF(D23="PRETINA",SUMIFS($I$4:$I$22,$C$4:$C$22,C23,$D$4:$D$22,D23,$E$4:$E$22,E23,$F$4:$F$22,F23,$G$4:$G$22,G23,$H$4:$H$22,H23,$B$4:$B$22,"INGRESO")+SUMIFS($I$4:$I$22,$C$4:$C$22,C23,$D$4:$D$22,D23,$E$4:$E$22,E23,$F$4:$F$22,F23,$G$4:$G$22,G23,$H$4:$H$22,H23,$B$4:$B$22,"DE CORTE")-SUMIFS($I$4:$I$22,$C$4:$C$22,C23,$D$4:$D$22,D23,$E$4:$E$22,E23,$F$4:$F$22,F23,$G$4:$G$22,G23,$H$4:$H$22,H23,$B$4:$B$22,"SALIDA"),SUMIFS($I$4:$I$22,$C$4:$C$22,C23,$D$4:$D$22,D23,$E$4:$E$22,E23,$G$4:$G$22,G23,$H$4:$H$22,H23,$B$4:$B$22,"INGRESO")+SUMIFS($I$4:$I$22,$C$4:$C$22,C23,$D$4:$D$22,D23,$E$4:$E$22,E23,$G$4:$G$22,G23,$H$4:$H$22,H23,$B$4:$B$22,"DE CORTE")-SUMIFS($I$4:$I$22,$C$4:$C$22,C23,$D$4:$D$22,D23,$E$4:$E$22,E23,$G$4:$G$22,G23,$H$4:$H$22,H23,$B$4:$B$22,"SALIDA"))),0) -> 0 | M23: =IF(C23="",0,L23+IF(OR(B23="INGRESO",B23="DE CORTE"),I23,IF(B23="SALIDA",-I23,0))) -> 0
J24: {=IFERROR(INDEX(PRECIOS_COMPLEMENTOS!$C$4:$F$17,MATCH(D24&"_"&E24,PRECIOS_COMPLEMENTOS!$H$4:$H$17,0),IF(OR(H24="S",H24="20cm"),1,IF(OR(H24="M",H24="25cm"),2,IF(OR(H24="L",H24="30cm"),3,IF(OR(H24="XL",H24="35cm"),4,0))))),0)} -> #REF! | K24: =IFERROR(I24*J24,0) -> 0 | L24: =IFERROR(IF(C24="",0,IF(D24="PRETINA",SUMIFS($I$4:$I$23,$C$4:$C$23,C24,$D$4:$D$23,D24,$E$4:$E$23,E24,$F$4:$F$23,F24,$G$4:$G$23,G24,$H$4:$H$23,H24,$B$4:$B$23,"INGRESO")+SUMIFS($I$4:$I$23,$C$4:$C$23,C24,$D$4:$D$23,D24,$E$4:$E$23,E24,$F$4:$F$23,F24,$G$4:$G$23,G24,$H$4:$H$23,H24,$B$4:$B$23,"DE CORTE")-SUMIFS($I$4:$I$23,$C$4:$C$23,C24,$D$4:$D$23,D24,$E$4:$E$23,E24,$F$4:$F$23,F24,$G$4:$G$23,G24,$H$4:$H$23,H24,$B$4:$B$23,"SALIDA"),SUMIFS($I$4:$I$23,$C$4:$C$23,C24,$D$4:$D$23,D24,$E$4:$E$23,E24,$G$4:$G$23,G24,$H$4:$H$23,H24,$B$4:$B$23,"INGRESO")+SUMIFS($I$4:$I$23,$C$4:$C$23,C24,$D$4:$D$23,D24,$E$4:$E$23,E24,$G$4:$G$23,G24,$H$4:$H$23,H24,$B$4:$B$23,"DE CORTE")-SUMIFS($I$4:$I$23,$C$4:$C$23,C24,$D$4:$D$23,D24,$E$4:$E$23,E24,$G$4:$G$23,G24,$H$4:$H$23,H24,$B$4:$B$23,"SALIDA"))),0) -> 0 | M24: =IF(C24="",0,L24+IF(OR(B24="INGRESO",B24="DE CORTE"),I24,IF(B24="SALIDA",-I24,0))) -> 0
J25: {=IFERROR(INDEX(PRECIOS_COMPLEMENTOS!$C$4:$F$17,MATCH(D25&"_"&E25,PRECIOS_COMPLEMENTOS!$H$4:$H$17,0),IF(OR(H25="S",H25="20cm"),1,IF(OR(H25="M",H25="25cm"),2,IF(OR(H25="L",H25="30cm"),3,IF(OR(H25="XL",H25="35cm"),4,0))))),0)} -> #REF! | K25: =IFERROR(I25*J25,0) -> 0 | L25: =IFERROR(IF(C25="",0,IF(D25="PRETINA",SUMIFS($I$4:$I$24,$C$4:$C$24,C25,$D$4:$D$24,D25,$E$4:$E$24,E25,$F$4:$F$24,F25,$G$4:$G$24,G25,$H$4:$H$24,H25,$B$4:$B$24,"INGRESO")+SUMIFS($I$4:$I$24,$C$4:$C$24,C25,$D$4:$D$24,D25,$E$4:$E$24,E25,$F$4:$F$24,F25,$G$4:$G$24,G25,$H$4:$H$24,H25,$B$4:$B$24,"DE CORTE")-SUMIFS($I$4:$I$24,$C$4:$C$24,C25,$D$4:$D$24,D25,$E$4:$E$24,E25,$F$4:$F$24,F25,$G$4:$G$24,G25,$H$4:$H$24,H25,$B$4:$B$24,"SALIDA"),SUMIFS($I$4:$I$24,$C$4:$C$24,C25,$D$4:$D$24,D25,$E$4:$E$24,E25,$G$4:$G$24,G25,$H$4:$H$24,H25,$B$4:$B$24,"INGRESO")+SUMIFS($I$4:$I$24,$C$4:$C$24,C25,$D$4:$D$24,D25,$E$4:$E$24,E25,$G$4:$G$24,G25,$H$4:$H$24,H25,$B$4:$B$24,"DE CORTE")-SUMIFS($I$4:$I$24,$C$4:$C$24,C25,$D$4:$D$24,D25,$E$4:$E$24,E25,$G$4:$G$24,G25,$H$4:$H$24,H25,$B$4:$B$24,"SALIDA"))),0) -> 0 | M25: =IF(C25="",0,L25+IF(OR(B25="INGRESO",B25="DE CORTE"),I25,IF(B25="SALIDA",-I25,0))) -> 0
J26: {=IFERROR(INDEX(PRECIOS_COMPLEMENTOS!$C$4:$F$17,MATCH(D26&"_"&E26,PRECIOS_COMPLEMENTOS!$H$4:$H$17,0),IF(OR(H26="S",H26="20cm"),1,IF(OR(H26="M",H26="25cm"),2,IF(OR(H26="L",H26="30cm"),3,IF(OR(H26="XL",H26="35cm"),4,0))))),0)} -> #REF! | K26: =IFERROR(I26*J26,0) -> 0 | L26: =IFERROR(IF(C26="",0,IF(D26="PRETINA",SUMIFS($I$4:$I$25,$C$4:$C$25,C26,$D$4:$D$25,D26,$E$4:$E$25,E26,$F$4:$F$25,F26,$G$4:$G$25,G26,$H$4:$H$25,H26,$B$4:$B$25,"INGRESO")+SUMIFS($I$4:$I$25,$C$4:$C$25,C26,$D$4:$D$25,D26,$E$4:$E$25,E26,$F$4:$F$25,F26,$G$4:$G$25,G26,$H$4:$H$25,H26,$B$4:$B$25,"DE CORTE")-SUMIFS($I$4:$I$25,$C$4:$C$25,C26,$D$4:$D$25,D26,$E$4:$E$25,E26,$F$4:$F$25,F26,$G$4:$G$25,G26,$H$4:$H$25,H26,$B$4:$B$25,"SALIDA"),SUMIFS($I$4:$I$25,$C$4:$C$25,C26,$D$4:$D$25,D26,$E$4:$E$25,E26,$G$4:$G$25,G26,$H$4:$H$25,H26,$B$4:$B$25,"INGRESO")+SUMIFS($I$4:$I$25,$C$4:$C$25,C26,$D$4:$D$25,D26,$E$4:$E$25,E26,$G$4:$G$25,G26,$H$4:$H$25,H26,$B$4:$B$25,"DE CORTE")-SUMIFS($I$4:$I$25,$C$4:$C$25,C26,$D$4:$D$25,D26,$E$4:$E$25,E26,$G$4:$G$25,G26,$H$4:$H$25,H26,$B$4:$B$25,"SALIDA"))),0) -> 0 | M26: =IF(C26="",0,L26+IF(OR(B26="INGRESO",B26="DE CORTE"),I26,IF(B26="SALIDA",-I26,0))) -> 0
J27: {=IFERROR(INDEX(PRECIOS_COMPLEMENTOS!$C$4:$F$17,MATCH(D27&"_"&E27,PRECIOS_COMPLEMENTOS!$H$4:$H$17,0),IF(OR(H27="S",H27="20cm"),1,IF(OR(H27="M",H27="25cm"),2,IF(OR(H27="L",H27="30cm"),3,IF(OR(H27="XL",H27="35cm"),4,0))))),0)} -> #REF! | K27: =IFERROR(I27*J27,0) -> 0 | L27: =IFERROR(IF(C27="",0,IF(D27="PRETINA",SUMIFS($I$4:$I$26,$C$4:$C$26,C27,$D$4:$D$26,D27,$E$4:$E$26,E27,$F$4:$F$26,F27,$G$4:$G$26,G27,$H$4:$H$26,H27,$B$4:$B$26,"INGRESO")+SUMIFS($I$4:$I$26,$C$4:$C$26,C27,$D$4:$D$26,D27,$E$4:$E$26,E27,$F$4:$F$26,F27,$G$4:$G$26,G27,$H$4:$H$26,H27,$B$4:$B$26,"DE CORTE")-SUMIFS($I$4:$I$26,$C$4:$C$26,C27,$D$4:$D$26,D27,$E$4:$E$26,E27,$F$4:$F$26,F27,$G$4:$G$26,G27,$H$4:$H$26,H27,$B$4:$B$26,"SALIDA"),SUMIFS($I$4:$I$26,$C$4:$C$26,C27,$D$4:$D$26,D27,$E$4:$E$26,E27,$G$4:$G$26,G27,$H$4:$H$26,H27,$B$4:$B$26,"INGRESO")+SUMIFS($I$4:$I$26,$C$4:$C$26,C27,$D$4:$D$26,D27,$E$4:$E$26,E27,$G$4:$G$26,G27,$H$4:$H$26,H27,$B$4:$B$26,"DE CORTE")-SUMIFS($I$4:$I$26,$C$4:$C$26,C27,$D$4:$D$26,D27,$E$4:$E$26,E27,$G$4:$G$26,G27,$H$4:$H$26,H27,$B$4:$B$26,"SALIDA"))),0) -> 0 | M27: =IF(C27="",0,L27+IF(OR(B27="INGRESO",B27="DE CORTE"),I27,IF(B27="SALIDA",-I27,0))) -> 0
J28: {=IFERROR(INDEX(PRECIOS_COMPLEMENTOS!$C$4:$F$17,MATCH(D28&"_"&E28,PRECIOS_COMPLEMENTOS!$H$4:$H$17,0),IF(OR(H28="S",H28="20cm"),1,IF(OR(H28="M",H28="25cm"),2,IF(OR(H28="L",H28="30cm"),3,IF(OR(H28="XL",H28="35cm"),4,0))))),0)} -> #REF! | K28: =IFERROR(I28*J28,0) -> 0 | L28: =IFERROR(IF(C28="",0,IF(D28="PRETINA",SUMIFS($I$4:$I$27,$C$4:$C$27,C28,$D$4:$D$27,D28,$E$4:$E$27,E28,$F$4:$F$27,F28,$G$4:$G$27,G28,$H$4:$H$27,H28,$B$4:$B$27,"INGRESO")+SUMIFS($I$4:$I$27,$C$4:$C$27,C28,$D$4:$D$27,D28,$E$4:$E$27,E28,$F$4:$F$27,F28,$G$4:$G$27,G28,$H$4:$H$27,H28,$B$4:$B$27,"DE CORTE")-SUMIFS($I$4:$I$27,$C$4:$C$27,C28,$D$4:$D$27,D28,$E$4:$E$27,E28,$F$4:$F$27,F28,$G$4:$G$27,G28,$H$4:$H$27,H28,$B$4:$B$27,"SALIDA"),SUMIFS($I$4:$I$27,$C$4:$C$27,C28,$D$4:$D$27,D28,$E$4:$E$27,E28,$G$4:$G$27,G28,$H$4:$H$27,H28,$B$4:$B$27,"INGRESO")+SUMIFS($I$4:$I$27,$C$4:$C$27,C28,$D$4:$D$27,D28,$E$4:$E$27,E28,$G$4:$G$27,G28,$H$4:$H$27,H28,$B$4:$B$27,"DE CORTE")-SUMIFS($I$4:$I$27,$C$4:$C$27,C28,$D$4:$D$27,D28,$E$4:$E$27,E28,$G$4:$G$27,G28,$H$4:$H$27,H28,$B$4:$B$27,"SALIDA"))),0) -> 0 | M28: =IF(C28="",0,L28+IF(OR(B28="INGRESO",B28="DE CORTE"),I28,IF(B28="SALIDA",-I28,0))) -> 0
J29: {=IFERROR(INDEX(PRECIOS_COMPLEMENTOS!$C$4:$F$17,MATCH(D29&"_"&E29,PRECIOS_COMPLEMENTOS!$H$4:$H$17,0),IF(OR(H29="S",H29="20cm"),1,IF(OR(H29="M",H29="25cm"),2,IF(OR(H29="L",H29="30cm"),3,IF(OR(H29="XL",H29="35cm"),4,0))))),0)} -> #REF! | K29: =IFERROR(I29*J29,0) -> 0 | L29: =IFERROR(IF(C29="",0,IF(D29="PRETINA",SUMIFS($I$4:$I$28,$C$4:$C$28,C29,$D$4:$D$28,D29,$E$4:$E$28,E29,$F$4:$F$28,F29,$G$4:$G$28,G29,$H$4:$H$28,H29,$B$4:$B$28,"INGRESO")+SUMIFS($I$4:$I$28,$C$4:$C$28,C29,$D$4:$D$28,D29,$E$4:$E$28,E29,$F$4:$F$28,F29,$G$4:$G$28,G29,$H$4:$H$28,H29,$B$4:$B$28,"DE CORTE")-SUMIFS($I$4:$I$28,$C$4:$C$28,C29,$D$4:$D$28,D29,$E$4:$E$28,E29,$F$4:$F$28,F29,$G$4:$G$28,G29,$H$4:$H$28,H29,$B$4:$B$28,"SALIDA"),SUMIFS($I$4:$I$28,$C$4:$C$28,C29,$D$4:$D$28,D29,$E$4:$E$28,E29,$G$4:$G$28,G29,$H$4:$H$28,H29,$B$4:$B$28,"INGRESO")+SUMIFS($I$4:$I$28,$C$4:$C$28,C29,$D$4:$D$28,D29,$E$4:$E$28,E29,$G$4:$G$28,G29,$H$4:$H$28,H29,$B$4:$B$28,"DE CORTE")-SUMIFS($I$4:$I$28,$C$4:$C$28,C29,$D$4:$D$28,D29,$E$4:$E$28,E29,$G$4:$G$28,G29,$H$4:$H$28,H29,$B$4:$B$28,"SALIDA"))),0) -> 0 | M29: =IF(C29="",0,L29+IF(OR(B29="INGRESO",B29="DE CORTE"),I29,IF(B29="SALIDA",-I29,0))) -> 0
J30: {=IFERROR(INDEX(PRECIOS_COMPLEMENTOS!$C$4:$F$17,MATCH(D30&"_"&E30,PRECIOS_COMPLEMENTOS!$H$4:$H$17,0),IF(OR(H30="S",H30="20cm"),1,IF(OR(H30="M",H30="25cm"),2,IF(OR(H30="L",H30="30cm"),3,IF(OR(H30="XL",H30="35cm"),4,0))))),0)} -> #REF! | K30: =IFERROR(I30*J30,0) -> 0 | L30: =IFERROR(IF(C30="",0,IF(D30="PRETINA",SUMIFS($I$4:$I$29,$C$4:$C$29,C30,$D$4:$D$29,D30,$E$4:$E$29,E30,$F$4:$F$29,F30,$G$4:$G$29,G30,$H$4:$H$29,H30,$B$4:$B$29,"INGRESO")+SUMIFS($I$4:$I$29,$C$4:$C$29,C30,$D$4:$D$29,D30,$E$4:$E$29,E30,$F$4:$F$29,F30,$G$4:$G$29,G30,$H$4:$H$29,H30,$B$4:$B$29,"DE CORTE")-SUMIFS($I$4:$I$29,$C$4:$C$29,C30,$D$4:$D$29,D30,$E$4:$E$29,E30,$F$4:$F$29,F30,$G$4:$G$29,G30,$H$4:$H$29,H30,$B$4:$B$29,"SALIDA"),SUMIFS($I$4:$I$29,$C$4:$C$29,C30,$D$4:$D$29,D30,$E$4:$E$29,E30,$G$4:$G$29,G30,$H$4:$H$29,H30,$B$4:$B$29,"INGRESO")+SUMIFS($I$4:$I$29,$C$4:$C$29,C30,$D$4:$D$29,D30,$E$4:$E$29,E30,$G$4:$G$29,G30,$H$4:$H$29,H30,$B$4:$B$29,"DE CORTE")-SUMIFS($I$4:$I$29,$C$4:$C$29,C30,$D$4:$D$29,D30,$E$4:$E$29,E30,$G$4:$G$29,G30,$H$4:$H$29,H30,$B$4:$B$29,"SALIDA"))),0) -> 0 | M30: =IF(C30="",0,L30+IF(OR(B30="INGRESO",B30="DE CORTE"),I30,IF(B30="SALIDA",-I30,0))) -> 0
J31: {=IFERROR(INDEX(PRECIOS_COMPLEMENTOS!$C$4:$F$17,MATCH(D31&"_"&E31,PRECIOS_COMPLEMENTOS!$H$4:$H$17,0),IF(OR(H31="S",H31="20cm"),1,IF(OR(H31="M",H31="25cm"),2,IF(OR(H31="L",H31="30cm"),3,IF(OR(H31="XL",H31="35cm"),4,0))))),0)} -> #REF! | K31: =IFERROR(I31*J31,0) -> 0 | L31: =IFERROR(IF(C31="",0,IF(D31="PRETINA",SUMIFS($I$4:$I$30,$C$4:$C$30,C31,$D$4:$D$30,D31,$E$4:$E$30,E31,$F$4:$F$30,F31,$G$4:$G$30,G31,$H$4:$H$30,H31,$B$4:$B$30,"INGRESO")+SUMIFS($I$4:$I$30,$C$4:$C$30,C31,$D$4:$D$30,D31,$E$4:$E$30,E31,$F$4:$F$30,F31,$G$4:$G$30,G31,$H$4:$H$30,H31,$B$4:$B$30,"DE CORTE")-SUMIFS($I$4:$I$30,$C$4:$C$30,C31,$D$4:$D$30,D31,$E$4:$E$30,E31,$F$4:$F$30,F31,$G$4:$G$30,G31,$H$4:$H$30,H31,$B$4:$B$30,"SALIDA"),SUMIFS($I$4:$I$30,$C$4:$C$30,C31,$D$4:$D$30,D31,$E$4:$E$30,E31,$G$4:$G$30,G31,$H$4:$H$30,H31,$B$4:$B$30,"INGRESO")+SUMIFS($I$4:$I$30,$C$4:$C$30,C31,$D$4:$D$30,D31,$E$4:$E$30,E31,$G$4:$G$30,G31,$H$4:$H$30,H31,$B$4:$B$30,"DE CORTE")-SUMIFS($I$4:$I$30,$C$4:$C$30,C31,$D$4:$D$30,D31,$E$4:$E$30,E31,$G$4:$G$30,G31,$H$4:$H$30,H31,$B$4:$B$30,"SALIDA"))),0) -> 0 | M31: =IF(C31="",0,L31+IF(OR(B31="INGRESO",B31="DE CORTE"),I31,IF(B31="SALIDA",-I31,0))) -> 0
J32: {=IFERROR(INDEX(PRECIOS_COMPLEMENTOS!$C$4:$F$17,MATCH(D32&"_"&E32,PRECIOS_COMPLEMENTOS!$H$4:$H$17,0),IF(OR(H32="S",H32="20cm"),1,IF(OR(H32="M",H32="25cm"),2,IF(OR(H32="L",H32="30cm"),3,IF(OR(H32="XL",H32="35cm"),4,0))))),0)} -> #REF! | K32: =IFERROR(I32*J32,0) -> 0 | L32: =IFERROR(IF(C32="",0,IF(D32="PRETINA",SUMIFS($I$4:$I$31,$C$4:$C$31,C32,$D$4:$D$31,D32,$E$4:$E$31,E32,$F$4:$F$31,F32,$G$4:$G$31,G32,$H$4:$H$31,H32,$B$4:$B$31,"INGRESO")+SUMIFS($I$4:$I$31,$C$4:$C$31,C32,$D$4:$D$31,D32,$E$4:$E$31,E32,$F$4:$F$31,F32,$G$4:$G$31,G32,$H$4:$H$31,H32,$B$4:$B$31,"DE CORTE")-SUMIFS($I$4:$I$31,$C$4:$C$31,C32,$D$4:$D$31,D32,$E$4:$E$31,E32,$F$4:$F$31,F32,$G$4:$G$31,G32,$H$4:$H$31,H32,$B$4:$B$31,"SALIDA"),SUMIFS($I$4:$I$31,$C$4:$C$31,C32,$D$4:$D$31,D32,$E$4:$E$31,E32,$G$4:$G$31,G32,$H$4:$H$31,H32,$B$4:$B$31,"INGRESO")+SUMIFS($I$4:$I$31,$C$4:$C$31,C32,$D$4:$D$31,D32,$E$4:$E$31,E32,$G$4:$G$31,G32,$H$4:$H$31,H32,$B$4:$B$31,"DE CORTE")-SUMIFS($I$4:$I$31,$C$4:$C$31,C32,$D$4:$D$31,D32,$E$4:$E$31,E32,$G$4:$G$31,G32,$H$4:$H$31,H32,$B$4:$B$31,"SALIDA"))),0) -> 0 | M32: =IF(C32="",0,L32+IF(OR(B32="INGRESO",B32="DE CORTE"),I32,IF(B32="SALIDA",-I32,0))) -> 0
J33: {=IFERROR(INDEX(PRECIOS_COMPLEMENTOS!$C$4:$F$17,MATCH(D33&"_"&E33,PRECIOS_COMPLEMENTOS!$H$4:$H$17,0),IF(OR(H33="S",H33="20cm"),1,IF(OR(H33="M",H33="25cm"),2,IF(OR(H33="L",H33="30cm"),3,IF(OR(H33="XL",H33="35cm"),4,0))))),0)} -> #REF! | K33: =IFERROR(I33*J33,0) -> 0 | L33: =IFERROR(IF(C33="",0,IF(D33="PRETINA",SUMIFS($I$4:$I$32,$C$4:$C$32,C33,$D$4:$D$32,D33,$E$4:$E$32,E33,$F$4:$F$32,F33,$G$4:$G$32,G33,$H$4:$H$32,H33,$B$4:$B$32,"INGRESO")+SUMIFS($I$4:$I$32,$C$4:$C$32,C33,$D$4:$D$32,D33,$E$4:$E$32,E33,$F$4:$F$32,F33,$G$4:$G$32,G33,$H$4:$H$32,H33,$B$4:$B$32,"DE CORTE")-SUMIFS($I$4:$I$32,$C$4:$C$32,C33,$D$4:$D$32,D33,$E$4:$E$32,E33,$F$4:$F$32,F33,$G$4:$G$32,G33,$H$4:$H$32,H33,$B$4:$B$32,"SALIDA"),SUMIFS($I$4:$I$32,$C$4:$C$32,C33,$D$4:$D$32,D33,$E$4:$E$32,E33,$G$4:$G$32,G33,$H$4:$H$32,H33,$B$4:$B$32,"INGRESO")+SUMIFS($I$4:$I$32,$C$4:$C$32,C33,$D$4:$D$32,D33,$E$4:$E$32,E33,$G$4:$G$32,G33,$H$4:$H$32,H33,$B$4:$B$32,"DE CORTE")-SUMIFS($I$4:$I$32,$C$4:$C$32,C33,$D$4:$D$32,D33,$E$4:$E$32,E33,$G$4:$G$32,G33,$H$4:$H$32,H33,$B$4:$B$32,"SALIDA"))),0) -> 0 | M33: =IF(C33="",0,L33+IF(OR(B33="INGRESO",B33="DE CORTE"),I33,IF(B33="SALIDA",-I33,0))) -> 0
J34: {=IFERROR(INDEX(PRECIOS_COMPLEMENTOS!$C$4:$F$17,MATCH(D34&"_"&E34,PRECIOS_COMPLEMENTOS!$H$4:$H$17,0),IF(OR(H34="S",H34="20cm"),1,IF(OR(H34="M",H34="25cm"),2,IF(OR(H34="L",H34="30cm"),3,IF(OR(H34="XL",H34="35cm"),4,0))))),0)} -> #REF! | K34: =IFERROR(I34*J34,0) -> 0 | L34: =IFERROR(IF(C34="",0,IF(D34="PRETINA",SUMIFS($I$4:$I$33,$C$4:$C$33,C34,$D$4:$D$33,D34,$E$4:$E$33,E34,$F$4:$F$33,F34,$G$4:$G$33,G34,$H$4:$H$33,H34,$B$4:$B$33,"INGRESO")+SUMIFS($I$4:$I$33,$C$4:$C$33,C34,$D$4:$D$33,D34,$E$4:$E$33,E34,$F$4:$F$33,F34,$G$4:$G$33,G34,$H$4:$H$33,H34,$B$4:$B$33,"DE CORTE")-SUMIFS($I$4:$I$33,$C$4:$C$33,C34,$D$4:$D$33,D34,$E$4:$E$33,E34,$F$4:$F$33,F34,$G$4:$G$33,G34,$H$4:$H$33,H34,$B$4:$B$33,"SALIDA"),SUMIFS($I$4:$I$33,$C$4:$C$33,C34,$D$4:$D$33,D34,$E$4:$E$33,E34,$G$4:$G$33,G34,$H$4:$H$33,H34,$B$4:$B$33,"INGRESO")+SUMIFS($I$4:$I$33,$C$4:$C$33,C34,$D$4:$D$33,D34,$E$4:$E$33,E34,$G$4:$G$33,G34,$H$4:$H$33,H34,$B$4:$B$33,"DE CORTE")-SUMIFS($I$4:$I$33,$C$4:$C$33,C34,$D$4:$D$33,D34,$E$4:$E$33,E34,$G$4:$G$33,G34,$H$4:$H$33,H34,$B$4:$B$33,"SALIDA"))),0) -> 0 | M34: =IF(C34="",0,L34+IF(OR(B34="INGRESO",B34="DE CORTE"),I34,IF(B34="SALIDA",-I34,0))) -> 0
J35: {=IFERROR(INDEX(PRECIOS_COMPLEMENTOS!$C$4:$F$17,MATCH(D35&"_"&E35,PRECIOS_COMPLEMENTOS!$H$4:$H$17,0),IF(OR(H35="S",H35="20cm"),1,IF(OR(H35="M",H35="25cm"),2,IF(OR(H35="L",H35="30cm"),3,IF(OR(H35="XL",H35="35cm"),4,0))))),0)} -> #REF! | K35: =IFERROR(I35*J35,0) -> 0 | L35: =IFERROR(IF(C35="",0,IF(D35="PRETINA",SUMIFS($I$4:$I$34,$C$4:$C$34,C35,$D$4:$D$34,D35,$E$4:$E$34,E35,$F$4:$F$34,F35,$G$4:$G$34,G35,$H$4:$H$34,H35,$B$4:$B$34,"INGRESO")+SUMIFS($I$4:$I$34,$C$4:$C$34,C35,$D$4:$D$34,D35,$E$4:$E$34,E35,$F$4:$F$34,F35,$G$4:$G$34,G35,$H$4:$H$34,H35,$B$4:$B$34,"DE CORTE")-SUMIFS($I$4:$I$34,$C$4:$C$34,C35,$D$4:$D$34,D35,$E$4:$E$34,E35,$F$4:$F$34,F35,$G$4:$G$34,G35,$H$4:$H$34,H35,$B$4:$B$34,"SALIDA"),SUMIFS($I$4:$I$34,$C$4:$C$34,C35,$D$4:$D$34,D35,$E$4:$E$34,E35,$G$4:$G$34,G35,$H$4:$H$34,H35,$B$4:$B$34,"INGRESO")+SUMIFS($I$4:$I$34,$C$4:$C$34,C35,$D$4:$D$34,D35,$E$4:$E$34,E35,$G$4:$G$34,G35,$H$4:$H$34,H35,$B$4:$B$34,"DE CORTE")-SUMIFS($I$4:$I$34,$C$4:$C$34,C35,$D$4:$D$34,D35,$E$4:$E$34,E35,$G$4:$G$34,G35,$H$4:$H$34,H35,$B$4:$B$34,"SALIDA"))),0) -> 0 | M35: =IF(C35="",0,L35+IF(OR(B35="INGRESO",B35="DE CORTE"),I35,IF(B35="SALIDA",-I35,0))) -> 0
J36: {=IFERROR(INDEX(PRECIOS_COMPLEMENTOS!$C$4:$F$17,MATCH(D36&"_"&E36,PRECIOS_COMPLEMENTOS!$H$4:$H$17,0),IF(OR(H36="S",H36="20cm"),1,IF(OR(H36="M",H36="25cm"),2,IF(OR(H36="L",H36="30cm"),3,IF(OR(H36="XL",H36="35cm"),4,0))))),0)} -> #REF! | K36: =IFERROR(I36*J36,0) -> 0 | L36: =IFERROR(IF(C36="",0,IF(D36="PRETINA",SUMIFS($I$4:$I$35,$C$4:$C$35,C36,$D$4:$D$35,D36,$E$4:$E$35,E36,$F$4:$F$35,F36,$G$4:$G$35,G36,$H$4:$H$35,H36,$B$4:$B$35,"INGRESO")+SUMIFS($I$4:$I$35,$C$4:$C$35,C36,$D$4:$D$35,D36,$E$4:$E$35,E36,$F$4:$F$35,F36,$G$4:$G$35,G36,$H$4:$H$35,H36,$B$4:$B$35,"DE CORTE")-SUMIFS($I$4:$I$35,$C$4:$C$35,C36,$D$4:$D$35,D36,$E$4:$E$35,E36,$F$4:$F$35,F36,$G$4:$G$35,G36,$H$4:$H$35,H36,$B$4:$B$35,"SALIDA"),SUMIFS($I$4:$I$35,$C$4:$C$35,C36,$D$4:$D$35,D36,$E$4:$E$35,E36,$G$4:$G$35,G36,$H$4:$H$35,H36,$B$4:$B$35,"INGRESO")+SUMIFS($I$4:$I$35,$C$4:$C$35,C36,$D$4:$D$35,D36,$E$4:$E$35,E36,$G$4:$G$35,G36,$H$4:$H$35,H36,$B$4:$B$35,"DE CORTE")-SUMIFS($I$4:$I$35,$C$4:$C$35,C36,$D$4:$D$35,D36,$E$4:$E$35,E36,$G$4:$G$35,G36,$H$4:$H$35,H36,$B$4:$B$35,"SALIDA"))),0) -> 0 | M36: =IF(C36="",0,L36+IF(OR(B36="INGRESO",B36="DE CORTE"),I36,IF(B36="SALIDA",-I36,0))) -> 0
J37: {=IFERROR(INDEX(PRECIOS_COMPLEMENTOS!$C$4:$F$17,MATCH(D37&"_"&E37,PRECIOS_COMPLEMENTOS!$H$4:$H$17,0),IF(OR(H37="S",H37="20cm"),1,IF(OR(H37="M",H37="25cm"),2,IF(OR(H37="L",H37="30cm"),3,IF(OR(H37="XL",H37="35cm"),4,0))))),0)} -> #REF! | K37: =IFERROR(I37*J37,0) -> 0 | L37: =IFERROR(IF(C37="",0,IF(D37="PRETINA",SUMIFS($I$4:$I$36,$C$4:$C$36,C37,$D$4:$D$36,D37,$E$4:$E$36,E37,$F$4:$F$36,F37,$G$4:$G$36,G37,$H$4:$H$36,H37,$B$4:$B$36,"INGRESO")+SUMIFS($I$4:$I$36,$C$4:$C$36,C37,$D$4:$D$36,D37,$E$4:$E$36,E37,$F$4:$F$36,F37,$G$4:$G$36,G37,$H$4:$H$36,H37,$B$4:$B$36,"DE CORTE")-SUMIFS($I$4:$I$36,$C$4:$C$36,C37,$D$4:$D$36,D37,$E$4:$E$36,E37,$F$4:$F$36,F37,$G$4:$G$36,G37,$H$4:$H$36,H37,$B$4:$B$36,"SALIDA"),SUMIFS($I$4:$I$36,$C$4:$C$36,C37,$D$4:$D$36,D37,$E$4:$E$36,E37,$G$4:$G$36,G37,$H$4:$H$36,H37,$B$4:$B$36,"INGRESO")+SUMIFS($I$4:$I$36,$C$4:$C$36,C37,$D$4:$D$36,D37,$E$4:$E$36,E37,$G$4:$G$36,G37,$H$4:$H$36,H37,$B$4:$B$36,"DE CORTE")-SUMIFS($I$4:$I$36,$C$4:$C$36,C37,$D$4:$D$36,D37,$E$4:$E$36,E37,$G$4:$G$36,G37,$H$4:$H$36,H37,$B$4:$B$36,"SALIDA"))),0) -> 0 | M37: =IF(C37="",0,L37+IF(OR(B37="INGRESO",B37="DE CORTE"),I37,IF(B37="SALIDA",-I37,0))) -> 0
J38: {=IFERROR(INDEX(PRECIOS_COMPLEMENTOS!$C$4:$F$17,MATCH(D38&"_"&E38,PRECIOS_COMPLEMENTOS!$H$4:$H$17,0),IF(OR(H38="S",H38="20cm"),1,IF(OR(H38="M",H38="25cm"),2,IF(OR(H38="L",H38="30cm"),3,IF(OR(H38="XL",H38="35cm"),4,0))))),0)} -> #REF! | K38: =IFERROR(I38*J38,0) -> 0 | L38: =IFERROR(IF(C38="",0,IF(D38="PRETINA",SUMIFS($I$4:$I$37,$C$4:$C$37,C38,$D$4:$D$37,D38,$E$4:$E$37,E38,$F$4:$F$37,F38,$G$4:$G$37,G38,$H$4:$H$37,H38,$B$4:$B$37,"INGRESO")+SUMIFS($I$4:$I$37,$C$4:$C$37,C38,$D$4:$D$37,D38,$E$4:$E$37,E38,$F$4:$F$37,F38,$G$4:$G$37,G38,$H$4:$H$37,H38,$B$4:$B$37,"DE CORTE")-SUMIFS($I$4:$I$37,$C$4:$C$37,C38,$D$4:$D$37,D38,$E$4:$E$37,E38,$F$4:$F$37,F38,$G$4:$G$37,G38,$H$4:$H$37,H38,$B$4:$B$37,"SALIDA"),SUMIFS($I$4:$I$37,$C$4:$C$37,C38,$D$4:$D$37,D38,$E$4:$E$37,E38,$G$4:$G$37,G38,$H$4:$H$37,H38,$B$4:$B$37,"INGRESO")+SUMIFS($I$4:$I$37,$C$4:$C$37,C38,$D$4:$D$37,D38,$E$4:$E$37,E38,$G$4:$G$37,G38,$H$4:$H$37,H38,$B$4:$B$37,"DE CORTE")-SUMIFS($I$4:$I$37,$C$4:$C$37,C38,$D$4:$D$37,D38,$E$4:$E$37,E38,$G$4:$G$37,G38,$H$4:$H$37,H38,$B$4:$B$37,"SALIDA"))),0) -> 0 | M38: =IF(C38="",0,L38+IF(OR(B38="INGRESO",B38="DE CORTE"),I38,IF(B38="SALIDA",-I38,0))) -> 0
J39: {=IFERROR(INDEX(PRECIOS_COMPLEMENTOS!$C$4:$F$17,MATCH(D39&"_"&E39,PRECIOS_COMPLEMENTOS!$H$4:$H$17,0),IF(OR(H39="S",H39="20cm"),1,IF(OR(H39="M",H39="25cm"),2,IF(OR(H39="L",H39="30cm"),3,IF(OR(H39="XL",H39="35cm"),4,0))))),0)} -> #REF! | K39: =IFERROR(I39*J39,0) -> 0 | L39: =IFERROR(IF(C39="",0,IF(D39="PRETINA",SUMIFS($I$4:$I$38,$C$4:$C$38,C39,$D$4:$D$38,D39,$E$4:$E$38,E39,$F$4:$F$38,F39,$G$4:$G$38,G39,$H$4:$H$38,H39,$B$4:$B$38,"INGRESO")+SUMIFS($I$4:$I$38,$C$4:$C$38,C39,$D$4:$D$38,D39,$E$4:$E$38,E39,$F$4:$F$38,F39,$G$4:$G$38,G39,$H$4:$H$38,H39,$B$4:$B$38,"DE CORTE")-SUMIFS($I$4:$I$38,$C$4:$C$38,C39,$D$4:$D$38,D39,$E$4:$E$38,E39,$F$4:$F$38,F39,$G$4:$G$38,G39,$H$4:$H$38,H39,$B$4:$B$38,"SALIDA"),SUMIFS($I$4:$I$38,$C$4:$C$38,C39,$D$4:$D$38,D39,$E$4:$E$38,E39,$G$4:$G$38,G39,$H$4:$H$38,H39,$B$4:$B$38,"INGRESO")+SUMIFS($I$4:$I$38,$C$4:$C$38,C39,$D$4:$D$38,D39,$E$4:$E$38,E39,$G$4:$G$38,G39,$H$4:$H$38,H39,$B$4:$B$38,"DE CORTE")-SUMIFS($I$4:$I$38,$C$4:$C$38,C39,$D$4:$D$38,D39,$E$4:$E$38,E39,$G$4:$G$38,G39,$H$4:$H$38,H39,$B$4:$B$38,"SALIDA"))),0) -> 0 | M39: =IF(C39="",0,L39+IF(OR(B39="INGRESO",B39="DE CORTE"),I39,IF(B39="SALIDA",-I39,0))) -> 0
J40: {=IFERROR(INDEX(PRECIOS_COMPLEMENTOS!$C$4:$F$17,MATCH(D40&"_"&E40,PRECIOS_COMPLEMENTOS!$H$4:$H$17,0),IF(OR(H40="S",H40="20cm"),1,IF(OR(H40="M",H40="25cm"),2,IF(OR(H40="L",H40="30cm"),3,IF(OR(H40="XL",H40="35cm"),4,0))))),0)} -> #REF! | K40: =IFERROR(I40*J40,0) -> 0 | L40: =IFERROR(IF(C40="",0,IF(D40="PRETINA",SUMIFS($I$4:$I$39,$C$4:$C$39,C40,$D$4:$D$39,D40,$E$4:$E$39,E40,$F$4:$F$39,F40,$G$4:$G$39,G40,$H$4:$H$39,H40,$B$4:$B$39,"INGRESO")+SUMIFS($I$4:$I$39,$C$4:$C$39,C40,$D$4:$D$39,D40,$E$4:$E$39,E40,$F$4:$F$39,F40,$G$4:$G$39,G40,$H$4:$H$39,H40,$B$4:$B$39,"DE CORTE")-SUMIFS($I$4:$I$39,$C$4:$C$39,C40,$D$4:$D$39,D40,$E$4:$E$39,E40,$F$4:$F$39,F40,$G$4:$G$39,G40,$H$4:$H$39,H40,$B$4:$B$39,"SALIDA"),SUMIFS($I$4:$I$39,$C$4:$C$39,C40,$D$4:$D$39,D40,$E$4:$E$39,E40,$G$4:$G$39,G40,$H$4:$H$39,H40,$B$4:$B$39,"INGRESO")+SUMIFS($I$4:$I$39,$C$4:$C$39,C40,$D$4:$D$39,D40,$E$4:$E$39,E40,$G$4:$G$39,G40,$H$4:$H$39,H40,$B$4:$B$39,"DE CORTE")-SUMIFS($I$4:$I$39,$C$4:$C$39,C40,$D$4:$D$39,D40,$E$4:$E$39,E40,$G$4:$G$39,G40,$H$4:$H$39,H40,$B$4:$B$39,"SALIDA"))),0) -> 0 | M40: =IF(C40="",0,L40+IF(OR(B40="INGRESO",B40="DE CORTE"),I40,IF(B40="SALIDA",-I40,0))) -> 0
J41: {=IFERROR(INDEX(PRECIOS_COMPLEMENTOS!$C$4:$F$17,MATCH(D41&"_"&E41,PRECIOS_COMPLEMENTOS!$H$4:$H$17,0),IF(OR(H41="S",H41="20cm"),1,IF(OR(H41="M",H41="25cm"),2,IF(OR(H41="L",H41="30cm"),3,IF(OR(H41="XL",H41="35cm"),4,0))))),0)} -> #REF! | K41: =IFERROR(I41*J41,0) -> 0 | L41: =IFERROR(IF(C41="",0,IF(D41="PRETINA",SUMIFS($I$4:$I$40,$C$4:$C$40,C41,$D$4:$D$40,D41,$E$4:$E$40,E41,$F$4:$F$40,F41,$G$4:$G$40,G41,$H$4:$H$40,H41,$B$4:$B$40,"INGRESO")+SUMIFS($I$4:$I$40,$C$4:$C$40,C41,$D$4:$D$40,D41,$E$4:$E$40,E41,$F$4:$F$40,F41,$G$4:$G$40,G41,$H$4:$H$40,H41,$B$4:$B$40,"DE CORTE")-SUMIFS($I$4:$I$40,$C$4:$C$40,C41,$D$4:$D$40,D41,$E$4:$E$40,E41,$F$4:$F$40,F41,$G$4:$G$40,G41,$H$4:$H$40,H41,$B$4:$B$40,"SALIDA"),SUMIFS($I$4:$I$40,$C$4:$C$40,C41,$D$4:$D$40,D41,$E$4:$E$40,E41,$G$4:$G$40,G41,$H$4:$H$40,H41,$B$4:$B$40,"INGRESO")+SUMIFS($I$4:$I$40,$C$4:$C$40,C41,$D$4:$D$40,D41,$E$4:$E$40,E41,$G$4:$G$40,G41,$H$4:$H$40,H41,$B$4:$B$40,"DE CORTE")-SUMIFS($I$4:$I$40,$C$4:$C$40,C41,$D$4:$D$40,D41,$E$4:$E$40,E41,$G$4:$G$40,G41,$H$4:$H$40,H41,$B$4:$B$40,"SALIDA"))),0) -> 0 | M41: =IF(C41="",0,L41+IF(OR(B41="INGRESO",B41="DE CORTE"),I41,IF(B41="SALIDA",-I41,0))) -> 0
J42: {=IFERROR(INDEX(PRECIOS_COMPLEMENTOS!$C$4:$F$17,MATCH(D42&"_"&E42,PRECIOS_COMPLEMENTOS!$H$4:$H$17,0),IF(OR(H42="S",H42="20cm"),1,IF(OR(H42="M",H42="25cm"),2,IF(OR(H42="L",H42="30cm"),3,IF(OR(H42="XL",H42="35cm"),4,0))))),0)} -> #REF! | K42: =IFERROR(I42*J42,0) -> 0 | L42: =IFERROR(IF(C42="",0,IF(D42="PRETINA",SUMIFS($I$4:$I$41,$C$4:$C$41,C42,$D$4:$D$41,D42,$E$4:$E$41,E42,$F$4:$F$41,F42,$G$4:$G$41,G42,$H$4:$H$41,H42,$B$4:$B$41,"INGRESO")+SUMIFS($I$4:$I$41,$C$4:$C$41,C42,$D$4:$D$41,D42,$E$4:$E$41,E42,$F$4:$F$41,F42,$G$4:$G$41,G42,$H$4:$H$41,H42,$B$4:$B$41,"DE CORTE")-SUMIFS($I$4:$I$41,$C$4:$C$41,C42,$D$4:$D$41,D42,$E$4:$E$41,E42,$F$4:$F$41,F42,$G$4:$G$41,G42,$H$4:$H$41,H42,$B$4:$B$41,"SALIDA"),SUMIFS($I$4:$I$41,$C$4:$C$41,C42,$D$4:$D$41,D42,$E$4:$E$41,E42,$G$4:$G$41,G42,$H$4:$H$41,H42,$B$4:$B$41,"INGRESO")+SUMIFS($I$4:$I$41,$C$4:$C$41,C42,$D$4:$D$41,D42,$E$4:$E$41,E42,$G$4:$G$41,G42,$H$4:$H$41,H42,$B$4:$B$41,"DE CORTE")-SUMIFS($I$4:$I$41,$C$4:$C$41,C42,$D$4:$D$41,D42,$E$4:$E$41,E42,$G$4:$G$41,G42,$H$4:$H$41,H42,$B$4:$B$41,"SALIDA"))),0) -> 0 | M42: =IF(C42="",0,L42+IF(OR(B42="INGRESO",B42="DE CORTE"),I42,IF(B42="SALIDA",-I42,0))) -> 0
J43: {=IFERROR(INDEX(PRECIOS_COMPLEMENTOS!$C$4:$F$17,MATCH(D43&"_"&E43,PRECIOS_COMPLEMENTOS!$H$4:$H$17,0),IF(OR(H43="S",H43="20cm"),1,IF(OR(H43="M",H43="25cm"),2,IF(OR(H43="L",H43="30cm"),3,IF(OR(H43="XL",H43="35cm"),4,0))))),0)} -> #REF! | K43: =IFERROR(I43*J43,0) -> 0 | L43: =IFERROR(IF(C43="",0,IF(D43="PRETINA",SUMIFS($I$4:$I$42,$C$4:$C$42,C43,$D$4:$D$42,D43,$E$4:$E$42,E43,$F$4:$F$42,F43,$G$4:$G$42,G43,$H$4:$H$42,H43,$B$4:$B$42,"INGRESO")+SUMIFS($I$4:$I$42,$C$4:$C$42,C43,$D$4:$D$42,D43,$E$4:$E$42,E43,$F$4:$F$42,F43,$G$4:$G$42,G43,$H$4:$H$42,H43,$B$4:$B$42,"DE CORTE")-SUMIFS($I$4:$I$42,$C$4:$C$42,C43,$D$4:$D$42,D43,$E$4:$E$42,E43,$F$4:$F$42,F43,$G$4:$G$42,G43,$H$4:$H$42,H43,$B$4:$B$42,"SALIDA"),SUMIFS($I$4:$I$42,$C$4:$C$42,C43,$D$4:$D$42,D43,$E$4:$E$42,E43,$G$4:$G$42,G43,$H$4:$H$42,H43,$B$4:$B$42,"INGRESO")+SUMIFS($I$4:$I$42,$C$4:$C$42,C43,$D$4:$D$42,D43,$E$4:$E$42,E43,$G$4:$G$42,G43,$H$4:$H$42,H43,$B$4:$B$42,"DE CORTE")-SUMIFS($I$4:$I$42,$C$4:$C$42,C43,$D$4:$D$42,D43,$E$4:$E$42,E43,$G$4:$G$42,G43,$H$4:$H$42,H43,$B$4:$B$42,"SALIDA"))),0) -> 0 | M43: =IF(C43="",0,L43+IF(OR(B43="INGRESO",B43="DE CORTE"),I43,IF(B43="SALIDA",-I43,0))) -> 0
J44: {=IFERROR(INDEX(PRECIOS_COMPLEMENTOS!$C$4:$F$17,MATCH(D44&"_"&E44,PRECIOS_COMPLEMENTOS!$H$4:$H$17,0),IF(OR(H44="S",H44="20cm"),1,IF(OR(H44="M",H44="25cm"),2,IF(OR(H44="L",H44="30cm"),3,IF(OR(H44="XL",H44="35cm"),4,0))))),0)} -> #REF! | K44: =IFERROR(I44*J44,0) -> 0 | L44: =IFERROR(IF(C44="",0,IF(D44="PRETINA",SUMIFS($I$4:$I$43,$C$4:$C$43,C44,$D$4:$D$43,D44,$E$4:$E$43,E44,$F$4:$F$43,F44,$G$4:$G$43,G44,$H$4:$H$43,H44,$B$4:$B$43,"INGRESO")+SUMIFS($I$4:$I$43,$C$4:$C$43,C44,$D$4:$D$43,D44,$E$4:$E$43,E44,$F$4:$F$43,F44,$G$4:$G$43,G44,$H$4:$H$43,H44,$B$4:$B$43,"DE CORTE")-SUMIFS($I$4:$I$43,$C$4:$C$43,C44,$D$4:$D$43,D44,$E$4:$E$43,E44,$F$4:$F$43,F44,$G$4:$G$43,G44,$H$4:$H$43,H44,$B$4:$B$43,"SALIDA"),SUMIFS($I$4:$I$43,$C$4:$C$43,C44,$D$4:$D$43,D44,$E$4:$E$43,E44,$G$4:$G$43,G44,$H$4:$H$43,H44,$B$4:$B$43,"INGRESO")+SUMIFS($I$4:$I$43,$C$4:$C$43,C44,$D$4:$D$43,D44,$E$4:$E$43,E44,$G$4:$G$43,G44,$H$4:$H$43,H44,$B$4:$B$43,"DE CORTE")-SUMIFS($I$4:$I$43,$C$4:$C$43,C44,$D$4:$D$43,D44,$E$4:$E$43,E44,$G$4:$G$43,G44,$H$4:$H$43,H44,$B$4:$B$43,"SALIDA"))),0) -> 0 | M44: =IF(C44="",0,L44+IF(OR(B44="INGRESO",B44="DE CORTE"),I44,IF(B44="SALIDA",-I44,0))) -> 0
J45: {=IFERROR(INDEX(PRECIOS_COMPLEMENTOS!$C$4:$F$17,MATCH(D45&"_"&E45,PRECIOS_COMPLEMENTOS!$H$4:$H$17,0),IF(OR(H45="S",H45="20cm"),1,IF(OR(H45="M",H45="25cm"),2,IF(OR(H45="L",H45="30cm"),3,IF(OR(H45="XL",H45="35cm"),4,0))))),0)} -> #REF! | K45: =IFERROR(I45*J45,0) -> 0 | L45: =IFERROR(IF(C45="",0,IF(D45="PRETINA",SUMIFS($I$4:$I$44,$C$4:$C$44,C45,$D$4:$D$44,D45,$E$4:$E$44,E45,$F$4:$F$44,F45,$G$4:$G$44,G45,$H$4:$H$44,H45,$B$4:$B$44,"INGRESO")+SUMIFS($I$4:$I$44,$C$4:$C$44,C45,$D$4:$D$44,D45,$E$4:$E$44,E45,$F$4:$F$44,F45,$G$4:$G$44,G45,$H$4:$H$44,H45,$B$4:$B$44,"DE CORTE")-SUMIFS($I$4:$I$44,$C$4:$C$44,C45,$D$4:$D$44,D45,$E$4:$E$44,E45,$F$4:$F$44,F45,$G$4:$G$44,G45,$H$4:$H$44,H45,$B$4:$B$44,"SALIDA"),SUMIFS($I$4:$I$44,$C$4:$C$44,C45,$D$4:$D$44,D45,$E$4:$E$44,E45,$G$4:$G$44,G45,$H$4:$H$44,H45,$B$4:$B$44,"INGRESO")+SUMIFS($I$4:$I$44,$C$4:$C$44,C45,$D$4:$D$44,D45,$E$4:$E$44,E45,$G$4:$G$44,G45,$H$4:$H$44,H45,$B$4:$B$44,"DE CORTE")-SUMIFS($I$4:$I$44,$C$4:$C$44,C45,$D$4:$D$44,D45,$E$4:$E$44,E45,$G$4:$G$44,G45,$H$4:$H$44,H45,$B$4:$B$44,"SALIDA"))),0) -> 0 | M45: =IF(C45="",0,L45+IF(OR(B45="INGRESO",B45="DE CORTE"),I45,IF(B45="SALIDA",-I45,0))) -> 0
J46: {=IFERROR(INDEX(PRECIOS_COMPLEMENTOS!$C$4:$F$17,MATCH(D46&"_"&E46,PRECIOS_COMPLEMENTOS!$H$4:$H$17,0),IF(OR(H46="S",H46="20cm"),1,IF(OR(H46="M",H46="25cm"),2,IF(OR(H46="L",H46="30cm"),3,IF(OR(H46="XL",H46="35cm"),4,0))))),0)} -> #REF! | K46: =IFERROR(I46*J46,0) -> 0 | L46: =IFERROR(IF(C46="",0,IF(D46="PRETINA",SUMIFS($I$4:$I$45,$C$4:$C$45,C46,$D$4:$D$45,D46,$E$4:$E$45,E46,$F$4:$F$45,F46,$G$4:$G$45,G46,$H$4:$H$45,H46,$B$4:$B$45,"INGRESO")+SUMIFS($I$4:$I$45,$C$4:$C$45,C46,$D$4:$D$45,D46,$E$4:$E$45,E46,$F$4:$F$45,F46,$G$4:$G$45,G46,$H$4:$H$45,H46,$B$4:$B$45,"DE CORTE")-SUMIFS($I$4:$I$45,$C$4:$C$45,C46,$D$4:$D$45,D46,$E$4:$E$45,E46,$F$4:$F$45,F46,$G$4:$G$45,G46,$H$4:$H$45,H46,$B$4:$B$45,"SALIDA"),SUMIFS($I$4:$I$45,$C$4:$C$45,C46,$D$4:$D$45,D46,$E$4:$E$45,E46,$G$4:$G$45,G46,$H$4:$H$45,H46,$B$4:$B$45,"INGRESO")+SUMIFS($I$4:$I$45,$C$4:$C$45,C46,$D$4:$D$45,D46,$E$4:$E$45,E46,$G$4:$G$45,G46,$H$4:$H$45,H46,$B$4:$B$45,"DE CORTE")-SUMIFS($I$4:$I$45,$C$4:$C$45,C46,$D$4:$D$45,D46,$E$4:$E$45,E46,$G$4:$G$45,G46,$H$4:$H$45,H46,$B$4:$B$45,"SALIDA"))),0) -> 0 | M46: =IF(C46="",0,L46+IF(OR(B46="INGRESO",B46="DE CORTE"),I46,IF(B46="SALIDA",-I46,0))) -> 0
J47: {=IFERROR(INDEX(PRECIOS_COMPLEMENTOS!$C$4:$F$17,MATCH(D47&"_"&E47,PRECIOS_COMPLEMENTOS!$H$4:$H$17,0),IF(OR(H47="S",H47="20cm"),1,IF(OR(H47="M",H47="25cm"),2,IF(OR(H47="L",H47="30cm"),3,IF(OR(H47="XL",H47="35cm"),4,0))))),0)} -> #REF! | K47: =IFERROR(I47*J47,0) -> 0 | L47: =IFERROR(IF(C47="",0,IF(D47="PRETINA",SUMIFS($I$4:$I$46,$C$4:$C$46,C47,$D$4:$D$46,D47,$E$4:$E$46,E47,$F$4:$F$46,F47,$G$4:$G$46,G47,$H$4:$H$46,H47,$B$4:$B$46,"INGRESO")+SUMIFS($I$4:$I$46,$C$4:$C$46,C47,$D$4:$D$46,D47,$E$4:$E$46,E47,$F$4:$F$46,F47,$G$4:$G$46,G47,$H$4:$H$46,H47,$B$4:$B$46,"DE CORTE")-SUMIFS($I$4:$I$46,$C$4:$C$46,C47,$D$4:$D$46,D47,$E$4:$E$46,E47,$F$4:$F$46,F47,$G$4:$G$46,G47,$H$4:$H$46,H47,$B$4:$B$46,"SALIDA"),SUMIFS($I$4:$I$46,$C$4:$C$46,C47,$D$4:$D$46,D47,$E$4:$E$46,E47,$G$4:$G$46,G47,$H$4:$H$46,H47,$B$4:$B$46,"INGRESO")+SUMIFS($I$4:$I$46,$C$4:$C$46,C47,$D$4:$D$46,D47,$E$4:$E$46,E47,$G$4:$G$46,G47,$H$4:$H$46,H47,$B$4:$B$46,"DE CORTE")-SUMIFS($I$4:$I$46,$C$4:$C$46,C47,$D$4:$D$46,D47,$E$4:$E$46,E47,$G$4:$G$46,G47,$H$4:$H$46,H47,$B$4:$B$46,"SALIDA"))),0) -> 0 | M47: =IF(C47="",0,L47+IF(OR(B47="INGRESO",B47="DE CORTE"),I47,IF(B47="SALIDA",-I47,0))) -> 0
J48: {=IFERROR(INDEX(PRECIOS_COMPLEMENTOS!$C$4:$F$17,MATCH(D48&"_"&E48,PRECIOS_COMPLEMENTOS!$H$4:$H$17,0),IF(OR(H48="S",H48="20cm"),1,IF(OR(H48="M",H48="25cm"),2,IF(OR(H48="L",H48="30cm"),3,IF(OR(H48="XL",H48="35cm"),4,0))))),0)} -> #REF! | K48: =IFERROR(I48*J48,0) -> 0 | L48: =IFERROR(IF(C48="",0,IF(D48="PRETINA",SUMIFS($I$4:$I$47,$C$4:$C$47,C48,$D$4:$D$47,D48,$E$4:$E$47,E48,$F$4:$F$47,F48,$G$4:$G$47,G48,$H$4:$H$47,H48,$B$4:$B$47,"INGRESO")+SUMIFS($I$4:$I$47,$C$4:$C$47,C48,$D$4:$D$47,D48,$E$4:$E$47,E48,$F$4:$F$47,F48,$G$4:$G$47,G48,$H$4:$H$47,H48,$B$4:$B$47,"DE CORTE")-SUMIFS($I$4:$I$47,$C$4:$C$47,C48,$D$4:$D$47,D48,$E$4:$E$47,E48,$F$4:$F$47,F48,$G$4:$G$47,G48,$H$4:$H$47,H48,$B$4:$B$47,"SALIDA"),SUMIFS($I$4:$I$47,$C$4:$C$47,C48,$D$4:$D$47,D48,$E$4:$E$47,E48,$G$4:$G$47,G48,$H$4:$H$47,H48,$B$4:$B$47,"INGRESO")+SUMIFS($I$4:$I$47,$C$4:$C$47,C48,$D$4:$D$47,D48,$E$4:$E$47,E48,$G$4:$G$47,G48,$H$4:$H$47,H48,$B$4:$B$47,"DE CORTE")-SUMIFS($I$4:$I$47,$C$4:$C$47,C48,$D$4:$D$47,D48,$E$4:$E$47,E48,$G$4:$G$47,G48,$H$4:$H$47,H48,$B$4:$B$47,"SALIDA"))),0) -> 0 | M48: =IF(C48="",0,L48+IF(OR(B48="INGRESO",B48="DE CORTE"),I48,IF(B48="SALIDA",-I48,0))) -> 0
J49: {=IFERROR(INDEX(PRECIOS_COMPLEMENTOS!$C$4:$F$17,MATCH(D49&"_"&E49,PRECIOS_COMPLEMENTOS!$H$4:$H$17,0),IF(OR(H49="S",H49="20cm"),1,IF(OR(H49="M",H49="25cm"),2,IF(OR(H49="L",H49="30cm"),3,IF(OR(H49="XL",H49="35cm"),4,0))))),0)} -> #REF! | K49: =IFERROR(I49*J49,0) -> 0 | L49: =IFERROR(IF(C49="",0,IF(D49="PRETINA",SUMIFS($I$4:$I$48,$C$4:$C$48,C49,$D$4:$D$48,D49,$E$4:$E$48,E49,$F$4:$F$48,F49,$G$4:$G$48,G49,$H$4:$H$48,H49,$B$4:$B$48,"INGRESO")+SUMIFS($I$4:$I$48,$C$4:$C$48,C49,$D$4:$D$48,D49,$E$4:$E$48,E49,$F$4:$F$48,F49,$G$4:$G$48,G49,$H$4:$H$48,H49,$B$4:$B$48,"DE CORTE")-SUMIFS($I$4:$I$48,$C$4:$C$48,C49,$D$4:$D$48,D49,$E$4:$E$48,E49,$F$4:$F$48,F49,$G$4:$G$48,G49,$H$4:$H$48,H49,$B$4:$B$48,"SALIDA"),SUMIFS($I$4:$I$48,$C$4:$C$48,C49,$D$4:$D$48,D49,$E$4:$E$48,E49,$G$4:$G$48,G49,$H$4:$H$48,H49,$B$4:$B$48,"INGRESO")+SUMIFS($I$4:$I$48,$C$4:$C$48,C49,$D$4:$D$48,D49,$E$4:$E$48,E49,$G$4:$G$48,G49,$H$4:$H$48,H49,$B$4:$B$48,"DE CORTE")-SUMIFS($I$4:$I$48,$C$4:$C$48,C49,$D$4:$D$48,D49,$E$4:$E$48,E49,$G$4:$G$48,G49,$H$4:$H$48,H49,$B$4:$B$48,"SALIDA"))),0) -> 0 | M49: =IF(C49="",0,L49+IF(OR(B49="INGRESO",B49="DE CORTE"),I49,IF(B49="SALIDA",-I49,0))) -> 0
J50: {=IFERROR(INDEX(PRECIOS_COMPLEMENTOS!$C$4:$F$17,MATCH(D50&"_"&E50,PRECIOS_COMPLEMENTOS!$H$4:$H$17,0),IF(OR(H50="S",H50="20cm"),1,IF(OR(H50="M",H50="25cm"),2,IF(OR(H50="L",H50="30cm"),3,IF(OR(H50="XL",H50="35cm"),4,0))))),0)} -> #REF! | K50: =IFERROR(I50*J50,0) -> 0 | L50: =IFERROR(IF(C50="",0,IF(D50="PRETINA",SUMIFS($I$4:$I$49,$C$4:$C$49,C50,$D$4:$D$49,D50,$E$4:$E$49,E50,$F$4:$F$49,F50,$G$4:$G$49,G50,$H$4:$H$49,H50,$B$4:$B$49,"INGRESO")+SUMIFS($I$4:$I$49,$C$4:$C$49,C50,$D$4:$D$49,D50,$E$4:$E$49,E50,$F$4:$F$49,F50,$G$4:$G$49,G50,$H$4:$H$49,H50,$B$4:$B$49,"DE CORTE")-SUMIFS($I$4:$I$49,$C$4:$C$49,C50,$D$4:$D$49,D50,$E$4:$E$49,E50,$F$4:$F$49,F50,$G$4:$G$49,G50,$H$4:$H$49,H50,$B$4:$B$49,"SALIDA"),SUMIFS($I$4:$I$49,$C$4:$C$49,C50,$D$4:$D$49,D50,$E$4:$E$49,E50,$G$4:$G$49,G50,$H$4:$H$49,H50,$B$4:$B$49,"INGRESO")+SUMIFS($I$4:$I$49,$C$4:$C$49,C50,$D$4:$D$49,D50,$E$4:$E$49,E50,$G$4:$G$49,G50,$H$4:$H$49,H50,$B$4:$B$49,"DE CORTE")-SUMIFS($I$4:$I$49,$C$4:$C$49,C50,$D$4:$D$49,D50,$E$4:$E$49,E50,$G$4:$G$49,G50,$H$4:$H$49,H50,$B$4:$B$49,"SALIDA"))),0) -> 0 | M50: =IF(C50="",0,L50+IF(OR(B50="INGRESO",B50="DE CORTE"),I50,IF(B50="SALIDA",-I50,0))) -> 0
J51: {=IFERROR(INDEX(PRECIOS_COMPLEMENTOS!$C$4:$F$17,MATCH(D51&"_"&E51,PRECIOS_COMPLEMENTOS!$H$4:$H$17,0),IF(OR(H51="S",H51="20cm"),1,IF(OR(H51="M",H51="25cm"),2,IF(OR(H51="L",H51="30cm"),3,IF(OR(H51="XL",H51="35cm"),4,0))))),0)} -> #REF! | K51: =IFERROR(I51*J51,0) -> 0 | L51: =IFERROR(IF(C51="",0,IF(D51="PRETINA",SUMIFS($I$4:$I$50,$C$4:$C$50,C51,$D$4:$D$50,D51,$E$4:$E$50,E51,$F$4:$F$50,F51,$G$4:$G$50,G51,$H$4:$H$50,H51,$B$4:$B$50,"INGRESO")+SUMIFS($I$4:$I$50,$C$4:$C$50,C51,$D$4:$D$50,D51,$E$4:$E$50,E51,$F$4:$F$50,F51,$G$4:$G$50,G51,$H$4:$H$50,H51,$B$4:$B$50,"DE CORTE")-SUMIFS($I$4:$I$50,$C$4:$C$50,C51,$D$4:$D$50,D51,$E$4:$E$50,E51,$F$4:$F$50,F51,$G$4:$G$50,G51,$H$4:$H$50,H51,$B$4:$B$50,"SALIDA"),SUMIFS($I$4:$I$50,$C$4:$C$50,C51,$D$4:$D$50,D51,$E$4:$E$50,E51,$G$4:$G$50,G51,$H$4:$H$50,H51,$B$4:$B$50,"INGRESO")+SUMIFS($I$4:$I$50,$C$4:$C$50,C51,$D$4:$D$50,D51,$E$4:$E$50,E51,$G$4:$G$50,G51,$H$4:$H$50,H51,$B$4:$B$50,"DE CORTE")-SUMIFS($I$4:$I$50,$C$4:$C$50,C51,$D$4:$D$50,D51,$E$4:$E$50,E51,$G$4:$G$50,G51,$H$4:$H$50,H51,$B$4:$B$50,"SALIDA"))),0) -> 0 | M51: =IF(C51="",0,L51+IF(OR(B51="INGRESO",B51="DE CORTE"),I51,IF(B51="SALIDA",-I51,0))) -> 0
J52: {=IFERROR(INDEX(PRECIOS_COMPLEMENTOS!$C$4:$F$17,MATCH(D52&"_"&E52,PRECIOS_COMPLEMENTOS!$H$4:$H$17,0),IF(OR(H52="S",H52="20cm"),1,IF(OR(H52="M",H52="25cm"),2,IF(OR(H52="L",H52="30cm"),3,IF(OR(H52="XL",H52="35cm"),4,0))))),0)} -> #REF! | K52: =IFERROR(I52*J52,0) -> 0 | L52: =IFERROR(IF(C52="",0,IF(D52="PRETINA",SUMIFS($I$4:$I$51,$C$4:$C$51,C52,$D$4:$D$51,D52,$E$4:$E$51,E52,$F$4:$F$51,F52,$G$4:$G$51,G52,$H$4:$H$51,H52,$B$4:$B$51,"INGRESO")+SUMIFS($I$4:$I$51,$C$4:$C$51,C52,$D$4:$D$51,D52,$E$4:$E$51,E52,$F$4:$F$51,F52,$G$4:$G$51,G52,$H$4:$H$51,H52,$B$4:$B$51,"DE CORTE")-SUMIFS($I$4:$I$51,$C$4:$C$51,C52,$D$4:$D$51,D52,$E$4:$E$51,E52,$F$4:$F$51,F52,$G$4:$G$51,G52,$H$4:$H$51,H52,$B$4:$B$51,"SALIDA"),SUMIFS($I$4:$I$51,$C$4:$C$51,C52,$D$4:$D$51,D52,$E$4:$E$51,E52,$G$4:$G$51,G52,$H$4:$H$51,H52,$B$4:$B$51,"INGRESO")+SUMIFS($I$4:$I$51,$C$4:$C$51,C52,$D$4:$D$51,D52,$E$4:$E$51,E52,$G$4:$G$51,G52,$H$4:$H$51,H52,$B$4:$B$51,"DE CORTE")-SUMIFS($I$4:$I$51,$C$4:$C$51,C52,$D$4:$D$51,D52,$E$4:$E$51,E52,$G$4:$G$51,G52,$H$4:$H$51,H52,$B$4:$B$51,"SALIDA"))),0) -> 0 | M52: =IF(C52="",0,L52+IF(OR(B52="INGRESO",B52="DE CORTE"),I52,IF(B52="SALIDA",-I52,0))) -> 0
J53: {=IFERROR(INDEX(PRECIOS_COMPLEMENTOS!$C$4:$F$17,MATCH(D53&"_"&E53,PRECIOS_COMPLEMENTOS!$H$4:$H$17,0),IF(OR(H53="S",H53="20cm"),1,IF(OR(H53="M",H53="25cm"),2,IF(OR(H53="L",H53="30cm"),3,IF(OR(H53="XL",H53="35cm"),4,0))))),0)} -> #REF! | K53: =IFERROR(I53*J53,0) -> 0 | L53: =IFERROR(IF(C53="",0,IF(D53="PRETINA",SUMIFS($I$4:$I$52,$C$4:$C$52,C53,$D$4:$D$52,D53,$E$4:$E$52,E53,$F$4:$F$52,F53,$G$4:$G$52,G53,$H$4:$H$52,H53,$B$4:$B$52,"INGRESO")+SUMIFS($I$4:$I$52,$C$4:$C$52,C53,$D$4:$D$52,D53,$E$4:$E$52,E53,$F$4:$F$52,F53,$G$4:$G$52,G53,$H$4:$H$52,H53,$B$4:$B$52,"DE CORTE")-SUMIFS($I$4:$I$52,$C$4:$C$52,C53,$D$4:$D$52,D53,$E$4:$E$52,E53,$F$4:$F$52,F53,$G$4:$G$52,G53,$H$4:$H$52,H53,$B$4:$B$52,"SALIDA"),SUMIFS($I$4:$I$52,$C$4:$C$52,C53,$D$4:$D$52,D53,$E$4:$E$52,E53,$G$4:$G$52,G53,$H$4:$H$52,H53,$B$4:$B$52,"INGRESO")+SUMIFS($I$4:$I$52,$C$4:$C$52,C53,$D$4:$D$52,D53,$E$4:$E$52,E53,$G$4:$G$52,G53,$H$4:$H$52,H53,$B$4:$B$52,"DE CORTE")-SUMIFS($I$4:$I$52,$C$4:$C$52,C53,$D$4:$D$52,D53,$E$4:$E$52,E53,$G$4:$G$52,G53,$H$4:$H$52,H53,$B$4:$B$52,"SALIDA"))),0) -> 0 | M53: =IF(C53="",0,L53+IF(OR(B53="INGRESO",B53="DE CORTE"),I53,IF(B53="SALIDA",-I53,0))) -> 0
J54: {=IFERROR(INDEX(PRECIOS_COMPLEMENTOS!$C$4:$F$17,MATCH(D54&"_"&E54,PRECIOS_COMPLEMENTOS!$H$4:$H$17,0),IF(OR(H54="S",H54="20cm"),1,IF(OR(H54="M",H54="25cm"),2,IF(OR(H54="L",H54="30cm"),3,IF(OR(H54="XL",H54="35cm"),4,0))))),0)} -> #REF! | K54: =IFERROR(I54*J54,0) -> 0 | L54: =IFERROR(IF(C54="",0,IF(D54="PRETINA",SUMIFS($I$4:$I$53,$C$4:$C$53,C54,$D$4:$D$53,D54,$E$4:$E$53,E54,$F$4:$F$53,F54,$G$4:$G$53,G54,$H$4:$H$53,H54,$B$4:$B$53,"INGRESO")+SUMIFS($I$4:$I$53,$C$4:$C$53,C54,$D$4:$D$53,D54,$E$4:$E$53,E54,$F$4:$F$53,F54,$G$4:$G$53,G54,$H$4:$H$53,H54,$B$4:$B$53,"DE CORTE")-SUMIFS($I$4:$I$53,$C$4:$C$53,C54,$D$4:$D$53,D54,$E$4:$E$53,E54,$F$4:$F$53,F54,$G$4:$G$53,G54,$H$4:$H$53,H54,$B$4:$B$53,"SALIDA"),SUMIFS($I$4:$I$53,$C$4:$C$53,C54,$D$4:$D$53,D54,$E$4:$E$53,E54,$G$4:$G$53,G54,$H$4:$H$53,H54,$B$4:$B$53,"INGRESO")+SUMIFS($I$4:$I$53,$C$4:$C$53,C54,$D$4:$D$53,D54,$E$4:$E$53,E54,$G$4:$G$53,G54,$H$4:$H$53,H54,$B$4:$B$53,"DE CORTE")-SUMIFS($I$4:$I$53,$C$4:$C$53,C54,$D$4:$D$53,D54,$E$4:$E$53,E54,$G$4:$G$53,G54,$H$4:$H$53,H54,$B$4:$B$53,"SALIDA"))),0) -> 0 | M54: =IF(C54="",0,L54+IF(OR(B54="INGRESO",B54="DE CORTE"),I54,IF(B54="SALIDA",-I54,0))) -> 0
J55: {=IFERROR(INDEX(PRECIOS_COMPLEMENTOS!$C$4:$F$17,MATCH(D55&"_"&E55,PRECIOS_COMPLEMENTOS!$H$4:$H$17,0),IF(OR(H55="S",H55="20cm"),1,IF(OR(H55="M",H55="25cm"),2,IF(OR(H55="L",H55="30cm"),3,IF(OR(H55="XL",H55="35cm"),4,0))))),0)} -> #REF! | K55: =IFERROR(I55*J55,0) -> 0 | L55: =IFERROR(IF(C55="",0,IF(D55="PRETINA",SUMIFS($I$4:$I$54,$C$4:$C$54,C55,$D$4:$D$54,D55,$E$4:$E$54,E55,$F$4:$F$54,F55,$G$4:$G$54,G55,$H$4:$H$54,H55,$B$4:$B$54,"INGRESO")+SUMIFS($I$4:$I$54,$C$4:$C$54,C55,$D$4:$D$54,D55,$E$4:$E$54,E55,$F$4:$F$54,F55,$G$4:$G$54,G55,$H$4:$H$54,H55,$B$4:$B$54,"DE CORTE")-SUMIFS($I$4:$I$54,$C$4:$C$54,C55,$D$4:$D$54,D55,$E$4:$E$54,E55,$F$4:$F$54,F55,$G$4:$G$54,G55,$H$4:$H$54,H55,$B$4:$B$54,"SALIDA"),SUMIFS($I$4:$I$54,$C$4:$C$54,C55,$D$4:$D$54,D55,$E$4:$E$54,E55,$G$4:$G$54,G55,$H$4:$H$54,H55,$B$4:$B$54,"INGRESO")+SUMIFS($I$4:$I$54,$C$4:$C$54,C55,$D$4:$D$54,D55,$E$4:$E$54,E55,$G$4:$G$54,G55,$H$4:$H$54,H55,$B$4:$B$54,"DE CORTE")-SUMIFS($I$4:$I$54,$C$4:$C$54,C55,$D$4:$D$54,D55,$E$4:$E$54,E55,$G$4:$G$54,G55,$H$4:$H$54,H55,$B$4:$B$54,"SALIDA"))),0) -> 0 | M55: =IF(C55="",0,L55+IF(OR(B55="INGRESO",B55="DE CORTE"),I55,IF(B55="SALIDA",-I55,0))) -> 0
J56: {=IFERROR(INDEX(PRECIOS_COMPLEMENTOS!$C$4:$F$17,MATCH(D56&"_"&E56,PRECIOS_COMPLEMENTOS!$H$4:$H$17,0),IF(OR(H56="S",H56="20cm"),1,IF(OR(H56="M",H56="25cm"),2,IF(OR(H56="L",H56="30cm"),3,IF(OR(H56="XL",H56="35cm"),4,0))))),0)} -> #REF! | K56: =IFERROR(I56*J56,0) -> 0 | L56: =IFERROR(IF(C56="",0,IF(D56="PRETINA",SUMIFS($I$4:$I$55,$C$4:$C$55,C56,$D$4:$D$55,D56,$E$4:$E$55,E56,$F$4:$F$55,F56,$G$4:$G$55,G56,$H$4:$H$55,H56,$B$4:$B$55,"INGRESO")+SUMIFS($I$4:$I$55,$C$4:$C$55,C56,$D$4:$D$55,D56,$E$4:$E$55,E56,$F$4:$F$55,F56,$G$4:$G$55,G56,$H$4:$H$55,H56,$B$4:$B$55,"DE CORTE")-SUMIFS($I$4:$I$55,$C$4:$C$55,C56,$D$4:$D$55,D56,$E$4:$E$55,E56,$F$4:$F$55,F56,$G$4:$G$55,G56,$H$4:$H$55,H56,$B$4:$B$55,"SALIDA"),SUMIFS($I$4:$I$55,$C$4:$C$55,C56,$D$4:$D$55,D56,$E$4:$E$55,E56,$G$4:$G$55,G56,$H$4:$H$55,H56,$B$4:$B$55,"INGRESO")+SUMIFS($I$4:$I$55,$C$4:$C$55,C56,$D$4:$D$55,D56,$E$4:$E$55,E56,$G$4:$G$55,G56,$H$4:$H$55,H56,$B$4:$B$55,"DE CORTE")-SUMIFS($I$4:$I$55,$C$4:$C$55,C56,$D$4:$D$55,D56,$E$4:$E$55,E56,$G$4:$G$55,G56,$H$4:$H$55,H56,$B$4:$B$55,"SALIDA"))),0) -> 0 | M56: =IF(C56="",0,L56+IF(OR(B56="INGRESO",B56="DE CORTE"),I56,IF(B56="SALIDA",-I56,0))) -> 0
J57: {=IFERROR(INDEX(PRECIOS_COMPLEMENTOS!$C$4:$F$17,MATCH(D57&"_"&E57,PRECIOS_COMPLEMENTOS!$H$4:$H$17,0),IF(OR(H57="S",H57="20cm"),1,IF(OR(H57="M",H57="25cm"),2,IF(OR(H57="L",H57="30cm"),3,IF(OR(H57="XL",H57="35cm"),4,0))))),0)} -> #REF! | K57: =IFERROR(I57*J57,0) -> 0 | L57: =IFERROR(IF(C57="",0,IF(D57="PRETINA",SUMIFS($I$4:$I$56,$C$4:$C$56,C57,$D$4:$D$56,D57,$E$4:$E$56,E57,$F$4:$F$56,F57,$G$4:$G$56,G57,$H$4:$H$56,H57,$B$4:$B$56,"INGRESO")+SUMIFS($I$4:$I$56,$C$4:$C$56,C57,$D$4:$D$56,D57,$E$4:$E$56,E57,$F$4:$F$56,F57,$G$4:$G$56,G57,$H$4:$H$56,H57,$B$4:$B$56,"DE CORTE")-SUMIFS($I$4:$I$56,$C$4:$C$56,C57,$D$4:$D$56,D57,$E$4:$E$56,E57,$F$4:$F$56,F57,$G$4:$G$56,G57,$H$4:$H$56,H57,$B$4:$B$56,"SALIDA"),SUMIFS($I$4:$I$56,$C$4:$C$56,C57,$D$4:$D$56,D57,$E$4:$E$56,E57,$G$4:$G$56,G57,$H$4:$H$56,H57,$B$4:$B$56,"INGRESO")+SUMIFS($I$4:$I$56,$C$4:$C$56,C57,$D$4:$D$56,D57,$E$4:$E$56,E57,$G$4:$G$56,G57,$H$4:$H$56,H57,$B$4:$B$56,"DE CORTE")-SUMIFS($I$4:$I$56,$C$4:$C$56,C57,$D$4:$D$56,D57,$E$4:$E$56,E57,$G$4:$G$56,G57,$H$4:$H$56,H57,$B$4:$B$56,"SALIDA"))),0) -> 0 | M57: =IF(C57="",0,L57+IF(OR(B57="INGRESO",B57="DE CORTE"),I57,IF(B57="SALIDA",-I57,0))) -> 0
J58: {=IFERROR(INDEX(PRECIOS_COMPLEMENTOS!$C$4:$F$17,MATCH(D58&"_"&E58,PRECIOS_COMPLEMENTOS!$H$4:$H$17,0),IF(OR(H58="S",H58="20cm"),1,IF(OR(H58="M",H58="25cm"),2,IF(OR(H58="L",H58="30cm"),3,IF(OR(H58="XL",H58="35cm"),4,0))))),0)} -> #REF! | K58: =IFERROR(I58*J58,0) -> 0 | L58: =IFERROR(IF(C58="",0,IF(D58="PRETINA",SUMIFS($I$4:$I$57,$C$4:$C$57,C58,$D$4:$D$57,D58,$E$4:$E$57,E58,$F$4:$F$57,F58,$G$4:$G$57,G58,$H$4:$H$57,H58,$B$4:$B$57,"INGRESO")+SUMIFS($I$4:$I$57,$C$4:$C$57,C58,$D$4:$D$57,D58,$E$4:$E$57,E58,$F$4:$F$57,F58,$G$4:$G$57,G58,$H$4:$H$57,H58,$B$4:$B$57,"DE CORTE")-SUMIFS($I$4:$I$57,$C$4:$C$57,C58,$D$4:$D$57,D58,$E$4:$E$57,E58,$F$4:$F$57,F58,$G$4:$G$57,G58,$H$4:$H$57,H58,$B$4:$B$57,"SALIDA"),SUMIFS($I$4:$I$57,$C$4:$C$57,C58,$D$4:$D$57,D58,$E$4:$E$57,E58,$G$4:$G$57,G58,$H$4:$H$57,H58,$B$4:$B$57,"INGRESO")+SUMIFS($I$4:$I$57,$C$4:$C$57,C58,$D$4:$D$57,D58,$E$4:$E$57,E58,$G$4:$G$57,G58,$H$4:$H$57,H58,$B$4:$B$57,"DE CORTE")-SUMIFS($I$4:$I$57,$C$4:$C$57,C58,$D$4:$D$57,D58,$E$4:$E$57,E58,$G$4:$G$57,G58,$H$4:$H$57,H58,$B$4:$B$57,"SALIDA"))),0) -> 0 | M58: =IF(C58="",0,L58+IF(OR(B58="INGRESO",B58="DE CORTE"),I58,IF(B58="SALIDA",-I58,0))) -> 0
