Workbook
Name LISTA_SERVICIOS_TINTOR: PRECIOS_TINTORERIA!$A$4:$A$15
Name LISTA_HILOS: HILOS!$A$4:$A$22
Name LISTA_PROVEEDORES: PROVEEDORES!$A$4:$A$32
Name LISTA_TIPOS_TEJIDO: PRECIOS_TEJEDURIA!$A$4:$A$22
Name LISTA_PROGRAMAS: PROGRAMAS!$A$4:$A$103
Name LISTA_COLORES: COLORES!$A$4:$A$52

Sheet PROGRAMAS
A1: PROGRAMAS — Master con resumen hilo/tej/tint, comisión y costos totales
A2: Solo resumen. La operación detallada (factura tejeduría, tintorería por color, etc.) se llena en PROGRAMA_DETALLE.
A3: ID PROGRAMA | B3: FECHA INICIO | C3: DESCRIPCIÓN | D3: TIPO HILO | E3: ROLLOS OBJETIVO | F3: KG OBJETIVO | G3: TIPO TEJIDO | H3: CLIENTE | I3: ESTADO | J3: NOTAS | K3: ROLLOS DETALLE (auto) | L3: KG DETALLE (auto) | M3: KG HILO COMPRADO | N3: COSTO HILO TOTAL | O3: N° FACTURA HILO | P3: GUÍA HILO | Q3: KG TEJ ENVIADO | R3: KG TEJ RETORNADO | S3: KG CONOS EXTORNO | T3: KG MERMA TEJ | U3: % MERMA TEJ | V3: KG TINT ENVIADO | W3: KG TINT RETORNADO | X3: KG MERMA TINT (etapa) | Y3: % MERMA TINT | Z3: KG MERMA TOTAL | AA3: % MERMA TOTAL | AB3: COMISIÓN JOSÉ | AC3: ESTADO PAGO COMISIÓN | AD3: FECHA ENTREGA | AE3: INVERSIÓN TOTAL | AF3: COSTO PROM S/./kg | AG3: DÍAS ENTREGA
A4: PIQUE-001 | B4: 46113 | C4: PIQUE | D4: Hilo 30/1 PC | E4: 50 | F4: 1000 | G4: Pique 30/1 | H4: OverShark | I4: CERRADO | K4: =IFERROR(SUMIFS(PROGRAMA_DETALLE!$E$4:$E$503,PROGRAMA_DETALLE!$A$4:$A$503,A4),0) -> 50 | L4: =IFERROR(SUMIFS(PROGRAMA_DETALLE!$F$4:$F$503,PROGRAMA_DETALLE!$A$4:$A$503,A4),0) -> 1000 | M4: =IF(A4="","",IFERROR(SUMIFS(COMPRAS_HILO!$D$4:$D$203,COMPRAS_HILO!$B$4:$B$203,A4),0)) -> 1000 | N4: =IF(A4="","",IFERROR(SUMIFS(COMPRAS_HILO!$H$4:$H$203,COMPRAS_HILO!$B$4:$B$203,A4),0)) -> 10500 | O4: =IFERROR(IF(SUMPRODUCT((COMPRAS_HILO!$B$4:$B$203=A4)*1)=0,"",LOOKUP(2,1/((COMPRAS_HILO!$B$4:$B$203=A4)*(COMPRAS_HILO!$J$4:$J$203<>"")),COMPRAS_HILO!$J$4:$J$203)),"") -> COTTOON-001 | Q4: =IF(A4="","",IFERROR(SUMIFS(PROGRAMA_DETALLE!$H$4:$H$503,PROGRAMA_DETALLE!$A$4:$A$503,A4),0)) -> 1000 | R4: =IF(A4="","",IFERROR(SUMIFS(PROGRAMA_DETALLE!$I$4:$I$503,PROGRAMA_DETALLE!$A$4:$A$503,A4),0)) -> 980 | S4: 5 | T4: =IFERROR(Q4-R4-S4,0) -> 15 | U4: =IFERROR(T4/Q4,0) -> 0.015 | V4: =IF(A4="","",IFERROR(SUMIFS(PROGRAMA_DETALLE!$R$4:$R$503,PROGRAMA_DETALLE!$A$4:$A$503,A4),0)) -> 980 | W4: =IF(A4="","",IFERROR(SUMIFS(PROGRAMA_DETALLE!$S$4:$S$503,PROGRAMA_DETALLE!$A$4:$A$503,A4),0)) -> 890 | X4: =IFERROR(V4-W4,0) -> 90 | Y4: =IFERROR(X4/V4,0) -> 0.091836735 | Z4: =IFERROR(Q4-W4-S4,0) -> 105 | AA4: =IFERROR(Z4/Q4,0) -> 0.105 | AB4: =IFERROR(W4*DASHBOARD!$C$2,0) -> 267 | AC4: PENDIENTE | AD4: 46142 | AE4: =IFERROR(N4+IFERROR(SUMIFS(PROGRAMA_DETALLE!$M$4:$M$503,PROGRAMA_DETALLE!$A$4:$A$503,A4),0)+IFERROR(SUMIFS(PROGRAMA_DETALLE!$Z$4:$Z$503,PROGRAMA_DETALLE!$A$4:$A$503,A4),0)+AB4,0) -> 19171.175 | AF4: =IFERROR(AE4/W4,0) -> 21.540646 | AG4: =IFERROR(AD4-B4,"") -> 29
A5: FULL LYCRA 50/1-001 | B5: 46152 | C5: 50/1 ALGODON 100% | D5: hilo 50/1 cotton +lycra 4% | E5: 25 | F5: 500 | G5: full lycra | H5: OverShark | I5: EN TEJEDURÍA | K5: =IFERROR(SUMIFS(PROGRAMA_DETALLE!$E$4:$E$503,PROGRAMA_DETALLE!$A$4:$A$503,A5),0) -> 25 | L5: =IFERROR(SUMIFS(PROGRAMA_DETALLE!$F$4:$F$503,PROGRAMA_DETALLE!$A$4:$A$503,A5),0) -> 500 | M5: =IF(A5="","",IFERROR(SUMIFS(COMPRAS_HILO!$D$4:$D$203,COMPRAS_HILO!$B$4:$B$203,A5),0)) -> 500 | N5: =IF(A5="","",IFERROR(SUMIFS(COMPRAS_HILO!$H$4:$H$203,COMPRAS_HILO!$B$4:$B$203,A5),0)) -> 9625 | O5: =IFERROR(IF(SUMPRODUCT((COMPRAS_HILO!$B$4:$B$203=A5)*1)=0,"",LOOKUP(2,1/((COMPRAS_HILO!$B$4:$B$203=A5)*(COMPRAS_HILO!$J$4:$J$203<>"")),COMPRAS_HILO!$J$4:$J$203)),"") -> COTTOON-001 | Q5: =IF(A5="","",IFERROR(SUMIFS(PROGRAMA_DETALLE!$H$4:$H$503,PROGRAMA_DETALLE!$A$4:$A$503,A5),0)) -> 500 | R5: =IF(A5="","",IFERROR(SUMIFS(PROGRAMA_DETALLE!$I$4:$I$503,PROGRAMA_DETALLE!$A$4:$A$503,A5),0)) -> 0 | T5: =IFERROR(Q5-R5-S5,0) -> 500 | U5: =IFERROR(T5/Q5,0) -> 1 | V5: =IF(A5="","",IFERROR(SUMIFS(PROGRAMA_DETALLE!$R$4:$R$503,PROGRAMA_DETALLE!$A$4:$A$503,A5),0)) -> 0 | W5: =IF(A5="","",IFERROR(SUMIFS(PROGRAMA_DETALLE!$S$4:$S$503,PROGRAMA_DETALLE!$A$4:$A$503,A5),0)) -> 0 | X5: =IFERROR(V5-W5,0) -> 0 | Y5: =IFERROR(X5/V5,0) -> 0 | Z5: =IFERROR(Q5-W5-S5,0) -> 500 | AA5: =IFERROR(Z5/Q5,0) -> 1 | AB5: =IFERROR(W5*DASHBOARD!$C$2,0) -> 0 | AE5: =IFERROR(N5+IFERROR(SUMIFS(PROGRAMA_DETALLE!$M$4:$M$503,PROGRAMA_DETALLE!$A$4:$A$503,A5),0)+IFERROR(SUMIFS(PROGRAMA_DETALLE!$Z$4:$Z$503,PROGRAMA_DETALLE!$A$4:$A$503,A5),0)+AB5,0) -> 9625 | AF5: =IFERROR(AE5/W5,0) -> 0 | AG5: =IFERROR(AD5-B5,"") -> -46152
A6: frecnh terry - 001 | B6: 46152 | C6: french terry 30/1 | D6: Hilo 30/1 PC | E6: 145 | F6: 2943 | G6: French terry 30/1 | H6: Bravos | I6: EN TEJEDURÍA | K6: =IFERROR(SUMIFS(PROGRAMA_DETALLE!$E$4:$E$503,PROGRAMA_DETALLE!$A$4:$A$503,A6),0) -> 145 | L6: =IFERROR(SUMIFS(PROGRAMA_DETALLE!$F$4:$F$503,PROGRAMA_DETALLE!$A$4:$A$503,A6),0) -> 2900 | M6: =IF(A6="","",IFERROR(SUMIFS(COMPRAS_HILO!$D$4:$D$203,COMPRAS_HILO!$B$4:$B$203,A6),0)) -> 3000 | N6: =IF(A6="","",IFERROR(SUMIFS(COMPRAS_HILO!$H$4:$H$203,COMPRAS_HILO!$B$4:$B$203,A6),0)) -> 31050 | O6: =IFERROR(IF(SUMPRODUCT((COMPRAS_HILO!$B$4:$B$203=A6)*1)=0,"",LOOKUP(2,1/((COMPRAS_HILO!$B$4:$B$203=A6)*(COMPRAS_HILO!$J$4:$J$203<>"")),COMPRAS_HILO!$J$4:$J$203)),"") | Q6: =IF(A6="","",IFERROR(SUMIFS(PROGRAMA_DETALLE!$H$4:$H$503,PROGRAMA_DETALLE!$A$4:$A$503,A6),0)) -> 0 | R6: =IF(A6="","",IFERROR(SUMIFS(PROGRAMA_DETALLE!$I$4:$I$503,PROGRAMA_DETALLE!$A$4:$A$503,A6),0)) -> 0 | T6: =IFERROR(Q6-R6-S6,0) -> 0 | U6: =IFERROR(T6/Q6,0) -> 0 | V6: =IF(A6="","",IFERROR(SUMIFS(PROGRAMA_DETALLE!$R$4:$R$503,PROGRAMA_DETALLE!$A$4:$A$503,A6),0)) -> 0 | W6: =IF(A6="","",IFERROR(SUMIFS(PROGRAMA_DETALLE!$S$4:$S$503,PROGRAMA_DETALLE!$A$4:$A$503,A6),0)) -> 0 | X6: =IFERROR(V6-W6,0) -> 0 | Y6: =IFERROR(X6/V6,0) -> 0 | Z6: =IFERROR(Q6-W6-S6,0) -> 0 | AA6: =IFERROR(Z6/Q6,0) -> 0 | AB6: =IFERROR(W6*DASHBOARD!$C$2,0) -> 0 | AE6: =IFERROR(N6+IFERROR(SUMIFS(PROGRAMA_DETALLE!$M$4:$M$503,PROGRAMA_DETALLE!$A$4:$A$503,A6),0)+IFERROR(SUMIFS(PROGRAMA_DETALLE!$Z$4:$Z$503,PROGRAMA_DETALLE!$A$4:$A$503,A6),0)+AB6,0) -> 31050 | AF6: =IFERROR(AE6/W6,0) -> 0 | AG6: =IFERROR(AD6-B6,"") -> -46152
A7: jersey algodon - 001 | B7: 46313 | C7: ALGODON 30/1 | D7: Hilo 30/1 ALGODON | E7: 33 | F7: 660 | G7: Jersey 30/1 | H7: OverShark | I7: EN TINTORERÍA | K7: =IFERROR(SUMIFS(PROGRAMA_DETALLE!$E$4:$E$503,PROGRAMA_DETALLE!$A$4:$A$503,A7),0) -> 0 | L7: =IFERROR(SUMIFS(PROGRAMA_DETALLE!$F$4:$F$503,PROGRAMA_DETALLE!$A$4:$A$503,A7),0) -> 0 | M7: =IF(A7="","",IFERROR(SUMIFS(COMPRAS_HILO!$D$4:$D$203,COMPRAS_HILO!$B$4:$B$203,A7),0)) -> 660 | N7: =IF(A7="","",IFERROR(SUMIFS(COMPRAS_HILO!$H$4:$H$203,COMPRAS_HILO!$B$4:$B$203,A7),0)) -> 9108 | O7: =IFERROR(IF(SUMPRODUCT((COMPRAS_HILO!$B$4:$B$203=A7)*1)=0,"",LOOKUP(2,1/((COMPRAS_HILO!$B$4:$B$203=A7)*(COMPRAS_HILO!$J$4:$J$203<>"")),COMPRAS_HILO!$J$4:$J$203)),"") | Q7: =IF(A7="","",IFERROR(SUMIFS(PROGRAMA_DETALLE!$H$4:$H$503,PROGRAMA_DETALLE!$A$4:$A$503,A7),0)) -> 0 | R7: =IF(A7="","",IFERROR(SUMIFS(PROGRAMA_DETALLE!$I$4:$I$503,PROGRAMA_DETALLE!$A$4:$A$503,A7),0)) -> 0 | T7: =IFERROR(Q7-R7-S7,0) -> 0 | U7: =IFERROR(T7/Q7,0) -> 0 | V7: =IF(A7="","",IFERROR(SUMIFS(PROGRAMA_DETALLE!$R$4:$R$503,PROGRAMA_DETALLE!$A$4:$A$503,A7),0)) -> 0 | W7: =IF(A7="","",IFERROR(SUMIFS(PROGRAMA_DETALLE!$S$4:$S$503,PROGRAMA_DETALLE!$A$4:$A$503,A7),0)) -> 0 | X7: =IFERROR(V7-W7,0) -> 0 | Y7: =IFERROR(X7/V7,0) -> 0 | Z7: =IFERROR(Q7-W7-S7,0) -> 0 | AA7: =IFERROR(Z7/Q7,0) -> 0 | AB7: =IFERROR(W7*DASHBOARD!$C$2,0) -> 0 | AE7: =IFERROR(N7+IFERROR(SUMIFS(PROGRAMA_DETALLE!$M$4:$M$503,PROGRAMA_DETALLE!$A$4:$A$503,A7),0)+IFERROR(SUMIFS(PROGRAMA_DETALLE!$Z$4:$Z$503,PROGRAMA_DETALLE!$A$4:$A$503,A7),0)+AB7,0) -> 9108 | AF7: =IFERROR(AE7/W7,0) -> 0 | AG7: =IFERROR(AD7-B7,"") -> -46313
A8: rib 1x1- jersey algodon -001 | B8: 46160 | C8: rib complemento ja-001 | D8: Hilo 30/1 ALGODON | E8: 2 | F8: 40 | G8: Rib 1x1 | H8: OverShark | I8: EN TINTORERÍA | K8: =IFERROR(SUMIFS(PROGRAMA_DETALLE!$E$4:$E$503,PROGRAMA_DETALLE!$A$4:$A$503,A8),0) -> 0 | L8: =IFERROR(SUMIFS(PROGRAMA_DETALLE!$F$4:$F$503,PROGRAMA_DETALLE!$A$4:$A$503,A8),0) -> 0 | M8: =IF(A8="","",IFERROR(SUMIFS(COMPRAS_HILO!$D$4:$D$203,COMPRAS_HILO!$B$4:$B$203,A8),0)) -> 0 | N8: =IF(A8="","",IFERROR(SUMIFS(COMPRAS_HILO!$H$4:$H$203,COMPRAS_HILO!$B$4:$B$203,A8),0)) -> 0 | O8: =IFERROR(IF(SUMPRODUCT((COMPRAS_HILO!$B$4:$B$203=A8)*1)=0,"",LOOKUP(2,1/((COMPRAS_HILO!$B$4:$B$203=A8)*(COMPRAS_HILO!$J$4:$J$203<>"")),COMPRAS_HILO!$J$4:$J$203)),"") | Q8: =IF(A8="","",IFERROR(SUMIFS(PROGRAMA_DETALLE!$H$4:$H$503,PROGRAMA_DETALLE!$A$4:$A$503,A8),0)) -> 0 | R8: =IF(A8="","",IFERROR(SUMIFS(PROGRAMA_DETALLE!$I$4:$I$503,PROGRAMA_DETALLE!$A$4:$A$503,A8),0)) -> 0 | T8: =IFERROR(Q8-R8-S8,0) -> 0 | U8: =IFERROR(T8/Q8,0) -> 0 | V8: =IF(A8="","",IFERROR(SUMIFS(PROGRAMA_DETALLE!$R$4:$R$503,PROGRAMA_DETALLE!$A$4:$A$503,A8),0)) -> 0 | W8: =IF(A8="","",IFERROR(SUMIFS(PROGRAMA_DETALLE!$S$4:$S$503,PROGRAMA_DETALLE!$A$4:$A$503,A8),0)) -> 0 | X8: =IFERROR(V8-W8,0) -> 0 | Y8: =IFERROR(X8/V8,0) -> 0 | Z8: =IFERROR(Q8-W8-S8,0) -> 0 | AA8: =IFERROR(Z8/Q8,0) -> 0 | AB8: =IFERROR(W8*DASHBOARD!$C$2,0) -> 0 | AE8: =IFERROR(N8+IFERROR(SUMIFS(PROGRAMA_DETALLE!$M$4:$M$503,PROGRAMA_DETALLE!$A$4:$A$503,A8),0)+IFERROR(SUMIFS(PROGRAMA_DETALLE!$Z$4:$Z$503,PROGRAMA_DETALLE!$A$4:$A$503,A8),0)+AB8,0) -> 0 | AF8: =IFERROR(AE8/W8,0) -> 0 | AG8: =IFERROR(AD8-B8,"") -> -46160
K9: =IFERROR(SUMIFS(PROGRAMA_DETALLE!$E$4:$E$503,PROGRAMA_DETALLE!$A$4:$A$503,A9),0) -> 0 | L9: =IFERROR(SUMIFS(PROGRAMA_DETALLE!$F$4:$F$503,PROGRAMA_DETALLE!$A$4:$A$503,A9),0) -> 0 | M9: =IF(A9="","",IFERROR(SUMIFS(COMPRAS_HILO!$D$4:$D$203,COMPRAS_HILO!$B$4:$B$203,A9),0)) | N9: =IF(A9="","",IFERROR(SUMIFS(COMPRAS_HILO!$H$4:$H$203,COMPRAS_HILO!$B$4:$B$203,A9),0)) | O9: =IFERROR(IF(SUMPRODUCT((COMPRAS_HILO!$B$4:$B$203=A9)*1)=0,"",LOOKUP(2,1/((COMPRAS_HILO!$B$4:$B$203=A9)*(COMPRAS_HILO!$J$4:$J$203<>"")),COMPRAS_HILO!$J$4:$J$203)),"") | Q9: =IF(A9="","",IFERROR(SUMIFS(PROGRAMA_DETALLE!$H$4:$H$503,PROGRAMA_DETALLE!$A$4:$A$503,A9),0)) | R9: =IF(A9="","",IFERROR(SUMIFS(PROGRAMA_DETALLE!$I$4:$I$503,PROGRAMA_DETALLE!$A$4:$A$503,A9),0)) | T9: =IFERROR(Q9-R9-S9,0) -> 0 | U9: =IFERROR(T9/Q9,0) -> 0 | V9: =IF(A9="","",IFERROR(SUMIFS(PROGRAMA_DETALLE!$R$4:$R$503,PROGRAMA_DETALLE!$A$4:$A$503,A9),0)) | W9: =IF(A9="","",IFERROR(SUMIFS(PROGRAMA_DETALLE!$S$4:$S$503,PROGRAMA_DETALLE!$A$4:$A$503,A9),0)) | X9: =IFERROR(V9-W9,0) -> 0 | Y9: =IFERROR(X9/V9,0) -> 0 | Z9: =IFERROR(Q9-W9-S9,0) -> 0 | AA9: =IFERROR(Z9/Q9,0) -> 0 | AB9: =IFERROR(W9*DASHBOARD!$C$2,0) -> 0 | AE9: =IFERROR(N9+IFERROR(SUMIFS(PROGRAMA_DETALLE!$M$4:$M$503,PROGRAMA_DETALLE!$A$4:$A$503,A9),0)+IFERROR(SUMIFS(PROGRAMA_DETALLE!$Z$4:$Z$503,PROGRAMA_DETALLE!$A$4:$A$503,A9),0)+AB9,0) -> 0 | AF9: =IFERROR(AE9/W9,0) -> 0 | AG9: =IFERROR(AD9-B9,"") -> 0
K10: =IFERROR(SUMIFS(PROGRAMA_DETALLE!$E$4:$E$503,PROGRAMA_DETALLE!$A$4:$A$503,A10),0) -> 0 | L10: =IFERROR(SUMIFS(PROGRAMA_DETALLE!$F$4:$F$503,PROGRAMA_DETALLE!$A$4:$A$503,A10),0) -> 0 | M10: =IF(A10="","",IFERROR(SUMIFS(COMPRAS_HILO!$D$4:$D$203,COMPRAS_HILO!$B$4:$B$203,A10),0)) | N10: =IF(A10="","",IFERROR(SUMIFS(COMPRAS_HILO!$H$4:$H$203,COMPRAS_HILO!$B$4:$B$203,A10),0)) | O10: =IFERROR(IF(SUMPRODUCT((COMPRAS_HILO!$B$4:$B$203=A10)*1)=0,"",LOOKUP(2,1/((COMPRAS_HILO!$B$4:$B$203=A10)*(COMPRAS_HILO!$J$4:$J$203<>"")),COMPRAS_HILO!$J$4:$J$203)),"") | Q10: =IF(A10="","",IFERROR(SUMIFS(PROGRAMA_DETALLE!$H$4:$H$503,PROGRAMA_DETALLE!$A$4:$A$503,A10),0)) | R10: =IF(A10="","",IFERROR(SUMIFS(PROGRAMA_DETALLE!$I$4:$I$503,PROGRAMA_DETALLE!$A$4:$A$503,A10),0)) | T10: =IFERROR(Q10-R10-S10,0) -> 0 | U10: =IFERROR(T10/Q10,0) -> 0 | V10: =IF(A10="","",IFERROR(SUMIFS(PROGRAMA_DETALLE!$R$4:$R$503,PROGRAMA_DETALLE!$A$4:$A$503,A10),0)) | W10: =IF(A10="","",IFERROR(SUMIFS(PROGRAMA_DETALLE!$S$4:$S$503,PROGRAMA_DETALLE!$A$4:$A$503,A10),0)) | X10: =IFERROR(V10-W10,0) -> 0 | Y10: =IFERROR(X10/V10,0) -> 0 | Z10: =IFERROR(Q10-W10-S10,0) -> 0 | AA10: =IFERROR(Z10/Q10,0) -> 0 | AB10: =IFERROR(W10*DASHBOARD!$C$2,0) -> 0 | AE10: =IFERROR(N10+IFERROR(SUMIFS(PROGRAMA_DETALLE!$M$4:$M$503,PROGRAMA_DETALLE!$A$4:$A$503,A10),0)+IFERROR(SUMIFS(PROGRAMA_DETALLE!$Z$4:$Z$503,PROGRAMA_DETALLE!$A$4:$A$503,A10),0)+AB10,0) -> 0 | AF10: =IFERROR(AE10/W10,0) -> 0 | AG10: =IFERROR(AD10-B10,"") -> 0
K11: =IFERROR(SUMIFS(PROGRAMA_DETALLE!$E$4:$E$503,PROGRAMA_DETALLE!$A$4:$A$503,A11),0) -> 0 | L11: =IFERROR(SUMIFS(PROGRAMA_DETALLE!$F$4:$F$503,PROGRAMA_DETALLE!$A$4:$A$503,A11),0) -> 0 | M11: =IF(A11="","",IFERROR(SUMIFS(COMPRAS_HILO!$D$4:$D$203,COMPRAS_HILO!$B$4:$B$203,A11),0)) | N11: =IF(A11="","",IFERROR(SUMIFS(COMPRAS_HILO!$H$4:$H$203,COMPRAS_HILO!$B$4:$B$203,A11),0)) | O11: =IFERROR(IF(SUMPRODUCT((COMPRAS_HILO!$B$4:$B$203=A11)*1)=0,"",LOOKUP(2,1/((COMPRAS_HILO!$B$4:$B$203=A11)*(COMPRAS_HILO!$J$4:$J$203<>"")),COMPRAS_HILO!$J$4:$J$203)),"") | Q11: =IF(A11="","",IFERROR(SUMIFS(PROGRAMA_DETALLE!$H$4:$H$503,PROGRAMA_DETALLE!$A$4:$A$503,A11),0)) | R11: =IF(A11="","",IFERROR(SUMIFS(PROGRAMA_DETALLE!$I$4:$I$503,PROGRAMA_DETALLE!$A$4:$A$503,A11),0)) | T11: =IFERROR(Q11-R11-S11,0) -> 0 | U11: =IFERROR(T11/Q11,0) -> 0 | V11: =IF(A11="","",IFERROR(SUMIFS(PROGRAMA_DETALLE!$R$4:$R$503,PROGRAMA_DETALLE!$A$4:$A$503,A11),0)) | W11: =IF(A11="","",IFERROR(SUMIFS(PROGRAMA_DETALLE!$S$4:$S$503,PROGRAMA_DETALLE!$A$4:$A$503,A11),0)) | X11: =IFERROR(V11-W11,0) -> 0 | Y11: =IFERROR(X11/V11,0) -> 0 | Z11: =IFERROR(Q11-W11-S11,0) -> 0 | AA11: =IFERROR(Z11/Q11,0) -> 0 | AB11: =IFERROR(W11*DASHBOARD!$C$2,0) -> 0 | AE11: =IFERROR(N11+IFERROR(SUMIFS(PROGRAMA_DETALLE!$M$4:$M$503,PROGRAMA_DETALLE!$A$4:$A$503,A11),0)+IFERROR(SUMIFS(PROGRAMA_DETALLE!$Z$4:$Z$503,PROGRAMA_DETALLE!$A$4:$A$503,A11),0)+AB11,0) -> 0 | AF11: =IFERROR(AE11/W11,0) -> 0 | AG11: =IFERROR(AD11-B11,"") -> 0
K12: =IFERROR(SUMIFS(PROGRAMA_DETALLE!$E$4:$E$503,PROGRAMA_DETALLE!$A$4:$A$503,A12),0) -> 0 | L12: =IFERROR(SUMIFS(PROGRAMA_DETALLE!$F$4:$F$503,PROGRAMA_DETALLE!$A$4:$A$503,A12),0) -> 0 | M12: =IF(A12="","",IFERROR(SUMIFS(COMPRAS_HILO!$D$4:$D$203,COMPRAS_HILO!$B$4:$B$203,A12),0)) | N12: =IF(A12="","",IFERROR(SUMIFS(COMPRAS_HILO!$H$4:$H$203,COMPRAS_HILO!$B$4:$B$203,A12),0)) | O12: =IFERROR(IF(SUMPRODUCT((COMPRAS_HILO!$B$4:$B$203=A12)*1)=0,"",LOOKUP(2,1/((COMPRAS_HILO!$B$4:$B$203=A12)*(COMPRAS_HILO!$J$4:$J$203<>"")),COMPRAS_HILO!$J$4:$J$203)),"") | Q12: =IF(A12="","",IFERROR(SUMIFS(PROGRAMA_DETALLE!$H$4:$H$503,PROGRAMA_DETALLE!$A$4:$A$503,A12),0)) | R12: =IF(A12="","",IFERROR(SUMIFS(PROGRAMA_DETALLE!$I$4:$I$503,PROGRAMA_DETALLE!$A$4:$A$503,A12),0)) | T12: =IFERROR(Q12-R12-S12,0) -> 0 | U12: =IFERROR(T12/Q12,0) -> 0 | V12: =IF(A12="","",IFERROR(SUMIFS(PROGRAMA_DETALLE!$R$4:$R$503,PROGRAMA_DETALLE!$A$4:$A$503,A12),0)) | W12: =IF(A12="","",IFERROR(SUMIFS(PROGRAMA_DETALLE!$S$4:$S$503,PROGRAMA_DETALLE!$A$4:$A$503,A12),0)) | X12: =IFERROR(V12-W12,0) -> 0 | Y12: =IFERROR(X12/V12,0) -> 0 | Z12: =IFERROR(Q12-W12-S12,0) -> 0 | AA12: =IFERROR(Z12/Q12,0) -> 0 | AB12: =IFERROR(W12*DASHBOARD!$C$2,0) -> 0 | AE12: =IFERROR(N12+IFERROR(SUMIFS(PROGRAMA_DETALLE!$M$4:$M$503,PROGRAMA_DETALLE!$A$4:$A$503,A12),0)+IFERROR(SUMIFS(PROGRAMA_DETALLE!$Z$4:$Z$503,PROGRAMA_DETALLE!$A$4:$A$503,A12),0)+AB12,0) -> 0 | AF12: =IFERROR(AE12/W12,0) -> 0 | AG12: =IFERROR(AD12-B12,"") -> 0
K13: =IFERROR(SUMIFS(PROGRAMA_DETALLE!$E$4:$E$503,PROGRAMA_DETALLE!$A$4:$A$503,A13),0) -> 0 | L13: =IFERROR(SUMIFS(PROGRAMA_DETALLE!$F$4:$F$503,PROGRAMA_DETALLE!$A$4:$A$503,A13),0) -> 0 | M13: =IF(A13="","",IFERROR(SUMIFS(COMPRAS_HILO!$D$4:$D$203,COMPRAS_HILO!$B$4:$B$203,A13),0)) | N13: =IF(A13="","",IFERROR(SUMIFS(COMPRAS_HILO!$H$4:$H$203,COMPRAS_HILO!$B$4:$B$203,A13),0)) | O13: =IFERROR(IF(SUMPRODUCT((COMPRAS_HILO!$B$4:$B$203=A13)*1)=0,"",LOOKUP(2,1/((COMPRAS_HILO!$B$4:$B$203=A13)*(COMPRAS_HILO!$J$4:$J$203<>"")),COMPRAS_HILO!$J$4:$J$203)),"") | Q13: =IF(A13="","",IFERROR(SUMIFS(PROGRAMA_DETALLE!$H$4:$H$503,PROGRAMA_DETALLE!$A$4:$A$503,A13),0)) | R13: =IF(A13="","",IFERROR(SUMIFS(PROGRAMA_DETALLE!$I$4:$I$503,PROGRAMA_DETALLE!$A$4:$A$503,A13),0)) | T13: =IFERROR(Q13-R13-S13,0) -> 0 | U13: =IFERROR(T13/Q13,0) -> 0 | V13: =IF(A13="","",IFERROR(SUMIFS(PROGRAMA_DETALLE!$R$4:$R$503,PROGRAMA_DETALLE!$A$4:$A$503,A13),0)) | W13: =IF(A13="","",IFERROR(SUMIFS(PROGRAMA_DETALLE!$S$4:$S$503,PROGRAMA_DETALLE!$A$4:$A$503,A13),0)) | X13: =IFERROR(V13-W13,0) -> 0 | Y13: =IFERROR(X13/V13,0) -> 0 | Z13: =IFERROR(Q13-W13-S13,0) -> 0 | AA13: =IFERROR(Z13/Q13,0) -> 0 | AB13: =IFERROR(W13*DASHBOARD!$C$2,0) -> 0 | AE13: =IFERROR(N13+IFERROR(SUMIFS(PROGRAMA_DETALLE!$M$4:$M$503,PROGRAMA_DETALLE!$A$4:$A$503,A13),0)+IFERROR(SUMIFS(PROGRAMA_DETALLE!$Z$4:$Z$503,PROGRAMA_DETALLE!$A$4:$A$503,A13),0)+AB13,0) -> 0 | AF13: =IFERROR(AE13/W13,0) -> 0 | AG13: =IFERROR(AD13-B13,"") -> 0
K14: =IFERROR(SUMIFS(PROGRAMA_DETALLE!$E$4:$E$503,PROGRAMA_DETALLE!$A$4:$A$503,A14),0) -> 0 | L14: =IFERROR(SUMIFS(PROGRAMA_DETALLE!$F$4:$F$503,PROGRAMA_DETALLE!$A$4:$A$503,A14),0) -> 0 | M14: =IF(A14="","",IFERROR(SUMIFS(COMPRAS_HILO!$D$4:$D$203,COMPRAS_HILO!$B$4:$B$203,A14),0)) | N14: =IF(A14="","",IFERROR(SUMIFS(COMPRAS_HILO!$H$4:$H$203,COMPRAS_HILO!$B$4:$B$203,A14),0)) | O14: =IFERROR(IF(SUMPRODUCT((COMPRAS_HILO!$B$4:$B$203=A14)*1)=0,"",LOOKUP(2,1/((COMPRAS_HILO!$B$4:$B$203=A14)*(COMPRAS_HILO!$J$4:$J$203<>"")),COMPRAS_HILO!$J$4:$J$203)),"") | Q14: =IF(A14="","",IFERROR(SUMIFS(PROGRAMA_DETALLE!$H$4:$H$503,PROGRAMA_DETALLE!$A$4:$A$503,A14),0)) | R14: =IF(A14="","",IFERROR(SUMIFS(PROGRAMA_DETALLE!$I$4:$I$503,PROGRAMA_DETALLE!$A$4:$A$503,A14),0)) | T14: =IFERROR(Q14-R14-S14,0) -> 0 | U14: =IFERROR(T14/Q14,0) -> 0 | V14: =IF(A14="","",IFERROR(SUMIFS(PROGRAMA_DETALLE!$R$4:$R$503,PROGRAMA_DETALLE!$A$4:$A$503,A14),0)) | W14: =IF(A14="","",IFERROR(SUMIFS(PROGRAMA_DETALLE!$S$4:$S$503,PROGRAMA_DETALLE!$A$4:$A$503,A14),0)) | X14: =IFERROR(V14-W14,0) -> 0 | Y14: =IFERROR(X14/V14,0) -> 0 | Z14: =IFERROR(Q14-W14-S14,0) -> 0 | AA14: =IFERROR(Z14/Q14,0) -> 0 | AB14: =IFERROR(W14*DASHBOARD!$C$2,0) -> 0 | AE14: =IFERROR(N14+IFERROR(SUMIFS(PROGRAMA_DETALLE!$M$4:$M$503,PROGRAMA_DETALLE!$A$4:$A$503,A14),0)+IFERROR(SUMIFS(PROGRAMA_DETALLE!$Z$4:$Z$503,PROGRAMA_DETALLE!$A$4:$A$503,A14),0)+AB14,0) -> 0 | AF14: =IFERROR(AE14/W14,0) -> 0 | AG14: =IFERROR(AD14-B14,"") -> 0
K15: =IFERROR(SUMIFS(PROGRAMA_DETALLE!$E$4:$E$503,PROGRAMA_DETALLE!$A$4:$A$503,A15),0) -> 0 | L15: =IFERROR(SUMIFS(PROGRAMA_DETALLE!$F$4:$F$503,PROGRAMA_DETALLE!$A$4:$A$503,A15),0) -> 0 | M15: =IF(A15="","",IFERROR(SUMIFS(COMPRAS_HILO!$D$4:$D$203,COMPRAS_HILO!$B$4:$B$203,A15),0)) | N15: =IF(A15="","",IFERROR(SUMIFS(COMPRAS_HILO!$H$4:$H$203,COMPRAS_HILO!$B$4:$B$203,A15),0)) | O15: =IFERROR(IF(SUMPRODUCT((COMPRAS_HILO!$B$4:$B$203=A15)*1)=0,"",LOOKUP(2,1/((COMPRAS_HILO!$B$4:$B$203=A15)*(COMPRAS_HILO!$J$4:$J$203<>"")),COMPRAS_HILO!$J$4:$J$203)),"") | Q15: =IF(A15="","",IFERROR(SUMIFS(PROGRAMA_DETALLE!$H$4:$H$503,PROGRAMA_DETALLE!$A$4:$A$503,A15),0)) | R15: =IF(A15="","",IFERROR(SUMIFS(PROGRAMA_DETALLE!$I$4:$I$503,PROGRAMA_DETALLE!$A$4:$A$503,A15),0)) | T15: =IFERROR(Q15-R15-S15,0) -> 0 | U15: =IFERROR(T15/Q15,0) -> 0 | V15: =IF(A15="","",IFERROR(SUMIFS(PROGRAMA_DETALLE!$R$4:$R$503,PROGRAMA_DETALLE!$A$4:$A$503,A15),0)) | W15: =IF(A15="","",IFERROR(SUMIFS(PROGRAMA_DETALLE!$S$4:$S$503,PROGRAMA_DETALLE!$A$4:$A$503,A15),0)) | X15: =IFERROR(V15-W15,0) -> 0 | Y15: =IFERROR(X15/V15,0) -> 0 | Z15: =IFERROR(Q15-W15-S15,0) -> 0 | AA15: =IFERROR(Z15/Q15,0) -> 0 | AB15: =IFERROR(W15*DASHBOARD!$C$2,0) -> 0 | AE15: =IFERROR(N15+IFERROR(SUMIFS(PROGRAMA_DETALLE!$M$4:$M$503,PROGRAMA_DETALLE!$A$4:$A$503,A15),0)+IFERROR(SUMIFS(PROGRAMA_DETALLE!$Z$4:$Z$503,PROGRAMA_DETALLE!$A$4:$A$503,A15),0)+AB15,0) -> 0 | AF15: =IFERROR(AE15/W15,0) -> 0 | AG15: =IFERROR(AD15-B15,"") -> 0
K16: =IFERROR(SUMIFS(PROGRAMA_DETALLE!$E$4:$E$503,PROGRAMA_DETALLE!$A$4:$A$503,A16),0) -> 0 | L16: =IFERROR(SUMIFS(PROGRAMA_DETALLE!$F$4:$F$503,PROGRAMA_DETALLE!$A$4:$A$503,A16),0) -> 0 | M16: =IF(A16="","",IFERROR(SUMIFS(COMPRAS_HILO!$D$4:$D$203,COMPRAS_HILO!$B$4:$B$203,A16),0)) | N16: =IF(A16="","",IFERROR(SUMIFS(COMPRAS_HILO!$H$4:$H$203,COMPRAS_HILO!$B$4:$B$203,A16),0)) | O16: =IFERROR(IF(SUMPRODUCT((COMPRAS_HILO!$B$4:$B$203=A16)*1)=0,"",LOOKUP(2,1/((COMPRAS_HILO!$B$4:$B$203=A16)*(COMPRAS_HILO!$J$4:$J$203<>"")),COMPRAS_HILO!$J$4:$J$203)),"") | Q16: =IF(A16="","",IFERROR(SUMIFS(PROGRAMA_DETALLE!$H$4:$H$503,PROGRAMA_DETALLE!$A$4:$A$503,A16),0)) | R16: =IF(A16="","",IFERROR(SUMIFS(PROGRAMA_DETALLE!$I$4:$I$503,PROGRAMA_DETALLE!$A$4:$A$503,A16),0)) | T16: =IFERROR(Q16-R16-S16,0) -> 0 | U16: =IFERROR(T16/Q16,0) -> 0 | V16: =IF(A16="","",IFERROR(SUMIFS(PROGRAMA_DETALLE!$R$4:$R$503,PROGRAMA_DETALLE!$A$4:$A$503,A16),0)) | W16: =IF(A16="","",IFERROR(SUMIFS(PROGRAMA_DETALLE!$S$4:$S$503,PROGRAMA_DETALLE!$A$4:$A$503,A16),0)) | X16: =IFERROR(V16-W16,0) -> 0 | Y16: =IFERROR(X16/V16,0) -> 0 | Z16: =IFERROR(Q16-W16-S16,0) -> 0 | AA16: =IFERROR(Z16/Q16,0) -> 0 | AB16: =IFERROR(W16*DASHBOARD!$C$2,0) -> 0 | AE16: =IFERROR(N16+IFERROR(SUMIFS(PROGRAMA_DETALLE!$M$4:$M$503,PROGRAMA_DETALLE!$A$4:$A$503,A16),0)+IFERROR(SUMIFS(PROGRAMA_DETALLE!$Z$4:$Z$503,PROGRAMA_DETALLE!$A$4:$A$503,A16),0)+AB16,0) -> 0 | AF16: =IFERROR(AE16/W16,0) -> 0 | AG16: =IFERROR(AD16-B16,"") -> 0
K17: =IFERROR(SUMIFS(PROGRAMA_DETALLE!$E$4:$E$503,PROGRAMA_DETALLE!$A$4:$A$503,A17),0) -> 0 | L17: =IFERROR(SUMIFS(PROGRAMA_DETALLE!$F$4:$F$503,PROGRAMA_DETALLE!$A$4:$A$503,A17),0) -> 0 | M17: =IF(A17="","",IFERROR(SUMIFS(COMPRAS_HILO!$D$4:$D$203,COMPRAS_HILO!$B$4:$B$203,A17),0)) | N17: =IF(A17="","",IFERROR(SUMIFS(COMPRAS_HILO!$H$4:$H$203,COMPRAS_HILO!$B$4:$B$203,A17),0)) | O17: =IFERROR(IF(SUMPRODUCT((COMPRAS_HILO!$B$4:$B$203=A17)*1)=0,"",LOOKUP(2,1/((COMPRAS_HILO!$B$4:$B$203=A17)*(COMPRAS_HILO!$J$4:$J$203<>"")),COMPRAS_HILO!$J$4:$J$203)),"") | Q17: =IF(A17="","",IFERROR(SUMIFS(PROGRAMA_DETALLE!$H$4:$H$503,PROGRAMA_DETALLE!$A$4:$A$503,A17),0)) | R17: =IF(A17="","",IFERROR(SUMIFS(PROGRAMA_DETALLE!$I$4:$I$503,PROGRAMA_DETALLE!$A$4:$A$503,A17),0)) | T17: =IFERROR(Q17-R17-S17,0) -> 0 | U17: =IFERROR(T17/Q17,0) -> 0 | V17: =IF(A17="","",IFERROR(SUMIFS(PROGRAMA_DETALLE!$R$4:$R$503,PROGRAMA_DETALLE!$A$4:$A$503,A17),0)) | W17: =IF(A17="","",IFERROR(SUMIFS(PROGRAMA_DETALLE!$S$4:$S$503,PROGRAMA_DETALLE!$A$4:$A$503,A17),0)) | X17: =IFERROR(V17-W17,0) -> 0 | Y17: =IFERROR(X17/V17,0) -> 0 | Z17: =IFERROR(Q17-W17-S17,0) -> 0 | AA17: =IFERROR(Z17/Q17,0) -> 0 | AB17: =IFERROR(W17*DASHBOARD!$C$2,0) -> 0 | AE17: =IFERROR(N17+IFERROR(SUMIFS(PROGRAMA_DETALLE!$M$4:$M$503,PROGRAMA_DETALLE!$A$4:$A$503,A17),0)+IFERROR(SUMIFS(PROGRAMA_DETALLE!$Z$4:$Z$503,PROGRAMA_DETALLE!$A$4:$A$503,A17),0)+AB17,0) -> 0 | AF17: =IFERROR(AE17/W17,0) -> 0 | AG17: =IFERROR(AD17-B17,"") -> 0
K18: =IFERROR(SUMIFS(PROGRAMA_DETALLE!$E$4:$E$503,PROGRAMA_DETALLE!$A$4:$A$503,A18),0) -> 0 | L18: =IFERROR(SUMIFS(PROGRAMA_DETALLE!$F$4:$F$503,PROGRAMA_DETALLE!$A$4:$A$503,A18),0) -> 0 | M18: =IF(A18="","",IFERROR(SUMIFS(COMPRAS_HILO!$D$4:$D$203,COMPRAS_HILO!$B$4:$B$203,A18),0)) | N18: =IF(A18="","",IFERROR(SUMIFS(COMPRAS_HILO!$H$4:$H$203,COMPRAS_HILO!$B$4:$B$203,A18),0)) | O18: =IFERROR(IF(SUMPRODUCT((COMPRAS_HILO!$B$4:$B$203=A18)*1)=0,"",LOOKUP(2,1/((COMPRAS_HILO!$B$4:$B$203=A18)*(COMPRAS_HILO!$J$4:$J$203<>"")),COMPRAS_HILO!$J$4:$J$203)),"") | Q18: =IF(A18="","",IFERROR(SUMIFS(PROGRAMA_DETALLE!$H$4:$H$503,PROGRAMA_DETALLE!$A$4:$A$503,A18),0)) | R18: =IF(A18="","",IFERROR(SUMIFS(PROGRAMA_DETALLE!$I$4:$I$503,PROGRAMA_DETALLE!$A$4:$A$503,A18),0)) | T18: =IFERROR(Q18-R18-S18,0) -> 0 | U18: =IFERROR(T18/Q18,0) -> 0 | V18: =IF(A18="","",IFERROR(SUMIFS(PROGRAMA_DETALLE!$R$4:$R$503,PROGRAMA_DETALLE!$A$4:$A$503,A18),0)) | W18: =IF(A18="","",IFERROR(SUMIFS(PROGRAMA_DETALLE!$S$4:$S$503,PROGRAMA_DETALLE!$A$4:$A$503,A18),0)) | X18: =IFERROR(V18-W18,0) -> 0 | Y18: =IFERROR(X18/V18,0) -> 0 | Z18: =IFERROR(Q18-W18-S18,0) -> 0 | AA18: =IFERROR(Z18/Q18,0) -> 0 | AB18: =IFERROR(W18*DASHBOARD!$C$2,0) -> 0 | AE18: =IFERROR(N18+IFERROR(SUMIFS(PROGRAMA_DETALLE!$M$4:$M$503,PROGRAMA_DETALLE!$A$4:$A$503,A18),0)+IFERROR(SUMIFS(PROGRAMA_DETALLE!$Z$4:$Z$503,PROGRAMA_DETALLE!$A$4:$A$503,A18),0)+AB18,0) -> 0 | AF18: =IFERROR(AE18/W18,0) -> 0 | AG18: =IFERROR(AD18-B18,"") -> 0
K19: =IFERROR(SUMIFS(PROGRAMA_DETALLE!$E$4:$E$503,PROGRAMA_DETALLE!$A$4:$A$503,A19),0) -> 0 | L19: =IFERROR(SUMIFS(PROGRAMA_DETALLE!$F$4:$F$503,PROGRAMA_DETALLE!$A$4:$A$503,A19),0) -> 0 | M19: =IF(A19="","",IFERROR(SUMIFS(COMPRAS_HILO!$D$4:$D$203,COMPRAS_HILO!$B$4:$B$203,A19),0)) | N19: =IF(A19="","",IFERROR(SUMIFS(COMPRAS_HILO!$H$4:$H$203,COMPRAS_HILO!$B$4:$B$203,A19),0)) | O19: =IFERROR(IF(SUMPRODUCT((COMPRAS_HILO!$B$4:$B$203=A19)*1)=0,"",LOOKUP(2,1/((COMPRAS_HILO!$B$4:$B$203=A19)*(COMPRAS_HILO!$J$4:$J$203<>"")),COMPRAS_HILO!$J$4:$J$203)),"") | Q19: =IF(A19="","",IFERROR(SUMIFS(PROGRAMA_DETALLE!$H$4:$H$503,PROGRAMA_DETALLE!$A$4:$A$503,A19),0)) | R19: =IF(A19="","",IFERROR(SUMIFS(PROGRAMA_DETALLE!$I$4:$I$503,PROGRAMA_DETALLE!$A$4:$A$503,A19),0)) | T19: =IFERROR(Q19-R19-S19,0) -> 0 | U19: =IFERROR(T19/Q19,0) -> 0 | V19: =IF(A19="","",IFERROR(SUMIFS(PROGRAMA_DETALLE!$R$4:$R$503,PROGRAMA_DETALLE!$A$4:$A$503,A19),0)) | W19: =IF(A19="","",IFERROR(SUMIFS(PROGRAMA_DETALLE!$S$4:$S$503,PROGRAMA_DETALLE!$A$4:$A$503,A19),0)) | X19: =IFERROR(V19-W19,0) -> 0 | Y19: =IFERROR(X19/V19,0) -> 0 | Z19: =IFERROR(Q19-W19-S19,0) -> 0 | AA19: =IFERROR(Z19/Q19,0) -> 0 | AB19: =IFERROR(W19*DASHBOARD!$C$2,0) -> 0 | AE19: =IFERROR(N19+IFERROR(SUMIFS(PROGRAMA_DETALLE!$M$4:$M$503,PROGRAMA_DETALLE!$A$4:$A$503,A19),0)+IFERROR(SUMIFS(PROGRAMA_DETALLE!$Z$4:$Z$503,PROGRAMA_DETALLE!$A$4:$A$503,A19),0)+AB19,0) -> 0 | AF19: =IFERROR(AE19/W19,0) -> 0 | AG19: =IFERROR(AD19-B19,"") -> 0
K20: =IFERROR(SUMIFS(PROGRAMA_DETALLE!$E$4:$E$503,PROGRAMA_DETALLE!$A$4:$A$503,A20),0) -> 0 | L20: =IFERROR(SUMIFS(PROGRAMA_DETALLE!$F$4:$F$503,PROGRAMA_DETALLE!$A$4:$A$503,A20),0) -> 0 | M20: =IF(A20="","",IFERROR(SUMIFS(COMPRAS_HILO!$D$4:$D$203,COMPRAS_HILO!$B$4:$B$203,A20),0)) | N20: =IF(A20="","",IFERROR(SUMIFS(COMPRAS_HILO!$H$4:$H$203,COMPRAS_HILO!$B$4:$B$203,A20),0)) | O20: =IFERROR(IF(SUMPRODUCT((COMPRAS_HILO!$B$4:$B$203=A20)*1)=0,"",LOOKUP(2,1/((COMPRAS_HILO!$B$4:$B$203=A20)*(COMPRAS_HILO!$J$4:$J$203<>"")),COMPRAS_HILO!$J$4:$J$203)),"") | Q20: =IF(A20="","",IFERROR(SUMIFS(PROGRAMA_DETALLE!$H$4:$H$503,PROGRAMA_DETALLE!$A$4:$A$503,A20),0)) | R20: =IF(A20="","",IFERROR(SUMIFS(PROGRAMA_DETALLE!$I$4:$I$503,PROGRAMA_DETALLE!$A$4:$A$503,A20),0)) | T20: =IFERROR(Q20-R20-S20,0) -> 0 | U20: =IFERROR(T20/Q20,0) -> 0 | V20: =IF(A20="","",IFERROR(SUMIFS(PROGRAMA_DETALLE!$R$4:$R$503,PROGRAMA_DETALLE!$A$4:$A$503,A20),0)) | W20: =IF(A20="","",IFERROR(SUMIFS(PROGRAMA_DETALLE!$S$4:$S$503,PROGRAMA_DETALLE!$A$4:$A$503,A20),0)) | X20: =IFERROR(V20-W20,0) -> 0 | Y20: =IFERROR(X20/V20,0) -> 0 | Z20: =IFERROR(Q20-W20-S20,0) -> 0 | AA20: =IFERROR(Z20/Q20,0) -> 0 | AB20: =IFERROR(W20*DASHBOARD!$C$2,0) -> 0 | AE20: =IFERROR(N20+IFERROR(SUMIFS(PROGRAMA_DETALLE!$M$4:$M$503,PROGRAMA_DETALLE!$A$4:$A$503,A20),0)+IFERROR(SUMIFS(PROGRAMA_DETALLE!$Z$4:$Z$503,PROGRAMA_DETALLE!$A$4:$A$503,A20),0)+AB20,0) -> 0 | AF20: =IFERROR(AE20/W20,0) -> 0 | AG20: =IFERROR(AD20-B20,"") -> 0
... K103: =IFERROR(SUMIFS(PROGRAMA_DETALLE!$E$4:$E$503,PROGRAMA_DETALLE!$A$4:$A$503,A103),0) -> 0 | L103: =IFERROR(SUMIFS(PROGRAMA_DETALLE!$F$4:$F$503,PROGRAMA_DETALLE!$A$4:$A$503,A103),0) -> 0 | M103: =IF(A103="","",IFERROR(SUMIFS(COMPRAS_HILO!$D$4:$D$203,COMPRAS_HILO!$B$4:$B$203,A103),0)) | N103: =IF(A103="","",IFERROR(SUMIFS(COMPRAS_HILO!$H$4:$H$203,COMPRAS_HILO!$B$4:$B$203,A103),0)) | O103: =IFERROR(IF(SUMPRODUCT((COMPRAS_HILO!$B$4:$B$203=A103)*1)=0,"",LOOKUP(2,1/((COMPRAS_HILO!$B$4:$B$203=A103)*(COMPRAS_HILO!$J$4:$J$203<>"")),COMPRAS_HILO!$J$4:$J$203)),"") | Q103: =IF(A103="","",IFERROR(SUMIFS(PROGRAMA_DETALLE!$H$4:$H$503,PROGRAMA_DETALLE!$A$4:$A$503,A103),0)) | R103: =IF(A103="","",IFERROR(SUMIFS(PROGRAMA_DETALLE!$I$4:$I$503,PROGRAMA_DETALLE!$A$4:$A$503,A103),0)) | T103: =IFERROR(Q103-R103-S103,0) -> 0 | U103: =IFERROR(T103/Q103,0) -> 0 | V103: =IF(A103="","",IFERROR(SUMIFS(PROGRAMA_DETALLE!$R$4:$R$503,PROGRAMA_DETALLE!$A$4:$A$503,A103),0)) | W103: =IF(A103="","",IFERROR(SUMIFS(PROGRAMA_DETALLE!$S$4:$S$503,PROGRAMA_DETALLE!$A$4:$A$503,A103),0)) | X103: =IFERROR(V103-W103,0) -> 0 | Y103: =IFERROR(X103/V103,0) -> 0 | Z103: =IFERROR(Q103-W103-S103,0) -> 0 | AA103: =IFERROR(Z103/Q103,0) -> 0 | AB103: =IFERROR(W103*DASHBOARD!$C$2,0) -> 0 | AE103: =IFERROR(N103+IFERROR(SUMIFS(PROGRAMA_DETALLE!$M$4:$M$503,PROGRAMA_DETALLE!$A$4:$A$503,A103),0)+IFERROR(SUMIFS(PROGRAMA_DETALLE!$Z$4:$Z$503,PROGRAMA_DETALLE!$A$4:$A$503,A103),0)+AB103,0) -> 0 | AF103: =IFERROR(AE103/W103,0) -> 0 | AG103: =IFERROR(AD103-B103,"") -> 0

Sheet COMPRAS_HILO
A1: COMPRAS DE HILO — Asignaciones de factura a programas + estado pago
A2: 1 fila = asignación de factura a un programa. Para USD pon MONEDA=USD y TC. ESTADO PAGO permite control contable: PAGADO/PENDIENTE/PARCIAL/ANULADO.
A3: FECHA | B3: PROGRAMA | C3: TIPO HILO | D3: KG ASIGNADOS | E3: PRECIO/KG | F3: MONEDA | G3: TC | H3: TOTAL S/. | I3: PROVEEDOR | J3: N° FACTURA | K3: COSTO REAL FACT. | L3: DIFERENCIA | M3: ESTADO PAGO | N3: FECHA PAGO | O3: MONTO PAGADO S/. | P3: SALDO S/. | Q3: NOTAS
A4: 46113 | B4: PIQUE-001 | C4: Hilo 30/1 PC | D4: 1000 | E4: 3 | F4: USD | G4: 3.5 | H4: =IFERROR(D4*E4*IF(F4="USD",G4,1),0) -> 10500 | I4: COTTON MIX | J4: COTTOON-001 | K4: 10500 | L4: =IFERROR(K4-H4,0) -> 0 | M4: PAGADO | N4: 46113 | O4: 10500 | P4: =IFERROR(H4-O4,0) -> 0
A5: 46152 | B5: FULL LYCRA 50/1-001 | C5: hilo 50/1 cotton +lycra 4% | D5: 500 | E5: 5.5 | F5: USD | G5: 3.5 | H5: =IFERROR(D5*E5*IF(F5="USD",G5,1),0) -> 9625 | I5: COTTON MIX | J5: f002-4472 | K5: 9625 | L5: =IFERROR(K5-H5,0) -> 0 | M5: PAGADO | N5: 46152 | O5: 9525 | P5: =IFERROR(H5-O5,0) -> 100
B6: frecnh terry - 001 | C6: Hilo 30/1 PC | D6: 3000 | E6: 3 | F6: USD | G6: 3.45 | H6: =IFERROR(D6*E6*IF(F6="USD",G6,1),0) -> 31050 | I6: COTTON MIX | K6: 31050 | L6: =IFERROR(K6-H6,0) -> 0 | M6: PAGADO | P6: =IFERROR(H6-O6,0) -> 31050
B7: jersey algodon - 001 | C7: Hilo 30/1 ALGODON | D7: 660 | E7: 4 | F7: USD | G7: 3.45 | H7: =IFERROR(D7*E7*IF(F7="USD",G7,1),0) -> 9108 | I7: COTTON MIX | K7: 9108 | L7: =IFERROR(K7-H7,0) -> 0 | M7: PAGADO | P7: =IFERROR(H7-O7,0) -> 9108
H8: =IFERROR(D8*E8*IF(F8="USD",G8,1),0) -> 0 | L8: =IFERROR(K8-H8,0) -> 0 | P8: =IFERROR(H8-O8,0) -> 0
H9: =IFERROR(D9*E9*IF(F9="USD",G9,1),0) -> 0 | L9: =IFERROR(K9-H9,0) -> 0 | P9: =IFERROR(H9-O9,0) -> 0
H10: =IFERROR(D10*E10*IF(F10="USD",G10,1),0) -> 0 | L10: =IFERROR(K10-H10,0) -> 0 | P10: =IFERROR(H10-O10,0) -> 0
H11: =IFERROR(D11*E11*IF(F11="USD",G11,1),0) -> 0 | L11: =IFERROR(K11-H11,0) -> 0 | P11: =IFERROR(H11-O11,0) -> 0
H12: =IFERROR(D12*E12*IF(F12="USD",G12,1),0) -> 0 | L12: =IFERROR(K12-H12,0) -> 0 | P12: =IFERROR(H12-O12,0) -> 0
H13: =IFERROR(D13*E13*IF(F13="USD",G13,1),0) -> 0 | L13: =IFERROR(K13-H13,0) -> 0 | P13: =IFERROR(H13-O13,0) -> 0
H14: =IFERROR(D14*E14*IF(F14="USD",G14,1),0) -> 0 | L14: =IFERROR(K14-H14,0) -> 0 | P14: =IFERROR(H14-O14,0) -> 0
H15: =IFERROR(D15*E15*IF(F15="USD",G15,1),0) -> 0 | L15: =IFERROR(K15-H15,0) -> 0 | P15: =IFERROR(H15-O15,0) -> 0
H16: =IFERROR(D16*E16*IF(F16="USD",G16,1),0) -> 0 | L16: =IFERROR(K16-H16,0) -> 0 | P16: =IFERROR(H16-O16,0) -> 0
H17: =IFERROR(D17*E17*IF(F17="USD",G17,1),0) -> 0 | L17: =IFERROR(K17-H17,0) -> 0 | P17: =IFERROR(H17-O17,0) -> 0
H18: =IFERROR(D18*E18*IF(F18="USD",G18,1),0) -> 0 | L18: =IFERROR(K18-H18,0) -> 0 | P18: =IFERROR(H18-O18,0) -> 0
H19: =IFERROR(D19*E19*IF(F19="USD",G19,1),0) -> 0 | L19: =IFERROR(K19-H19,0) -> 0 | P19: =IFERROR(H19-O19,0) -> 0
... H203: =IFERROR(D203*E203*IF(F203="USD",G203,1),0) -> 0 | L203: =IFERROR(K203-H203,0) -> 0 | P203: =IFERROR(H203-O203,0) -> 0

Sheet PROGRAMA_DETALLE
A1: PROGRAMA DETALLE — Plan + Tejeduría + Tintorería + Costos por color
A2: 1 fila = 1 color de un programa. Precio tej y tint salen automáticos del catálogo. Llenas: KG enviado/retornado, factura, guía, pago, fecha tint, moneda/TC.
A3: ID PROGRAMA | B3: COLOR | C3: CATEG. | D3: TIPO SERVICIO | E3: ROLLOS PLAN | F3: KG PLAN | G3: PRIORIDAD | H3: KG TEJ ENVIADO | I3: KG TEJ RETORNADO | J3: PRECIO/KG TEJ (auto) | K3: MONEDA TEJ | L3: TC TEJ | M3: TOTAL TEJ (auto) | N3: FACTURA TEJ | O3: GUÍA TEJ | P3: ESTADO PAGO TEJ | Q3: FECHA ENVÍO TINT | R3: KG ENVIADO TINT | S3: KG RETORNADO TINT | T3: ROLLOS FINAL | U3: KG MERMA TINT | V3: % MERMA TINT | W3: PRECIO/KG TINT (auto) | X3: MONEDA TINT | Y3: TC TINT | Z3: COSTO TINT (auto) | AA3: GUÍA TRASLADO TINT | AB3: FACTURA TINT | AC3: ESTADO PAGO TINT | AD3: COSTO HILO (prorr.) | AE3: COSTO TEJ COLOR | AF3: COSTO TINT COLOR | AG3: COSTO TOTAL COLOR | AH3: COSTO/KG COLOR | AI3: NOTAS
A4: PIQUE-001 | B4: Negro | C4: =IFERROR(VLOOKUP(B4,COLORES!$A$4:$B$52,2,FALSE()),"") -> OSCURO | D4: REACTIVO (oscuros) | E4: 20 | F4: 400 | G4: URGENTE | H4: 400 | I4: 395 | J4: =IFERROR(VLOOKUP(VLOOKUP(A4,PROGRAMAS!$A$4:$G$103,7,FALSE()),PRECIOS_TEJEDURIA!$A$4:$B$22,2,FALSE()),0) -> 0.5 | K4: USD | L4: 3.55 | M4: =IFERROR(H4*J4*IF(K4="USD",L4,1),0) -> 710 | N4: TEJ-001 | O4: TEJ-001 | P4: PAGADO | Q4: 46114 | R4: 395 | S4: 380 | T4: 20 | U4: =IFERROR(R4-S4,0) -> 15 | V4: =IFERROR(U4/R4,0) -> 0.037974684 | W4: {=IFERROR(INDEX(PRECIOS_TINTORERIA!$B$4:$U$15,MATCH(D4,PRECIOS_TINTORERIA!$A$4:$A$15,0),MATCH(VLOOKUP(A4,PROGRAMAS!$A$4:$G$103,7,FALSE()),PRECIOS_TINTORERIA!$B$3:$U$3,0)),0)} -> 2.7 | X4: USD | Y4: 3.55 | Z4: =IFERROR(R4*W4*IF(X4="USD",Y4,1),0) -> 3786.075 | AA4: TIN-001 | AB4: TIN-001 | AC4: PAGADO | AD4: =IFERROR((SUMIFS(COMPRAS_HILO!$H$4:$H$203,COMPRAS_HILO!$B$4:$B$203,A4))*F4/SUMIFS($F$4:$F$503,$A$4:$A$503,A4),0) -> 4200 | AE4: =M4 -> 710 | AF4: =Z4 -> 3786.075 | AG4: =AD4+AE4+AF4 -> 8696.075 | AH4: =IFERROR(AG4/S4,0) -> 22.884408
A5: PIQUE-001 | B5: Perla | C5: =IFERROR(VLOOKUP(B5,COLORES!$A$4:$B$52,2,FALSE()),"") -> PPT | D5: PPT (perla/blanco) | E5: 10 | F5: 200 | G5: MEDIA | H5: 200 | I5: 195 | J5: =IFERROR(VLOOKUP(VLOOKUP(A5,PROGRAMAS!$A$4:$G$103,7,FALSE()),PRECIOS_TEJEDURIA!$A$4:$B$22,2,FALSE()),0) -> 0.5 | K5: USD | L5: 3.55 | M5: =IFERROR(H5*J5*IF(K5="USD",L5,1),0) -> 355 | N5: TEJ-002 | O5: TEJ-002 | P5: PAGADO | Q5: 46114 | R5: 195 | S5: 170 | T5: 10 | U5: =IFERROR(R5-S5,0) -> 25 | V5: =IFERROR(U5/R5,0) -> 0.12820513 | W5: {=IFERROR(INDEX(PRECIOS_TINTORERIA!$B$4:$U$15,MATCH(D5,PRECIOS_TINTORERIA!$A$4:$A$15,0),MATCH(VLOOKUP(A5,PROGRAMAS!$A$4:$G$103,7,FALSE()),PRECIOS_TINTORERIA!$B$3:$U$3,0)),0)} -> 1.1 | X5: USD | Y5: 3.55 | Z5: =IFERROR(R5*W5*IF(X5="USD",Y5,1),0) -> 761.475 | AA5: TIN-002 | AB5: TIN-002 | AC5: PAGADO | AD5: =IFERROR((SUMIFS(COMPRAS_HILO!$H$4:$H$203,COMPRAS_HILO!$B$4:$B$203,A5))*F5/SUMIFS($F$4:$F$503,$A$4:$A$503,A5),0) -> 2100 | AE5: =M5 -> 355 | AF5: =Z5 -> 761.475 | AG5: =AD5+AE5+AF5 -> 3216.475 | AH5: =IFERROR(AG5/S5,0) -> 18.920441
A6: PIQUE-001 | B6: Beige | C6: =IFERROR(VLOOKUP(B6,COLORES!$A$4:$B$52,2,FALSE()),"") -> CLARO | D6: DIRECTO (claros) | E6: 10 | F6: 200 | G6: ALTA | H6: 200 | I6: 195 | J6: =IFERROR(VLOOKUP(VLOOKUP(A6,PROGRAMAS!$A$4:$G$103,7,FALSE()),PRECIOS_TEJEDURIA!$A$4:$B$22,2,FALSE()),0) -> 0.5 | K6: USD | L6: 3.55 | M6: =IFERROR(H6*J6*IF(K6="USD",L6,1),0) -> 355 | N6: TEJ-003 | O6: TEJ-003 | P6: PAGADO | Q6: 46114 | R6: 195 | S6: 170 | T6: 10 | U6: =IFERROR(R6-S6,0) -> 25 | V6: =IFERROR(U6/R6,0) -> 0.12820513 | W6: {=IFERROR(INDEX(PRECIOS_TINTORERIA!$B$4:$U$15,MATCH(D6,PRECIOS_TINTORERIA!$A$4:$A$15,0),MATCH(VLOOKUP(A6,PROGRAMAS!$A$4:$G$103,7,FALSE()),PRECIOS_TINTORERIA!$B$3:$U$3,0)),0)} -> 1.95 | X6: USD | Y6: 3.5 | Z6: =IFERROR(R6*W6*IF(X6="USD",Y6,1),0) -> 1330.875 | AA6: TIN-003 | AB6: TIN-003 | AC6: PAGADO | AD6: =IFERROR((SUMIFS(COMPRAS_HILO!$H$4:$H$203,COMPRAS_HILO!$B$4:$B$203,A6))*F6/SUMIFS($F$4:$F$503,$A$4:$A$503,A6),0) -> 2100 | AE6: =M6 -> 355 | AF6: =Z6 -> 1330.875 | AG6: =AD6+AE6+AF6 -> 3785.875 | AH6: =IFERROR(AG6/S6,0) -> 22.269853
A7: PIQUE-001 | B7: Melange | C7: =IFERROR(VLOOKUP(B7,COLORES!$A$4:$B$52,2,FALSE()),"") -> MELANGE | D7: LAVADO (melange) | E7: 10 | F7: 200 | G7: OPCIONAL | H7: 200 | I7: 195 | J7: =IFERROR(VLOOKUP(VLOOKUP(A7,PROGRAMAS!$A$4:$G$103,7,FALSE()),PRECIOS_TEJEDURIA!$A$4:$B$22,2,FALSE()),0) -> 0.5 | K7: USD | L7: 3.55 | M7: =IFERROR(H7*J7*IF(K7="USD",L7,1),0) -> 355 | N7: TEJ-004 | O7: TEJ-004 | P7: PAGADO | Q7: 46114 | R7: 195 | S7: 170 | T7: 10 | U7: =IFERROR(R7-S7,0) -> 25 | V7: =IFERROR(U7/R7,0) -> 0.12820513 | W7: {=IFERROR(INDEX(PRECIOS_TINTORERIA!$B$4:$U$15,MATCH(D7,PRECIOS_TINTORERIA!$A$4:$A$15,0),MATCH(VLOOKUP(A7,PROGRAMAS!$A$4:$G$103,7,FALSE()),PRECIOS_TINTORERIA!$B$3:$U$3,0)),0)} -> 1.1 | X7: USD | Y7: 3.5 | Z7: =IFERROR(R7*W7*IF(X7="USD",Y7,1),0) -> 750.75 | AA7: TIN-004 | AB7: TIN-004 | AC7: PAGADO | AD7: =IFERROR((SUMIFS(COMPRAS_HILO!$H$4:$H$203,COMPRAS_HILO!$B$4:$B$203,A7))*F7/SUMIFS($F$4:$F$503,$A$4:$A$503,A7),0) -> 2100 | AE7: =M7 -> 355 | AF7: =Z7 -> 750.75 | AG7: =AD7+AE7+AF7 -> 3205.75 | AH7: =IFERROR(AG7/S7,0) -> 18.857353
C8: =IFERROR(VLOOKUP(B8,COLORES!$A$4:$B$52,2,FALSE()),"") | J8: =IFERROR(VLOOKUP(VLOOKUP(A8,PROGRAMAS!$A$4:$G$103,7,FALSE()),PRECIOS_TEJEDURIA!$A$4:$B$22,2,FALSE()),0) -> 0 | M8: =IFERROR(H8*J8*IF(K8="USD",L8,1),0) -> 0 | U8: =IFERROR(R8-S8,0) -> 0 | V8: =IFERROR(U8/R8,0) -> 0 | W8: {=IFERROR(INDEX(PRECIOS_TINTORERIA!$B$4:$U$15,MATCH(D8,PRECIOS_TINTORERIA!$A$4:$A$15,0),MATCH(VLOOKUP(A8,PROGRAMAS!$A$4:$G$103,7,FALSE()),PRECIOS_TINTORERIA!$B$3:$U$3,0)),0)} -> 0 | Z8: =IFERROR(R8*W8*IF(X8="USD",Y8,1),0) -> 0 | AD8: =IFERROR((SUMIFS(COMPRAS_HILO!$H$4:$H$203,COMPRAS_HILO!$B$4:$B$203,A8))*F8/SUMIFS($F$4:$F$503,$A$4:$A$503,A8),0) -> 0 | AE8: =M8 -> 0 | AF8: =Z8 -> 0 | AG8: =AD8+AE8+AF8 -> 0 | AH8: =IFERROR(AG8/S8,0) -> 0
C9: =IFERROR(VLOOKUP(B9,COLORES!$A$4:$B$52,2,FALSE()),"") | J9: =IFERROR(VLOOKUP(VLOOKUP(A9,PROGRAMAS!$A$4:$G$103,7,FALSE()),PRECIOS_TEJEDURIA!$A$4:$B$22,2,FALSE()),0) -> 0 | M9: =IFERROR(H9*J9*IF(K9="USD",L9,1),0) -> 0 | U9: =IFERROR(R9-S9,0) -> 0 | V9: =IFERROR(U9/R9,0) -> 0 | W9: {=IFERROR(INDEX(PRECIOS_TINTORERIA!$B$4:$U$15,MATCH(D9,PRECIOS_TINTORERIA!$A$4:$A$15,0),MATCH(VLOOKUP(A9,PROGRAMAS!$A$4:$G$103,7,FALSE()),PRECIOS_TINTORERIA!$B$3:$U$3,0)),0)} -> 0 | Z9: =IFERROR(R9*W9*IF(X9="USD",Y9,1),0) -> 0 | AD9: =IFERROR((SUMIFS(COMPRAS_HILO!$H$4:$H$203,COMPRAS_HILO!$B$4:$B$203,A9))*F9/SUMIFS($F$4:$F$503,$A$4:$A$503,A9),0) -> 0 | AE9: =M9 -> 0 | AF9: =Z9 -> 0 | AG9: =AD9+AE9+AF9 -> 0 | AH9: =IFERROR(AG9/S9,0) -> 0
A10: FULL LYCRA 50/1-001 | B10: Negro | C10: =IFERROR(VLOOKUP(B10,COLORES!$A$4:$B$52,2,FALSE()),"") -> OSCURO | D10: REACTIVO (oscuros) | E10: 8 | F10: 160 | G10: MEDIA | H10: 160 | J10: =IFERROR(VLOOKUP(VLOOKUP(A10,PROGRAMAS!$A$4:$G$103,7,FALSE()),PRECIOS_TEJEDURIA!$A$4:$B$22,2,FALSE()),0) -> 0.7 | K10: USD | M10: =IFERROR(H10*J10*IF(K10="USD",L10,1),0) -> 0 | U10: =IFERROR(R10-S10,0) -> 0 | V10: =IFERROR(U10/R10,0) -> 0 | W10: {=IFERROR(INDEX(PRECIOS_TINTORERIA!$B$4:$U$15,MATCH(D10,PRECIOS_TINTORERIA!$A$4:$A$15,0),MATCH(VLOOKUP(A10,PROGRAMAS!$A$4:$G$103,7,FALSE()),PRECIOS_TINTORERIA!$B$3:$U$3,0)),0)} -> 0 | Z10: =IFERROR(R10*W10*IF(X10="USD",Y10,1),0) -> 0 | AD10: =IFERROR((SUMIFS(COMPRAS_HILO!$H$4:$H$203,COMPRAS_HILO!$B$4:$B$203,A10))*F10/SUMIFS($F$4:$F$503,$A$4:$A$503,A10),0) -> 3080 | AE10: =M10 -> 0 | AF10: =Z10 -> 0 | AG10: =AD10+AE10+AF10 -> 3080 | AH10: =IFERROR(AG10/S10,0) -> 0
A11: FULL LYCRA 50/1-001 | B11: Perla | C11: =IFERROR(VLOOKUP(B11,COLORES!$A$4:$B$52,2,FALSE()),"") -> PPT | D11: PPT (perla/blanco) | E11: 9 | F11: 180 | G11: MEDIA | H11: 180 | J11: =IFERROR(VLOOKUP(VLOOKUP(A11,PROGRAMAS!$A$4:$G$103,7,FALSE()),PRECIOS_TEJEDURIA!$A$4:$B$22,2,FALSE()),0) -> 0.7 | K11: USD | M11: =IFERROR(H11*J11*IF(K11="USD",L11,1),0) -> 0 | U11: =IFERROR(R11-S11,0) -> 0 | V11: =IFERROR(U11/R11,0) -> 0 | W11: {=IFERROR(INDEX(PRECIOS_TINTORERIA!$B$4:$U$15,MATCH(D11,PRECIOS_TINTORERIA!$A$4:$A$15,0),MATCH(VLOOKUP(A11,PROGRAMAS!$A$4:$G$103,7,FALSE()),PRECIOS_TINTORERIA!$B$3:$U$3,0)),0)} -> 0 | Z11: =IFERROR(R11*W11*IF(X11="USD",Y11,1),0) -> 0 | AD11: =IFERROR((SUMIFS(COMPRAS_HILO!$H$4:$H$203,COMPRAS_HILO!$B$4:$B$203,A11))*F11/SUMIFS($F$4:$F$503,$A$4:$A$503,A11),0) -> 3465 | AE11: =M11 -> 0 | AF11: =Z11 -> 0 | AG11: =AD11+AE11+AF11 -> 3465 | AH11: =IFERROR(AG11/S11,0) -> 0
A12: FULL LYCRA 50/1-001 | B12: Colegial | C12: =IFERROR(VLOOKUP(B12,COLORES!$A$4:$B$52,2,FALSE()),"") -> OSCURO | D12: REACTIVO (oscuros) | E12: 8 | F12: 160 | G12: MEDIA | H12: 160 | J12: =IFERROR(VLOOKUP(VLOOKUP(A12,PROGRAMAS!$A$4:$G$103,7,FALSE()),PRECIOS_TEJEDURIA!$A$4:$B$22,2,FALSE()),0) -> 0.7 | K12: USD | M12: =IFERROR(H12*J12*IF(K12="USD",L12,1),0) -> 0 | U12: =IFERROR(R12-S12,0) -> 0 | V12: =IFERROR(U12/R12,0) -> 0 | W12: {=IFERROR(INDEX(PRECIOS_TINTORERIA!$B$4:$U$15,MATCH(D12,PRECIOS_TINTORERIA!$A$4:$A$15,0),MATCH(VLOOKUP(A12,PROGRAMAS!$A$4:$G$103,7,FALSE()),PRECIOS_TINTORERIA!$B$3:$U$3,0)),0)} -> 0 | Z12: =IFERROR(R12*W12*IF(X12="USD",Y12,1),0) -> 0 | AD12: =IFERROR((SUMIFS(COMPRAS_HILO!$H$4:$H$203,COMPRAS_HILO!$B$4:$B$203,A12))*F12/SUMIFS($F$4:$F$503,$A$4:$A$503,A12),0) -> 3080 | AE12: =M12 -> 0 | AF12: =Z12 -> 0 | AG12: =AD12+AE12+AF12 -> 3080 | AH12: =IFERROR(AG12/S12,0) -> 0
C13: =IFERROR(VLOOKUP(B13,COLORES!$A$4:$B$52,2,FALSE()),"") | J13: =IFERROR(VLOOKUP(VLOOKUP(A13,PROGRAMAS!$A$4:$G$103,7,FALSE()),PRECIOS_TEJEDURIA!$A$4:$B$22,2,FALSE()),0) -> 0 | M13: =IFERROR(H13*J13*IF(K13="USD",L13,1),0) -> 0 | U13: =IFERROR(R13-S13,0) -> 0 | V13: =IFERROR(U13/R13,0) -> 0 | W13: {=IFERROR(INDEX(PRECIOS_TINTORERIA!$B$4:$U$15,MATCH(D13,PRECIOS_TINTORERIA!$A$4:$A$15,0),MATCH(VLOOKUP(A13,PROGRAMAS!$A$4:$G$103,7,FALSE()),PRECIOS_TINTORERIA!$B$3:$U$3,0)),0)} -> 0 | Z13: =IFERROR(R13*W13*IF(X13="USD",Y13,1),0) -> 0 | AD13: =IFERROR((SUMIFS(COMPRAS_HILO!$H$4:$H$203,COMPRAS_HILO!$B$4:$B$203,A13))*F13/SUMIFS($F$4:$F$503,$A$4:$A$503,A13),0) -> 0 | AE13: =M13 -> 0 | AF13: =Z13 -> 0 | AG13: =AD13+AE13+AF13 -> 0 | AH13: =IFERROR(AG13/S13,0) -> 0
A14: frecnh terry - 001 | B14: Negro | C14: =IFERROR(VLOOKUP(B14,COLORES!$A$4:$B$52,2,FALSE()),"") -> OSCURO | D14: REACTIVO (oscuros) | E14: 40 | F14: 800 | G14: ALTA | J14: =IFERROR(VLOOKUP(VLOOKUP(A14,PROGRAMAS!$A$4:$G$103,7,FALSE()),PRECIOS_TEJEDURIA!$A$4:$B$22,2,FALSE()),0) -> 0.4 | M14: =IFERROR(H14*J14*IF(K14="USD",L14,1),0) -> 0 | U14: =IFERROR(R14-S14,0) -> 0 | V14: =IFERROR(U14/R14,0) -> 0 | W14: {=IFERROR(INDEX(PRECIOS_TINTORERIA!$B$4:$U$15,MATCH(D14,PRECIOS_TINTORERIA!$A$4:$A$15,0),MATCH(VLOOKUP(A14,PROGRAMAS!$A$4:$G$103,7,FALSE()),PRECIOS_TINTORERIA!$B$3:$U$3,0)),0)} -> 0 | Z14: =IFERROR(R14*W14*IF(X14="USD",Y14,1),0) -> 0 | AD14: =IFERROR((SUMIFS(COMPRAS_HILO!$H$4:$H$203,COMPRAS_HILO!$B$4:$B$203,A14))*F14/SUMIFS($F$4:$F$503,$A$4:$A$503,A14),0) -> 8565.5172 | AE14: =M14 -> 0 | AF14: =Z14 -> 0 | AG14: =AD14+AE14+AF14 -> 8565.5172 | AH14: =IFERROR(AG14/S14,0) -> 0
A15: frecnh terry - 001 | B15: Perla | C15: =IFERROR(VLOOKUP(B15,COLORES!$A$4:$B$52,2,FALSE()),"") -> PPT | D15: PPT (perla/blanco) | E15: 10 | F15: 200 | G15: BAJA | J15: =IFERROR(VLOOKUP(VLOOKUP(A15,PROGRAMAS!$A$4:$G$103,7,FALSE()),PRECIOS_TEJEDURIA!$A$4:$B$22,2,FALSE()),0) -> 0.4 | M15: =IFERROR(H15*J15*IF(K15="USD",L15,1),0) -> 0 | U15: =IFERROR(R15-S15,0) -> 0 | V15: =IFERROR(U15/R15,0) -> 0 | W15: {=IFERROR(INDEX(PRECIOS_TINTORERIA!$B$4:$U$15,MATCH(D15,PRECIOS_TINTORERIA!$A$4:$A$15,0),MATCH(VLOOKUP(A15,PROGRAMAS!$A$4:$G$103,7,FALSE()),PRECIOS_TINTORERIA!$B$3:$U$3,0)),0)} -> 0 | Z15: =IFERROR(R15*W15*IF(X15="USD",Y15,1),0) -> 0 | AD15: =IFERROR((SUMIFS(COMPRAS_HILO!$H$4:$H$203,COMPRAS_HILO!$B$4:$B$203,A15))*F15/SUMIFS($F$4:$F$503,$A$4:$A$503,A15),0) -> 2141.3793 | AE15: =M15 -> 0 | AF15: =Z15 -> 0 | AG15: =AD15+AE15+AF15 -> 2141.3793 | AH15: =IFERROR(AG15/S15,0) -> 0
A16: frecnh terry - 001 | B16: Azul Marino | C16: =IFERROR(VLOOKUP(B16,COLORES!$A$4:$B$52,2,FALSE()),"") -> OSCURO | D16: REACTIVO (oscuros) | E16: 25 | F16: 500 | G16: ALTA | J16: =IFERROR(VLOOKUP(VLOOKUP(A16,PROGRAMAS!$A$4:$G$103,7,FALSE()),PRECIOS_TEJEDURIA!$A$4:$B$22,2,FALSE()),0) -> 0.4 | M16: =IFERROR(H16*J16*IF(K16="USD",L16,1),0) -> 0 | U16: =IFERROR(R16-S16,0) -> 0 | V16: =IFERROR(U16/R16,0) -> 0 | W16: {=IFERROR(INDEX(PRECIOS_TINTORERIA!$B$4:$U$15,MATCH(D16,PRECIOS_TINTORERIA!$A$4:$A$15,0),MATCH(VLOOKUP(A16,PROGRAMAS!$A$4:$G$103,7,FALSE()),PRECIOS_TINTORERIA!$B$3:$U$3,0)),0)} -> 0 | Z16: =IFERROR(R16*W16*IF(X16="USD",Y16,1),0) -> 0 | AD16: =IFERROR((SUMIFS(COMPRAS_HILO!$H$4:$H$203,COMPRAS_HILO!$B$4:$B$203,A16))*F16/SUMIFS($F$4:$F$503,$A$4:$A$503,A16),0) -> 5353.4483 | AE16: =M16 -> 0 | AF16: =Z16 -> 0 | AG16: =AD16+AE16+AF16 -> 5353.4483 | AH16: =IFERROR(AG16/S16,0) -> 0
A17: frecnh terry - 001 | B17: Vino | C17: =IFERROR(VLOOKUP(B17,COLORES!$A$4:$B$52,2,FALSE()),"") -> OSCURO | D17: REACTIVO (oscuros) | E17: 20 | F17: 400 | G17: ALTA | J17: =IFERROR(VLOOKUP(VLOOKUP(A17,PROGRAMAS!$A$4:$G$103,7,FALSE()),PRECIOS_TEJEDURIA!$A$4:$B$22,2,FALSE()),0) -> 0.4 | M17: =IFERROR(H17*J17*IF(K17="USD",L17,1),0) -> 0 | U17: =IFERROR(R17-S17,0) -> 0 | V17: =IFERROR(U17/R17,0) -> 0 | W17: {=IFERROR(INDEX(PRECIOS_TINTORERIA!$B$4:$U$15,MATCH(D17,PRECIOS_TINTORERIA!$A$4:$A$15,0),MATCH(VLOOKUP(A17,PROGRAMAS!$A$4:$G$103,7,FALSE()),PRECIOS_TINTORERIA!$B$3:$U$3,0)),0)} -> 0 | Z17: =IFERROR(R17*W17*IF(X17="USD",Y17,1),0) -> 0 | AD17: =IFERROR((SUMIFS(COMPRAS_HILO!$H$4:$H$203,COMPRAS_HILO!$B$4:$B$203,A17))*F17/SUMIFS($F$4:$F$503,$A$4:$A$503,A17),0) -> 4282.7586 | AE17: =M17 -> 0 | AF17: =Z17 -> 0 | AG17: =AD17+AE17+AF17 -> 4282.7586 | AH17: =IFERROR(AG17/S17,0) -> 0
A18: frecnh terry - 001 | B18: Denim | C18: =IFERROR(VLOOKUP(B18,COLORES!$A$4:$B$52,2,FALSE()),"") -> CLARO | D18: DIRECTO (claros) | E18: 10 | F18: 200 | G18: MEDIA | J18: =IFERROR(VLOOKUP(VLOOKUP(A18,PROGRAMAS!$A$4:$G$103,7,FALSE()),PRECIOS_TEJEDURIA!$A$4:$B$22,2,FALSE()),0) -> 0.4 | M18: =IFERROR(H18*J18*IF(K18="USD",L18,1),0) -> 0 | U18: =IFERROR(R18-S18,0) -> 0 | V18: =IFERROR(U18/R18,0) -> 0 | W18: {=IFERROR(INDEX(PRECIOS_TINTORERIA!$B$4:$U$15,MATCH(D18,PRECIOS_TINTORERIA!$A$4:$A$15,0),MATCH(VLOOKUP(A18,PROGRAMAS!$A$4:$G$103,7,FALSE()),PRECIOS_TINTORERIA!$B$3:$U$3,0)),0)} -> 0 | Z18: =IFERROR(R18*W18*IF(X18="USD",Y18,1),0) -> 0 | AD18: =IFERROR((SUMIFS(COMPRAS_HILO!$H$4:$H$203,COMPRAS_HILO!$B$4:$B$203,A18))*F18/SUMIFS($F$4:$F$503,$A$4:$A$503,A18),0) -> 2141.3793 | AE18: =M18 -> 0 | AF18: =Z18 -> 0 | AG18: =AD18+AE18+AF18 -> 2141.3793 | AH18: =IFERROR(AG18/S18,0) -> 0
A19: frecnh terry - 001 | B19: Pacay | C19: =IFERROR(VLOOKUP(B19,COLORES!$A$4:$B$52,2,FALSE()),"") -> CLARO | D19: DIRECTO (claros) | E19: 10 | F19: 200 | G19: MEDIA | J19: =IFERROR(VLOOKUP(VLOOKUP(A19,PROGRAMAS!$A$4:$G$103,7,FALSE()),PRECIOS_TEJEDURIA!$A$4:$B$22,2,FALSE()),0) -> 0.4 | M19: =IFERROR(H19*J19*IF(K19="USD",L19,1),0) -> 0 | U19: =IFERROR(R19-S19,0) -> 0 | V19: =IFERROR(U19/R19,0) -> 0 | W19: {=IFERROR(INDEX(PRECIOS_TINTORERIA!$B$4:$U$15,MATCH(D19,PRECIOS_TINTORERIA!$A$4:$A$15,0),MATCH(VLOOKUP(A19,PROGRAMAS!$A$4:$G$103,7,FALSE()),PRECIOS_TINTORERIA!$B$3:$U$3,0)),0)} -> 0 | Z19: =IFERROR(R19*W19*IF(X19="USD",Y19,1),0) -> 0 | AD19: =IFERROR((SUMIFS(COMPRAS_HILO!$H$4:$H$203,COMPRAS_HILO!$B$4:$B$203,A19))*F19/SUMIFS($F$4:$F$503,$A$4:$A$503,A19),0) -> 2141.3793 | AE19: =M19 -> 0 | AF19: =Z19 -> 0 | AG19: =AD19+AE19+AF19 -> 2141.3793 | AH19: =IFERROR(AG19/S19,0) -> 0
A20: frecnh terry - 001 | B20: Topo | C20: =IFERROR(VLOOKUP(B20,COLORES!$A$4:$B$52,2,FALSE()),"") -> CLARO | D20: DIRECTO (claros) | E20: 10 | F20: 200 | G20: MEDIA | J20: =IFERROR(VLOOKUP(VLOOKUP(A20,PROGRAMAS!$A$4:$G$103,7,FALSE()),PRECIOS_TEJEDURIA!$A$4:$B$22,2,FALSE()),0) -> 0.4 | M20: =IFERROR(H20*J20*IF(K20="USD",L20,1),0) -> 0 | U20: =IFERROR(R20-S20,0) -> 0 | V20: =IFERROR(U20/R20,0) -> 0 | W20: {=IFERROR(INDEX(PRECIOS_TINTORERIA!$B$4:$U$15,MATCH(D20,PRECIOS_TINTORERIA!$A$4:$A$15,0),MATCH(VLOOKUP(A20,PROGRAMAS!$A$4:$G$103,7,FALSE()),PRECIOS_TINTORERIA!$B$3:$U$3,0)),0)} -> 0 | Z20: =IFERROR(R20*W20*IF(X20="USD",Y20,1),0) -> 0 | AD20: =IFERROR((SUMIFS(COMPRAS_HILO!$H$4:$H$203,COMPRAS_HILO!$B$4:$B$203,A20))*F20/SUMIFS($F$4:$F$503,$A$4:$A$503,A20),0) -> 2141.3793 | AE20: =M20 -> 0 | AF20: =Z20 -> 0 | AG20: =AD20+AE20+AF20 -> 2141.3793 | AH20: =IFERROR(AG20/S20,0) -> 0
A21: frecnh terry - 001 | B21: Palo Rosa | C21: =IFERROR(VLOOKUP(B21,COLORES!$A$4:$B$52,2,FALSE()),"") -> CLARO | D21: DIRECTO (claros) | E21: 10 | F21: 200 | G21: MEDIA | J21: =IFERROR(VLOOKUP(VLOOKUP(A21,PROGRAMAS!$A$4:$G$103,7,FALSE()),PRECIOS_TEJEDURIA!$A$4:$B$22,2,FALSE()),0) -> 0.4 | M21: =IFERROR(H21*J21*IF(K21="USD",L21,1),0) -> 0 | U21: =IFERROR(R21-S21,0) -> 0 | V21: =IFERROR(U21/R21,0) -> 0 | W21: {=IFERROR(INDEX(PRECIOS_TINTORERIA!$B$4:$U$15,MATCH(D21,PRECIOS_TINTORERIA!$A$4:$A$15,0),MATCH(VLOOKUP(A21,PROGRAMAS!$A$4:$G$103,7,FALSE()),PRECIOS_TINTORERIA!$B$3:$U$3,0)),0)} -> 0 | Z21: =IFERROR(R21*W21*IF(X21="USD",Y21,1),0) -> 0 | AD21: =IFERROR((SUMIFS(COMPRAS_HILO!$H$4:$H$203,COMPRAS_HILO!$B$4:$B$203,A21))*F21/SUMIFS($F$4:$F$503,$A$4:$A$503,A21),0) -> 2141.3793 | AE21: =M21 -> 0 | AF21: =Z21 -> 0 | AG21: =AD21+AE21+AF21 -> 2141.3793 | AH21: =IFERROR(AG21/S21,0) -> 0
A22: frecnh terry - 001 | B22: Beige | C22: =IFERROR(VLOOKUP(B22,COLORES!$A$4:$B$52,2,FALSE()),"") -> CLARO | D22: DIRECTO (claros) | E22: 10 | F22: 200 | G22: MEDIA | J22: =IFERROR(VLOOKUP(VLOOKUP(A22,PROGRAMAS!$A$4:$G$103,7,FALSE()),PRECIOS_TEJEDURIA!$A$4:$B$22,2,FALSE()),0) -> 0.4 | M22: =IFERROR(H22*J22*IF(K22="USD",L22,1),0) -> 0 | U22: =IFERROR(R22-S22,0) -> 0 | V22: =IFERROR(U22/R22,0) -> 0 | W22: {=IFERROR(INDEX(PRECIOS_TINTORERIA!$B$4:$U$15,MATCH(D22,PRECIOS_TINTORERIA!$A$4:$A$15,0),MATCH(VLOOKUP(A22,PROGRAMAS!$A$4:$G$103,7,FALSE()),PRECIOS_TINTORERIA!$B$3:$U$3,0)),0)} -> 0 | Z22: =IFERROR(R22*W22*IF(X22="USD",Y22,1),0) -> 0 | AD22: =IFERROR((SUMIFS(COMPRAS_HILO!$H$4:$H$203,COMPRAS_HILO!$B$4:$B$203,A22))*F22/SUMIFS($F$4:$F$503,$A$4:$A$503,A22),0) -> 2141.3793 | AE22: =M22 -> 0 | AF22: =Z22 -> 0 | AG22: =AD22+AE22+AF22 -> 2141.3793 | AH22: =IFERROR(AG22/S22,0) -> 0
C23: =IFERROR(VLOOKUP(B23,COLORES!$A$4:$B$52,2,FALSE()),"") | J23: =IFERROR(VLOOKUP(VLOOKUP(A23,PROGRAMAS!$A$4:$G$103,7,FALSE()),PRECIOS_TEJEDURIA!$A$4:$B$22,2,FALSE()),0) -> 0 | M23: =IFERROR(H23*J23*IF(K23="USD",L23,1),0) -> 0 | U23: =IFERROR(R23-S23,0) -> 0 | V23: =IFERROR(U23/R23,0) -> 0 | W23: {=IFERROR(INDEX(PRECIOS_TINTORERIA!$B$4:$U$15,MATCH(D23,PRECIOS_TINTORERIA!$A$4:$A$15,0),MATCH(VLOOKUP(A23,PROGRAMAS!$A$4:$G$103,7,FALSE()),PRECIOS_TINTORERIA!$B$3:$U$3,0)),0)} -> 0 | Z23: =IFERROR(R23*W23*IF(X23="USD",Y23,1),0) -> 0 | AD23: =IFERROR((SUMIFS(COMPRAS_HILO!$H$4:$H$203,COMPRAS_HILO!$B$4:$B$203,A23))*F23/SUMIFS($F$4:$F$503,$A$4:$A$503,A23),0) -> 0 | AE23: =M23 -> 0 | AF23: =Z23 -> 0 | AG23: =AD23+AE23+AF23 -> 0 | AH23: =IFERROR(AG23/S23,0) -> 0
A24: jersey algodon - 001 | B24: Negro | C24: =IFERROR(VLOOKUP(B24,COLORES!$A$4:$B$52,2,FALSE()),"") -> OSCURO | D24: REACTIVO (oscuros) | J24: =IFERROR(VLOOKUP(VLOOKUP(A24,PROGRAMAS!$A$4:$G$103,7,FALSE()),PRECIOS_TEJEDURIA!$A$4:$B$22,2,FALSE()),0) -> 0 | M24: =IFERROR(H24*J24*IF(K24="USD",L24,1),0) -> 0 | U24: =IFERROR(R24-S24,0) -> 0 | V24: =IFERROR(U24/R24,0) -> 0 | W24: {=IFERROR(INDEX(PRECIOS_TINTORERIA!$B$4:$U$15,MATCH(D24,PRECIOS_TINTORERIA!$A$4:$A$15,0),MATCH(VLOOKUP(A24,PROGRAMAS!$A$4:$G$103,7,FALSE()),PRECIOS_TINTORERIA!$B$3:$U$3,0)),0)} -> 0 | Z24: =IFERROR(R24*W24*IF(X24="USD",Y24,1),0) -> 0 | AD24: =IFERROR((SUMIFS(COMPRAS_HILO!$H$4:$H$203,COMPRAS_HILO!$B$4:$B$203,A24))*F24/SUMIFS($F$4:$F$503,$A$4:$A$503,A24),0) -> 0 | AE24: =M24 -> 0 | AF24: =Z24 -> 0 | AG24: =AD24+AE24+AF24 -> 0 | AH24: =IFERROR(AG24/S24,0) -> 0
A25: rib 1x1- jersey algodon -001 | B25: Negro | C25: =IFERROR(VLOOKUP(B25,COLORES!$A$4:$B$52,2,FALSE()),"") -> OSCURO | D25: REACTIVO (oscuros) | J25: =IFERROR(VLOOKUP(VLOOKUP(A25,PROGRAMAS!$A$4:$G$103,7,FALSE()),PRECIOS_TEJEDURIA!$A$4:$B$22,2,FALSE()),0) -> 0.6 | M25: =IFERROR(H25*J25*IF(K25="USD",L25,1),0) -> 0 | U25: =IFERROR(R25-S25,0) -> 0 | V25: =IFERROR(U25/R25,0) -> 0 | W25: {=IFERROR(INDEX(PRECIOS_TINTORERIA!$B$4:$U$15,MATCH(D25,PRECIOS_TINTORERIA!$A$4:$A$15,0),MATCH(VLOOKUP(A25,PROGRAMAS!$A$4:$G$103,7,FALSE()),PRECIOS_TINTORERIA!$B$3:$U$3,0)),0)} -> 3 | Z25: =IFERROR(R25*W25*IF(X25="USD",Y25,1),0) -> 0 | AD25: =IFERROR((SUMIFS(COMPRAS_HILO!$H$4:$H$203,COMPRAS_HILO!$B$4:$B$203,A25))*F25/SUMIFS($F$4:$F$503,$A$4:$A$503,A25),0) -> 0 | AE25: =M25 -> 0 | AF25: =Z25 -> 0 | AG25: =AD25+AE25+AF25 -> 0 | AH25: =IFERROR(AG25/S25,0) -> 0
A26: jersey algodon - 001 | B26: Perla | C26: =IFERROR(VLOOKUP(B26,COLORES!$A$4:$B$52,2,FALSE()),"") -> PPT | D26: REACTIVO (oscuros) | J26: =IFERROR(VLOOKUP(VLOOKUP(A26,PROGRAMAS!$A$4:$G$103,7,FALSE()),PRECIOS_TEJEDURIA!$A$4:$B$22,2,FALSE()),0) -> 0 | M26: =IFERROR(H26*J26*IF(K26="USD",L26,1),0) -> 0 | U26: =IFERROR(R26-S26,0) -> 0 | V26: =IFERROR(U26/R26,0) -> 0 | W26: {=IFERROR(INDEX(PRECIOS_TINTORERIA!$B$4:$U$15,MATCH(D26,PRECIOS_TINTORERIA!$A$4:$A$15,0),MATCH(VLOOKUP(A26,PROGRAMAS!$A$4:$G$103,7,FALSE()),PRECIOS_TINTORERIA!$B$3:$U$3,0)),0)} -> 0 | Z26: =IFERROR(R26*W26*IF(X26="USD",Y26,1),0) -> 0 | AD26: =IFERROR((SUMIFS(COMPRAS_HILO!$H$4:$H$203,COMPRAS_HILO!$B$4:$B$203,A26))*F26/SUMIFS($F$4:$F$503,$A$4:$A$503,A26),0) -> 0 | AE26: =M26 -> 0 | AF26: =Z26 -> 0 | AG26: =AD26+AE26+AF26 -> 0 | AH26: =IFERROR(AG26/S26,0) -> 0
A27: rib 1x1- jersey algodon -001 | B27: Perla | C27: =IFERROR(VLOOKUP(B27,COLORES!$A$4:$B$52,2,FALSE()),"") -> PPT | D27: REACTIVO (oscuros) | J27: =IFERROR(VLOOKUP(VLOOKUP(A27,PROGRAMAS!$A$4:$G$103,7,FALSE()),PRECIOS_TEJEDURIA!$A$4:$B$22,2,FALSE()),0) -> 0.6 | M27: =IFERROR(H27*J27*IF(K27="USD",L27,1),0) -> 0 | U27: =IFERROR(R27-S27,0) -> 0 | V27: =IFERROR(U27/R27,0) -> 0 | W27: {=IFERROR(INDEX(PRECIOS_TINTORERIA!$B$4:$U$15,MATCH(D27,PRECIOS_TINTORERIA!$A$4:$A$15,0),MATCH(VLOOKUP(A27,PROGRAMAS!$A$4:$G$103,7,FALSE()),PRECIOS_TINTORERIA!$B$3:$U$3,0)),0)} -> 3 | Z27: =IFERROR(R27*W27*IF(X27="USD",Y27,1),0) -> 0 | AD27: =IFERROR((SUMIFS(COMPRAS_HILO!$H$4:$H$203,COMPRAS_HILO!$B$4:$B$203,A27))*F27/SUMIFS($F$4:$F$503,$A$4:$A$503,A27),0) -> 0 | AE27: =M27 -> 0 | AF27: =Z27 -> 0 | AG27: =AD27+AE27+AF27 -> 0 | AH27: =IFERROR(AG27/S27,0) -> 0
A28: jersey algodon - 001 | B28: Beige | C28: =IFERROR(VLOOKUP(B28,COLORES!$A$4:$B$52,2,FALSE()),"") -> CLARO | J28: =IFERROR(VLOOKUP(VLOOKUP(A28,PROGRAMAS!$A$4:$G$103,7,FALSE()),PRECIOS_TEJEDURIA!$A$4:$B$22,2,FALSE()),0) -> 0 | M28: =IFERROR(H28*J28*IF(K28="USD",L28,1),0) -> 0 | U28: =IFERROR(R28-S28,0) -> 0 | V28: =IFERROR(U28/R28,0) -> 0 | W28: {=IFERROR(INDEX(PRECIOS_TINTORERIA!$B$4:$U$15,MATCH(D28,PRECIOS_TINTORERIA!$A$4:$A$15,0),MATCH(VLOOKUP(A28,PROGRAMAS!$A$4:$G$103,7,FALSE()),PRECIOS_TINTORERIA!$B$3:$U$3,0)),0)} -> 0 | Z28: =IFERROR(R28*W28*IF(X28="USD",Y28,1),0) -> 0 | AD28: =IFERROR((SUMIFS(COMPRAS_HILO!$H$4:$H$203,COMPRAS_HILO!$B$4:$B$203,A28))*F28/SUMIFS($F$4:$F$503,$A$4:$A$503,A28),0) -> 0 | AE28: =M28 -> 0 | AF28: =Z28 -> 0 | AG28: =AD28+AE28+AF28 -> 0 | AH28: =IFERROR(AG28/S28,0) -> 0
A29: rib 1x1- jersey algodon -001 | B29: Beige | C29: =IFERROR(VLOOKUP(B29,COLORES!$A$4:$B$52,2,FALSE()),"") -> CLARO | J29: =IFERROR(VLOOKUP(VLOOKUP(A29,PROGRAMAS!$A$4:$G$103,7,FALSE()),PRECIOS_TEJEDURIA!$A$4:$B$22,2,FALSE()),0) -> 0.6 | M29: =IFERROR(H29*J29*IF(K29="USD",L29,1),0) -> 0 | U29: =IFERROR(R29-S29,0) -> 0 | V29: =IFERROR(U29/R29,0) -> 0 | W29: {=IFERROR(INDEX(PRECIOS_TINTORERIA!$B$4:$U$15,MATCH(D29,PRECIOS_TINTORERIA!$A$4:$A$15,0),MATCH(VLOOKUP(A29,PROGRAMAS!$A$4:$G$103,7,FALSE()),PRECIOS_TINTORERIA!$B$3:$U$3,0)),0)} -> 0 | Z29: =IFERROR(R29*W29*IF(X29="USD",Y29,1),0) -> 0 | AD29: =IFERROR((SUMIFS(COMPRAS_HILO!$H$4:$H$203,COMPRAS_HILO!$B$4:$B$203,A29))*F29/SUMIFS($F$4:$F$503,$A$4:$A$503,A29),0) -> 0 | AE29: =M29 -> 0 | AF29: =Z29 -> 0 | AG29: =AD29+AE29+AF29 -> 0 | AH29: =IFERROR(AG29/S29,0) -> 0
A30: jersey algodon - 001 | B30: Acero | C30: =IFERROR(VLOOKUP(B30,COLORES!$A$4:$B$52,2,FALSE()),"") -> OSCURO | J30: =IFERROR(VLOOKUP(VLOOKUP(A30,PROGRAMAS!$A$4:$G$103,7,FALSE()),PRECIOS_TEJEDURIA!$A$4:$B$22,2,FALSE()),0) -> 0 | M30: =IFERROR(H30*J30*IF(K30="USD",L30,1),0) -> 0 | U30: =IFERROR(R30-S30,0) -> 0 | V30: =IFERROR(U30/R30,0) -> 0 | W30: {=IFERROR(INDEX(PRECIOS_TINTORERIA!$B$4:$U$15,MATCH(D30,PRECIOS_TINTORERIA!$A$4:$A$15,0),MATCH(VLOOKUP(A30,PROGRAMAS!$A$4:$G$103,7,FALSE()),PRECIOS_TINTORERIA!$B$3:$U$3,0)),0)} -> 0 | Z30: =IFERROR(R30*W30*IF(X30="USD",Y30,1),0) -> 0 | AD30: =IFERROR((SUMIFS(COMPRAS_HILO!$H$4:$H$203,COMPRAS_HILO!$B$4:$B$203,A30))*F30/SUMIFS($F$4:$F$503,$A$4:$A$503,A30),0) -> 0 | AE30: =M30 -> 0 | AF30: =Z30 -> 0 | AG30: =AD30+AE30+AF30 -> 0 | AH30: =IFERROR(AG30/S30,0) -> 0
A31: rib 1x1- jersey algodon -001 | B31: Acero | C31: =IFERROR(VLOOKUP(B31,COLORES!$A$4:$B$52,2,FALSE()),"") -> OSCURO | J31: =IFERROR(VLOOKUP(VLOOKUP(A31,PROGRAMAS!$A$4:$G$103,7,FALSE()),PRECIOS_TEJEDURIA!$A$4:$B$22,2,FALSE()),0) -> 0.6 | M31: =IFERROR(H31*J31*IF(K31="USD",L31,1),0) -> 0 | U31: =IFERROR(R31-S31,0) -> 0 | V31: =IFERROR(U31/R31,0) -> 0 | W31: {=IFERROR(INDEX(PRECIOS_TINTORERIA!$B$4:$U$15,MATCH(D31,PRECIOS_TINTORERIA!$A$4:$A$15,0),MATCH(VLOOKUP(A31,PROGRAMAS!$A$4:$G$103,7,FALSE()),PRECIOS_TINTORERIA!$B$3:$U$3,0)),0)} -> 0 | Z31: =IFERROR(R31*W31*IF(X31="USD",Y31,1),0) -> 0 | AD31: =IFERROR((SUMIFS(COMPRAS_HILO!$H$4:$H$203,COMPRAS_HILO!$B$4:$B$203,A31))*F31/SUMIFS($F$4:$F$503,$A$4:$A$503,A31),0) -> 0 | AE31: =M31 -> 0 | AF31: =Z31 -> 0 | AG31: =AD31+AE31+AF31 -> 0 | AH31: =IFERROR(AG31/S31,0) -> 0
C32: =IFERROR(VLOOKUP(B32,COLORES!$A$4:$B$52,2,FALSE()),"") | J32: =IFERROR(VLOOKUP(VLOOKUP(A32,PROGRAMAS!$A$4:$G$103,7,FALSE()),PRECIOS_TEJEDURIA!$A$4:$B$22,2,FALSE()),0) -> 0 | M32: =IFERROR(H32*J32*IF(K32="USD",L32,1),0) -> 0 | U32: =IFERROR(R32-S32,0) -> 0 | V32: =IFERROR(U32/R32,0) -> 0 | W32: {=IFERROR(INDEX(PRECIOS_TINTORERIA!$B$4:$U$15,MATCH(D32,PRECIOS_TINTORERIA!$A$4:$A$15,0),MATCH(VLOOKUP(A32,PROGRAMAS!$A$4:$G$103,7,FALSE()),PRECIOS_TINTORERIA!$B$3:$U$3,0)),0)} -> 0 | Z32: =IFERROR(R32*W32*IF(X32="USD",Y32,1),0) -> 0 | AD32: =IFERROR((SUMIFS(COMPRAS_HILO!$H$4:$H$203,COMPRAS_HILO!$B$4:$B$203,A32))*F32/SUMIFS($F$4:$F$503,$A$4:$A$503,A32),0) -> 0 | AE32: =M32 -> 0 | AF32: =Z32 -> 0 | AG32: =AD32+AE32+AF32 -> 0 | AH32: =IFERROR(AG32/S32,0) -> 0
C33: =IFERROR(VLOOKUP(B33,COLORES!$A$4:$B$52,2,FALSE()),"") | J33: =IFERROR(VLOOKUP(VLOOKUP(A33,PROGRAMAS!$A$4:$G$103,7,FALSE()),PRECIOS_TEJEDURIA!$A$4:$B$22,2,FALSE()),0) -> 0 | M33: =IFERROR(H33*J33*IF(K33="USD",L33,1),0) -> 0 | U33: =IFERROR(R33-S33,0) -> 0 | V33: =IFERROR(U33/R33,0) -> 0 | W33: {=IFERROR(INDEX(PRECIOS_TINTORERIA!$B$4:$U$15,MATCH(D33,PRECIOS_TINTORERIA!$A$4:$A$15,0),MATCH(VLOOKUP(A33,PROGRAMAS!$A$4:$G$103,7,FALSE()),PRECIOS_TINTORERIA!$B$3:$U$3,0)),0)} -> 0 | Z33: =IFERROR(R33*W33*IF(X33="USD",Y33,1),0) -> 0 | AD33: =IFERROR((SUMIFS(COMPRAS_HILO!$H$4:$H$203,COMPRAS_HILO!$B$4:$B$203,A33))*F33/SUMIFS($F$4:$F$503,$A$4:$A$503,A33),0) -> 0 | AE33: =M33 -> 0 | AF33: =Z33 -> 0 | AG33: =AD33+AE33+AF33 -> 0 | AH33: =IFERROR(AG33/S33,0) -> 0
C34: =IFERROR(VLOOKUP(B34,COLORES!$A$4:$B$52,2,FALSE()),"") | J34: =IFERROR(VLOOKUP(VLOOKUP(A34,PROGRAMAS!$A$4:$G$103,7,FALSE()),PRECIOS_TEJEDURIA!$A$4:$B$22,2,FALSE()),0) -> 0 | M34: =IFERROR(H34*J34*IF(K34="USD",L34,1),0) -> 0 | U34: =IFERROR(R34-S34,0) -> 0 | V34: =IFERROR(U34/R34,0) -> 0 | W34: {=IFERROR(INDEX(PRECIOS_TINTORERIA!$B$4:$U$15,MATCH(D34,PRECIOS_TINTORERIA!$A$4:$A$15,0),MATCH(VLOOKUP(A34,PROGRAMAS!$A$4:$G$103,7,FALSE()),PRECIOS_TINTORERIA!$B$3:$U$3,0)),0)} -> 0 | Z34: =IFERROR(R34*W34*IF(X34="USD",Y34,1),0) -> 0 | AD34: =IFERROR((SUMIFS(COMPRAS_HILO!$H$4:$H$203,COMPRAS_HILO!$B$4:$B$203,A34))*F34/SUMIFS($F$4:$F$503,$A$4:$A$503,A34),0) -> 0 | AE34: =M34 -> 0 | AF34: =Z34 -> 0 | AG34: =AD34+AE34+AF34 -> 0 | AH34: =IFERROR(AG34/S34,0) -> 0
C35: =IFERROR(VLOOKUP(B35,COLORES!$A$4:$B$52,2,FALSE()),"") | J35: =IFERROR(VLOOKUP(VLOOKUP(A35,PROGRAMAS!$A$4:$G$103,7,FALSE()),PRECIOS_TEJEDURIA!$A$4:$B$22,2,FALSE()),0) -> 0 | M35: =IFERROR(H35*J35*IF(K35="USD",L35,1),0) -> 0 | U35: =IFERROR(R35-S35,0) -> 0 | V35: =IFERROR(U35/R35,0) -> 0 | W35: {=IFERROR(INDEX(PRECIOS_TINTORERIA!$B$4:$U$15,MATCH(D35,PRECIOS_TINTORERIA!$A$4:$A$15,0),MATCH(VLOOKUP(A35,PROGRAMAS!$A$4:$G$103,7,FALSE()),PRECIOS_TINTORERIA!$B$3:$U$3,0)),0)} -> 0 | Z35: =IFERROR(R35*W35*IF(X35="USD",Y35,1),0) -> 0 | AD35: =IFERROR((SUMIFS(COMPRAS_HILO!$H$4:$H$203,COMPRAS_HILO!$B$4:$B$203,A35))*F35/SUMIFS($F$4:$F$503,$A$4:$A$503,A35),0) -> 0 | AE35: =M35 -> 0 | AF35: =Z35 -> 0 | AG35: =AD35+AE35+AF35 -> 0 | AH35: =IFERROR(AG35/S35,0) -> 0
C36: =IFERROR(VLOOKUP(B36,COLORES!$A$4:$B$52,2,FALSE()),"") | J36: =IFERROR(VLOOKUP(VLOOKUP(A36,PROGRAMAS!$A$4:$G$103,7,FALSE()),PRECIOS_TEJEDURIA!$A$4:$B$22,2,FALSE()),0) -> 0 | M36: =IFERROR(H36*J36*IF(K36="USD",L36,1),0) -> 0 | U36: =IFERROR(R36-S36,0) -> 0 | V36: =IFERROR(U36/R36,0) -> 0 | W36: {=IFERROR(INDEX(PRECIOS_TINTORERIA!$B$4:$U$15,MATCH(D36,PRECIOS_TINTORERIA!$A$4:$A$15,0),MATCH(VLOOKUP(A36,PROGRAMAS!$A$4:$G$103,7,FALSE()),PRECIOS_TINTORERIA!$B$3:$U$3,0)),0)} -> 0 | Z36: =IFERROR(R36*W36*IF(X36="USD",Y36,1),0) -> 0 | AD36: =IFERROR((SUMIFS(COMPRAS_HILO!$H$4:$H$203,COMPRAS_HILO!$B$4:$B$203,A36))*F36/SUMIFS($F$4:$F$503,$A$4:$A$503,A36),0) -> 0 | AE36: =M36 -> 0 | AF36: =Z36 -> 0 | AG36: =AD36+AE36+AF36 -> 0 | AH36: =IFERROR(AG36/S36,0) -> 0
C37: =IFERROR(VLOOKUP(B37,COLORES!$A$4:$B$52,2,FALSE()),"") | J37: =IFERROR(VLOOKUP(VLOOKUP(A37,PROGRAMAS!$A$4:$G$103,7,FALSE()),PRECIOS_TEJEDURIA!$A$4:$B$22,2,FALSE()),0) -> 0 | M37: =IFERROR(H37*J37*IF(K37="USD",L37,1),0) -> 0 | U37: =IFERROR(R37-S37,0) -> 0 | V37: =IFERROR(U37/R37,0) -> 0 | W37: {=IFERROR(INDEX(PRECIOS_TINTORERIA!$B$4:$U$15,MATCH(D37,PRECIOS_TINTORERIA!$A$4:$A$15,0),MATCH(VLOOKUP(A37,PROGRAMAS!$A$4:$G$103,7,FALSE()),PRECIOS_TINTORERIA!$B$3:$U$3,0)),0)} -> 0 | Z37: =IFERROR(R37*W37*IF(X37="USD",Y37,1),0) -> 0 | AD37: =IFERROR((SUMIFS(COMPRAS_HILO!$H$4:$H$203,COMPRAS_HILO!$B$4:$B$203,A37))*F37/SUMIFS($F$4:$F$503,$A$4:$A$503,A37),0) -> 0 | AE37: =M37 -> 0 | AF37: =Z37 -> 0 | AG37: =AD37+AE37+AF37 -> 0 | AH37: =IFERROR(AG37/S37,0) -> 0
C38: =IFERROR(VLOOKUP(B38,COLORES!$A$4:$B$52,2,FALSE()),"") | J38: =IFERROR(VLOOKUP(VLOOKUP(A38,PROGRAMAS!$A$4:$G$103,7,FALSE()),PRECIOS_TEJEDURIA!$A$4:$B$22,2,FALSE()),0) -> 0 | M38: =IFERROR(H38*J38*IF(K38="USD",L38,1),0) -> 0 | U38: =IFERROR(R38-S38,0) -> 0 | V38: =IFERROR(U38/R38,0) -> 0 | W38: {=IFERROR(INDEX(PRECIOS_TINTORERIA!$B$4:$U$15,MATCH(D38,PRECIOS_TINTORERIA!$A$4:$A$15,0),MATCH(VLOOKUP(A38,PROGRAMAS!$A$4:$G$103,7,FALSE()),PRECIOS_TINTORERIA!$B$3:$U$3,0)),0)} -> 0 | Z38: =IFERROR(R38*W38*IF(X38="USD",Y38,1),0) -> 0 | AD38: =IFERROR((SUMIFS(COMPRAS_HILO!$H$4:$H$203,COMPRAS_HILO!$B$4:$B$203,A38))*F38/SUMIFS($F$4:$F$503,$A$4:$A$503,A38),0) -> 0 | AE38: =M38 -> 0 | AF38: =Z38 -> 0 | AG38: =AD38+AE38+AF38 -> 0 | AH38: =IFERROR(AG38/S38,0) -> 0
C39: =IFERROR(VLOOKUP(B39,COLORES!$A$4:$B$52,2,FALSE()),"") | J39: =IFERROR(VLOOKUP(VLOOKUP(A39,PROGRAMAS!$A$4:$G$103,7,FALSE()),PRECIOS_TEJEDURIA!$A$4:$B$22,2,FALSE()),0) -> 0 | M39: =IFERROR(H39*J39*IF(K39="USD",L39,1),0) -> 0 | U39: =IFERROR(R39-S39,0) -> 0 | V39: =IFERROR(U39/R39,0) -> 0 | W39: {=IFERROR(INDEX(PRECIOS_TINTORERIA!$B$4:$U$15,MATCH(D39,PRECIOS_TINTORERIA!$A$4:$A$15,0),MATCH(VLOOKUP(A39,PROGRAMAS!$A$4:$G$103,7,FALSE()),PRECIOS_TINTORERIA!$B$3:$U$3,0)),0)} -> 0 | Z39: =IFERROR(R39*W39*IF(X39="USD",Y39,1),0) -> 0 | AD39: =IFERROR((SUMIFS(COMPRAS_HILO!$H$4:$H$203,COMPRAS_HILO!$B$4:$B$203,A39))*F39/SUMIFS($F$4:$F$503,$A$4:$A$503,A39),0) -> 0 | AE39: =M39 -> 0 | AF39: =Z39 -> 0 | AG39: =AD39+AE39+AF39 -> 0 | AH39: =IFERROR(AG39/S39,0) -> 0
C40: =IFERROR(VLOOKUP(B40,COLORES!$A$4:$B$52,2,FALSE()),"") | J40: =IFERROR(VLOOKUP(VLOOKUP(A40,PROGRAMAS!$A$4:$G$103,7,FALSE()),PRECIOS_TEJEDURIA!$A$4:$B$22,2,FALSE()),0) -> 0 | M40: =IFERROR(H40*J40*IF(K40="USD",L40,1),0) -> 0 | U40: =IFERROR(R40-S40,0) -> 0 | V40: =IFERROR(U40/R40,0) -> 0 | W40: {=IFERROR(INDEX(PRECIOS_TINTORERIA!$B$4:$U$15,MATCH(D40,PRECIOS_TINTORERIA!$A$4:$A$15,0),MATCH(VLOOKUP(A40,PROGRAMAS!$A$4:$G$103,7,FALSE()),PRECIOS_TINTORERIA!$B$3:$U$3,0)),0)} -> 0 | Z40: =IFERROR(R40*W40*IF(X40="USD",Y40,1),0) -> 0 | AD40: =IFERROR((SUMIFS(COMPRAS_HILO!$H$4:$H$203,COMPRAS_HILO!$B$4:$B$203,A40))*F40/SUMIFS($F$4:$F$503,$A$4:$A$503,A40),0) -> 0 | AE40: =M40 -> 0 | AF40: =Z40 -> 0 | AG40: =AD40+AE40+AF40 -> 0 | AH40: =IFERROR(AG40/S40,0) -> 0
C41: =IFERROR(VLOOKUP(B41,COLORES!$A$4:$B$52,2,FALSE()),"") | J41: =IFERROR(VLOOKUP(VLOOKUP(A41,PROGRAMAS!$A$4:$G$103,7,FALSE()),PRECIOS_TEJEDURIA!$A$4:$B$22,2,FALSE()),0) -> 0 | M41: =IFERROR(H41*J41*IF(K41="USD",L41,1),0) -> 0 | U41: =IFERROR(R41-S41,0) -> 0 | V41: =IFERROR(U41/R41,0) -> 0 | W41: {=IFERROR(INDEX(PRECIOS_TINTORERIA!$B$4:$U$15,MATCH(D41,PRECIOS_TINTORERIA!$A$4:$A$15,0),MATCH(VLOOKUP(A41,PROGRAMAS!$A$4:$G$103,7,FALSE()),PRECIOS_TINTORERIA!$B$3:$U$3,0)),0)} -> 0 | Z41: =IFERROR(R41*W41*IF(X41="USD",Y41,1),0) -> 0 | AD41: =IFERROR((SUMIFS(COMPRAS_HILO!$H$4:$H$203,COMPRAS_HILO!$B$4:$B$203,A41))*F41/SUMIFS($F$4:$F$503,$A$4:$A$503,A41),0) -> 0 | AE41: =M41 -> 0 | AF41: =Z41 -> 0 | AG41: =AD41+AE41+AF41 -> 0 | AH41: =IFERROR(AG41/S41,0) -> 0
C42: =IFERROR(VLOOKUP(B42,COLORES!$A$4:$B$52,2,FALSE()),"") | J42: =IFERROR(VLOOKUP(VLOOKUP(A42,PROGRAMAS!$A$4:$G$103,7,FALSE()),PRECIOS_TEJEDURIA!$A$4:$B$22,2,FALSE()),0) -> 0 | M42: =IFERROR(H42*J42*IF(K42="USD",L42,1),0) -> 0 | U42: =IFERROR(R42-S42,0) -> 0 | V42: =IFERROR(U42/R42,0) -> 0 | W42: {=IFERROR(INDEX(PRECIOS_TINTORERIA!$B$4:$U$15,MATCH(D42,PRECIOS_TINTORERIA!$A$4:$A$15,0),MATCH(VLOOKUP(A42,PROGRAMAS!$A$4:$G$103,7,FALSE()),PRECIOS_TINTORERIA!$B$3:$U$3,0)),0)} -> 0 | Z42: =IFERROR(R42*W42*IF(X42="USD",Y42,1),0) -> 0 | AD42: =IFERROR((SUMIFS(COMPRAS_HILO!$H$4:$H$203,COMPRAS_HILO!$B$4:$B$203,A42))*F42/SUMIFS($F$4:$F$503,$A$4:$A$503,A42),0) -> 0 | AE42: =M42 -> 0 | AF42: =Z42 -> 0 | AG42: =AD42+AE42+AF42 -> 0 | AH42: =IFERROR(AG42/S42,0) -> 0
C43: =IFERROR(VLOOKUP(B43,COLORES!$A$4:$B$52,2,FALSE()),"") | J43: =IFERROR(VLOOKUP(VLOOKUP(A43,PROGRAMAS!$A$4:$G$103,7,FALSE()),PRECIOS_TEJEDURIA!$A$4:$B$22,2,FALSE()),0) -> 0 | M43: =IFERROR(H43*J43*IF(K43="USD",L43,1),0) -> 0 | U43: =IFERROR(R43-S43,0) -> 0 | V43: =IFERROR(U43/R43,0) -> 0 | W43: {=IFERROR(INDEX(PRECIOS_TINTORERIA!$B$4:$U$15,MATCH(D43,PRECIOS_TINTORERIA!$A$4:$A$15,0),MATCH(VLOOKUP(A43,PROGRAMAS!$A$4:$G$103,7,FALSE()),PRECIOS_TINTORERIA!$B$3:$U$3,0)),0)} -> 0 | Z43: =IFERROR(R43*W43*IF(X43="USD",Y43,1),0) -> 0 | AD43: =IFERROR((SUMIFS(COMPRAS_HILO!$H$4:$H$203,COMPRAS_HILO!$B$4:$B$203,A43))*F43/SUMIFS($F$4:$F$503,$A$4:$A$503,A43),0) -> 0 | AE43: =M43 -> 0 | AF43: =Z43 -> 0 | AG43: =AD43+AE43+AF43 -> 0 | AH43: =IFERROR(AG43/S43,0) -> 0
... C503: =IFERROR(VLOOKUP(B503,COLORES!$A$4:$B$52,2,FALSE()),"") | J503: =IFERROR(VLOOKUP(VLOOKUP(A503,PROGRAMAS!$A$4:$G$103,7,FALSE()),PRECIOS_TEJEDURIA!$A$4:$B$22,2,FALSE()),0) -> 0 | M503: =IFERROR(H503*J503*IF(K503="USD",L503,1),0) -> 0 | U503: =IFERROR(R503-S503,0) -> 0 | V503: =IFERROR(U503/R503,0) -> 0 | W503: {=IFERROR(INDEX(PRECIOS_TINTORERIA!$B$4:$U$15,MATCH(D503,PRECIOS_TINTORERIA!$A$4:$A$15,0),MATCH(VLOOKUP(A503,PROGRAMAS!$A$4:$G$103,7,FALSE()),PRECIOS_TINTORERIA!$B$3:$U$3,0)),0)} -> 0 | Z503: =IFERROR(R503*W503*IF(X503="USD",Y503,1),0) -> 0 | AD503: =IFERROR((SUMIFS(COMPRAS_HILO!$H$4:$H$203,COMPRAS_HILO!$B$4:$B$203,A503))*F503/SUMIFS($F$4:$F$503,$A$4:$A$503,A503),0) -> 0 | AE503: =M503 -> 0 | AF503: =Z503 -> 0 | AG503: =AD503+AE503+AF503 -> 0 | AH503: =IFERROR(AG503/S503,0) -> 0

Sheet PRECIOS_TINTORERIA
A1: PRECIOS TINTORERÍA — S/. por kg recibido (matriz servicio × tela, escalable)
A2: REACTIVO=oscuros, DIRECTO=claros, PPT=perla/blancos, LAVADO=melange, TERMOFIJADO=spandex/lycra, COMPACTADO=algodón. Hay 20 columnas de tela y 12 filas de servicio editables. Si no aplica = vacío.
A3: TIPO SERVICIO | B3: Jersey cotton | C3: Pique 30/1 | D3: Wafle 30/1 | E3: French terry 24/1 | F3: Rib 1x1 | G3: Rib 2x1 lycrado | H3: Interlock 50/1 Pima | I3: Jersey 20/1 | J3: Jersey full lycra | K3: Pique pima | L3: Wafle pima | M3: French terry pima | N3: jersey pc
A4: REACTIVO (oscuros) | B4: 4 | C4: 2.7 | D4: 3 | E4: 3.5 | F4: 3 | G4: 3.2 | H4: 4 | I4: 3 | J4: 3.05 | K4: 3.5 | L4: 3.3 | M4: 3.8 | N4: 3
A5: DIRECTO (claros) | B5: 1.9 | C5: 1.95 | D5: 1.9 | E5: 2.3 | F5: 1.9 | G5: 2.1 | H5: 2.5 | I5: 1.9 | J5: 2.3 | K5: 2.3 | L5: 2.1 | M5: 2.5 | N5: 3
A6: PPT (perla/blanco) | B6: 1.2 | C6: 1.1 | D6: 1.2 | E6: 1.5 | F6: 1.2 | G6: 1.3 | H6: 1.8 | I6: 1.2 | J6: 1.5 | K6: 1.5 | L6: 1.3 | M6: 1.8 | N6: 3
A7: LAVADO (melange) | B7: 1 | C7: 1.1 | D7: 1 | E7: 1.2 | F7: 1 | G7: 1.1 | H7: 1.5 | I7: 1 | J7: 1.2 | K7: 1.2 | L7: 1.1 | M7: 1.5 | N7: 3
A8: TERMOFIJADO | G8: 1.5 | J8: 1.5
A9: COMPACTADO EN RAMA | B9: 0.8 | C9: 0.85 | D9: 0.8 | E9: 0.9 | F9: 0.8 | H9: 1 | I9: 0.8 | J9: 0.9 | K9: 1 | L9: 0.95 | M9: 1.05 | N9: 3

Sheet PRECIOS_TEJEDURIA
A1: PRECIOS TEJEDURÍA — S/. por kg recibido (no entregado)
A2: Tejeduría cobra por kg que se le envía. La merma es pérdida del programa, no del proveedor.
A3: TIPO TEJIDO | B3: PRECIO S/./kg | C3: PROVEEDOR HABITUAL | D3: NOTAS
A4: Jersey cotton | B4: 0.5 | C4: Tejeduría Andina
A5: Pique 30/1 | B5: 0.5 | C5: Tejeduría Andina
A6: Wafle 30/1 | B6: 0.45 | C6: Tejeduría Andina
A7: French terry 30/1 | B7: 0.4 | C7: Tejedos del Norte
A8: Rib 1x1 | B8: 0.6 | C8: Tejedos del Norte
A9: Rib 2x1 lycrado | B9: 0.8 | C9: Tejedos del Norte | D9: Más caro por lycra
A10: Interlock 50/1 Pima | B10: 1.2 | C10: Tejeduría Andina
A11: Jersey 20/1 | B11: 0.45 | C11: Tejeduría Andina
A12: full lycra | B12: 0.7
A13: Pique pima | B13: 0.7
A14: Wafle pima | B14: 0.7
A15: French terry pima | B15: 0.7
A16: jersey pc | B16: 0.7

Sheet INSTRUCCIONES
A1: SISTEMA COSTOS DE PRODUCCIÓN — OVERSHARK
A3: FLUJO COMPLETO DE UN PROGRAMA:
A4: 1. ANÁLISIS — Defines qué producir en base a inventario actual.
A5: 2. CREAR PROGRAMA — Vas a hoja PROGRAMAS, agregas fila con ID y descripción (ej: "PG2026-05-001 Jersey 30/1 negro+perla+azul").
A6: 3. COMPRAR HILO — Cuando llega la factura, registras en COMPRAS_HILO: kg, precio/kg, factura, asociada al programa.
A7: 4. ENVÍO A TEJEDURÍA — Registras en TEJEDURIA: kg enviados, tipo de tejido. Cuando regresa, llenas kg tela retornada y kg conos extorno.
A8: 5. ENVÍO A TINTORERÍA — Registras en TINTORERIA: kg enviados, tipo de servicio (reactivo/directo/ppt/lavado/etc). Cuando regresa, llenas kg final y rollos.
A9: 6. CIERRE PROGRAMA — En PROGRAMAS marca estado "CERRADO". El costo queda congelado.
A11: CÁLCULOS AUTOMÁTICOS:
A12: • COSTOS_PROGRAMA — suma costo hilo + costo tejido + costo teñido por programa.
A13: • Costo por kg final = Costo total / kg tela tintorería retornada.
A14: • Costo por prenda = Costo/kg × kg consumo prenda + indirectos prorrateados.
... A40: • ROJO = alerta

Sheet CONFIG
A1: CONFIGURACIÓN GENERAL
A2: Parámetro | B2: Valor | C2: Descripción
A3: Tipo de cambio S/. por USD | B3: 3.5 | C3: Tipo de cambio actual para reportes en USD
A4: Costos indirectos mensuales (S/.) | B4: 15000 | C4: Luz, alquiler, planilla admin. Se prorratea entre prendas producidas.
A5: Prendas producidas mes (estimadas) | B5: 8000 | C5: Para prorrateo de indirectos por prenda
A6: Margen merma estándar tejeduría | B6: 0.005 | C6: 0.5% es lo ideal en tejeduría
A7: Margen merma máximo tejeduría | B7: 0.01 | C7: 1% es el límite aceptable
A8: Margen merma estándar tintorería | B8: 0.05 | C8: 5% en tintorería es típico
A9: Margen merma máximo tintorería | B9: 0.07 | C9: 7% es el límite aceptable

Sheet PROVEEDORES
A1: PROVEEDORES — Hilos / Tejedurías / Tintorerías
A2: Lista de proveedores. TIPO indica si es de HILO, TEJEDURÍA o TINTORERÍA.
A3: PROVEEDOR | B3: TIPO | C3: RUC | D3: CONTACTO | E3: NOTAS
A4: COTTON MIX | B4: HILO | C4: 20111111111 | D4: Carlos Pérez | E4: Hilo policotton 30/1, 20/1
A5: FARIDE | B5: HILO | C5: 20222222222 | D5: Ana López | E5: Pima, algodón
A6: Tejeduría Andina | B6: TEJEDURÍA | C6: 20333333333 | D6: Roberto Sotelo | E6: Jersey, pique, wafle
A7: Tejedos del Norte | B7: TEJEDURÍA | C7: 20444444444 | E7: French terry, rib
A8: Tintorería Inca Color | B8: TINTORERÍA | C8: 20555555555 | D8: María Vargas | E8: Reactivo, directo, lavado
A9: TermoTeñidos SAC | B9: TINTORERÍA | C9: 20666666666 | E9: Termofijado, compactado

Sheet HILOS
A1: CATÁLOGO DE HILOS — Editable
A2: Tipos de hilo disponibles. PRECIO REFERENCIAL es solo para estimaciones; el precio real de cada compra se registra en COMPRAS_HILO.
A3: TIPO HILO | B3: COMPOSICIÓN | C3: PRECIO REFERENCIAL S/./kg | D3: FECHA ÚLTIMO PRECIO | E3: NOTAS
A4: Hilo 30/1 PC | B4: Policotton 65% poliéster 35% algodón | C4: 3.3 | D4: 2026-05-01 | E4: Para jersey 30/1, wafle 30/1, pique 30/1, rib 1x1
A5: Hilo 20/1 PC | B5: Policotton 65/35 | C5: 3.1 | D5: 2026-05-01 | E5: Para french terry 24/1, telas más pesadas
A6: Hilo 30/1 ALGODON | B6: Algodón pima 100% | C6: 8.5 | D6: 2026-04-15 | E6: Premium, para línea pima gold
A7: Hilo 24/1 Algodón | B7: Algodón 100% | C7: 5.8 | D7: 2026-04-20 | E7: Para french terry algodón
A8: Hilo 50/1 Pima | B8: Algodón pima 100% | C8: 9.5 | D8: 2026-04-15 | E8: Interlock pima
A9: Hilo 30/1 con Lycra | B9: Policotton + 5% Spandex | C9: 4.8 | D9: 2026-04-20 | E9: Rib 2x1 lycrado, top mujer
A10: hilo 50/1 cottom | C10: 10
A11: hilo 50/1 cotton +lycra 4%

Sheet COLORES
A1: CATÁLOGO DE COLORES — Editable
A2: Lista de colores que usas en programas. CATEGORÍA mapea al tipo de servicio en tintorería (oscuros=REACTIVO, claros=DIRECTO, etc.).
A3: COLOR | B3: CATEGORÍA | C3: SERVICIO TÍPICO | D3: NOTAS
A4: Negro | B4: OSCURO | C4: REACTIVO (oscuros)
A5: Perla | B5: PPT | C5: PPT (perla/blanco)
A6: Blanco | B6: PPT | C6: PPT (perla/blanco)
A7: Beige | B7: CLARO | C7: DIRECTO (claros)
A8: Topo | B8: CLARO | C8: DIRECTO (claros)
A9: Cemento | B9: CLARO | C9: DIRECTO (claros)
A10: Pacay | B10: CLARO | C10: DIRECTO (claros)
A11: Denim | B11: CLARO | C11: DIRECTO (claros)
A12: Palo Rosa | B12: CLARO | C12: DIRECTO (claros)
A13: Camote | B13: CLARO | C13: DIRECTO (claros)
A14: Azul Marino | B14: OSCURO | C14: REACTIVO (oscuros)
A15: Vino | B15: OSCURO | C15: REACTIVO (oscuros)
... A23: Rosa | B23: CLARO | C23: DIRECTO (claros)

Sheet STOCK_EXTORNO
A1: STOCK EXTORNO — Conos sobrantes de tejeduría (reusables para rectilíneos)
A2: Auto-calculado desde PROGRAMAS!Q (kg conos extorno). Estos kg son los conos que se devuelven y se valorizan al precio del hilo del programa.
A3: TIPO HILO | B3: KG EXTORNO ACUMULADO | C3: PRECIO PROMEDIO S/./kg | D3: VALOR S/. | E3: KG USADOS | F3: KG DISPONIBLES
A4: =IF(HILOS!A4="","",HILOS!A4) -> Hilo 30/1 PC | B4: =IFERROR(SUMIFS(PROGRAMAS!$S$4:$S$103,PROGRAMAS!$D$4:$D$103,A4),0) -> 5 | C4: =IFERROR(SUMIFS(COMPRAS_HILO!$H$4:$H$203,COMPRAS_HILO!$C$4:$C$203,A4)/SUMIFS(COMPRAS_HILO!$D$4:$D$203,COMPRAS_HILO!$C$4:$C$203,A4),0) -> 10.3875 | D4: =B4*C4 -> 51.9375 | F4: =B4-E4 -> 5
A5: =IF(HILOS!A5="","",HILOS!A5) -> Hilo 20/1 PC | B5: =IFERROR(SUMIFS(PROGRAMAS!$S$4:$S$103,PROGRAMAS!$D$4:$D$103,A5),0) -> 0 | C5: =IFERROR(SUMIFS(COMPRAS_HILO!$H$4:$H$203,COMPRAS_HILO!$C$4:$C$203,A5)/SUMIFS(COMPRAS_HILO!$D$4:$D$203,COMPRAS_HILO!$C$4:$C$203,A5),0) -> 0 | D5: =B5*C5 -> 0 | F5: =B5-E5 -> 0
A6: =IF(HILOS!A6="","",HILOS!A6) -> Hilo 30/1 ALGODON | B6: =IFERROR(SUMIFS(PROGRAMAS!$S$4:$S$103,PROGRAMAS!$D$4:$D$103,A6),0) -> 0 | C6: =IFERROR(SUMIFS(COMPRAS_HILO!$H$4:$H$203,COMPRAS_HILO!$C$4:$C$203,A6)/SUMIFS(COMPRAS_HILO!$D$4:$D$203,COMPRAS_HILO!$C$4:$C$203,A6),0) -> 13.8 | D6: =B6*C6 -> 0 | F6: =B6-E6 -> 0
A7: =IF(HILOS!A7="","",HILOS!A7) -> Hilo 24/1 Algodón | B7: =IFERROR(SUMIFS(PROGRAMAS!$S$4:$S$103,PROGRAMAS!$D$4:$D$103,A7),0) -> 0 | C7: =IFERROR(SUMIFS(COMPRAS_HILO!$H$4:$H$203,COMPRAS_HILO!$C$4:$C$203,A7)/SUMIFS(COMPRAS_HILO!$D$4:$D$203,COMPRAS_HILO!$C$4:$C$203,A7),0) -> 0 | D7: =B7*C7 -> 0 | F7: =B7-E7 -> 0
A8: =IF(HILOS!A8="","",HILOS!A8) -> Hilo 50/1 Pima | B8: =IFERROR(SUMIFS(PROGRAMAS!$S$4:$S$103,PROGRAMAS!$D$4:$D$103,A8),0) -> 0 | C8: =IFERROR(SUMIFS(COMPRAS_HILO!$H$4:$H$203,COMPRAS_HILO!$C$4:$C$203,A8)/SUMIFS(COMPRAS_HILO!$D$4:$D$203,COMPRAS_HILO!$C$4:$C$203,A8),0) -> 0 | D8: =B8*C8 -> 0 | F8: =B8-E8 -> 0
A9: =IF(HILOS!A9="","",HILOS!A9) -> Hilo 30/1 con Lycra | B9: =IFERROR(SUMIFS(PROGRAMAS!$S$4:$S$103,PROGRAMAS!$D$4:$D$103,A9),0) -> 0 | C9: =IFERROR(SUMIFS(COMPRAS_HILO!$H$4:$H$203,COMPRAS_HILO!$C$4:$C$203,A9)/SUMIFS(COMPRAS_HILO!$D$4:$D$203,COMPRAS_HILO!$C$4:$C$203,A9),0) -> 0 | D9: =B9*C9 -> 0 | F9: =B9-E9 -> 0
A10: =IF(HILOS!A10="","",HILOS!A10) -> hilo 50/1 cottom | B10: =IFERROR(SUMIFS(PROGRAMAS!$S$4:$S$103,PROGRAMAS!$D$4:$D$103,A10),0) -> 0 | C10: =IFERROR(SUMIFS(COMPRAS_HILO!$H$4:$H$203,COMPRAS_HILO!$C$4:$C$203,A10)/SUMIFS(COMPRAS_HILO!$D$4:$D$203,COMPRAS_HILO!$C$4:$C$203,A10),0) -> 0 | D10: =B10*C10 -> 0 | F10: =B10-E10 -> 0
A11: =IF(HILOS!A11="","",HILOS!A11) -> hilo 50/1 cotton +lycra 4% | B11: =IFERROR(SUMIFS(PROGRAMAS!$S$4:$S$103,PROGRAMAS!$D$4:$D$103,A11),0) -> 0 | C11: =IFERROR(SUMIFS(COMPRAS_HILO!$H$4:$H$203,COMPRAS_HILO!$C$4:$C$203,A11)/SUMIFS(COMPRAS_HILO!$D$4:$D$203,COMPRAS_HILO!$C$4:$C$203,A11),0) -> 19.25 | D11: =B11*C11 -> 0 | F11: =B11-E11 -> 0
A12: =IF(HILOS!A12="","",HILOS!A12) | B12: =IFERROR(SUMIFS(PROGRAMAS!$S$4:$S$103,PROGRAMAS!$D$4:$D$103,A12),0) -> 0 | C12: =IFERROR(SUMIFS(COMPRAS_HILO!$H$4:$H$203,COMPRAS_HILO!$C$4:$C$203,A12)/SUMIFS(COMPRAS_HILO!$D$4:$D$203,COMPRAS_HILO!$C$4:$C$203,A12),0) -> 0 | D12: =B12*C12 -> 0 | F12: =B12-E12 -> 0
A13: =IF(HILOS!A13="","",HILOS!A13) | B13: =IFERROR(SUMIFS(PROGRAMAS!$S$4:$S$103,PROGRAMAS!$D$4:$D$103,A13),0) -> 0 | C13: =IFERROR(SUMIFS(COMPRAS_HILO!$H$4:$H$203,COMPRAS_HILO!$C$4:$C$203,A13)/SUMIFS(COMPRAS_HILO!$D$4:$D$203,COMPRAS_HILO!$C$4:$C$203,A13),0) -> 0 | D13: =B13*C13 -> 0 | F13: =B13-E13 -> 0
A14: =IF(HILOS!A14="","",HILOS!A14) | B14: =IFERROR(SUMIFS(PROGRAMAS!$S$4:$S$103,PROGRAMAS!$D$4:$D$103,A14),0) -> 0 | C14: =IFERROR(SUMIFS(COMPRAS_HILO!$H$4:$H$203,COMPRAS_HILO!$C$4:$C$203,A14)/SUMIFS(COMPRAS_HILO!$D$4:$D$203,COMPRAS_HILO!$C$4:$C$203,A14),0) -> 0 | D14: =B14*C14 -> 0 | F14: =B14-E14 -> 0
A15: =IF(HILOS!A15="","",HILOS!A15) | B15: =IFERROR(SUMIFS(PROGRAMAS!$S$4:$S$103,PROGRAMAS!$D$4:$D$103,A15),0) -> 0 | C15: =IFERROR(SUMIFS(COMPRAS_HILO!$H$4:$H$203,COMPRAS_HILO!$C$4:$C$203,A15)/SUMIFS(COMPRAS_HILO!$D$4:$D$203,COMPRAS_HILO!$C$4:$C$203,A15),0) -> 0 | D15: =B15*C15 -> 0 | F15: =B15-E15 -> 0
... A22: =IF(HILOS!A22="","",HILOS!A22) | B22: =IFERROR(SUMIFS(PROGRAMAS!$S$4:$S$103,PROGRAMAS!$D$4:$D$103,A22),0) -> 0 | C22: =IFERROR(SUMIFS(COMPRAS_HILO!$H$4:$H$203,COMPRAS_HILO!$C$4:$C$203,A22)/SUMIFS(COMPRAS_HILO!$D$4:$D$203,COMPRAS_HILO!$C$4:$C$203,A22),0) -> 0 | D22: =B22*C22 -> 0 | F22: =B22-E22 -> 0

Sheet STOCK_INTERMEDIO
A1: STOCK INTERMEDIO — KG en cada etapa del flujo
A2: Auto-calculado. EN HILO = comprado - enviado a tejeduría. EN CRUDO = retornado tejeduría - enviado tintorería. FINAL = retornado tintorería.
A3: CATEGORÍA | B3: TIPO | C3: KG INGRESADO | D3: KG SALIDO (a sig. etapa) | E3: KG STOCK ACTUAL | F3: VALOR APROX S/. | G3: NOTAS
A4: STOCK EN HILO
A5: HILO | B5: =IF(HILOS!A4="","",HILOS!A4) -> Hilo 30/1 PC | C5: =IFERROR(SUMIFS(COMPRAS_HILO!$D$4:$D$203,COMPRAS_HILO!$C$4:$C$203,B5),0) -> 4000 | D5: =IFERROR(SUMIFS(PROGRAMAS!$Q$4:$Q$103,PROGRAMAS!$D$4:$D$103,B5),0) -> 1000 | E5: =C5-D5 -> 3000 | F5: =IFERROR(E5*SUMIFS(COMPRAS_HILO!$H$4:$H$203,COMPRAS_HILO!$C$4:$C$203,B5)/SUMIFS(COMPRAS_HILO!$D$4:$D$203,COMPRAS_HILO!$C$4:$C$203,B5),0) -> 31162.5
A6: HILO | B6: =IF(HILOS!A5="","",HILOS!A5) -> Hilo 20/1 PC | C6: =IFERROR(SUMIFS(COMPRAS_HILO!$D$4:$D$203,COMPRAS_HILO!$C$4:$C$203,B6),0) -> 0 | D6: =IFERROR(SUMIFS(PROGRAMAS!$Q$4:$Q$103,PROGRAMAS!$D$4:$D$103,B6),0) -> 0 | E6: =C6-D6 -> 0 | F6: =IFERROR(E6*SUMIFS(COMPRAS_HILO!$H$4:$H$203,COMPRAS_HILO!$C$4:$C$203,B6)/SUMIFS(COMPRAS_HILO!$D$4:$D$203,COMPRAS_HILO!$C$4:$C$203,B6),0) -> 0
A7: HILO | B7: =IF(HILOS!A6="","",HILOS!A6) -> Hilo 30/1 ALGODON | C7: =IFERROR(SUMIFS(COMPRAS_HILO!$D$4:$D$203,COMPRAS_HILO!$C$4:$C$203,B7),0) -> 660 | D7: =IFERROR(SUMIFS(PROGRAMAS!$Q$4:$Q$103,PROGRAMAS!$D$4:$D$103,B7),0) -> 0 | E7: =C7-D7 -> 660 | F7: =IFERROR(E7*SUMIFS(COMPRAS_HILO!$H$4:$H$203,COMPRAS_HILO!$C$4:$C$203,B7)/SUMIFS(COMPRAS_HILO!$D$4:$D$203,COMPRAS_HILO!$C$4:$C$203,B7),0) -> 9108
A8: HILO | B8: =IF(HILOS!A7="","",HILOS!A7) -> Hilo 24/1 Algodón | C8: =IFERROR(SUMIFS(COMPRAS_HILO!$D$4:$D$203,COMPRAS_HILO!$C$4:$C$203,B8),0) -> 0 | D8: =IFERROR(SUMIFS(PROGRAMAS!$Q$4:$Q$103,PROGRAMAS!$D$4:$D$103,B8),0) -> 0 | E8: =C8-D8 -> 0 | F8: =IFERROR(E8*SUMIFS(COMPRAS_HILO!$H$4:$H$203,COMPRAS_HILO!$C$4:$C$203,B8)/SUMIFS(COMPRAS_HILO!$D$4:$D$203,COMPRAS_HILO!$C$4:$C$203,B8),0) -> 0
A9: HILO | B9: =IF(HILOS!A8="","",HILOS!A8) -> Hilo 50/1 Pima | C9: =IFERROR(SUMIFS(COMPRAS_HILO!$D$4:$D$203,COMPRAS_HILO!$C$4:$C$203,B9),0) -> 0 | D9: =IFERROR(SUMIFS(PROGRAMAS!$Q$4:$Q$103,PROGRAMAS!$D$4:$D$103,B9),0) -> 0 | E9: =C9-D9 -> 0 | F9: =IFERROR(E9*SUMIFS(COMPRAS_HILO!$H$4:$H$203,COMPRAS_HILO!$C$4:$C$203,B9)/SUMIFS(COMPRAS_HILO!$D$4:$D$203,COMPRAS_HILO!$C$4:$C$203,B9),0) -> 0
A10: HILO | B10: =IF(HILOS!A9="","",HILOS!A9) -> Hilo 30/1 con Lycra | C10: =IFERROR(SUMIFS(COMPRAS_HILO!$D$4:$D$203,COMPRAS_HILO!$C$4:$C$203,B10),0) -> 0 | D10: =IFERROR(SUMIFS(PROGRAMAS!$Q$4:$Q$103,PROGRAMAS!$D$4:$D$103,B10),0) -> 0 | E10: =C10-D10 -> 0 | F10: =IFERROR(E10*SUMIFS(COMPRAS_HILO!$H$4:$H$203,COMPRAS_HILO!$C$4:$C$203,B10)/SUMIFS(COMPRAS_HILO!$D$4:$D$203,COMPRAS_HILO!$C$4:$C$203,B10),0) -> 0
A11: HILO | B11: =IF(HILOS!A10="","",HILOS!A10) -> hilo 50/1 cottom | C11: =IFERROR(SUMIFS(COMPRAS_HILO!$D$4:$D$203,COMPRAS_HILO!$C$4:$C$203,B11),0) -> 0 | D11: =IFERROR(SUMIFS(PROGRAMAS!$Q$4:$Q$103,PROGRAMAS!$D$4:$D$103,B11),0) -> 0 | E11: =C11-D11 -> 0 | F11: =IFERROR(E11*SUMIFS(COMPRAS_HILO!$H$4:$H$203,COMPRAS_HILO!$C$4:$C$203,B11)/SUMIFS(COMPRAS_HILO!$D$4:$D$203,COMPRAS_HILO!$C$4:$C$203,B11),0) -> 0
A12: HILO | B12: =IF(HILOS!A11="","",HILOS!A11) -> hilo 50/1 cotton +lycra 4% | C12: =IFERROR(SUMIFS(COMPRAS_HILO!$D$4:$D$203,COMPRAS_HILO!$C$4:$C$203,B12),0) -> 500 | D12: =IFERROR(SUMIFS(PROGRAMAS!$Q$4:$Q$103,PROGRAMAS!$D$4:$D$103,B12),0) -> 500 | E12: =C12-D12 -> 0 | F12: =IFERROR(E12*SUMIFS(COMPRAS_HILO!$H$4:$H$203,COMPRAS_HILO!$C$4:$C$203,B12)/SUMIFS(COMPRAS_HILO!$D$4:$D$203,COMPRAS_HILO!$C$4:$C$203,B12),0) -> 0
A13: HILO | B13: =IF(HILOS!A12="","",HILOS!A12) | C13: =IFERROR(SUMIFS(COMPRAS_HILO!$D$4:$D$203,COMPRAS_HILO!$C$4:$C$203,B13),0) -> 0 | D13: =IFERROR(SUMIFS(PROGRAMAS!$Q$4:$Q$103,PROGRAMAS!$D$4:$D$103,B13),0) -> 0 | E13: =C13-D13 -> 0 | F13: =IFERROR(E13*SUMIFS(COMPRAS_HILO!$H$4:$H$203,COMPRAS_HILO!$C$4:$C$203,B13)/SUMIFS(COMPRAS_HILO!$D$4:$D$203,COMPRAS_HILO!$C$4:$C$203,B13),0) -> 0
A14: HILO | B14: =IF(HILOS!A13="","",HILOS!A13) | C14: =IFERROR(SUMIFS(COMPRAS_HILO!$D$4:$D$203,COMPRAS_HILO!$C$4:$C$203,B14),0) -> 0 | D14: =IFERROR(SUMIFS(PROGRAMAS!$Q$4:$Q$103,PROGRAMAS!$D$4:$D$103,B14),0) -> 0 | E14: =C14-D14 -> 0 | F14: =IFERROR(E14*SUMIFS(COMPRAS_HILO!$H$4:$H$203,COMPRAS_HILO!$C$4:$C$203,B14)/SUMIFS(COMPRAS_HILO!$D$4:$D$203,COMPRAS_HILO!$C$4:$C$203,B14),0) -> 0
A15: HILO | B15: =IF(HILOS!A14="","",HILOS!A14) | C15: =IFERROR(SUMIFS(COMPRAS_HILO!$D$4:$D$203,COMPRAS_HILO!$C$4:$C$203,B15),0) -> 0 | D15: =IFERROR(SUMIFS(PROGRAMAS!$Q$4:$Q$103,PROGRAMAS!$D$4:$D$103,B15),0) -> 0 | E15: =C15-D15 -> 0 | F15: =IFERROR(E15*SUMIFS(COMPRAS_HILO!$H$4:$H$203,COMPRAS_HILO!$C$4:$C$203,B15)/SUMIFS(COMPRAS_HILO!$D$4:$D$203,COMPRAS_HILO!$C$4:$C$203,B15),0) -> 0
A16: HILO | B16: =IF(HILOS!A15="","",HILOS!A15) | C16: =IFERROR(SUMIFS(COMPRAS_HILO!$D$4:$D$203,COMPRAS_HILO!$C$4:$C$203,B16),0) -> 0 | D16: =IFERROR(SUMIFS(PROGRAMAS!$Q$4:$Q$103,PROGRAMAS!$D$4:$D$103,B16),0) -> 0 | E16: =C16-D16 -> 0 | F16: =IFERROR(E16*SUMIFS(COMPRAS_HILO!$H$4:$H$203,COMPRAS_HILO!$C$4:$C$203,B16)/SUMIFS(COMPRAS_HILO!$D$4:$D$203,COMPRAS_HILO!$C$4:$C$203,B16),0) -> 0
... A23: HILO | B23: =IF(HILOS!A22="","",HILOS!A22) | C23: =IFERROR(SUMIFS(COMPRAS_HILO!$D$4:$D$203,COMPRAS_HILO!$C$4:$C$203,B23),0) -> 0 | D23: =IFERROR(SUMIFS(PROGRAMAS!$Q$4:$Q$103,PROGRAMAS!$D$4:$D$103,B23),0) -> 0 | E23: =C23-D23 -> 0 | F23: =IFERROR(E23*SUMIFS(COMPRAS_HILO!$H$4:$H$203,COMPRAS_HILO!$C$4:$C$203,B23)/SUMIFS(COMPRAS_HILO!$D$4:$D$203,COMPRAS_HILO!$C$4:$C$203,B23),0) -> 0
A25: STOCK EN CRUDO (tela tejida sin teñir)
A26: CRUDO | B26: =IF(PRECIOS_TEJEDURIA!A4="","",PRECIOS_TEJEDURIA!A4) -> Jersey cotton | C26: =IFERROR(SUMIFS(PROGRAMAS!$R$4:$R$103,PROGRAMAS!$G$4:$G$103,B26),0) -> 0 | D26: =IFERROR(SUMIFS(PROGRAMAS!$V$4:$V$103,PROGRAMAS!$G$4:$G$103,B26),0) -> 0 | E26: =C26-D26 -> 0 | F26: =""
A27: CRUDO | B27: =IF(PRECIOS_TEJEDURIA!A5="","",PRECIOS_TEJEDURIA!A5) -> Pique 30/1 | C27: =IFERROR(SUMIFS(PROGRAMAS!$R$4:$R$103,PROGRAMAS!$G$4:$G$103,B27),0) -> 980 | D27: =IFERROR(SUMIFS(PROGRAMAS!$V$4:$V$103,PROGRAMAS!$G$4:$G$103,B27),0) -> 980 | E27: =C27-D27 -> 0 | F27: =""
A28: CRUDO | B28: =IF(PRECIOS_TEJEDURIA!A6="","",PRECIOS_TEJEDURIA!A6) -> Wafle 30/1 | C28: =IFERROR(SUMIFS(PROGRAMAS!$R$4:$R$103,PROGRAMAS!$G$4:$G$103,B28),0) -> 0 | D28: =IFERROR(SUMIFS(PROGRAMAS!$V$4:$V$103,PROGRAMAS!$G$4:$G$103,B28),0) -> 0 | E28: =C28-D28 -> 0 | F28: =""
A29: CRUDO | B29: =IF(PRECIOS_TEJEDURIA!A7="","",PRECIOS_TEJEDURIA!A7) -> French terry 30/1 | C29: =IFERROR(SUMIFS(PROGRAMAS!$R$4:$R$103,PROGRAMAS!$G$4:$G$103,B29),0) -> 0 | D29: =IFERROR(SUMIFS(PROGRAMAS!$V$4:$V$103,PROGRAMAS!$G$4:$G$103,B29),0) -> 0 | E29: =C29-D29 -> 0 | F29: =""
A30: CRUDO | B30: =IF(PRECIOS_TEJEDURIA!A8="","",PRECIOS_TEJEDURIA!A8) -> Rib 1x1 | C30: =IFERROR(SUMIFS(PROGRAMAS!$R$4:$R$103,PROGRAMAS!$G$4:$G$103,B30),0) -> 0 | D30: =IFERROR(SUMIFS(PROGRAMAS!$V$4:$V$103,PROGRAMAS!$G$4:$G$103,B30),0) -> 0 | E30: =C30-D30 -> 0 | F30: =""
A31: CRUDO | B31: =IF(PRECIOS_TEJEDURIA!A9="","",PRECIOS_TEJEDURIA!A9) -> Rib 2x1 lycrado | C31: =IFERROR(SUMIFS(PROGRAMAS!$R$4:$R$103,PROGRAMAS!$G$4:$G$103,B31),0) -> 0 | D31: =IFERROR(SUMIFS(PROGRAMAS!$V$4:$V$103,PROGRAMAS!$G$4:$G$103,B31),0) -> 0 | E31: =C31-D31 -> 0 | F31: =""
A32: CRUDO | B32: =IF(PRECIOS_TEJEDURIA!A10="","",PRECIOS_TEJEDURIA!A10) -> Interlock 50/1 Pima | C32: =IFERROR(SUMIFS(PROGRAMAS!$R$4:$R$103,PROGRAMAS!$G$4:$G$103,B32),0) -> 0 | D32: =IFERROR(SUMIFS(PROGRAMAS!$V$4:$V$103,PROGRAMAS!$G$4:$G$103,B32),0) -> 0 | E32: =C32-D32 -> 0 | F32: =""
A33: CRUDO | B33: =IF(PRECIOS_TEJEDURIA!A11="","",PRECIOS_TEJEDURIA!A11) -> Jersey 20/1 | C33: =IFERROR(SUMIFS(PROGRAMAS!$R$4:$R$103,PROGRAMAS!$G$4:$G$103,B33),0) -> 0 | D33: =IFERROR(SUMIFS(PROGRAMAS!$V$4:$V$103,PROGRAMAS!$G$4:$G$103,B33),0) -> 0 | E33: =C33-D33 -> 0 | F33: =""
A34: CRUDO | B34: =IF(PRECIOS_TEJEDURIA!A12="","",PRECIOS_TEJEDURIA!A12) -> full lycra | C34: =IFERROR(SUMIFS(PROGRAMAS!$R$4:$R$103,PROGRAMAS!$G$4:$G$103,B34),0) -> 0 | D34: =IFERROR(SUMIFS(PROGRAMAS!$V$4:$V$103,PROGRAMAS!$G$4:$G$103,B34),0) -> 0 | E34: =C34-D34 -> 0 | F34: =""
A35: CRUDO | B35: =IF(PRECIOS_TEJEDURIA!A13="","",PRECIOS_TEJEDURIA!A13) -> Pique pima | C35: =IFERROR(SUMIFS(PROGRAMAS!$R$4:$R$103,PROGRAMAS!$G$4:$G$103,B35),0) -> 0 | D35: =IFERROR(SUMIFS(PROGRAMAS!$V$4:$V$103,PROGRAMAS!$G$4:$G$103,B35),0) -> 0 | E35: =C35-D35 -> 0 | F35: =""
A36: CRUDO | B36: =IF(PRECIOS_TEJEDURIA!A14="","",PRECIOS_TEJEDURIA!A14) -> Wafle pima | C36: =IFERROR(SUMIFS(PROGRAMAS!$R$4:$R$103,PROGRAMAS!$G$4:$G$103,B36),0) -> 0 | D36: =IFERROR(SUMIFS(PROGRAMAS!$V$4:$V$103,PROGRAMAS!$G$4:$G$103,B36),0) -> 0 | E36: =C36-D36 -> 0 | F36: =""
A37: CRUDO | B37: =IF(PRECIOS_TEJEDURIA!A15="","",PRECIOS_TEJEDURIA!A15) -> French terry pima | C37: =IFERROR(SUMIFS(PROGRAMAS!$R$4:$R$103,PROGRAMAS!$G$4:$G$103,B37),0) -> 0 | D37: =IFERROR(SUMIFS(PROGRAMAS!$V$4:$V$103,PROGRAMAS!$G$4:$G$103,B37),0) -> 0 | E37: =C37-D37 -> 0 | F37: =""
... A44: CRUDO | B44: =IF(PRECIOS_TEJEDURIA!A22="","",PRECIOS_TEJEDURIA!A22) | C44: =IFERROR(SUMIFS(PROGRAMAS!$R$4:$R$103,PROGRAMAS!$G$4:$G$103,B44),0) -> 0 | D44: =IFERROR(SUMIFS(PROGRAMAS!$V$4:$V$103,PROGRAMAS!$G$4:$G$103,B44),0) -> 0 | E44: =C44-D44 -> 0 | F44: =""
A46: STOCK FINAL (tela teñida lista en planta)
A47: FINAL | B47: =IF(PRECIOS_TEJEDURIA!A4="","",PRECIOS_TEJEDURIA!A4) -> Jersey cotton | C47: =IFERROR(SUMIFS(PROGRAMAS!$W$4:$W$103,PROGRAMAS!$G$4:$G$103,B47),0) -> 0 | D47: 0 | E47: =C47-D47 -> 0
A48: FINAL | B48: =IF(PRECIOS_TEJEDURIA!A5="","",PRECIOS_TEJEDURIA!A5) -> Pique 30/1 | C48: =IFERROR(SUMIFS(PROGRAMAS!$W$4:$W$103,PROGRAMAS!$G$4:$G$103,B48),0) -> 890 | D48: 0 | E48: =C48-D48 -> 890
A49: FINAL | B49: =IF(PRECIOS_TEJEDURIA!A6="","",PRECIOS_TEJEDURIA!A6) -> Wafle 30/1 | C49: =IFERROR(SUMIFS(PROGRAMAS!$W$4:$W$103,PROGRAMAS!$G$4:$G$103,B49),0) -> 0 | D49: 0 | E49: =C49-D49 -> 0
A50: FINAL | B50: =IF(PRECIOS_TEJEDURIA!A7="","",PRECIOS_TEJEDURIA!A7) -> French terry 30/1 | C50: =IFERROR(SUMIFS(PROGRAMAS!$W$4:$W$103,PROGRAMAS!$G$4:$G$103,B50),0) -> 0 | D50: 0 | E50: =C50-D50 -> 0
A51: FINAL | B51: =IF(PRECIOS_TEJEDURIA!A8="","",PRECIOS_TEJEDURIA!A8) -> Rib 1x1 | C51: =IFERROR(SUMIFS(PROGRAMAS!$W$4:$W$103,PROGRAMAS!$G$4:$G$103,B51),0) -> 0 | D51: 0 | E51: =C51-D51 -> 0
A52: FINAL | B52: =IF(PRECIOS_TEJEDURIA!A9="","",PRECIOS_TEJEDURIA!A9) -> Rib 2x1 lycrado | C52: =IFERROR(SUMIFS(PROGRAMAS!$W$4:$W$103,PROGRAMAS!$G$4:$G$103,B52),0) -> 0 | D52: 0 | E52: =C52-D52 -> 0
A53: FINAL | B53: =IF(PRECIOS_TEJEDURIA!A10="","",PRECIOS_TEJEDURIA!A10) -> Interlock 50/1 Pima | C53: =IFERROR(SUMIFS(PROGRAMAS!$W$4:$W$103,PROGRAMAS!$G$4:$G$103,B53),0) -> 0 | D53: 0 | E53: =C53-D53 -> 0
A54: FINAL | B54: =IF(PRECIOS_TEJEDURIA!A11="","",PRECIOS_TEJEDURIA!A11) -> Jersey 20/1 | C54: =IFERROR(SUMIFS(PROGRAMAS!$W$4:$W$103,PROGRAMAS!$G$4:$G$103,B54),0) -> 0 | D54: 0 | E54: =C54-D54 -> 0
A55: FINAL | B55: =IF(PRECIOS_TEJEDURIA!A12="","",PRECIOS_TEJEDURIA!A12) -> full lycra | C55: =IFERROR(SUMIFS(PROGRAMAS!$W$4:$W$103,PROGRAMAS!$G$4:$G$103,B55),0) -> 0 | D55: 0 | E55: =C55-D55 -> 0
A56: FINAL | B56: =IF(PRECIOS_TEJEDURIA!A13="","",PRECIOS_TEJEDURIA!A13) -> Pique pima | C56: =IFERROR(SUMIFS(PROGRAMAS!$W$4:$W$103,PROGRAMAS!$G$4:$G$103,B56),0) -> 0 | D56: 0 | E56: =C56-D56 -> 0
A57: FINAL | B57: =IF(PRECIOS_TEJEDURIA!A14="","",PRECIOS_TEJEDURIA!A14) -> Wafle pima | C57: =IFERROR(SUMIFS(PROGRAMAS!$W$4:$W$103,PROGRAMAS!$G$4:$G$103,B57),0) -> 0 | D57: 0 | E57: =C57-D57 -> 0
A58: FINAL | B58: =IF(PRECIOS_TEJEDURIA!A15="","",PRECIOS_TEJEDURIA!A15) -> French terry pima | C58: =IFERROR(SUMIFS(PROGRAMAS!$W$4:$W$103,PROGRAMAS!$G$4:$G$103,B58),0) -> 0 | D58: 0 | E58: =C58-D58 -> 0
... A65: FINAL | B65: =IF(PRECIOS_TEJEDURIA!A22="","",PRECIOS_TEJEDURIA!A22) | C65: =IFERROR(SUMIFS(PROGRAMAS!$W$4:$W$103,PROGRAMAS!$G$4:$G$103,B65),0) -> 0 | D65: 0 | E65: =C65-D65 -> 0

Sheet CUENTAS_POR_PAGAR
A1: CUENTAS POR PAGAR — Facturas pendientes y parciales
A2: Auto-consolidado. Filtra ESTADO=PENDIENTE o PARCIAL para ver lo que debes. Suma SALDO = total adeudado.
A3: ORIGEN | B3: FECHA | C3: PROVEEDOR | D3: N° FACTURA | E3: CONCEPTO | F3: TOTAL S/. | G3: PAGADO S/. | H3: SALDO S/. | I3: ESTADO
A4: HILO | B4: =IF(COMPRAS_HILO!A4="","",COMPRAS_HILO!A4) -> 46113 | C4: =IF(COMPRAS_HILO!I4="","",COMPRAS_HILO!I4) -> COTTON MIX | D4: =IF(COMPRAS_HILO!J4="","",COMPRAS_HILO!J4) -> COTTOON-001 | E4: =IF(COMPRAS_HILO!C4="","","Compra "&COMPRAS_HILO!C4) -> Compra Hilo 30/1 PC | F4: =IF(COMPRAS_HILO!H4=0,"",COMPRAS_HILO!H4) -> 10500 | G4: =IF(COMPRAS_HILO!O4=0,"",COMPRAS_HILO!O4) -> 10500 | H4: =IF(COMPRAS_HILO!P4=0,"",COMPRAS_HILO!P4) | I4: =IF(COMPRAS_HILO!M4="","",COMPRAS_HILO!M4) -> PAGADO
A5: HILO | B5: =IF(COMPRAS_HILO!A5="","",COMPRAS_HILO!A5) -> 46152 | C5: =IF(COMPRAS_HILO!I5="","",COMPRAS_HILO!I5) -> COTTON MIX | D5: =IF(COMPRAS_HILO!J5="","",COMPRAS_HILO!J5) -> f002-4472 | E5: =IF(COMPRAS_HILO!C5="","","Compra "&COMPRAS_HILO!C5) -> Compra hilo 50/1 cotton +lycra 4% | F5: =IF(COMPRAS_HILO!H5=0,"",COMPRAS_HILO!H5) -> 9625 | G5: =IF(COMPRAS_HILO!O5=0,"",COMPRAS_HILO!O5) -> 9525 | H5: =IF(COMPRAS_HILO!P5=0,"",COMPRAS_HILO!P5) -> 100 | I5: =IF(COMPRAS_HILO!M5="","",COMPRAS_HILO!M5) -> PAGADO
A6: HILO | B6: =IF(COMPRAS_HILO!A6="","",COMPRAS_HILO!A6) | C6: =IF(COMPRAS_HILO!I6="","",COMPRAS_HILO!I6) -> COTTON MIX | D6: =IF(COMPRAS_HILO!J6="","",COMPRAS_HILO!J6) | E6: =IF(COMPRAS_HILO!C6="","","Compra "&COMPRAS_HILO!C6) -> Compra Hilo 30/1 PC | F6: =IF(COMPRAS_HILO!H6=0,"",COMPRAS_HILO!H6) -> 31050 | G6: =IF(COMPRAS_HILO!O6=0,"",COMPRAS_HILO!O6) | H6: =IF(COMPRAS_HILO!P6=0,"",COMPRAS_HILO!P6) -> 31050 | I6: =IF(COMPRAS_HILO!M6="","",COMPRAS_HILO!M6) -> PAGADO
A7: HILO | B7: =IF(COMPRAS_HILO!A7="","",COMPRAS_HILO!A7) | C7: =IF(COMPRAS_HILO!I7="","",COMPRAS_HILO!I7) -> COTTON MIX | D7: =IF(COMPRAS_HILO!J7="","",COMPRAS_HILO!J7) | E7: =IF(COMPRAS_HILO!C7="","","Compra "&COMPRAS_HILO!C7) -> Compra Hilo 30/1 ALGODON | F7: =IF(COMPRAS_HILO!H7=0,"",COMPRAS_HILO!H7) -> 9108 | G7: =IF(COMPRAS_HILO!O7=0,"",COMPRAS_HILO!O7) | H7: =IF(COMPRAS_HILO!P7=0,"",COMPRAS_HILO!P7) -> 9108 | I7: =IF(COMPRAS_HILO!M7="","",COMPRAS_HILO!M7) -> PAGADO
A8: HILO | B8: =IF(COMPRAS_HILO!A8="","",COMPRAS_HILO!A8) | C8: =IF(COMPRAS_HILO!I8="","",COMPRAS_HILO!I8) | D8: =IF(COMPRAS_HILO!J8="","",COMPRAS_HILO!J8) | E8: =IF(COMPRAS_HILO!C8="","","Compra "&COMPRAS_HILO!C8) | F8: =IF(COMPRAS_HILO!H8=0,"",COMPRAS_HILO!H8) | G8: =IF(COMPRAS_HILO!O8=0,"",COMPRAS_HILO!O8) | H8: =IF(COMPRAS_HILO!P8=0,"",COMPRAS_HILO!P8) | I8: =IF(COMPRAS_HILO!M8="","",COMPRAS_HILO!M8)
A9: HILO | B9: =IF(COMPRAS_HILO!A9="","",COMPRAS_HILO!A9) | C9: =IF(COMPRAS_HILO!I9="","",COMPRAS_HILO!I9) | D9: =IF(COMPRAS_HILO!J9="","",COMPRAS_HILO!J9) | E9: =IF(COMPRAS_HILO!C9="","","Compra "&COMPRAS_HILO!C9) | F9: =IF(COMPRAS_HILO!H9=0,"",COMPRAS_HILO!H9) | G9: =IF(COMPRAS_HILO!O9=0,"",COMPRAS_HILO!O9) | H9: =IF(COMPRAS_HILO!P9=0,"",COMPRAS_HILO!P9) | I9: =IF(COMPRAS_HILO!M9="","",COMPRAS_HILO!M9)
A10: HILO | B10: =IF(COMPRAS_HILO!A10="","",COMPRAS_HILO!A10) | C10: =IF(COMPRAS_HILO!I10="","",COMPRAS_HILO!I10) | D10: =IF(COMPRAS_HILO!J10="","",COMPRAS_HILO!J10) | E10: =IF(COMPRAS_HILO!C10="","","Compra "&COMPRAS_HILO!C10) | F10: =IF(COMPRAS_HILO!H10=0,"",COMPRAS_HILO!H10) | G10: =IF(COMPRAS_HILO!O10=0,"",COMPRAS_HILO!O10) | H10: =IF(COMPRAS_HILO!P10=0,"",COMPRAS_HILO!P10) | I10: =IF(COMPRAS_HILO!M10="","",COMPRAS_HILO!M10)
A11: HILO | B11: =IF(COMPRAS_HILO!A11="","",COMPRAS_HILO!A11) | C11: =IF(COMPRAS_HILO!I11="","",COMPRAS_HILO!I11) | D11: =IF(COMPRAS_HILO!J11="","",COMPRAS_HILO!J11) | E11: =IF(COMPRAS_HILO!C11="","","Compra "&COMPRAS_HILO!C11) | F11: =IF(COMPRAS_HILO!H11=0,"",COMPRAS_HILO!H11) | G11: =IF(COMPRAS_HILO!O11=0,"",COMPRAS_HILO!O11) | H11: =IF(COMPRAS_HILO!P11=0,"",COMPRAS_HILO!P11) | I11: =IF(COMPRAS_HILO!M11="","",COMPRAS_HILO!M11)
A12: HILO | B12: =IF(COMPRAS_HILO!A12="","",COMPRAS_HILO!A12) | C12: =IF(COMPRAS_HILO!I12="","",COMPRAS_HILO!I12) | D12: =IF(COMPRAS_HILO!J12="","",COMPRAS_HILO!J12) | E12: =IF(COMPRAS_HILO!C12="","","Compra "&COMPRAS_HILO!C12) | F12: =IF(COMPRAS_HILO!H12=0,"",COMPRAS_HILO!H12) | G12: =IF(COMPRAS_HILO!O12=0,"",COMPRAS_HILO!O12) | H12: =IF(COMPRAS_HILO!P12=0,"",COMPRAS_HILO!P12) | I12: =IF(COMPRAS_HILO!M12="","",COMPRAS_HILO!M12)
A13: HILO | B13: =IF(COMPRAS_HILO!A13="","",COMPRAS_HILO!A13) | C13: =IF(COMPRAS_HILO!I13="","",COMPRAS_HILO!I13) | D13: =IF(COMPRAS_HILO!J13="","",COMPRAS_HILO!J13) | E13: =IF(COMPRAS_HILO!C13="","","Compra "&COMPRAS_HILO!C13) | F13: =IF(COMPRAS_HILO!H13=0,"",COMPRAS_HILO!H13) | G13: =IF(COMPRAS_HILO!O13=0,"",COMPRAS_HILO!O13) | H13: =IF(COMPRAS_HILO!P13=0,"",COMPRAS_HILO!P13) | I13: =IF(COMPRAS_HILO!M13="","",COMPRAS_HILO!M13)
A14: HILO | B14: =IF(COMPRAS_HILO!A14="","",COMPRAS_HILO!A14) | C14: =IF(COMPRAS_HILO!I14="","",COMPRAS_HILO!I14) | D14: =IF(COMPRAS_HILO!J14="","",COMPRAS_HILO!J14) | E14: =IF(COMPRAS_HILO!C14="","","Compra "&COMPRAS_HILO!C14) | F14: =IF(COMPRAS_HILO!H14=0,"",COMPRAS_HILO!H14) | G14: =IF(COMPRAS_HILO!O14=0,"",COMPRAS_HILO!O14) | H14: =IF(COMPRAS_HILO!P14=0,"",COMPRAS_HILO!P14) | I14: =IF(COMPRAS_HILO!M14="","",COMPRAS_HILO!M14)
A15: HILO | B15: =IF(COMPRAS_HILO!A15="","",COMPRAS_HILO!A15) | C15: =IF(COMPRAS_HILO!I15="","",COMPRAS_HILO!I15) | D15: =IF(COMPRAS_HILO!J15="","",COMPRAS_HILO!J15) | E15: =IF(COMPRAS_HILO!C15="","","Compra "&COMPRAS_HILO!C15) | F15: =IF(COMPRAS_HILO!H15=0,"",COMPRAS_HILO!H15) | G15: =IF(COMPRAS_HILO!O15=0,"",COMPRAS_HILO!O15) | H15: =IF(COMPRAS_HILO!P15=0,"",COMPRAS_HILO!P15) | I15: =IF(COMPRAS_HILO!M15="","",COMPRAS_HILO!M15)
... A203: HILO | B203: =IF(COMPRAS_HILO!A203="","",COMPRAS_HILO!A203) | C203: =IF(COMPRAS_HILO!I203="","",COMPRAS_HILO!I203) | D203: =IF(COMPRAS_HILO!J203="","",COMPRAS_HILO!J203) | E203: =IF(COMPRAS_HILO!C203="","","Compra "&COMPRAS_HILO!C203) | F203: =IF(COMPRAS_HILO!H203=0,"",COMPRAS_HILO!H203) | G203: =IF(COMPRAS_HILO!O203=0,"",COMPRAS_HILO!O203) | H203: =IF(COMPRAS_HILO!P203=0,"",COMPRAS_HILO!P203) | I203: =IF(COMPRAS_HILO!M203="","",COMPRAS_HILO!M203)
A204: TEJEDURÍA | B204: =IFERROR(VLOOKUP(PROGRAMA_DETALLE!A4,PROGRAMAS!$A$4:$B$103,2,FALSE()),"") -> 46113 | C204: =IF(PROGRAMA_DETALLE!A4="","","Tejedora") -> Tejedora | D204: =IF(PROGRAMA_DETALLE!N4="","",PROGRAMA_DETALLE!N4) -> TEJ-001 | E204: =IF(PROGRAMA_DETALLE!A4="","","Tejido "&PROGRAMA_DETALLE!A4&" "&PROGRAMA_DETALLE!B4) -> Tejido PIQUE-001 Negro | F204: =IF(PROGRAMA_DETALLE!M4=0,"",PROGRAMA_DETALLE!M4) -> 710 | G204: =IF(PROGRAMA_DETALLE!P4="PAGADO",PROGRAMA_DETALLE!M4,0) -> 710 | H204: =IF(OR(PROGRAMA_DETALLE!P4="PENDIENTE",PROGRAMA_DETALLE!P4="PARCIAL"),PROGRAMA_DETALLE!M4,0) -> 0 | I204: =IF(PROGRAMA_DETALLE!P4="","",PROGRAMA_DETALLE!P4) -> PAGADO
A205: TEJEDURÍA | B205: =IFERROR(VLOOKUP(PROGRAMA_DETALLE!A5,PROGRAMAS!$A$4:$B$103,2,FALSE()),"") -> 46113 | C205: =IF(PROGRAMA_DETALLE!A5="","","Tejedora") -> Tejedora | D205: =IF(PROGRAMA_DETALLE!N5="","",PROGRAMA_DETALLE!N5) -> TEJ-002 | E205: =IF(PROGRAMA_DETALLE!A5="","","Tejido "&PROGRAMA_DETALLE!A5&" "&PROGRAMA_DETALLE!B5) -> Tejido PIQUE-001 Perla | F205: =IF(PROGRAMA_DETALLE!M5=0,"",PROGRAMA_DETALLE!M5) -> 355 | G205: =IF(PROGRAMA_DETALLE!P5="PAGADO",PROGRAMA_DETALLE!M5,0) -> 355 | H205: =IF(OR(PROGRAMA_DETALLE!P5="PENDIENTE",PROGRAMA_DETALLE!P5="PARCIAL"),PROGRAMA_DETALLE!M5,0) -> 0 | I205: =IF(PROGRAMA_DETALLE!P5="","",PROGRAMA_DETALLE!P5) -> PAGADO
A206: TEJEDURÍA | B206: =IFERROR(VLOOKUP(PROGRAMA_DETALLE!A6,PROGRAMAS!$A$4:$B$103,2,FALSE()),"") -> 46113 | C206: =IF(PROGRAMA_DETALLE!A6="","","Tejedora") -> Tejedora | D206: =IF(PROGRAMA_DETALLE!N6="","",PROGRAMA_DETALLE!N6) -> TEJ-003 | E206: =IF(PROGRAMA_DETALLE!A6="","","Tejido "&PROGRAMA_DETALLE!A6&" "&PROGRAMA_DETALLE!B6) -> Tejido PIQUE-001 Beige | F206: =IF(PROGRAMA_DETALLE!M6=0,"",PROGRAMA_DETALLE!M6) -> 355 | G206: =IF(PROGRAMA_DETALLE!P6="PAGADO",PROGRAMA_DETALLE!M6,0) -> 355 | H206: =IF(OR(PROGRAMA_DETALLE!P6="PENDIENTE",PROGRAMA_DETALLE!P6="PARCIAL"),PROGRAMA_DETALLE!M6,0) -> 0 | I206: =IF(PROGRAMA_DETALLE!P6="","",PROGRAMA_DETALLE!P6) -> PAGADO
A207: TEJEDURÍA | B207: =IFERROR(VLOOKUP(PROGRAMA_DETALLE!A7,PROGRAMAS!$A$4:$B$103,2,FALSE()),"") -> 46113 | C207: =IF(PROGRAMA_DETALLE!A7="","","Tejedora") -> Tejedora | D207: =IF(PROGRAMA_DETALLE!N7="","",PROGRAMA_DETALLE!N7) -> TEJ-004 | E207: =IF(PROGRAMA_DETALLE!A7="","","Tejido "&PROGRAMA_DETALLE!A7&" "&PROGRAMA_DETALLE!B7) -> Tejido PIQUE-001 Melange | F207: =IF(PROGRAMA_DETALLE!M7=0,"",PROGRAMA_DETALLE!M7) -> 355 | G207: =IF(PROGRAMA_DETALLE!P7="PAGADO",PROGRAMA_DETALLE!M7,0) -> 355 | H207: =IF(OR(PROGRAMA_DETALLE!P7="PENDIENTE",PROGRAMA_DETALLE!P7="PARCIAL"),PROGRAMA_DETALLE!M7,0) -> 0 | I207: =IF(PROGRAMA_DETALLE!P7="","",PROGRAMA_DETALLE!P7) -> PAGADO
A208: TEJEDURÍA | B208: =IFERROR(VLOOKUP(PROGRAMA_DETALLE!A8,PROGRAMAS!$A$4:$B$103,2,FALSE()),"") | C208: =IF(PROGRAMA_DETALLE!A8="","","Tejedora") | D208: =IF(PROGRAMA_DETALLE!N8="","",PROGRAMA_DETALLE!N8) | E208: =IF(PROGRAMA_DETALLE!A8="","","Tejido "&PROGRAMA_DETALLE!A8&" "&PROGRAMA_DETALLE!B8) | F208: =IF(PROGRAMA_DETALLE!M8=0,"",PROGRAMA_DETALLE!M8) | G208: =IF(PROGRAMA_DETALLE!P8="PAGADO",PROGRAMA_DETALLE!M8,0) -> 0 | H208: =IF(OR(PROGRAMA_DETALLE!P8="PENDIENTE",PROGRAMA_DETALLE!P8="PARCIAL"),PROGRAMA_DETALLE!M8,0) -> 0 | I208: =IF(PROGRAMA_DETALLE!P8="","",PROGRAMA_DETALLE!P8)
A209: TEJEDURÍA | B209: =IFERROR(VLOOKUP(PROGRAMA_DETALLE!A9,PROGRAMAS!$A$4:$B$103,2,FALSE()),"") | C209: =IF(PROGRAMA_DETALLE!A9="","","Tejedora") | D209: =IF(PROGRAMA_DETALLE!N9="","",PROGRAMA_DETALLE!N9) | E209: =IF(PROGRAMA_DETALLE!A9="","","Tejido "&PROGRAMA_DETALLE!A9&" "&PROGRAMA_DETALLE!B9) | F209: =IF(PROGRAMA_DETALLE!M9=0,"",PROGRAMA_DETALLE!M9) | G209: =IF(PROGRAMA_DETALLE!P9="PAGADO",PROGRAMA_DETALLE!M9,0) -> 0 | H209: =IF(OR(PROGRAMA_DETALLE!P9="PENDIENTE",PROGRAMA_DETALLE!P9="PARCIAL"),PROGRAMA_DETALLE!M9,0) -> 0 | I209: =IF(PROGRAMA_DETALLE!P9="","",PROGRAMA_DETALLE!P9)
A210: TEJEDURÍA | B210: =IFERROR(VLOOKUP(PROGRAMA_DETALLE!A10,PROGRAMAS!$A$4:$B$103,2,FALSE()),"") -> 46152 | C210: =IF(PROGRAMA_DETALLE!A10="","","Tejedora") -> Tejedora | D210: =IF(PROGRAMA_DETALLE!N10="","",PROGRAMA_DETALLE!N10) | E210: =IF(PROGRAMA_DETALLE!A10="","","Tejido "&PROGRAMA_DETALLE!A10&" "&PROGRAMA_DETALLE!B10) -> Tejido FULL LYCRA 50/1-001 Negro | F210: =IF(PROGRAMA_DETALLE!M10=0,"",PROGRAMA_DETALLE!M10) | G210: =IF(PROGRAMA_DETALLE!P10="PAGADO",PROGRAMA_DETALLE!M10,0) -> 0 | H210: =IF(OR(PROGRAMA_DETALLE!P10="PENDIENTE",PROGRAMA_DETALLE!P10="PARCIAL"),PROGRAMA_DETALLE!M10,0) -> 0 | I210: =IF(PROGRAMA_DETALLE!P10="","",PROGRAMA_DETALLE!P10)
A211: TEJEDURÍA | B211: =IFERROR(VLOOKUP(PROGRAMA_DETALLE!A11,PROGRAMAS!$A$4:$B$103,2,FALSE()),"") -> 46152 | C211: =IF(PROGRAMA_DETALLE!A11="","","Tejedora") -> Tejedora | D211: =IF(PROGRAMA_DETALLE!N11="","",PROGRAMA_DETALLE!N11) | E211: =IF(PROGRAMA_DETALLE!A11="","","Tejido "&PROGRAMA_DETALLE!A11&" "&PROGRAMA_DETALLE!B11) -> Tejido FULL LYCRA 50/1-001 Perla | F211: =IF(PROGRAMA_DETALLE!M11=0,"",PROGRAMA_DETALLE!M11) | G211: =IF(PROGRAMA_DETALLE!P11="PAGADO",PROGRAMA_DETALLE!M11,0) -> 0 | H211: =IF(OR(PROGRAMA_DETALLE!P11="PENDIENTE",PROGRAMA_DETALLE!P11="PARCIAL"),PROGRAMA_DETALLE!M11,0) -> 0 | I211: =IF(PROGRAMA_DETALLE!P11="","",PROGRAMA_DETALLE!P11)
A212: TEJEDURÍA | B212: =IFERROR(VLOOKUP(PROGRAMA_DETALLE!A12,PROGRAMAS!$A$4:$B$103,2,FALSE()),"") -> 46152 | C212: =IF(PROGRAMA_DETALLE!A12="","","Tejedora") -> Tejedora | D212: =IF(PROGRAMA_DETALLE!N12="","",PROGRAMA_DETALLE!N12) | E212: =IF(PROGRAMA_DETALLE!A12="","","Tejido "&PROGRAMA_DETALLE!A12&" "&PROGRAMA_DETALLE!B12) -> Tejido FULL LYCRA 50/1-001 Colegial | F212: =IF(PROGRAMA_DETALLE!M12=0,"",PROGRAMA_DETALLE!M12) | G212: =IF(PROGRAMA_DETALLE!P12="PAGADO",PROGRAMA_DETALLE!M12,0) -> 0 | H212: =IF(OR(PROGRAMA_DETALLE!P12="PENDIENTE",PROGRAMA_DETALLE!P12="PARCIAL"),PROGRAMA_DETALLE!M12,0) -> 0 | I212: =IF(PROGRAMA_DETALLE!P12="","",PROGRAMA_DETALLE!P12)
A213: TEJEDURÍA | B213: =IFERROR(VLOOKUP(PROGRAMA_DETALLE!A13,PROGRAMAS!$A$4:$B$103,2,FALSE()),"") | C213: =IF(PROGRAMA_DETALLE!A13="","","Tejedora") | D213: =IF(PROGRAMA_DETALLE!N13="","",PROGRAMA_DETALLE!N13) | E213: =IF(PROGRAMA_DETALLE!A13="","","Tejido "&PROGRAMA_DETALLE!A13&" "&PROGRAMA_DETALLE!B13) | F213: =IF(PROGRAMA_DETALLE!M13=0,"",PROGRAMA_DETALLE!M13) | G213: =IF(PROGRAMA_DETALLE!P13="PAGADO",PROGRAMA_DETALLE!M13,0) -> 0 | H213: =IF(OR(PROGRAMA_DETALLE!P13="PENDIENTE",PROGRAMA_DETALLE!P13="PARCIAL"),PROGRAMA_DETALLE!M13,0) -> 0 | I213: =IF(PROGRAMA_DETALLE!P13="","",PROGRAMA_DETALLE!P13)
A214: TEJEDURÍA | B214: =IFERROR(VLOOKUP(PROGRAMA_DETALLE!A14,PROGRAMAS!$A$4:$B$103,2,FALSE()),"") -> 46152 | C214: =IF(PROGRAMA_DETALLE!A14="","","Tejedora") -> Tejedora | D214: =IF(PROGRAMA_DETALLE!N14="","",PROGRAMA_DETALLE!N14) | E214: =IF(PROGRAMA_DETALLE!A14="","","Tejido "&PROGRAMA_DETALLE!A14&" "&PROGRAMA_DETALLE!B14) -> Tejido frecnh terry - 001 Negro | F214: =IF(PROGRAMA_DETALLE!M14=0,"",PROGRAMA_DETALLE!M14) | G214: =IF(PROGRAMA_DETALLE!P14="PAGADO",PROGRAMA_DETALLE!M14,0) -> 0 | H214: =IF(OR(PROGRAMA_DETALLE!P14="PENDIENTE",PROGRAMA_DETALLE!P14="PARCIAL"),PROGRAMA_DETALLE!M14,0) -> 0 | I214: =IF(PROGRAMA_DETALLE!P14="","",PROGRAMA_DETALLE!P14)
A215: TEJEDURÍA | B215: =IFERROR(VLOOKUP(PROGRAMA_DETALLE!A15,PROGRAMAS!$A$4:$B$103,2,FALSE()),"") -> 46152 | C215: =IF(PROGRAMA_DETALLE!A15="","","Tejedora") -> Tejedora | D215: =IF(PROGRAMA_DETALLE!N15="","",PROGRAMA_DETALLE!N15) | E215: =IF(PROGRAMA_DETALLE!A15="","","Tejido "&PROGRAMA_DETALLE!A15&" "&PROGRAMA_DETALLE!B15) -> Tejido frecnh terry - 001 Perla | F215: =IF(PROGRAMA_DETALLE!M15=0,"",PROGRAMA_DETALLE!M15) | G215: =IF(PROGRAMA_DETALLE!P15="PAGADO",PROGRAMA_DETALLE!M15,0) -> 0 | H215: =IF(OR(PROGRAMA_DETALLE!P15="PENDIENTE",PROGRAMA_DETALLE!P15="PARCIAL"),PROGRAMA_DETALLE!M15,0) -> 0 | I215: =IF(PROGRAMA_DETALLE!P15="","",PROGRAMA_DETALLE!P15)
... A703: TEJEDURÍA | B703: =IFERROR(VLOOKUP(PROGRAMA_DETALLE!A503,PROGRAMAS!$A$4:$B$103,2,FALSE()),"") | C703: =IF(PROGRAMA_DETALLE!A503="","","Tejedora") | D703: =IF(PROGRAMA_DETALLE!N503="","",PROGRAMA_DETALLE!N503) | E703: =IF(PROGRAMA_DETALLE!A503="","","Tejido "&PROGRAMA_DETALLE!A503&" "&PROGRAMA_DETALLE!B503) | F703: =IF(PROGRAMA_DETALLE!M503=0,"",PROGRAMA_DETALLE!M503) | G703: =IF(PROGRAMA_DETALLE!P503="PAGADO",PROGRAMA_DETALLE!M503,0) -> 0 | H703: =IF(OR(PROGRAMA_DETALLE!P503="PENDIENTE",PROGRAMA_DETALLE!P503="PARCIAL"),PROGRAMA_DETALLE!M503,0) -> 0 | I703: =IF(PROGRAMA_DETALLE!P503="","",PROGRAMA_DETALLE!P503)
A704: TINTORERÍA | B704: =IF(PROGRAMA_DETALLE!Q4="","",PROGRAMA_DETALLE!Q4) -> 46114 | C704: =IF(PROGRAMA_DETALLE!A4="","","Tintorería") -> Tintorería | D704: =IF(PROGRAMA_DETALLE!AB4="","",PROGRAMA_DETALLE!AB4) -> TIN-001 | E704: =IF(PROGRAMA_DETALLE!A4="","","Teñido "&PROGRAMA_DETALLE!D4&" "&PROGRAMA_DETALLE!B4) -> Teñido REACTIVO (oscuros) Negro | F704: =IF(PROGRAMA_DETALLE!Z4=0,"",PROGRAMA_DETALLE!Z4) -> 3786.075 | G704: =IF(PROGRAMA_DETALLE!AC4="PAGADO",PROGRAMA_DETALLE!Z4,0) -> 3786.075 | H704: =IF(OR(PROGRAMA_DETALLE!AC4="PENDIENTE",PROGRAMA_DETALLE!AC4="PARCIAL"),PROGRAMA_DETALLE!Z4,0) -> 0 | I704: =IF(PROGRAMA_DETALLE!AC4="","",PROGRAMA_DETALLE!AC4) -> PAGADO
A705: TINTORERÍA | B705: =IF(PROGRAMA_DETALLE!Q5="","",PROGRAMA_DETALLE!Q5) -> 46114 | C705: =IF(PROGRAMA_DETALLE!A5="","","Tintorería") -> Tintorería | D705: =IF(PROGRAMA_DETALLE!AB5="","",PROGRAMA_DETALLE!AB5) -> TIN-002 | E705: =IF(PROGRAMA_DETALLE!A5="","","Teñido "&PROGRAMA_DETALLE!D5&" "&PROGRAMA_DETALLE!B5) -> Teñido PPT (perla/blanco) Perla | F705: =IF(PROGRAMA_DETALLE!Z5=0,"",PROGRAMA_DETALLE!Z5) -> 761.475 | G705: =IF(PROGRAMA_DETALLE!AC5="PAGADO",PROGRAMA_DETALLE!Z5,0) -> 761.475 | H705: =IF(OR(PROGRAMA_DETALLE!AC5="PENDIENTE",PROGRAMA_DETALLE!AC5="PARCIAL"),PROGRAMA_DETALLE!Z5,0) -> 0 | I705: =IF(PROGRAMA_DETALLE!AC5="","",PROGRAMA_DETALLE!AC5) -> PAGADO
A706: TINTORERÍA | B706: =IF(PROGRAMA_DETALLE!Q6="","",PROGRAMA_DETALLE!Q6) -> 46114 | C706: =IF(PROGRAMA_DETALLE!A6="","","Tintorería") -> Tintorería | D706: =IF(PROGRAMA_DETALLE!AB6="","",PROGRAMA_DETALLE!AB6) -> TIN-003 | E706: =IF(PROGRAMA_DETALLE!A6="","","Teñido "&PROGRAMA_DETALLE!D6&" "&PROGRAMA_DETALLE!B6) -> Teñido DIRECTO (claros) Beige | F706: =IF(PROGRAMA_DETALLE!Z6=0,"",PROGRAMA_DETALLE!Z6) -> 1330.875 | G706: =IF(PROGRAMA_DETALLE!AC6="PAGADO",PROGRAMA_DETALLE!Z6,0) -> 1330.875 | H706: =IF(OR(PROGRAMA_DETALLE!AC6="PENDIENTE",PROGRAMA_DETALLE!AC6="PARCIAL"),PROGRAMA_DETALLE!Z6,0) -> 0 | I706: =IF(PROGRAMA_DETALLE!AC6="","",PROGRAMA_DETALLE!AC6) -> PAGADO
A707: TINTORERÍA | B707: =IF(PROGRAMA_DETALLE!Q7="","",PROGRAMA_DETALLE!Q7) -> 46114 | C707: =IF(PROGRAMA_DETALLE!A7="","","Tintorería") -> Tintorería | D707: =IF(PROGRAMA_DETALLE!AB7="","",PROGRAMA_DETALLE!AB7) -> TIN-004 | E707: =IF(PROGRAMA_DETALLE!A7="","","Teñido "&PROGRAMA_DETALLE!D7&" "&PROGRAMA_DETALLE!B7) -> Teñido LAVADO (melange) Melange | F707: =IF(PROGRAMA_DETALLE!Z7=0,"",PROGRAMA_DETALLE!Z7) -> 750.75 | G707: =IF(PROGRAMA_DETALLE!AC7="PAGADO",PROGRAMA_DETALLE!Z7,0) -> 750.75 | H707: =IF(OR(PROGRAMA_DETALLE!AC7="PENDIENTE",PROGRAMA_DETALLE!AC7="PARCIAL"),PROGRAMA_DETALLE!Z7,0) -> 0 | I707: =IF(PROGRAMA_DETALLE!AC7="","",PROGRAMA_DETALLE!AC7) -> PAGADO
A708: TINTORERÍA | B708: =IF(PROGRAMA_DETALLE!Q8="","",PROGRAMA_DETALLE!Q8) | C708: =IF(PROGRAMA_DETALLE!A8="","","Tintorería") | D708: =IF(PROGRAMA_DETALLE!AB8="","",PROGRAMA_DETALLE!AB8) | E708: =IF(PROGRAMA_DETALLE!A8="","","Teñido "&PROGRAMA_DETALLE!D8&" "&PROGRAMA_DETALLE!B8) | F708: =IF(PROGRAMA_DETALLE!Z8=0,"",PROGRAMA_DETALLE!Z8) | G708: =IF(PROGRAMA_DETALLE!AC8="PAGADO",PROGRAMA_DETALLE!Z8,0) -> 0 | H708: =IF(OR(PROGRAMA_DETALLE!AC8="PENDIENTE",PROGRAMA_DETALLE!AC8="PARCIAL"),PROGRAMA_DETALLE!Z8,0) -> 0 | I708: =IF(PROGRAMA_DETALLE!AC8="","",PROGRAMA_DETALLE!AC8)
A709: TINTORERÍA | B709: =IF(PROGRAMA_DETALLE!Q9="","",PROGRAMA_DETALLE!Q9) | C709: =IF(PROGRAMA_DETALLE!A9="","","Tintorería") | D709: =IF(PROGRAMA_DETALLE!AB9="","",PROGRAMA_DETALLE!AB9) | E709: =IF(PROGRAMA_DETALLE!A9="","","Teñido "&PROGRAMA_DETALLE!D9&" "&PROGRAMA_DETALLE!B9) | F709: =IF(PROGRAMA_DETALLE!Z9=0,"",PROGRAMA_DETALLE!Z9) | G709: =IF(PROGRAMA_DETALLE!AC9="PAGADO",PROGRAMA_DETALLE!Z9,0) -> 0 | H709: =IF(OR(PROGRAMA_DETALLE!AC9="PENDIENTE",PROGRAMA_DETALLE!AC9="PARCIAL"),PROGRAMA_DETALLE!Z9,0) -> 0 | I709: =IF(PROGRAMA_DETALLE!AC9="","",PROGRAMA_DETALLE!AC9)
A710: TINTORERÍA | B710: =IF(PROGRAMA_DETALLE!Q10="","",PROGRAMA_DETALLE!Q10) | C710: =IF(PROGRAMA_DETALLE!A10="","","Tintorería") -> Tintorería | D710: =IF(PROGRAMA_DETALLE!AB10="","",PROGRAMA_DETALLE!AB10) | E710: =IF(PROGRAMA_DETALLE!A10="","","Teñido "&PROGRAMA_DETALLE!D10&" "&PROGRAMA_DETALLE!B10) -> Teñido REACTIVO (oscuros) Negro | F710: =IF(PROGRAMA_DETALLE!Z10=0,"",PROGRAMA_DETALLE!Z10) | G710: =IF(PROGRAMA_DETALLE!AC10="PAGADO",PROGRAMA_DETALLE!Z10,0) -> 0 | H710: =IF(OR(PROGRAMA_DETALLE!AC10="PENDIENTE",PROGRAMA_DETALLE!AC10="PARCIAL"),PROGRAMA_DETALLE!Z10,0) -> 0 | I710: =IF(PROGRAMA_DETALLE!AC10="","",PROGRAMA_DETALLE!AC10)
A711: TINTORERÍA | B711: =IF(PROGRAMA_DETALLE!Q11="","",PROGRAMA_DETALLE!Q11) | C711: =IF(PROGRAMA_DETALLE!A11="","","Tintorería") -> Tintorería | D711: =IF(PROGRAMA_DETALLE!AB11="","",PROGRAMA_DETALLE!AB11) | E711: =IF(PROGRAMA_DETALLE!A11="","","Teñido "&PROGRAMA_DETALLE!D11&" "&PROGRAMA_DETALLE!B11) -> Teñido PPT (perla/blanco) Perla | F711: =IF(PROGRAMA_DETALLE!Z11=0,"",PROGRAMA_DETALLE!Z11) | G711: =IF(PROGRAMA_DETALLE!AC11="PAGADO",PROGRAMA_DETALLE!Z11,0) -> 0 | H711: =IF(OR(PROGRAMA_DETALLE!AC11="PENDIENTE",PROGRAMA_DETALLE!AC11="PARCIAL"),PROGRAMA_DETALLE!Z11,0) -> 0 | I711: =IF(PROGRAMA_DETALLE!AC11="","",PROGRAMA_DETALLE!AC11)
A712: TINTORERÍA | B712: =IF(PROGRAMA_DETALLE!Q12="","",PROGRAMA_DETALLE!Q12) | C712: =IF(PROGRAMA_DETALLE!A12="","","Tintorería") -> Tintorería | D712: =IF(PROGRAMA_DETALLE!AB12="","",PROGRAMA_DETALLE!AB12) | E712: =IF(PROGRAMA_DETALLE!A12="","","Teñido "&PROGRAMA_DETALLE!D12&" "&PROGRAMA_DETALLE!B12) -> Teñido REACTIVO (oscuros) Colegial | F712: =IF(PROGRAMA_DETALLE!Z12=0,"",PROGRAMA_DETALLE!Z12) | G712: =IF(PROGRAMA_DETALLE!AC12="PAGADO",PROGRAMA_DETALLE!Z12,0) -> 0 | H712: =IF(OR(PROGRAMA_DETALLE!AC12="PENDIENTE",PROGRAMA_DETALLE!AC12="PARCIAL"),PROGRAMA_DETALLE!Z12,0) -> 0 | I712: =IF(PROGRAMA_DETALLE!AC12="","",PROGRAMA_DETALLE!AC12)
A713: TINTORERÍA | B713: =IF(PROGRAMA_DETALLE!Q13="","",PROGRAMA_DETALLE!Q13) | C713: =IF(PROGRAMA_DETALLE!A13="","","Tintorería") | D713: =IF(PROGRAMA_DETALLE!AB13="","",PROGRAMA_DETALLE!AB13) | E713: =IF(PROGRAMA_DETALLE!A13="","","Teñido "&PROGRAMA_DETALLE!D13&" "&PROGRAMA_DETALLE!B13) | F713: =IF(PROGRAMA_DETALLE!Z13=0,"",PROGRAMA_DETALLE!Z13) | G713: =IF(PROGRAMA_DETALLE!AC13="PAGADO",PROGRAMA_DETALLE!Z13,0) -> 0 | H713: =IF(OR(PROGRAMA_DETALLE!AC13="PENDIENTE",PROGRAMA_DETALLE!AC13="PARCIAL"),PROGRAMA_DETALLE!Z13,0) -> 0 | I713: =IF(PROGRAMA_DETALLE!AC13="","",PROGRAMA_DETALLE!AC13)
A714: TINTORERÍA | B714: =IF(PROGRAMA_DETALLE!Q14="","",PROGRAMA_DETALLE!Q14) | C714: =IF(PROGRAMA_DETALLE!A14="","","Tintorería") -> Tintorería | D714: =IF(PROGRAMA_DETALLE!AB14="","",PROGRAMA_DETALLE!AB14) | E714: =IF(PROGRAMA_DETALLE!A14="","","Teñido "&PROGRAMA_DETALLE!D14&" "&PROGRAMA_DETALLE!B14) -> Teñido REACTIVO (oscuros) Negro | F714: =IF(PROGRAMA_DETALLE!Z14=0,"",PROGRAMA_DETALLE!Z14) | G714: =IF(PROGRAMA_DETALLE!AC14="PAGADO",PROGRAMA_DETALLE!Z14,0) -> 0 | H714: =IF(OR(PROGRAMA_DETALLE!AC14="PENDIENTE",PROGRAMA_DETALLE!AC14="PARCIAL"),PROGRAMA_DETALLE!Z14,0) -> 0 | I714: =IF(PROGRAMA_DETALLE!AC14="","",PROGRAMA_DETALLE!AC14)
A715: TINTORERÍA | B715: =IF(PROGRAMA_DETALLE!Q15="","",PROGRAMA_DETALLE!Q15) | C715: =IF(PROGRAMA_DETALLE!A15="","","Tintorería") -> Tintorería | D715: =IF(PROGRAMA_DETALLE!AB15="","",PROGRAMA_DETALLE!AB15) | E715: =IF(PROGRAMA_DETALLE!A15="","","Teñido "&PROGRAMA_DETALLE!D15&" "&PROGRAMA_DETALLE!B15) -> Teñido PPT (perla/blanco) Perla | F715: =IF(PROGRAMA_DETALLE!Z15=0,"",PROGRAMA_DETALLE!Z15) | G715: =IF(PROGRAMA_DETALLE!AC15="PAGADO",PROGRAMA_DETALLE!Z15,0) -> 0 | H715: =IF(OR(PROGRAMA_DETALLE!AC15="PENDIENTE",PROGRAMA_DETALLE!AC15="PARCIAL"),PROGRAMA_DETALLE!Z15,0) -> 0 | I715: =IF(PROGRAMA_DETALLE!AC15="","",PROGRAMA_DETALLE!AC15)
... A1203: TINTORERÍA | B1203: =IF(PROGRAMA_DETALLE!Q503="","",PROGRAMA_DETALLE!Q503) | C1203: =IF(PROGRAMA_DETALLE!A503="","","Tintorería") | D1203: =IF(PROGRAMA_DETALLE!AB503="","",PROGRAMA_DETALLE!AB503) | E1203: =IF(PROGRAMA_DETALLE!A503="","","Teñido "&PROGRAMA_DETALLE!D503&" "&PROGRAMA_DETALLE!B503) | F1203: =IF(PROGRAMA_DETALLE!Z503=0,"",PROGRAMA_DETALLE!Z503) | G1203: =IF(PROGRAMA_DETALLE!AC503="PAGADO",PROGRAMA_DETALLE!Z503,0) -> 0 | H1203: =IF(OR(PROGRAMA_DETALLE!AC503="PENDIENTE",PROGRAMA_DETALLE!AC503="PARCIAL"),PROGRAMA_DETALLE!Z503,0) -> 0 | I1203: =IF(PROGRAMA_DETALLE!AC503="","",PROGRAMA_DETALLE!AC503)

Sheet COSTOS_PROGRAMA
A1: COSTOS POR PROGRAMA — Auto-calculado
A2: Por cada programa: costo hilo + tejido + teñido. Dividido entre kg final = costo por kg de tela tintorería.
A3: PROGRAMA | B3: TIPO HILO | C3: KG HILO COMPRADO | D3: COSTO HILO | E3: COSTO TEJIDO | F3: COSTO TEÑIDO | G3: COSTO TOTAL S/. | H3: KG TELA FINAL | I3: % MERMA TOTAL | J3: COSTO/KG TELA S/. | K3: ESTADO
A4: =IF(PROGRAMAS!A4="","",PROGRAMAS!A4) -> PIQUE-001 | B4: =IF(PROGRAMAS!D4="","",PROGRAMAS!D4) -> Hilo 30/1 PC | C4: =IF(PROGRAMAS!M4=0,"",PROGRAMAS!M4) -> 1000 | D4: =IF(PROGRAMAS!N4=0,"",PROGRAMAS!N4) -> 10500 | E4: =IFERROR(SUMIFS(PROGRAMA_DETALLE!$M$4:$M$503,PROGRAMA_DETALLE!$A$4:$A$503,A4),0) -> 1775 | F4: =IFERROR(SUMIFS(PROGRAMA_DETALLE!$Z$4:$Z$503,PROGRAMA_DETALLE!$A$4:$A$503,A4),0) -> 6629.175 | G4: =IF(PROGRAMAS!AE4=0,"",PROGRAMAS!AE4) -> 19171.175 | H4: =IF(PROGRAMAS!W4=0,"",PROGRAMAS!W4) -> 890 | I4: =IFERROR((C4-H4)/C4,0) -> 0.11 | J4: =IFERROR(G4/H4,0) -> 21.540646 | K4: =IF(PROGRAMAS!I4="","",PROGRAMAS!I4) -> CERRADO
A5: =IF(PROGRAMAS!A5="","",PROGRAMAS!A5) -> FULL LYCRA 50/1-001 | B5: =IF(PROGRAMAS!D5="","",PROGRAMAS!D5) -> hilo 50/1 cotton +lycra 4% | C5: =IF(PROGRAMAS!M5=0,"",PROGRAMAS!M5) -> 500 | D5: =IF(PROGRAMAS!N5=0,"",PROGRAMAS!N5) -> 9625 | E5: =IFERROR(SUMIFS(PROGRAMA_DETALLE!$M$4:$M$503,PROGRAMA_DETALLE!$A$4:$A$503,A5),0) -> 0 | F5: =IFERROR(SUMIFS(PROGRAMA_DETALLE!$Z$4:$Z$503,PROGRAMA_DETALLE!$A$4:$A$503,A5),0) -> 0 | G5: =IF(PROGRAMAS!AE5=0,"",PROGRAMAS!AE5) -> 9625 | H5: =IF(PROGRAMAS!W5=0,"",PROGRAMAS!W5) | I5: =IFERROR((C5-H5)/C5,0) -> 1 | J5: =IFERROR(G5/H5,0) -> 0 | K5: =IF(PROGRAMAS!I5="","",PROGRAMAS!I5) -> EN TEJEDURÍA
A6: =IF(PROGRAMAS!A6="","",PROGRAMAS!A6) -> frecnh terry - 001 | B6: =IF(PROGRAMAS!D6="","",PROGRAMAS!D6) -> Hilo 30/1 PC | C6: =IF(PROGRAMAS!M6=0,"",PROGRAMAS!M6) -> 3000 | D6: =IF(PROGRAMAS!N6=0,"",PROGRAMAS!N6) -> 31050 | E6: =IFERROR(SUMIFS(PROGRAMA_DETALLE!$M$4:$M$503,PROGRAMA_DETALLE!$A$4:$A$503,A6),0) -> 0 | F6: =IFERROR(SUMIFS(PROGRAMA_DETALLE!$Z$4:$Z$503,PROGRAMA_DETALLE!$A$4:$A$503,A6),0) -> 0 | G6: =IF(PROGRAMAS!AE6=0,"",PROGRAMAS!AE6) -> 31050 | H6: =IF(PROGRAMAS!W6=0,"",PROGRAMAS!W6) | I6: =IFERROR((C6-H6)/C6,0) -> 1 | J6: =IFERROR(G6/H6,0) -> 0 | K6: =IF(PROGRAMAS!I6="","",PROGRAMAS!I6) -> EN TEJEDURÍA
A7: =IF(PROGRAMAS!A7="","",PROGRAMAS!A7) -> jersey algodon - 001 | B7: =IF(PROGRAMAS!D7="","",PROGRAMAS!D7) -> Hilo 30/1 ALGODON | C7: =IF(PROGRAMAS!M7=0,"",PROGRAMAS!M7) -> 660 | D7: =IF(PROGRAMAS!N7=0,"",PROGRAMAS!N7) -> 9108 | E7: =IFERROR(SUMIFS(PROGRAMA_DETALLE!$M$4:$M$503,PROGRAMA_DETALLE!$A$4:$A$503,A7),0) -> 0 | F7: =IFERROR(SUMIFS(PROGRAMA_DETALLE!$Z$4:$Z$503,PROGRAMA_DETALLE!$A$4:$A$503,A7),0) -> 0 | G7: =IF(PROGRAMAS!AE7=0,"",PROGRAMAS!AE7) -> 9108 | H7: =IF(PROGRAMAS!W7=0,"",PROGRAMAS!W7) | I7: =IFERROR((C7-H7)/C7,0) -> 1 | J7: =IFERROR(G7/H7,0) -> 0 | K7: =IF(PROGRAMAS!I7="","",PROGRAMAS!I7) -> EN TINTORERÍA
A8: =IF(PROGRAMAS!A8="","",PROGRAMAS!A8) -> rib 1x1- jersey algodon -001 | B8: =IF(PROGRAMAS!D8="","",PROGRAMAS!D8) -> Hilo 30/1 ALGODON | C8: =IF(PROGRAMAS!M8=0,"",PROGRAMAS!M8) | D8: =IF(PROGRAMAS!N8=0,"",PROGRAMAS!N8) | E8: =IFERROR(SUMIFS(PROGRAMA_DETALLE!$M$4:$M$503,PROGRAMA_DETALLE!$A$4:$A$503,A8),0) -> 0 | F8: =IFERROR(SUMIFS(PROGRAMA_DETALLE!$Z$4:$Z$503,PROGRAMA_DETALLE!$A$4:$A$503,A8),0) -> 0 | G8: =IF(PROGRAMAS!AE8=0,"",PROGRAMAS!AE8) | H8: =IF(PROGRAMAS!W8=0,"",PROGRAMAS!W8) | I8: =IFERROR((C8-H8)/C8,0) -> 0 | J8: =IFERROR(G8/H8,0) -> 0 | K8: =IF(PROGRAMAS!I8="","",PROGRAMAS!I8) -> EN TINTORERÍA
A9: =IF(PROGRAMAS!A9="","",PROGRAMAS!A9) | B9: =IF(PROGRAMAS!D9="","",PROGRAMAS!D9) | C9: =IF(PROGRAMAS!M9=0,"",PROGRAMAS!M9) | D9: =IF(PROGRAMAS!N9=0,"",PROGRAMAS!N9) | E9: =IFERROR(SUMIFS(PROGRAMA_DETALLE!$M$4:$M$503,PROGRAMA_DETALLE!$A$4:$A$503,A9),0) -> 0 | F9: =IFERROR(SUMIFS(PROGRAMA_DETALLE!$Z$4:$Z$503,PROGRAMA_DETALLE!$A$4:$A$503,A9),0) -> 0 | G9: =IF(PROGRAMAS!AE9=0,"",PROGRAMAS!AE9) | H9: =IF(PROGRAMAS!W9=0,"",PROGRAMAS!W9) | I9: =IFERROR((C9-H9)/C9,0) -> 0 | J9: =IFERROR(G9/H9,0) -> 0 | K9: =IF(PROGRAMAS!I9="","",PROGRAMAS!I9)
A10: =IF(PROGRAMAS!A10="","",PROGRAMAS!A10) | B10: =IF(PROGRAMAS!D10="","",PROGRAMAS!D10) | C10: =IF(PROGRAMAS!M10=0,"",PROGRAMAS!M10) | D10: =IF(PROGRAMAS!N10=0,"",PROGRAMAS!N10) | E10: =IFERROR(SUMIFS(PROGRAMA_DETALLE!$M$4:$M$503,PROGRAMA_DETALLE!$A$4:$A$503,A10),0) -> 0 | F10: =IFERROR(SUMIFS(PROGRAMA_DETALLE!$Z$4:$Z$503,PROGRAMA_DETALLE!$A$4:$A$503,A10),0) -> 0 | G10: =IF(PROGRAMAS!AE10=0,"",PROGRAMAS!AE10) | H10: =IF(PROGRAMAS!W10=0,"",PROGRAMAS!W10) | I10: =IFERROR((C10-H10)/C10,0) -> 0 | J10: =IFERROR(G10/H10,0) -> 0 | K10: =IF(PROGRAMAS!I10="","",PROGRAMAS!I10)
A11: =IF(PROGRAMAS!A11="","",PROGRAMAS!A11) | B11: =IF(PROGRAMAS!D11="","",PROGRAMAS!D11) | C11: =IF(PROGRAMAS!M11=0,"",PROGRAMAS!M11) | D11: =IF(PROGRAMAS!N11=0,"",PROGRAMAS!N11) | E11: =IFERROR(SUMIFS(PROGRAMA_DETALLE!$M$4:$M$503,PROGRAMA_DETALLE!$A$4:$A$503,A11),0) -> 0 | F11: =IFERROR(SUMIFS(PROGRAMA_DETALLE!$Z$4:$Z$503,PROGRAMA_DETALLE!$A$4:$A$503,A11),0) -> 0 | G11: =IF(PROGRAMAS!AE11=0,"",PROGRAMAS!AE11) | H11: =IF(PROGRAMAS!W11=0,"",PROGRAMAS!W11) | I11: =IFERROR((C11-H11)/C11,0) -> 0 | J11: =IFERROR(G11/H11,0) -> 0 | K11: =IF(PROGRAMAS!I11="","",PROGRAMAS!I11)
A12: =IF(PROGRAMAS!A12="","",PROGRAMAS!A12) | B12: =IF(PROGRAMAS!D12="","",PROGRAMAS!D12) | C12: =IF(PROGRAMAS!M12=0,"",PROGRAMAS!M12) | D12: =IF(PROGRAMAS!N12=0,"",PROGRAMAS!N12) | E12: =IFERROR(SUMIFS(PROGRAMA_DETALLE!$M$4:$M$503,PROGRAMA_DETALLE!$A$4:$A$503,A12),0) -> 0 | F12: =IFERROR(SUMIFS(PROGRAMA_DETALLE!$Z$4:$Z$503,PROGRAMA_DETALLE!$A$4:$A$503,A12),0) -> 0 | G12: =IF(PROGRAMAS!AE12=0,"",PROGRAMAS!AE12) | H12: =IF(PROGRAMAS!W12=0,"",PROGRAMAS!W12) | I12: =IFERROR((C12-H12)/C12,0) -> 0 | J12: =IFERROR(G12/H12,0) -> 0 | K12: =IF(PROGRAMAS!I12="","",PROGRAMAS!I12)
A13: =IF(PROGRAMAS!A13="","",PROGRAMAS!A13) | B13: =IF(PROGRAMAS!D13="","",PROGRAMAS!D13) | C13: =IF(PROGRAMAS!M13=0,"",PROGRAMAS!M13) | D13: =IF(PROGRAMAS!N13=0,"",PROGRAMAS!N13) | E13: =IFERROR(SUMIFS(PROGRAMA_DETALLE!$M$4:$M$503,PROGRAMA_DETALLE!$A$4:$A$503,A13),0) -> 0 | F13: =IFERROR(SUMIFS(PROGRAMA_DETALLE!$Z$4:$Z$503,PROGRAMA_DETALLE!$A$4:$A$503,A13),0) -> 0 | G13: =IF(PROGRAMAS!AE13=0,"",PROGRAMAS!AE13) | H13: =IF(PROGRAMAS!W13=0,"",PROGRAMAS!W13) | I13: =IFERROR((C13-H13)/C13,0) -> 0 | J13: =IFERROR(G13/H13,0) -> 0 | K13: =IF(PROGRAMAS!I13="","",PROGRAMAS!I13)
A14: =IF(PROGRAMAS!A14="","",PROGRAMAS!A14) | B14: =IF(PROGRAMAS!D14="","",PROGRAMAS!D14) | C14: =IF(PROGRAMAS!M14=0,"",PROGRAMAS!M14) | D14: =IF(PROGRAMAS!N14=0,"",PROGRAMAS!N14) | E14: =IFERROR(SUMIFS(PROGRAMA_DETALLE!$M$4:$M$503,PROGRAMA_DETALLE!$A$4:$A$503,A14),0) -> 0 | F14: =IFERROR(SUMIFS(PROGRAMA_DETALLE!$Z$4:$Z$503,PROGRAMA_DETALLE!$A$4:$A$503,A14),0) -> 0 | G14: =IF(PROGRAMAS!AE14=0,"",PROGRAMAS!AE14) | H14: =IF(PROGRAMAS!W14=0,"",PROGRAMAS!W14) | I14: =IFERROR((C14-H14)/C14,0) -> 0 | J14: =IFERROR(G14/H14,0) -> 0 | K14: =IF(PROGRAMAS!I14="","",PROGRAMAS!I14)
A15: =IF(PROGRAMAS!A15="","",PROGRAMAS!A15) | B15: =IF(PROGRAMAS!D15="","",PROGRAMAS!D15) | C15: =IF(PROGRAMAS!M15=0,"",PROGRAMAS!M15) | D15: =IF(PROGRAMAS!N15=0,"",PROGRAMAS!N15) | E15: =IFERROR(SUMIFS(PROGRAMA_DETALLE!$M$4:$M$503,PROGRAMA_DETALLE!$A$4:$A$503,A15),0) -> 0 | F15: =IFERROR(SUMIFS(PROGRAMA_DETALLE!$Z$4:$Z$503,PROGRAMA_DETALLE!$A$4:$A$503,A15),0) -> 0 | G15: =IF(PROGRAMAS!AE15=0,"",PROGRAMAS!AE15) | H15: =IF(PROGRAMAS!W15=0,"",PROGRAMAS!W15) | I15: =IFERROR((C15-H15)/C15,0) -> 0 | J15: =IFERROR(G15/H15,0) -> 0 | K15: =IF(PROGRAMAS!I15="","",PROGRAMAS!I15)
... A103: =IF(PROGRAMAS!A103="","",PROGRAMAS!A103) | B103: =IF(PROGRAMAS!D103="","",PROGRAMAS!D103) | C103: =IF(PROGRAMAS!M103=0,"",PROGRAMAS!M103) | D103: =IF(PROGRAMAS!N103=0,"",PROGRAMAS!N103) | E103: =IFERROR(SUMIFS(PROGRAMA_DETALLE!$M$4:$M$503,PROGRAMA_DETALLE!$A$4:$A$503,A103),0) -> 0 | F103: =IFERROR(SUMIFS(PROGRAMA_DETALLE!$Z$4:$Z$503,PROGRAMA_DETALLE!$A$4:$A$503,A103),0) -> 0 | G103: =IF(PROGRAMAS!AE103=0,"",PROGRAMAS!AE103) | H103: =IF(PROGRAMAS!W103=0,"",PROGRAMAS!W103) | I103: =IFERROR((C103-H103)/C103,0) -> 0 | J103: =IFERROR(G103/H103,0) -> 0 | K103: =IF(PROGRAMAS!I103="","",PROGRAMAS!I103)

Sheet DASHBOARD
A1: DASHBOARD — Resumen de Producción y Costos | AK1: =IF(HILOS!A4="","",HILOS!A4) -> Hilo 30/1 PC | AL1: =IFERROR(SUMIFS(COMPRAS_HILO!$D$4:$D$203,COMPRAS_HILO!$C$4:$C$203,AK1),0) -> 4000 | AM1: =IFERROR(SUMIFS(COMPRAS_HILO!$H$4:$H$203,COMPRAS_HILO!$C$4:$C$203,AK1),0) -> 41550 | AN1: =AM1-ROW()/1000000 -> 41550 | AO1: =IF(COLORES!A4="","",COLORES!A4) -> Negro | AP1: =IFERROR(SUMIFS(PROGRAMA_DETALLE!$S$4:$S$503,PROGRAMA_DETALLE!$B$4:$B$503,AO1),0) -> 380 | AQ1: =AP1-ROW()/1000000 -> 380
A2: Comisión José S/./kg final: | C2: 0.3 | D2: (editable — afecta comisión en PROGRAMAS!AB y por tanto la INVERSIÓN TOTAL) | AK2: =IF(HILOS!A5="","",HILOS!A5) -> Hilo 20/1 PC | AL2: =IFERROR(SUMIFS(COMPRAS_HILO!$D$4:$D$203,COMPRAS_HILO!$C$4:$C$203,AK2),0) -> 0 | AM2: =IFERROR(SUMIFS(COMPRAS_HILO!$H$4:$H$203,COMPRAS_HILO!$C$4:$C$203,AK2),0) -> 0 | AN2: =AM2-ROW()/1000000 -> -2e-06 | AO2: =IF(COLORES!A5="","",COLORES!A5) -> Perla | AP2: =IFERROR(SUMIFS(PROGRAMA_DETALLE!$S$4:$S$503,PROGRAMA_DETALLE!$B$4:$B$503,AO2),0) -> 170 | AQ2: =AP2-ROW()/1000000 -> 170
AK3: =IF(HILOS!A6="","",HILOS!A6) -> Hilo 30/1 ALGODON | AL3: =IFERROR(SUMIFS(COMPRAS_HILO!$D$4:$D$203,COMPRAS_HILO!$C$4:$C$203,AK3),0) -> 660 | AM3: =IFERROR(SUMIFS(COMPRAS_HILO!$H$4:$H$203,COMPRAS_HILO!$C$4:$C$203,AK3),0) -> 9108 | AN3: =AM3-ROW()/1000000 -> 9108 | AO3: =IF(COLORES!A6="","",COLORES!A6) -> Blanco | AP3: =IFERROR(SUMIFS(PROGRAMA_DETALLE!$S$4:$S$503,PROGRAMA_DETALLE!$B$4:$B$503,AO3),0) -> 0 | AQ3: =AP3-ROW()/1000000 -> -3e-06
A4: PROGRAMAS ACTIVOS | C4: ROLLOS PRODUCIDOS | E4: KG TELA PRODUCIDA | G4: INVERSIÓN TOTAL | AK4: =IF(HILOS!A7="","",HILOS!A7) -> Hilo 24/1 Algodón | AL4: =IFERROR(SUMIFS(COMPRAS_HILO!$D$4:$D$203,COMPRAS_HILO!$C$4:$C$203,AK4),0) -> 0 | AM4: =IFERROR(SUMIFS(COMPRAS_HILO!$H$4:$H$203,COMPRAS_HILO!$C$4:$C$203,AK4),0) -> 0 | AN4: =AM4-ROW()/1000000 -> -4e-06 | AO4: =IF(COLORES!A7="","",COLORES!A7) -> Beige | AP4: =IFERROR(SUMIFS(PROGRAMA_DETALLE!$S$4:$S$503,PROGRAMA_DETALLE!$B$4:$B$503,AO4),0) -> 170 | AQ4: =AP4-ROW()/1000000 -> 170
A5: =SUMPRODUCT((PROGRAMAS!$A$4:$A$103<>"")*(PROGRAMAS!$I$4:$I$103<>"CERRADO")) -> 4 | C5: =SUM(PROGRAMA_DETALLE!$T$4:$T$503) -> 50 | E5: =SUM(PROGRAMAS!$W$4:$W$103) -> 890 | G5: =SUM(PROGRAMAS!$AE$4:$AE$103) -> 68954.175 | AK5: =IF(HILOS!A8="","",HILOS!A8) -> Hilo 50/1 Pima | AL5: =IFERROR(SUMIFS(COMPRAS_HILO!$D$4:$D$203,COMPRAS_HILO!$C$4:$C$203,AK5),0) -> 0 | AM5: =IFERROR(SUMIFS(COMPRAS_HILO!$H$4:$H$203,COMPRAS_HILO!$C$4:$C$203,AK5),0) -> 0 | AN5: =AM5-ROW()/1000000 -> -5e-06 | AO5: =IF(COLORES!A8="","",COLORES!A8) -> Topo | AP5: =IFERROR(SUMIFS(PROGRAMA_DETALLE!$S$4:$S$503,PROGRAMA_DETALLE!$B$4:$B$503,AO5),0) -> 0 | AQ5: =AP5-ROW()/1000000 -> -5e-06
A6: COSTO/KG PROMEDIO | C6: COMISIÓN JOSÉ TOTAL | E6: CXP PENDIENTE | G6: TIEMPO PROM ENTREGA | AK6: =IF(HILOS!A9="","",HILOS!A9) -> Hilo 30/1 con Lycra | AL6: =IFERROR(SUMIFS(COMPRAS_HILO!$D$4:$D$203,COMPRAS_HILO!$C$4:$C$203,AK6),0) -> 0 | AM6: =IFERROR(SUMIFS(COMPRAS_HILO!$H$4:$H$203,COMPRAS_HILO!$C$4:$C$203,AK6),0) -> 0 | AN6: =AM6-ROW()/1000000 -> -6e-06 | AO6: =IF(COLORES!A9="","",COLORES!A9) -> Cemento | AP6: =IFERROR(SUMIFS(PROGRAMA_DETALLE!$S$4:$S$503,PROGRAMA_DETALLE!$B$4:$B$503,AO6),0) -> 0 | AQ6: =AP6-ROW()/1000000 -> -6e-06
A7: =IFERROR(SUM(PROGRAMAS!$AE$4:$AE$103)/SUM(PROGRAMAS!$W$4:$W$103),0) -> 77.476601 | C7: =SUM(PROGRAMAS!$AB$4:$AB$103) -> 267 | E7: =SUMIFS(CUENTAS_POR_PAGAR!H4:H1203,CUENTAS_POR_PAGAR!I4:I1203,"PENDIENTE")+SUMIFS(CUENTAS_POR_PAGAR!H4:H1203,CUENTAS_POR_PAGAR!I4:I1203,"PARCIAL") -> 0 | G7: =IFERROR(AVERAGEIF(PROGRAMAS!$AG$4:$AG$103,">0"),"") -> 29 | AK7: =IF(HILOS!A10="","",HILOS!A10) -> hilo 50/1 cottom | AL7: =IFERROR(SUMIFS(COMPRAS_HILO!$D$4:$D$203,COMPRAS_HILO!$C$4:$C$203,AK7),0) -> 0 | AM7: =IFERROR(SUMIFS(COMPRAS_HILO!$H$4:$H$203,COMPRAS_HILO!$C$4:$C$203,AK7),0) -> 0 | AN7: =AM7-ROW()/1000000 -> -7e-06 | AO7: =IF(COLORES!A10="","",COLORES!A10) -> Pacay | AP7: =IFERROR(SUMIFS(PROGRAMA_DETALLE!$S$4:$S$503,PROGRAMA_DETALLE!$B$4:$B$503,AO7),0) -> 0 | AQ7: =AP7-ROW()/1000000 -> -7e-06
AK8: =IF(HILOS!A11="","",HILOS!A11) -> hilo 50/1 cotton +lycra 4% | AL8: =IFERROR(SUMIFS(COMPRAS_HILO!$D$4:$D$203,COMPRAS_HILO!$C$4:$C$203,AK8),0) -> 500 | AM8: =IFERROR(SUMIFS(COMPRAS_HILO!$H$4:$H$203,COMPRAS_HILO!$C$4:$C$203,AK8),0) -> 9625 | AN8: =AM8-ROW()/1000000 -> 9625 | AO8: =IF(COLORES!A11="","",COLORES!A11) -> Denim | AP8: =IFERROR(SUMIFS(PROGRAMA_DETALLE!$S$4:$S$503,PROGRAMA_DETALLE!$B$4:$B$503,AO8),0) -> 0 | AQ8: =AP8-ROW()/1000000 -> -8e-06
A9: ESTADO DE PROGRAMAS | E9: TOP HILOS POR INVERSIÓN | AK9: =IF(HILOS!A12="","",HILOS!A12) | AL9: =IFERROR(SUMIFS(COMPRAS_HILO!$D$4:$D$203,COMPRAS_HILO!$C$4:$C$203,AK9),0) -> 0 | AM9: =IFERROR(SUMIFS(COMPRAS_HILO!$H$4:$H$203,COMPRAS_HILO!$C$4:$C$203,AK9),0) -> 0 | AN9: =AM9-ROW()/1000000 -> -9e-06 | AO9: =IF(COLORES!A12="","",COLORES!A12) -> Palo Rosa | AP9: =IFERROR(SUMIFS(PROGRAMA_DETALLE!$S$4:$S$503,PROGRAMA_DETALLE!$B$4:$B$503,AO9),0) -> 0 | AQ9: =AP9-ROW()/1000000 -> -9e-06
A10: ESTADO | B10: CANT. | C10: % TOTAL | E10: # | F10: TIPO HILO | G10: KG TOTAL | H10: INVERSIÓN | I10: % TOTAL | AK10: =IF(HILOS!A13="","",HILOS!A13) | AL10: =IFERROR(SUMIFS(COMPRAS_HILO!$D$4:$D$203,COMPRAS_HILO!$C$4:$C$203,AK10),0) -> 0 | AM10: =IFERROR(SUMIFS(COMPRAS_HILO!$H$4:$H$203,COMPRAS_HILO!$C$4:$C$203,AK10),0) -> 0 | AN10: =AM10-ROW()/1000000 -> -1e-05 | AO10: =IF(COLORES!A13="","",COLORES!A13) -> Camote | AP10: =IFERROR(SUMIFS(PROGRAMA_DETALLE!$S$4:$S$503,PROGRAMA_DETALLE!$B$4:$B$503,AO10),0) -> 0 | AQ10: =AP10-ROW()/1000000 -> -1e-05
A11: NUEVO | B11: =COUNTIF(PROGRAMAS!$I$4:$I$103,"NUEVO") -> 0 | C11: =IFERROR(B11/SUMPRODUCT((PROGRAMAS!$A$4:$A$103<>"")*1),0) -> 0 | E11: 1 | F11: {=IFERROR(IF(LARGE($AN$1:$AN$19,1)<=0,"",INDEX($AK$1:$AK$19,MATCH(LARGE($AN$1:$AN$19,1),$AN$1:$AN$19,0))),"")} -> Hilo 30/1 PC | G11: {=IFERROR(IF(LARGE($AN$1:$AN$19,1)<=0,"",INDEX($AL$1:$AL$19,MATCH(LARGE($AN$1:$AN$19,1),$AN$1:$AN$19,0))),"")} -> 4000 | H11: {=IFERROR(IF(LARGE($AN$1:$AN$19,1)<=0,"",INDEX($AM$1:$AM$19,MATCH(LARGE($AN$1:$AN$19,1),$AN$1:$AN$19,0))),"")} -> 41550 | I11: =IFERROR(H11/SUM($AM$1:$AM$19),0) -> 0.68924904 | AK11: =IF(HILOS!A14="","",HILOS!A14) | AL11: =IFERROR(SUMIFS(COMPRAS_HILO!$D$4:$D$203,COMPRAS_HILO!$C$4:$C$203,AK11),0) -> 0 | AM11: =IFERROR(SUMIFS(COMPRAS_HILO!$H$4:$H$203,COMPRAS_HILO!$C$4:$C$203,AK11),0) -> 0 | AN11: =AM11-ROW()/1000000 -> -1.1e-05 | AO11: =IF(COLORES!A14="","",COLORES!A14) -> Azul Marino | AP11: =IFERROR(SUMIFS(PROGRAMA_DETALLE!$S$4:$S$503,PROGRAMA_DETALLE!$B$4:$B$503,AO11),0) -> 0 | AQ11: =AP11-ROW()/1000000 -> -1.1e-05
A12: EN COMPRA | B12: =COUNTIF(PROGRAMAS!$I$4:$I$103,"EN COMPRA") -> 0 | C12: =IFERROR(B12/SUMPRODUCT((PROGRAMAS!$A$4:$A$103<>"")*1),0) -> 0 | E12: 2 | F12: {=IFERROR(IF(LARGE($AN$1:$AN$19,2)<=0,"",INDEX($AK$1:$AK$19,MATCH(LARGE($AN$1:$AN$19,2),$AN$1:$AN$19,0))),"")} -> hilo 50/1 cotton +lycra 4% | G12: {=IFERROR(IF(LARGE($AN$1:$AN$19,2)<=0,"",INDEX($AL$1:$AL$19,MATCH(LARGE($AN$1:$AN$19,2),$AN$1:$AN$19,0))),"")} -> 500 | H12: {=IFERROR(IF(LARGE($AN$1:$AN$19,2)<=0,"",INDEX($AM$1:$AM$19,MATCH(LARGE($AN$1:$AN$19,2),$AN$1:$AN$19,0))),"")} -> 9625 | I12: =IFERROR(H12/SUM($AM$1:$AM$19),0) -> 0.15966359 | AK12: =IF(HILOS!A15="","",HILOS!A15) | AL12: =IFERROR(SUMIFS(COMPRAS_HILO!$D$4:$D$203,COMPRAS_HILO!$C$4:$C$203,AK12),0) -> 0 | AM12: =IFERROR(SUMIFS(COMPRAS_HILO!$H$4:$H$203,COMPRAS_HILO!$C$4:$C$203,AK12),0) -> 0 | AN12: =AM12-ROW()/1000000 -> -1.2e-05 | AO12: =IF(COLORES!A15="","",COLORES!A15) -> Vino | AP12: =IFERROR(SUMIFS(PROGRAMA_DETALLE!$S$4:$S$503,PROGRAMA_DETALLE!$B$4:$B$503,AO12),0) -> 0 | AQ12: =AP12-ROW()/1000000 -> -1.2e-05
A13: EN TEJEDURÍA | B13: =COUNTIF(PROGRAMAS!$I$4:$I$103,"EN TEJEDURÍA") -> 2 | C13: =IFERROR(B13/SUMPRODUCT((PROGRAMAS!$A$4:$A$103<>"")*1),0) -> 0.4 | E13: 3 | F13: {=IFERROR(IF(LARGE($AN$1:$AN$19,3)<=0,"",INDEX($AK$1:$AK$19,MATCH(LARGE($AN$1:$AN$19,3),$AN$1:$AN$19,0))),"")} -> Hilo 30/1 ALGODON | G13: {=IFERROR(IF(LARGE($AN$1:$AN$19,3)<=0,"",INDEX($AL$1:$AL$19,MATCH(LARGE($AN$1:$AN$19,3),$AN$1:$AN$19,0))),"")} -> 660 | H13: {=IFERROR(IF(LARGE($AN$1:$AN$19,3)<=0,"",INDEX($AM$1:$AM$19,MATCH(LARGE($AN$1:$AN$19,3),$AN$1:$AN$19,0))),"")} -> 9108 | I13: =IFERROR(H13/SUM($AM$1:$AM$19),0) -> 0.15108737 | AK13: =IF(HILOS!A16="","",HILOS!A16) | AL13: =IFERROR(SUMIFS(COMPRAS_HILO!$D$4:$D$203,COMPRAS_HILO!$C$4:$C$203,AK13),0) -> 0 | AM13: =IFERROR(SUMIFS(COMPRAS_HILO!$H$4:$H$203,COMPRAS_HILO!$C$4:$C$203,AK13),0) -> 0 | AN13: =AM13-ROW()/1000000 -> -1.3e-05 | AO13: =IF(COLORES!A16="","",COLORES!A16) -> Botella | AP13: =IFERROR(SUMIFS(PROGRAMA_DETALLE!$S$4:$S$503,PROGRAMA_DETALLE!$B$4:$B$503,AO13),0) -> 0 | AQ13: =AP13-ROW()/1000000 -> -1.3e-05
A14: EN TINTORERÍA | B14: =COUNTIF(PROGRAMAS!$I$4:$I$103,"EN TINTORERÍA") -> 2 | C14: =IFERROR(B14/SUMPRODUCT((PROGRAMAS!$A$4:$A$103<>"")*1),0) -> 0.4 | E14: 4 | F14: {=IFERROR(IF(LARGE($AN$1:$AN$19,4)<=0,"",INDEX($AK$1:$AK$19,MATCH(LARGE($AN$1:$AN$19,4),$AN$1:$AN$19,0))),"")} | G14: {=IFERROR(IF(LARGE($AN$1:$AN$19,4)<=0,"",INDEX($AL$1:$AL$19,MATCH(LARGE($AN$1:$AN$19,4),$AN$1:$AN$19,0))),"")} | H14: {=IFERROR(IF(LARGE($AN$1:$AN$19,4)<=0,"",INDEX($AM$1:$AM$19,MATCH(LARGE($AN$1:$AN$19,4),$AN$1:$AN$19,0))),"")} | I14: =IFERROR(H14/SUM($AM$1:$AM$19),0) -> 0 | AK14: =IF(HILOS!A17="","",HILOS!A17) | AL14: =IFERROR(SUMIFS(COMPRAS_HILO!$D$4:$D$203,COMPRAS_HILO!$C$4:$C$203,AK14),0) -> 0 | AM14: =IFERROR(SUMIFS(COMPRAS_HILO!$H$4:$H$203,COMPRAS_HILO!$C$4:$C$203,AK14),0) -> 0 | AN14: =AM14-ROW()/1000000 -> -1.4e-05 | AO14: =IF(COLORES!A17="","",COLORES!A17) -> Colegial | AP14: =IFERROR(SUMIFS(PROGRAMA_DETALLE!$S$4:$S$503,PROGRAMA_DETALLE!$B$4:$B$503,AO14),0) -> 0 | AQ14: =AP14-ROW()/1000000 -> -1.4e-05
A15: EN PLANTA | B15: =COUNTIF(PROGRAMAS!$I$4:$I$103,"EN PLANTA") -> 0 | C15: =IFERROR(B15/SUMPRODUCT((PROGRAMAS!$A$4:$A$103<>"")*1),0) -> 0 | E15: 5 | F15: {=IFERROR(IF(LARGE($AN$1:$AN$19,5)<=0,"",INDEX($AK$1:$AK$19,MATCH(LARGE($AN$1:$AN$19,5),$AN$1:$AN$19,0))),"")} | G15: {=IFERROR(IF(LARGE($AN$1:$AN$19,5)<=0,"",INDEX($AL$1:$AL$19,MATCH(LARGE($AN$1:$AN$19,5),$AN$1:$AN$19,0))),"")} | H15: {=IFERROR(IF(LARGE($AN$1:$AN$19,5)<=0,"",INDEX($AM$1:$AM$19,MATCH(LARGE($AN$1:$AN$19,5),$AN$1:$AN$19,0))),"")} | I15: =IFERROR(H15/SUM($AM$1:$AM$19),0) -> 0 | AK15: =IF(HILOS!A18="","",HILOS!A18) | AL15: =IFERROR(SUMIFS(COMPRAS_HILO!$D$4:$D$203,COMPRAS_HILO!$C$4:$C$203,AK15),0) -> 0 | AM15: =IFERROR(SUMIFS(COMPRAS_HILO!$H$4:$H$203,COMPRAS_HILO!$C$4:$C$203,AK15),0) -> 0 | AN15: =AM15-ROW()/1000000 -> -1.5e-05 | AO15: =IF(COLORES!A18="","",COLORES!A18) -> Marrón | AP15: =IFERROR(SUMIFS(PROGRAMA_DETALLE!$S$4:$S$503,PROGRAMA_DETALLE!$B$4:$B$503,AO15),0) -> 0 | AQ15: =AP15-ROW()/1000000 -> -1.5e-05
A16: CERRADO | B16: =COUNTIF(PROGRAMAS!$I$4:$I$103,"CERRADO") -> 1 | C16: =IFERROR(B16/SUMPRODUCT((PROGRAMAS!$A$4:$A$103<>"")*1),0) -> 0.2 | E16: 6 | F16: {=IFERROR(IF(LARGE($AN$1:$AN$19,6)<=0,"",INDEX($AK$1:$AK$19,MATCH(LARGE($AN$1:$AN$19,6),$AN$1:$AN$19,0))),"")} | G16: {=IFERROR(IF(LARGE($AN$1:$AN$19,6)<=0,"",INDEX($AL$1:$AL$19,MATCH(LARGE($AN$1:$AN$19,6),$AN$1:$AN$19,0))),"")} | H16: {=IFERROR(IF(LARGE($AN$1:$AN$19,6)<=0,"",INDEX($AM$1:$AM$19,MATCH(LARGE($AN$1:$AN$19,6),$AN$1:$AN$19,0))),"")} | I16: =IFERROR(H16/SUM($AM$1:$AM$19),0) -> 0 | AK16: =IF(HILOS!A19="","",HILOS!A19) | AL16: =IFERROR(SUMIFS(COMPRAS_HILO!$D$4:$D$203,COMPRAS_HILO!$C$4:$C$203,AK16),0) -> 0 | AM16: =IFERROR(SUMIFS(COMPRAS_HILO!$H$4:$H$203,COMPRAS_HILO!$C$4:$C$203,AK16),0) -> 0 | AN16: =AM16-ROW()/1000000 -> -1.6e-05 | AO16: =IF(COLORES!A19="","",COLORES!A19) -> Acero | AP16: =IFERROR(SUMIFS(PROGRAMA_DETALLE!$S$4:$S$503,PROGRAMA_DETALLE!$B$4:$B$503,AO16),0) -> 0 | AQ16: =AP16-ROW()/1000000 -> -1.6e-05
A17: TOTAL | B17: =SUM(B11:B16) -> 5 | AK17: =IF(HILOS!A20="","",HILOS!A20) | AL17: =IFERROR(SUMIFS(COMPRAS_HILO!$D$4:$D$203,COMPRAS_HILO!$C$4:$C$203,AK17),0) -> 0 | AM17: =IFERROR(SUMIFS(COMPRAS_HILO!$H$4:$H$203,COMPRAS_HILO!$C$4:$C$203,AK17),0) -> 0 | AN17: =AM17-ROW()/1000000 -> -1.7e-05 | AO17: =IF(COLORES!A20="","",COLORES!A20) -> Azul | AP17: =IFERROR(SUMIFS(PROGRAMA_DETALLE!$S$4:$S$503,PROGRAMA_DETALLE!$B$4:$B$503,AO17),0) -> 0 | AQ17: =AP17-ROW()/1000000 -> -1.7e-05
AK18: =IF(HILOS!A21="","",HILOS!A21) | AL18: =IFERROR(SUMIFS(COMPRAS_HILO!$D$4:$D$203,COMPRAS_HILO!$C$4:$C$203,AK18),0) -> 0 | AM18: =IFERROR(SUMIFS(COMPRAS_HILO!$H$4:$H$203,COMPRAS_HILO!$C$4:$C$203,AK18),0) -> 0 | AN18: =AM18-ROW()/1000000 -> -1.8e-05 | AO18: =IF(COLORES!A21="","",COLORES!A21) -> Melange | AP18: =IFERROR(SUMIFS(PROGRAMA_DETALLE!$S$4:$S$503,PROGRAMA_DETALLE!$B$4:$B$503,AO18),0) -> 170 | AQ18: =AP18-ROW()/1000000 -> 169.99998
A19: TOP COLORES MÁS PRODUCIDOS (kg) | E19: CUENTAS POR PAGAR — RESUMEN | AK19: =IF(HILOS!A22="","",HILOS!A22) | AL19: =IFERROR(SUMIFS(COMPRAS_HILO!$D$4:$D$203,COMPRAS_HILO!$C$4:$C$203,AK19),0) -> 0 | AM19: =IFERROR(SUMIFS(COMPRAS_HILO!$H$4:$H$203,COMPRAS_HILO!$C$4:$C$203,AK19),0) -> 0 | AN19: =AM19-ROW()/1000000 -> -1.9e-05 | AO19: =IF(COLORES!A22="","",COLORES!A22) -> Hoja | AP19: =IFERROR(SUMIFS(PROGRAMA_DETALLE!$S$4:$S$503,PROGRAMA_DETALLE!$B$4:$B$503,AO19),0) -> 0 | AQ19: =AP19-ROW()/1000000 -> -1.9e-05
A20: # | B20: COLOR | C20: KG PRODUCIDOS | E20: CATEGORÍA | F20: TOTAL FACTURADO | G20: PAGADO | H20: SALDO PENDIENTE | I20: % PAGADO | AO20: =IF(COLORES!A23="","",COLORES!A23) -> Rosa | AP20: =IFERROR(SUMIFS(PROGRAMA_DETALLE!$S$4:$S$503,PROGRAMA_DETALLE!$B$4:$B$503,AO20),0) -> 0 | AQ20: =AP20-ROW()/1000000 -> -2e-05
A21: 1 | B21: {=IFERROR(IF(LARGE($AQ$1:$AQ$20,1)<=0,"",INDEX($AO$1:$AO$20,MATCH(LARGE($AQ$1:$AQ$20,1),$AQ$1:$AQ$20,0))),"")} -> Negro | C21: {=IFERROR(IF(LARGE($AQ$1:$AQ$20,1)<=0,"",INDEX($AP$1:$AP$20,MATCH(LARGE($AQ$1:$AQ$20,1),$AQ$1:$AQ$20,0))),"")} -> 380 | E21: HILO | F21: =SUM(CUENTAS_POR_PAGAR!F4:F203) -> 60283 | G21: =SUM(CUENTAS_POR_PAGAR!G4:G203) -> 20025 | H21: =SUMIF(CUENTAS_POR_PAGAR!I4:I203,"PENDIENTE",CUENTAS_POR_PAGAR!H4:H203)+SUMIF(CUENTAS_POR_PAGAR!I4:I203,"PARCIAL",CUENTAS_POR_PAGAR!H4:H203) -> 0 | I21: =IFERROR(G21/F21,0) -> 0.3321832
A22: 2 | B22: {=IFERROR(IF(LARGE($AQ$1:$AQ$20,2)<=0,"",INDEX($AO$1:$AO$20,MATCH(LARGE($AQ$1:$AQ$20,2),$AQ$1:$AQ$20,0))),"")} -> Perla | C22: {=IFERROR(IF(LARGE($AQ$1:$AQ$20,2)<=0,"",INDEX($AP$1:$AP$20,MATCH(LARGE($AQ$1:$AQ$20,2),$AQ$1:$AQ$20,0))),"")} -> 170 | E22: TEJEDURÍA | F22: =SUM(CUENTAS_POR_PAGAR!F204:F703) -> 1775 | G22: =SUM(CUENTAS_POR_PAGAR!G204:G703) -> 1775 | H22: =SUMIF(CUENTAS_POR_PAGAR!I204:I703,"PENDIENTE",CUENTAS_POR_PAGAR!H204:H703)+SUMIF(CUENTAS_POR_PAGAR!I204:I703,"PARCIAL",CUENTAS_POR_PAGAR!H204:H703) -> 0 | I22: =IFERROR(G22/F22,0) -> 1
A23: 3 | B23: {=IFERROR(IF(LARGE($AQ$1:$AQ$20,3)<=0,"",INDEX($AO$1:$AO$20,MATCH(LARGE($AQ$1:$AQ$20,3),$AQ$1:$AQ$20,0))),"")} -> Beige | C23: {=IFERROR(IF(LARGE($AQ$1:$AQ$20,3)<=0,"",INDEX($AP$1:$AP$20,MATCH(LARGE($AQ$1:$AQ$20,3),$AQ$1:$AQ$20,0))),"")} -> 170 | E23: TINTORERÍA | F23: =SUM(CUENTAS_POR_PAGAR!F704:F1203) -> 6629.175 | G23: =SUM(CUENTAS_POR_PAGAR!G704:G1203) -> 6629.175 | H23: =SUMIF(CUENTAS_POR_PAGAR!I704:I1203,"PENDIENTE",CUENTAS_POR_PAGAR!H704:H1203)+SUMIF(CUENTAS_POR_PAGAR!I704:I1203,"PARCIAL",CUENTAS_POR_PAGAR!H704:H1203) -> 0 | I23: =IFERROR(G23/F23,0) -> 1
A24: 4 | B24: {=IFERROR(IF(LARGE($AQ$1:$AQ$20,4)<=0,"",INDEX($AO$1:$AO$20,MATCH(LARGE($AQ$1:$AQ$20,4),$AQ$1:$AQ$20,0))),"")} -> Melange | C24: {=IFERROR(IF(LARGE($AQ$1:$AQ$20,4)<=0,"",INDEX($AP$1:$AP$20,MATCH(LARGE($AQ$1:$AQ$20,4),$AQ$1:$AQ$20,0))),"")} -> 170 | E24: COMISIÓN JOSÉ | F24: =SUM(PROGRAMAS!$AB$4:$AB$103) -> 267 | G24: =SUMIFS(PROGRAMAS!$AB$4:$AB$103,PROGRAMAS!$AC$4:$AC$103,"PAGADO") -> 0 | H24: =SUMIFS(PROGRAMAS!$AB$4:$AB$103,PROGRAMAS!$AC$4:$AC$103,"PENDIENTE")+SUMIFS(PROGRAMAS!$AB$4:$AB$103,PROGRAMAS!$AC$4:$AC$103,"PARCIAL") -> 267 | I24: =IFERROR(G24/F24,0) -> 0
A25: 5 | B25: {=IFERROR(IF(LARGE($AQ$1:$AQ$20,5)<=0,"",INDEX($AO$1:$AO$20,MATCH(LARGE($AQ$1:$AQ$20,5),$AQ$1:$AQ$20,0))),"")} | C25: {=IFERROR(IF(LARGE($AQ$1:$AQ$20,5)<=0,"",INDEX($AP$1:$AP$20,MATCH(LARGE($AQ$1:$AQ$20,5),$AQ$1:$AQ$20,0))),"")} | E25: TOTAL | F25: =SUM(F21:F24) -> 68954.175 | G25: =SUM(G21:G24) -> 28429.175 | H25: =SUM(H21:H24) -> 267 | I25: =IFERROR(G25/F25,0) -> 0.41229084
A26: 6 | B26: {=IFERROR(IF(LARGE($AQ$1:$AQ$20,6)<=0,"",INDEX($AO$1:$AO$20,MATCH(LARGE($AQ$1:$AQ$20,6),$AQ$1:$AQ$20,0))),"")} | C26: {=IFERROR(IF(LARGE($AQ$1:$AQ$20,6)<=0,"",INDEX($AP$1:$AP$20,MATCH(LARGE($AQ$1:$AQ$20,6),$AQ$1:$AQ$20,0))),"")}
A27: 7 | B27: {=IFERROR(IF(LARGE($AQ$1:$AQ$20,7)<=0,"",INDEX($AO$1:$AO$20,MATCH(LARGE($AQ$1:$AQ$20,7),$AQ$1:$AQ$20,0))),"")} | C27: {=IFERROR(IF(LARGE($AQ$1:$AQ$20,7)<=0,"",INDEX($AP$1:$AP$20,MATCH(LARGE($AQ$1:$AQ$20,7),$AQ$1:$AQ$20,0))),"")}
A28: 8 | B28: {=IFERROR(IF(LARGE($AQ$1:$AQ$20,8)<=0,"",INDEX($AO$1:$AO$20,MATCH(LARGE($AQ$1:$AQ$20,8),$AQ$1:$AQ$20,0))),"")} | C28: {=IFERROR(IF(LARGE($AQ$1:$AQ$20,8)<=0,"",INDEX($AP$1:$AP$20,MATCH(LARGE($AQ$1:$AQ$20,8),$AQ$1:$AQ$20,0))),"")}
A31: COMPARATIVO DE PROGRAMAS
A32: PROGRAMA | B32: FECHA INICIO | C32: FECHA ENTREGA | D32: DÍAS | E32: TIPO HILO | F32: KG HILO | G32: KG FINAL | H32: % MERMA | I32: COSTO TOTAL | J32: COSTO/KG | K32: ESTADO
A33: =IF(PROGRAMAS!A4="","",PROGRAMAS!A4) -> PIQUE-001 | B33: =IF(PROGRAMAS!A4="","",PROGRAMAS!B4) -> 46113 | C33: =IF(PROGRAMAS!A4="","",PROGRAMAS!AD4) -> 46142 | D33: =IF(PROGRAMAS!A4="","",PROGRAMAS!AG4) -> 29 | E33: =IF(PROGRAMAS!A4="","",PROGRAMAS!D4) -> Hilo 30/1 PC | F33: =IF(PROGRAMAS!A4="","",PROGRAMAS!M4) -> 1000 | G33: =IF(PROGRAMAS!A4="","",PROGRAMAS!W4) -> 890 | H33: =IF(PROGRAMAS!A4="","",PROGRAMAS!AA4) -> 0.105 | I33: =IF(PROGRAMAS!A4="","",PROGRAMAS!AE4) -> 19171.175 | J33: =IF(PROGRAMAS!A4="","",PROGRAMAS!AF4) -> 21.540646 | K33: =IF(PROGRAMAS!A4="","",PROGRAMAS!I4) -> CERRADO
A34: =IF(PROGRAMAS!A5="","",PROGRAMAS!A5) -> FULL LYCRA 50/1-001 | B34: =IF(PROGRAMAS!A5="","",PROGRAMAS!B5) -> 46152 | C34: =IF(PROGRAMAS!A5="","",PROGRAMAS!AD5) | D34: =IF(PROGRAMAS!A5="","",PROGRAMAS!AG5) -> -46152 | E34: =IF(PROGRAMAS!A5="","",PROGRAMAS!D5) -> hilo 50/1 cotton +lycra 4% | F34: =IF(PROGRAMAS!A5="","",PROGRAMAS!M5) -> 500 | G34: =IF(PROGRAMAS!A5="","",PROGRAMAS!W5) -> 0 | H34: =IF(PROGRAMAS!A5="","",PROGRAMAS!AA5) -> 1 | I34: =IF(PROGRAMAS!A5="","",PROGRAMAS!AE5) -> 9625 | J34: =IF(PROGRAMAS!A5="","",PROGRAMAS!AF5) -> 0 | K34: =IF(PROGRAMAS!A5="","",PROGRAMAS!I5) -> EN TEJEDURÍA
A35: =IF(PROGRAMAS!A6="","",PROGRAMAS!A6) -> frecnh terry - 001 | B35: =IF(PROGRAMAS!A6="","",PROGRAMAS!B6) -> 46152 | C35: =IF(PROGRAMAS!A6="","",PROGRAMAS!AD6) | D35: =IF(PROGRAMAS!A6="","",PROGRAMAS!AG6) -> -46152 | E35: =IF(PROGRAMAS!A6="","",PROGRAMAS!D6) -> Hilo 30/1 PC | F35: =IF(PROGRAMAS!A6="","",PROGRAMAS!M6) -> 3000 | G35: =IF(PROGRAMAS!A6="","",PROGRAMAS!W6) -> 0 | H35: =IF(PROGRAMAS!A6="","",PROGRAMAS!AA6) -> 0 | I35: =IF(PROGRAMAS!A6="","",PROGRAMAS!AE6) -> 31050 | J35: =IF(PROGRAMAS!A6="","",PROGRAMAS!AF6) -> 0 | K35: =IF(PROGRAMAS!A6="","",PROGRAMAS!I6) -> EN TEJEDURÍA
A36: =IF(PROGRAMAS!A7="","",PROGRAMAS!A7) -> jersey algodon - 001 | B36: =IF(PROGRAMAS!A7="","",PROGRAMAS!B7) -> 46313 | C36: =IF(PROGRAMAS!A7="","",PROGRAMAS!AD7) | D36: =IF(PROGRAMAS!A7="","",PROGRAMAS!AG7) -> -46313 | E36: =IF(PROGRAMAS!A7="","",PROGRAMAS!D7) -> Hilo 30/1 ALGODON | F36: =IF(PROGRAMAS!A7="","",PROGRAMAS!M7) -> 660 | G36: =IF(PROGRAMAS!A7="","",PROGRAMAS!W7) -> 0 | H36: =IF(PROGRAMAS!A7="","",PROGRAMAS!AA7) -> 0 | I36: =IF(PROGRAMAS!A7="","",PROGRAMAS!AE7) -> 9108 | J36: =IF(PROGRAMAS!A7="","",PROGRAMAS!AF7) -> 0 | K36: =IF(PROGRAMAS!A7="","",PROGRAMAS!I7) -> EN TINTORERÍA
A37: =IF(PROGRAMAS!A8="","",PROGRAMAS!A8) -> rib 1x1- jersey algodon -001 | B37: =IF(PROGRAMAS!A8="","",PROGRAMAS!B8) -> 46160 | C37: =IF(PROGRAMAS!A8="","",PROGRAMAS!AD8) | D37: =IF(PROGRAMAS!A8="","",PROGRAMAS!AG8) -> -46160 | E37: =IF(PROGRAMAS!A8="","",PROGRAMAS!D8) -> Hilo 30/1 ALGODON | F37: =IF(PROGRAMAS!A8="","",PROGRAMAS!M8) -> 0 | G37: =IF(PROGRAMAS!A8="","",PROGRAMAS!W8) -> 0 | H37: =IF(PROGRAMAS!A8="","",PROGRAMAS!AA8) -> 0 | I37: =IF(PROGRAMAS!A8="","",PROGRAMAS!AE8) -> 0 | J37: =IF(PROGRAMAS!A8="","",PROGRAMAS!AF8) -> 0 | K37: =IF(PROGRAMAS!A8="","",PROGRAMAS!I8) -> EN TINTORERÍA
A38: =IF(PROGRAMAS!A9="","",PROGRAMAS!A9) | B38: =IF(PROGRAMAS!A9="","",PROGRAMAS!B9) | C38: =IF(PROGRAMAS!A9="","",PROGRAMAS!AD9) | D38: =IF(PROGRAMAS!A9="","",PROGRAMAS!AG9) | E38: =IF(PROGRAMAS!A9="","",PROGRAMAS!D9) | F38: =IF(PROGRAMAS!A9="","",PROGRAMAS!M9) | G38: =IF(PROGRAMAS!A9="","",PROGRAMAS!W9) | H38: =IF(PROGRAMAS!A9="","",PROGRAMAS!AA9) | I38: =IF(PROGRAMAS!A9="","",PROGRAMAS!AE9) | J38: =IF(PROGRAMAS!A9="","",PROGRAMAS!AF9) | K38: =IF(PROGRAMAS!A9="","",PROGRAMAS!I9)
A39: =IF(PROGRAMAS!A10="","",PROGRAMAS!A10) | B39: =IF(PROGRAMAS!A10="","",PROGRAMAS!B10) | C39: =IF(PROGRAMAS!A10="","",PROGRAMAS!AD10) | D39: =IF(PROGRAMAS!A10="","",PROGRAMAS!AG10) | E39: =IF(PROGRAMAS!A10="","",PROGRAMAS!D10) | F39: =IF(PROGRAMAS!A10="","",PROGRAMAS!M10) | G39: =IF(PROGRAMAS!A10="","",PROGRAMAS!W10) | H39: =IF(PROGRAMAS!A10="","",PROGRAMAS!AA10) | I39: =IF(PROGRAMAS!A10="","",PROGRAMAS!AE10) | J39: =IF(PROGRAMAS!A10="","",PROGRAMAS!AF10) | K39: =IF(PROGRAMAS!A10="","",PROGRAMAS!I10)
A40: =IF(PROGRAMAS!A11="","",PROGRAMAS!A11) | B40: =IF(PROGRAMAS!A11="","",PROGRAMAS!B11) | C40: =IF(PROGRAMAS!A11="","",PROGRAMAS!AD11) | D40: =IF(PROGRAMAS!A11="","",PROGRAMAS!AG11) | E40: =IF(PROGRAMAS!A11="","",PROGRAMAS!D11) | F40: =IF(PROGRAMAS!A11="","",PROGRAMAS!M11) | G40: =IF(PROGRAMAS!A11="","",PROGRAMAS!W11) | H40: =IF(PROGRAMAS!A11="","",PROGRAMAS!AA11) | I40: =IF(PROGRAMAS!A11="","",PROGRAMAS!AE11) | J40: =IF(PROGRAMAS!A11="","",PROGRAMAS!AF11) | K40: =IF(PROGRAMAS!A11="","",PROGRAMAS!I11)
A41: =IF(PROGRAMAS!A12="","",PROGRAMAS!A12) | B41: =IF(PROGRAMAS!A12="","",PROGRAMAS!B12) | C41: =IF(PROGRAMAS!A12="","",PROGRAMAS!AD12) | D41: =IF(PROGRAMAS!A12="","",PROGRAMAS!AG12) | E41: =IF(PROGRAMAS!A12="","",PROGRAMAS!D12) | F41: =IF(PROGRAMAS!A12="","",PROGRAMAS!M12) | G41: =IF(PROGRAMAS!A12="","",PROGRAMAS!W12) | H41: =IF(PROGRAMAS!A12="","",PROGRAMAS!AA12) | I41: =IF(PROGRAMAS!A12="","",PROGRAMAS!AE12) | J41: =IF(PROGRAMAS!A12="","",PROGRAMAS!AF12) | K41: =IF(PROGRAMAS!A12="","",PROGRAMAS!I12)
A42: =IF(PROGRAMAS!A13="","",PROGRAMAS!A13) | B42: =IF(PROGRAMAS!A13="","",PROGRAMAS!B13) | C42: =IF(PROGRAMAS!A13="","",PROGRAMAS!AD13) | D42: =IF(PROGRAMAS!A13="","",PROGRAMAS!AG13) | E42: =IF(PROGRAMAS!A13="","",PROGRAMAS!D13) | F42: =IF(PROGRAMAS!A13="","",PROGRAMAS!M13) | G42: =IF(PROGRAMAS!A13="","",PROGRAMAS!W13) | H42: =IF(PROGRAMAS!A13="","",PROGRAMAS!AA13) | I42: =IF(PROGRAMAS!A13="","",PROGRAMAS!AE13) | J42: =IF(PROGRAMAS!A13="","",PROGRAMAS!AF13) | K42: =IF(PROGRAMAS!A13="","",PROGRAMAS!I13)
A43: =IF(PROGRAMAS!A14="","",PROGRAMAS!A14) | B43: =IF(PROGRAMAS!A14="","",PROGRAMAS!B14) | C43: =IF(PROGRAMAS!A14="","",PROGRAMAS!AD14) | D43: =IF(PROGRAMAS!A14="","",PROGRAMAS!AG14) | E43: =IF(PROGRAMAS!A14="","",PROGRAMAS!D14) | F43: =IF(PROGRAMAS!A14="","",PROGRAMAS!M14) | G43: =IF(PROGRAMAS!A14="","",PROGRAMAS!W14) | H43: =IF(PROGRAMAS!A14="","",PROGRAMAS!AA14) | I43: =IF(PROGRAMAS!A14="","",PROGRAMAS!AE14) | J43: =IF(PROGRAMAS!A14="","",PROGRAMAS!AF14) | K43: =IF(PROGRAMAS!A14="","",PROGRAMAS!I14)
A44: =IF(PROGRAMAS!A15="","",PROGRAMAS!A15) | B44: =IF(PROGRAMAS!A15="","",PROGRAMAS!B15) | C44: =IF(PROGRAMAS!A15="","",PROGRAMAS!AD15) | D44: =IF(PROGRAMAS!A15="","",PROGRAMAS!AG15) | E44: =IF(PROGRAMAS!A15="","",PROGRAMAS!D15) | F44: =IF(PROGRAMAS!A15="","",PROGRAMAS!M15) | G44: =IF(PROGRAMAS!A15="","",PROGRAMAS!W15) | H44: =IF(PROGRAMAS!A15="","",PROGRAMAS!AA15) | I44: =IF(PROGRAMAS!A15="","",PROGRAMAS!AE15) | J44: =IF(PROGRAMAS!A15="","",PROGRAMAS!AF15) | K44: =IF(PROGRAMAS!A15="","",PROGRAMAS!I15)
... A132: =IF(PROGRAMAS!A103="","",PROGRAMAS!A103) | B132: =IF(PROGRAMAS!A103="","",PROGRAMAS!B103) | C132: =IF(PROGRAMAS!A103="","",PROGRAMAS!AD103) | D132: =IF(PROGRAMAS!A103="","",PROGRAMAS!AG103) | E132: =IF(PROGRAMAS!A103="","",PROGRAMAS!D103) | F132: =IF(PROGRAMAS!A103="","",PROGRAMAS!M103) | G132: =IF(PROGRAMAS!A103="","",PROGRAMAS!W103) | H132: =IF(PROGRAMAS!A103="","",PROGRAMAS!AA103) | I132: =IF(PROGRAMAS!A103="","",PROGRAMAS!AE103) | J132: =IF(PROGRAMAS!A103="","",PROGRAMAS!AF103) | K132: =IF(PROGRAMAS!A103="","",PROGRAMAS!I103)
